Workbook

Sheet Resumen LTP
A2: Informe
A3: Resumen LTP 2015
A4: Al 31 de diciembre de 2015
A5: Unidad de Pesquería | B5: Zona | C5: Cuota LTP R.Ex Nº 3510 | D5: Arriendos u otro | E5: Cuota Final | F5: Desembarque total (t) | G5: Aguas internacionales | H5: Saldo total (t) | I5: % consumido 2015
A6: Anchoveta | B6: XV- I - II | C6: =SUM('Pelagicos LTP '!E6:E11) -> 521962 | D6: =SUM('Pelagicos LTP '!F6:F11) -> -31713.134 | E6: =C6+D6 -> 490248.87 | F6: =SUM('Pelagicos LTP '!H6:H11) -> 343447.74 | H6: =E6-F6 -> 146801.13 | I6: =F6/E6 -> 0.70055794
A7: Anchoveta | B7: III - IV | C7: =SUM('Pelagicos LTP '!E14:E31) -> 14664.999 | D7: =SUM('Pelagicos LTP '!F14:F31) -> -13322.349 | E7: =C7+D7 -> 1342.65 | F7: =SUM('Pelagicos LTP '!H14:H31) -> 0 | H7: =E7-F7 -> 1342.65 | I7: =F7/E7 -> 0
A8: Anchoveta | B8: V - X | C8: =SUM('Pelagicos LTP '!E34:E90) -> 7380 | D8: =SUM('Pelagicos LTP '!F34:F90) -> -2509.409 | E8: =C8+D8 -> 4870.591 | F8: =SUM('Pelagicos LTP '!H34:H90) -> 4082.495 | H8: =E8-F8 -> 788.096 | I8: =F8/E8 -> 0.83819294
A9: Camarón nailon | B9: II-VIII | C9: =SUM('Crustaceos LTP'!AU6:AU41) -> 4026.004 | D9: =SUM('Crustaceos LTP'!AV6:AV41) -> 95.489311 | E9: =C9+D9 -> 4121.4933 | F9: =SUM('Crustaceos LTP'!AX6:AX41) -> 3198.195 | H9: =E9-F9 -> 923.29831 | I9: =F9/E9 -> 0.77597967
A10: Congrio dorado | B10: NE F + H | C10: =SUM('Demersales LTP '!E7:E16) -> 416.499 | D10: =SUM('Demersales LTP '!F7:F16) -> 0 | E10: =C10+D10 -> 416.499 | F10: =SUM('Demersales LTP '!H7:H16) -> 326.756 | H10: =E10-F10 -> 89.743 | I10: =F10/E10 -> 0.78453009
A11: Congrio dorado | B11: SE | C11: =SUM('Demersales LTP '!E18:E27) -> 236 | D11: =SUM('Demersales LTP '!F18:F27) -> 0 | E11: =C11+D11 -> 236 | F11: =SUM('Demersales LTP '!H18:H27) -> 202.405 | H11: =E11-F11 -> 33.595 | I11: =F11/E11 -> 0.85764831
A12: Jurel | B12: XV - I - II | C12: =SUM('Pelagicos LTP '!E93:E98) -> 41448.004 | D12: =SUM('Pelagicos LTP '!F93:F98) -> -2000 | E12: =C12+D12 -> 39448.004 | F12: =SUM('Pelagicos LTP '!H93:H98) -> 34552.018 | H12: =E12-F12 -> 4895.986 | I12: =F12/E12 -> 0.87588761
A13: Jurel | B13: III - IV | C13: =SUM('Pelagicos LTP '!E101:E126) -> 8758.999 | D13: =SUM('Pelagicos LTP '!F101:F126) -> 10916.367 | E13: =C13+D13 -> 19675.366 | F13: =SUM('Pelagicos LTP '!H101:H126) -> 19246.318 | G13: 10817.393 | H13: =E13-F13 -> 429.048 | I13: =F13/E13 -> 0.97819365
A14: Jurel | B14: V - IX | C14: =SUM('Pelagicos LTP '!E129:E192) -> 187467 | D14: =SUM('Pelagicos LTP '!F129:F192) -> -18812.762 | E14: =C14+D14 -> 168654.23 | F14: =SUM('Pelagicos LTP '!H129:H192) -> 166902.08 | G14: 30546.078 | H14: =E14-F14 -> 1752.158 | I14: =F14/E14 -> 0.98961095
A15: Jurel | B15: XIV - X | C15: =SUM('Pelagicos LTP '!E195:E246) -> 26281.998 | D15: =SUM('Pelagicos LTP '!F195:F246) -> 1569.772 | E15: =C15+D15 -> 27851.77 | F15: =SUM('Pelagicos LTP '!H195:H246) -> 27333.01 | G15: 14939.449 | H15: =E15-F15 -> 518.76 | I15: =F15/E15 -> 0.98137425
A16: Langostino amarillo | B16: III-IV | C16: =SUM('Crustaceos LTP'!Q54:Q75) -> 1779.999 | D16: =SUM('Crustaceos LTP'!R54:R75) -> 136.4822 | E16: =C16+D16 -> 1916.4812 | F16: =SUM('Crustaceos LTP'!Z54:Z75) -> 1645.675 | H16: =E16-F16 -> 270.8062 | I16: =F16/E16 -> 0.85869614
A17: Langostino colorado | B17: I -IV | C17: =SUM('Crustaceos LTP'!W82:W95) -> 66.001 | D17: =SUM('Crustaceos LTP'!X82:X95) -> 91.64944 | E17: =C17+D17 -> 157.65044 | F17: =SUM('Crustaceos LTP'!AF82:AF95) -> 43.833 | H17: =E17-F17 -> 113.81744 | I17: =F17/E17 -> 0.27803919
A18: Merluza común | B18: IV- 41º 28, 6 | C18: =SUM('Demersales LTP '!E132:E203) -> 13542.001 | D18: =SUM('Demersales LTP '!F132:F203) -> 27.340383 | E18: =C18+D18 -> 13569.341 | F18: =SUM('Demersales LTP '!H132:H203) -> 11853.182 | H18: =E18-F18 -> 1716.1594 | I18: =F18/E18 -> 0.8735267
A19: Merluza de cola | B19: V -X | C19: =SUM('Demersales LTP '!E64:E111) -> 24102.999 | D19: =SUM('Demersales LTP '!F64:F111) -> -11045.804 | E19: =C19+D19 -> 13057.195 | F19: =SUM('Demersales LTP '!H64:H111) -> 12247.079 | H19: =E19-F19 -> 810.11583 | I19: =F19/E19 -> 0.93795637
A20: Merluza de cola | B20: XI -XII | C20: =SUM('Demersales LTP '!E115:E130) -> 16067.926 | D20: =SUM('Demersales LTP '!F115:F130) -> 11045.768 | E20: =C20+D20 -> 27113.694 | F20: =SUM('Demersales LTP '!H115:H130) -> 23899.017 | H20: =E20-F20 -> 3214.6773 | I20: =F20/E20 -> 0.88143713
A21: Merluza de tres aletas | B21: 41º28,6 - XII | C21: =SUM('Demersales LTP '!E53:E62) -> 13770 | D21: =SUM('Demersales LTP '!F53:F62) -> 0 | E21: =C21+D21 -> 13770 | F21: =SUM('Demersales LTP '!H53:H62) -> 7117.143 | H21: =E21-F21 -> 6652.857 | I21: =F21/E21 -> 0.51685861
A22: Merluza del sur | B22: NE F + H | C22: =SUM('Demersales LTP '!E29:E38) -> 3898.001 | D22: =SUM('Demersales LTP '!F29:F38) -> 2527.3077 | E22: =C22+D22 -> 6425.3087 | F22: =SUM('Demersales LTP '!H29:H38) -> 6326.556 | H22: =E22-F22 -> 98.752718 | I22: =F22/E22 -> 0.98463067
A23: Merluza del sur | B23: SE | C23: =SUM('Demersales LTP '!E42:E51) -> 2492.999 | D23: =SUM('Demersales LTP '!F42:F51) -> -382.92242 | E23: =C23+D23 -> 2110.0766 | F23: =SUM('Demersales LTP '!H42:H51) -> 1706.025 | H23: =E23-F23 -> 404.05158 | I23: =F23/E23 -> 0.80851331
A24: Sardina común | B24: V -X | C24: =SUM('Pelagicos LTP '!E249:E317) -> 103024 | D24: =SUM('Pelagicos LTP '!F249:F317) -> -21833.554 | E24: =C24+D24 -> 81190.444 | F24: =SUM('Pelagicos LTP '!H249:H317) -> 78031.757 | H24: =E24-F24 -> 3158.687 | I24: =F24/E24 -> 0.96109534
A25: Sardina española | B25: XV- I - II | C25: =SUM('Pelagicos LTP '!E320:E327) -> 735 | D25: =SUM('Pelagicos LTP '!F320:F327) -> 0 | E25: =C25+D25 -> 735 | F25: =SUM('Pelagicos LTP '!H320:H327) -> 2.236 | H25: =E25-F25 -> 732.764 | I25: =F25/E25 -> 0.0030421769
A26: Sardina española | B26: III - IV | C26: =SUM('Pelagicos LTP '!E330:E349) -> 875.002 | D26: =SUM('Pelagicos LTP '!F330:F349) -> -193.4 | E26: =C26+D26 -> 681.602 | F26: =SUM('Pelagicos LTP '!H330:H349) -> 0 | H26: =E26-F26 -> 681.602 | I26: =F26/E26 -> 0
A28: Nota: El desembarque de aguas internacionales (columna G) Jurel desde III a X regiones, esta incorporado en la columna de desembarque total. Solo se incorpora el dato en la columna G para tenerlo de referencia

Sheet Pelagicos LTP 
B1: 2015. CUOTAS LTP Y SU CONSUMO DE RECURSOS PELÁGICOS al 31 de diciembre de 2015
C4: Periodo | E4: CUOTA (TONELADAS) | H4: OPERACIÓN | K4: RESUMEN ANUAL
A5: Unidad de pesquería | B5: Titular de cuota LTP | C5: Inicial | D5: Final | E5: Cuota Asignada por Res N° 3510 mod por Res N° 908 | F5: Traspaso, Cesion, Arriendo, etc) | G5: Cuota Efectiva | H5: Desembarque (t) | I5: Saldo (t) | J5: % consumido | K5: Cuota asignada (t) | L5: Traspaso, Cesion, Arriendo, etc) | M5: Cuota Efectiva | N5: Desembarque (t) | O5: Saldo (t) | P5: % consumido
A6: Anchoveta XV - I - II | B6: Arica Seafood Producer S.A. | C6: 42005 | D6: 42185 | E6: 2784.854 | F6: =-2784.854 -> -2784.854 | G6: =E6+F6 -> 0 | I6: =G6-H6 -> 0 | J6: =H6/G6 -> #DIV/0! | K6: =E6+E7 -> 3713.134 | L6: =F6+F7 -> -3713.134 | M6: =K6+L6 -> 0 | N6: =H6+H7 -> 0 | O6: =M6-N6 -> 0 | P6: =N6/M6 -> #DIV/0!
C7: 42186 | D7: 42369 | E7: 928.28 | F7: =-928.28 -> -928.28 | G7: =E7+F7+I6 -> 0 | I7: =G7-H7 -> 0 | J7: =H7/G7 -> #DIV/0!
B8: Camanchaca S.A. Cia. Pesq. | C8: 42005 | D8: 42185 | E8: 77269.213 | G8: =+E8+F8 -> 77269.213 | H8: 28288.036 | I8: =G8-H8 -> 48981.177 | J8: =H8/G8 -> 0.36609712 | K8: =E8+E9 -> 103025.49 | L8: =F8+F9 -> 0 | M8: =K8+L8 -> 103025.49 | N8: =H8+H9 -> 66618.994 | O8: =M8-N8 -> 36406.492 | P8: =N8/M8 -> 0.64662635
C9: 42186 | D9: 42369 | E9: 25756.273 | G9: =E9+F9+I8 -> 74737.45 | H9: 38330.958 | I9: =G9-H9 -> 36406.492 | J9: =H9/G9 -> 0.51287484
B10: Corpesca S.A. | C10: 42005 | D10: 42185 | E10: 311417.93 | G10: =E10+F10 -> 311417.93 | H10: 108923.8 | I10: =G10-H10 -> 202494.13 | J10: =H10/G10 -> 0.34976729 | K10: =E10+E11 -> 415223.38 | L10: =F10+F11 -> -28000 | M10: =K10+L10 -> 387223.38 | N10: =H10+H11 -> 276828.74 | O10: =M10-N10 -> 110394.64 | P10: =N10/M10 -> 0.7149071
C11: 42186 | D11: 42369 | E11: 103805.45 | F11: =-10000-4000-10000-4000 -> -28000 | G11: =E11+F11+I10 -> 278299.58 | H11: 167904.94 | I11: =G11-H11 -> 110394.64 | J11: =H11/G11 -> 0.60332445
A14: Anchoveta III - IV | B14: Alimentos Marinos S.A., | C14: 42005 | D14: 42308 | E14: 917.826 | F14: =-2.05 -> -2.05 | G14: =E14+F14 -> 915.776 | I14: =G14-H14 -> 915.776 | J14: =H14/G14 -> 0 | K14: =E14+E15 -> 966.115 | L14: =F14+F15 -> -2.05 | M14: =K14+L14 -> 964.065 | N14: =H14+H15 -> 0 | O14: =M14-N14 -> 964.065 | P14: =N14/M14 -> 0
C15: 42309 | D15: 42369 | E15: 48.289 | G15: =E15+F15+I14 -> 964.065 | I15: =G15-H15 -> 964.065 | J15: =H15/G15 -> 0
B16: Bahia Caldera S.A. Pesq. | C16: 42005 | D16: 42308 | E16: 3871.888 | F16: =-3871.888 -> -3871.888 | G16: =E16+F16 -> 0 | I16: =G16-H16 -> 0 | J16: =H16/G16 -> #DIV/0! | K16: =E16+E17 -> 4075.598 | L16: =F16+F17 -> -4075.598 | M16: =K16+L16 -> 0 | N16: =H16+H17 -> 0 | O16: =M16-N16 -> 0 | P16: =N16/M16 -> #DIV/0!
C17: 42309 | D17: 42369 | E17: 203.71 | F17: =-203.71 -> -203.71 | G17: =E17+F17+I16 -> 0 | I17: =G17-H17 -> 0 | J17: =H17/G17 -> #DIV/0!
B18: Blumar S.A. | C18: 42005 | D18: 42308 | E18: 3025.302 | F18: =-3025.302 -> -3025.302 | G18: =E18+F18 -> 0 | I18: =G18-H18 -> 0 | J18: =H18/G18 -> #DIV/0! | K18: =E18+E19 -> 3184.471 | L18: =F18+F19 -> -3133.151 | M18: =K18+L18 -> 51.32 | N18: =H18+H19 -> 0 | O18: =M18-N18 -> 51.32 | P18: =N18/M18 -> 0
C19: 42309 | D19: 42369 | E19: 159.169 | F19: =-107.849 -> -107.849 | G19: =E19+F19+I18 -> 51.32 | I19: =G19-H19 -> 51.32 | J19: =H19/G19 -> 0
B20: Camanchaca S.A. Cia. Pesq. | C20: 42005 | D20: 42308 | E20: 12.678 | G20: =E20+F20 -> 12.678 | I20: =G20-H20 -> 12.678 | J20: =H20/G20 -> 0 | K20: =E20+E21 -> 13.345 | L20: =F20+F21 -> 0 | M20: =K20+L20 -> 13.345 | N20: =H20+H21 -> 0 | O20: =M20-N20 -> 13.345 | P20: =N20/M20 -> 0
C21: 42309 | D21: 42369 | E21: 0.667 | G21: =E21+F21+I20 -> 13.345 | I21: =G21-H21 -> 13.345 | J21: =H21/G21 -> 0
B22: Inversiones Pesqueras S.p.A | C22: 42005 | D22: 42308 | E22: 159.184 | F22: =-83.737 -> -83.737 | G22: =E22+F22 -> 75.447 | I22: =G22-H22 -> 75.447 | J22: =H22/G22 -> 0 | K22: =E22+E23 -> 167.559 | L22: =F22+F23 -> -83.737 | M22: =K22+L22 -> 83.822 | N22: =H22+H23 -> 0 | O22: =M22-N22 -> 83.822 | P22: =N22/M22 -> 0
C23: 42309 | D23: 42369 | E23: 8.375 | G23: =E23+F23+I22 -> 83.822 | I23: =G23-H23 -> 83.822 | J23: =H23/G23 -> 0
B24: Orizón S.A. | C24: 42005 | D24: 42308 | E24: 5903.054 | F24: =-5903.054 -> -5903.054 | G24: =E24+F24 -> 0 | I24: =G24-H24 -> 0 | J24: =H24/G24 -> #DIV/0! | K24: =E24+E25 -> 6213.63 | L24: =F24+F25 -> -6113.6 | M24: =K24+L24 -> 100.03 | N24: =H24+H25 -> 0 | O24: =M24-N24 -> 100.03 | P24: =N24/M24 -> 0
C25: 42309 | D25: 42369 | E25: 310.576 | F25: -210.546 | G25: =E25+F25+I24 -> 100.03 | I25: =G25-H25 -> 100.03 | J25: =H25/G25 -> 0
B26: Camanchaca Pesca Sur S.A. | C26: 42005 | D26: 42308 | E26: 42.068 | G26: =E26+F26 -> 42.068 | I26: =G26-H26 -> 42.068 | J26: =H26/G26 -> 0 | K26: =E26+E27 -> 44.281 | L26: =F26+F27 -> 0 | M26: =K26+L26 -> 44.281 | N26: =H26+H27 -> 0 | O26: =M26-N26 -> 44.281 | P26: =N26/M26 -> 0
C27: 42309 | D27: 42369 | E27: 2.213 | G27: =E27+F27+I26 -> 44.281 | I27: =G27-H27 -> 44.281 | J27: =H27/G27 -> 0
B28: Centro Sur SpA. Pesq. | C28: 42005 | D28: 42308 | E28: 0 | F28: =83.737 -> 83.737 | G28: =E28+F28 -> 83.737 | I28: =G28-H28 -> 83.737 | J28: =H28/G28 -> 0 | K28: =E28+E29 -> 0 | L28: =F28+F29 -> 83.737 | M28: =K28+L28 -> 83.737 | N28: =H28+H29 -> 0 | O28: =M28-N28 -> 83.737 | P28: =N28/M28 -> 0
C29: 42309 | D29: 42369 | E29: 0 | G29: =E29+F29+I28 -> 83.737 | I29: =G29-H29 -> 83.737 | J29: =H29/G29 -> 0
B30: Foodcorp S.A. | C30: 42005 | D30: 42308 | E30: 0 | F30: =2.05 -> 2.05 | G30: =E30+F30 -> 2.05 | I30: =G30-H30 -> 2.05 | J30: =H30/G30 -> 0 | K30: =E30+E31 -> 0 | L30: =F30+F31 -> 2.05 | M30: =K30+L30 -> 2.05 | N30: =H30+H31 -> 0 | O30: =M30-N30 -> 2.05 | P30: =N30/M30 -> 0
C31: 42309 | D31: 42369 | E31: 0 | G31: =E31+F31+I30 -> 2.05 | I31: =G31-H31 -> 2.05 | J31: =H31/G31 -> 0
A34: Anchoveta V-X | B34: Alimentos Marinos S.A. | C34: 42005 | D34: 42124 | E34: 1173.088 | F34: =-209.025-111.48-350-350 -> -1020.505 | G34: =E34+F34 -> 152.583 | H34: 24.487 | I34: =G34-H34 -> 128.096 | J34: =H34/G34 -> 0.16048315 | K34: =E34+E35+E36 -> 1380.103 | L34: =F34+F35+F36 -> -1353.405 | M34: =K34+L34 -> 26.698 | N34: =H34+H35+H36 -> 24.487 | O34: =M34-N34 -> 2.211 | P34: =N34/M34 -> 0.91718481
C35: 42125 | D35: 42247 | E35: 138.01 | F35: =-332.9 -> -332.9 | G35: =E35+F35+I34 -> -66.794 | I35: =G35-H35 -> -66.794 | J35: =H35/G35 -> 0
C36: 42248 | D36: 42369 | E36: 69.005 | G36: =E36+F36+I35 -> 2.211 | I36: =G36-H36 -> 2.211 | J36: =H36/G36 -> 0
B37: Berta Elena Ltda. Soc. Pesq. | C37: 42005 | D37: 42124 | E37: 21.98 | F37: =-21.98 -> -21.98 | G37: =E37+F37 -> 0 | I37: =G37-H37 -> 0 | J37: =H37/G37 -> #DIV/0! | K37: =E37+E38+E39 -> 25.859 | L37: =F37+F38+F39 -> -25.859 | M37: =K37+L37 -> 0 | N37: =H37+H38+H39 -> 0 | O37: =M37-N37 -> 0 | P37: =N37/M37 -> #DIV/0!
C38: 42125 | D38: 42247 | E38: 2.586 | F38: =-2.586 -> -2.586 | G38: =E38+F38+I37 -> 0 | I38: =G38-H38 -> 0 | J38: =H38/G38 -> #DIV/0!
C39: 42248 | D39: 42369 | E39: 1.293 | F39: =-1.293 -> -1.293 | G39: =E39+F39+I38 -> 0 | I39: =G39-H39 -> 0 | J39: =H39/G39 -> #DIV/0!
B40: Blumar S.A. | C40: 42005 | D40: 42124 | E40: 1474.91 | F40: =-660 -> -660 | G40: =E40+F40 -> 814.91 | H40: 183.551 | I40: =G40-H40 -> 631.359 | J40: =H40/G40 -> 0.22524082 | K40: =E40+E41+E42 -> 1735.188 | L40: =F40+F41+F42 -> -680 | M40: =K40+L40 -> 1055.188 | N40: =H40+H41+H42 -> 832.744 | O40: =M40-N40 -> 222.444 | P40: =N40/M40 -> 0.78919017
C41: 42125 | D41: 42247 | E41: 173.519 | F41: =-20 -> -20 | G41: =E41+F41+I40 -> 784.878 | I41: =G41-H41 -> 784.878 | J41: =H41/G41 -> 0
C42: 42248 | D42: 42369 | E42: 86.759 | G42: =E42+F42+I41 -> 871.637 | H42: 649.193 | I42: =G42-H42 -> 222.444 | J42: =H42/G42 -> 0.74479743
B43: Camanchaca Pesca Sur S.A. | C43: 42005 | D43: 42124 | E43: 971.124 | F43: =-21 -> -21 | G43: =E43+F43 -> 950.124 | H43: 437.43 | I43: =G43-H43 -> 512.694 | J43: =H43/G43 -> 0.46039254 | K43: =E43+E44+E45 -> 1142.499 | L43: =F43+F44+F45 -> -230 | M43: =K43+L43 -> 912.499 | N43: =H43+H44+H45 -> 878.06 | O43: =M43-N43 -> 34.439 | P43: =N43/M43 -> 0.96225859
C44: 42125 | D44: 42247 | E44: 114.25 | G44: =E44+F44+I43 -> 626.944 | H44: 7.4 | I44: =G44-H44 -> 619.544 | J44: =H44/G44 -> 0.011803287
C45: 42248 | D45: 42369 | E45: 57.125 | F45: =-9-200 -> -209 | G45: =E45+F45+I44 -> 467.669 | H45: 433.23 | I45: =G45-H45 -> 34.439 | J45: =H45/G45 -> 0.92636031
B46: Camanchaca S.A. Cia. Pesq. | C46: 42005 | D46: 42124 | E46: 48.678 | G46: =E46+F46 -> 48.678 | I46: =G46-H46 -> 48.678 | J46: =H46/G46 -> 0 | K46: =E46+E47+E48 -> 57.268 | L46: =F46+F47+F48 -> 0 | M46: =K46+L46 -> 57.268 | N46: =H46+H47+H48 -> 0 | O46: =M46-N46 -> 57.268 | P46: =N46/M46 -> 0
C47: 42125 | D47: 42247 | E47: 5.727 | G47: =E47+F47+I46 -> 54.405 | I47: =G47-H47 -> 54.405 | J47: =H47/G47 -> 0
C48: 42248 | D48: 42369 | E48: 2.863 | G48: =E48+F48+I47 -> 57.268 | I48: =G48-H48 -> 57.268 | J48: =H48/G48 -> 0
B49: Operaciones Arandu SpA. | C49: 42005 | D49: 42124 | E49: 66.623 | F49: =-66.623 -> -66.623 | G49: =E49+F49 -> 0 | I49: =G49-H49 -> 0 | J49: =H49/G49 -> #DIV/0! | K49: =E49+E50+E51 -> 78.38 | L49: =F49+F50+F51 -> -78.38 | M49: =K49+L49 -> 0 | N49: =H49+H50+H51 -> 0 | O49: =M49-N49 -> 0 | P49: =N49/M49 -> #DIV/0!
C50: 42125 | D50: 42247 | E50: 7.838 | F50: =-7.838 -> -7.838 | G50: =E50+F50+I49 -> 0 | I50: =G50-H50 -> 0 | J50: =H50/G50 -> #DIV/0!
C51: 42248 | D51: 42369 | E51: 3.919 | F51: =-3.919 -> -3.919 | G51: =E51+F51+I50 -> 0 | I51: =G51-H51 -> 0 | J51: =H51/G51 -> #DIV/0!
B52: Centro Sur SpA. Pesq. | C52: 42005 | D52: 42124 | E52: 66.56 | G52: =E52+F52 -> 66.56 | H52: 11.201 | I52: =G52-H52 -> 55.359 | J52: =H52/G52 -> 0.16828425 | K52: =E52+E53+E54 -> 78.306 | L52: =F52+F53+F54 -> 0 | M52: =K52+L52 -> 78.306 | N52: =H52+H53+H54 -> 47.77 | O52: =M52-N52 -> 30.536 | P52: =N52/M52 -> 0.61004265
C53: 42125 | D53: 42247 | E53: 7.831 | G53: =E53+F53+I52 -> 63.19 | I53: =G53-H53 -> 63.19 | J53: =H53/G53 -> 0
C54: 42248 | D54: 42369 | E54: 3.915 | G54: =E54+F54+I53 -> 67.105 | H54: =36.569 -> 36.569 | I54: =G54-H54 -> 30.536 | J54: =H54/G54 -> 0.54495194
B55: Foodcorp S.A. | C55: 42005 | D55: 42124 | E55: 249.422 | F55: =-249.422 -> -249.422 | G55: =E55+F55 -> 0 | H55: 15.91 | I55: =G55-H55 -> -15.91 | J55: =H55/G55 -> #DIV/0! | K55: =E55+E56+E57 -> 293.438 | L55: =F55+F56+F57 -> -276 | M55: =K55+L55 -> 17.438 | N55: =H55+H56+H57 -> 15.91 | O55: =M55-N55 -> 1.528 | P55: =N55/M55 -> 0.91237527
C56: 42125 | D56: 42247 | E56: 29.344 | F56: =-5.578-21 -> -26.578 | G56: =E56+F56+I55 -> -13.144 | I56: =G56-H56 -> -13.144 | J56: =H56/G56 -> 0
C57: 42248 | D57: 42369 | E57: 14.672 | G57: =E57+F57+I56 -> 1.528 | I57: =G57-H57 -> 1.528 | J57: =H57/G57 -> 0
B58: Genmar Ltda. Soc. Pesq. | C58: 42005 | D58: 42124 | E58: 1.901 | F58: =-1.901 -> -1.901 | G58: =E58+F58 -> 0 | I58: =G58-H58 -> 0 | J58: =H58/G58 -> #DIV/0! | K58: =E58+E59+E60 -> 2.237 | L58: =F58+F59+F60 -> -2.237 | M58: =K58+L58 -> 0 | N58: =H58+H59+H60 -> 0 | O58: =M58-N58 -> 0 | P58: =N58/M58 -> #DIV/0!
C59: 42125 | D59: 42247 | E59: 0.224 | F59: =-0.224 -> -0.224 | G59: =E59+F59+I58 -> 0 | I59: =G59-H59 -> 0 | J59: =H59/G59 -> #DIV/0!
C60: 42248 | D60: 42369 | E60: 0.112 | F60: =-0.112 -> -0.112 | G60: =E60+F60+I59 -> 0 | I60: =G60-H60 -> 0 | J60: =H60/G60 -> #DIV/0!
B61: Inostroza Concha Pelantaro | C61: 42005 | D61: 42124 | E61: 5.887 | F61: -5.887 | G61: =E61+F61 -> 0 | I61: =G61-H61 -> 0 | J61: =H61/G61 -> #DIV/0! | K61: =E61+E62+E63 -> 6.926 | L61: =F61+F62+F63 -> -6.926 | M61: =K61+L61 -> 0 | N61: =H61+H62+H63 -> 0 | O61: =M61-N61 -> 0 | P61: =N61/M61 -> #DIV/0!
C62: 42125 | D62: 42247 | E62: 0.693 | F62: -0.693 | G62: =E62+F62+I61 -> 0 | I62: =G62-H62 -> 0 | J62: =H62/G62 -> #DIV/0!
C63: 42248 | D63: 42369 | E63: 0.346 | F63: -0.346 | G63: =E63+F63+I62 -> 0 | I63: =G63-H63 -> 0 | J63: =H63/G63 -> #DIV/0!
B64: Inversiones Pesqueras SpA. | C64: 42005 | D64: 42124 | E64: 60.223 | F64: =43.98+78.38 -> 122.36 | G64: =E64+F64 -> 182.583 | H64: 43.569 | I64: =G64-H64 -> 139.014 | J64: =H64/G64 -> 0.23862572 | K64: =E64+E65+E66 -> 70.851 | L64: =F64+F65+F66 -> 122.36 | M64: =K64+L64 -> 193.211 | N64: =H64+H65+H66 -> 43.569 | O64: =M64-N64 -> 149.642 | P64: =N64/M64 -> 0.22549958
C65: 42125 | D65: 42247 | E65: 7.085 | G65: =E65+F65+I64 -> 146.099 | I65: =G65-H65 -> 146.099 | J65: =H65/G65 -> 0
C66: 42248 | D66: 42369 | E66: 3.543 | G66: =E66+F66+I65 -> 149.642 | I66: =G66-H66 -> 149.642 | J66: =H66/G66 -> 0
B67: Burita Inversiones SpA. | C67: 42005 | D67: 42124 | E67: 37.387 | F67: =-37.387 -> -37.387 | G67: =E67+F67 -> 0 | I67: =G67-H67 -> 0 | J67: =H67/G67 -> #DIV/0! | K67: =E67+E68+E69 -> 43.984 | L67: =F67+F68+F69 -> -43.984 | M67: =K67+L67 -> 0 | N67: =H67+H68+H69 -> 0 | O67: =M67-N67 -> 0 | P67: =N67/M67 -> #DIV/0!
C68: 42125 | D68: 42247 | E68: 4.398 | F68: =-4.398 -> -4.398 | G68: =E68+F68+I67 -> 0 | I68: =G68-H68 -> 0 | J68: =H68/G68 -> #DIV/0!
C69: 42248 | D69: 42369 | E69: 2.199 | F69: =-2.199 -> -2.199 | G69: =E69+F69+I68 -> 0 | I69: =G69-H69 -> 0 | J69: =H69/G69 -> #DIV/0!
B70: Isla Quhua S.A. Pesq. | C70: 42005 | D70: 42124 | E70: 51.979 | F70: =-20 -> -20 | G70: =E70+F70 -> 31.979 | I70: =G70-H70 -> 31.979 | J70: =H70/G70 -> 0 | K70: =E70+E71+E72 -> 61.152 | L70: =F70+F71+F72 -> -20 | M70: =K70+L70 -> 41.152 | N70: =H70+H71+H72 -> 0 | O70: =M70-N70 -> 41.152 | P70: =N70/M70 -> 0
C71: 42125 | D71: 42247 | E71: 6.115 | G71: =E71+F71+I70 -> 38.094 | I71: =G71-H71 -> 38.094 | J71: =H71/G71 -> 0
C72: 42248 | D72: 42369 | E72: 3.058 | G72: =E72+F72+I71 -> 41.152 | I72: =G72-H72 -> 41.152 | J72: =H72/G72 -> 0
B73: Landes S.A. Soc Pesq. | C73: 42005 | D73: 42124 | E73: 439.245 | F73: =183 -> 183 | G73: =E73+F73 -> 622.245 | H73: 142.389 | I73: =G73-H73 -> 479.856 | J73: =H73/G73 -> 0.22883109 | K73: =E73+E74+E75 -> 516.759 | L73: =F73+F74+F75 -> 183 | M73: =K73+L73 -> 699.759 | N73: =H73+H74+H75 -> 639.607 | O73: =M73-N73 -> 60.152 | P73: =N73/M73 -> 0.91403898
C74: 42125 | D74: 42247 | E74: 51.676 | G74: =E74+F74+I73 -> 531.532 | H74: 201.245 | I74: =G74-H74 -> 330.287 | J74: =H74/G74 -> 0.37861314
C75: 42248 | D75: 42369 | E75: 25.838 | G75: =E75+F75+I74 -> 356.125 | H75: 295.973 | I75: =G75-H75 -> 60.152 | J75: =H75/G75 -> 0.83109302
B76: Lota Protein S.A. | C76: 42005 | D76: 42124 | E76: 72.531 | F76: =1.901+21.98+5.887 -> 29.768 | G76: =E76+F76 -> 102.299 | H76: 26.565 | I76: =G76-H76 -> 75.734 | J76: =H76/G76 -> 0.25967996 | K76: =E76+E77+E78 -> 85.331 | L76: =F76+F77+F78 -> 35.022 | M76: =K76+L76 -> 120.353 | N76: =H76+H77+H78 -> 39.519 | O76: =M76-N76 -> 80.834 | P76: =N76/M76 -> 0.32835908
C77: 42125 | D77: 42247 | E77: 8.533 | F77: =0.224+2.586+0.693 -> 3.503 | G77: =E77+F77+I76 -> 87.77 | I77: =G77-H77 -> 87.77 | J77: =H77/G77 -> 0
C78: 42248 | D78: 42369 | E78: 4.267 | F78: =0.112+1.293+0.346 -> 1.751 | G78: =E78+F78+I77 -> 93.788 | H78: 12.954 | I78: =G78-H78 -> 80.834 | J78: =H78/G78 -> 0.13812002
B79: Mar profundo S.A. Soc Pesq. | C79: 42005 | D79: 42124 | E79: 25.87 | G79: =E79+F79 -> 25.87 | I79: =G79-H79 -> 25.87 | J79: =H79/G79 -> 0 | K79: =E79+E80+E81 -> 30.436 | L79: =F79+F80+F81 -> 0 | M79: =K79+L79 -> 30.436 | N79: =H79+H80+H81 -> 0 | O79: =M79-N79 -> 30.436 | P79: =N79/M79 -> 0
C80: 42125 | D80: 42247 | E80: 3.044 | G80: =E80+F80+I79 -> 28.914 | I80: =G80-H80 -> 28.914 | J80: =H80/G80 -> 0
C81: 42248 | D81: 42369 | E81: 1.522 | G81: =E81+F81+I80 -> 30.436 | I81: =G81-H81 -> 30.436 | J81: =H81/G81 -> 0
B82: Orizon S.A. | C82: 42005 | D82: 42124 | E82: 1336.754 | G82: =E82+F82 -> 1336.754 | H82: 1134.432 | I82: =G82-H82 -> 202.322 | J82: =H82/G82 -> 0.8486468 | K82: =E82+E83+E84 -> 1572.652 | L82: =F82+F83+F84 -> 0 | M82: =K82+L82 -> 1572.652 | N82: =H82+H83+H84 -> 1560.829 | O82: =M82-N82 -> 11.823 | P82: =N82/M82 -> 0.99248213
C83: 42125 | D83: 42247 | E83: 157.265 | G83: =E83+F83+I82 -> 359.587 | I83: =G83-H83 -> 359.587 | J83: =H83/G83 -> 0
C84: 42248 | D84: 42369 | E84: 78.633 | G84: =E84+F84+I83 -> 438.22 | H84: 426.397 | I84: =G84-H84 -> 11.823 | J84: =H84/G84 -> 0.9730204
B85: Santana SpA. Inv. | C85: 42005 | D85: 42124 | E85: 25.338 | G85: =E85+F85 -> 25.338 | I85: =G85-H85 -> 25.338 | J85: =H85/G85 -> 0 | K85: =E85+E86+E87 -> 29.809 | L85: =F85+F86+F87 -> 0 | M85: =K85+L85 -> 29.809 | N85: =H85+H86+H87 -> 0 | O85: =M85-N85 -> 29.809 | P85: =N85/M85 -> 0
C86: 42125 | D86: 42247 | E86: 2.981 | G86: =E86+F86+I85 -> 28.319 | I86: =G86-H86 -> 28.319 | J86: =H86/G86 -> 0
C87: 42248 | D87: 42369 | E87: 1.49 | G87: =E87+F87+I86 -> 29.809 | I87: =G87-H87 -> 29.809 | J87: =H87/G87 -> 0
B88: San Antonio S.A. Pesq. | C88: 42005 | D88: 42124 | E88: 143.499 | F88: =-133 -> -133 | G88: =E88+F88 -> 10.499 | I88: =G88-H88 -> 10.499 | J88: =H88/G88 -> 0 | K88: =E88+E89+E90 -> 168.822 | L88: =F88+F89+F90 -> -133 | M88: =K88+L88 -> 35.822 | N88: =H88+H89+H90 -> 0 | O88: =M88-N88 -> 35.822 | P88: =N88/M88 -> 0
C89: 42125 | D89: 42247 | E89: 16.882 | G89: =E89+F89+I88 -> 27.381 | I89: =G89-H89 -> 27.381 | J89: =H89/G89 -> 0
C90: 42248 | D90: 42369 | E90: 8.441 | G90: =E90+F90+I89 -> 35.822 | I90: =G90-H90 -> 35.822 | J90: =H90/G90 -> 0
A93: Jurel XV-I-II (Res N° 3510 modificada por Res N° 908) | B93: Arica Seafood Producer S.A. | C93: 42005 | D93: 42277 | E93: 162.434 | G93: =E93+F93 -> 162.434 | I93: =G93-H93 -> 162.434 | J93: =H93/G93 -> 0 | K93: =E93+E94 -> 170.981 | L93: =F93+F94 -> 0 | M93: =K93+L93 -> 170.981 | N93: =H93+H94 -> 0 | O93: =M93-N93 -> 170.981 | P93: =N93/M93 -> 0
C94: 42278 | D94: 42369 | E94: 8.547 | G94: =E94+F94+I93 -> 170.981 | I94: =G94-H94 -> 170.981 | J94: =H94/G94 -> 0
B95: Camanchaca S.A. Cia. Pesq. | C95: 42005 | D95: 42277 | E95: 6881.771 | G95: =E95+F95 -> 6881.771 | H95: 5867.633 | I95: =G95-H95 -> 1014.138 | J95: =H95/G95 -> 0.85263415 | K95: =E95+E96 -> 7243.896 | L95: =F95+F96 -> 0 | M95: =K95+L95 -> 7243.896 | N95: =H95+H96 -> 5867.633 | O95: =M95-N95 -> 1376.263 | P95: =N95/M95 -> 0.81001066
C96: 42278 | D96: 42369 | E96: 362.125 | G96: =E96+F96+I95 -> 1376.263 | I96: =G96-H96 -> 1376.263 | J96: =H96/G96 -> 0
B97: Corpesca S.A. | C97: 42005 | D97: 42277 | E97: 32331.799 | G97: =E97+F97 -> 32331.799 | H97: 28660.071 | I97: =G97-H97 -> 3671.728 | J97: =H97/G97 -> 0.88643601 | K97: =E97+E98 -> 34033.127 | L97: =F97+F98 -> -2000 | M97: =K97+L97 -> 32033.127 | N97: =H97+H98 -> 28684.385 | O97: =M97-N97 -> 3348.742 | P97: =N97/M97 -> 0.89546003
C98: 42278 | D98: 42369 | E98: 1701.328 | F98: =-2000 -> -2000 | G98: =E98+F98+I97 -> 3373.056 | H98: 24.314 | I98: =G98-H98 -> 3348.742 | J98: =H98/G98 -> 0.0072083001
A101: Jurel III - IV (Res N° 3510 modificada por Res N° 908) | B101: Alimentos Marinos S.A. | C101: 42005 | D101: 42277 | E101: 820.825 | G101: =E101+F101 -> 820.825 | H101: 863.516 | I101: =G101-H101 -> -42.691 | J101: =H101/G101 -> 1.0520099 | K101: =E101+E102 -> 864.032 | L101: =F101+F102 -> 0 | M101: =K101+L101 -> 864.032 | N101: =H101+H102 -> 863.516 | O101: =M101-N101 -> 0.516 | P101: =N101/M101 -> 0.9994028
C102: 42278 | D102: 42369 | E102: 43.207 | G102: =E102+F102+I101 -> 0.516 | I102: =G102-H102 -> 0.516 | J102: =H102/G102 -> 0
B103: Arica Seafood Producer S.A | C103: 42005 | D103: 42277 | E103: 2.531 | G103: =E103+F103 -> 2.531 | I103: =G103-H103 -> 2.531 | J103: =H103/G103 -> 0 | K103: =E103+E104 -> 2.664 | L103: =F103+F104 -> 0 | M103: =K103+L103 -> 2.664 | N103: =H103+H104 -> 0 | O103: =M103-N103 -> 2.664 | P103: =N103/M103 -> 0
C104: 42278 | D104: 42369 | E104: 0.133 | G104: =E104+F104+I103 -> 2.664 | I104: =G104-H104 -> 2.664 | J104: =H104/G104 -> 0
B105: Bahia Caldera S.A. Pesq. | C105: 42005 | D105: 42277 | E105: 36.885 | G105: =E105+F105 -> 36.885 | I105: =G105-H105 -> 36.885 | J105: =H105/G105 -> 0 | K105: =E105+E106 -> 38.827 | L105: =F105+F106 -> 0 | M105: =K105+L105 -> 38.827 | N105: =H105+H106 -> 0 | O105: =M105-N105 -> 38.827 | P105: =N105/M105 -> 0
C106: 42278 | D106: 42369 | E106: 1.942 | G106: =E106+F106+I105 -> 38.827 | I106: =G106-H106 -> 38.827 | J106: =H106/G106 -> 0
B107: Blumar S.A. | C107: 42005 | D107: 42277 | E107: 2234.371 | F107: =2000 -> 2000 | G107: =E107+F107 -> 4234.371 | H107: 4140.179 | I107: =G107-H107 -> 94.192 | J107: =H107/G107 -> 0.97775537 | K107: =E107+E108 -> 2351.984 | L107: =F107+F108 -> 2000 | M107: =K107+L107 -> 4351.984 | N107: =H107+H108 -> 4140.179 | O107: =M107-N107 -> 211.805 | P107: =N107/M107 -> 0.95133139
C108: 42278 | D108: 42369 | E108: 117.613 | G108: =E108+F108+I107 -> 211.805 | I108: =G108-H108 -> 211.805 | J108: =H108/G108 -> 0
B109: Camanchaca S.A. CIA. Pesq. | C109: 42005 | D109: 42277 | E109: 145.95 | F109: =-145.95 -> -145.95 | G109: =E109+F109 -> 0 | I109: =G109-H109 -> 0 | J109: =H109/G109 -> #DIV/0! | K109: =E109+E110 -> 153.633 | L109: =F109+F110 -> -153.633 | M109: =K109+L109 -> 0 | N109: =H109+H110 -> 0 | O109: =M109-N109 -> 0 | P109: =N109/M109 -> #DIV/0!
C110: 42278 | D110: 42369 | E110: 7.683 | F110: =-7.683 -> -7.683 | G110: =E110+F110+I109 -> 0 | I110: =G110-H110 -> 0 | J110: =H110/G110 -> #DIV/0!
...

Sheet Demersales LTP 
B2: 2015. CUOTAS LTP Y SU CONSUMO DE RECURSOS PECES DEMERSALES al 31 de diciembre de 2015.
C5: Periodo | E5: Cuota (t) | H5: Operación | K5: Resumen anual
A6: Unidad de pesquería | B6: Armador | C6: Inicial | D6: Final | E6: Cuota Asignada | F6: Traspaso, Cesion, Arriendo, etc) | G6: Cuota Efectiva | H6: Desembarque (t) | I6: Saldo (t) | J6: % consumido | K6: Cuota Total | L6: Traspaso, Cesion, Arriendo, etc) | M6: Cuota Efectiva | N6: Desembarque (t) | O6: Saldo (t) | P6: % consumido
A7: Congrio dorado NE H/F (41º28,6 LS hasta 47º) | B7: Emdepes S.A. | C7: 42005 | D7: 42063 | E7: 0.526 | G7: =E7+F7 -> 0.526 | I7: =G7-H7 -> 0.526 | J7: =H7/G7 -> 0 | K7: =E7+E8 -> 1.054 | L7: =F7+F8 -> 0 | M7: =K7+L7 -> 1.054 | N7: =H7+H8 -> 0.198 | O7: =M7-N7 -> 0.856 | P7: =N7/M7 -> 0.18785579
C8: 42064 | D8: 42369 | E8: 0.528 | G8: =E8+F8+I7 -> 1.054 | H8: 0.198 | I8: =G8-H8 -> 0.856 | J8: =H8/G8 -> 0.18785579
B9: Grimar S.A.Pesq. | C9: 42005 | D9: 42063 | E9: 7.677 | G9: =E9+F9 -> 7.677 | H9: 2.361 | I9: =G9-H9 -> 5.316 | J9: =H9/G9 -> 0.30754201 | K9: =E9+E10 -> 15.373 | L9: =F9+F10 -> 0 | M9: =K9+L9 -> 15.373 | N9: =H9+H10 -> 15.373 | O9: =M9-N9 -> 0 | P9: =N9/M9 -> 1
C10: 42064 | D10: 42369 | E10: 7.696 | G10: =E10+F10+I9 -> 13.012 | H10: 13.012 | I10: =G10-H10 -> 0 | J10: =H10/G10 -> 1
B11: Deris S.A. | C11: 42005 | D11: 42063 | E11: 144.492 | G11: =E11+F11 -> 144.492 | H11: 3.111 | I11: =G11-H11 -> 141.381 | J11: =H11/G11 -> 0.021530604 | K11: =E11+E12 -> 289.331 | L11: =F11+F12 -> 0 | M11: =K11+L11 -> 289.331 | N11: =H11+H12 -> 236.759 | O11: =M11-N11 -> 52.572 | P11: =N11/M11 -> 0.81829807
C12: 42064 | D12: 42369 | E12: 144.839 | G12: =E12+F12+I11 -> 286.22 | H12: 233.648 | I12: =G12-H12 -> 52.572 | J12: =H12/G12 -> 0.81632311
B13: Pesca Cisne S.A. Pesq. | C13: 42005 | D13: 42063 | E13: 12.325 | G13: =E13+F13 -> 12.325 | I13: =G13-H13 -> 12.325 | J13: =H13/G13 -> 0 | K13: =E13+E14 -> 24.68 | L13: =F13+F14 -> 0 | M13: =K13+L13 -> 24.68 | N13: =H13+H14 -> 0 | O13: =M13-N13 -> 24.68 | P13: =N13/M13 -> 0
C14: 42064 | D14: 42369 | E14: 12.355 | G14: =E14+F14+I13 -> 24.68 | I14: =G14-H14 -> 24.68 | J14: =H14/G14 -> 0
B15: Sur Austral S.A. Pesq. | C15: 42005 | D15: 42063 | E15: 42.979 | G15: =E15+F15 -> 42.979 | H15: 0.407 | I15: =G15-H15 -> 42.572 | J15: =H15/G15 -> 0.009469741 | K15: =E15+E16 -> 86.061 | L15: =F15+F16 -> 0 | M15: =K15+L15 -> 86.061 | N15: =H15+H16 -> 74.426 | O15: =M15-N15 -> 11.635 | P15: =N15/M15 -> 0.8648052
C16: 42064 | D16: 42369 | E16: 43.082 | G16: =E16+F16+I15 -> 85.654 | H16: 74.019 | I16: =G16-H16 -> 11.635 | J16: =H16/G16 -> 0.86416279
A18: Congrio dorado SE (47º hasta 57º) | B18: Emdepes S.A., | C18: 42005 | D18: 42063 | E18: 20.491 | G18: =E18+F18 -> 20.491 | I18: =G18-H18 -> 20.491 | J18: =H18/G18 -> 0 | K18: =E18+E19 -> 40.982 | L18: =F18+F19 -> 0 | M18: =K18+L18 -> 40.982 | N18: =H18+H19 -> 32.265 | O18: =M18-N18 -> 8.717 | P18: =N18/M18 -> 0.78729686
C19: 42064 | D19: 42369 | E19: 20.491 | G19: =E19+F19+I18 -> 40.982 | H19: 32.265 | I19: =G19-H19 -> 8.717 | J19: =H19/G19 -> 0.78729686
B20: Grimar S.A.Pesq. | C20: 42005 | D20: 42063 | E20: 0.061 | G20: =E20+F20 -> 0.061 | I20: =G20-H20 -> 0.061 | J20: =H20/G20 -> 0 | K20: =E20+E21 -> 0.122 | L20: =F20+F21 -> 0 | M20: =K20+L20 -> 0.122 | N20: =H20+H21 -> 0 | O20: =M20-N20 -> 0.122 | P20: =N20/M20 -> 0
C21: 42064 | D21: 42369 | E21: 0.061 | G21: =E21+F21+I20 -> 0.122 | I21: =G21-H21 -> 0.122 | J21: =H21/G21 -> 0
B22: Deris S.A. | C22: 42005 | D22: 42063 | E22: 70.164 | G22: =E22+F22 -> 70.164 | H22: 0.169 | I22: =G22-H22 -> 69.995 | J22: =H22/G22 -> 0.0024086426 | K22: =E22+E23 -> 140.328 | L22: =F22+F23 -> 0 | M22: =K22+L22 -> 140.328 | N22: =H22+H23 -> 116.013 | O22: =M22-N22 -> 24.315 | P22: =N22/M22 -> 0.82672738
C23: 42064 | D23: 42369 | E23: 70.164 | G23: =E23+F23+I22 -> 140.159 | H23: 115.844 | I23: =G23-H23 -> 24.315 | J23: =H23/G23 -> 0.82651845
B24: Pesca Cisne S.A | C24: 42005 | D24: 42063 | E24: 27.254 | G24: =E24+F24 -> 27.254 | H24: 42.875 | I24: =G24-H24 -> -15.621 | J24: =H24/G24 -> 1.5731636 | K24: =E24+E25 -> 54.508 | L24: =F24+F25 -> 0 | M24: =K24+L24 -> 54.508 | N24: =H24+H25 -> 54.127 | O24: =M24-N24 -> 0.381 | P24: =N24/M24 -> 0.9930102
C25: 42064 | D25: 42369 | E25: 27.254 | G25: =E25+F25+I24 -> 11.633 | H25: 11.252 | I25: =G25-H25 -> 0.381 | J25: =H25/G25 -> 0.96724835
B26: Sur Austral S.A. Pesq. | C26: 42005 | D26: 42063 | E26: 0.03 | G26: =E26+F26 -> 0.03 | I26: =G26-H26 -> 0.03 | J26: =H26/G26 -> 0 | K26: =E26+E27 -> 0.06 | L26: =F26+F27 -> 0 | M26: =K26+L26 -> 0.06 | N26: =H26+H27 -> 0 | O26: =M26-N26 -> 0.06 | P26: =N26/M26 -> 0
C27: 42064 | D27: 42369 | E27: 0.03 | G27: =E27+F27+I26 -> 0.06 | I27: =G27-H27 -> 0.06 | J27: =H27/G27 -> 0
A29: Merluza del sur NE F/H (41º28,6 LS al 47º LS) (Res Ex. N°3510/14. Modificada por Res Ex. N°1919/15 | B29: Emdepes S.A. | C29: 42005 | D29: 42035 | E29: 174.061 | F29: =253.457 -> 253.457 | G29: =E29+F29 -> 427.518 | I29: =G29-H29 -> 427.518 | J29: =H29/G29 -> 0 | K29: =E29+E30 -> 497.061 | L29: =F29+F30 -> 535.266 | M29: =K29+L29 -> 1032.327 | N29: =H29+H30 -> 1031.673 | O29: =M29-N29 -> 0.654 | P29: =N29/M29 -> 0.99936648
C30: 42036 | D30: 42369 | E30: 323 | F30: =281.809 -> 281.809 | G30: =E30+F30+I29 -> 1032.327 | H30: 1031.673 | I30: =G30-H30 -> 0.654 | J30: =H30/G30 -> 0.99936648
B31: Grimar S.A. Pesq. | C31: 42005 | D31: 42035 | E31: 40.42 | F31: =17.91+387.736+68.671+4.576+20.345+19.926+8.489+215.459+12.732+7.159+18.315+16.555+8.283+18.764+0.031698 -> 824.9517 | G31: =E31+F31 -> 865.3717 | H31: 47.83 | I31: =G31-H31 -> 817.5417 | J31: =H31/G31 -> 0.055271047 | K31: =E31+E32 -> 115.426 | L31: =F31+F32 -> 824.9517 | M31: =K31+L31 -> 940.3777 | N31: =H31+H32 -> 990.622 | O31: =M31-N31 -> -50.244302 | P31: =N31/M31 -> 1.0534299
C32: 42036 | D32: 42369 | E32: 75.006 | G32: 887.952 | H32: 942.792 | I32: =G32-H32 -> -54.84 | J32: =H32/G32 -> 1.0617601
B33: Deris S.A. | C33: 42005 | D33: 42035 | E33: 632.229 | F33: =70.075+20.904+276.15+600+200 -> 1167.129 | G33: =E33+F33 -> 1799.358 | I33: =G33-H33 -> 1799.358 | J33: =H33/G33 -> 0 | K33: =E33+E34 -> 1805.442 | L33: =F33+F34 -> 1167.129 | M33: =K33+L33 -> 2972.571 | N33: =H33+H34 -> 2944.326 | O33: =M33-N33 -> 28.245 | P33: =N33/M33 -> 0.99049812
C34: 42036 | D34: 42369 | E34: 1173.213 | G34: =E34+F34+I33 -> 2972.571 | H34: 2944.326 | I34: =G34-H34 -> 28.245 | J34: =H34/G34 -> 0.99049812
B35: Pesca Cisne S.A. | C35: 42005 | D35: 42035 | E35: 40.601 | G35: =E35+F35 -> 40.601 | I35: =G35-H35 -> 40.601 | J35: =H35/G35 -> 0 | K35: =E35+E36 -> 115.943 | L35: =F35+F36 -> 0 | M35: =K35+L35 -> 115.943 | N35: =H35+H36 -> 0 | O35: =M35-N35 -> 115.943 | P35: =N35/M35 -> 0
C36: 42036 | D36: 42369 | E36: 75.342 | G36: =E36+F36+I35 -> 115.943 | I36: =G36-H36 -> 115.943 | J36: =H36/G36 -> 0
B37: Sur Austral S.A. Pesq. | C37: 42005 | D37: 42035 | E37: 477.69 | F37: =-0.03898 -> -0.03898 | G37: =E37+F37 -> 477.65102 | H37: 35.301 | I37: =G37-H37 -> 442.35002 | J37: =H37/G37 -> 0.073905422 | K37: =E37+E38 -> 1364.129 | L37: =F37+F38 -> -0.03898 | M37: =K37+L37 -> 1364.09 | N37: =H37+H38 -> 1359.935 | O37: =M37-N37 -> 4.15502 | P37: =N37/M37 -> 0.996954
C38: 42036 | D38: 42369 | E38: 886.439 | G38: =E38+F38+I37 -> 1328.789 | H38: 1324.634 | I38: =G38-H38 -> 4.15502 | J38: =H38/G38 -> 0.99687308
B39: Congelados del Pacífico S.A. | C39: 42005 | D39: 42035 | E39: 0 | F39: =0.03898 -> 0.03898 | G39: =E39+F39 -> 0.03898 | H39: 0 | I39: =G39-H39 -> 0.03898 | J39: =H39/G39 -> 0 | K39: =E39+E40 -> 0 | L39: =F39+F40 -> 0.03898 | M39: =K39+L39 -> 0.03898 | N39: =H39+H40 -> 0.137 | O39: =M39-N39 -> -0.09802 | P39: =N39/M39 -> 3.5146229
C40: 42036 | D40: 42369 | E40: 0 | G40: =E40+F40+I39 -> 0.03898 | H40: 0.137 | I40: =G40-H40 -> -0.09802 | J40: =H40/G40 -> 3.5146229
A42: Merluza Del Sur SE Fabrica (47º LS al 57º LS) (Res Ex. N°3510/14. Modificada por Res Ex. N°1919/15 | B42: Emdepes S.A. | C42: 42005 | D42: 42035 | E42: 253.457 | F42: =-253.457 -> -253.457 | G42: =E42+F42 -> 0 | I42: =G42-H42 -> 0 | J42: =H42/G42 -> #DIV/0! | K42: =E42+E43 -> 724.62 | L42: =F42+F43 -> -535.266 | M42: =K42+L42 -> 189.354 | N42: =H42+H43 -> 98.394 | O42: =M42-N42 -> 90.96 | P42: =N42/M42 -> 0.5196299
C43: 41671 | D43: 42369 | E43: 471.163 | F43: =-281.809 -> -281.809 | G43: =E43+F43+I42 -> 189.354 | H43: 98.394 | I43: =G43-H43 -> 90.96 | J43: =H43/G43 -> 0.5196299
B44: Grimar S.A. Pesq. | C44: 42005 | D44: 42035 | E44: 0.49 | F44: =35.875 -> 35.875 | G44: =E44+F44 -> 36.365 | I44: =G44-H44 -> 36.365 | J44: =H44/G44 -> 0 | K44: =E44+E45 -> 1.4 | L44: =F44+F45 -> 35.875 | M44: =K44+L44 -> 37.275 | N44: =H44+H45 -> 0 | O44: =M44-N44 -> 37.275 | P44: =N44/M44 -> 0
C45: 41671 | D45: 42369 | E45: 0.91 | G45: =E45+F45+I44 -> 37.275 | I45: =G45-H45 -> 37.275 | J45: =H45/G45 -> 0
B46: Deris S.A. | C46: 42005 | D46: 42035 | E46: 471.697 | F46: =824.178-600-200+29.485+0.004576 -> 53.667576 | G46: =E46+F46 -> 525.36458 | I46: =G46-H46 -> 525.36458 | J46: =H46/G46 -> 0 | K46: =E46+E47 -> 1348.557 | L46: =F46+F47 -> 53.667576 | M46: =K46+L46 -> 1402.2246 | N46: =H46+H47 -> 1190.658 | O46: =M46-N46 -> 211.56658 | P46: =N46/M46 -> 0.84912076
C47: 41671 | D47: 42369 | E47: 876.86 | G47: =E47+F47+I46 -> 1402.2246 | H47: 1190.658 | I47: =G47-H47 -> 211.56658 | J47: =H47/G47 -> 0.84912076
B48: Pesca Cisne S.A. | C48: 42005 | D48: 42035 | E48: 142.707 | F48: =62.801 -> 62.801 | G48: =E48+F48 -> 205.508 | I48: =G48-H48 -> 205.508 | J48: =H48/G48 -> 0 | K48: =E48+E49 -> 407.992 | L48: =F48+F49 -> 62.801 | M48: =K48+L48 -> 470.793 | N48: =H48+H49 -> 416.973 | O48: =M48-N48 -> 53.82 | P48: =N48/M48 -> 0.88568224
C49: 41671 | D49: 42369 | E49: 265.285 | G49: =E49+F49+I48 -> 470.793 | H49: 416.973 | I49: =G49-H49 -> 53.82 | J49: =H49/G49 -> 0.88568224
B50: Sur Austral S.A. Pesq. | C50: 42005 | D50: 42035 | E50: 3.648 | G50: =E50+F50 -> 3.648 | I50: =G50-H50 -> 3.648 | J50: =H50/G50 -> 0 | K50: =E50+E51 -> 10.43 | L50: =F50+F51 -> 0 | M50: =K50+L50 -> 10.43 | N50: =H50+H51 -> 0 | O50: =M50-N50 -> 10.43 | P50: =N50/M50 -> 0
C51: 41671 | D51: 42369 | E51: 6.782 | G51: =E51+F51+I50 -> 10.43 | I51: =G51-H51 -> 10.43 | J51: =H51/G51 -> 0
A53: Merluza tres aletas NE/SE (41º28,6 LS hasta 57º) | B53: Emdepes S.A. | C53: 42005 | D53: 42094 | E53: 5047.676 | G53: =E53+F53 -> 5047.676 | I53: =G53-H53 -> 5047.676 | J53: =H53/G53 -> 0 | K53: =E53+E54 -> 13754.376 | L53: =F53+F54 -> 0 | M53: =K53+L53 -> 13754.376 | N53: =H53+H54 -> 7109.556 | O53: =M53-N53 -> 6644.82 | P53: =N53/M53 -> 0.51689411
C54: 42095 | D54: 42369 | E54: 8706.7 | G54: =E54+F54+I53 -> 13754.376 | H54: 7109.556 | I54: =G54-H54 -> 6644.82 | J54: =H54/G54 -> 0.51689411
B55: Grimar S.A. Pesq. | C55: 42005 | D55: 42094 | E55: 0.149 | G55: =E55+F55 -> 0.149 | I55: =G55-H55 -> 0.149 | J55: =H55/G55 -> 0 | K55: =E55+E56 -> 0.405 | L55: =F55+F56 -> 0 | M55: =K55+L55 -> 0.405 | N55: =H55+H56 -> 0 | O55: =M55-N55 -> 0.405 | P55: =N55/M55 -> 0
C56: 42095 | D56: 42369 | E56: 0.256 | G56: =E56+F56+I55 -> 0.405 | I56: =G56-H56 -> 0.405 | J56: =H56/G56 -> 0
B57: Deris S.A. | C57: 42005 | D57: 42094 | E57: 5.179 | F57: =-0.4 -> -0.4 | G57: =E57+F57 -> 4.779 | H57: 0.036 | I57: =G57-H57 -> 4.743 | J57: =H57/G57 -> 0.0075329567 | K57: =E57+E58 -> 14.112 | L57: =F57+F58 -> -0.4 | M57: =K57+L57 -> 13.712 | N57: =H57+H58 -> 7.587 | O57: =M57-N57 -> 6.125 | P57: =N57/M57 -> 0.55331097
C58: 42095 | D58: 42369 | E58: 8.933 | G58: =E58+F58+I57 -> 13.676 | H58: 7.551 | I58: =G58-H58 -> 6.125 | J58: =H58/G58 -> 0.55213513
B59: Sur Austral S.A. Pesq. | C59: 42005 | D59: 42094 | E59: 0.406 | G59: =E59+F59 -> 0.406 | I59: =G59-H59 -> 0.406 | J59: =H59/G59 -> 0 | K59: =E59+E60 -> 1.107 | L59: =F59+F60 -> 0 | M59: =K59+L59 -> 1.107 | N59: =H59+H60 -> 0 | O59: =M59-N59 -> 1.107 | P59: =N59/M59 -> 0
C60: 42095 | D60: 42369 | E60: 0.701 | G60: =E60+F60+I59 -> 1.107 | I60: =G60-H60 -> 1.107 | J60: =H60/G60 -> 0
B61: Pesca Cisne S.A. | C61: 42005 | D61: 42094 | E61: 0 | F61: =0.4 -> 0.4 | G61: =E61+F61 -> 0.4 | I61: =G61-H61 -> 0.4 | J61: =H61/G61 -> 0 | K61: =E61+E62 -> 0 | L61: =F61+F62 -> 0.4 | M61: =K61+L61 -> 0.4 | N61: =H61+H62 -> 0 | O61: =M61-N61 -> 0.4 | P61: =N61/M61 -> 0
C62: 42095 | D62: 42369 | E62: 0 | G62: =E62+F62+I61 -> 0.4 | I62: =G62-H62 -> 0.4 | J62: =H62/G62 -> 0
A64: Merluza cola V-X | B64: Alimentos Marinos S.A. | C64: 42005 | D64: 42094 | E64: 1251.574 | F64: =-1251.574 -> -1251.574 | G64: =E64+F64 -> 0 | I64: =G64-H64 -> 0 | J64: =H64/G64 -> #DIV/0! | K64: =E64+E65 -> 3129 | L64: =F64+F65 -> -3128 | M64: =K64+L64 -> 1 | N64: =H64+H65 -> 0 | O64: =M64-N64 -> 1 | P64: =N64/M64 -> 0
C65: 42095 | D65: 42369 | E65: 1877.426 | F65: =-748.426-1128 -> -1876.426 | G65: =E65+F65+I64 -> 1 | I65: =G65-H65 -> 1 | J65: =H65/G65 -> 0
B66: Bio Bio S.A.Pesq. | C66: 42005 | D66: 42094 | E66: 902.274 | F66: =-0.48206-0.24103+0.24105-901.79196 -> -902.274 | G66: =E66+F66 -> 0 | I66: =G66-H66 -> 0 | J66: =H66/G66 -> #DIV/0! | K66: =E66+E67 -> 2255.732 | L66: =F66+F67 -> -1494.6089 | M66: =K66+L66 -> 761.1231 | N66: =H66+H67 -> 727.056 | O66: =M66-N66 -> 34.0671 | P66: =N66/M66 -> 0.95524101
C67: 42095 | D67: 42369 | E67: 1353.458 | F67: =-598.4149+6.08 -> -592.3349 | G67: =E67+F67+I66 -> 761.1231 | H67: 727.056 | I67: =G67-H67 -> 34.0671 | J67: =H67/G67 -> 0.95524101
B68: Blumar S.A. | C68: 42005 | D68: 42094 | E68: 2164.631 | F68: =-2164.631+0.24105 -> -2164.3899 | G68: =E68+F68 -> 0.24105 | I68: =G68-H68 -> 0.24105 | J68: =H68/G68 -> 0 | K68: =E68+E69 -> 5411.69 | L68: =F68+F69 -> -5411.2077 | M68: =K68+L68 -> 0.48225 | N68: =H68+H69 -> 0 | O68: =M68-N68 -> 0.48225 | P68: =N68/M68 -> 0
C69: 42095 | D69: 42369 | E69: 3247.059 | F69: =-3246.8178 -> -3246.8178 | G69: =E69+F69+I68 -> 0.48225 | I69: =G69-H69 -> 0.48225 | J69: =H69/G69 -> 0
B70: Bento Inversiones SpA. | C70: 42005 | D70: 42094 | E70: 320 | F70: =-320 -> -320 | G70: =E70+F70 -> 0 | I70: =G70-H70 -> 0 | J70: =H70/G70 -> #DIV/0! | K70: =E70+E71 -> 800.017 | L70: =F70+F71 -> -800.017 | M70: =K70+L70 -> 0 | N70: =H70+H71 -> 0 | O70: =M70-N70 -> 0 | P70: =N70/M70 -> #DIV/0!
C71: 42095 | D71: 42369 | E71: 480.017 | F71: =-480.017 -> -480.017 | G71: =E71+F71+I70 -> 0 | I71: =G71-H71 -> 0 | J71: =H71/G71 -> #DIV/0!
B72: Centro Sur S.A. Pesq. | C72: 42005 | D72: 42094 | E72: 0.193 | G72: =E72+F72 -> 0.193 | I72: =G72-H72 -> 0.193 | J72: =H72/G72 -> 0 | K72: =E72+E73 -> 0.482 | L72: =F72+F73 -> 0 | M72: =K72+L72 -> 0.482 | N72: =H72+H73 -> 0 | O72: =M72-N72 -> 0.482 | P72: =N72/M72 -> 0
C73: 42095 | D73: 42369 | E73: 0.289 | G73: =E73+F73+I72 -> 0.482 | I73: =G73-H73 -> 0.482 | J73: =H73/G73 -> 0
B74: Foodcorp S.A. | C74: 42005 | D74: 42094 | E74: 52.643 | F74: =-52.643 -> -52.643 | G74: =E74+F74 -> 0 | I74: =G74-H74 -> 0 | J74: =H74/G74 -> #DIV/0! | K74: =E74+E75 -> 131.61 | L74: =F74+F75 -> -131 | M74: =K74+L74 -> 0.61 | N74: =H74+H75 -> 0 | O74: =M74-N74 -> 0.61 | P74: =N74/M74 -> 0
C75: 42095 | D75: 42369 | E75: 78.967 | F75: =-78.357 -> -78.357 | G75: =E75+F75+I74 -> 0.61 | I75: =G75-H75 -> 0.61 | J75: =H75/G75 -> 0
B76: Grimar S.A.Pesq. | C76: 42005 | D76: 42094 | E76: 536.183 | F76: =320+51.19+24.794 -> 395.984 | G76: =E76+F76 -> 932.167 | H76: 1363.065 | I76: =G76-H76 -> -430.898 | J76: =H76/G76 -> 1.4622541 | K76: =E76+E77 -> 1340.486 | L76: =F76+F77 -> 697.198 | M76: =K76+L76 -> 2037.684 | N76: =H76+H77 -> 2148.035 | O76: =M76-N76 -> -110.351 | P76: =N76/M76 -> 1.0541551
C77: 42095 | D77: 42369 | E77: 804.303 | F77: =480.017+74.387+37.192+750.104-1040.486 -> 301.214 | G77: =E77+F77+I76 -> 674.619 | H77: 784.97 | I77: =G77-H77 -> -110.351 | J77: =H77/G77 -> 1.1635753
B78: Inostroza Concha Pelantaro. | C78: 42005 | D78: 42094 | E78: 2.913 | F78: =-2.913 -> -2.913 | G78: =E78+F78 -> 0 | I78: =G78-H78 -> 0 | J78: =H78/G78 -> #DIV/0! | K78: =E78+E79 -> 7.282 | L78: =F78+F79 -> -7.282 | M78: =K78+L78 -> 0 | N78: =H78+H79 -> 0 | O78: =M78-N78 -> 0 | P78: =N78/M78 -> #DIV/0!
C79: 42095 | D79: 42369 | E79: 4.369 | F79: =-4.369 -> -4.369 | G79: =E79+F79+I78 -> 0 | I79: =G79-H79 -> 0 | J79: =H79/G79 -> #DIV/0!
B80: MG Inversiones SpA. | C80: 42005 | D80: 42094 | E80: 51.19 | F80: =-51.19 -> -51.19 | G80: =E80+F80 -> 0 | I80: =G80-H80 -> 0 | J80: =H80/G80 -> #DIV/0! | K80: =E80+E81 -> 127.977 | L80: =F80+F81 -> -125.577 | M80: =K80+L80 -> 2.4 | N80: =H80+H81 -> 0 | O80: =M80-N80 -> 2.4 | P80: =N80/M80 -> 0
C81: 42095 | D81: 42369 | E81: 76.787 | F81: =-74.387 -> -74.387 | G81: =E81+F81+I80 -> 2.4 | I81: =G81-H81 -> 2.4 | J81: =H81/G81 -> 0
B82: Inversiones Pesqueras SpA. | C82: 42005 | D82: 42094 | E82: 0.222 | G82: =E82+F82 -> 0.222 | I82: =G82-H82 -> 0.222 | J82: =H82/G82 -> 0 | K82: =E82+E83 -> 0.555 | L82: =F82+F83 -> 0 | M82: =K82+L82 -> 0.555 | N82: =H82+H83 -> 0 | O82: =M82-N82 -> 0.555 | P82: =N82/M82 -> 0
C83: 42095 | D83: 42369 | E83: 0.333 | G83: =E83+F83+I82 -> 0.555 | I83: =G83-H83 -> 0.555 | J83: =H83/G83 -> 0
B84: Isla Quihua S.A. Pesq. | C84: 42005 | D84: 42094 | E84: 91.23 | F84: =-91.23 -> -91.23 | G84: =E84+F84 -> 0 | I84: =G84-H84 -> 0 | J84: =H84/G84 -> #DIV/0! | K84: =E84+E85 -> 228.08 | L84: =F84+F85 -> -228 | M84: =K84+L84 -> 0.08 | N84: =H84+H85 -> 0 | O84: =M84-N84 -> 0.08 | P84: =N84/M84 -> 0
C85: 42095 | D85: 42369 | E85: 136.85 | F85: =-136.77 -> -136.77 | G85: =E85+F85+I84 -> 0.08 | I85: =G85-H85 -> 0.08 | J85: =H85/G85 -> 0
B86: Landes S.A. Soc Pesq. | C86: 42005 | D86: 42094 | E86: 454.82 | F86: =-454.82 -> -454.82 | G86: =E86+F86 -> 0 | I86: =G86-H86 -> 0 | J86: =H86/G86 -> #DIV/0! | K86: =E86+E87 -> 1137.074 | L86: =F86+F87 -> -1085.728 | M86: =K86+L86 -> 51.346 | N86: =H86+H87 -> 0 | O86: =M86-N86 -> 51.346 | P86: =N86/M86 -> 0
C87: 42095 | D87: 42369 | E87: 682.254 | F87: =-630.908 -> -630.908 | G87: =E87+F87+I86 -> 51.346 | I87: =G87-H87 -> 51.346 | J87: =H87/G87 -> 0
B88: Lota Protein S.A. | C88: 42005 | D88: 42094 | E88: 284.983 | F88: =2.913-284.983-0.24272-0.24272 -> -282.55544 | G88: =E88+F88 -> 2.42756 | I88: =G88-H88 -> 2.42756 | J88: =H88/G88 -> 0 | K88: =E88+E89 -> 712.472 | L88: =F88+F89 -> -698.92744 | M88: =K88+L88 -> 13.54456 | N88: =H88+H89 -> 0 | O88: =M88-N88 -> 13.54456 | P88: =N88/M88 -> 0
C89: 42095 | D89: 42369 | E89: 427.489 | F89: =4.369-420.741 -> -416.372 | G89: =E89+F89+I88 -> 13.54456 | I89: =G89-H89 -> 13.54456 | J89: =H89/G89 -> 0
B90: Mar Profundo S.a. Pesq. | C90: 42005 | D90: 42094 | E90: 68.84 | F90: =-68.84 -> -68.84 | G90: =E90+F90 -> 0 | I90: =G90-H90 -> 0 | J90: =H90/G90 -> #DIV/0! | K90: =E90+E91 -> 172.103 | L90: =F90+F91 -> -172 | M90: =K90+L90 -> 0.103 | N90: =H90+H91 -> 0 | O90: =M90-N90 -> 0.103 | P90: =N90/M90 -> 0
C91: 42095 | D91: 42369 | E91: 103.263 | F91: =-103.16 -> -103.16 | G91: =E91+F91+I90 -> 0.103 | I91: =G91-H91 -> 0.103 | J91: =H91/G91 -> 0
B92: Orizon S.A. | C92: 42005 | D92: 42094 | E92: 2031.338 | F92: =-2031.338 -> -2031.338 | G92: =E92+F92 -> 0 | I92: =G92-H92 -> 0 | J92: =H92/G92 -> #DIV/0! | K92: =E92+E93 -> 5078.451 | L92: =F92+F93 -> -5000 | M92: =K92+L92 -> 78.451 | N92: =H92+H93 -> 0 | O92: =M92-N92 -> 78.451 | P92: =N92/M92 -> 0
C93: 42095 | D93: 42369 | E93: 3047.113 | F93: =-2968.662 -> -2968.662 | G93: =E93+F93+I92 -> 78.451 | I93: =G93-H93 -> 78.451 | J93: =H93/G93 -> 0
B94: Deris S.A. | C94: 42005 | D94: 42094 | E94: 34.888 | F94: =-34.888 -> -34.888 | G94: =E94+F94 -> 0 | I94: =G94-H94 -> 0 | J94: =H94/G94 -> #DIV/0! | K94: =E94+E95 -> 87.222 | L94: =F94+F95 -> -87.222 | M94: =K94+L94 -> 0 | N94: =H94+H95 -> 0 | O94: =M94-N94 -> 0 | P94: =N94/M94 -> #DIV/0!
C95: 42095 | D95: 42369 | E95: 52.334 | F95: =-52.334 -> -52.334 | G95: =E95+F95+I94 -> 0 | I95: =G95-H95 -> 0 | J95: =H95/G95 -> #DIV/0!
B96: Redina SpA. INV. | C96: 42005 | D96: 42094 | E96: 24.794 | F96: =-24.794 -> -24.794 | G96: =E96+F96 -> 0 | I96: =G96-H96 -> 0 | J96: =H96/G96 -> #DIV/0! | K96: =E96+E97 -> 61.986 | L96: =F96+F97 -> -61.986 | M96: =K96+L96 -> 0 | N96: =H96+H97 -> 0 | O96: =M96-N96 -> 0 | P96: =N96/M96 -> #DIV/0!
C97: 42095 | D97: 42369 | E97: 37.192 | F97: =-37.192 -> -37.192 | G97: =E97+F97+I96 -> 0 | I97: =G97-H97 -> 0 | J97: =H97/G97 -> #DIV/0!
B98: San Antonio S.A. pesq. | C98: 42005 | D98: 42094 | E98: 25.739 | F98: =-25.739 -> -25.739 | G98: =E98+F98 -> 0 | I98: =G98-H98 -> 0 | J98: =H98/G98 -> #DIV/0! | K98: =E98+E99 -> 64.348 | L98: =F98+F99 -> -64 | M98: =K98+L98 -> 0.348 | N98: =H98+H99 -> 0 | O98: =M98-N98 -> 0.348 | P98: =N98/M98 -> 0
C99: 42095 | D99: 42369 | E99: 38.609 | F99: =-38.261 -> -38.261 | G99: =E99+F99+I98 -> 0.348 | I99: =G99-H99 -> 0.348 | J99: =H99/G99 -> 0
B100: Sur Austral S.A. Pesq. | C100: 42005 | D100: 42094 | E100: 541.84 | F100: =750.104-375 -> 375.104 | G100: =E100+F100 -> 916.944 | H100: 1440.888 | I100: =G100-H100 -> -523.944 | J100: =H100/G100 -> 1.5714024 | K100: =E100+E101 -> 1354.628 | L100: =F100+F101 -> 1399.3596 | M100: =K100+L100 -> 2753.9876 | N100: =H100+H101 -> 2723.855 | O100: =M100-N100 -> 30.132595 | P100: =N100/M100 -> 0.98905856
C101: 42095 | D101: 42369 | E101: 812.788 | F101: =1500.206875-581+105.04872 -> 1024.2556 | G101: =E101+F101+I100 -> 1313.0996 | H101: 1282.967 | I101: =G101-H101 -> 30.132595 | J101: =H101/G101 -> 0.97705232
B102: Camanchaca Pesca Sur S.A. | C102: 42005 | D102: 42094 | E102: 800.705 | F102: =-750.104-350.225 -> -1100.329 | G102: =E102+F102 -> -299.624 | I102: =G102-H102 -> -299.624 | J102: =H102/G102 -> 0 | K102: =E102+E103 -> 2001.804 | L102: =F102+F103 -> -1850.433 | M102: =K102+L102 -> 151.371 | N102: =H102+H103 -> 0 | O102: =M102-N102 -> 151.371 | P102: =N102/M102 -> 0
C103: 42095 | D103: 42369 | E103: 1201.099 | F103: =-750.104 -> -750.104 | G103: =E103+F103+I102 -> 151.371 | I103: =G103-H103 -> 151.371 | J103: =H103/G103 -> 0
B104: Congelados del Pacífico S.A. | C104: 42005 | D104: 42094 | E104: 0 | F104: =5411.44889+0.48206+0.24103-0.24105-0.24105+284.983-0.24105+454.82 -> 6151.2518 | G104: =E104+F104 -> 6151.2518 | H104: 2020.758 | I104: =G104-H104 -> 4130.4938 | J104: =H104/G104 -> 0.32851167 | K104: =E104+E105 -> 0 | L104: =F104+F105 -> 7202.9008 | M104: =K104+L104 -> 7202.9008 | N104: =H104+H105 -> 6648.133 | O104: =M104-N104 -> 554.76783 | P104: =N104/M104 -> 0.92297994
C105: 42095 | D105: 42369 | E105: 0 | F105: =420.741+630.908 -> 1051.649 | G105: =E105+F105+I104 -> 5182.1428 | H105: 4627.375 | I105: =G105-H105 -> 554.76783 | J105: =H105/G105 -> 0.89294625
B106: Pesquera Antonio Cruz Cordoba Nakouzi EIRL | C106: 42005 | D106: 42094 | E106: 0 | F106: =0.24105 -> 0.24105 | G106: =E106+F106 -> 0.24105 | H106: 0 | I106: =G106-H106 -> 0.24105 | J106: =H106/G106 -> 0 | K106: =E106+E107 -> 0 | L106: =F106+F107 -> 0.24105 | M106: =K106+L106 -> 0.24105 | N106: =H106+H107 -> 0 | O106: =M106-N106 -> 0.24105 | P106: =N106/M106 -> 0
C107: 42095 | D107: 42369 | E107: 0 | G107: =E107+F107+I106 -> 0.24105 | I107: =G107-H107 -> 0.24105 | J107: =H107/G107 -> 0
B108: Enfemar Ltda. Soc. Pesq. | C108: 42005 | D108: 42094 | E108: 0 | F108: =0.24272 -> 0.24272 | G108: =E108+F108 -> 0.24272 | H108: 0 | I108: =G108-H108 -> 0.24272 | J108: =H108/G108 -> 0 | K108: =E108+E109 -> 0 | L108: =F108+F109 -> 0.24272 | M108: =K108+L108 -> 0.24272 | N108: =H108+H109 -> 0 | O108: =M108-N108 -> 0.24272 | P108: =N108/M108 -> 0
...

Sheet Crustaceos  LTP
B1: 2015. CUOTAS LTP Y SU CONSUMO DE RECURSOS CRUSTÁCEOS al 31 de diciembre del 2015 | AV1: * registra la sumatoria de los traspasos en todas las regiones
C4: Periodo | E4: Cuota II Región (t) | H4: Operación II región | K4: Cuota III Región (t) | N4: Operación III Región | Q4: Cuota IV Región (t) | T4: Operación IV Región | W4: Cuota V Región (t) | Z4: Operación V Región | AC4: Cuota VI Región (t) | AF4: Operación VI Región | AI4: Cuota VII Región (t) | AL4: Operación VII Región | AO4: Cuota VIII Región (t) | AR4: Operación VIII Región | AU4: Cuota y Operación Camaron Nailon II-VIII | BA4: Resumen Global Anual II-VIII
A5: Unidad de pesquería | B5: Armador | C5: Inicial | D5: Final | E5: Cuota Asignada | F5: Traspaso, Cesion, Arriendo, etc) | G5: Cuota Efectiva | H5: Desembarque (t) | I5: Saldo (t) | J5: Cuota Total efectiva | K5: Cuota Asignada | L5: Traspaso, Cesion, Arriendo, etc) | M5: Cuota Efectiva | N5: Desembarque (t) | O5: Saldo (t) | P5: Cuota Total efectiva | Q5: Cuota Asignada | R5: Traspaso, Cesion, Arriendo, etc) | S5: Cuota Efectiva | T5: Desembarque (t) | U5: Saldo (t) | V5: Cuota Total efectiva | W5: Cuota Asignada | X5: Traspaso, Cesion, Arriendo, etc) | Y5: Cuota Efectiva | Z5: Desembarque (t) | AA5: Saldo (t) | AB5: Cuota Total efectiva | AC5: Cuota Asignada | AD5: Traspaso, Cesion, Arriendo, etc) | AE5: Cuota Efectiva | AF5: Desembarque (t) | AG5: Saldo (t) | AH5: Cuota Total efectiva | AI5: Cuota Asignada | AJ5: Traspaso, Cesion, Arriendo, etc) | AK5: Cuota Efectiva | AL5: Desembarque (t) | AM5: Saldo (t) | AN5: Cuota Total efectiva | AO5: Cuota Asignada | AP5: Traspaso, Cesion, Arriendo, etc) | AQ5: Cuota Efectiva | AR5: Desembarque (t) | AS5: Saldo (t) | AT5: Cuota Total efectiva | AU5: Cuota Asignada II-VIII | AV5: * Traspaso, Cesion, Arriendo, etc) | AW5: Cuota Efectiva | AX5: Desembarque (t) II-VIII | AY5: Saldo (t) | AZ5: % consumido | BA5: Cuota Total | BB5: * Traspaso, Cesion, Arriendo, etc) | BC5: Cuota Efectiva | BD5: Desembarque (t) | BE5: Saldo (t) | BF5: % consumido
A6: Camarón nailon II-VIII | B6: Antarctic Seafood S.A. | C6: 42005 | D6: 42216 | E6: 1.398 | G6: =E6+F6 -> 1.398 | I6: =G6-H6 -> 1.398 | J6: =E6+E7+F6+F7 -> 1.747 | K6: 6.466 | M6: =K6+L6 -> 6.466 | O6: =M6-N6 -> 6.466 | P6: =K6+K7+L6+L7 -> 8.039 | Q6: 44.734 | S6: =Q6+R6 -> 44.734 | T6: 33.895 | U6: =S6-T6 -> 10.839 | V6: =Q6+Q7+R6+R7 -> 55.918 | W6: 83.877 | Y6: =W6+X6 -> 83.877 | Z6: 77.779 | AA6: =Y6-Z6 -> 6.098 | AB6: =W6+W7+X6+X7 -> 104.846 | AC6: 142.591 | AE6: =AC6+AD6 -> 142.591 | AF6: 49.746 | AG6: =AE6-AF6 -> 92.845 | AH6: =AC6+AC7+AD6+AD7 -> 178.239 | AI6: 141.193 | AK6: =AI6+AJ6 -> 141.193 | AL6: 137.93 | AM6: =AK6-AL6 -> 3.263 | AN6: =AI6+AI7+AJ6+AJ7 -> 176.491 | AO6: 142.591 | AQ6: =AO6+AP6 -> 142.591 | AR6: 141.052 | AS6: =AQ6-AR6 -> 1.539 | AT6: =AO6+AO7+AP6+AP7 -> 178.239 | AU6: =E6+K6+Q6+W6+AC6+AI6+AO6 -> 562.85 | AV6: =F6+L6+R6+X6+AD6+AJ6+AP6 -> 0 | AW6: =AU6+AV6 -> 562.85 | AX6: =H6+N6+T6+Z6+AF6+AL6+AR6 -> 440.402 | AY6: =AW6-AX6 -> 122.448 | AZ6: =AX6/AW6 -> 0.78245003 | BA6: =AU6+AU7 -> 703.519 | BB6: =AV6+AV7 -> 0 | BC6: =BA6+BB6 -> 703.519 | BD6: =AX6+AX7 -> 638.827 | BE6: =BC6-BD6 -> 64.692 | BF6: =BD6/BC6 -> 0.90804513
C7: 42278 | D7: 42369 | E7: 0.349 | G7: =E7+F7+I6 -> 1.747 | I7: =G7-H7 -> 1.747 | K7: 1.573 | M7: =K7+L7+O6 -> 8.039 | O7: =M7-N7 -> 8.039 | Q7: 11.184 | S7: =Q7+R7+U6 -> 22.023 | T7: 20.322 | U7: =S7-T7 -> 1.701 | W7: 20.969 | Y7: =W7+X7+AA6 -> 27.067 | Z7: 12.891 | AA7: =Y7-Z7 -> 14.176 | AC7: 35.648 | AE7: =AC7+AD7+AG6 -> 128.493 | AF7: 91.02 | AG7: =AE7-AF7 -> 37.473 | AI7: 35.298 | AK7: =AI7+AJ7+AM6 -> 38.561 | AL7: 37.549 | AM7: =AK7-AL7 -> 1.012 | AO7: 35.648 | AQ7: =AO7+AP7+AS6 -> 37.187 | AR7: 36.643 | AS7: =AQ7-AR7 -> 0.544 | AU7: =E7+K7+Q7+W7+AC7+AI7+AO7 -> 140.669 | AV7: =F7+L7+R7+X7+AD7+AJ7+AP7 -> 0 | AW7: =AU7+AV7+AY6 -> 263.117 | AX7: =H7+N7+T7+Z7+AF7+AL7+AR7 -> 198.425 | AY7: =AW7-AX7 -> 64.692 | AZ7: =AX7/AW7 -> 0.75413219
B8: Baycic Baycic Maria | C8: 41640 | D8: 42216 | E8: 0.533 | F8: =-0.533 -> -0.533 | G8: =E8+F8 -> 0 | I8: =G8-H8 -> 0 | J8: =E8+E9+F8+F9 -> 0 | K8: 2.465 | L8: =-2.465 -> -2.465 | M8: =K8+L8 -> 0 | O8: =M8-N8 -> 0 | P8: =K8+K9+L8+L9 -> 0 | Q8: 17.058 | R8: =-17.058 -> -17.058 | S8: =Q8+R8 -> 0 | U8: =S8-T8 -> 0 | V8: =Q8+Q9+R8+R9 -> 0 | W8: 31.984 | X8: =-31.984 -> -31.984 | Y8: =W8+X8 -> 0 | AA8: =Y8-Z8 -> 0 | AB8: =W8+W9+X8+X9 -> 0 | AC8: 54.373 | AD8: =-54.373 -> -54.373 | AE8: =AC8+AD8 -> 0 | AG8: =AE8-AF8 -> 0 | AH8: =AC8+AC9+AD8+AD9 -> 0 | AI8: 53.84 | AJ8: =-53.84 -> -53.84 | AK8: =AI8+AJ8 -> 0 | AM8: =AK8-AL8 -> 0 | AN8: =AI8+AI9+AJ8+AJ9 -> 0 | AO8: 54.373 | AP8: =-54.373 -> -54.373 | AQ8: =AO8+AP8 -> 0 | AS8: =AQ8-AR8 -> 0 | AT8: =AO8+AO9+AP8+AP9 -> 0 | AU8: =E8+K8+Q8+W8+AC8+AI8+AO8 -> 214.626 | AV8: =F8+L8+R8+X8+AD8+AJ8+AP8 -> -214.626 | AW8: =AU8+AV8 -> 0 | AX8: =H8+N8+T8+Z8+AF8+AL8+AR8 -> 0 | AY8: =AW8-AX8 -> 0 | AZ8: =AX8/AW8 -> #DIV/0! | BA8: =AU8+AU9 -> 268.266 | BB8: =AV8+AV9 -> -268.266 | BC8: =BA8+BB8 -> 0 | BD8: =AX8+AX9 -> 0 | BE8: =BC8-BD8 -> 0 | BF8: =BD8/BC8 -> #DIV/0!
C9: 42278 | D9: 42369 | E9: 0.133 | F9: =-0.133 -> -0.133 | G9: =E9+F9+I8 -> 0 | I9: =G9-H9 -> 0 | K9: 0.6 | L9: =-0.6 -> -0.6 | M9: =K9+L9+O8 -> 0 | O9: =M9-N9 -> 0 | Q9: 4.265 | R9: =-4.265 -> -4.265 | S9: =Q9+R9+U8 -> 0 | U9: =S9-T9 -> 0 | W9: 7.996 | X9: =-7.996 -> -7.996 | Y9: =W9+X9+AA8 -> 0 | AA9: =Y9-Z9 -> 0 | AC9: 13.593 | AD9: =-13.593 -> -13.593 | AE9: =AC9+AD9+AG8 -> 0 | AG9: =AE9-AF9 -> 0 | AI9: 13.46 | AJ9: =-13.46 -> -13.46 | AK9: =AI9+AJ9+AM8 -> 0 | AM9: =AK9-AL9 -> 0 | AO9: 13.593 | AP9: =-13.593 -> -13.593 | AQ9: =AO9+AP9+AS8 -> 0 | AS9: =AQ9-AR9 -> 0 | AU9: =E9+K9+Q9+W9+AC9+AI9+AO9 -> 53.64 | AV9: =F9+L9+R9+X9+AD9+AJ9+AP9 -> -53.64 | AW9: =AU9+AV9+AY8 -> 0 | AX9: =H9+N9+T9+Z9+AF9+AL9+AR9 -> 0 | AY9: =AW9-AX9 -> 0 | AZ9: =AX9/AW9 -> #DIV/0!
B10: Blumar S.A. | C10: 41640 | D10: 42216 | E10: 0.171 | G10: =E10+F10 -> 0.171 | I10: =G10-H10 -> 0.171 | J10: =E10+E11+F10+F11 -> 0.214 | K10: 0.791 | M10: =K10+L10 -> 0.791 | O10: =M10-N10 -> 0.791 | P10: =K10+K11+L10+L11 -> 0.984 | Q10: 5.476 | R10: -0.04026 | S10: =Q10+R10 -> 5.43574 | U10: =S10-T10 -> 5.43574 | V10: =Q10+Q11+R10+R11 -> 6.80474 | W10: 10.268 | X10: -0.04026 | Y10: =W10+X10 -> 10.22774 | AA10: =Y10-Z10 -> 10.22774 | AB10: =W10+W11+X10+X11 -> 12.79474 | AC10: 17.455 | AD10: -0.04026 | AE10: =AC10+AD10 -> 17.41474 | AG10: =AE10-AF10 -> 17.41474 | AH10: =AC10+AC11+AD10+AD11 -> 21.77874 | AI10: 17.284 | AJ10: =-0.04026-17.244 -> -17.28426 | AK10: =AI10+AJ10 -> -0.00026 | AM10: =AK10-AL10 -> -0.00026 | AN10: =AI10+AI11+AJ10+AJ11 -> 2.31974 | AO10: 17.455 | AP10: =-0.04026-17.415 -> -17.45526 | AQ10: =AO10+AP10 -> -0.00026 | AS10: =AQ10-AR10 -> -0.00026 | AT10: =AO10+AO11+AP10+AP11 -> 2.37274 | AU10: =E10+K10+Q10+W10+AC10+AI10+AO10 -> 68.9 | AV10: =F10+L10+R10+X10+AD10+AJ10+AP10 -> -34.8603 | AW10: =AU10+AV10 -> 34.0397 | AX10: =H10+N10+T10+Z10+AF10+AL10+AR10 -> 0 | AY10: =AW10-AX10 -> 34.0397 | AZ10: =AX10/AW10 -> 0 | BA10: =AU10+AU11 -> 86.121 | BB10: =AV10+AV11 -> -39.01334 | BC10: =BA10+BB10 -> 47.10766 | BD10: =AX10+AX11 -> 0 | BE10: =BC10-BD10 -> 47.10766 | BF10: =BD10/BC10 -> 0
C11: 42278 | D11: 42369 | E11: 0.043 | G11: =E11+F11+I10 -> 0.214 | I11: =G11-H11 -> 0.214 | K11: 0.193 | M11: =K11+L11+O10 -> 0.984 | O11: =M11-N11 -> 0.984 | Q11: 1.369 | S11: =Q11+R11+U10 -> 6.80474 | U11: =S11-T11 -> 6.80474 | W11: 2.567 | Y11: =W11+X11+AA10 -> 12.79474 | AA11: =Y11-Z11 -> 12.79474 | AC11: 4.364 | AE11: =AC11+AD11+AG10 -> 21.77874 | AG11: =AE11-AF11 -> 21.77874 | AI11: 4.321 | AJ11: =-2.001 -> -2.001 | AK11: =AI11+AJ11+AM10 -> 2.31974 | AM11: =AK11-AL11 -> 2.31974 | AO11: 4.364 | AP11: =-1.991 -> -1.991 | AQ11: =AO11+AP11+AS10 -> 2.37274 | AS11: =AQ11-AR11 -> 2.37274 | AU11: =E11+K11+Q11+W11+AC11+AI11+AO11 -> 17.221 | AV11: =F11+L11+R11+X11+AD11+AJ11+AP11-0.16104016 -> -4.1530402 | AW11: =AU11+AV11+AY10 -> 47.10766 | AX11: =H11+N11+T11+Z11+AF11+AL11+AR11 -> 0 | AY11: =AW11-AX11 -> 47.10766 | AZ11: =AX11/AW11 -> 0
B12: Bracpesca S.A | C12: 41640 | D12: 42216 | E12: 1.373 | G12: =E12+F12 -> 1.373 | I12: =G12-H12 -> 1.373 | J12: =E12+E13+F12+F13 -> 1.716 | K12: 6.349 | M12: =K12+L12 -> 6.349 | O12: =M12-N12 -> 6.349 | P12: =K12+K13+L12+L13 -> 7.893 | Q12: 43.928 | R12: =-39.334 -> -39.334 | S12: =Q12+R12 -> 4.594 | T12: 8.938 | U12: =S12-T12 -> -4.344 | V12: =Q12+Q13+R12+R13 -> 15.576 | W12: 82.364 | Y12: =W12+X12 -> 82.364 | Z12: 57.115 | AA12: =Y12-Z12 -> 25.249 | AB12: =W12+W13+X12+X13 -> 102.955 | AC12: 140.019 | AE12: =AC12+AD12 -> 140.019 | AF12: 29.985 | AG12: =AE12-AF12 -> 110.034 | AH12: =AC12+AC13+AD12+AD13 -> 175.024 | AI12: 138.646 | AK12: =AI12+AJ12 -> 138.646 | AL12: 133.969 | AM12: =AK12-AL12 -> 4.677 | AN12: =AI12+AI13+AJ12+AJ13 -> 173.308 | AO12: 140.019 | AQ12: =AO12+AP12 -> 140.019 | AR12: 70.761 | AS12: =AQ12-AR12 -> 69.258 | AT12: =AO12+AO13+AP12+AP13 -> 175.024 | AU12: =E12+K12+Q12+W12+AC12+AI12+AO12 -> 552.698 | AV12: =F12+L12+R12+X12+AD12+AJ12+AP12 -> -39.334 | AW12: =AU12+AV12 -> 513.364 | AX12: =H12+N12+T12+Z12+AF12+AL12+AR12 -> 300.768 | AY12: =AW12-AX12 -> 212.596 | AZ12: =AX12/AW12 -> 0.58587669 | BA12: =AU12+AU13 -> 690.83 | BB12: =AV12+AV13 -> -39.334 | BC12: =BA12+BB12 -> 651.496 | BD12: =AX12+AX13 -> 354.62 | BE12: =BC12-BD12 -> 296.876 | BF12: =BD12/BC12 -> 0.54431647
C13: 42278 | D13: 42369 | E13: 0.343 | G13: =E13+F13+I12 -> 1.716 | I13: =G13-H13 -> 1.716 | K13: 1.544 | M13: =K13+L13+O12 -> 7.893 | O13: =M13-N13 -> 7.893 | Q13: 10.982 | S13: =Q13+R13+U12 -> 6.638 | T13: 4.578 | U13: =S13-T13 -> 2.06 | W13: 20.591 | Y13: =W13+X13+AA12 -> 45.84 | Z13: 8.378 | AA13: =Y13-Z13 -> 37.462 | AC13: 35.005 | AE13: =AC13+AD13+AG12 -> 145.039 | AF13: 2.201 | AG13: =AE13-AF13 -> 142.838 | AI13: 34.662 | AK13: =AI13+AJ13+AM12 -> 39.339 | AL13: 33.946 | AM13: =AK13-AL13 -> 5.393 | AO13: 35.005 | AQ13: =AO13+AP13+AS12 -> 104.263 | AR13: 4.749 | AS13: =AQ13-AR13 -> 99.514 | AU13: =E13+K13+Q13+W13+AC13+AI13+AO13 -> 138.132 | AV13: =F13+L13+R13+X13+AD13+AJ13+AP13 -> 0 | AW13: =AU13+AV13+AY12 -> 350.728 | AX13: =H13+N13+T13+Z13+AF13+AL13+AR13 -> 53.852 | AY13: =AW13-AX13 -> 296.876 | AZ13: =AX13/AW13 -> 0.15354349
B14: Camanchaca Pesca Sur S.A. | C14: 41640 | D14: 42216 | E14: 0.007 | G14: =E14+F14 -> 0.007 | I14: =G14-H14 -> 0.007 | J14: =E14+E15+F14+F15 -> 0.009 | K14: 0.033 | M14: =K14+L14 -> 0.033 | O14: =M14-N14 -> 0.033 | P14: =K14+K15+L14+L15 -> 0.041 | Q14: 0.228 | S14: =Q14+R14 -> 0.228 | U14: =S14-T14 -> 0.228 | V14: =Q14+Q15+R14+R15 -> 0.285 | W14: 0.427 | X14: =-0.0040269-0.0040269 -> -0.0080538 | Y14: =W14+X14 -> 0.4189462 | AA14: =Y14-Z14 -> 0.4189462 | AB14: =W14+W15+X14+X15 -> 0.5259462 | AC14: 0.727 | AE14: =AC14+AD14 -> 0.727 | AG14: =AE14-AF14 -> 0.727 | AH14: =AC14+AC15+AD14+AD15 -> 0.909 | AI14: 0.719 | AJ14: =19.245 -> 19.245 | AK14: =AI14+AJ14 -> 19.964 | AM14: =AK14-AL14 -> 19.964 | AN14: =AI14+AI15+AJ14+AJ15 -> 20.144 | AO14: 0.727 | AP14: =19.406 -> 19.406 | AQ14: =AO14+AP14 -> 20.133 | AS14: =AQ14-AR14 -> 20.133 | AT14: =AO14+AO15+AP14+AP15 -> 20.315 | AU14: =E14+K14+Q14+W14+AC14+AI14+AO14 -> 2.868 | AV14: =F14+L14+R14+X14+AD14+AJ14+AP14 -> 38.642946 | AW14: =AU14+AV14 -> 41.510946 | AX14: =H14+N14+T14+Z14+AF14+AL14+AR14 -> 0 | AY14: =AW14-AX14 -> 41.510946 | AZ14: =AX14/AW14 -> 0 | BA14: =AU14+AU15 -> 3.586 | BB14: =AV14+AV15 -> 38.642946 | BC14: =BA14+BB14 -> 42.228946 | BD14: =AX14+AX15 -> 37.871 | BE14: =BC14-BD14 -> 4.3579462 | BF14: =BD14/BC14 -> 0.89680192
C15: 42278 | D15: 42369 | E15: 0.002 | G15: =E15+F15+I14 -> 0.009 | I15: =G15-H15 -> 0.009 | K15: 0.008 | M15: =K15+L15+O14 -> 0.041 | O15: =M15-N15 -> 0.041 | Q15: 0.057 | S15: =Q15+R15+U14 -> 0.285 | U15: =S15-T15 -> 0.285 | W15: 0.107 | Y15: =W15+X15+AA14 -> 0.5259462 | AA15: =Y15-Z15 -> 0.5259462 | AC15: 0.182 | AE15: =AC15+AD15+AG14 -> 0.909 | AG15: =AE15-AF15 -> 0.909 | AI15: 0.18 | AK15: =AI15+AJ15+AM14 -> 20.144 | AL15: 20.876 | AM15: =AK15-AL15 -> -0.732 | AO15: 0.182 | AQ15: =AO15+AP15+AS14 -> 20.315 | AR15: 16.995 | AS15: =AQ15-AR15 -> 3.32 | AU15: =E15+K15+Q15+W15+AC15+AI15+AO15 -> 0.718 | AV15: =F15+L15+R15+X15+AD15+AJ15+AP15 -> 0 | AW15: =AU15+AV15+AY14 -> 42.228946 | AX15: =H15+N15+T15+Z15+AF15+AL15+AR15 -> 37.871 | AY15: =AW15-AX15 -> 4.3579462 | AZ15: =AX15/AW15 -> 0.89680192
B16: Antonio Cruz Cordova nakouzi E.I.R.L. | C16: 41640 | D16: 42216 | E16: 0.044 | G16: =E16+F16 -> 0.044 | I16: =G16-H16 -> 0.044 | J16: =E16+E17+F16+F17 -> 0.055 | K16: 0.204 | M16: =K16+L16 -> 0.204 | O16: =M16-N16 -> 0.204 | P16: =K16+K17+L16+L17 -> 0.254 | Q16: 1.413 | S16: =Q16+R16 -> 1.413 | U16: =S16-T16 -> 1.413 | V16: =Q16+Q17+R16+R17 -> 1.766 | W16: 2.65 | Y16: =W16+X16 -> 2.65 | AA16: =Y16-Z16 -> 2.65 | AB16: =W16+W17+X16+X17 -> 22.313 | AC16: 4.505 | AE16: =AC16+AD16 -> 4.505 | AG16: =AE16-AF16 -> 4.505 | AH16: =AC16+AC17+AD16+AD17 -> 5.631 | AI16: 4.461 | AK16: =AI16+AJ16 -> 4.461 | AM16: =AK16-AL16 -> 4.461 | AN16: =AI16+AI17+AJ16+AJ17 -> 5.576 | AO16: 4.505 | AQ16: =AO16+AP16 -> 4.505 | AS16: =AQ16-AR16 -> 4.505 | AT16: =AO16+AO17+AP16+AP17 -> 5.631 | AU16: =E16+K16+Q16+W16+AC16+AI16+AO16 -> 17.782 | AV16: =F16+L16+R16+X16+AD16+AJ16+AP16 -> 0 | AW16: =AU16+AV16 -> 17.782 | AX16: =H16+N16+T16+Z16+AF16+AL16+AR16 -> 0 | AY16: =AW16-AX16 -> 17.782 | AZ16: =AX16/AW16 -> 0 | BA16: =AU16+AU17 -> 22.226 | BB16: =AV16+AV17 -> 19 | BC16: =BA16+BB16 -> 41.226 | BD16: =AX16+AX17 -> 21.254 | BE16: =BC16-BD16 -> 19.972 | BF16: =BD16/BC16 -> 0.51554844
C17: 42278 | D17: 42369 | E17: 0.011 | G17: =E17+F17+I16 -> 0.055 | I17: =G17-H17 -> 0.055 | K17: 0.05 | M17: =K17+L17+O16 -> 0.254 | O17: =M17-N17 -> 0.254 | Q17: 0.353 | S17: =Q17+R17+U16 -> 1.766 | U17: =S17-T17 -> 1.766 | W17: 0.663 | X17: =19 -> 19 | Y17: =W17+X17+AA16 -> 22.313 | Z17: 21.254 | AA17: =Y17-Z17 -> 1.059 | AC17: 1.126 | AE17: =AC17+AD17+AG16 -> 5.631 | AG17: =AE17-AF17 -> 5.631 | AI17: 1.115 | AK17: =AI17+AJ17+AM16 -> 5.576 | AM17: =AK17-AL17 -> 5.576 | AO17: 1.126 | AQ17: =AO17+AP17+AS16 -> 5.631 | AS17: =AQ17-AR17 -> 5.631 | AU17: =E17+K17+Q17+W17+AC17+AI17+AO17 -> 4.444 | AV17: =F17+L17+R17+X17+AD17+AJ17+AP17 -> 19 | AW17: =AU17+AV17+AY16 -> 41.226 | AX17: =H17+N17+T17+Z17+AF17+AL17+AR17 -> 21.254 | AY17: =AW17-AX17 -> 19.972 | AZ17: =AX17/AW17 -> 0.51554844
B18: Costa Brava Ltda. Pesq. | C18: 41640 | D18: 42216 | E18: 0.195 | F18: =-0.195 -> -0.195 | G18: =E18+F18 -> 0 | I18: =G18-H18 -> 0 | J18: =E18+E19+F18+F19 -> 0 | K18: 0.901 | L18: =-0.901 -> -0.901 | M18: =K18+L18 -> 0 | O18: =M18-N18 -> 0 | P18: =K18+K19+L18+L19 -> 0 | Q18: 6.237 | R18: =-6.237 -> -6.237 | S18: =Q18+R18 -> 0 | U18: =S18-T18 -> 0 | V18: =Q18+Q19+R18+R19 -> 0 | W18: 11.694 | X18: =-11.694 -> -11.694 | Y18: =W18+X18 -> 0 | AA18: =Y18-Z18 -> 0 | AB18: =W18+W19+X18+X19 -> 0 | AC18: 19.88 | AD18: =-19.88 -> -19.88 | AE18: =AC18+AD18 -> 0 | AG18: =AE18-AF18 -> 0 | AH18: =AC18+AC19+AD18+AD19 -> 0 | AI18: 19.685 | AJ18: =-19.685 -> -19.685 | AK18: =AI18+AJ18 -> 0 | AM18: =AK18-AL18 -> 0 | AN18: =AI18+AI19+AJ18+AJ19 -> 0 | AO18: 19.88 | AP18: =-19.88 -> -19.88 | AQ18: =AO18+AP18 -> 0 | AS18: =AQ18-AR18 -> 0 | AT18: =AO18+AO19+AP18+AP19 -> 0 | AU18: =E18+K18+Q18+W18+AC18+AI18+AO18 -> 78.472 | AV18: =F18+L18+R18+X18+AD18+AJ18+AP18 -> -78.472 | AW18: =AU18+AV18 -> 0 | AX18: =H18+N18+T18+Z18+AF18+AL18+AR18 -> 0 | AY18: =AW18-AX18 -> 0 | AZ18: =AX18/AW18 -> #DIV/0! | BA18: =AU18+AU19 -> 98.084 | BB18: =AV18+AV19 -> -98.084 | BC18: =BA18+BB18 -> 0 | BD18: =AX18+AX19 -> 0 | BE18: =BC18-BD18 -> 0 | BF18: =BD18/BC18 -> #DIV/0!
C19: 42278 | D19: 42369 | E19: 0.049 | F19: =-0.049 -> -0.049 | G19: =E19+F19+I18 -> 0 | I19: =G19-H19 -> 0 | K19: 0.219 | L19: =-0.219 -> -0.219 | M19: =K19+L19+O18 -> 0 | O19: =M19-N19 -> 0 | Q19: 1.559 | R19: =-1.559 -> -1.559 | S19: =Q19+R19+U18 -> 0 | U19: =S19-T19 -> 0 | W19: 2.924 | X19: =-2.924 -> -2.924 | Y19: =W19+X19+AA18 -> 0 | AA19: =Y19-Z19 -> 0 | AC19: 4.97 | AD19: =-4.97 -> -4.97 | AE19: =AC19+AD19+AG18 -> 0 | AG19: =AE19-AF19 -> 0 | AI19: 4.921 | AJ19: =-4.921 -> -4.921 | AK19: =AI19+AJ19+AM18 -> 0 | AM19: =AK19-AL19 -> 0 | AO19: 4.97 | AP19: =-4.97 -> -4.97 | AQ19: =AO19+AP19+AS18 -> 0 | AS19: =AQ19-AR19 -> 0 | AU19: =E19+K19+Q19+W19+AC19+AI19+AO19 -> 19.612 | AV19: =F19+L19+R19+X19+AD19+AJ19+AP19 -> -19.612 | AW19: =AU19+AV19+AY18 -> 0 | AX19: =H19+N19+T19+Z19+AF19+AL19+AR19 -> 0 | AY19: =AW19-AX19 -> 0 | AZ19: =AX19/AW19 -> #DIV/0!
B20: Grimar S.A. Pesq. | C20: 41640 | D20: 42216 | E20: 0.027 | G20: =E20+F20 -> 0.027 | I20: =G20-H20 -> 0.027 | J20: =E20+E21+F20+F21 -> 0.034 | K20: 0.124 | M20: =K20+L20 -> 0.124 | O20: =M20-N20 -> 0.124 | P20: =K20+K21+L20+L21 -> 0.154 | Q20: 0.855 | S20: =Q20+R20 -> 0.855 | U20: =S20-T20 -> 0.855 | V20: =Q20+Q21+R20+R21 -> 1.069 | W20: 1.603 | Y20: =W20+X20 -> 1.603 | AA20: =Y20-Z20 -> 1.603 | AB20: =W20+W21+X20+X21 -> 2.004 | AC20: 2.725 | AE20: =AC20+AD20 -> 2.725 | AG20: =AE20-AF20 -> 2.725 | AH20: =AC20+AC21+AD20+AD21 -> 3.406 | AI20: 2.699 | AK20: =AI20+AJ20 -> 2.699 | AM20: =AK20-AL20 -> 2.699 | AN20: =AI20+AI21+AJ20+AJ21 -> 3.374 | AO20: 2.725 | AQ20: =AO20+AP20 -> 2.725 | AS20: =AQ20-AR20 -> 2.725 | AT20: =AO20+AO21+AP20+AP21 -> 3.406 | AU20: =E20+K20+Q20+W20+AC20+AI20+AO20 -> 10.758 | AV20: =F20+L20+R20+X20+AD20+AJ20+AP20 -> 0 | AW20: =AU20+AV20 -> 10.758 | AX20: =H20+N20+T20+Z20+AF20+AL20+AR20 -> 0 | AY20: =AW20-AX20 -> 10.758 | AZ20: =AX20/AW20 -> 0 | BA20: =AU20+AU21 -> 13.447 | BB20: =AV20+AV21 -> 0 | BC20: =BA20+BB20 -> 13.447 | BD20: =AX20+AX21 -> 0 | BE20: =BC20-BD20 -> 13.447 | BF20: =BD20/BC20 -> 0
C21: 42278 | D21: 42369 | E21: 0.007 | G21: =E21+F21+I20 -> 0.034 | I21: =G21-H21 -> 0.034 | K21: 0.03 | M21: =K21+L21+O20 -> 0.154 | O21: =M21-N21 -> 0.154 | Q21: 0.214 | S21: =Q21+R21+U20 -> 1.069 | U21: =S21-T21 -> 1.069 | W21: 0.401 | Y21: =W21+X21+AA20 -> 2.004 | AA21: =Y21-Z21 -> 2.004 | AC21: 0.681 | AE21: =AC21+AD21+AG20 -> 3.406 | AG21: =AE21-AF21 -> 3.406 | AI21: 0.675 | AK21: =AI21+AJ21+AM20 -> 3.374 | AM21: =AK21-AL21 -> 3.374 | AO21: 0.681 | AQ21: =AO21+AP21+AS20 -> 3.406 | AS21: =AQ21-AR21 -> 3.406 | AU21: =E21+K21+Q21+W21+AC21+AI21+AO21 -> 2.689 | AV21: =F21+L21+R21+X21+AD21+AJ21+AP21 -> 0 | AW21: =AU21+AV21+AY20 -> 13.447 | AX21: =H21+N21+T21+Z21+AF21+AL21+AR21 -> 0 | AY21: =AW21-AX21 -> 13.447 | AZ21: =AX21/AW21 -> 0
B22: Isladamas S.A. Pesq. | C22: 41640 | D22: 42216 | E22: 1.234 | F22: =0.195+0.347 -> 0.542 | G22: =E22+F22 -> 1.776 | I22: =G22-H22 -> 1.776 | J22: 2.803 | K22: 5.706 | L22: =0.901+1.607 -> 2.508 | M22: =K22+L22 -> 8.214 | O22: =M22-N22 -> 8.214 | P22: =K22+K23+L22+L23 -> 10.212 | Q22: 39.479 | R22: =6.237+11.117 -> 17.354 | S22: =Q22+R22 -> 56.833 | T22: 15.433 | U22: =S22-T22 -> 41.4 | V22: =Q22+Q23+X22+R23 -> 86.220974 | W22: 74.023 | X22: =-0.004026+11.694+20.844 -> 32.533974 | Y22: =W22+X22 -> 106.55697 | Z22: 83.847 | AA22: =Y22-Z22 -> 22.709974 | AB22: =W22+W23+X22+X23 -> 114.19797 | AC22: 125.839 | AD22: =19.88+35.435 -> 55.315 | AE22: =AC22+AD22 -> 181.154 | AF22: 87.861 | AG22: =AE22-AF22 -> 93.293 | AH22: =AC22+AC23+AD22+AD23 -> 226.443 | AI22: 124.605 | AJ22: =19.685+35.087 -> 54.772 | AK22: =AI22+AJ22 -> 179.377 | AL22: 176.465 | AM22: =AK22-AL22 -> 2.912 | AN22: =AI22+AI23+AJ22+AJ23 -> 224.221 | AO22: 125.839 | AP22: =19.88+35.435 -> 55.315 | AQ22: =AO22+AP22 -> 181.154 | AR22: 94.739 | AS22: =AQ22-AR22 -> 86.415 | AT22: =AO22+AO23+AP22+AP23 -> 226.443 | AU22: =E22+K22+Q22+W22+AC22+AI22+AO22 -> 496.725 | AV22: =F22+L22+X22+R22+AD22+AJ22+AP22 -> 218.33997 | AW22: =AU22+AV22 -> 715.06497 | AX22: =H22+N22+T22+Z22+AF22+AL22+AR22 -> 458.345 | AY22: =AW22-AX22 -> 256.71997 | AZ22: =AX22/AW22 -> 0.64098371 | BA22: =AU22+AU23 -> 620.868 | BB22: =AV22+AV23 -> 253.90997 | BC22: =BA22+BB22 -> 874.77797 | BD22: =AX22+AX23 -> 611.282 | BE22: =BC22-BD22 -> 263.49597 | BF22: =BD22/BC22 -> 0.69878531
C23: 42278 | D23: 42369 | E23: 0.308 | F23: =0.049+0.087 -> 0.136 | G23: =E23+F23+I22 -> 2.22 | I23: =G23-H23 -> 2.22 | K23: 1.388 | L23: =0.219+0.391 -> 0.61 | M23: =K23+L23+O22 -> 10.212 | N23: 10.236 | O23: =M23-N23 -> -0.024 | Q23: 9.87 | R23: =1.559+2.779 -> 4.338 | S23: =Q23+R23+U22 -> 55.608 | T23: 11.961 | U23: =S23-T23 -> 43.647 | W23: 18.506 | X23: =2.924+5.211-19 -> -10.865 | Y23: =W23+X23+AA22 -> 30.350974 | Z23: 26.743 | AA23: =Y23-Z23 -> 3.607974 | AC23: 31.46 | AD23: =4.97+8.859 -> 13.829 | AE23: =AC23+AD23+AG22 -> 138.582 | AF23: 19.935 | AG23: =AE23-AF23 -> 118.647 | AI23: 31.151 | AJ23: =4.921+8.772 -> 13.693 | AK23: =AI23+AJ23+AM22 -> 47.756 | AL23: 43.457 | AM23: =AK23-AL23 -> 4.299 | AO23: 31.46 | AP23: =4.97+8.859 -> 13.829 | AQ23: =AO23+AP23+AS22 -> 131.704 | AR23: 40.605 | AS23: =AQ23-AR23 -> 91.099 | AU23: =E23+K23+Q23+W23+AC23+AI23+AO23 -> 124.143 | AV23: =F23+L23+R23+X23+AD23+AJ23+AP23 -> 35.57 | AW23: =AU23+AV23+AY22 -> 416.43297 | AX23: =H23+N23+T23+Z23+AF23+AL23+AR23 -> 152.937 | AY23: =AW23-AX23 -> 263.49597 | AZ23: =AX23/AW23 -> 0.36725478
B24: Landes S.A. Soc. Pesq. | C24: 41640 | D24: 42216 | E24: 0.015 | G24: =E24+F24 -> 0.015 | I24: =G24-H24 -> 0.015 | J24: =E24+E25+F24+F25 -> 0.019 | K24: 0.067 | M24: =K24+L24 -> 0.067 | O24: =M24-N24 -> 0.067 | P24: =K24+K25+L24+L25 -> 0.083 | Q24: 0.467 | S24: =Q24+R24 -> 0.467 | U24: =S24-T24 -> 0.467 | V24: =Q24+Q25+R24+R25 -> 0.584 | W24: 0.875 | Y24: =W24+X24 -> 0.875 | AA24: =Y24-Z24 -> 0.875 | AB24: =W24+W25+X24+X25 -> 1.094 | AC24: 1.488 | AE24: =AC24+AD24 -> 1.488 | AG24: =AE24-AF24 -> 1.488 | AH24: =AC24+AC25+AD24+AD25 -> 1.86 | AI24: 1.473 | AK24: =AI24+AJ24 -> 1.473 | AM24: =AK24-AL24 -> 1.473 | AN24: =AI24+AI25+AJ24+AJ25 -> 1.841 | AO24: 1.488 | AQ24: =AO24+AP24 -> 1.488 | AS24: =AQ24-AR24 -> 1.488 | AT24: =AO24+AO25+AP24+AP25 -> 1.86 | AU24: =E24+K24+Q24+W24+AC24+AI24+AO24 -> 5.873 | AV24: =F24+L24+R24+X24+AD24+AJ24+AP24 -> 0 | AW24: =AU24+AV24 -> 5.873 | AX24: =H24+N24+T24+Z24+AF24+AL24+AR24 -> 0 | AY24: =AW24-AX24 -> 5.873 | AZ24: =AX24/AW24 -> 0 | BA24: =AU24+AU25 -> 7.341 | BB24: =AV24+AV25 -> 0 | BC24: =BA24+BB24 -> 7.341 | BD24: =AX24+AX25 -> 0 | BE24: =BC24-BD24 -> 7.341 | BF24: =BD24/BC24 -> 0
C25: 42278 | D25: 42369 | E25: 0.004 | G25: =E25+F25+I24 -> 0.019 | I25: =G25-H25 -> 0.019 | K25: 0.016 | M25: =K25+L25+O24 -> 0.083 | O25: =M25-N25 -> 0.083 | Q25: 0.117 | S25: =Q25+R25+U24 -> 0.584 | U25: =S25-T25 -> 0.584 | W25: 0.219 | Y25: =W25+X25+AA24 -> 1.094 | AA25: =Y25-Z25 -> 1.094 | AC25: 0.372 | AE25: =AC25+AD25+AG24 -> 1.86 | AG25: =AE25-AF25 -> 1.86 | AI25: 0.368 | AK25: =AI25+AJ25+AM24 -> 1.841 | AM25: =AK25-AL25 -> 1.841 | AO25: 0.372 | AQ25: =AO25+AP25+AS24 -> 1.86 | AS25: =AQ25-AR25 -> 1.86 | AU25: =E25+K25+Q25+W25+AC25+AI25+AO25 -> 1.468 | AV25: =F25+L25+R25+X25+AD25+AJ25+AP25 -> 0 | AW25: =AU25+AV25+AY24 -> 7.341 | AX25: =H25+N25+T25+Z25+AF25+AL25+AR25 -> 0 | AY25: =AW25-AX25 -> 7.341 | AZ25: =AX25/AW25 -> 0
B26: Morozin Baycic Maria Ana | C26: 41640 | D26: 42216 | E26: 0.306 | F26: =-0.306 -> -0.306 | G26: =E26+F26 -> 0 | I26: =G26-H26 -> 0 | J26: =E26+E27+F26+F27 -> 0 | K26: 1.414 | L26: =-1.414 -> -1.414 | M26: =K26+L26 -> 0 | O26: =M26-N26 -> 0 | P26: =K26+K27+L26+L27 -> 0 | Q26: 9.784 | R26: =-9.784 -> -9.784 | S26: =Q26+R26 -> 0 | U26: =S26-T26 -> 0 | V26: =Q26+Q27+R26+R27 -> 0 | W26: 18.345 | X26: =-18.345 -> -18.345 | Y26: =W26+X26 -> 0 | AA26: =Y26-Z26 -> 0 | AB26: =W26+W27+X26+X27 -> 0 | AC26: 31.186 | AD26: =-31.186 -> -31.186 | AE26: =AC26+AD26 -> 0 | AG26: =AE26-AF26 -> 0 | AH26: =AC26+AC27+AD26+AD27 -> 0 | AI26: 30.881 | AJ26: =-30.881 -> -30.881 | AK26: =AI26+AJ26 -> 0 | AM26: =AK26-AL26 -> 0 | AN26: =AI26+AI27+AJ26+AJ27 -> 0 | AO26: 31.186 | AP26: =-31.186 -> -31.186 | AQ26: =AO26+AP26 -> 0 | AS26: =AQ26-AR26 -> 0 | AT26: =AO26+AO27+AP26+AP27 -> 0 | AU26: =E26+K26+Q26+W26+AC26+AI26+AO26 -> 123.102 | AV26: =F26+L26+R26+X26+AD26+AJ26+AP26 -> -123.102 | AW26: =AU26+AV26 -> 0 | AX26: =H26+N26+T26+Z26+AF26+AL26+AR26 -> 0 | AY26: =AW26-AX26 -> 0 | AZ26: =AX26/AW26 -> #DIV/0! | BA26: =AU26+AU27 -> 153.868 | BB26: =AV26+AV27 -> -153.868 | BC26: =BA26+BB26 -> 0 | BD26: =AX26+AX27 -> 0 | BE26: =BC26-BD26 -> 0 | BF26: =BD26/BC26 -> #DIV/0!
C27: 42278 | D27: 42369 | E27: 0.076 | F27: =-0.076 -> -0.076 | G27: =E27+F27+I26 -> 0 | I27: =G27-H27 -> 0 | K27: 0.344 | L27: =-0.344 -> -0.344 | M27: =K27+L27+O26 -> 0 | O27: =M27-N27 -> 0 | Q27: 2.446 | R27: =-2.446 -> -2.446 | S27: =Q27+R27+U26 -> 0 | U27: =S27-T27 -> 0 | W27: 4.586 | X27: =-4.586 -> -4.586 | Y27: =W27+X27+AA26 -> 0 | AA27: =Y27-Z27 -> 0 | AC27: 7.797 | AD27: =-7.797 -> -7.797 | AE27: =AC27+AD27+AG26 -> 0 | AG27: =AE27-AF27 -> 0 | AI27: 7.72 | AJ27: =-7.72 -> -7.72 | AK27: =AI27+AJ27+AM26 -> 0 | AM27: =AK27-AL27 -> 0 | AO27: 7.797 | AP27: =-7.797 -> -7.797 | AQ27: =AO27+AP27+AS26 -> 0 | AS27: =AQ27-AR27 -> 0 | AU27: =E27+K27+Q27+W27+AC27+AI27+AO27 -> 30.766 | AV27: =F27+L27+R27+X27+AD27+AJ27+AP27 -> -30.766 | AW27: =AU27+AV27+AY26 -> 0 | AX27: =H27+N27+T27+Z27+AF27+AL27+AR27 -> 0 | AY27: =AW27-AX27 -> 0 | AZ27: =AX27/AW27 -> #DIV/0!
B28: Morozin Yurecic Mario | C28: 41640 | D28: 42216 | E28: 0.69 | F28: =-0.69 -> -0.69 | G28: =E28+F28 -> 0 | I28: =G28-H28 -> 0 | J28: =E28+E29+F28+F29 -> 0 | K28: 3.189 | L28: =-3.189 -> -3.189 | M28: =K28+L28 -> 0 | O28: =M28-N28 -> 0 | P28: =K28+K29+L28+L29 -> 0 | Q28: 22.066 | R28: =-22.066 -> -22.066 | S28: =Q28+R28 -> 0 | U28: =S28-T28 -> 0 | V28: =Q28+Q29+R28+R29 -> 0 | W28: 41.374 | X28: =-41.374 -> -41.374 | Y28: =W28+X28 -> 0 | AA28: =Y28-Z28 -> 0 | AB28: =W28+W29+X28+X29 -> 0 | AC28: 70.336 | AD28: =-70.336 -> -70.336 | AE28: =AC28+AD28 -> 0 | AG28: =AE28-AF28 -> 0 | AH28: =AC28+AC29+AD28+AD29 -> 0 | AI28: 69.647 | AJ28: =-69.647 -> -69.647 | AK28: =AI28+AJ28 -> 0 | AM28: =AK28-AL28 -> 0 | AN28: =AI28+AI29+AJ28+AJ29 -> 0 | AO28: 70.336 | AP28: =-70.336 -> -70.336 | AQ28: =AO28+AP28 -> 0 | AS28: =AQ28-AR28 -> 0 | AT28: =AO28+AO29+AP28+AP29 -> 0 | AU28: =E28+K28+Q28+W28+AC28+AI28+AO28 -> 277.638 | AV28: =F28+L28+R28+X28+AD28+AJ28+AP28 -> -277.638 | AW28: =AU28+AV28 -> 0 | AX28: =H28+N28+T28+Z28+AF28+AL28+AR28 -> 0 | AY28: =AW28-AX28 -> 0 | AZ28: =AX28/AW28 -> #DIV/0! | BA28: =AU28+AU29 -> 347.027 | BB28: =AV28+AV29 -> -347.027 | BC28: =BA28+BB28 -> 0 | BD28: =AX28+AX29 -> 0 | BE28: =BC28-BD28 -> 0 | BF28: =BD28/BC28 -> #DIV/0!
C29: 42278 | D29: 42369 | E29: 0.172 | F29: =-0.172 -> -0.172 | G29: =E29+F29+I28 -> 0 | I29: =G29-H29 -> 0 | K29: 0.776 | L29: =-0.776 -> -0.776 | M29: =K29+L29+O28 -> 0 | O29: =M29-N29 -> 0 | Q29: 5.517 | R29: =-5.517 -> -5.517 | S29: =Q29+R29+U28 -> 0 | U29: =S29-T29 -> 0 | W29: 10.344 | X29: =-10.344 -> -10.344 | Y29: =W29+X29+AA28 -> 0 | AA29: =Y29-Z29 -> 0 | AC29: 17.584 | AD29: =-17.584 -> -17.584 | AE29: =AC29+AD29+AG28 -> 0 | AG29: =AE29-AF29 -> 0 | AI29: 17.412 | AJ29: =-17.412 -> -17.412 | AK29: =AI29+AJ29+AM28 -> 0 | AM29: =AK29-AL29 -> 0 | AO29: 17.584 | AP29: =-17.584 -> -17.584 | AQ29: =AO29+AP29+AS28 -> 0 | AS29: =AQ29-AR29 -> 0 | AU29: =E29+K29+Q29+W29+AC29+AI29+AO29 -> 69.389 | AV29: =F29+L29+R29+X29+AD29+AJ29+AP29 -> -69.389 | AW29: =AU29+AV29+AY28 -> 0 | AX29: =H29+N29+T29+Z29+AF29+AL29+AR29 -> 0 | AY29: =AW29-AX29 -> 0 | AZ29: =AX29/AW29 -> #DIV/0!
B30: Quintero Ltda. Soc. Pesq. | C30: 41640 | D30: 42216 | E30: 0.165 | F30: =-0.165 -> -0.165 | G30: =E30+F30 -> 0 | I30: =G30-H30 -> 0 | J30: =E30+E31+F30+F31 -> 0 | K30: 0.764 | L30: =-0.764 -> -0.764 | M30: =K30+L30 -> 0 | O30: =M30-N30 -> 0 | P30: =K30+K31+L30+L31 -> 0 | Q30: 5.283 | R30: =-5.283 -> -5.283 | S30: =Q30+R30 -> 0 | U30: =S30-T30 -> 0 | V30: =Q30+Q31+R30+R31 -> 99.997 | W30: 9.905 | X30: =-9.905 -> -9.905 | Y30: =W30+X30 -> 0 | AA30: =Y30-Z30 -> 0 | AB30: =W30+W31+X30+X31 -> 0 | AC30: 16.839 | AD30: =-16.839 -> -16.839 | AE30: =AC30+AD30 -> 0 | AG30: =AE30-AF30 -> 0 | AH30: =AC30+AC31+AD30+AD31 -> 0 | AI30: 16.674 | AJ30: =-16.674 -> -16.674 | AK30: =AI30+AJ30 -> 0 | AM30: =AK30-AL30 -> 0 | AN30: =AI30+AI31+AJ30+AJ31 -> 0 | AO30: 16.839 | AP30: =-16.839 -> -16.839 | AQ30: =AO30+AP30 -> 0 | AS30: =AQ30-AR30 -> 0 | AT30: =AO30+AO31+AP30+AP31 -> 0 | AU30: =E30+K30+Q30+W30+AC30+AI30+AO30 -> 66.469 | AV30: =F30+L30+R30+X30+AD30+AJ30+AP30 -> -66.469 | AW30: =AU30+AV30 -> 0 | AX30: =H30+N30+T30+Z30+AF30+AL30+AR30 -> 0 | AY30: =AW30-AX30 -> 0 | AZ30: =AX30/AW30 -> #DIV/0! | BA30: =AU30+AU31 -> 83.081 | BB30: =AV30+AV31 -> 16.916 | BC30: =BA30+BB30 -> 99.997 | BD30: =AX30+AX31 -> 76.412 | BE30: =BC30-BD30 -> 23.585 | BF30: =BD30/BC30 -> 0.76414292
C31: 42278 | D31: 42369 | E31: 0.041 | F31: =-0.041 -> -0.041 | G31: =E31+F31+I30 -> 0 | I31: =G31-H31 -> 0 | K31: 0.186 | L31: =-0.186 -> -0.186 | M31: =K31+L31+O30 -> 0 | O31: =M31-N31 -> 0 | Q31: 1.321 | R31: =-1.321+99.997 -> 98.676 | S31: =Q31+R31+U30 -> 99.997 | T31: 76.412 | U31: =S31-T31 -> 23.585 | W31: 2.476 | X31: =-2.476 -> -2.476 | Y31: =W31+X31+AA30 -> 0 | AA31: =Y31-Z31 -> 0 | AC31: 4.21 | AD31: =-4.21 -> -4.21 | AE31: =AC31+AD31+AG30 -> 0 | AG31: =AE31-AF31 -> 0 | AI31: 4.168 | AJ31: =-4.168 -> -4.168 | AK31: =AI31+AJ31+AM30 -> 0 | AM31: =AK31-AL31 -> 0 | AO31: 4.21 | AP31: =-4.21 -> -4.21 | AQ31: =AO31+AP31+AS30 -> 0 | AS31: =AQ31-AR31 -> 0 | AU31: =E31+K31+Q31+W31+AC31+AI31+AO31 -> 16.612 | AV31: =F31+L31+R31+X31+AD31+AJ31+AP31 -> 83.385 | AW31: =AU31+AV31+AY30 -> 99.997 | AX31: =H31+N31+T31+Z31+AF31+AL31+AR31 -> 76.412 | AY31: =AW31-AX31 -> 23.585 | AZ31: =AX31/AW31 -> 0.76414292
B32: Quintero S.A., Pesquera | C32: 41640 | D32: 42216 | E32: 1.203 | F32: =0.69+0.165+0.306+0.533 -> 1.694 | G32: =E32+F32 -> 2.897 | I32: =G32-H32 -> 2.897 | J32: =E32+E33+F32+F33 -> 3.62 | K32: 5.563 | L32: =3.189+0.764+1.414+2.465 -> 7.832 | M32: =K32+L32 -> 13.395 | O32: =M32-N32 -> 13.395 | P32: =K32+K33+L32+L33 -> 16.654 | Q32: 38.491 | R32: =22.066+5.283+9.784+17.058+9.384 -> 63.575 | S32: =Q32+R32 -> 102.066 | T32: 99.271 | U32: =S32-T32 -> 2.795 | V32: =Q32+Q33+R32+R33 -> 127.37 | W32: 72.17 | X32: =41.374+9.905+18.345+31.984+17.595-0.1 -> 119.103 | Y32: =W32+X32 -> 191.273 | Z32: 186.488 | AA32: =Y32-Z32 -> 4.785 | AB32: =W32+W33+X32+X33 -> 238.948 | AC32: 122.69 | AD32: =70.336+16.839+31.186+54.373+29.912 -> 202.646 | AE32: =AC32+AD32 -> 325.336 | AF32: 323.773 | AG32: =AE32-AF32 -> 1.563 | AH32: =AC32+AC33+AD32+AD33 -> 406.487 | AI32: 121.487 | AJ32: =69.647+16.674+30.881+53.84+29.619 -> 200.661 | AK32: =AI32+AJ32 -> 322.148 | AL32: 318.548 | AM32: =AK32-AL32 -> 3.6 | AN32: =AI32+AI33+AJ32+AJ33 -> 402.465 | AO32: 122.69 | AP32: =70.336+16.839+31.186+54.373+29.912 -> 202.646 | AQ32: =AO32+AP32 -> 325.336 | AR32: 26.852 | AS32: =AQ32-AR32 -> 298.484 | AT32: =AO32+AO33+AP32+AP33 -> 406.487 | AU32: =E32+K32+Q32+W32+AC32+AI32+AO32 -> 484.294 | AV32: =F32+L32+R32+X32+AD32+AJ32+AP32 -> 798.157 | AW32: =AU32+AV32 -> 1282.451 | AX32: =H32+N32+T32+Z32+AF32+AL32+AR32 -> 954.932 | AY32: =AW32-AX32 -> 327.519 | AZ32: =AX32/AW32 -> 0.7446148 | BA32: =AU32+AU33 -> 605.33 | BB32: =AV32+AV33 -> 996.701 | BC32: =BA32+BB32 -> 1602.031 | BD32: =AX32+AX33 -> 1457.679 | BE32: =BC32-BD32 -> 144.352 | BF32: =BD32/BC32 -> 0.90989438
C33: 42278 | D33: 42369 | E33: 0.301 | F33: =0.172+0.041+0.076+0.133 -> 0.422 | G33: =E33+F33+I32 -> 3.62 | I33: =G33-H33 -> 3.62 | K33: 1.353 | L33: =0.776+0.186+0.344+0.6 -> 1.906 | M33: =K33+L33+O32 -> 16.654 | O33: =M33-N33 -> 16.654 | Q33: 9.623 | R33: =5.517+1.321+2.446+4.265+2.132 -> 15.681 | S33: =Q33+R33+U32 -> 28.099 | T33: 18.91 | U33: =S33-T33 -> 9.189 | W33: 18.043 | X33: =10.344+2.476+4.586+7.996+4.23 -> 29.632 | Y33: =W33+X33+AA32 -> 52.46 | Z33: 47.939 | AA33: =Y33-Z33 -> 4.521 | AC33: 30.672 | AD33: =17.584+4.21+7.797+13.593+7.295 -> 50.479 | AE33: =AC33+AD33+AG32 -> 82.714 | AF33: 79.507 | AG33: =AE33-AF33 -> 3.207 | AI33: 30.372 | AJ33: =17.412+4.168+7.72+13.46+7.185 -> 49.945 | AK33: =AI33+AJ33+AM32 -> 83.917 | AL33: 82.833 | AM33: =AK33-AL33 -> 1.084 | AO33: 30.672 | AP33: =17.584+4.21+7.797+13.593+7.295 -> 50.479 | AQ33: =AO33+AP33+AS32 -> 379.635 | AR33: 273.558 | AS33: =AQ33-AR33 -> 106.077 | AU33: =E33+K33+Q33+W33+AC33+AI33+AO33 -> 121.036 | AV33: =F33+L33+R33+X33+AD33+AJ33+AP33 -> 198.544 | AW33: =AU33+AV33+AY32 -> 647.099 | AX33: =H33+N33+T33+Z33+AF33+AL33+AR33 -> 502.747 | AY33: =AW33-AX33 -> 144.352 | AZ33: =AX33/AW33 -> 0.7769244
B34: Rubio y Mauad Ltda. | C34: 41640 | D34: 42216 | E34: 0.293 | G34: =E34+F34 -> 0.293 | I34: =G34-H34 -> 0.293 | J34: =E34+E35+F34+F35 -> 0.366 | K34: 1.356 | M34: =K34+L34 -> 1.356 | O34: =M34-N34 -> 1.356 | P34: =K34+K35+L34+L35 -> 1.686 | Q34: 9.384 | R34: =-9.384 -> -9.384 | S34: =Q34+R34 -> 0 | U34: =S34-T34 -> 0 | V34: =Q34+Q35+R34+R35 -> 35.213627 | W34: 17.595 | X34: =-17.595 -> -17.595 | Y34: =W34+X34 -> 0 | AA34: =Y34-Z34 -> 0 | AB34: =W34+W35+X34+X35 -> 0.169054 | AC34: 29.912 | AD34: =-29.912 -> -29.912 | AE34: =AC34+AD34 -> 0 | AG34: =AE34-AF34 -> 0 | AH34: =AC34+AC35+AD34+AD35 -> 0.1829158 | AI34: 29.619 | AJ34: =-29.619 -> -29.619 | AK34: =AI34+AJ34 -> 0 | AM34: =AK34-AL34 -> 0 | AN34: =AI34+AI35+AJ34+AJ35 -> 0.2199184 | AO34: 29.912 | AP34: =-29.912 -> -29.912 | AQ34: =AO34+AP34 -> 0 | AS34: =AQ34-AR34 -> 0 | AT34: =AO34+AO35+AP34+AP35 -> 0.1829158 | AU34: =E34+K34+Q34+W34+AC34+AI34+AO34 -> 118.071 | AV34: =F34+L34+R34+X34+AD34+AJ34+AP34 -> -116.422 | AW34: =AU34+AV34 -> 1.649 | AX34: =H34+N34+T34+Z34+AF34+AL34+AR34 -> 0 | AY34: =AW34-AX34 -> 1.649 | AZ34: =AX34/AW34 -> 0 | BA34: =AU34+AU35 -> 147.58 | BB34: =AV34+AV35 -> -109.55957 | BC34: =BA34+BB34 -> 38.020431 | BD34: =AX34+AX35 -> 0.25 | BE34: =BC34-BD34 -> 37.770431 | BF34: =BD34/BC34 -> 0.006575412
C35: 42278 | D35: 42369 | E35: 0.073 | G35: =E35+F35+I34 -> 0.366 | I35: =G35-H35 -> 0.366 | K35: 0.33 | M35: =K35+L35+O34 -> 1.686 | O35: =M35-N35 -> 1.686 | Q35: 2.346 | R35: =-2.132373+35 -> 32.867627 | S35: =Q35+R35+U34 -> 35.213627 | T35: 0.25 | U35: =S35-T35 -> 34.963627 | W35: 4.399 | X35: =-4.229946 -> -4.229946 | Y35: =W35+X35+AA34 -> 0.169054 | AA35: =Y35-Z35 -> 0.169054 | AC35: 7.478 | AD35: =-7.2950842 -> -7.2950842 | AE35: =AC35+AD35+AG34 -> 0.1829158 | AG35: =AE35-AF35 -> 0.1829158 | AI35: 7.405 | AJ35: =-7.1850816 -> -7.1850816 | AK35: =AI35+AJ35+AM34 -> 0.2199184 | AM35: =AK35-AL35 -> 0.2199184 | AO35: 7.478 | AP35: =-7.2950842 -> -7.2950842 | AQ35: =AO35+AP35+AS34 -> 0.1829158 | AS35: =AQ35-AR35 -> 0.1829158 | AU35: =E35+K35+Q35+W35+AC35+AI35+AO35 -> 29.509 | AV35: =F35+L35+R35+X35+AD35+AJ35+AP35 -> 6.862431 | AW35: =AU35+AV35+AY34 -> 38.020431 | AX35: =H35+N35+T35+Z35+AF35+AL35+AR35 -> 0.25 | AY35: =AW35-AX35 -> 37.770431 | AZ35: =AX35/AW35 -> 0.006575412
B36: Sunrise S.A. Pesq. | C36: 41640 | D36: 42216 | E36: 0.347 | F36: =-0.347 -> -0.347 | G36: =E36+F36 -> 0 | I36: =G36-H36 -> 0 | J36: =E36+E37+F36+F37 -> 0 | K36: 1.607 | L36: =-1.607 -> -1.607 | M36: =K36+L36 -> 0 | O36: =M36-N36 -> 0 | P36: =K36+K37+L36+L37 -> 0 | Q36: 11.117 | R36: =-11.117 -> -11.117 | S36: =Q36+R36 -> 0 | U36: =S36-T36 -> 0 | V36: =Q36+Q37+R36+R37 -> 0 | W36: 20.844 | X36: =-20.844 -> -20.844 | Y36: =W36+X36 -> 0 | AA36: =Y36-Z36 -> 0 | AB36: =W36+W37+X36+X37 -> 0 | AC36: 35.435 | AD36: =-35.435 -> -35.435 | AE36: =AC36+AD36 -> 0 | AG36: =AE36-AF36 -> 0 | AH36: =AC36+AC37+AD36+AD37 -> 0 | AI36: 35.087 | AJ36: =-35.087 -> -35.087 | AK36: =AI36+AJ36 -> 0 | AM36: =AK36-AL36 -> 0 | AN36: =AI36+AI37+AJ36+AJ37 -> 0 | AO36: 35.435 | AP36: =-35.435 -> -35.435 | AQ36: =AO36+AP36 -> 0 | AS36: =AQ36-AR36 -> 0 | AT36: =AO36+AO37+AP36+AP37 -> 0 | AU36: =E36+K36+Q36+W36+AC36+AI36+AO36 -> 139.872 | AV36: =F36+L36+R36+X36+AD36+AJ36+AP36 -> -139.872 | AW36: =AU36+AV36 -> 0 | AX36: =H36+N36+T36+Z36+AF36+AL36+AR36 -> 0 | AY36: =AW36-AX36 -> 0 | AZ36: =AX36/AW36 -> #DIV/0! | BA36: =AU36+AU37 -> 174.83 | BB36: =AV36+AV37 -> -174.83 | BC36: =BA36+BB36 -> 0 | BD36: =AX36+AX37 -> 0 | BE36: =BC36-BD36 -> 0 | BF36: =BD36/BC36 -> #DIV/0!
C37: 42278 | D37: 42369 | E37: 0.087 | F37: =-0.087 -> -0.087 | G37: =E37+F37+I36 -> 0 | I37: =G37-H37 -> 0 | K37: 0.391 | L37: =-0.391 -> -0.391 | M37: =K37+L37+O36 -> 0 | O37: =M37-N37 -> 0 | Q37: 2.779 | R37: =-2.779 -> -2.779 | S37: =Q37+R37+U36 -> 0 | U37: =S37-T37 -> 0 | W37: 5.211 | X37: =-5.211 -> -5.211 | Y37: =W37+X37+AA36 -> 0 | AA37: =Y37-Z37 -> 0 | AC37: 8.859 | AD37: =-8.859 -> -8.859 | AE37: =AC37+AD37+AG36 -> 0 | AG37: =AE37-AF37 -> 0 | AI37: 8.772 | AJ37: =-8.772 -> -8.772 | AK37: =AI37+AJ37+AM36 -> 0 | AM37: =AK37-AL37 -> 0 | AO37: 8.859 | AP37: =-8.859 -> -8.859 | AQ37: =AO37+AP37+AS36 -> 0 | AS37: =AQ37-AR37 -> 0 | AU37: =E37+K37+Q37+W37+AC37+AI37+AO37 -> 34.958 | AV37: =F37+L37+R37+X37+AD37+AJ37+AP37 -> -34.958 | AW37: =AU37+AV37+AY36 -> 0 | AX37: =H37+N37+T37+Z37+AF37+AL37+AR37 -> 0 | AY37: =AW37-AX37 -> 0 | AZ37: =AX37/AW37 -> #DIV/0!
B38: Congelados del Pacífico S.A. | C38: 41640 | D38: 42216 | E38: 0 | G38: =E38+F38 -> 0 | I38: =G38-H38 -> 0 | J38: =E38+E39+F38+F39 -> 0 | K38: 0 | M38: =K38+L38 -> 0 | O38: =M38-N38 -> 0 | P38: =K38+K39+L38+L39 -> 0 | Q38: 0 | R38: 0.04026 | S38: =Q38+R38 -> 0.04026 | U38: =S38-T38 -> 0.04026 | V38: =Q38+Q39+R38+R39 -> 0.04026 | W38: 0 | X38: 0.04026 | Y38: =W38+X38 -> 0.04026 | AA38: =Y38-Z38 -> 0.04026 | AB38: =W38+W39+X38+X39 -> 0.04026 | AC38: 0 | AD38: 0.04026 | AE38: =AC38+AD38 -> 0.04026 | AG38: =AE38-AF38 -> 0.04026 | AH38: =AC38+AC39+AD38+AD39 -> 0.04026 | AI38: 0 | AJ38: 0.04026 | AK38: =AI38+AJ38 -> 0.04026 | AM38: =AK38-AL38 -> 0.04026 | AN38: =AI38+AI39+AJ38+AJ39 -> 0.04026 | AO38: 0 | AP38: 0.04026 | AQ38: =AO38+AP38 -> 0.04026 | AS38: =AQ38-AR38 -> 0.04026 | AT38: =AO38+AO39+AP38+AP39 -> 0.04026 | AU38: =E38+K38+Q38+W38+AC38+AI38+AO38 -> 0 | AV38: =F38+L38+R38+X38+AD38+AJ38+AP38 -> 0.2013 | AW38: =AU38+AV38 -> 0.2013 | AX38: =H38+N38+T38+Z38+AF38+AL38+AR38 -> 0 | AY38: =AW38-AX38 -> 0.2013 | AZ38: =AX38/AW38 -> 0 | BA38: =AU38+AU39 -> 0 | BB38: =AV38+AV39 -> 0.2013 | BC38: =BA38+BB38 -> 0.2013 | BD38: =AX38+AX39 -> 0 | BE38: =BC38-BD38 -> 0.2013 | BF38: =BD38/BC38 -> 0
C39: 42278 | D39: 42369 | E39: 0 | G39: =E39+F39+I38 -> 0 | I39: =G39-H39 -> 0 | K39: 0 | M39: =K39+L39+O38 -> 0 | O39: =M39-N39 -> 0 | Q39: 0 | S39: =Q39+R39+U38 -> 0.04026 | U39: =S39-T39 -> 0.04026 | W39: 0 | Y39: =W39+X39+AA38 -> 0.04026 | AA39: =Y39-Z39 -> 0.04026 | AC39: 0 | AE39: =AC39+AD39+AG38 -> 0.04026 | AG39: =AE39-AF39 -> 0.04026 | AI39: 0 | AK39: =AI39+AJ39+AM38 -> 0.04026 | AM39: =AK39-AL39 -> 0.04026 | AO39: 0 | AQ39: =AO39+AP39+AS38 -> 0.04026 | AS39: =AQ39-AR39 -> 0.04026 | AU39: =E39+K39+Q39+W39+AC39+AI39+AO39 -> 0 | AV39: =F39+L39+R39+X39+AD39+AJ39+AP39 -> 0 | AW39: =AU39+AV39+AY38 -> 0.2013 | AX39: =H39+N39+T39+Z39+AF39+AL39+AR39 -> 0 | AY39: =AW39-AX39 -> 0.2013 | AZ39: =AX39/AW39 -> 0
B40: Enfemar Pesq. S.A. | C40: 41640 | D40: 42216 | E40: 0 | G40: =E40+F40 -> 0 | I40: =G40-H40 -> 0 | K40: 0 | M40: =K40+L40 -> 0 | O40: =M40-N40 -> 0 | P40: =K40+K41+L40+L41 -> 0 | Q40: 0 | S40: =Q40+R40 -> 0 | U40: =S40-T40 -> 0 | V40: =Q40+Q41+R40+R41 -> 0 | W40: 0 | X40: =0.1 -> 0.1 | Y40: =W40+X40 -> 0.1 | AA40: =Y40-Z40 -> 0.1 | AB40: =W40+W41+X40+X41 -> 0.1 | AC40: 0 | AE40: =AC40+AD40 -> 0 | AG40: =AE40-AF40 -> 0 | AH40: =AC40+AC41+AD40+AD41 -> 0 | AI40: 0 | AK40: =AI40+AJ40 -> 0 | AM40: =AK40-AL40 -> 0 | AN40: =AI40+AI41+AJ40+AJ41 -> 0 | AO40: 0 | AQ40: =AO40+AP40 -> 0 | AS40: =AQ40-AR40 -> 0 | AT40: =AO40+AO41+AP40+AP41 -> 0 | AU40: =E40+K40+Q40+W40+AC40+AI40+AO40 -> 0 | AV40: =F40+L40+R40+X40+AD40+AJ40+AP40 -> 0.1 | AW40: =AU40+AV40 -> 0.1 | AX40: =H40+N40+T40+Z40+AF40+AL40+AR40 -> 0 | AY40: =AW40-AX40 -> 0.1 | AZ40: =AX40/AW40 -> 0 | BA40: =AU40+AU41 -> 0 | BB40: =AV40+AV41 -> 0.1 | BC40: =BA40+BB40 -> 0.1 | BD40: =AX40+AX41 -> 0 | BE40: =BC40-BD40 -> 0.1 | BF40: =BD40/BC40 -> 0
C41: 42278 | D41: 42369 | E41: 0 | G41: =E41+F41+I40 -> 0 | I41: =G41-H41 -> 0 | K41: 0 | M41: =K41+L41+O40 -> 0 | O41: =M41-N41 -> 0 | Q41: 0 | S41: =Q41+R41+U40 -> 0 | U41: =S41-T41 -> 0 | W41: 0 | Y41: =W41+X41+AA40 -> 0.1 | AA41: =Y41-Z41 -> 0.1 | AC41: 0 | AE41: =AC41+AD41+AG40 -> 0 | AG41: =AE41-AF41 -> 0 | AI41: 0 | AK41: =AI41+AJ41+AM40 -> 0 | AM41: =AK41-AL41 -> 0 | AO41: 0 | AQ41: =AO41+AP41+AS40 -> 0 | AS41: =AQ41-AR41 -> 0 | AU41: =E41+K41+Q41+W41+AC41+AI41+AO41 -> 0 | AV41: =F41+L41+R41+X41+AD41+AJ41+AP41 -> 0 | AW41: =AU41+AV41+AY40 -> 0.1 | AX41: =H41+N41+T41+Z41+AF41+AL41+AR41 -> 0 | AY41: =AW41-AX41 -> 0.1 | AZ41: =AX41/AW41 -> 0
B42: Pesquera CMK | C42: 41640 | D42: 42216 | E42: 0 | G42: =E42+F42 -> 0 | I42: =G42-H42 -> 0 | K42: 0 | M42: =K42+L42 -> 0 | O42: =M42-N42 -> 0 | P42: =K42+K43+L42+L43 -> 0 | Q42: 0 | S42: =Q42+R42 -> 0 | U42: =S42-T42 -> 0 | V42: =Q42+Q43+R42+R43 -> 0 | W42: 0 | X42: =0.0040269 -> 0.0040269 | Y42: =W42+X42 -> 0.0040269 | Z42: 0 | AA42: =Y42-Z42 -> 0.0040269 | AB42: =W42+W43+X42+X43 -> 0.0040269 | AC42: 0 | AE42: =AC42+AD42 -> 0 | AG42: =AE42-AF42 -> 0 | AH42: =AC42+AC43+AD42+AD43 -> 0 | AI42: 0 | AK42: =AI42+AJ42 -> 0 | AM42: =AK42-AL42 -> 0 | AN42: =AI42+AI43+AJ42+AJ43 -> 0 | AO42: 0 | AQ42: =AO42+AP42 -> 0 | AS42: =AQ42-AR42 -> 0 | AT42: =AO42+AO43+AP42+AP43 -> 0 | AU42: =E42+K42+Q42+W42+AC42+AI42+AO42 -> 0 | AV42: =F42+L42+R42+X42+AD42+AJ42+AP42 -> 0.0040269 | AW42: =AU42+AV42 -> 0.0040269 | AX42: =H42+N42+T42+Z42+AF42+AL42+AR42 -> 0 | AY42: =AW42-AX42 -> 0.0040269 | AZ42: =AX42/AW42 -> 0 | BA42: =AU42+AU43 -> 0 | BB42: =AV42+AV43 -> 0.0040269 | BC42: =BA42+BB42 -> 0.0040269 | BD42: =AX42+AX43 -> 0 | BE42: =BC42-BD42 -> 0.0040269 | BF42: =BD42/BC42 -> 0
C43: 42278 | D43: 42369 | E43: 0 | G43: =E43+F43+I42 -> 0 | I43: =G43-H43 -> 0 | K43: 0 | M43: =K43+L43+O42 -> 0 | O43: =M43-N43 -> 0 | Q43: 0 | S43: =Q43+R43+U42 -> 0 | U43: =S43-T43 -> 0 | W43: 0 | Y43: =W43+X43+AA42 -> 0.0040269 | AA43: =Y43-Z43 -> 0.0040269 | AC43: 0 | AE43: =AC43+AD43+AG42 -> 0 | AG43: =AE43-AF43 -> 0 | AI43: 0 | AK43: =AI43+AJ43+AM42 -> 0 | AM43: =AK43-AL43 -> 0 | AO43: 0 | AQ43: =AO43+AP43+AS42 -> 0 | AS43: =AQ43-AR43 -> 0 | AU43: =E43+K43+Q43+W43+AC43+AI43+AO43 -> 0 | AV43: =F43+L43+R43+X43+AD43+AJ43+AP43 -> 0 | AW43: =AU43+AV43+AY42 -> 0.0040269 | AX43: =H43+N43+T43+Z43+AF43+AL43+AR43 -> 0 | AY43: =AW43-AX43 -> 0.0040269 | AZ43: =AX43/AW43 -> 0
B44: Jorge Cofre Reyes | C44: 41640 | D44: 42216 | E44: 0 | G44: =E44+F44 -> 0 | I44: =G44-H44 -> 0 | K44: 0 | M44: =K44+L44 -> 0 | O44: =M44-N44 -> 0 | P44: =K44+K45+L44+L45 -> 0 | Q44: 0 | S44: =Q44+R44 -> 0 | U44: =S44-T44 -> 0 | V44: =Q44+Q45+R44+R45 -> 0 | W44: 0 | X44: =0.0040269 -> 0.0040269 | Y44: =W44+X44 -> 0.0040269 | Z44: 0 | AA44: =Y44-Z44 -> 0.0040269 | AB44: =W44+W45+X44+X45 -> 0.0040269 | AC44: 0 | AE44: =AC44+AD44 -> 0 | AG44: =AE44-AF44 -> 0 | AH44: =AC44+AC45+AD44+AD45 -> 0 | AI44: 0 | AK44: =AI44+AJ44 -> 0 | AM44: =AK44-AL44 -> 0 | AN44: =AI44+AI45+AJ44+AJ45 -> 0 | AO44: 0 | AQ44: =AO44+AP44 -> 0 | AS44: =AQ44-AR44 -> 0 | AT44: =AO44+AO45+AP44+AP45 -> 0 | AU44: =E44+K44+Q44+W44+AC44+AI44+AO44 -> 0 | AV44: =F44+L44+R44+X44+AD44+AJ44+AP44 -> 0.0040269 | AW44: =AU44+AV44 -> 0.0040269 | AX44: =H44+N44+T44+Z44+AF44+AL44+AR44 -> 0 | AY44: =AW44-AX44 -> 0.0040269 | AZ44: =AX44/AW44 -> 0 | BA44: =AU44+AU45 -> 0 | BB44: =AV44+AV45 -> 0.0040269 | BC44: =BA44+BB44 -> 0.0040269 | BD44: =AX44+AX45 -> 0 | BE44: =BC44-BD44 -> 0.0040269 | BF44: =BD44/BC44 -> 0
C45: 42278 | D45: 42369 | E45: 0 | G45: =E45+F45+I44 -> 0 | I45: =G45-H45 -> 0 | K45: 0 | M45: =K45+L45+O44 -> 0 | O45: =M45-N45 -> 0 | Q45: 0 | S45: =Q45+R45+U44 -> 0 | U45: =S45-T45 -> 0 | W45: 0 | Y45: =W45+X45+AA44 -> 0.0040269 | AA45: =Y45-Z45 -> 0.0040269 | AC45: 0 | AE45: =AC45+AD45+AG44 -> 0 | AG45: =AE45-AF45 -> 0 | AI45: 0 | AK45: =AI45+AJ45+AM44 -> 0 | AM45: =AK45-AL45 -> 0 | AO45: 0 | AQ45: =AO45+AP45+AS44 -> 0 | AS45: =AQ45-AR45 -> 0 | AU45: =E45+K45+Q45+W45+AC45+AI45+AO45 -> 0 | AV45: =F45+L45+R45+X45+AD45+AJ45+AP45 -> 0 | AW45: =AU45+AV45+AY44 -> 0.0040269 | AX45: =H45+N45+T45+Z45+AF45+AL45+AR45 -> 0 | AY45: =AW45-AX45 -> 0.0040269 | AZ45: =AX45/AW45 -> 0
B46: Antonio Da Venezia Retamales | C46: 41640 | D46: 42216 | E46: 0 | G46: =E46+F46 -> 0 | I46: =G46-H46 -> 0 | K46: 0 | M46: =K46+L46 -> 0 | O46: =M46-N46 -> 0 | P46: =K46+K47+L46+L47 -> 0 | Q46: 0 | S46: =Q46+R46 -> 0 | U46: =S46-T46 -> 0 | V46: =Q46+Q47+R46+R47 -> 0 | W46: 0 | X46: =0.0040269 -> 0.0040269 | Y46: =W46+X46 -> 0.0040269 | Z46: 0 | AA46: =Y46-Z46 -> 0.0040269 | AB46: =W46+W47+X46+X47 -> 0.0040269 | AC46: 0 | AE46: =AC46+AD46 -> 0 | AG46: =AE46-AF46 -> 0 | AH46: =AC46+AC47+AD46+AD47 -> 0 | AI46: 0 | AK46: =AI46+AJ46 -> 0 | AM46: =AK46-AL46 -> 0 | AN46: =AI46+AI47+AJ46+AJ47 -> 0 | AO46: 0 | AQ46: =AO46+AP46 -> 0 | AS46: =AQ46-AR46 -> 0 | AT46: =AO46+AO47+AP46+AP47 -> 0 | AU46: =E46+K46+Q46+W46+AC46+AI46+AO46 -> 0 | AV46: =F46+L46+R46+X46+AD46+AJ46+AP46 -> 0.0040269 | AW46: =AU46+AV46 -> 0.0040269 | AX46: =H46+N46+T46+Z46+AF46+AL46+AR46 -> 0 | AY46: =AW46-AX46 -> 0.0040269 | AZ46: =AX46/AW46 -> 0 | BA46: =AU46+AU47 -> 0 | BB46: =AV46+AV47 -> 0.0040269 | BC46: =BA46+BB46 -> 0.0040269 | BD46: =AX46+AX47 -> 0 | BE46: =BC46-BD46 -> 0.0040269 | BF46: =BD46/BC46 -> 0
C47: 42278 | D47: 42369 | E47: 0 | G47: =E47+F47+I46 -> 0 | I47: =G47-H47 -> 0 | K47: 0 | M47: =K47+L47+O46 -> 0 | O47: =M47-N47 -> 0 | Q47: 0 | S47: =Q47+R47+U46 -> 0 | U47: =S47-T47 -> 0 | W47: 0 | Y47: =W47+X47+AA46 -> 0.0040269 | AA47: =Y47-Z47 -> 0.0040269 | AC47: 0 | AE47: =AC47+AD47+AG46 -> 0 | AG47: =AE47-AF47 -> 0 | AI47: 0 | AK47: =AI47+AJ47+AM46 -> 0 | AM47: =AK47-AL47 -> 0 | AO47: 0 | AQ47: =AO47+AP47+AS46 -> 0 | AS47: =AQ47-AR47 -> 0 | AU47: =E47+K47+Q47+W47+AC47+AI47+AO47 -> 0 | AV47: =F47+L47+R47+X47+AD47+AJ47+AP47 -> 0 | AW47: =AU47+AV47+AY46 -> 0.0040269 | AX47: =H47+N47+T47+Z47+AF47+AL47+AR47 -> 0 | AY47: =AW47-AX47 -> 0.0040269 | AZ47: =AX47/AW47 -> 0
B48: Pesquera Bio Bio S.A. | C48: 41640 | D48: 42216 | E48: 0 | G48: =E48+F48 -> 0 | I48: =G48-H48 -> 0 | K48: 0 | M48: =K48+L48 -> 0 | O48: =M48-N48 -> 0 | P48: =K48+K49+L48+L49 -> 0 | Q48: 0 | S48: =Q48+R48 -> 0 | U48: =S48-T48 -> 0 | V48: =Q48+Q49+R48+R49 -> 0 | W48: 0 | X48: =0.0040269 -> 0.0040269 | Y48: =W48+X48 -> 0.0040269 | Z48: 0 | AA48: =Y48-Z48 -> 0.0040269 | AB48: =W48+W49+X48+X49 -> 0.0040269 | AC48: 0 | AE48: =AC48+AD48 -> 0 | AG48: =AE48-AF48 -> 0 | AH48: =AC48+AC49+AD48+AD49 -> 0 | AI48: 0 | AK48: =AI48+AJ48 -> 0 | AM48: =AK48-AL48 -> 0 | AN48: =AI48+AI49+AJ48+AJ49 -> 0 | AO48: 0 | AQ48: =AO48+AP48 -> 0 | AS48: =AQ48-AR48 -> 0 | AT48: =AO48+AO49+AP48+AP49 -> 0 | AU48: =E48+K48+Q48+W48+AC48+AI48+AO48 -> 0 | AV48: 0.16104016 | AW48: =AU48+AV48 -> 0.16104016 | AX48: =H48+N48+T48+Z48+AF48+AL48+AR48 -> 0 | AY48: =AW48-AX48 -> 0.16104016 | AZ48: =AX48/AW48 -> 0 | BA48: =AU48+AU49 -> 0 | BB48: =AV48+AV49 -> 0.16104016 | BC48: =BA48+BB48 -> 0.16104016 | BD48: =AX48+AX49 -> 0 | BE48: =BC48-BD48 -> 0.16104016 | BF48: =BD48/BC48 -> 0
C49: 42278 | D49: 42369 | E49: 0 | G49: =E49+F49+I48 -> 0 | I49: =G49-H49 -> 0 | K49: 0 | M49: =K49+L49+O48 -> 0 | O49: =M49-N49 -> 0 | Q49: 0 | S49: =Q49+R49+U48 -> 0 | U49: =S49-T49 -> 0 | W49: 0 | Y49: =W49+X49+AA48 -> 0.0040269 | AA49: =Y49-Z49 -> 0.0040269 | AC49: 0 | AE49: =AC49+AD49+AG48 -> 0 | AG49: =AE49-AF49 -> 0 | AI49: 0 | AK49: =AI49+AJ49+AM48 -> 0 | AM49: =AK49-AL49 -> 0 | AO49: 0 | AQ49: =AO49+AP49+AS48 -> 0 | AS49: =AQ49-AR49 -> 0 | AU49: =E49+K49+Q49+W49+AC49+AI49+AO49 -> 0 | AV49: =F49+L49+R49+X49+AD49+AJ49+AP49 -> 0 | AW49: =AU49+AV49+AY48 -> 0.16104016 | AX49: =H49+N49+T49+Z49+AF49+AL49+AR49 -> 0 | AY49: =AW49-AX49 -> 0.16104016 | AZ49: =AX49/AW49 -> 0
C52: Periodo | E52: Cuota III Región (t) | H52: Operación III región | K52: Cuota IV Región (t) | N52: Operación IV Región | Q52: Cuota y Operación Langostino amarillo III-IV | W52: Resumen Global Anual Langostino amarillo III-IV
B53: Armador | C53: Inicial | D53: Final | E53: Cuota Asignada | F53: Traspaso, Cesion, Arriendo, etc) | G53: Cuota Efectiva | H53: Desembarque (t) | I53: Saldo (t) | J53: Cuota Total | K53: Cuota Asignada | L53: Traspaso, Cesion, Arriendo, etc) | M53: Cuota Efectiva | N53: Desembarque (t) | O53: Saldo (t) | P53: Cuota Total | Q53: Cuota Asignada III-IV | R53: * Traspaso, Cesion, Arriendo, etc) | S53: Cuota Efectiva | T53: Desembarque (t) III-IV | U53: Saldo (t) | V53: % consumido | W53: Cuota Total | X53: * Traspaso, Cesion, Arriendo, etc) | Y53: Cuota Efectiva | Z53: Desembarque (t) | AA53: Saldo (t) | AB53: % consumido
A54: Langostino amarillo III-IV | B54: Antarctic Seafood S.A | C54: 42064 | D54: 42246 | E54: 136.512 | G54: =E54+F54 -> 136.512 | H54: 78.335 | I54: =G54-H54 -> 58.177 | J54: =E54+E55+F54+F55 -> 151.767 | K54: 490.114 | M54: =K54+L54 -> 490.114 | N54: 411.842 | O54: =M54-N54 -> 78.272 | P54: =K54+K55+L54+L55 -> 544.484 | Q54: =E54+K54 -> 626.626 | R54: =F54+L54 -> 0 | S54: =Q54+R54 -> 626.626 | T54: =H54+N54 -> 490.177 | U54: =S54-T54 -> 136.449 | V54: =T54/S54 -> 0.7822481 | W54: =Q54+Q55 -> 696.251 | X54: =R54+R55 -> 0 | Y54: =W54+X54 -> 696.251 | Z54: =T54+T55 -> 695.635 | AA54: =Y54-Z54 -> 0.616 | AB54: =Z54/Y54 -> 0.99911526
C55: 42278 | D55: 42368 | E55: 15.255 | G55: =E55+F55+I54 -> 73.432 | H55: 72.438 | I55: =G55-H55 -> 0.994 | K55: 54.37 | M55: =K55+L55+O54 -> 132.642 | N55: 133.02 | O55: =M55-N55 -> -0.378 | Q55: =E55+K55 -> 69.625 | R55: =F55+L55 -> 0 | S55: =Q55+R55+U54 -> 206.074 | T55: =H55+N55 -> 205.458 | U55: =S55-T55 -> 0.616 | V55: =T55/S55 -> 0.99701078
B56: Baycic Baycic Maria | C56: 42064 | D56: 42246 | E56: 9.848 | F56: =-9.848 -> -9.848 | G56: =E56+F56 -> 0 | I56: =G56-H56 -> 0 | J56: =E56+E57+F56+F57 -> 0 | K56: 35.357 | L56: =-35.357 -> -35.357 | M56: =K56+L56 -> 0 | O56: =M56-N56 -> 0 | P56: =K56+K57+L56+L57 -> 0 | Q56: =E56+K56 -> 45.205 | R56: =F56+L56 -> -45.205 | S56: =Q56+R56 -> 0 | T56: =H56+N56 -> 0 | U56: =S56-T56 -> 0 | V56: =T56/S56 -> #DIV/0! | W56: =Q56+Q57 -> 50.228 | X56: =R56+R57 -> -50.228 | Y56: =W56+X56 -> 0 | Z56: =T56+T57 -> 0 | AA56: =Y56-Z56 -> 0 | AB56: =Z56/Y56 -> #DIV/0!
C57: 42278 | D57: 42368 | E57: 1.101 | F57: =-1.101 -> -1.101 | G57: =E57+F57+I56 -> 0 | I57: =G57-H57 -> 0 | K57: 3.922 | L57: =-3.922 -> -3.922 | M57: =K57+L57+O56 -> 0 | O57: =M57-N57 -> 0 | Q57: =E57+K57 -> 5.023 | R57: =F57+L57 -> -5.023 | S57: =Q57+R57+U56 -> 0 | T57: =H57+N57 -> 0 | U57: =S57-T57 -> 0 | V57: =T57/S57 -> #DIV/0!
B58: Bracpesca S.A | C58: 42064 | D58: 42246 | E58: 142.156 | G58: =E58+F58 -> 142.156 | I58: =G58-H58 -> 142.156 | J58: =E58+E59+F58+F59 -> 158.042 | K58: 510.377 | L58: =-1+136.5 -> 135.5 | M58: =K58+L58 -> 645.877 | N58: 411.802 | O58: =M58-N58 -> 234.075 | P58: =K58+K59+L58+L59 -> 702.495 | Q58: =E58+K58 -> 652.533 | R58: =F58+L58 -> 135.5 | S58: =Q58+R58 -> 788.033 | T58: =H58+N58 -> 411.802 | U58: =S58-T58 -> 376.231 | V58: =T58/S58 -> 0.52256949 | W58: =Q58+Q59 -> 725.037 | X58: =R58+R59 -> 135.5 | Y58: =W58+X58 -> 860.537 | Z58: =T58+T59 -> 690.126 | AA58: =Y58-Z58 -> 170.411 | AB58: =Z58/Y58 -> 0.80197133
C59: 42278 | D59: 42368 | E59: 15.886 | G59: =E59+F59+I58 -> 158.042 | I59: =G59-H59 -> 158.042 | K59: 56.618 | M59: =K59+L59+O58 -> 290.693 | N59: 278.324 | O59: =M59-N59 -> 12.369 | Q59: =E59+K59 -> 72.504 | R59: =F59+L59 -> 0 | S59: =Q59+R59+U58 -> 448.735 | T59: =H59+N59 -> 278.324 | U59: =S59-T59 -> 170.411 | V59: =T59/S59 -> 0.62024135
B60: Grimar S.A. Pesq. | C60: 42064 | D60: 42246 | E60: 0.071 | G60: =E60+F60 -> 0.071 | I60: =G60-H60 -> 0.071 | J60: =E60+E61+F60+F61 -> 0.079 | K60: 0.255 | L60: =1 -> 1 | M60: =K60+L60 -> 1.255 | O60: =M60-N60 -> 1.255 | P60: =K60+K61+L60+L61 -> 1.283 | Q60: =E60+K60 -> 0.326 | R60: =F60+L60 -> 1 | S60: =Q60+R60 -> 1.326 | T60: =H60+N60 -> 0 | U60: =S60-T60 -> 1.326 | V60: =T60/S60 -> 0 | W60: =Q60+Q61 -> 0.362 | X60: =R60+R61 -> 1 | Y60: =W60+X60 -> 1.362 | Z60: =T60+T61 -> 0 | AA60: =Y60-Z60 -> 1.362 | AB60: =Z60/Y60 -> 0
C61: 42278 | D61: 42368 | E61: 0.008 | G61: =E61+F61+I60 -> 0.079 | I61: =G61-H61 -> 0.079 | K61: 0.028 | M61: =K61+L61+O60 -> 1.283 | O61: =M61-N61 -> 1.283 | Q61: =E61+K61 -> 0.036 | R61: =F61+L61 -> 0 | S61: =Q61+R61+U60 -> 1.362 | T61: =H61+N61 -> 0 | U61: =S61-T61 -> 1.362 | V61: =T61/S61 -> 0
B62: Isladamas S.A. Pesq. | C62: 42064 | D62: 42246 | E62: 18.013 | F62: =8.894 -> 8.894 | G62: =E62+F62 -> 26.907 | H62: 18.265 | I62: =G62-H62 -> 8.642 | J62: =E62+E63+F62+F63 -> 29.914 | K62: 64.67 | L62: =31.932 -> 31.932 | M62: =K62+L62 -> 96.602 | N62: 80.1 | O62: =M62-N62 -> 16.502 | P62: =K62+K63+L62+L63 -> 107.318 | Q62: =E62+K62 -> 82.683 | R62: =F62+L62 -> 40.826 | S62: =Q62+R62 -> 123.509 | T62: =H62+N62 -> 98.365 | U62: =S62-T62 -> 25.144 | V62: =T62/S62 -> 0.79641969 | W62: =Q62+Q63 -> 91.87 | X62: =R62+R63 -> 45.362 | Y62: =W62+X62 -> 137.232 | Z62: =T62+T63 -> 135.877 | AA62: =Y62-Z62 -> 1.355 | AB62: =Z62/Y62 -> 0.99012621
C63: 42278 | D63: 42368 | E63: 2.013 | F63: =0.994 -> 0.994 | G63: =E63+F63+I62 -> 11.649 | H63: 10.236 | I63: =G63-H63 -> 1.413 | K63: 7.174 | L63: =3.542 -> 3.542 | M63: =K63+L63+O62 -> 27.218 | N63: 27.276 | O63: =M63-N63 -> -0.058 | Q63: =E63+K63 -> 9.187 | R63: =F63+L63 -> 4.536 | S63: =Q63+R63+U62 -> 38.867 | T63: =H63+N63 -> 37.512 | U63: =S63-T63 -> 1.355 | V63: =T63/S63 -> 0.96513752
B64: Morozin Baycic Maria Ana | C64: 42064 | D64: 42246 | E64: 2.448 | F64: =-2.448 -> -2.448 | G64: =E64+F64 -> 0 | I64: =G64-H64 -> 0 | J64: =E64+E65+F64+F65 -> 0 | K64: 8.791 | L64: =-8.791 -> -8.791 | M64: =K64+L64 -> 0 | O64: =M64-N64 -> 0 | P64: =K64+K65+L64+L65 -> 0 | Q64: =E64+K64 -> 11.239 | R64: =F64+L64 -> -11.239 | S64: =Q64+R64 -> 0 | T64: =H64+N64 -> 0 | U64: =S64-T64 -> 0 | V64: =T64/S64 -> #DIV/0! | W64: =Q64+Q65 -> 12.488 | X64: =R64+R65 -> -12.488 | Y64: =W64+X64 -> 0 | Z64: =T64+T65 -> 0 | AA64: =Y64-Z64 -> 0 | AB64: =Z64/Y64 -> #DIV/0!
C65: 42278 | D65: 42368 | E65: 0.274 | F65: =-0.274 -> -0.274 | G65: =E65+F65+I64 -> 0 | I65: =G65-H65 -> 0 | K65: 0.975 | L65: =-0.975 -> -0.975 | M65: =K65+L65+O64 -> 0 | O65: =M65-N65 -> 0 | Q65: =E65+K65 -> 1.249 | R65: =F65+L65 -> -1.249 | S65: =Q65+R65+U64 -> 0 | T65: =H65+N65 -> 0 | U65: =S65-T65 -> 0 | V65: =T65/S65 -> #DIV/0!
B66: Mororzin Yurecic Mario | C66: 42064 | D66: 42246 | E66: 1.099 | F66: =-1.099 -> -1.099 | G66: =E66+F66 -> 0 | I66: =G66-H66 -> 0 | J66: =E66+E67+F66+F67 -> 0 | K66: 3.946 | L66: =-3.946 -> -3.946 | M66: =K66+L66 -> 0 | O66: =M66-N66 -> 0 | P66: =K66+K67+L66+L67 -> 0 | Q66: =E66+K66 -> 5.045 | R66: =F66+L66 -> -5.045 | S66: =Q66+R66 -> 0 | T66: =H66+N66 -> 0 | U66: =S66-T66 -> 0 | V66: =T66/S66 -> #DIV/0! | W66: =Q66+Q67 -> 5.606 | X66: =R66+R67 -> -5.606 | Y66: =W66+X66 -> 0 | Z66: =T66+T67 -> 0 | AA66: =Y66-Z66 -> 0 | AB66: =Z66/Y66 -> #DIV/0!
C67: 42278 | D67: 42368 | E67: 0.123 | F67: =-0.123 -> -0.123 | G67: =E67+F67+I66 -> 0 | I67: =G67-H67 -> 0 | K67: 0.438 | L67: =-0.438 -> -0.438 | M67: =K67+L67+O66 -> 0 | O67: =M67-N67 -> 0 | Q67: =E67+K67 -> 0.561 | R67: =F67+L67 -> -0.561 | S67: =Q67+R67+U66 -> 0 | T67: =H67+N67 -> 0 | U67: =S67-T67 -> 0 | V67: =T67/S67 -> #DIV/0!
B68: Quintero S.A. Pesq. | C68: 42064 | D68: 42246 | E68: 11.711 | F68: =1.099+2.448+9.848 -> 13.395 | G68: =E68+F68 -> 25.106 | I68: =G68-H68 -> 25.106 | J68: =E68+E69+F68+F69 -> 27.913 | K68: 42.047 | L68: =3.946+8.791+35.357-0.1 -> 47.994 | M68: =K68+L68 -> 90.041 | N68: 67.604 | O68: =M68-N68 -> 22.437 | P68: =K68+K69+L68+L69 -> 100.0222 | Q68: =E68+K68 -> 53.758 | R68: =F68+L68 -> 61.389 | S68: =Q68+R68 -> 115.147 | T68: =H68+N68 -> 67.604 | U68: =S68-T68 -> 47.543 | V68: =T68/S68 -> 0.58711039 | W68: =Q68+Q69 -> 59.731 | X68: =R68+R69 -> 68.2042 | Y68: =W68+X68 -> 127.9352 | Z68: =T68+T69 -> 68.689 | AA68: =Y68-Z68 -> 59.2462 | AB68: =Z68/Y68 -> 0.53690462
C69: 42278 | D69: 42368 | E69: 1.309 | F69: =0.123+0.274+1.101 -> 1.498 | G69: =E69+F69+I68 -> 27.913 | I69: =G69-H69 -> 27.913 | K69: 4.664 | L69: =0.438+0.975+3.922-0.0178 -> 5.3172 | M69: =K69+L69+O68 -> 32.4182 | N69: 1.085 | O69: =M69-N69 -> 31.3332 | Q69: =E69+K69 -> 5.973 | R69: =F69+L69 -> 6.8152 | S69: =Q69+R69+U68 -> 60.3312 | T69: =H69+N69 -> 1.085 | U69: =S69-T69 -> 59.2462 | V69: =T69/S69 -> 0.017984061
B70: Rubio y Mauad Ltda. | C70: 42064 | D70: 42246 | E70: 18.247 | G70: =E70+F70 -> 18.247 | I70: =G70-H70 -> 18.247 | J70: =E70+E71+F70+F71 -> 20.286 | K70: 65.511 | M70: =K70+L70 -> 65.511 | O70: =M70-N70 -> 65.511 | P70: =K70+K71+L70+L71 -> 72.778 | Q70: =E70+K70 -> 83.758 | R70: =F70+L70 -> 0 | S70: =Q70+R70 -> 83.758 | T70: =H70+N70 -> 0 | U70: =S70-T70 -> 83.758 | V70: =T70/S70 -> 0 | W70: =Q70+Q71 -> 93.064 | X70: =R70+R71 -> 0 | Y70: =W70+X70 -> 93.064 | Z70: =T70+T71 -> 55.348 | AA70: =Y70-Z70 -> 37.716 | AB70: =Z70/Y70 -> 0.59473051
C71: 42278 | D71: 42368 | E71: 2.039 | G71: =E71+F71+I70 -> 20.286 | H71: 4.358 | I71: =G71-H71 -> 15.928 | K71: 7.267 | M71: =K71+L71+O70 -> 72.778 | N71: =8.54+42.45 -> 50.99 | O71: =M71-N71 -> 21.788 | Q71: =E71+K71 -> 9.306 | R71: =F71+L71 -> 0 | S71: =Q71+R71+U70 -> 93.064 | T71: =H71+N71 -> 55.348 | U71: =S71-T71 -> 37.716 | V71: =T71/S71 -> 0.59473051 | AD71: 55.909 | AE71: Chafic I
B72: Sunrise S.A. Pesq. | C72: 42064 | D72: 42246 | E72: 8.894 | F72: =-8.894 -> -8.894 | G72: =E72+F72 -> 0 | I72: =G72-H72 -> 0 | J72: =E72+E73+F72+F73 -> 0 | K72: 31.932 | L72: =-31.932 -> -31.932 | M72: =K72+L72 -> 0 | O72: =M72-N72 -> 0 | P72: =K72+K73+L72+L73 -> 0 | Q72: =E72+K72 -> 40.826 | R72: =F72+L72 -> -40.826 | S72: =Q72+R72 -> 0 | T72: =H72+N72 -> 0 | U72: =S72-T72 -> 0 | V72: =T72/S72 -> #DIV/0! | W72: =Q72+Q73 -> 45.362 | X72: =R72+R73 -> -45.362 | Y72: =W72+X72 -> 0 | Z72: =T72+T73 -> 0 | AA72: =Y72-Z72 -> 0 | AB72: =Z72/Y72 -> #DIV/0!
C73: 42278 | D73: 42368 | E73: 0.994 | F73: =-0.994 -> -0.994 | G73: =E73+F73+I72 -> 0 | I73: =G73-H73 -> 0 | K73: 3.542 | L73: =-3.542 -> -3.542 | M73: =K73+L73+O72 -> 0 | O73: =M73-N73 -> 0 | Q73: =E73+K73 -> 4.536 | R73: =F73+L73 -> -4.536 | S73: =Q73+R73+U72 -> 0 | T73: =H73+N73 -> 0 | U73: =S73-T73 -> 0 | V73: =T73/S73 -> #DIV/0!
B74: Enfemar Pesq. S.A. | C74: 42064 | D74: 42246 | E74: 0 | G74: =E74+F74 -> 0 | I74: =G74-H74 -> 0 | J74: =E74+E75+F74+F75 -> 0 | K74: 0 | L74: =0.1 -> 0.1 | M74: =K74+L74 -> 0.1 | O74: =M74-N74 -> 0.1 | P74: =K74+K75+L74+L75 -> 0.1 | Q74: =E74+K74 -> 0 | R74: =F74+L74 -> 0.1 | S74: =Q74+R74 -> 0.1 | T74: =H74+N74 -> 0 | U74: =S74-T74 -> 0.1 | V74: =T74/S74 -> 0 | W74: =Q74+Q75 -> 0 | X74: =R74+R75 -> 0.1 | Y74: =W74+X74 -> 0.1 | Z74: =T74+T75 -> 0 | AA74: =Y74-Z74 -> 0.1 | AB74: =Z74/Y74 -> 0
C75: 42278 | D75: 42368 | E75: 0 | G75: =E75+F75+I74 -> 0 | I75: =G75-H75 -> 0 | K75: 0 | M75: =K75+L75+O74 -> 0.1 | O75: =M75-N75 -> 0.1 | Q75: =E75+K75 -> 0 | R75: =F75+L75 -> 0 | S75: =Q75+R75+U74 -> 0.1 | T75: =H75+N75 -> 0 | U75: =S75-T75 -> 0.1 | V75: =T75/S75 -> 0
B76: Quintero Ltda. Soc. Pesq. | C76: 42064 | D76: 42246 | E76: 0 | G76: =E76+F76 -> 0 | I76: =G76-H76 -> 0 | J76: =E76+E77+F76+F77 -> 0 | K76: 0 | L76: =0.0178 -> 0.0178 | M76: =K76+L76 -> 0.0178 | O76: =M76-N76 -> 0.0178 | P76: =K76+K77+L76+L77 -> 0.0178 | Q76: =E76+K76 -> 0 | R76: =F76+L76 -> 0.0178 | S76: =Q76+R76 -> 0.0178 | T76: =H76+N76 -> 0 | U76: =S76-T76 -> 0.0178 | V76: =T76/S76 -> 0 | W76: =Q76+Q77 -> 0 | X76: =R76+R77 -> 0.0178 | Y76: =W76+X76 -> 0.0178 | Z76: =T76+T77 -> 0 | AA76: =Y76-Z76 -> 0.0178 | AB76: =Z76/Y76 -> 0
C77: 42278 | D77: 42368 | E77: 0 | G77: =E77+F77+I76 -> 0 | I77: =G77-H77 -> 0 | K77: 0 | M77: =K77+L77+O76 -> 0.0178 | O77: =M77-N77 -> 0.0178 | Q77: =E77+K77 -> 0 | R77: =F77+L77 -> 0 | S77: =Q77+R77+U76 -> 0.0178 | T77: =H77+N77 -> 0 | U77: =S77-T77 -> 0.0178 | V77: =T77/S77 -> 0
C80: Periodo | E80: Cuota II Región (t) | H80: Operación II región | K80: Cuota III Región (t) | N80: Operación III Región | Q80: Cuota IV Región (t) | T80: Operación IV Región | W80: Cuota y Operación Langostino colorado XV-IV | AC80: Resumen global anual XV-IV
B81: Armador | C81: Inicial | D81: Final | E81: Cuota Asignada | F81: Traspaso, Cesion, Arriendo, etc) | G81: Cuota Efectiva | H81: Desembarque (t) | I81: Saldo (t) | J81: Cuota Total | K81: Cuota Asignada | L81: Traspaso, Cesion, Arriendo, etc) | M81: Cuota Efectiva | N81: Desembarque (t) | O81: Saldo (t) | P81: Cuota Total | Q81: Cuota Asignada | R81: Traspaso, Cesion, Arriendo, etc) | S81: Cuota Efectiva | T81: Desembarque (t) | U81: Saldo (t) | V81: Cuota Total | W81: Cuota Asignada III-IV | X81: * Traspaso, Cesion, Arriendo, etc) | Y81: Cuota Efectiva | Z81: Desembarque (t) III-IV | AA81: Saldo (t) | AB81: % consumido | AC81: Cuota Total | AD81: * Traspaso, Cesion, Arriendo, etc) | AE81: Cuota Efectiva | AF81: Desembarque (t) | AG81: Saldo (t) | AH81: % consumido
A82: Langostino colorado XV- IV | B82: Antarctic Seafood S.A | C82: 42064 | D82: 42246 | E82: 1.263 | G82: =E82+F82 -> 1.263 | I82: =G82-H82 -> 1.263 | J82: =E82+E83+F82+F83 -> 1.516 | K82: 7.831 | M82: =K82+L82 -> 7.831 | O82: =M82-N82 -> 7.831 | P82: =K82+K83+L82+L83 -> 8.841 | Q82: 5.557 | R82: =15 -> 15 | S82: =Q82+R82 -> 20.557 | U82: =S82-T82 -> 20.557 | V82: =Q82+Q83+R82+R83 -> 21.315 | W82: =E82+K82+Q82 -> 14.651 | X82: =L82+R82+F82 -> 15 | Y82: =W82+X82 -> 29.651 | Z82: =H82+N82+T82 -> 0 | AA82: =Y82-Z82 -> 29.651 | AB82: =Z82/Y82 -> 0 | AC82: =W82+W83 -> 16.672 | AD82: =X82+X83 -> 15 | AE82: =AC82+AD82 -> 31.672 | AF82: =Z82+Z83 -> 17.475 | AG82: =AE82-AF82 -> 14.197 | AH82: =AF82/AE82 -> 0.55174918
C83: 42278 | D83: 42368 | E83: 0.253 | G83: =E83+F83+I82 -> 1.516 | I83: =G83-H83 -> 1.516 | K83: 1.01 | M83: =K83+L83+O82 -> 8.841 | O83: =M83-N83 -> 8.841 | Q83: 0.758 | S83: =Q83+R83+U82 -> 21.315 | T83: 17.475 | U83: =S83-T83 -> 3.84 | W83: =E83+K83+Q83 -> 2.021 | X83: =L83+R83+F83 -> 0 | Y83: =W83+X83+AA82 -> 31.672 | Z83: =H83+N83+T83 -> 17.475 | AA83: =Y83-Z83 -> 14.197 | AB83: =Z83/Y83 -> 0.55174918
B84: Bracpesca S.A | C84: 42064 | D84: 42246 | E84: 2.528 | G84: =E84+F84 -> 2.528 | I84: =G84-H84 -> 2.528 | J84: =E84+E85+F84+F85 -> 3.034 | K84: 15.676 | M84: =K84+L84 -> 15.676 | O84: =M84-N84 -> 15.676 | P84: =K84+K85+L84+L85 -> 17.699 | Q84: 11.125 | R84: =-1-0.2+76.65 -> 75.45 | S84: =Q84+R84 -> 86.575 | T84: 17.625 | U84: =S84-T84 -> 68.95 | V84: =Q84+Q85+R84+R85 -> 88.092 | W84: =E84+K84+Q84 -> 29.329 | X84: =L84+R84+F84 -> 75.45 | Y84: =W84+X84 -> 104.779 | Z84: =H84+N84+T84 -> 17.625 | AA84: =Y84-Z84 -> 87.154 | AB84: =Z84/Y84 -> 0.16821119 | AC84: =W84+W85 -> 33.375 | AD84: =X84+X85 -> 75.45 | AE84: =AC84+AD84 -> 108.825 | AF84: =Z84+Z85 -> 25.416 | AG84: =AE84-AF84 -> 83.409 | AH84: =AF84/AE84 -> 0.23354928
C85: 42278 | D85: 42368 | E85: 0.506 | G85: =E85+F85+I84 -> 3.034 | I85: =G85-H85 -> 3.034 | K85: 2.023 | M85: =K85+L85+O84 -> 17.699 | O85: =M85-N85 -> 17.699 | Q85: 1.517 | S85: =Q85+R85+U84 -> 70.467 | T85: 7.791 | U85: =S85-T85 -> 62.676 | W85: =E85+K85+Q85 -> 4.046 | X85: =L85+R85+F85 -> 0 | Y85: =W85+X85+AA84 -> 91.2 | Z85: =H85+N85+T85 -> 7.791 | AA85: =Y85-Z85 -> 83.409 | AB85: =Z85/Y85 -> 0.085427632
B86: Isladamas S.A. | C86: 42064 | D86: 42246 | E86: 0.576 | F86: =0.526 -> 0.526 | G86: =E86+F86 -> 1.102 | I86: =G86-H86 -> 1.102 | J86: =E86+E87+F86+F87 -> 1.322 | K86: 3.571 | L86: =3.264 -> 3.264 | M86: =K86+L86 -> 6.835 | O86: =M86-N86 -> 6.835 | P86: =K86+K87+L86+L87 -> 7.717 | Q86: 2.534 | R86: =0.01+2.316 -> 2.326 | S86: =Q86+R86 -> 4.86 | U86: =S86-T86 -> 4.86 | V86: =Q86+Q87+R86+R87 -> 5.522 | W86: =E86+K86+Q86 -> 6.681 | X86: =L86+R86+F86 -> 6.116 | Y86: =W86+X86 -> 12.797 | Z86: =H86+N86+T86 -> 0 | AA86: =Y86-Z86 -> 12.797 | AB86: =Z86/Y86 -> 0 | AC86: =W86+W87 -> 7.603 | AD86: =X86+X87 -> 6.958 | AE86: =AC86+AD86 -> 14.561 | AF86: =Z86+Z87 -> 0 | AG86: =AE86-AF86 -> 14.561 | AH86: =AF86/AE86 -> 0
C87: 42278 | D87: 42368 | E87: 0.115 | F87: =0.105 -> 0.105 | G87: =E87+F87+I86 -> 1.322 | I87: =G87-H87 -> 1.322 | K87: 0.461 | L87: =0.421 -> 0.421 | M87: =K87+L87+O86 -> 7.717 | O87: =M87-N87 -> 7.717 | Q87: 0.346 | R87: =0.316 -> 0.316 | S87: =Q87+R87+U86 -> 5.522 | U87: =S87-T87 -> 5.522 | W87: =E87+K87+Q87 -> 0.922 | X87: =L87+R87+F87 -> 0.842 | Y87: =W87+X87+AA86 -> 14.561 | Z87: =H87+N87+T87 -> 0 | AA87: =Y87-Z87 -> 14.561 | AB87: =Z87/Y87 -> 0
B88: Rubio y Mauad Ltda. | C88: 42064 | D88: 42246 | E88: 0.106 | G88: =E88+F88 -> 0.106 | I88: =G88-H88 -> 0.106 | J88: =E88+E89+F88+F89 -> 0.127 | K88: 0.659 | M88: =K88+L88 -> 0.659 | O88: =M88-N88 -> 0.659 | P88: =K88+K89+L88+L89 -> 0.744 | Q88: 0.468 | S88: =Q88+R88 -> 0.468 | U88: =S88-T88 -> 0.468 | V88: =Q88+Q89+R88+R89 -> 0.532 | W88: =E88+K88+Q88 -> 1.233 | X88: =L88+R88+F88 -> 0 | Y88: =W88+X88 -> 1.233 | Z88: =H88+N88+T88 -> 0 | AA88: =Y88-Z88 -> 1.233 | AB88: =Z88/Y88 -> 0 | AC88: =W88+W89 -> 1.403 | AD88: =X88+X89 -> 0 | AE88: =AC88+AD88 -> 1.403 | AF88: =Z88+Z89 -> 0.942 | AG88: =AE88-AF88 -> 0.461 | AH88: =AF88/AE88 -> 0.67141839
C89: 42278 | D89: 42368 | E89: 0.021 | G89: =E89+F89+I88 -> 0.127 | I89: =G89-H89 -> 0.127 | K89: 0.085 | M89: =K89+L89+O88 -> 0.744 | O89: =M89-N89 -> 0.744 | Q89: 0.064 | S89: =Q89+R89+U88 -> 0.532 | T89: 0.942 | U89: =S89-T89 -> -0.41 | W89: =E89+K89+Q89 -> 0.17 | X89: =L89+R89+F89 -> 0 | Y89: =W89+X89+AA88 -> 1.403 | Z89: =H89+N89+T89 -> 0.942 | AA89: =Y89-Z89 -> 0.461 | AB89: =Z89/Y89 -> 0.67141839
B90: Sunrise S.A. Pesq. | C90: 42064 | D90: 42246 | E90: 0.526 | F90: =-0.526 -> -0.526 | G90: =E90+F90 -> 0 | I90: =G90-H90 -> 0 | J90: =E90+E91+F90+F91 -> 0 | K90: 3.264 | L90: =-3.264 -> -3.264 | M90: =K90+L90 -> 0 | O90: =M90-N90 -> 0 | P90: =K90+K91+L90+L91 -> 0 | Q90: 2.316 | R90: =-2.316 -> -2.316 | S90: =Q90+R90 -> 0 | U90: =S90-T90 -> 0 | V90: =Q90+Q91+R90+R91 -> 0 | W90: =E90+K90+Q90 -> 6.106 | X90: =L90+R90+F90 -> -6.106 | Y90: =W90+X90 -> 0 | Z90: =H90+N90+T90 -> 0 | AA90: =Y90-Z90 -> 0 | AB90: =Z90/Y90 -> #DIV/0! | AC90: =W90+W91 -> 6.948 | AD90: =X90+X91 -> -6.948 | AE90: =AC90+AD90 -> 0 | AF90: =Z90+Z91 -> 0 | AG90: =AE90-AF90 -> 0 | AH90: =AF90/AE90 -> #DIV/0!
C91: 42278 | D91: 42368 | E91: 0.105 | F91: =-0.105 -> -0.105 | G91: =E91+F91+I90 -> 0 | I91: =G91-H91 -> 0 | K91: 0.421 | L91: =-0.421 -> -0.421 | M91: =K91+L91+O90 -> 0 | O91: =M91-N91 -> 0 | Q91: 0.316 | R91: =-0.316 -> -0.316 | S91: =Q91+R91+U90 -> 0 | U91: =S91-T91 -> 0 | W91: =E91+K91+Q91 -> 0.842 | X91: =L91+R91+F91 -> -0.842 | Y91: =W91+X91+AA90 -> 1.110223e-16 | Z91: =H91+N91+T91 -> 0 | AA91: =Y91-Z91 -> 1.110223e-16 | AB91: =Z91/Y91 -> 0
B92: Grimar S.A. Pesq. | C92: 42064 | D92: 42246 | E92: 0 | G92: =E92+F92 -> 0 | I92: =G92-H92 -> 0 | J92: =E92+E93+F92+F93 -> 0 | K92: 0 | M92: =K92+L92 -> 0 | O92: =M92-N92 -> 0 | P92: =K92+K93+L92+L93 -> 0 | Q92: 0 | R92: =1 -> 1 | S92: =Q92+R92 -> 1 | U92: =S92-T92 -> 1 | V92: =Q92+Q93+R92+R93 -> 1 | W92: =E92+K92+Q92 -> 0 | X92: =L92+R92+F92 -> 1 | Y92: =W92+X92 -> 1 | Z92: =H92+N92+T92 -> 0 | AA92: =Y92-Z92 -> 1 | AB92: =Z92/Y92 -> 0 | AC92: =W92+W93 -> 0 | AD92: =X92+X93 -> 1 | AE92: =AC92+AD92 -> 1 | AF92: =Z92+Z93 -> 0 | AG92: =AE92-AF92 -> 1 | AH92: =AF92/AE92 -> 0
C93: 42278 | D93: 42368 | E93: 0 | G93: =E93+F93+I92 -> 0 | I93: =G93-H93 -> 0 | K93: 0 | M93: =K93+L93+O92 -> 0 | O93: =M93-N93 -> 0 | Q93: 0 | S93: =Q93+R93+U92 -> 1 | U93: =S93-T93 -> 1 | W93: =E93+K93+Q93 -> 0 | X93: =L93+R93+F93 -> 0 | Y93: =W93+X93+AA92 -> 1 | Z93: =H93+N93+T93 -> 0 | AA93: =Y93-Z93 -> 1 | AB93: =Z93/Y93 -> 0
B94: Quintero S.A. Pesq. | C94: 42064 | D94: 42246 | E94: 0 | G94: =E94+F94 -> 0 | I94: =G94-H94 -> 0 | J94: =E94+E95+F94+F95 -> 0 | K94: 0 | M94: =K94+L94 -> 0 | O94: =M94-N94 -> 0 | P94: =K94+K95+L94+L95 -> 0 | Q94: 0 | R94: =0.2-0.01056 -> 0.18944 | S94: =Q94+R94 -> 0.18944 | U94: =S94-T94 -> 0.18944 | V94: =Q94+Q95+R94+R95 -> 0.18944 | W94: =E94+K94+Q94 -> 0 | X94: =L94+R94+F94 -> 0.18944 | Y94: =W94+X94 -> 0.18944 | Z94: =H94+N94+T94 -> 0 | AA94: =Y94-Z94 -> 0.18944 | AB94: =Z94/Y94 -> 0 | AC94: =W94+W95 -> 0 | AD94: =X94+X95 -> 0.18944 | AE94: =AC94+AD94 -> 0.18944 | AF94: =Z94+Z95 -> 0 | AG94: =AE94-AF94 -> 0.18944 | AH94: =AF94/AE94 -> 0
C95: 42278 | D95: 42368 | E95: 0 | G95: =E95+F95+I94 -> 0 | I95: =G95-H95 -> 0 | K95: 0 | M95: =K95+L95+O94 -> 0 | O95: =M95-N95 -> 0 | Q95: 0 | S95: =Q95+R95+U94 -> 0.18944 | U95: =S95-T95 -> 0.18944 | W95: =E95+K95+Q95 -> 0 | X95: =L95+R95+F95 -> 0 | Y95: =W95+X95+AA94 -> 0.18944 | Z95: =H95+N95+T95 -> 0 | AA95: =Y95-Z95 -> 0.18944 | AB95: =Z95/Y95 -> 0
B96: Quintero Ltda. Soc. Pesq. | C96: 42064 | D96: 42246 | E96: 0 | G96: =E96+F96 -> 0 | I96: =G96-H96 -> 0 | J96: =E96+E97+F96+F97 -> 0 | K96: 0 | M96: =K96+L96 -> 0 | O96: =M96-N96 -> 0 | P96: =K96+K97+L96+L97 -> 0 | Q96: 0 | R96: 0.01056 | S96: =Q96+R96 -> 0.01056 | U96: =S96-T96 -> 0.01056 | V96: =Q96+Q97+R96+R97 -> 0.01056 | W96: =E96+K96+Q96 -> 0 | X96: =L96+R96+F96 -> 0.01056 | Y96: =W96+X96 -> 0.01056 | Z96: =H96+N96+T96 -> 0 | AA96: =Y96-Z96 -> 0.01056 | AB96: =Z96/Y96 -> 0 | AC96: =W96+W97 -> 0 | AD96: =X96+X97 -> 0.01056 | AE96: =AC96+AD96 -> 0.01056 | AF96: =Z96+Z97 -> 0 | AG96: =AE96-AF96 -> 0.01056 | AH96: =AF96/AE96 -> 0
C97: 42278 | D97: 42368 | E97: 0 | G97: =E97+F97+I96 -> 0 | I97: =G97-H97 -> 0 | K97: 0 | M97: =K97+L97+O96 -> 0 | O97: =M97-N97 -> 0 | Q97: 0 | S97: =Q97+R97+U96 -> 0.01056 | U97: =S97-T97 -> 0.01056 | W97: =E97+K97+Q97 -> 0 | X97: =L97+R97+F97 -> 0 | Y97: =W97+X97+AA96 -> 0.01056 | Z97: =H97+N97+T97 -> 0 | AA97: =Y97-Z97 -> 0.01056 | AB97: =Z97/Y97 -> 0

Sheet Cuotas Regionales Crustaceos
A3: Cuotas Regionales Crustaceos Industriales, 2015
A4: Del 31 de diciembre de 2015
A6: Unidad de Pesquería | B6: Zona | C6: Cuota Global (t) | D6: Cuota Período | G6: Desembarque (t) | H6: Saldo (t) | I6: % Disponible | J6: Fecha cierre /Prom (t/día)
D7: Período | E7: autorizada | F7: efectiva
A8: Camarón nailon | B8: II | C8: =E8+E9 -> 10 | D8: Enero - Julio | E8: 8 | F8: =+E8 -> 8 | H8: =+F8-G8 -> 8 | I8: =1-G8/F8 -> 1
D9: Octubre - Diciembre | E9: 2 | F9: =+E9+H8 -> 10 | H9: =+F9-G9 -> 10 | I9: =1-G9/F9 -> 1
B10: III | C10: =E10+E11 -> 46 | D10: Enero - Julio | E10: 37 | F10: =+E10 -> 37 | H10: =+F10-G10 -> 37 | I10: =1-G10/F10 -> 1
D11: Octubre - Diciembre | E11: 9 | F11: =+E11+H10 -> 46 | H11: =+F11-G11 -> 46 | I11: =1-G11/F11 -> 1
B12: IV | C12: =E12+E13 -> 320 | D12: Enero - Julio | E12: 256 | F12: =+E12 -> 256 | G12: 157.537 | H12: =+F12-G12 -> 98.463 | I12: =1-G12/F12 -> 0.38462109
D13: Octubre - Diciembre | E13: 64 | F13: =+E13+H12 -> 162.463 | G13: 132.183 | H13: =+F13-G13 -> 30.28 | I13: =1-G13/F13 -> 0.1863809
B14: V | C14: =E14+E15 -> 600 | D14: Enero - Julio | E14: 480 | F14: =+E14 -> 480 | G14: 405.229 | H14: =+F14-G14 -> 74.771 | I14: =1-G14/F14 -> 0.15577292
D15: Octubre - Diciembre | E15: 120 | F15: =+E15+H14 -> 194.771 | G15: 117.205 | H15: =+F15-G15 -> 77.566 | I15: =1-G15/F15 -> 0.39824204
B16: VI | C16: =E16+E17 -> 1020 | D16: Enero - Julio | E16: 816 | F16: =+E16 -> 816 | G16: 491.365 | H16: =+F16-G16 -> 324.635 | I16: =1-G16/F16 -> 0.39783701
D17: Octubre - Diciembre | E17: 204 | F17: =+E17+H16 -> 528.635 | G17: 192.663 | H17: =+F17-G17 -> 335.972 | I17: =1-G17/F17 -> 0.63554627
B18: VII | C18: =E18+E19 -> 1010 | D18: Enero - Julio | E18: 808 | F18: =+E18 -> 808 | G18: 768.195 | H18: =+F18-G18 -> 39.805 | I18: =1-G18/F18 -> 0.049263614
D19: Octubre - Diciembre | E19: 202 | F19: =+E19+H18 -> 241.805 | G19: 218.661 | H19: =+F19-G19 -> 23.144 | I19: =1-G19/F19 -> 0.095713488
B20: VIII | C20: =E20+E21 -> 1020 | D20: Enero - Julio | E20: 816 | F20: =+E20 -> 816 | G20: 333.471 | H20: =+F20-G20 -> 482.529 | I20: =1-G20/F20 -> 0.59133456
D21: Octubre - Diciembre | E21: 204 | F21: =+E21+H20 -> 686.529 | G21: 372.55 | H21: =+F21-G21 -> 313.979 | I21: =1-G21/F21 -> 0.45734266
A22: Langostino amarillo | B22: III | C22: =+E22+E23 -> 388 | D22: Marzo - Agosto | E22: 349 | F22: =+E22 -> 349 | G22: 96.6 | H22: =+F22-G22 -> 252.4 | I22: =1-G22/F22 -> 0.72320917 | K22: Chafic I
D23: Octubre - Diciembre | E23: 39 | F23: =+E23+H22 -> 291.4 | G23: =82.674+13.459 -> 96.133 | H23: =+F23-G23 -> 195.267 | I23: =1-G23/F23 -> 0.67009952 | K23: 13.459
B24: IV | C24: =+E24+E25 -> 1392 | D24: Marzo - Agosto | E24: 1253 | F24: =+E24 -> 1253 | G24: 980.07 | H24: =+F24-G24 -> 272.93 | I24: =1-G24/F24 -> 0.21782123
D25: Octubre - Diciembre | E25: 139 | F25: =+E25+H24 -> 411.93 | G25: =325.058+42.45 -> 367.508 | H25: =+F25-G25 -> 44.422 | I25: =1-G25/F25 -> 0.10783871 | K25: 42.45
A26: Langostino amarillo Licitado | B26: V-VI | C26: =+E26+E27 -> 1379 | D26: Marzo - Agosto | E26: 1241 | F26: =+E26 -> 1241 | G26: 1181.543 | H26: =+F26-G26 -> 59.457 | I26: =1-G26/F26 -> 0.047910556 | J26: 42162
D27: Octubre - Diciembre | E27: 138 | F27: =E27+H26 -> 197.457 | G27: 102.998 | H27: =+F27-G27 -> 94.459 | I27: =1-G27/F27 -> 0.47837757
B28: VII-VIII | C28: =+E28+E29 -> 591 | D28: Marzo - Agosto | E28: 532 | F28: =+E28 -> 532 | G28: 259.123 | H28: =+F28-G28 -> 272.877 | I28: =1-G28/F28 -> 0.51292669
D29: Octubre - Diciembre | E29: 59 | F29: =E29+H28 -> 331.877 | G29: 176.053 | H29: =+F29-G29 -> 155.824 | I29: =1-G29/F29 -> 0.46952335
A30: Langostino colorado | B30: II | C30: =+E30+E31 -> 6 | D30: Marzo - Agosto | E30: 5 | F30: =+E30 -> 5 | H30: =+F30-G30 -> 5 | I30: =1-G30/F30 -> 1
D31: Octubre - Diciembre | E31: 1 | F31: =+E31+H30 -> 6 | H31: =+F31-G31 -> 6 | I31: =1-G31/F31 -> 1
B32: III | C32: =+E32+E33 -> 35 | D32: Marzo - Agosto | E32: 31 | F32: =+E32 -> 31 | H32: =+F32-G32 -> 31 | I32: =1-G32/F32 -> 1
D33: Octubre - Diciembre | E33: 4 | F33: =+E33+H32 -> 35 | H33: =+F33-G33 -> 35 | I33: =1-G33/F33 -> 1
B34: IV | C34: =+E34+E35 -> 25 | D34: Marzo - Agosto | E34: 22 | F34: =+E34 -> 22 | G34: 8.99 | H34: =+F34-G34 -> 13.01 | I34: =1-G34/F34 -> 0.59136364
D35: Octubre - Diciembre | E35: 3 | F35: =+E35+H34 -> 16.01 | G35: 12.386 | H35: =+F35-G35 -> 3.624 | I35: =1-G35/F35 -> 0.22635853
A36: Langostino colorado Licitado | B36: V | C36: =+E36+E37 -> 500 | D36: Marzo - Agosto | E36: 450 | F36: =+E36 -> 450 | G36: 536.021 | H36: =+F36-G36 -> -86.021 | I36: =1-G36/F36 -> -0.19115778 | J36: 42124
D37: Octubre - Diciembre | E37: 50 | F37: =+E37+H36 -> -36.021 | G37: 24.626 | H37: =+F37-G37 -> -60.647 | I37: =1-G36/(E37+E36) -> -0.072042
B38: VI | C38: =+E38+E39 -> 730 | D38: Marzo - Agosto | E38: 657 | F38: =+E38 -> 657 | G38: 657.287 | H38: =+F38-G38 -> -0.287 | I38: =1-G38/F38 -> -0.00043683409 | J38: 42184
D39: Octubre - Diciembre | E39: 73 | F39: =+E39+H38 -> 72.713 | G39: 17.189 | H39: =+F39-G39 -> 55.524 | I39: =1-G39/F39 -> 0.76360486
B40: VII | C40: =+E40+E41 -> 2300 | D40: Marzo - Agosto | E40: 2070 | F40: =+E40 -> 2070 | G40: 1731.103 | H40: =+F40-G40 -> 338.897 | I40: =1-G40/F40 -> 0.16371836
D41: Octubre - Diciembre | E41: 230 | F41: =+E41+H40 -> 568.897 | G41: 237.675 | H41: =+F41-G41 -> 331.222 | I41: =1-G41/F41 -> 0.58221787
B42: VIII | C42: =+E42+E43 -> 2300 | D42: Marzo - Agosto | E42: 2070 | F42: =+E42 -> 2070 | G42: 1346.03 | H42: =+F42-G42 -> 723.97 | I42: =1-G42/F42 -> 0.34974396
D43: Octubre - Diciembre | E43: 230 | F43: =+E43+H42 -> 953.97 | G43: 581.087 | H43: =+F43-G43 -> 372.883 | I43: =1-G43/F43 -> 0.39087498

Sheet Cuotas Licitadas 
B2: Cuotas Industriales Licitadas, año 2015
B3: Al 31 de diciembre de 2015
B5: Langostino amarillo V-VIII | C5: 1970
B6: Armador | C6: % Licitado | D6: Cuota licitada (t) | E6: Sanción (t) | F6: Transferencias | H6: Cuota efectiva (t) | I6: Operación
F7: Ingresos (t) | G7: Egresos (t) | I7: Desembarque (t) | J7: Saldo (t) | K7: % consumido
B8: CAMANCHACA PESCA SUR | C8: 39.01 | D8: 768.497 | F8: 347.40162 | G8: 492.1 | H8: 623.79862 | I8: 622.971 | J8: 0.82762 | K8: =+I8/H8 -> 0.99867326
B9: BLUMAR S.A. | C9: 17.66 | D9: 347.902 | G9: 347.61162 | H9: 0.29038 | J9: 0.29038 | K9: =+I9/H9 -> 0
B10: SUNRISE | C10: 1.16 | D10: 22.852 | G10: 22.852 | H10: 0 | J10: 0 | K10: =+I10/H10 -> #DIV/0!
B11: BRACPESCA S.A. | C11: 20.78 | D11: 409.366 | F11: 36.532 | G11: 1 | H11: 444.898 | I11: 444.728 | J11: 0.17 | K11: =+I11/H11 -> 0.99961789
B12: ISLADAMAS | C12: 10.51 | D12: 207.047 | F12: 62.852 | G12: 0.024 | H12: 269.875 | I12: 237.568 | J12: 32.307 | K12: =+I12/H12 -> 0.88028902
B13: VELIZ Y VELIZ | C13: 0.3 | D13: 5.91 | G13: 5.91 | H13: 0 | J13: 0 | K13: =+I13/H13 -> #DIV/0!
B14: DISTRIMAR | C14: 0 | D14: 0 | H14: 0 | J14: 0 | K14: =+I14/H14 -> #DIV/0!
B15: ANTARTIC SEAFOOD | C15: 6.8 | D15: 133.96 | F15: 44.128 | G15: 30.622 | H15: 147.466 | I15: 145.949 | J15: 1.517 | K15: =+I15/H15 -> 0.98971288
B16: GRIMAR S.A. | C16: 1 | D16: 19.7 | F16: 1 | H16: 20.7 | J16: 20.7 | K16: =+I16/H16 -> 0
B17: RUBIO Y MAUAD LTDA. | C17: 2.24 | D17: 44.128 | G17: 44.128 | H17: 0 | J17: 0 | K17: =+I17/H17 -> #DIV/0!
B18: MARIO MOROZIN YURECIC | C18: 0 | D18: 0 | H18: 0 | J18: 0 | K18: =+I18/H18 -> #DIV/0!
B19: SOC. PESQUERA QUINTERO LTDA. | C19: 0 | D19: 0 | H19: 0 | J19: 0 | K19: =+I19/H19 -> #DIV/0!
B20: PESQUERA QUINTERO S.A. | C20: 0.54 | D20: 10.638 | H20: 10.638 | I20: 5 | J20: 5.638 | K20: =+I20/H20 -> 0.47001316
B21: CONGELADOS PACIFICO S.A. | C21: 0 | D21: 0 | F21: 0.03 | H21: 0.03 | J21: 0.03 | K21: =+I21/H21 -> 0
B22: PESQUERA BIO BIO S.A. | C22: 0 | D22: 0 | H22: 0 | J22: 0 | K22: =+I22/H22 -> #DIV/0!
B23: PESQUERA ANTONIO CORDOVA NAKOUZI E.I.R.L. | C23: 0 | D23: 0 | F23: 0.18 | H23: 0.18 | J23: 0.18 | K23: =+I23/H23 -> 0
B24: PESQUERA ENFEMAR LTDA. | C24: 0 | D24: 0 | F24: 0.1 | H24: 0.1 | J24: 0.1 | K24: =+I24/H24 -> 0
B25: ANTONIO DA VENEZIA RETAMALES | C25: 0 | D25: 0 | F25: 0.024 | H25: 0.024 | J25: 0.024 | K25: =+I25/H25 -> 0
B26: JORGE COFRE REYES | C26: 0 | D26: 0 | F26: 200 | H26: 200 | I26: 199.131 | J26: 0.869 | K26: =+I26/H26 -> 0.995655
B27: PESQUERA CMK LTDA. | C27: 0 | D27: 0 | F27: 250 | H27: 250 | I27: 249.59 | J27: 0.41 | K27: =+I27/H27 -> 0.99836
B28: PESQUERA LANDES S.A. | C28: 0 | D28: 0 | F28: 2 | H28: 2 | J28: 2 | K28: =+I28/H28 -> 0
B30: Resumen | C30: % Licitado | D30: Cuota licitada (t) | E30: Sanción (t) | F30: Transferencias | H30: Cuota efectiva (t) | I30: Operación
B31: Langostino amarillo V-VIII | F31: Ingresos (t) | G31: Egresos (t) | I31: Desembarque (t) | J31: Saldo (t) | K31: % consumido
C32: =SUM(C8:C28) -> 100 | D32: =SUM(D8:D28) -> 1970 | E32: =SUM(E8:E18) -> 0 | F32: =SUM(F8:F28) -> 944.24762 | G32: =SUM(G8:G28) -> 944.24762 | H32: =SUM(H8:H28) -> 1970 | I32: =SUM(I8:I28) -> 1904.937 | J32: =SUM(J8:J28) -> 65.063 | K32: =+I32/H32 -> 0.9669731
B35: Langostino colorado V-VIII | C35: 5830
B36: Armador | C36: % Licitado | D36: Cuota licitada (t) | E36: Sanción (t) | F36: Transferencias | H36: Cuota efectiva (t) | I36: Operación
F37: Ingresos (t) | G37: Egresos (t) | I37: Desembarque (t) | J37: Saldo (t) | K37: % consumido
B38: CAMANCHACA PESCA SUR | C38: 67.8056 | D38: 3953.066 | F38: 908.89451 | G38: 1830.099 | H38: 3031.862 | I38: 3031.168 | J38: 0.69399 | K38: =+I38/H38 -> 0.9997711
B39: BLUMAR S.A. | C39: 15.1269 | D39: 881.898 | G39: 881.18051 | H39: 0.718 | J39: 0.7178 | K39: =+I39/H39 -> 0
B40: SUNRISE | C40: 0.5 | D40: 29.15 | G40: 29.15 | H40: 0 | J40: 0 | K40: =+I40/H40 -> #DIV/0!
B41: BRACPESCA | C41: 6.1215 | D41: 356.88345 | G41: 31.8075 | H41: 325.07595 | I41: 324.827 | J41: 0.24895 | K41: =+I41/H41 -> 0.99923418
B42: ISLADAMAS | C42: 2.813 | D42: 163.9979 | F42: 658.3 | G42: 0.024 | H42: 822.2739 | I42: 725.023 | J42: 97.2509 | K42: =+I42/H42 -> 0.88172931
B43: EMPACADORA DEL PACIFICO | C43: 1.5 | D43: 87.45 | H43: 87.45 | J43: 87.45 | K43: =+I43/H43 -> 0
B44: DISTRIMAR | C44: 0 | D44: 0 | H44: 0 | J44: 0 | K44: =+I44/H44 -> #DIV/0!
B45: ANTARTIC SEAFOOD | C45: 3.943 | D45: 229.8769 | F45: 97.215 | G45: 27.999 | H45: 299.0929 | I45: 297.793 | J45: 1.2999 | K45: =+I45/H45 -> 0.99565386
B46: ALIMAR | C46: 0.5 | D46: 29.15 | G46: 29.15 | H46: 0 | J46: 0 | K46: =+I46/H46 -> #DIV/0!
B47: RUBIO Y MAUAD LTDA. | C47: 0.69 | D47: 40.227 | G47: 38.6075 | H47: 1.6195 | J47: 1.6195 | K47: =+I47/H47 -> 0
B48: ARTIC S.A. ELAB | C48: 0.5 | D48: 29.15 | H48: 29.15 | J48: 29.15 | K48: =+I48/H48 -> 0
B49: MARIO MOROZIN YURECIC | C49: 0 | D49: 0 | H49: 0 | J49: 0 | K49: =+I49/H49 -> #DIV/0!
B50: SOC. PESQUERA QUINTERO LTDA. | C50: 0 | D50: 0 | H50: 0 | J50: 0 | K50: =+I50/H50 -> #DIV/0!
B51: PESQUERA QUINTERO S.A. | C51: 0 | D51: 0 | F51: 0.2 | H51: 0.2 | J51: 0.2 | K51: =+I51/H51 -> 0
B52: PESQUERA GRIMAR S.A. | C52: 0 | D52: 0 | F52: 1 | H52: 1 | J52: 1 | K52: =+I52/H52 -> 0
B53: CONGELADOS PACIFICO S.A. | C53: 0 | D53: 0 | F53: 0.105 | H53: 0.105 | J53: 0.105 | K53: =+I53/H53 -> 0
B54: PESQUERA BIO BIO S.A. | C54: 0 | D54: 0 | H54: 0 | J54: 0 | K54: =+I54/H54 -> #DIV/0!
B55: PESQUERA ANTONIO CORDOVA NAKOUZI E.I.R.L. | C55: 0 | D55: 0 | F55: 0.18 | H55: 0.18 | J55: 0.18 | K55: =+I55/H55 -> 0
B56: PESQUERA ENFEMAR LTDA. | C56: 0 | D56: 0 | F56: 0.1 | H56: 0.1 | J56: 0.1 | K56: =+I56/H56 -> 0
B57: ANTONIO DA VENEZIA RETAMALES | C57: 0 | D57: 0 | F57: 0.024 | H57: 0.024 | J57: 0.024 | K57: =+I57/H57 -> 0
B58: JORGE COFRE REYES | C58: 0 | D58: 0 | F58: 650 | H58: 650 | I58: 649.79 | J58: 0.21 | K58: =+I58/H58 -> 0.99967692
B59: PESQUERA CMK LTDA. | C59: 0 | D59: 0 | F59: 550 | H59: 550 | I59: 549.333 | J59: 0.667 | K59: =+I59/H59 -> 0.99878727
B60: SOC. PESQUERA LANDES S.A. | C60: 0 | D60: 0 | F60: 1.999 | H60: 1.999 | J60: 1.999 | K60: =+I60/H60 -> 0
B62: Resumen | C62: % Licitado | D62: Cuota licitada (t) | E62: Sanción (t) | F62: Transferencias | H62: Cuota efectiva (t) | I62: Operación
B63: Langostino colorado V-VIII | F63: Ingresos (t) | G63: Egresos (t) | I63: Desembarque (t) | J63: Saldo (t) | K63: % consumido
C64: =SUM(C38:C60) -> 99.5 | D64: =SUM(D38:D60) -> 5800.8492 | E64: =SUM(E38:E49) -> 0 | F64: =SUM(F38:F60) -> 2868.0175 | G64: =SUM(G38:G60) -> 2868.0175 | H64: =SUM(H38:H60) -> 5800.8502 | I64: =SUM(I38:I60) -> 5577.934 | J64: =SUM(J38:J60) -> 222.91604 | K64: =+I64/H64 -> 0.9615718
B66: Bacalao de profundidad | C66: 1337
B67: Armador | C67: % Licitado | D67: Cuota licitada (t) | E67: Sanción (t) | F67: Transferencias | H67: Cuota efectiva (t) | I67: Operación
F68: Ingresos (t) | G68: Egresos (t) | I68: Desembarque (t) | J68: Saldo (t) | K68: % consumido
A69: INDUSTRIALES | B69: BLUE OCEAN SEAFOOD | C69: 10.31 | D69: 137.845 | G69: 137.845 | H69: 0 | J69: 0 | K69: =+I69/H69 -> #DIV/0!
B70: DERIS S.A. | C70: 19.315 | D70: 258.242 | F70: 39.712 | H70: 297.954 | I70: 292.386 | J70: 5.568 | K70: =+I70/H70 -> 0.98131255
B71: PESCA CISNE | C71: 7.5 | D71: 100.275 | F71: 137.845 | G71: 27.693 | H71: 210.427 | I71: 209.316 | J71: 1.111 | K71: =+I71/H71 -> 0.99472026 | N71: ahora
B72: GLOBALPESCA S.P.A. | C72: 47.875 | D72: 640.089 | F72: 9.88 | G72: 34.899 | H72: 615.07 | I72: 614.999 | J72: 0.071 | K72: =+I72/H72 -> 0.99988457 | L72: =SUM(I69:I72) -> 1116.701 | N72: 1116.7
A73: ARTESANALES | B73: DANIEL MOLINA CISTERNAS | C73: 1.5 | D73: 20.055 | H73: 20.055 | I73: 19.64 | J73: 0.415 | K73: =+I73/H73 -> 0.97930691
B74: D. CISTERNAS G. | C74: 0.5 | D74: 6.685 | H74: 6.685 | I74: 6.87 | J74: -0.185 | K74: =+I74/H74 -> 1.0276739
B75: B. CEBALLOS MANCILLA | C75: 1 | D75: 13.37 | H75: 13.37 | I75: 13.165 | J75: 0.205 | K75: =+I75/H75 -> 0.98466717
B76: PESQUERA FRAPOLI S.A. | C76: 1 | D76: 13.37 | F76: 1.702 | H76: 15.072 | I76: 14.607 | J76: 0.465 | K76: =+I76/H76 -> 0.96914809
B77: JOSE ACEVEDO CORNEJO | C77: 0.5 | D77: 6.685 | H77: 6.685 | I77: 6.551 | J77: 0.134 | K77: =+I77/H77 -> 0.97995512
B78: ROBERTO GONZALEZ NAVARRO | C78: 2.5 | D78: 33.425 | F78: 13 | H78: 46.425 | I78: 40.684 | J78: 5.741 | K78: =+I78/H78 -> 0.87633818
B79: PAOLA MORA BURGOS | C79: 2.5 | D79: 33.425 | G79: 33.425 | H79: 0 | J79: 0 | K79: =+I79/H79 -> #DIV/0!
B80: TOMAS NEIRA PARRA | C80: 1 | D80: 13.37 | F80: 13.37 | G80: 17.507 | H80: 9.233 | I80: 9.233 | J80: 0 | K80: =+I80/H80 -> 1
B81: BOLIVAR GUZMAN ACUÑA | C81: 1.5 | D81: 20.055 | G81: 20.055 | H81: 0 | J81: 0 | K81: =+I81/H81 -> #DIV/0!
B82: RAUL GONZALEZ HURTADO | C82: 1 | D82: 13.37 | F82: 4.404 | H82: 17.774 | I82: 10.583 | J82: 7.191 | K82: =+I82/H82 -> 0.59542028
B83: A. POBLETE ARAVENA | C83: 1 | D83: 13.37 | G83: 13.37 | H83: 0 | J83: 0 | K83: =+I83/H83 -> #DIV/0!
B84: JUAN JOSE GUZMAN ROJAS | C84: 1 | D84: 13.37 | F84: 20.055 | G84: 1.702 | H84: 31.723 | I84: 31.723 | J84: 0 | K84: =+I84/H84 -> 1
B85: MIGUEL SERVANDO SILVA SILVA | C85: 0 | D85: 0 | F85: 6.418 | H85: 6.418 | I85: 6.166 | J85: 0.252 | K85: =+I85/H85 -> 0.96073543
B86: ELSA DEL ROSARIO NEIRA PARRA | C86: 0 | D86: 0 | F86: 6.685 | H86: 6.685 | I86: 7.127 | J86: -0.442 | K86: =+I86/H86 -> 1.0661182 | N86: ahora
B87: JOSE MORA MOYA | C87: 0 | D87: 0 | F87: 33.425 | H87: 33.425 | I87: 25.759 | J87: 7.666 | K87: =+I87/H87 -> 0.77065071 | L87: =SUM(I73:I87) -> 192.108 | N87: 185.041
B89: Resumen | C89: % Licitado | D89: Cuota licitada (t) | E89: Sanción (t) | F89: Transferencias | H89: Cuota efectiva (t) | I89: Operación
B90: Bacalao de profundidad | F90: Ingresos (t) | G90: Egresos (t) | I90: Desembarque (t) | J90: Saldo (t) | K90: % consumido
C91: =SUM(C69:C87) -> 100 | D91: =SUM(D69:D87) -> 1337.001 | E91: =SUM(E69:E87) -> 0 | F91: =SUM(F69:F87) -> 286.496 | G91: =SUM(G69:G87) -> 286.496 | H91: =SUM(H69:H87) -> 1337.001 | I91: =SUM(I69:I87) -> 1308.809 | J91: =SUM(J69:J87) -> 28.192 | K91: =+I91/H91 -> 0.978914 | L91: =L72+L87 -> 1308.809 | M91: =M72+M87 -> 0 | N91: =N72+N87 -> 1301.741

Sheet Cuotas Globales 
A2: Cuotas globales Sin LTP (en conjunto con artesanales), 2015
A3: Al 31 de diciembre de 2015
A5: Cuotas globales Fuera Unidad de Pesquería
A6: Unidad de Pesquería | B6: Fracción | C6: Cuota Global asignada (t) | D6: Cuota Período | G6: Desembarque total (t) | H6: Saldo (t) | I6: % Consumo | J6: Fecha cierre | K6: Desembarques
D7: Período | E7: autorizada | F7: efectiva | K7: Industrial | L7: Artesanal
A8: Merluza común | B8: Objetivo | C8: 40 | D8: Ene- Dic. | E8: 40 | F8: =+E8 -> 40 | G8: =K8+L8 -> 4.741 | H8: =+F8-G8 -> 35.259 | I8: =G8/F8 -> 0.118525 | K8: 0.006 | L8: 4.735
A9: Merluza de cola | B9: Objetivo | D9: Ene -Dic. | F9: =+E9 -> 0 | H9: =+F9-G9 -> 0 | I9: =G9/F9 -> #DIV/0!
B10: F. Acompañante | F10: =+E10 -> 0 | I10: 0
A11: Merluza del sur | B11: Objetivo | C11: 108 | D11: Ene -Dic. | E11: 108 | F11: =+E11 -> 108 | G11: =K11+L11 -> 355.046 | H11: =+F11-G11 -> -247.046 | I11: =G11/F11 -> 3.287463 | J11: 42030 | K11: 355.046
B12: F. Acompañante | I12: 0 | K12: 9.779 | L12: 0.016
A13: Langostino amarillo | B13: Objetivo (XV-I-II-IX-XIV-X) | C13: =E13 -> 7 | D13: Ene -Dic. | E13: 7 | F13: =+E13 -> 7 | G13: =K13+L13 -> 0 | H13: =+F13-G13 -> 7 | I13: =G13/F13 -> 0 | K13: 0 | L13: 0
B14: F. Acompañante | C14: =E14 -> 13 | E14: 13 | F14: =+E14 -> 13 | I14: 0
A15: Camarón nailon | B15: Objetivo (XV-I-IX-XIV-X) | C15: =E15 -> 10 | D15: Ene -Dic. | E15: 10 | F15: =+E15 -> 10 | G15: =K15+L15 -> 0 | H15: =+F15-G15 -> 10 | I15: =G15/F15 -> 0 | K15: 0 | L15: 0
B16: F. Acompañante | C16: =E16 -> 10 | E16: 10 | F16: =+E16 -> 10 | I16: 0
A17: Langostino colorado | B17: Objetivo (IX-XIV-X) | C17: =E17 -> 5 | D17: Ene -Dic. | E17: 5 | F17: =+E17 -> 5 | G17: =K17+L17 -> 0.013 | H17: =+F17-G17 -> 4.987 | I17: =G17/F17 -> 0.0026 | K17: 0 | L17: 0.013
B18: F. Acompañante | C18: =E18 -> 7 | E18: 7 | F18: =+E18 -> 7
A19: Congrio Dorado | B19: V Región | C19: 7 | D19: Enero-Junio | E19: 3 | F19: 3 | G19: =K19+L19 -> 0.505 | H19: =+F19-G19 -> 2.495 | I19: =G19/F19 -> 0.16833333 | L19: 0.505
D20: Julio-Diciembre | E20: 3 | F20: 3 | G20: =K20+L20 -> 0.571 | H20: =+F20-G20 -> 2.429 | I20: =G20/F20 -> 0.19033333 | K20: 0.024 | L20: 0.547
D21: F. Acompañante | E21: 1 | F21: 1 | G21: =K21+L21 -> 0 | H21: =+F21-G21 -> 1 | I21: =G21/F21 -> 0
B22: VI Región | C22: 7 | D22: Enero-Junio | E22: 3 | F22: 3 | H22: =+F22-G22 -> 3 | I22: =G22/F22 -> 0
D23: Julio-Diciembre | E23: 3 | F23: 3 | G23: =K23+L23 -> 0.1 | H23: =+F23-G23 -> 2.9 | I23: =G23/F23 -> 0.033333333 | L23: 0.1
D24: F. Acompañante | E24: 1 | F24: 1 | I24: =G24/F24 -> 0
B25: VII Región | C25: 7 | D25: Enero-Junio | E25: 3 | F25: 3 | G25: =K25+L25 -> 0.51 | H25: =+F25-G25 -> 2.49 | I25: =G25/F25 -> 0.17 | L25: 0.51
D26: Julio-Diciembre | E26: 3 | F26: 3 | H26: =+F26-G26 -> 3 | I26: =G26/F26 -> 0
D27: F. Acompañante | E27: 1 | F27: 1 | I27: =G27/F27 -> 0
B28: VIII Región | C28: 40 | D28: Enero-Junio | E28: 18 | F28: =E28 -> 18 | G28: =K28+L28 -> 18.401 | H28: =+F28-G28 -> -0.401 | I28: =G28/F28 -> 1.0222778 | J28: 42030 | L28: 18.401
D29: Julio-Diciembre | E29: 18 | F29: =E29+H28 -> 17.599 | G29: =K29+L29 -> 19.162 | H29: =+F29-G29 -> -1.563 | I29: =G29/F29 -> 1.0888119 | J29: 42362 | L29: 19.162
D30: F. Acompañante | E30: 4 | F30: =E30 -> 4 | G30: =K30+L30 -> 0.171 | H30: =+F30-G30 -> 3.829 | I30: =G30/F30 -> 0.04275 | L30: 0.171
B31: IX Región | C31: 7 | D31: Enero-Junio | E31: 3 | F31: 3 | H31: =+F31-G31 -> 3 | I31: =G31/F31 -> 0
D32: Julio-Diciembre | E32: 3 | F32: 3 | H32: =+F32-G32 -> 3 | I32: =G32/F32 -> 0
D33: F. Acompañante | E33: 1 | F33: 1 | I33: =G33/F33 -> 0
B34: XIV Región | C34: 41 | D34: Enero-Junio | E34: 19 | F34: 19 | G34: =K34+L34 -> 18.704 | H34: =+F34-G34 -> 0.296 | I34: =G34/F34 -> 0.98442105 | J34: 42087 | L34: 18.704
D35: Julio-Diciembre | E35: 18 | F35: 18 | G35: =K35+L35 -> 20.084 | H35: =+F35-G35 -> -2.084 | I35: =G35/F35 -> 1.1157778 | J35: 42333 | L35: 20.084
D36: F. Acompañante | E36: 4 | F36: 4 | I36: =G36/F36 -> 0
B37: X Región (al norte del 41º28,6´S) | C37: 7 | D37: Enero-Junio | E37: 3 | F37: =E37 -> 3 | G37: =K37+L37 -> 0.03 | H37: =+F37-G37 -> 2.97 | I37: =G37/F37 -> 0.01 | K37: 0.03
D38: Julio-Diciembre | E38: 3 | F38: =E38+H37 -> 5.97 | G38: =K38+L38 -> 0 | H38: =+F38-G38 -> 5.97 | I38: =G38/F38 -> 0
D39: F. Acompañante | E39: 1 | F39: =E39 -> 1 | G39: =K39+L39 -> 0 | H39: =+F39-G39 -> 1 | I39: =G39/F39 -> 0
B40: Investigación | C40: 2 | D40: Ene-Dic. | E40: 2 | F40: 2
A43: Recursos sin cuota
A44: Unidad de Pesquería | B44: Cuota | C44: Período | D44: Sector | F44: Desem. (ton) | G44: Total Desem. (ton)
A45: Caballa XV-XII | B45: S/cuota | C45: enero - diciembre | D45: Artesanal | F45: 25302.232 | G45: =+SUM(F45:F46) -> 45445.927
D46: Industrial | F46: 20143.695
A47: Pez espada XV-XII | B47: S/cuota | C47: enero - diciembre | D47: Artesanal | F47: 5889.504 | G47: =+SUM(F47:F48) -> 6033.142
D48: Industrial | F48: 143.638
A49: Reineta | B49: S/cuota | C49: enero - diciembre | D49: Artesanal | F49: 29544.113 | G49: =F49+F50 -> 34045.687
D50: Industrial | F50: 4501.574
A52: Recursos con cuota Global
A53: Unidad de Pesquería | B53: Fracción | C53: Cuota asignada (t) | D53: Período | E53: Sector | G53: Desem. (ton) | H53: Total Desem. (ton) | J53: Saldo | K53: Fecha de Cierre | L53: % CONSUMO | M53: Fecha de Cierre
A54: Jibia o calamar rojo XV-XII | B54: Investigación | C54: 1000 | D54: Ene Dic | E54: Artesanal e industrial | G54: 0 | H54: =G56+G55+G54+G57 -> 143445.82 | J54: =C54-G54 -> 1000 | L54: =G54/C54 -> 0
B55: F. Acompañante | C55: 1576 | E55: Artesanal | G55: 18.276 | J55: =C55-G55 -> 1557.724 | L55: =G55/C55 -> 0.011596447
B56: Artesanal | C56: 156024 | E56: Artesanal | G56: 103979 | J56: =C56-G56 -> 52045 | L56: =G56/C56 -> 0.66642952
B57: Industrial | C57: 39400 | E57: Industrial | G57: 39448.541 | J57: =C57-G57 -> -48.541 | L57: =G57/C57 -> 1.001232 | M57: 42099
A58: Bacalao de profundidad D ex. N°816-14 | B58: XV hasta paralelo 47º LS | C58: 982 | D58: Ene- Dic. | E58: Artesanal | G58: 1047.659 | H58: 1047.659 | J58: =C58-H58 -> -65.659 | L58: =G58/C58 -> 1.0668625 | M58: 42114
A59: Bacalao de profundidad D ex. N°862-15 (modif. D ex.N°816-14) | B59: XV hasta paralelo 47º LS | C59: 229 | D59: Nov - Dic | E59: Artesanal | G59: 373.326 | H59: 373.326 | J59: =C59-H59 -> -144.326 | L59: =G59/C59 -> 1.6302445 | M59: 42328
A62: Veda Extractiva Raya Volantin y Raya Espinosa D.Ex.N°21 de 22/01/2014
A63: Unidad de Pesquería | B63: Sector | C63: Período | D63: Fraccionamiento | F63: Cuota (t) | G63: Desembarques | I63: Saldo | J63: Cuota Total(t) | K63: Total Desembarque (ton) | L63: Saldo | M63: % CONSUMO | N63: Fecha de Cierre
G64: Industrial | H64: Artesanal
A65: Raya Volantín | B65: Artesanal e industrial | C65: 16 Ene-30 Nov | D65: IV-VII | E65: Merluza común/Arrastre/1% | F65: 14 | G65: 0 | H65: 0.112 | I65: =F65-G65-H65 -> 13.888 | J65: =SUM(+F65+F66+F67) -> 22 | K65: =G65+H65+G66+H66+G67+H67 -> 0.672 | L65: =SUM(J65-K65) -> 21.328 | M65: =K65/J65 -> 0.030545455
E66: Congrio dorado/Espinel/1% | F66: 2 | G66: 0 | H66: 0 | I66: =F66-G66-H66 -> 2
E67: Crustáceos demersales/Arrastre/1% | F67: 6 | G67: =0.394+0.011+0.007+0.023+0.105 -> 0.54 | H67: 0.02 | I67: =F67-G67-H67 -> 5.44
D68: VIII-41º28,6´LS | E68: Merluza común/Arrastre/1% | F68: 14 | G68: 0.279 | H68: 0 | I68: =F68-G68-H68 -> 13.721 | J68: =SUM(F68+F69+F70) -> 36 | K68: =SUM(G68+H68+G69+H69+G70+H70) -> 0.513 | L68: =SUM(J68-K68) -> 35.487 | M68: =K68/J68 -> 0.01425
E69: Congrio dorado/Espinel/1% | F69: 20 | G69: 0 | H69: =0.082+0.001+0.12+0.031 -> 0.234 | I69: =F69-G69-H69 -> 19.766
E70: Crustáceos demersales/Arrastre/1% | F70: 2 | G70: 0 | H70: 0 | I70: =F70-G70-H70 -> 2
A71: Raya Espinosa | B71: Artesanal e industrial | C71: 16 Ene-30 Nov | D71: IV-VII | E71: Merluza común/Arrastre/1% | F71: 7 | G71: 0.039 | H71: 0 | I71: =F71-G71-H71 -> 6.961 | J71: =SUM(+F71+F72+F73) -> 11 | K71: =G71+G72+G73+H71+H72+H73 -> 0.04 | L71: =SUM(J71-K71) -> 10.96 | M71: =K71/J71 -> 0.0036363636
E72: Congrio dorado/Espinel/1% | F72: 1 | G72: 0 | H72: 0.001 | I72: =F72-G72-H72 -> 0.999
E73: Crustáceos demersales/Arrastre/1% | F73: 3 | G73: 0 | H73: 0 | I73: =F73-G73-H73 -> 3
D74: VIII-41º28,6´LS | E74: Merluza común/Arrastre/1% | F74: 7 | G74: =5.652+0.469 -> 6.121 | H74: 0 | I74: =F74-G74-H74 -> 0.879 | J74: =SUM(F74+F75+F76) -> 20 | K74: =G74+G75+G76+H74+H75+H76 -> 6.121 | L74: =SUM(J74-K74) -> 13.879 | M74: =K74/J74 -> 0.30605
E75: Congrio dorado/Espinel/1% | F75: 10 | G75: 0 | H75: 0 | I75: =F75-G75-H75 -> 10
E76: Crustáceos demersales/Arrastre/1% | F76: 3 | G76: 0 | H76: 0 | I76: =F76-G76-H76 -> 3
A79: Veda Extractiva Raya Volantin y Raya Espinosa D.Ex.N°113 de 2013; Modif por N°367-2013; N°501-2013; N°527-2013; N°20-2014
A80: Unidad de Pesquería | B80: Período | C80: Sector | D80: Fraccionamiento | F80: Cuota (t) | G80: Desembarques | H80: Saldo | I80: Cuota Total(t) | J80: Total Desem. (ton) | K80: Saldo | L80: % CONSUMO | M80: Fecha de Cierre
A82: Raya Volantín | B82: 2013-2015 | C82: Artesanal | D82: 41º28,6´LS - XII | E82: Merluza del sur/Espinel/1% | F82: 2 | G82: 0.302 | H82: =F82-G82 -> 1.698 | I82: =F82+F84+F83 -> 46 | J82: =G82+G84+G83 -> 7.686 | K82: =I82-J82 -> 38.314 | L82: =J82/I82 -> 0.16708696
C83: Artesanal | E83: Congrio dorado/Espinel/20% | F83: 30 | G83: =5.963+0.283+0.294+0.387+0.139 -> 7.066 | H83: =F83-G83 -> 22.934
C84: Industrial | E84: Merluza del Sur y Congrio dorado/1% | F84: 14 | G84: 0.318 | H84: =F84-G84 -> 13.682
A85: Raya Espinosa | B85: 2013-2015 | C85: Artesanal | D85: 41º28,6´LS - XII | E85: Merluza del sur/Espinel/1% | F85: 1 | G85: 0 | H85: =F85-G85 -> 1 | I85: =F85+F87+F86 -> 18 | J85: =G85+G87+G86 -> 0.717 | K85: =I85-J85 -> 17.283 | L85: =J85/I85 -> 0.039833333
C86: Artesanal | E86: Congrio dorado/Espinel/20% | F86: 10 | G86: 0.003 | H86: =F86-G86 -> 9.997
C87: Industrial | E87: Merluza del Sur y Congrio dorado/1% | F87: 7 | G87: 0.714 | H87: =F87-G87 -> 6.286
B90: Desembarque de Besugo como Fauna Acompañante
A91: Armador | B91: De Esp Ob. Crustaceos demersales | C91: De Esp. Obj. Peces arrastre | D91: De Esp. Obj. Peces palangre | E91: Total
A92: Baycic Baycic Maria | E92: =B92+C92+D92 -> 0
A93: Congelados del Pacifico | C93: 1.246 | E93: =B93+C93+D93 -> 1.246
A94: Blumar S.A. | E94: =B94+C94+D94 -> 0
A95: Bracpesca S.A. | E95: =B95+C95+D95 -> 0
A96: Concepción S.A. | E96: =B96+C96+D96 -> 0
A97: Grimar | E97: =B97+C97+D97 -> 0
A98: Isladamas S.A. | E98: =B98+C98+D98 -> 0
A99: Morozin Yurecic Mario | E99: =B99+C99+D99 -> 0
A100: Quintero Ltda. | E100: =B100+C100+D100 -> 0
A101: Quintero S.A. Pesq. | B101: 0.132 | E101: =B101+C101+D101 -> 0.132
A102: Pesca Chile | E102: =B102+C102+D102 -> 0
A103: Total | B103: =SUM(B92:B102) -> 0.132 | C103: =SUM(C92:C101) -> 1.246 | D103: =SUM(D92:D101) -> 0 | E103: =SUM(E92:E102) -> 1.378

Sheet PI
C4: Pesca de Investigación: Resolucion Nº 1920. Del 15.07.15 al 30.12.15
C5: Zona | D5: Imputa a reserva de Inv. | E5: Cuota (ton) | F5: Desembarque (ton) | G5: Saldo
B6: Langostino amarillo | C6: III-IV | D6: Dec. Nº 953/2014 | E6: 35 | F6: 0 | G6: =E6-F6 -> 35
C7: V-VIII | D7: Dec. Nº 790/2014 | E7: 25 | F7: 12.354 | G7: =E7-F7 -> 12.646
B8: Langostino colorado | C8: XV-IV | D8: Dec. Nº 953/2014 | E8: 15 | F8: 0 | G8: =E8-F8 -> 15
C9: V-VIII | D9: Dec. Nº 791/2014 | E9: 50 | F9: 28.245 | G9: =E9-F9 -> 21.755
B10: Merluza Común | C10: IV-VIII | D10: Dec. Nº 958/2014 | E10: 15 | F10: 1.494 | G10: =E10-F10 -> 13.506
B11: Camaron nailón | C11: II-VIII | D11: Dec. Nº 953/2014 | E11: 25 | F11: 10.142 | G11: =E11-F11 -> 14.858

Sheet Hoja1
D2: =+C2*B2 -> 0
D3: =+C3*B3 -> 0
