Workbook

Sheet Resumen LTP-PEP
C2: Informe
C3: Resumen Cuotas LTP 2016
C4: actualizado al 27-01-2017
C6: Unidad de Pesquería | D6: Zona | E6: D.Ex. Establece cuota | F6: D.Ex. Modifica cuota | G6: Cuota Asignada Sector Industrial | H6: Cuota LTP Asignada con sus Modificaciones | I6: Transferencias de Cuotas | J6: Cuota Efectiva | K6: Desembarque total (t) | L6: Aguas internacionales | M6: Saldo total (t) | N6: % consumido 2016
B7: Peces Pelágicos | C7: Anchoveta | D7: XV- I - II | E7: 1185/22-12-15 | G7: 636926 | H7: =SUM('Pelagicos LTP '!E6:E11) -> 636926 | I7: =SUM('Pelagicos LTP '!F6:F11) -> -4530.964 | J7: =H7+I7 -> 632395.04 | K7: =SUM('Pelagicos LTP '!H6:H11) -> 152165.06 | M7: =J7-K7 -> 480229.97 | N7: =K7/J7 -> 0.24061711
C8: Anchoveta | D8: III - IV | E8: 1184/22-12-15 | F8: 474/17-06-16 | G8: 12790 | H8: =SUM('Pelagicos LTP '!E14:E29) -> 17265 | I8: =SUM('Pelagicos LTP '!F14:F31) -> -12467.402 | J8: =H8+I8 -> 4797.598 | K8: =SUM('Pelagicos LTP '!H14:H31) -> 0 | M8: =J8-K8 -> 4797.598 | N8: =K8/J8 -> 0
C9: Anchoveta | D9: V - X | E9: 943/11-11-15 | F9: 346/09-05-16 | G9: 7388 | H9: =SUM('Pelagicos LTP '!E34:E93) -> 8573.998 | I9: =SUM('Pelagicos LTP '!F34:F93) -> -2138.553 | J9: =H9+I9 -> 6435.445 | K9: =SUM('Pelagicos LTP '!H34:H93) -> 5288.222 | M9: =J9-K9 -> 1147.223 | N9: =K9/J9 -> 0.8217337
C10: Sardina común | D10: V -X | E10: 943/11-11-15 | F10: 346/09-05-16 | G10: 61191.025 | H10: =SUM('Pelagicos LTP '!E99:E179) -> 70750.021 | I10: =SUM('Pelagicos LTP '!F99:F179) -> 15645.432 | J10: =H10+I10 -> 86395.453 | K10: =SUM('Pelagicos LTP '!H99:H179) -> 84377.544 | M10: =J10-K10 -> 2017.909 | N10: =K10/J10 -> 0.97664334 | Q10: IAN TAYLOR CHILE S.A. | R10: 2236.305
C11: Jurel | D11: XV - I - II | E11: 1142/18-12-15 | F11: 121/03-03-16 | G11: 43245.005 | H11: =SUM('Pelagicos LTP '!E183:E190) -> 41430.004 | I11: =SUM('Pelagicos LTP '!F183:F188) -> -15327.317 | J11: =H11+I11 -> 26102.687 | K11: =SUM('Pelagicos LTP '!H183:H188) -> 24199.027 | M11: =J11-K11 -> 1903.66 | N11: =K11/J11 -> 0.92707034
C12: Jurel | D12: III - IV | E12: 1142/18-12-15 | F12: 121/03-03-16 | G12: 9139 | H12: =SUM('Pelagicos LTP '!E193:E220) -> 8743.999 | I12: =SUM('Pelagicos LTP '!F193:F220) -> 2490.803 | J12: =H12+I12 -> 11234.802 | K12: =SUM('Pelagicos LTP '!H193:H220) -> 11038.451 | L12: =400+145 -> 545 | M12: =J12-K12 -> 196.351 | N12: =K12/J12 -> 0.98252297 | Q12: Rótulos de fila | R12: Suma de SumaDeSumaDeNr_Toneladas
C13: Jurel | D13: V - IX | E13: 1142/18-12-15 | F13: 121/03-03-16 | G13: 195598 | H13: =SUM('Pelagicos LTP '!E223:E288) -> 187555.01 | I13: =SUM('Pelagicos LTP '!F223:F288) -> 14063.417 | J13: =H13+I13 -> 201618.43 | K13: =SUM('Pelagicos LTP '!H223:H288) -> 200066.04 | L13: =467.273 -> 467.273 | M13: =J13-K13 -> 1552.384 | N13: =K13/J13 -> 0.99230039 | Q13: ALIMENTOS MARINOS S.A. | R13: 2191.783
C14: Jurel | D14: XIV - X | E14: 1142/18-12-15 | F14: 121/03-03-16 | G14: 27421.995 | H14: =SUM('Pelagicos LTP '!E291:E340) -> 26117.998 | I14: =SUM('Pelagicos LTP '!F291:F340) -> -2334.346 | J14: =H14+I14 -> 23783.652 | K14: =SUM('Pelagicos LTP '!H291:H340) -> 23260.74 | L14: 2146.783 | M14: =J14-K14 -> 522.912 | N14: =K14/J14 -> 0.97801381 | Q14: CAMANCHACA PESCA SUR S.A. | R14: 281.698
C15: Sardina española | D15: XV- I - II | E15: 1185/22-12-15 | G15: 742 | H15: =SUM('Pelagicos LTP '!E343:E348) -> 742 | I15: =SUM('Pelagicos LTP '!F343:F348) -> 0 | J15: =H15+I15 -> 742 | K15: =SUM('Pelagicos LTP '!H343:H348) -> 0 | M15: =J15-K15 -> 742 | N15: =K15/J15 -> 0 | Q15: Total general | R15: 4709.786
C16: Sardina española | D16: III - IV | E16: 1184/22-12-15 | G16: 875.002 | H16: =SUM('Pelagicos LTP '!E351:E368) -> 875.002 | I16: =SUM('Pelagicos LTP '!F351:F368) -> -100 | J16: =H16+I16 -> 775.002 | K16: =SUM('Pelagicos LTP '!H351:H366) -> 0 | M16: =J16-K16 -> 775.002 | N16: =K16/J16 -> 0
B17: Peces Demersales | C17: Congrio dorado | D17: paralelo 41° 28,6’ - 47° L.S. | E17: 1186/22-12-15 | G17: 418.501 | H17: =SUM('Demersales LTP '!E7:E16) -> 418.501 | I17: =SUM('Demersales LTP '!F7:F16) -> -33.432 | J17: =H17+I17 -> 385.069 | K17: =SUM('Demersales LTP '!H7:H16) -> 371.505 | M17: =J17-K17 -> 13.564 | N17: =K17/J17 -> 0.96477514
C18: Congrio dorado | D18: paralelo 47° - 57° L.S. | E18: 1186/22-12-15 | G18: 238 | H18: =SUM('Demersales LTP '!E21:E30) -> 238 | I18: =SUM('Demersales LTP '!F21:F30) -> 0 | J18: =H18+I18 -> 238 | K18: =SUM('Demersales LTP '!H21:H30) -> 226.948 | M18: =J18-K18 -> 11.052 | N18: =K18/J18 -> 0.95356303
C19: Merluza del sur | D19: paralelo 41° 28,6’ - 47° L.S. | E19: 1186/22-12-15 | F19: 645/25-08-16 | G19: 3937.961 | H19: =SUM('Demersales LTP '!E33:E48) -> 4313.001 | I19: =SUM('Demersales LTP '!F33:F48) -> 3591.581 | J19: =H19+I19 -> 7904.582 | K19: =SUM('Demersales LTP '!H33:H48) -> 7501.967 | M19: =J19-K19 -> 402.615 | N19: =K19/J19 -> 0.94906562
C20: Merluza del sur | D20: paralelo 47° - 57° L.S. | E20: 1186/22-12-15 | F20: 645/25-08-16 | G20: 2518 | H20: =SUM('Demersales LTP '!E51:E60) -> 2758.001 | I20: =SUM('Demersales LTP '!F51:F60) -> -14.013 | J20: =H20+I20 -> 2743.988 | K20: =SUM('Demersales LTP '!H51:H60) -> 2427.755 | M20: =J20-K20 -> 316.233 | N20: =K20/J20 -> 0.88475423
C21: Merluza de tres aletas | D21: paralelo 41º28,6´ - XII | E21: 1186/22-12-15 | G21: 11516 | H21: =SUM('Demersales LTP '!E63:E70) -> 11516 | I21: =SUM('Demersales LTP '!F63:F70) -> 0 | J21: =H21+I21 -> 11516 | K21: =SUM('Demersales LTP '!H63:H70) -> 8270.994 | M21: =J21-K21 -> 3245.006 | N21: =K21/J21 -> 0.71821761
C22: Merluza de cola | D22: V -X | E22: 1140/18-12-15 | G22: 24132.998 | H22: =SUM('Demersales LTP '!E73:E120) -> 24132.998 | I22: =SUM('Demersales LTP '!F73:F120) -> -8138.485 | J22: =H22+I22 -> 15994.513 | K22: =SUM('Demersales LTP '!H73:H116) -> 9407.792 | M22: =J22-K22 -> 6586.721 | N22: =K22/J22 -> 0.58818871
C23: Merluza de cola | D23: XI -XII | E23: 1140/18-12-15 | G23: 16088 | H23: =SUM('Demersales LTP '!E125:E136) -> 16087.423 | I23: =SUM('Demersales LTP '!F125:F136) -> 8138.081 | J23: =H23+I23 -> 24225.504 | K23: =SUM('Demersales LTP '!H125:H134) -> 18670.551 | M23: =J23-K23 -> 5554.953 | N23: =K23/J23 -> 0.77069815
C24: Merluza común | D24: IV- 41º 28, 6 | E24: 1186/22-12-15 | G24: 13542 | H24: =SUM('Demersales LTP '!E141:E194) -> 13542 | I24: =SUM('Demersales LTP '!F141:F194) -> 107.55371 | J24: =H24+I24 -> 13649.554 | K24: =SUM('Demersales LTP '!H141:H194) -> 13445.023 | M24: =J24-K24 -> 204.53071 | N24: =K24/J24 -> 0.98501557
B25: Crustáceos | C25: Camarón nailon | D25: II-VIII | E25: 945/11-11-15 | G25: 4405 | H25: 4405 | I25: =+'Crustaceos LTP'!AV52 -> 287.23528 | J25: =H25+I25 -> 4692.2353 | K25: =+'Crustaceos LTP'!AX52 -> 3855.7171 | M25: =J25-K25 -> 836.51822 | N25: =K25/J25 -> 0.82172287
C26: Langostino amarillo | D26: III-IV | E26: 945/11-11-15 | G26: 1482.004 | H26: 1482.004 | I26: =+'Crustaceos LTP'!X82 -> 467.3 | J26: =H26+I26 -> 1949.304 | K26: =+'Crustaceos LTP'!Z82 -> 1829.24 | M26: =J26-K26 -> 120.064 | N26: =K26/J26 -> 0.93840673
C27: Langostino colorado | D27: XV-IV | E27: 945/11-11-15 | F27: 147/15-03-16 | G27: 91.004 | H27: 169 | I27: =+'Crustaceos LTP'!X100 -> 129.99 | J27: =H27+I27 -> 298.99 | K27: =+'Crustaceos LTP'!Z100 -> 256.63 | M27: =J27-K27 -> 42.36 | N27: =K27/J27 -> 0.85832302
I29: =33.39-33.432 -> -0.042
C31: Nota: El desembarque de aguas internacionales (columna G) Jurel desde III a X regiones, esta incorporado en la columna de desembarque total. Solo se incorpora el dato en la columna G para tenerlo de referencia
C34: Informe
C35: Resumen Cuotas PEP 2016
C38: Unidad de Pesquería | D38: Zona | E38: D.Ex. Establece cuota | F38: D.Ex. Modifica cuota | G38: Cuota PEP Asignada | H38: Cuota PEP Asignada con sus Modificaciones | I38: Cuota PEP Adjudicada | J38: Transferencias de Cuotas | K38: Cuota Efectiva | L38: Desembarque total (t) | M38: Saldo total (t) | N38: % consumido 2016
C39: Langostino amarillo | D39: V-VIII | E39: 944/11-11-15 | G39: 1830 | H39: =+'Cuotas Licitadas '!D13 -> 1830 | I39: =+'Cuotas Licitadas '!E39 -> 1830 | J39: ='Cuotas Licitadas '!F39 -> 818.08746 | K39: ='Cuotas Licitadas '!H39 -> 1830.0007 | L39: ='Cuotas Licitadas '!I39 -> 1785.373 | M39: =K39-L39 -> 44.627668 | N39: =L39/K39 -> 0.97561331
C40: Langostino colorado | D40: V-VIII | E40: 944/11-11-15 | F40: 148/15-03-16 | G40: 3130 | H40: ='Cuotas Licitadas '!D50 -> 4618 | I40: =+'Cuotas Licitadas '!E78 -> 4502.5501 | J40: =+'Cuotas Licitadas '!F78 -> 2104.0325 | K40: =+'Cuotas Licitadas '!H78 -> 4502.5501 | L40: =+'Cuotas Licitadas '!I78 -> 4428.684 | M40: =K40-L40 -> 73.866139 | N40: =L40/K40 -> 0.9835946
C41: Bacalao licitado | D41: 47° L.S. al 57° L.S. | E41: 946/11-11-15 | G41: 1636 | H41: =+'Cuotas Licitadas '!E87 -> 1636 | I41: =+'Cuotas Licitadas '!E116 -> 1635.9999 | J41: =+'Cuotas Licitadas '!F116 -> 89.595 | K41: =+'Cuotas Licitadas '!H116 -> 1635.9999 | L41: =+'Cuotas Licitadas '!I116 -> 1615.093 | M41: =K41-L41 -> 20.906889 | N41: =L41/K41 -> 0.98722073

Sheet Pelagicos LTP 
A1: Cuotas LTP Recursos Pelágicos Año 2016 actualizado al 27-01-2017
C4: Periodo | E4: CUOTA (TONELADAS) | H4: OPERACIÓN | K4: RESUMEN ANUAL
A5: Unidad de pesquería | B5: Titular de cuota LTP | C5: Inicial | D5: Final | E5: Cuota Asignada por R. Ex N°3520-15 y Mod | F5: Traspaso, Cesion, Arriendo, etc) | G5: Cuota Efectiva | H5: captura (t) | I5: Saldo (t) | J5: % consumido | K5: Cuota asignada (t) | L5: Traspaso, Cesion, Arriendo, etc) | M5: Cuota Efectiva | N5: Captura (t) | O5: Saldo (t) | P5: % consumido
A6: Anchoveta XV - I - II | B6: ARICA SEAFOOD PRODUCER S.A. | C6: 42005 | D6: 42185 | E6: 3398.22 | G6: =E6+F6 -> 3398.22 | I6: =G6-H6 -> 3398.22 | J6: =H6/G6 -> 0 | K6: =E6+E7 -> 4530.965 | L6: =F6+F7 -> -4530.964 | M6: =K6+L6 -> 0.001 | N6: =H6+H7 -> 0 | O6: =M6-N6 -> 0.001 | P6: =N6/M6 -> 0
C7: 42186 | D7: 42369 | E7: 1132.745 | F7: =-4530.964 -> -4530.964 | G7: =E7+F7+I6 -> 0.001 | I7: =G7-H7 -> 0.001 | J7: =H7/G7 -> 0
B8: CAMANCHACA S.A. CIA. PESQ | C8: 42005 | D8: 42185 | E8: 94287.815 | G8: =+E8+F8 -> 94287.815 | H8: 16244.86 | I8: =G8-H8 -> 78042.955 | J8: =H8/G8 -> 0.17229013 | K8: =E8+E9 -> 125717.22 | L8: =F8+F9 -> 0 | M8: =K8+L8 -> 125717.22 | N8: =H8+H9 -> 29997.803 | O8: =M8-N8 -> 95719.415 | P8: =N8/M8 -> 0.23861332
C9: 42186 | D9: 42369 | E9: 31429.403 | G9: =E9+F9+I8 -> 109472.36 | H9: 13752.943 | I9: =G9-H9 -> 95719.415 | J9: =H9/G9 -> 0.12562937
B10: CORPESCA S.A | C10: 42005 | D10: 42185 | E10: 380007.97 | G10: =E10+F10 -> 380007.97 | H10: 89313.017 | I10: =G10-H10 -> 290694.95 | J10: =H10/G10 -> 0.23502933 | K10: =E10+E11 -> 506677.82 | L10: =F10+F11 -> 0 | M10: =K10+L10 -> 506677.82 | N10: =H10+H11 -> 122167.26 | O10: =M10-N10 -> 384510.56 | P10: =N10/M10 -> 0.24111429
C11: 42186 | D11: 42369 | E11: 126669.85 | G11: =E11+F11+I10 -> 417364.8 | H11: 32854.243 | I11: =G11-H11 -> 384510.56 | J11: =H11/G11 -> 0.078718289
K12: =SUM(K6:K11) -> 636926 | L12: =SUM(L6:L11) -> -4530.964 | M12: =SUM(M6:M11) -> 632395.04 | N12: =SUM(N6:N11) -> 152165.06 | O12: =SUM(O6:O11) -> 480229.97 | P12: =+N12/M12 -> 0.24061711
A14: Anchoveta III - IV. | B14: ALIMENTOS MARINOS S.A. | C14: 42005 | D14: 42308 | E14: 1080.547 | G14: =E14+F14 -> 1080.547 | I14: =G14-H14 -> 1080.547 | J14: =H14/G14 -> 0 | K14: =E14+E15 -> 1137.401 | L14: =F14+F15 -> 0 | M14: =K14+L14 -> 1137.401 | N14: =H14+H15 -> 0 | O14: =M14-N14 -> 1137.401 | P14: =N14/M14 -> 0
C15: 42309 | D15: 42369 | E15: 56.854 | G15: =E15+F15+I14 -> 1137.401 | I15: =G15-H15 -> 1137.401 | J15: =H15/G15 -> 0
B16: BAHIA CALDERA S.A. PESQ. | C16: 42005 | D16: 42308 | E16: 8055.856 | F16: =-3554.512-2147.89 -> -5702.402 | G16: =E16+F16 -> 2353.454 | I16: =G16-H16 -> 2353.454 | J16: =H16/G16 -> 0 | K16: =E16+E17 -> 8479.719 | L16: =F16+F17 -> -5702.402 | M16: =K16+L16 -> 2777.317 | N16: =H16+H17 -> 0 | O16: =M16-N16 -> 2777.317 | P16: =N16/M16 -> 0
C17: 42309 | D17: 42369 | E17: 423.863 | G17: =E17+F17+I16 -> 2777.317 | I17: =G17-H17 -> 2777.317 | J17: =H17/G17 -> 0
B18: BLUMAR S.A. | C18: 42005 | D18: 42308 | E18: 62.332 | F18: =-2727.319+2727.319 -> 0 | G18: =E18+F18 -> 62.332 | I18: =G18-H18 -> 62.332 | J18: =H18/G18 -> 0 | K18: =E18+E19 -> 65.612 | L18: =F18+F19 -> 0 | M18: =K18+L18 -> 65.612 | N18: =H18+H19 -> 0 | O18: =M18-N18 -> 65.612 | P18: =N18/M18 -> 0
C19: 42309 | D19: 42369 | E19: 3.28 | G19: =E19+F19+I18 -> 65.612 | I19: =G19-H19 -> 65.612 | J19: =H19/G19 -> 0
B20: CAMANCHACA S.A. CIA. PESQ | C20: 42005 | D20: 42308 | E20: 14.926 | G20: =E20+F20 -> 14.926 | I20: =G20-H20 -> 14.926 | J20: =H20/G20 -> 0 | K20: =E20+E21 -> 15.711 | L20: =F20+F21 -> 0 | M20: =K20+L20 -> 15.711 | N20: =H20+H21 -> 0 | O20: =M20-N20 -> 15.711 | P20: =N20/M20 -> 0
C21: 42309 | D21: 42369 | E21: 0.785 | G21: =E21+F21+I20 -> 15.711 | I21: =G21-H21 -> 15.711 | J21: =H21/G21 -> 0
B22: INVERSIONES PESQUERAS SpA | C22: 42005 | D22: 42308 | E22: 187.406 | F22: -187.403 | G22: =E22+F22 -> 0.003 | I22: =G22-H22 -> 0.003 | J22: =H22/G22 -> 0 | K22: =E22+E23 -> 197.266 | L22: =F22+F23 -> -187.403 | M22: =K22+L22 -> 9.863 | N22: =H22+H23 -> 0 | O22: =M22-N22 -> 9.863 | P22: =N22/M22 -> 0
C23: 42309 | D23: 42369 | E23: 9.86 | G23: =E23+F23+I22 -> 9.863 | I23: =G23-H23 -> 9.863 | J23: =H23/G23 -> 0
B24: ORIZON S.A | C24: 42005 | D24: 42308 | E24: 6949.604 | F24: -6765 | G24: =E24+F24 -> 184.604 | I24: =G24-H24 -> 184.604 | J24: =H24/G24 -> 0 | K24: =E24+E25 -> 7315.261 | L24: =F24+F25 -> -6765 | M24: =K24+L24 -> 550.261 | N24: =H24+H25 -> 0 | O24: =M24-N24 -> 550.261 | P24: =N24/M24 -> 0
C25: 42309 | D25: 42369 | E25: 365.657 | G25: =E25+F25+I24 -> 550.261 | I25: =G25-H25 -> 550.261 | J25: =H25/G25 -> 0
B26: CAMANCHACA PESCA SUR S.A. | C26: 42005 | D26: 42308 | E26: 49.526 | G26: =E26+F26 -> 49.526 | I26: =G26-H26 -> 49.526 | J26: =H26/G26 -> 0 | K26: =E26+E27 -> 52.132 | L26: =F26+F27 -> 0 | M26: =K26+L26 -> 52.132 | N26: =H26+H27 -> 0 | O26: =M26-N26 -> 52.132 | P26: =N26/M26 -> 0
C27: 42309 | D27: 42369 | E27: 2.606 | G27: =E27+F27+I26 -> 52.132 | I27: =G27-H27 -> 52.132 | J27: =H27/G27 -> 0
B28: LANDES S.A. SOC. PESQ. | C28: 42005 | D28: 42308 | E28: 1.803 | G28: =E28+F28 -> 1.803 | I28: =G28-H28 -> 1.803 | J28: =H28/G28 -> 0 | K28: =E28+E29 -> 1.898 | L28: =F28+F29 -> 0 | M28: =K28+L28 -> 1.898 | N28: =H28+H29 -> 0 | O28: =M28-N28 -> 1.898 | P28: =N28/M28 -> 0
C29: 42309 | D29: 42369 | E29: 0.095 | G29: =E29+F29+I28 -> 1.898 | I29: =G29-H29 -> 1.898 | J29: =H29/G29 -> 0
B30: PESQUERA LITORAL SpA | C30: 42005 | D30: 42308 | E30: 0 | F30: 187.403 | G30: =E30+F30 -> 187.403 | I30: =G30-H30 -> 187.403 | J30: =H30/G30 -> 0 | K30: =E30+E31 -> 0 | L30: =F30+F31 -> 187.403 | M30: =K30+L30 -> 187.403 | N30: =H30+H31 -> 0 | O30: =M30-N30 -> 187.403 | P30: =N30/M30 -> 0
C31: 42309 | D31: 42369 | E31: 0 | F31: 0 | G31: =E31+F31+I30 -> 187.403 | I31: =G31-H31 -> 187.403 | J31: =H31/G31 -> 0
K32: =SUM(K14:K29) -> 17265 | L32: =SUM(L14:L31) -> -12467.402 | M32: =SUM(M14:M31) -> 4797.598 | N32: =SUM(N14:N29) -> 0 | O32: =SUM(O14:O29) -> 4610.195 | P32: =+N32/M32 -> 0
M33: =+L32-M32 -> -17265
A34: Anchoveta V-X | B34: ALIMENTOS MARINOS S.A. | C34: 42005 | D34: 42124 | E34: 1362.899 | F34: =-469.505+44.339+35.36+71.045+196.135-411.22-157 -> -690.846 | G34: =E34+F34 -> 672.053 | I34: =G34-H34 -> 672.053 | J34: =H34/G34 -> 0 | K34: =E34+E35+E36 -> 1603.389 | L34: =F34+F35+F36 -> -690.846 | M34: =K34+L34 -> 912.543 | N34: =H34+H35+H36 -> 730.633 | O34: =M34-N34 -> 181.91 | P34: =N34/M34 -> 0.80065597
C35: 42125 | D35: 42247 | E35: 160.264 | G35: =E35+F35+I34 -> 832.317 | H35: 78.325 | I35: =G35-H35 -> 753.992 | J35: =H35/G35 -> 0.09410477
C36: 42248 | D36: 42369 | E36: 80.226 | G36: =E36+F36+I35 -> 834.218 | H36: 652.308 | I36: =G36-H36 -> 181.91 | J36: =H36/G36 -> 0.78193949
B37: BERTA ELENA LTDA. SOC. PESQ. | C37: 42005 | D37: 42124 | E37: 0 | F37: 0 | G37: =E37+F37 -> 0 | I37: =G37-H37 -> 0 | J37: =H37/G37 -> #DIV/0! | K37: =E37+E38+E39 -> 0 | L37: =F37+F38+F39 -> 0 | M37: =K37+L37 -> 0 | N37: =H37+H38+H39 -> 0 | O37: =M37-N37 -> 0 | P37: =N37/M37 -> #DIV/0!
C38: 42125 | D38: 42247 | E38: 0 | F38: 0 | G38: =E38+F38+I37 -> 0 | I38: =G38-H38 -> 0 | J38: =H38/G38 -> #DIV/0!
C39: 42248 | D39: 42369 | E39: 0 | F39: 0 | G39: =E39+F39+I38 -> 0 | I39: =G39-H39 -> 0 | J39: =H39/G39 -> #DIV/0!
B40: BLUMAR S.A. | C40: 42005 | D40: 42124 | E40: 1713.557 | F40: =-85-10-1100 -> -1195 | G40: =E40+F40 -> 518.557 | H40: 61.974 | I40: =G40-H40 -> 456.583 | J40: =H40/G40 -> 0.11951242 | K40: =E40+E41+E42 -> 2015.922 | L40: =F40+F41+F42 -> -1195 | M40: =K40+L40 -> 820.922 | N40: =H40+H41+H42 -> 567.191 | O40: =M40-N40 -> 253.731 | P40: =N40/M40 -> 0.69091948
C41: 42125 | D41: 42247 | E41: 201.498 | G41: =E41+F41+I40 -> 658.081 | H41: 147.945 | I41: =G41-H41 -> 510.136 | J41: =H41/G41 -> 0.22481275
C42: 42248 | D42: 42369 | E42: 100.867 | G42: =E42+F42+I41 -> 611.003 | H42: 357.272 | I42: =G42-H42 -> 253.731 | J42: =H42/G42 -> 0.58473035
B43: CAMANCHACA PESCA SUR S.A. | C43: 42005 | D43: 42124 | E43: 1128.256 | F43: =-35+34+85.98 -> 84.98 | G43: =E43+F43 -> 1213.236 | H43: 609.719 | I43: =G43-H43 -> 603.517 | J43: =H43/G43 -> 0.50255597 | K43: =E43+E44+E45 -> 1327.342 | L43: =F43+F44+F45 -> 84.98 | M43: =K43+L43 -> 1412.322 | N43: =H43+H44+H45 -> 1361.678 | O43: =M43-N43 -> 50.644 | P43: =N43/M43 -> 0.96414132
C44: 42125 | D44: 42247 | E44: 132.672 | G44: =E44+F44+I43 -> 736.189 | H44: 481.615 | I44: =G44-H44 -> 254.574 | J44: =H44/G44 -> 0.65420021
C45: 42248 | D45: 42369 | E45: 66.414 | G45: =E45+F45+I44 -> 320.988 | H45: 270.344 | I45: =G45-H45 -> 50.644 | J45: =H45/G45 -> 0.84222463
B46: CAMANCHACA S.A. CIA. PESQ | C46: 42005 | D46: 42124 | E46: 56.555 | F46: =48.9+20 -> 68.9 | G46: =E46+F46 -> 125.455 | I46: =G46-H46 -> 125.455 | J46: =H46/G46 -> 0 | K46: =E46+E47+E48 -> 66.534 | L46: =F46+F47+F48 -> 68.9 | M46: =K46+L46 -> 135.434 | N46: =H46+H47+H48 -> 0 | O46: =M46-N46 -> 135.434 | P46: =N46/M46 -> 0
C47: 42125 | D47: 42247 | E47: 6.65 | G47: =E47+F47+I46 -> 132.105 | I47: =G47-H47 -> 132.105 | J47: =H47/G47 -> 0
C48: 42248 | D48: 42369 | E48: 3.329 | G48: =E48+F48+I47 -> 135.434 | I48: =G48-H48 -> 135.434 | J48: =H48/G48 -> 0
B49: OPERACIONES ARANDU SpA | C49: 42005 | D49: 42124 | E49: 77.403 | F49: -77.403 | G49: =E49+F49 -> 0 | I49: =G49-H49 -> 0 | J49: =H49/G49 -> #DIV/0! | K49: =E49+E50+E51 -> 91.061 | L49: =F49+F50+F51 -> -91.061 | M49: =K49+L49 -> 0 | N49: =H49+H50+H51 -> 0 | O49: =M49-N49 -> 0 | P49: 0
C50: 42125 | D50: 42247 | E50: 9.102 | F50: -9.102 | G50: =E50+F50+I49 -> 0 | I50: =G50-H50 -> 0 | J50: =H50/G50 -> #DIV/0!
C51: 42248 | D51: 42369 | E51: 4.556 | F51: -4.556 | G51: =E51+F51+I50 -> 0 | I51: =G51-H51 -> 0 | J51: =H51/G51 -> #DIV/0!
B52: CENTRO SUR SpA PESQ. antes CENTRO SUR S.A. PESQ. | C52: 42005 | D52: 42124 | E52: 77.329 | F52: -77.329 | G52: =E52+F52 -> 0 | I52: =G52-H52 -> 0 | J52: =H52/G52 -> #DIV/0! | K52: =E52+E53+E54 -> 90.974 | L52: =F52+F53+F54 -> -90.974 | M52: =K52+L52 -> 0 | N52: =H52+H53+H54 -> 0 | O52: =M52-N52 -> 0 | P52: 0
C53: 42125 | D53: 42247 | E53: 9.093 | F53: -9.093 | G53: =E53+F53+I52 -> 0 | I53: =G53-H92 -> -43.872 | J53: =H92/G53 -> #DIV/0!
C54: 42248 | D54: 42369 | E54: 4.552 | F54: -4.552 | G54: =E54+F54+I53 -> -43.872 | I54: =G54-H54 -> -43.872 | J54: =H54/G54 -> 0
B55: FOODCORP CHILE S.A. | C55: 42005 | D55: 42124 | E55: 289.78 | F55: =-16-228-37 -> -281 | G55: =E55+F55 -> 8.78 | I55: =G55-H55 -> 8.78 | J55: =H55/G55 -> 0 | K55: =E55+E56+E57 -> 340.913 | L55: =F55+F56+F57 -> -281 | M55: =K55+L55 -> 59.913 | N55: =H55+H56+H57 -> 58.074 | O55: =M55-N55 -> 1.839 | P55: =N55/M55 -> 0.96930549
C56: 42125 | D56: 42247 | E56: 34.075 | G56: =E56+F56+I55 -> 42.855 | I56: =G56-H56 -> 42.855 | J56: =H56/G56 -> 0
C57: 42248 | D57: 42369 | E57: 17.058 | G57: =E57+F57+I56 -> 59.913 | H57: 58.074 | I57: =G57-H57 -> 1.839 | J57: =H57/G57 -> 0.96930549
B58: GENMAR LTDA. SOC. PESQ. | C58: 42005 | D58: 42124 | E58: 2.209 | F58: -2.209 | G58: =E58+F58 -> 0 | I58: =G58-H58 -> 0 | J58: =H58/G58 -> #DIV/0! | K58: =E58+E59+E60 -> 2.599 | L58: =F58+F59+F60 -> -2.599 | M58: =K58+L58 -> 0 | N58: =H58+H59+H60 -> 0 | O58: =M58-N58 -> 0 | P58: 0
C59: 42125 | D59: 42247 | E59: 0.26 | F59: -0.26 | G59: =E59+F59+I58 -> 0 | I59: =G59-H59 -> 0 | J59: =H59/G59 -> #DIV/0!
C60: 42248 | D60: 42369 | E60: 0.13 | F60: -0.13 | G60: =E60+F60+I59 -> 0 | I60: =G60-H60 -> 0 | J60: =H60/G60 -> #DIV/0!
B61: INOSTROZA CONCHA PELANTARO | C61: 42005 | D61: 42124 | E61: 6.84 | F61: -6.84 | G61: =E61+F61 -> 0 | I61: =G61-H61 -> 0 | J61: =H61/G61 -> #DIV/0! | K61: =E61+E62+E63 -> 8.047 | L61: =F61+F62+F63 -> -8.047 | M61: =K61+L61 -> 0 | N61: =H61+H62+H63 -> 0 | O61: =M61-N61 -> 0 | P61: 0
C62: 42125 | D62: 42247 | E62: 0.804 | F62: -0.804 | G62: =E62+F62+I61 -> 0 | I62: =G62-H62 -> 0 | J62: =H62/G62 -> #DIV/0!
C63: 42248 | D63: 42369 | E63: 0.403 | F63: -0.403 | G63: =E63+F63+I62 -> 0 | I63: =G63-H63 -> 0 | J63: =H63/G63 -> #DIV/0!
B64: INVERSIONES PESQUERAS SpA | C64: 42005 | D64: 42124 | E64: 69.967 | F64: -69.967 | G64: =E64+F64 -> 0 | I64: =G64-H64 -> 0 | J64: =H64/G64 -> #DIV/0! | K64: =E64+E65+E66 -> 82.313 | L64: =F64+F65+F66 -> -82.313 | M64: =K64+L64 -> 0 | N64: =H64+H65+H66 -> 0 | O64: =M64-N64 -> 0 | P64: 0
C65: 42125 | D65: 42247 | E65: 8.227 | F65: -8.227 | G65: =E65+F65+I64 -> 0 | I65: =G65-H65 -> 0 | J65: =H65/G65 -> #DIV/0!
C66: 42248 | D66: 42369 | E66: 4.119 | F66: -4.119 | G66: =E66+F66+I65 -> 0 | I66: =G66-H66 -> 0 | J66: =H66/G66 -> #DIV/0!
B67: BURITA INVERSIONES SpA | C67: 42005 | D67: 42124 | E67: 43.436 | F67: -0.429 | G67: =E67+F67 -> 43.007 | I67: =G67-H67 -> 43.007 | J67: =H67/G67 -> 0 | K67: =E67+E68+E69 -> 51.101 | L67: =F67+F68+F69 -> -0.429 | M67: =K67+L67 -> 50.672 | N67: =H67+H68+H69 -> 0 | O67: =M67-N67 -> 50.672 | P67: =N67/M67 -> 0
C68: 42125 | D68: 42247 | E68: 5.108 | G68: =E68+F68+I67 -> 48.115 | I68: =G68-H68 -> 48.115 | J68: =H68/G68 -> 0
C69: 42248 | D69: 42369 | E69: 2.557 | G69: =E69+F69+I68 -> 50.672 | I69: =G69-H69 -> 50.672 | J69: =H69/G69 -> 0
B70: ISLA QUIHUA S.A. PESQ. | C70: 42005 | D70: 42124 | E70: 60.389 | F70: =+-E70 -> -60.389 | G70: =E70+F70 -> 0 | I70: =G70-H70 -> 0 | J70: =H70/G70 -> #DIV/0! | K70: =E70+E71+E72 -> 71.045 | L70: =F70+F71+F72 -> -71.045 | M70: =K70+L70 -> 0 | N70: =H70+H71+H72 -> 0 | O70: =M70-N70 -> 0 | P70: =N70/M70 -> #DIV/0!
C71: 42125 | D71: 42247 | E71: 7.101 | F71: =+-E71 -> -7.101 | G71: =E71+F71+I70 -> 0 | I71: =G71-H71 -> 0 | J71: =H71/G71 -> #DIV/0!
C72: 42248 | D72: 42369 | E72: 3.555 | F72: =+-E72 -> -3.555 | G72: =E72+F72+I71 -> 0 | I72: =G72-H72 -> 0 | J72: =H72/G72 -> #DIV/0!
B73: LANDES S.A. SOC. PESQ. | C73: 42005 | D73: 42124 | E73: 510.317 | F73: =5+1.406-1.406+34.767+16.21+63 -> 118.977 | G73: =E73+F73 -> 629.294 | H73: 141.153 | I73: =G73-H73 -> 488.141 | J73: =H73/G73 -> 0.22430374 | K73: =E73+E74+E75 -> 600.364 | L73: =F73+F74+F75 -> 118.977 | M73: =K73+L73 -> 719.341 | N73: =H73+H74+H75 -> 706.92 | O73: =M73-N73 -> 12.421 | P73: =N73/M73 -> 0.98273281
C74: 42125 | D74: 42247 | E74: 60.008 | G74: =E74+F74+I73 -> 548.149 | H74: 68.939 | I74: =G74-H74 -> 479.21 | J74: =H74/G74 -> 0.1257669
C75: 42248 | D75: 42369 | E75: 30.039 | G75: =E75+F75+I74 -> 509.249 | H75: 496.828 | I75: =G75-H75 -> 12.421 | J75: =H75/G75 -> 0.97560918
B76: LOTA PROTEIN S.A. | C76: 42005 | D76: 42124 | E76: 109.803 | F76: =2.239+6.934+87+150+18.58 -> 264.753 | G76: =E76+F76 -> 374.556 | H76: 100.244 | I76: =G76-H76 -> 274.312 | J76: =H76/G76 -> 0.26763421 | K76: =E76+E77+E78 -> 129.178 | L76: =F76+F77+F78 -> 264.753 | M76: =K76+L76 -> 393.931 | N76: =H76+H77+H78 -> 178.866 | O76: =M76-N76 -> 215.065 | P76: =N76/M76 -> 0.45405414
C77: 42125 | D77: 42247 | E77: 12.912 | G77: =E77+F77+I76 -> 287.224 | H77: 6.735 | I77: =G77-H77 -> 280.489 | J77: =H77/G77 -> 0.023448598
C78: 42248 | D78: 42369 | E78: 6.463 | G78: =E78+F78+I77 -> 286.952 | H78: 71.887 | I78: =G78-H78 -> 215.065 | J78: =H78/G78 -> 0.25051925
B79: MAR PROFUNDO S.A. SOC. PESQ. | C79: 42005 | D79: 42124 | E79: 30.056 | F79: =-E79 -> -30.056 | G79: =E79+F79 -> 0 | I79: =G79-H79 -> 0 | J79: =H79/G79 -> #DIV/0! | K79: =E79+E80+E81 -> 35.359 | L79: =F79+F80+F81 -> -35.359 | M79: =K79+L79 -> 0 | N79: =H79+H80+H81 -> 0 | O79: =M79-N79 -> 0 | P79: =N79/M79 -> #DIV/0!
C80: 42125 | D80: 42247 | E80: 3.534 | F80: =-E80 -> -3.534 | G80: =E80+F80+I79 -> 0 | I80: =G80-H80 -> 0 | J80: =H80/G80 -> #DIV/0!
C81: 42248 | D81: 42369 | E81: 1.769 | F81: =-E81 -> -1.769 | G81: =E81+F81+I80 -> 0 | I81: =G81-H81 -> 0 | J81: =H81/G81 -> #DIV/0!
B82: ORIZON S.A | C82: 42005 | D82: 42124 | E82: 1553.047 | F82: =4.297-150-50 -> -195.703 | G82: =E82+F82 -> 1357.344 | H82: 253.981 | I82: =G82-H82 -> 1103.363 | J82: =H82/G82 -> 0.18711616 | K82: =E82+E83+E84 -> 1827.089 | L82: =F82+F83+F84 -> -195.703 | M82: =K82+L82 -> 1631.386 | N82: =H82+H83+H84 -> 1423.995 | O82: =M82-N82 -> 207.391 | P82: =N82/M82 -> 0.87287435
C83: 42125 | D83: 42247 | E83: 182.624 | G83: =E83+F83+I82 -> 1285.987 | H83: 620.35 | I83: =G83-H83 -> 665.637 | J83: =H83/G83 -> 0.48239212
C84: 42248 | D84: 42369 | E84: 91.418 | G84: =E84+F84+I83 -> 757.055 | H84: 549.664 | I84: =G84-H84 -> 207.391 | J84: =H84/G84 -> 0.72605557
B85: INVERSIONES SANTANA SpA | C85: 42005 | D85: 42124 | E85: 29.438 | F85: -29.438 | G85: =E85+F85 -> 0 | I85: =G85-H85 -> 0 | J85: =H85/G85 -> #DIV/0! | K85: =E85+E86+E87 -> 34.633 | L85: =F85+F86+F87 -> -34.633 | M85: =K85+L85 -> 0 | N85: =H85+H86+H87 -> 0 | O85: =M85-N85 -> 0 | P85: =N85/M85 -> #DIV/0!
C86: 42125 | D86: 42247 | E86: 3.462 | F86: -3.462 | G86: =E86+F86+I85 -> 0 | I86: =G86-H86 -> 0 | J86: =H86/G86 -> #DIV/0!
C87: 42248 | D87: 42369 | E87: 1.733 | F87: -1.733 | G87: =E87+F87+I86 -> 0 | I87: =G87-H87 -> 0 | J87: =H87/G87 -> #DIV/0!
B88: SAN ANTONIO S.A. PESQ. | C88: 42005 | D88: 42124 | E88: 166.717 | F88: =-E88 -> -166.717 | G88: =E88+F88 -> 0 | I88: =G88-H88 -> 0 | J88: =H88/G88 -> #DIV/0! | K88: =E88+E89+E90 -> 196.135 | L88: =F88+F89+F90 -> -196.135 | M88: =K88+L88 -> 0 | N88: =H88+H89+H90 -> 0 | O88: =M88-N88 -> 0 | P88: =N88/M88 -> #DIV/0!
C89: 42125 | D89: 42247 | E89: 19.604 | F89: =-E89 -> -19.604 | G89: =E89+F89+I88 -> 0 | I89: =G89-H89 -> 0 | J89: =H89/G89 -> #DIV/0!
C90: 42248 | D90: 42369 | E90: 9.814 | F90: =-E90 -> -9.814 | G90: =E90+F90+I89 -> 0 | I90: =G90-H90 -> 0 | J90: =H90/G90 -> #DIV/0!
B91: PESQUERA LITORAL SpA | C91: 42005 | D91: 42124 | F91: =82.313+90.974+91.061+34.633 -> 298.981 | G91: =E91+F91 -> 298.981 | I91: =G91-H91 -> 298.981 | J91: =H91/G91 -> 0 | K91: =E91+E92+E93 -> 0 | L91: =F91+F92+F93 -> 298.981 | M91: =K91+L91 -> 298.981 | N91: =H91+H92+H93 -> 260.865 | O91: =M91-N91 -> 38.116 | P91: =N91/M91 -> 0.87251364
C92: 42125 | D92: 42247 | G92: =E92+F92+I91 -> 298.981 | H92: =7.395+36.477 -> 43.872 | I92: =G92-H92 -> 255.109 | J92: =H92/G92 -> 0.14673842
C93: 42248 | D93: 42369 | G93: =E93+F93+I92 -> 255.109 | H93: 216.993 | I93: =G93-H93 -> 38.116 | J93: =H93/G93 -> 0.85058936
B94: PAOLA POBLETE NOVOA | C94: 42005 | D94: 42124 | F94: 0.429 | G94: =E94+F94 -> 0.429 | I94: =G94-H94 -> 0.429 | J94: =H94/G94 -> 0 | K94: =E94+E95+E96 -> 0 | L94: =F94+F95+F96 -> 0.429 | M94: =K94+L94 -> 0.429 | N94: =H94+H95+H96 -> 0 | O94: =M94-N94 -> 0.429 | P94: =N94/M94 -> 0
C95: 42125 | D95: 42247 | G95: =E95+F95+I94 -> 0.429 | I95: =G95-H95 -> 0.429 | J95: =H95/G95 -> 0
C96: 42248 | D96: 42369 | G96: =E96+F96+I95 -> 0.429 | I96: =G96-H96 -> 0.429 | J96: =H96/G96 -> 0
E97: =SUM(E34:E96) -> 8573.998 | H97: =SUM(H6:H93) -> 157453.29 | K97: =SUM(K34:K96) -> 8573.998 | L97: =SUM(L34:L96) -> -2138.124 | M97: =SUM(M34:M96) -> 6435.874 | N97: =SUM(N34:N96) -> 5288.222 | O97: =SUM(O34:O96) -> 1147.652 | P97: =+N97/M97 -> 0.82167892
A99: Sardina común V-X | B99: ALIMENTOS MARINOS S.A. | C99: 42005 | D99: 42124 | E99: 4697.221 | F99: =-3350.744+912.712+350+800+434+213.282+262.291+223.973+100 -> -54.486 | G99: =E99+F99 -> 4642.735 | I99: =G99-H99 -> 4642.735 | J99: =H99/G99 -> 0 | K99: =E99+E100+E101 -> 5555.566 | L99: =F99+F100+F101 -> -54.486 | M99: =K99+L99 -> 5501.08 | N99: =H99+H100+H101 -> 5547.428 | O99: =M99-N99 -> -46.348 | P99: =N99/M99 -> 1.0084253
C100: 42125 | D100: 42247 | E100: 552.573 | G100: =E100+F100+I99 -> 5195.308 | H100: 1985.04 | I100: =G100-H100 -> 3210.268 | J100: =H100/G100 -> 0.38208322
C101: 42248 | D101: 42369 | E101: 305.772 | G101: =E101+F101+I100 -> 3516.04 | H101: 3562.388 | I101: =G101-H101 -> -46.348 | J101: =H101/G101 -> 1.0131819
B102: SOC. PESQUERA BERTA ELENA LDTA. | C102: 42005 | D102: 42124 | E102: 0 | F102: =-903.96+903.96 -> 0 | G102: =E102+F102 -> 0 | I102: =G102-H102 -> 0 | J102: =H102/G102 -> #DIV/0! | K102: =E102+E103+E104 -> 0 | L102: =F102+F103+F104 -> 0 | M102: =K102+L102 -> 0 | N102: =H102+H103+H104 -> 0 | O102: =M102-N102 -> 0 | P102: =N102/M102 -> #DIV/0!
C103: 42125 | D103: 42247 | E103: 0 | G103: =E103+F103+I102 -> 0 | I103: =G103-H103 -> 0 | J103: =H103/G103 -> #DIV/0!
C104: 42248 | D104: 42369 | E104: 0 | G104: =E104+F104+I103 -> 0 | I104: =G104-H104 -> 0 | J104: =H104/G104 -> #DIV/0!
...

Sheet Demersales LTP 
A2: Cuotas LTP Recursos Demersales Año 2016 actualizado al 27-01-2017
C5: Periodo | E5: Cuota (t) | H5: Operación | K5: Resumen anual
A6: Unidad de pesquería | B6: Armador | C6: Inicial | D6: Final | E6: Cuota Asignada | F6: Traspaso, Cesion, Arriendo, etc) | G6: Cuota Efectiva | H6: Desembarque (t) | I6: Saldo (t) | J6: % consumido | K6: Cuota Total | L6: Traspaso, Cesion, Arriendo, etc) | M6: Cuota Efectiva | N6: Desembarque (t) | O6: Saldo (t) | P6: % consumido
A7: Congrio dorado NE H/F (41º28,6 LS hasta 47º) | B7: Emdepes S.A. | C7: 42005 | D7: 42063 | E7: 0.529 | G7: =E7+F7 -> 0.529 | I7: =G7-H7 -> 0.529 | J7: =H7/G7 -> 0 | K7: =E7+E8 -> 1.059 | L7: =F7+F8 -> 0 | M7: =K7+L7 -> 1.059 | N7: =H7+H8 -> 1.001 | O7: =M7-N7 -> 0.058 | P7: =N7/M7 -> 0.94523135
C8: 42064 | D8: 42369 | E8: 0.53 | G8: =E8+F8+I7 -> 1.059 | H8: 1.001 | I8: =G8-H8 -> 0.058 | J8: =H8/G8 -> 0.94523135
B9: Grimar S.A.Pesq. | C9: 42005 | D9: 42063 | E9: 7.714 | G9: =E9+F9 -> 7.714 | H9: 1.984 | I9: =G9-H9 -> 5.73 | J9: =H9/G9 -> 0.25719471 | K9: =E9+E10 -> 15.447 | L9: =F9+F10 -> 0 | M9: =K9+L9 -> 15.447 | N9: =H9+H10 -> 14.367 | O9: =M9-N9 -> 1.08 | P9: =N9/M9 -> 0.93008351
C10: 42064 | D10: 42369 | E10: 7.733 | G10: =E10+F10+I9 -> 13.463 | H10: 12.383 | I10: =G10-H10 -> 1.08 | J10: =H10/G10 -> 0.91978014
B11: Deris S.A. | C11: 42005 | D11: 42063 | E11: 145.187 | F11: =-33.39+60.001+23.728 -> 50.339 | G11: =E11+F11 -> 195.526 | H11: 53.215 | I11: =G11-H11 -> 142.311 | J11: =H11/G11 -> 0.27216329 | K11: =E11+E12 -> 290.721 | L11: =F11+F12 -> 50.339 | M11: =K11+L11 -> 341.06 | N11: =H11+H12 -> 336.726 | O11: =M11-N11 -> 4.334 | P11: =N11/M11 -> 0.98729256
C12: 42064 | D12: 42369 | E12: 145.534 | G12: =E12+F12+I11 -> 287.845 | H12: 283.511 | I12: =G12-H12 -> 4.334 | J12: =H12/G12 -> 0.98494329
B13: Pesca Cisne S.A. Pesq. | C13: 42005 | D13: 42063 | E13: 12.385 | F13: =-0.042-23.728 -> -23.77 | G13: =E13+F13 -> -11.385 | I13: =G13-H13 -> -11.385 | J13: =H13/G13 -> 0 | K13: =E13+E14 -> 24.799 | L13: =F13+F14 -> -23.77 | M13: =K13+L13 -> 1.029 | N13: =H13+H14 -> 0 | O13: =M13-N13 -> 1.029 | P13: =N13/M13 -> 0
C14: 42064 | D14: 42369 | E14: 12.414 | G14: =E14+F14+I13 -> 1.029 | I14: =G14-H14 -> 1.029 | J14: =H14/G14 -> 0
B15: Sur Austral S.A. Pesq. | C15: 42005 | D15: 42063 | E15: 43.186 | F15: -60.001 | G15: =E15+F15 -> -16.815 | I15: =G15-H15 -> -16.815 | J15: =H15/G15 -> 0 | K15: =E15+E16 -> 86.475 | L15: =F15+F16 -> -60.001 | M15: =K15+L15 -> 26.474 | N15: =H15+H16 -> 19.411 | O15: =M15-N15 -> 7.063 | P15: =N15/M15 -> 0.73320994
C16: 42064 | D16: 42369 | E16: 43.289 | G16: =E16+F16+I15 -> 26.474 | H16: 19.411 | I16: =G16-H16 -> 7.063 | J16: =H16/G16 -> 0.73320994
B17: Alimentos Marinos S.A. | C17: 42005 | D17: 42063 | E17: 0 | F17: 0.042 | G17: =E17+F17 -> 0.042 | I17: =G17-H17 -> 0.042 | J17: =H17/G17 -> 0 | K17: =E17+E18 -> 0 | L17: =F17+F18 -> 0.042 | M17: =K17+L17 -> 0.042 | N17: =H17+H18 -> 0 | O17: =M17-N17 -> 0.042 | P17: =N17/M17 -> 0
C18: 42064 | D18: 42369 | E18: 0 | G18: =E18+F18+I17 -> 0.042 | I18: =G18-H18 -> 0.042 | J18: =H18/G18 -> 0
K19: =SUM(K7:K16) -> 418.501 | L19: =SUM(L7:L16) -> -33.432 | M19: =SUM(M7:M16) -> 385.069 | N19: =SUM(N7:N16) -> 371.505 | O19: =SUM(O7:O16) -> 13.564 | P19: =+N19/M19 -> 0.96477514
L20: 33.39
A21: Congrio dorado SE (47º hasta 57º) | B21: Emdepes S.A., | C21: 42005 | D21: 42063 | E21: 20.665 | G21: =E21+F21 -> 20.665 | I21: =G21-H21 -> 20.665 | J21: =H21/G21 -> 0 | K21: =E21+E22 -> 41.33 | L21: =F21+F22 -> 0 | M21: =K21+L21 -> 41.33 | N21: =H21+H22 -> 41.071 | O21: =M21-N21 -> 0.259 | P21: =N21/M21 -> 0.99373337
C22: 42064 | D22: 42369 | E22: 20.665 | G22: =E22+F22+I21 -> 41.33 | H22: 41.071 | I22: =G22-H22 -> 0.259 | J22: =H22/G22 -> 0.99373337
B23: Grimar S.A.Pesq. | C23: 42005 | D23: 42063 | E23: 0.062 | G23: =E23+F23 -> 0.062 | I23: =G23-H23 -> 0.062 | J23: =H23/G23 -> 0 | K23: =E23+E24 -> 0.124 | L23: =F23+F24 -> 0 | M23: =K23+L23 -> 0.124 | N23: =H23+H24 -> 0 | O23: =M23-N23 -> 0.124 | P23: =N23/M23 -> 0
C24: 42064 | D24: 42369 | E24: 0.062 | G24: =E24+F24+I23 -> 0.124 | I24: =G24-H24 -> 0.124 | J24: =H24/G24 -> 0
B25: Deris S.A. | C25: 42005 | D25: 42063 | E25: 70.758 | F25: =-23.7 -> -23.7 | G25: =E25+F25 -> 47.058 | H25: 4.937 | I25: =G25-H25 -> 42.121 | J25: =H25/G25 -> 0.10491309 | K25: =E25+E26 -> 141.516 | L25: =F25+F26 -> -23.7 | M25: =K25+L25 -> 117.816 | N25: =H25+H26 -> 111.844 | O25: =M25-N25 -> 5.972 | P25: =N25/M25 -> 0.94931079
C26: 42064 | D26: 42369 | E26: 70.758 | G26: =E26+F26+I25 -> 112.879 | H26: 106.907 | I26: =G26-H26 -> 5.972 | J26: =H26/G26 -> 0.94709379
B27: Pesca Cisne S.A | C27: 42005 | D27: 42063 | E27: 27.485 | F27: =23.7 -> 23.7 | G27: =E27+F27 -> 51.185 | H27: 74.033 | I27: =G27-H27 -> -22.848 | J27: =H27/G27 -> 1.4463808 | K27: =E27+E28 -> 54.97 | L27: =F27+F28 -> 23.7 | M27: =K27+L27 -> 78.67 | N27: =H27+H28 -> 74.033 | O27: =M27-N27 -> 4.637 | P27: =N27/M27 -> 0.94105758
C28: 42064 | D28: 42369 | E28: 27.485 | G28: =E28+F28+I27 -> 4.637 | I28: =G28-H28 -> 4.637 | J28: =H28/G28 -> 0
B29: Sur Austral S.A. Pesq. | C29: 42005 | D29: 42063 | E29: 0.03 | G29: =E29+F29 -> 0.03 | I29: =G29-H29 -> 0.03 | J29: =H29/G29 -> 0 | K29: =E29+E30 -> 0.06 | L29: =F29+F30 -> 0 | M29: =K29+L29 -> 0.06 | N29: =H29+H30 -> 0 | O29: =M29-N29 -> 0.06 | P29: =N29/M29 -> 0
C30: 42064 | D30: 42369 | E30: 0.03 | G30: =E30+F30+I29 -> 0.06 | I30: =G30-H30 -> 0.06 | J30: =H30/G30 -> 0
H31: =SUM(H7:H30) -> 598.453 | K31: =SUM(K21:K30) -> 238 | L31: =SUM(L21:L30) -> 0 | M31: =SUM(M21:M30) -> 238 | N31: =SUM(N21:N30) -> 226.948 | O31: =SUM(O21:O30) -> 11.052 | P31: =+N31/M31 -> 0.95356303
A33: Merluza del sur NE F/H (41º28,6 LS al 47º LS) | B33: Emdepes S.A. | C33: 42005 | D33: 42035 | E33: 192.551 | F33: =73.003+134.435+55.338+500+5.6+140+5.008+55.613-55.613 -> 913.384 | G33: =E33+F33 -> 1105.935 | I33: =G33-H33 -> 1105.935 | J33: =H33/G33 -> 0 | K33: =E33+E34 -> 549.981 | L33: =F33+F34 -> 913.384 | M33: =K33+L33 -> 1463.365 | N33: =H33+H34 -> 1457.811 | O33: =M33-N33 -> 5.554 | P33: =N33/M33 -> 0.99620464
C34: 42036 | D34: 42369 | E34: 357.43 | G34: =E34+F34+I33 -> 1463.365 | H34: 1457.811 | I34: =G34-H34 -> 5.554 | J34: =H34/G34 -> 0.99620464
B35: Grimar S.A. Pesq. | C35: 42005 | D35: 42035 | E35: 44.713 | F35: =140.465+163.676+58.764+946.461+11.815+79.944+370+10.43+8.737 -> 1790.292 | G35: =E35+F35 -> 1835.005 | H35: 50.073 | I35: =G35-H35 -> 1784.932 | J35: =H35/G35 -> 0.027287664 | K35: =E35+E36 -> 127.714 | L35: =F35+F36 -> 1790.292 | M35: =K35+L35 -> 1918.006 | N35: =H35+H36 -> 1543.442 | O35: =M35-N35 -> 374.564 | P35: =N35/M35 -> 0.80471177
C36: 42036 | D36: 42369 | E36: 83.001 | G36: =E36+F36+I35 -> 1867.933 | H36: 1493.369 | I36: =G36-H36 -> 374.564 | J36: =H36/G36 -> 0.79947675
B37: Pesca Cisne S.A. | C37: 42005 | D37: 42035 | E37: 44.838 | F37: -128 | G37: =E37+F37 -> -83.162 | I37: =G37-H37 -> -83.162 | J37: =H37/G37 -> 0 | K37: =E37+E38 -> 128.071 | L37: =F37+F38 -> -128 | M37: =K37+L37 -> 0.071 | N37: =H37+H38 -> 0 | O37: =M37-N37 -> 0.071 | P37: =N37/M37 -> 0
C38: 42036 | D38: 42369 | E38: 83.233 | G38: =E38+F38+I37 -> 0.071 | I38: =G38-H38 -> 0.071 | J38: =H38/G38 -> 0
B39: Sur Austral S.A. Pesq. | C39: 42005 | D39: 42035 | E39: 528.373 | F39: =64.108+18.6+71.024+6.667+7.506-100-21+11 -> 57.905 | G39: =E39+F39 -> 586.278 | H39: 33.625 | I39: =G39-H39 -> 552.653 | J39: =H39/G39 -> 0.057353337 | K39: =E39+E40 -> 1509.188 | L39: =F39+F40 -> 57.905 | M39: =K39+L39 -> 1567.093 | N39: =H39+H40 -> 1601.998 | O39: =M39-N39 -> -34.905 | P39: =N39/M39 -> 1.0222737
C40: 42036 | D40: 42369 | E40: 980.815 | G40: =E40+F40+I39 -> 1533.468 | H40: 1568.373 | I40: =G40-H40 -> -34.905 | J40: =H40/G40 -> 1.0227621
B41: Deris S.A. | C41: 42005 | D41: 42035 | E41: 699.389 | F41: =700+138+130+90-100+21-21 -> 958 | G41: =E41+F41 -> 1657.389 | I41: =G41-H41 -> 1657.389 | J41: =H41/G41 -> 0 | K41: =E41+E42 -> 1997.659 | L41: =F41+F42 -> 958 | M41: =K41+L41 -> 2955.659 | N41: =H41+H42 -> 2898.684 | O41: =M41-N41 -> 56.975 | P41: =N41/M41 -> 0.98072342
C42: 42036 | D42: 42369 | E42: 1298.27 | G42: =E42+F42+I41 -> 2955.659 | H42: 2898.684 | I42: =G42-H42 -> 56.975 | J42: =H42/G42 -> 0.98072342
B43: Congelados del Pacífico S.A. | C43: 42005 | D43: 42035 | E43: 0 | F43: 0.17252 | G43: =E43+F43 -> 0.17252 | I43: =G43-H43 -> 0.17252 | J43: =H43/G43 -> 0 | K43: =E43+E44 -> 0 | L43: =F43+F44 -> 0.17252 | M43: =K43+L43 -> 0.17252 | N43: =H43+H44 -> 0.032 | O43: =M43-N43 -> 0.14052 | P43: =N43/M43 -> 0.18548574
C44: 42036 | D44: 42369 | E44: 0 | G44: =E44+F44+I43 -> 0.17252 | H44: 0.032 | I44: =G44-H44 -> 0.14052 | J44: =H44/G44 -> 0.18548574
B45: Alimentos Marinos S.A. | C45: 42005 | D45: 42035 | E45: 0.076 | G45: =E45+F45 -> 0.076 | I45: =G45-H45 -> 0.076 | J45: =H45/G45 -> 0 | K45: =E45+E46 -> 0.216 | L45: =F45+F46 -> 0 | M45: =K45+L45 -> 0.216 | N45: =H45+H46 -> 0 | O45: =M45-N45 -> 0.216 | P45: =N45/M45 -> 0
C46: 42036 | D46: 42369 | E46: 0.14 | G46: =E46+F46+I45 -> 0.216 | I46: =G46-H46 -> 0.216 | J46: =H46/G46 -> 0
B47: Bio Bio S.A. Pesq | C47: 42005 | D47: 42035 | E47: 0.06 | F47: =-0.17252 -> -0.17252 | G47: =E47+F47 -> -0.11252 | I47: =G47-H47 -> -0.11252 | J47: =H47/G47 -> 0 | K47: =E47+E48 -> 0.172 | L47: =F47+F48 -> -0.17252 | M47: =K47+L47 -> -0.00052 | N47: =H47+H48 -> 0 | O47: =M47-N47 -> -0.00052 | P47: =N47/M47 -> 0
C48: 42036 | D48: 42369 | E48: 0.112 | G48: =E48+F48+I47 -> -0.00052 | I48: =G48-H48 -> -0.00052 | J48: =H48/G48 -> 0
K49: =SUM(K33:K48) -> 4313.001 | L49: =SUM(L33:L48) -> 3591.581 | M49: =SUM(M33:M48) -> 7904.582 | N49: =SUM(N33:N48) -> 7501.967 | O49: =SUM(O33:O48) -> 402.615 | P49: =+N49/M49 -> 0.94906562
A51: Merluza Del Sur SE Fabrica (47º LS al 57º LS) | B51: Emdepes S.A. | C51: 42005 | D51: 42035 | E51: 280.489 | F51: =206.443+107.167-500-140+26.307+5.008+55.613+4.445 -> -235.017 | G51: =E51+F51 -> 45.472 | I51: =G51-H51 -> 45.472 | J51: =H51/G51 -> 0 | K51: =E51+E52 -> 801.646 | L51: =F51+F52 -> -235.017 | M51: =K51+L51 -> 566.629 | N51: =H51+H52 -> 563.579 | O51: =M51-N51 -> 3.05 | P51: =N51/M51 -> 0.99461729
C52: 41671 | D52: 42369 | E52: 521.157 | G52: =E52+F52+I51 -> 566.629 | H52: 563.579 | I52: =G52-H52 -> 3.05 | J52: =H52/G52 -> 0.99461729
B53: Grimar S.A. Pesq. | C53: 42005 | D53: 42035 | E53: 0.542 | G53: =E53+F53 -> 0.542 | I53: =G53-H53 -> 0.542 | J53: =H53/G53 -> 0 | K53: =E53+E54 -> 1.549 | L53: =F53+F54 -> 0 | M53: =K53+L53 -> 1.549 | N53: =H53+H54 -> 0 | O53: =M53-N53 -> 1.549 | P53: =N53/M53 -> 0
C54: 41671 | D54: 42369 | E54: 1.007 | G54: =E54+F54+I53 -> 1.549 | I54: =G54-H54 -> 1.549 | J54: =H54/G54 -> 0
B55: Pesca Cisne S.A. | C55: 42005 | D55: 42035 | E55: 157.927 | G55: =E55+F55 -> 157.927 | I55: =G55-H55 -> 157.927 | J55: =H55/G55 -> 0 | K55: =E55+E56 -> 451.36 | L55: =F55+F56 -> 175.7 | M55: =K55+L55 -> 627.06 | N55: =H55+H56 -> 333.381 | O55: =M55-N55 -> 293.679 | P55: =N55/M55 -> 0.53165726
C56: 41671 | D56: 42369 | E56: 293.433 | F56: =47.7+128 -> 175.7 | G56: =E56+F56+I55 -> 627.06 | H56: 333.381 | I56: =G56-H56 -> 293.679 | J56: =H56/G56 -> 0.53165726
B57: Deris S.A. | C57: 42005 | D57: 42035 | E57: 522.005 | F57: =1129.586-36.282-700-138-130-90+21 -> 56.304 | G57: =E57+F57 -> 578.309 | I57: =G57-H57 -> 578.309 | J57: =H57/G57 -> 0 | K57: =E57+E58 -> 1491.906 | L57: =F57+F58 -> 56.304 | M57: =K57+L57 -> 1548.21 | N57: =H57+H58 -> 1530.795 | O57: =M57-N57 -> 17.415 | P57: =N57/M57 -> 0.98875153
C58: 41671 | D58: 42369 | E58: 969.901 | G58: =E58+F58+I57 -> 1548.21 | H58: 1530.795 | I58: =G58-H58 -> 17.415 | J58: =H58/G58 -> 0.98875153
B59: Sur Austral S.A. Pesq. | C59: 42005 | D59: 42035 | E59: 4.038 | F59: -11 | G59: =E59+F59 -> -6.962 | I59: =G59-H59 -> -6.962 | J59: =H59/G59 -> 0 | K59: =E59+E60 -> 11.54 | L59: =F59+F60 -> -11 | M59: =K59+L59 -> 0.54 | N59: =H59+H60 -> 0 | O59: =M59-N59 -> 0.54 | P59: =N59/M59 -> 0
C60: 41671 | D60: 42369 | E60: 7.502 | G60: =E60+F60+I59 -> 0.54 | I60: =G60-H60 -> 0.54 | J60: =H60/G60 -> 0
H61: =SUM(H33:H60) -> 9929.722 | K61: =SUM(K51:K60) -> 2758.001 | L61: =SUM(L51:L60) -> -14.013 | M61: =SUM(M51:M60) -> 2743.988 | N61: =SUM(N51:N60) -> 2427.755 | O61: =SUM(O51:O60) -> 316.233 | P61: =+N61/M61 -> 0.88475423
A63: Merluza tres aletas NE/SE (41º28,6 LS hasta 57º) | B63: Emdepes S.A. | C63: 42005 | D63: 42094 | E63: 4221.205 | G63: =E63+F63 -> 4221.205 | I63: =G63-H63 -> 4221.205 | J63: =H63/G63 -> 0 | K63: =E63+E64 -> 11502.934 | L63: =F63+F64 -> 0 | M63: =K63+L63 -> 11502.934 | N63: =H63+H64 -> 8265.429 | O63: =M63-N63 -> 3237.505 | P63: =N63/M63 -> 0.71854963
C64: 42095 | D64: 42369 | E64: 7281.729 | G64: =E64+F64+I63 -> 11502.934 | H64: 8265.429 | I64: =G64-H64 -> 3237.505 | J64: =H64/G64 -> 0.71854963
B65: Grimar S.A. Pesq. | C65: 42005 | D65: 42094 | E65: 0.124 | G65: =E65+F65 -> 0.124 | I65: =G65-H65 -> 0.124 | J65: =H65/G65 -> 0 | K65: =E65+E66 -> 0.338 | L65: =F65+F66 -> 0 | M65: =K65+L65 -> 0.338 | N65: =H65+H66 -> 0.046 | O65: =M65-N65 -> 0.292 | P65: =N65/M65 -> 0.13609467
C66: 42095 | D66: 42369 | E66: 0.214 | G66: =E66+F66+I65 -> 0.338 | H66: =0.019+0.027 -> 0.046 | I66: =G66-H66 -> 0.292 | J66: =H66/G66 -> 0.13609467
B67: Deris S.A. | C67: 42005 | D67: 42094 | E67: 4.331 | G67: =E67+F67 -> 4.331 | H67: 0.071 | I67: =G67-H67 -> 4.26 | J67: =H67/G67 -> 0.016393443 | K67: =E67+E68 -> 11.802 | L67: =F67+F68 -> 0 | M67: =K67+L67 -> 11.802 | N67: =H67+H68 -> 5.341 | O67: =M67-N67 -> 6.461 | P67: =N67/M67 -> 0.45255042
C68: 42095 | D68: 42369 | E68: 7.471 | G68: =E68+F68+I67 -> 11.731 | H68: 5.27 | I68: =G68-H68 -> 6.461 | J68: =H68/G68 -> 0.44923706
B69: Sur Austral S.A. Pesq. | C69: 42005 | D69: 42094 | E69: 0.34 | G69: =E69+F69 -> 0.34 | I69: =G69-H69 -> 0.34 | J69: =H69/G69 -> 0 | K69: =E69+E70 -> 0.926 | L69: =F69+F70 -> 0 | M69: =K69+L69 -> 0.926 | N69: =H69+H70 -> 0.178 | O69: =M69-N69 -> 0.748 | P69: =N69/M69 -> 0.19222462
C70: 42095 | D70: 42369 | E70: 0.586 | G70: =E70+F70+I69 -> 0.926 | H70: 0.178 | I70: =G70-H70 -> 0.748 | J70: =H70/G70 -> 0.19222462
H71: =SUM(H63:H70) -> 8270.994 | K71: =SUM(K63:K70) -> 11516 | L71: =SUM(L63:L70) -> 0 | M71: =SUM(M63:M70) -> 11516 | N71: =SUM(N63:N70) -> 8270.994 | O71: =SUM(O63:O70) -> 3245.006 | P71: =+N71/M71 -> 0.71821761
A73: Merluza cola V-X | B73: Alimentos Marinos S.A. | C73: 42005 | D73: 42094 | E73: 1253.132 | F73: -0.244 | G73: =E73+F73 -> 1252.888 | I73: =G73-H73 -> 1252.888 | J73: =H73/G73 -> 0 | K73: =E73+E74 -> 3132.895 | L73: =F73+F74 -> -0.244 | M73: =K73+L73 -> 3132.651 | N73: =H73+H74 -> 0 | O73: =M73-N73 -> 3132.651 | P73: =N73/M73 -> 0
C74: 42095 | D74: 42369 | E74: 1879.763 | G74: =E74+F74+I73 -> 3132.651 | I74: =G74-H74 -> 3132.651 | J74: =H74/G74 -> 0
B75: Bio Bio S.A.Pesq. | C75: 42005 | D75: 42094 | E75: 302.58 | F75: =-0.483-0.241+6.088-0.72399-755.742+949.506-949.505 -> -751.10099 | G75: =E75+F75 -> -448.52099 | H75: 61.821 | I75: =G75-H75 -> -510.34199 | J75: =H75/G75 -> -0.13783301 | K75: =E75+E76 -> 756.466 | L75: =F75+F76 -> -751.10099 | M75: =K75+L75 -> 5.36501 | N75: =H75+H76 -> 67.795 | O75: =M75-N75 -> -62.42999 | P75: =N75/M75 -> 12.63651
C76: 42095 | D76: 42369 | E76: 453.886 | G76: =E76+F76+I75 -> -56.45599 | H76: 5.974 | I76: =G76-H76 -> -62.42999 | J76: =H76/G76 -> -0.10581694
B77: Blumar S.A. | C77: 42005 | D77: 42094 | E77: 2167.325 | F77: =-3490.893-212.373-1715.159+0.72399 -> -5417.701 | G77: =E77+F77 -> -3250.376 | I77: =G77-H77 -> -3250.376 | J77: =H77/G77 -> 0 | K77: =E77+E78 -> 5418.425 | L77: =F77+F78 -> -5417.701 | M77: =K77+L77 -> 0.72399 | N77: =H77+H78 -> 0 | O77: =M77-N77 -> 0.72399 | P77: =N77/M77 -> 0
C78: 42095 | D78: 42369 | E78: 3251.1 | G78: =E78+F78+I77 -> 0.72399 | I78: =G78-H78 -> 0.72399 | J78: =H78/G78 -> 0
B79: Bento Inversiones SpA. | C79: 42005 | D79: 42094 | E79: 320.399 | F79: -320.399 | G79: =E79+F79 -> 0 | I79: =G79-H79 -> 0 | J79: =H79/G79 -> #DIV/0! | K79: =E79+E80 -> 801.013 | L79: =F79+F80 -> -801.013 | M79: =K79+L79 -> 0 | N79: =H79+H80 -> 0 | O79: =M79-N79 -> 0 | P79: =N79/M79 -> #DIV/0!
C80: 42095 | D80: 42369 | E80: 480.614 | F80: -480.614 | G80: =E80+F80+I79 -> 0 | I80: =G80-H80 -> 0 | J80: =H80/G80 -> #DIV/0!
B81: Centro Sur S.A. Pesq. | C81: 42005 | D81: 42094 | E81: 0.193 | F81: =-0.193 -> -0.193 | G81: =E81+F81 -> 0 | I81: =G81-H81 -> 0 | J81: =H81/G81 -> #DIV/0! | K81: =E81+E82 -> 0.483 | L81: =F81+F82 -> -0.483 | M81: =K81+L81 -> 0 | N81: =H81+H82 -> 0 | O81: =M81-N81 -> 0 | P81: =N81/M81 -> #DIV/0!
C82: 42095 | D82: 42369 | E82: 0.29 | F82: -0.29 | G82: =E82+F82+I81 -> 0 | I82: =G82-H82 -> 0 | J82: =H82/G82 -> #DIV/0!
B83: Foodcorp S.A. | C83: 42005 | D83: 42094 | E83: 52.708 | G83: =E83+F83 -> 52.708 | I83: =G83-H83 -> 52.708 | J83: =H83/G83 -> 0 | K83: =E83+E84 -> 131.773 | L83: =F83+F84 -> 0 | M83: =K83+L83 -> 131.773 | N83: =H83+H84 -> 0 | O83: =M83-N83 -> 131.773 | P83: =N83/M83 -> 0
C84: 42095 | D84: 42369 | E84: 79.065 | G84: =E84+F84+I83 -> 131.773 | I84: =G84-H84 -> 131.773 | J84: =H84/G84 -> 0
B85: Grimar S.A.Pesq. | C85: 42005 | D85: 42094 | E85: 536.851 | F85: =1715.159-407-400+989.965-500 -> 1398.124 | G85: =E85+F85 -> 1934.975 | H85: 1553.374 | I85: =G85-H85 -> 381.601 | J85: =H85/G85 -> 0.80278763 | K85: =E85+E86 -> 1342.155 | L85: =F85+F86 -> 1398.124 | M85: =K85+L85 -> 2740.279 | N85: =H85+H86 -> 2318.956 | O85: =M85-N85 -> 421.323 | P85: =N85/M85 -> 0.84624814
C86: 42095 | D86: 42369 | E86: 805.304 | G86: =E86+F86+I85 -> 1186.905 | H86: 765.582 | I86: =G86-H86 -> 421.323 | J86: =H86/G86 -> 0.64502382
B87: Inostroza Concha Pelantaro. | C87: 42005 | D87: 42094 | E87: 2.916 | F87: -2.916 | G87: =E87+F87 -> 0 | I87: =G87-H87 -> 0 | J87: =H87/G87 -> #DIV/0! | K87: =E87+E88 -> 7.29 | L87: =F87+F88 -> -7.29 | M87: =K87+L87 -> 0 | N87: =H87+H88 -> 0 | O87: =M87-N87 -> 0 | P87: =N87/M87 -> #DIV/0!
C88: 42095 | D88: 42369 | E88: 4.374 | F88: -4.374 | G88: =E88+F88+I87 -> 0 | I88: =G88-H88 -> 0 | J88: =H88/G88 -> #DIV/0!
B89: MG Inversiones SpA. | C89: 42005 | D89: 42094 | E89: 51.254 | F89: -51.254 | G89: =E89+F89 -> 0 | I89: =G89-H89 -> 0 | J89: =H89/G89 -> #DIV/0! | K89: =E89+E90 -> 128.137 | L89: =F89+F90 -> -128.137 | M89: =K89+L89 -> 0 | N89: =H89+H90 -> 0 | O89: =M89-N89 -> 0 | P89: =N89/M89 -> #DIV/0!
C90: 42095 | D90: 42369 | E90: 76.883 | F90: -76.883 | G90: =E90+F90+I89 -> 0 | I90: =G90-H90 -> 0 | J90: =H90/G90 -> #DIV/0!
B91: Inversiones Pesqueras SpA. | C91: 42005 | D91: 42094 | E91: 0.222 | F91: -0.222 | G91: =E91+F91 -> 0 | I91: =G91-H91 -> 0 | J91: =H91/G91 -> #DIV/0! | K91: =E91+E92 -> 0.555 | L91: =F91+F92 -> -0.555 | M91: =K91+L91 -> 0 | N91: =H91+H92 -> 0 | O91: =M91-N91 -> 0 | P91: =N91/M91 -> #DIV/0!
C92: 42095 | D92: 42369 | E92: 0.333 | F92: -0.333 | G92: =E92+F92+I91 -> 0 | I92: =G92-H92 -> 0 | J92: =H92/G92 -> #DIV/0!
B93: Isla Quihua S.A. Pesq. | C93: 42005 | D93: 42094 | E93: 91.343 | G93: =E93+F93 -> 91.343 | I93: =G93-H93 -> 91.343 | J93: =H93/G93 -> 0 | K93: =E93+E94 -> 228.363 | L93: =F93+F94 -> 0 | M93: =K93+L93 -> 228.363 | N93: =H93+H94 -> 0 | O93: =M93-N93 -> 228.363 | P93: =N93/M93 -> 0
C94: 42095 | D94: 42369 | E94: 137.02 | G94: =E94+F94+I93 -> 228.363 | I94: =G94-H94 -> 228.363 | J94: =H94/G94 -> 0
B95: Landes S.A. Soc Pesq. | C95: 42005 | D95: 42094 | E95: 455.386 | F95: -949.506 | G95: =E95+F97 -> 458.05898 | I95: =G95-H95 -> 458.05898 | J95: =H95/G95 -> 0 | K95: =E95+E96 -> 1138.489 | L95: =F95+F96 -> -949.506 | M95: =K95+L95 -> 188.983 | N95: =H95+H96 -> 0.338 | O95: =M95-N95 -> 188.645 | P95: =N95/M95 -> 0.0017885207
C96: 42095 | D96: 42369 | E96: 683.103 | G96: =E96+F98+I95 -> 1145.536 | H96: 0.338 | I96: =G96-H96 -> 1145.198 | J96: =H96/G96 -> 0.00029505839
B97: Lota Protein S.A. | C97: 42005 | D97: 42094 | E97: 285.338 | F97: =2.916-0.24302 -> 2.67298 | G97: =E97+F99 -> 285.338 | I97: =G97-H97 -> 285.338 | J97: =H97/G97 -> 0 | K97: =E97+E98 -> 713.36 | L97: =F97+F98 -> 7.04698 | M97: =K97+L97 -> 720.40698 | N97: =H97+H98 -> 0 | O97: =M97-N97 -> 720.40698 | P97: =N97/M97 -> 0
C98: 42095 | D98: 42369 | E98: 428.022 | F98: =4.374 -> 4.374 | G98: =E98+F100+I97 -> 713.36 | I98: =G98-H98 -> 713.36 | J98: =H98/G98 -> 0
B99: Mar Profundo S.a. Pesq. | C99: 42005 | D99: 42094 | E99: 68.925 | G99: =E99+F99 -> 68.925 | I99: =G99-H99 -> 68.925 | J99: =H99/G99 -> 0 | K99: =E99+E100 -> 172.317 | L99: =F99+F100 -> 0 | M99: =K99+L99 -> 172.317 | N99: =H99+H100 -> 0 | O99: =M99-N99 -> 172.317 | P99: =N99/M99 -> 0
C100: 42095 | D100: 42369 | E100: 103.392 | G100: =E100+F100+I99 -> 172.317 | I100: =G100-H100 -> 172.317 | J100: =H100/G100 -> 0
B101: Orizon S.A. | C101: 42005 | D101: 42094 | E101: 2033.867 | F101: =-2033.867 -> -2033.867 | G101: =E101+F101 -> 0 | I101: =G101-H101 -> 0 | J101: =H101/G101 -> #DIV/0! | K101: =E101+E102 -> 5084.773 | L101: =F101+F102 -> -5000 | M101: =K101+L101 -> 84.773 | N101: =H101+H102 -> 0 | O101: =M101-N101 -> 84.773 | P101: =N101/M101 -> 0
C102: 42095 | D102: 42369 | E102: 3050.906 | F102: =-2966.133 -> -2966.133 | G102: =E102+F102+I101 -> 84.773 | I102: =G102-H102 -> 84.773 | J102: =H102/G102 -> 0
B103: Deris S.A. | C103: 42005 | D103: 42094 | E103: 34.931 | F103: =-34.931 -> -34.931 | G103: =E103+F103 -> 0 | I103: =G103-H103 -> 0 | J103: =H103/G103 -> #DIV/0! | K103: =E103+E104 -> 87.33 | L103: =F103+F104 -> -87.33 | M103: =K103+L103 -> 0 | N103: =H103+H104 -> 0 | O103: =M103-N103 -> 0 | P103: =N103/M103 -> #DIV/0!
C104: 42095 | D104: 42369 | E104: 52.399 | F104: =-52.399 -> -52.399 | G104: =E104+F104+I103 -> 0 | I104: =G104-H104 -> 0 | J104: =H104/G104 -> #DIV/0!
B105: Redina SpA. INV. | C105: 42005 | D105: 42094 | E105: 24.825 | F105: -24.825 | G105: =E105+F105 -> 0 | I105: =G105-H105 -> 0 | J105: =H105/G105 -> #DIV/0! | K105: =E105+E106 -> 62.063 | L105: =F105+F106 -> -62.063 | M105: =K105+L105 -> 0 | N105: =H105+H106 -> 0 | O105: =M105-N105 -> 0 | P105: =N105/M105 -> #DIV/0!
C106: 42095 | D106: 42369 | E106: 37.238 | F106: -37.238 | G106: =E106+F106+I105 -> 0 | I106: =G106-H106 -> 0 | J106: =H106/G106 -> #DIV/0!
B107: San Antonio S.A. pesq. | C107: 42005 | D107: 42094 | E107: 25.771 | G107: =E107+F107 -> 25.771 | I107: =G107-H107 -> 25.771 | J107: =H107/G107 -> 0 | K107: =E107+E108 -> 64.428 | L107: =F107+F108 -> 0 | M107: =K107+L107 -> 64.428 | N107: =H107+H108 -> 0 | O107: =M107-N107 -> 64.428 | P107: =N107/M107 -> 0
...

Sheet DATOS BIO BIO EXCESOS
A2: Merluza comun LTP | B2: Periodo | D2: Cuota (t) | G2: Operación | J2: Resumen anual
A3: Armador | B3: Inicial | C3: Final | D3: Cuota Asignada | E3: Traspaso, Cesion, Arriendo, etc) | F3: Cuota Efectiva | G3: Desembarque (t) | H3: Saldo (t) | I3: % consumido | J3: Cuota Total | K3: Traspaso, Cesion, Arriendo, etc) | L3: Cuota Efectiva | M3: Desembarque (t) | N3: Saldo (t) | O3: % consumido
A4: Bio Bio S.A. Merluza comun LTP | B4: 42005 | C4: 42216 | D4: 3750.94 | E4: =-2574.906+32.514+107.937 -> -2434.455 | F4: =D4+E4 -> 1316.485 | G4: 1360.591 | H4: =F4-G4 -> -44.106 | I4: =G4/F4 -> 1.0335029 | J4: =D4+D5 -> 5001.253 | K4: =E4+E5 -> -4971.988 | L4: =J4+K4 -> 29.265 | M4: =G4+G5 -> 1488.978 | N4: =L4-M4 -> -1459.713 | O4: =M4/L4 -> 50.879139
B5: 42217 | C5: 42369 | D5: 1250.313 | E5: -2537.533 | F5: =D5+E5+H4 -> -1331.326 | G5: 128.387 | H5: =F5-G5 -> -1459.713 | I5: =G5/F5 -> -0.096435434
A8: DETALLES MOVIMIENTOS TRASLATICIOS Y NO TRASLATICIOS:
A10: TRASLATICIOS
A11: Fecha Resolución | B11: Resolución | C11: TIPO | D11: UNIDAD DE PESQUERÍA | E11: PARTE 1 | F11: PARTE 2 | G11: COEFICIENTE | H11: Cuota 2016 | I11: Toneladas (según cuotas 2016
A12: 42179 | B12: 2012 | C12: Compra/Venta | D12: 011 Merluza común, IV región al paralelo 41° 28,6’ L.S. | E12: GRIMAR S.A. PESQ. | F12: BIO BIO S.A. PESQ. | G12: 0.0738853 | H12: 13542 | I12: 1000.554
A13: 42389 | B13: 104 | C13: Compra/Venta | D13: 011 Merluza común, IV región al paralelo 41° 28,6’ L.S. | E13: SUR AUSTRAL S.A. PESQ. | F13: BIO BIO S.A. PESQ. | G13: 0.002401 | H13: 13542 | I13: 32.514
A14: 42389 | B14: 106 | C14: Compra/Venta | D14: 011 Merluza común, IV región al paralelo 41° 28,6’ L.S. | E14: GRIMAR S.A. PESQ. | F14: BIO BIO S.A. PESQ. | G14: 0.0079705 | H14: 13542 | I14: 107.937
A15: 42389 | B15: 107 | C15: Modifica RES.N°.2144-13 | D15: 011 Merluza común, IV región al paralelo 41° 28,6’ L.S. | E15: GRIMAR S.A. PESQ. | F15: BIO BIO S.A. PESQ. | G15: 0.0082805 | H15: 13542 | I15: 112.135
A17: TRASLATICIOS
A18: Fecha Resolución | B18: Resolución | C18: TIPO | D18: UNIDAD DE PESQUERÍA | E18: PARTE 1 | F18: PARTE 2 | G18: COEFICIENTE | H18: Cuota 2016 | I18: Toneladas (según 2016)
A19: 42212 | B19: 2013 | C19: Compra/Venta | D19: 011 Merluza común, IV región al paralelo 41° 28,6’ L.S. | E19: BIO BIO S.A. PESQ. | F19: GRIMAR S.A. PESQ. | G19: 0.0970434 | H19: 13542 | I19: 1314.162
A22: Negocios No traslaticios
A23: Fecha | B23: Nº Certificado | C23: Negocio Juridico | D23: Recurso | E23: 1 UNIDAD PESQUERIA | F23: 1 CEDENTE | G23: 2 RECEPTOR | H23: 2 UNIDAD PESQUERIA | I23: Tons.Traspaso | J23: Coeficiente | K23: Cuota 2016 | L23: Tons traspaso según valor cuota 2016 modificada | M23: Desde
A24: 41662 | B24: 156 | C24: Comodato | D24: Merluza Comun | E24: 011 MERLUZA COMÚN, IV REGIÓN AL PARALELO 41° 28,6’ L.S. | F24: BIO BIO S.A. PESQ | G24: CONGELADOS PACIFICO S.A. | I24: total cuota | M24: 41662
A25: 41675 | B25: 163 | C25: Comodato | D25: Merluza Comun | E25: 011 MERLUZA COMÚN, IV REGIÓN AL PARALELO 41° 28,6’ L.S. | F25: BIO BIO S.A. PESQ | G25: CONGELADOS PACIFICO S.A. | H25: 011 MERLUZA COMÚN, IV REGIÓN AL PARALELO 41° 28,6’ L.S. | I25: 3298.995 | J25: 0.29545 | K25: 13542 | L25: 4000.984 | M25: 41675
A26: 42405 | B26: 17 | C26: Modifica N°163-2014 en el la vigencia del comodato | D26: Merluza Comun | E26: 011 MERLUZA COMÚN, IV REGIÓN AL PARALELO 41° 28,6’ L.S. | F26: BIO BIO S.A. PESQ | G26: CONGELADOS PACIFICO S.A. | H26: 011 MERLUZA COMÚN, IV REGIÓN AL PARALELO 41° 28,6’ L.S. | M26: 42405
A27: 42492 | B27: 73 | C27: Modifica N°163-2014 modificado por cert N° 17-2016, en el sentido de resciliación parcial quedando vigente sólo comodato de 2574,906 | D27: Merluza Comun | E27: 011 MERLUZA COMÚN, IV REGIÓN AL PARALELO 41° 28,6’ L.S. | F27: BIO BIO S.A. PESQ | G27: CONGELADOS PACIFICO S.A. | H27: 011 MERLUZA COMÚN, IV REGIÓN AL PARALELO 41° 28,6’ L.S. | I27: 2574.906 | M27: 42492
A28: 42655 | B28: 120 | C28: Comodato | D28: Merluza Comun | E28: 011 MERLUZA COMÚN, IV REGIÓN AL PARALELO 41° 28,6’ L.S. | F28: BIO BIO S.A. PESQ | G28: CONGELADOS PACIFICO S.A. | H28: 011 MERLUZA COMÚN, IV REGIÓN AL PARALELO 41° 28,6’ L.S. | I28: 2537.533 | J28: 0.1873824 | K28: 13542 | L28: 2537.532 | M28: 42655
A31: Cuota Merluza Bio BIO 4001,142
A32: Documentos Respaldo | B32: Datos BIO BIO SA | C32: Datos SERNAPESCA | D32: NOTAS
A33: R. Ex. N° 2012, 27-07-2015 | B33: 1000.111 | D33: No corresponde incluir negicio 2015, se incluye en la asignación de cuota 2016
A34: R. Ex. N° 104, 20-01-2016 | B34: 3.2514 | C34: 32.514 | D34: Diferencia, ya que el Cert N°73 deja vigente coef. 0,002401 equivalente a 32,514 ton.
A35: R. Ex. N° 106, 20-01-2016 | B35: 107.937 | C35: 107.937 | D35: ok
A36: Cert.N° 73, 02-05-2016 | B36: -1426.078 | C36: -2574.906 | D36: Diferencia, ya que el Cert N°73 deja vigente coef. 0,1901422 equivalente a 2574,906 ton.
A37: Cert.N° 120, 12-10-2016 | B37: -2537.533 | C37: -2537.533 | D37: ok
B38: =SUM(B33:B37) -> -2852.3116 | C38: =SUM(C33:C37) -> -4971.988
A42: VALOR CUOTA | B42: 13542 | C42: MONTOS MOVIMIENTOS | D42: TIPO NEGOCIO
A43: R. Ex. N° 2012, 27-jul-2015 | B43: 0.07385255 | C43: =+B42*B43 -> 1000.1112 | D43: Compra a GRIMAR 2015
A44: R. Ex. N° 104, 20-01-2016 | B44: 0.002401 | C44: =+B42*B44 -> 32.514342 | D44: Compra a SUR AUSTRAL 2016
A45: R. Ex. N° 106, 20-01-2016 | B45: 0.0079705 | C45: =+B42*B45 -> 107.93651 | D45: Compra a GRIMAR 2016
A46: R. Ex. N° 107, 20-01-2016 | D46: Modifica Resol inicial por Compra-Venta-OK
A47: Cert.N° 73, 02-05-2016 | B47: -0.1901422 | C47: =+B42*B47 -> -2574.9057 | D47: Comodato parcial a CONGELADOS (resciliación Comodato N° 163-14)
A48: Cert.N° 120, 12-10-2016 | B48: -0.1873824 | C48: =+B42*B48 -> -2537.5325 | D48: Comodato a CONGELADOS
C49: =SUM(C44:C48) -> -4971.9873
A51: Merluza cola V-X LTP | B51: Periodo | D51: Cuota (t) | G51: Operación | J51: Resumen anual
A52: Armador | B52: Inicial | C52: Final | D52: Cuota Asignada | E52: Traspaso, Cesion, Arriendo, etc) | F52: Cuota Efectiva | G52: Desembarque (t) | H52: Saldo (t) | I52: % consumido | J52: Cuota Total | K52: Traspaso, Cesion, Arriendo, etc) | L52: Cuota Efectiva | M52: Desembarque (t) | N52: Saldo (t) | O52: % consumido
A53: Bio Bio S.A.Pesq. | B53: 42005 | C53: 42094 | D53: 302.58 | E53: =0.483-0.241+6.088-0.72399-755.742+949.506-949.505 -> -750.13499 | F53: =D53+E53 -> -447.55499 | G53: 61.821 | H53: =F53-G53 -> -509.37599 | I53: =G53/F53 -> -0.13813051 | J53: =D53+D54 -> 756.466 | K53: =E53+E54 -> -750.13499 | L53: =J53+K53 -> 6.33101 | M53: =G53+G54 -> 67.795 | N53: =L53-M53 -> -61.46399 | O53: =M53/L53 -> 10.708402
B54: 42095 | C54: 42369 | D54: 453.886 | F54: =D54+E54+H53 -> -55.48999 | G54: 5.974 | H54: =F54-G54 -> -61.46399 | I54: =G54/F54 -> -0.10765906
A58: Documentos Respaldo | B58: Datos BIO BIO SA | C58: Datos SERNAPESCA | D58: NOTAS
A59: R. Ex. N° 2012, 27-07-2015 | B59: 1000.111 | D59: No corresponde incluir negicio 2015, se incluye en la asignación de cuota 2016
A60: R. Ex. N° 104, 20-01-2016 | B60: 3.2514 | C60: 32.514 | D60: Diferencia, ya que el Cert N°73 deja vigente coef. 0,002401 equivalente a 32,514 ton.
A61: R. Ex. N° 106, 20-01-2016 | B61: 107.937 | C61: 107.937 | D61: ok
A62: Cert.N° 73, 02-05-2016 | B62: -1426.078 | C62: -2574.906 | D62: Diferencia, ya que el Cert N°73 deja vigente coef. 0,1901422 equivalente a 2574,906 ton.
A63: Cert.N° 120, 12-10-2016 | B63: -2537.533 | C63: -2537.533 | D63: ok
B64: =SUM(B59:B63) -> -2852.3116 | C64: =SUM(C59:C63) -> -4971.988
A67: Co) Cede 0.483 ton a Congelados Pacifico (Cert N°158-2014) Modificado por Cert N°21-2016, extiende vigencia 2016.
A68: (T) Incrementa 6.088 ton por Traspaso desde BIO BIO SA. PESQ, XI-XII (Certificado N°07/20-01-2016)
A69: (Co) Cede 0,241 ton Congelados Pacifico S.A. Cert N°18/05-02-16
A70: (C-V) Vende 0,72399 ton a BLUMAR S.A (RES.EX. N° 986/05-04-2016)
A71: (Co) Cede 755,742 ton Congelados del Pacífico S.A.. Cert N°121/12-10-16
A72: (C-V) Incrementa 949,506 ton desde LANDES S.A. (RES.EX. N° 3198/21-10-2016)
A73: (Co) Cede 949,505 ton Congelados del Pacífico S.A.. Cert N°128/15-11-16 (modificado por Cert. N° 130/2016)

Sheet Crustaceos  LTP
A1: Cuotas LTP Recursos Crustáceos Año 2016 actualizado al 27-01-2017
R2: =+R14+X14+Z14:AD15 -> #VALUE! | AP2: 0
AV3: * registra la sumatoria de los traspasos en todas las regiones
C4: Periodo | E4: Cuota II-III Región (t) | H4: Operación II y III región | K4: Cuota IV Región (t) | N4: Operación IV Región | Q4: Cuota V Región (t) | T4: Operación V Región | W4: Cuota VI Región (t) | Z4: Operación VI Región | AC4: Cuota VII Región (t) | AF4: Operación VII Región | AI4: Cuota VIII Región (t) | AL4: Operación VIII Región | AO4: Cuota y Operación Camaron Nailon II-VIII | AU4: Resumen Global Anual II-VIII
A5: Unidad de pesquería | B5: Armador | C5: Inicial | D5: Final | E5: Cuota Asignada | F5: Traspaso, Cesion, Arriendo, etc) | G5: Cuota Efectiva | H5: Desembarque (t) | I5: Saldo (t) | J5: Cuota Total | K5: Cuota Asignada | L5: Traspaso, Cesion, Arriendo, etc) | M5: Cuota Efectiva | N5: Desembarque (t) | O5: Saldo (t) | P5: Cuota Total efectiva | Q5: Cuota Asignada | R5: Traspaso, Cesion, Arriendo, etc) | S5: Cuota Efectiva | T5: Desembarque (t) | U5: Saldo (t) | V5: Cuota Total | W5: Cuota Asignada | X5: Traspaso, Cesion, Arriendo, etc) | Y5: Cuota Efectiva | Z5: Desembarque (t) | AA5: Saldo (t) | AB5: Cuota Total | AC5: Cuota Asignada | AD5: Traspaso, Cesion, Arriendo, etc) | AE5: Cuota Efectiva | AF5: Desembarque (t) | AG5: Saldo (t) | AH5: Cuota Total | AI5: Cuota Asignada | AJ5: Traspaso, Cesion, Arriendo, etc) | AK5: Cuota Efectiva | AL5: Desembarque (t) | AM5: Saldo (t) | AN5: Cuota Total | AO5: Cuota Asignada II-VIII | AP5: * Traspaso, Cesion, Arriendo, etc) | AQ5: Cuota Efectiva | AR5: Desembarque (t) II-VIII | AS5: Saldo (t) | AT5: % consumido | AU5: Cuota Total | AV5: * Traspaso, Cesion, Arriendo, etc) | AW5: Cuota Efectiva | AX5: Desembarque (t) | AY5: Saldo (t) | AZ5: % consumido
A6: Camarón nailon II-VIII | B6: ANTARTIC SEAFOOD S.A. | C6: 42005 | D6: 42216 | E6: =7.278+0.588 -> 7.866 | F6: =1.7136955+0.2145 -> 1.9281955 | G6: =E6+F6 -> 9.7941955 | I6: =G6-H6 -> 9.7941955 | J6: =E6+E7+F6+F7 -> 10.757195 | K6: =66.839+5.4 -> 72.239 | L6: =15.57905+1.95 -> 17.52905 | M6: =K6+L6 -> 89.76805 | N6: 17.59 | O6: =M6-N6 -> 72.17805 | P6: =K6+K7+L6+L7 -> 97.79505 | Q6: =97.586+7.884 -> 105.47 | R6: =22.745413+2.847 -> 25.592413 | S6: =Q6+R6 -> 131.06241 | T6: 90.05 | U6: =S6-T6 -> 41.012413 | V6: =Q6+Q7+R6+R7 -> 142.78141 | W6: =139.026+11.232 -> 150.258 | X6: =32.404424+4.056 -> 36.460424 | Y6: =W6+X6 -> 186.71842 | Z6: 98.081 | AA6: =Y6-Z6 -> 88.637424 | AB6: =W6+W7+X6+X7 -> 203.41342 | AC6: =139.026+11.232 -> 150.258 | AD6: =32.404424+4.056 -> 36.460424 | AE6: =AC6+AD6 -> 186.71842 | AF6: 191.022 | AG6: =AE6-AF6 -> -4.303576 | AH6: =AC6+AC7+AD6+AD7 -> 203.41342 | AI6: =139.159724+11.2428 -> 150.40252 | AJ6: =32.4355821+4.0599 -> 36.495482 | AK6: =AI6+AJ6 -> 186.89801 | AL6: 193.325 | AM6: =AK6-AL6 -> -6.4269939 | AN6: =AI6+AI7+AJ6+AJ7 -> 203.6094 | AO6: =E6+K6+Q6+W6+AC6+AI6 -> 636.49352 | AP6: =F6+L6+R6+X6+AD6+AJ6 -> 154.46599 | AQ6: =AO6+AP6 -> 790.95951 | AR6: =H6+N6+T6+Z6+AF6+AL6 -> 590.068 | AS6: =AQ6-AR6 -> 200.89151 | AT6: =AR6/AQ6 -> 0.74601543 | AU6: =AO6+AO7 -> 707.30392 | AV6: =AP6+AP7 -> 154.46599 | AW6: =AU6+AV6 -> 861.7699 | AX6: =AR6+AR7 -> 807.551 | AY6: =AW6-AX6 -> 54.218904 | AZ6: =AX6/AW6 -> 0.93708424
C7: 42278 | D7: 42369 | E7: =0.891+0.072 -> 0.963 | G7: =E7+F7+I6 -> 10.757195 | H7: 0.208 | I7: =G7-H7 -> 10.549195 | K7: =7.427+0.6 -> 8.027 | M7: =K7+L7+O6 -> 80.20505 | N7: 60.145 | O7: =M7-N7 -> 20.06005 | Q7: =10.843+0.876 -> 11.719 | S7: =Q7+R7+U6 -> 52.731413 | T7: 49.666 | U7: =S7-T7 -> 3.065413 | W7: =15.447+1.248 -> 16.695 | Y7: =W7+X7+AA6 -> 105.33242 | Z7: 94.979 | AA7: =Y7-Z7 -> 10.353424 | AC7: =15.447+1.248 -> 16.695 | AE7: =AC7+AD7+AG6 -> 12.391424 | AF7: 7.458 | AG7: =AE7-AF7 -> 4.933424 | AI7: =15.4621916+1.2492 -> 16.711392 | AK7: =AI7+AJ7+AM6 -> 10.284398 | AL7: 5.027 | AM7: =AK7-AL7 -> 5.2573977 | AO7: =E7+K7+Q7+W7+AC7+AI7 -> 70.810392 | AP7: =F7+L7+R7+X7+AD7+AJ7 -> 0 | AQ7: =AO7+AP7+AS6 -> 271.7019 | AR7: =H7+N7+T7+Z7+AF7+AL7 -> 217.483 | AS7: =AQ7-AR7 -> 54.218904 | AT7: =AR7/AQ7 -> 0.8004471
B8: BAYCIC BAYCIC MARIA | C8: 41640 | D8: 42216 | E8: 2.775 | F8: =-3.1134455 -> -3.1134455 | G8: =E8+F8 -> -0.3384455 | I8: =G8-H8 -> -0.3384455 | J8: =E8+E9+F8+F9 -> 0.0015545 | K8: 25.487 | L8: =-28.30405 -> -28.30405 | M8: =K8+L8 -> -2.81705 | O8: =M8-N8 -> -2.81705 | P8: =K8+K9+L8+L9 -> 0.01495 | Q8: 37.211 | R8: =-41.323913 -> -41.323913 | S8: =Q8+R8 -> -4.112913 | U8: =S8-T8 -> -4.112913 | V8: =Q8+Q9+R8+R9 -> 0.022087 | W8: 53.013 | X8: =-58.872424 -> -58.872424 | Y8: =W8+X8 -> -5.859424 | AA8: =Y8-Z8 -> -5.859424 | AB8: =W8+W9+X8+X9 -> 0.030576 | AC8: 53.013 | AD8: =-58.872424 -> -58.872424 | AE8: =AC8+AD8 -> -5.859424 | AG8: =AE8-AF8 -> -5.859424 | AH8: =AC8+AC9+AD8+AD9 -> 0.030576 | AI8: 53.064236 | AJ8: =-58.9290321 -> -58.929032 | AK8: =AI8+AJ8 -> -5.8647962 | AM8: =AK8-AL8 -> -5.8647962 | AN8: =AI8+AI9+AJ8+AJ9 -> 0.03123001 | AO8: =E8+K8+Q8+W8+AC8+AI8 -> 224.56324 | AP8: =F8+L8+R8+X8+AD8+AJ8 -> -249.41529 | AQ8: =AO8+AP8 -> -24.852053 | AR8: =H8+N8+T8+Z8+AF8+AL8 -> 0 | AS8: =AQ8-AR8 -> -24.852053 | AT8: =AR8/AQ8 -> 0 | AU8: =AO8+AO9 -> 249.54626 | AV8: =AP8+AP9 -> -249.41529 | AW8: =AU8+AV8 -> 0.13097351 | AX8: =AR8+AR9 -> 0 | AY8: =AW8-AX8 -> 0.13097351 | AZ8: =AX8/AW8 -> 0
C9: 42278 | D9: 42369 | E9: 0.34 | G9: =E9+F9+I8 -> 0.0015545 | I9: =G9-H9 -> 0.0015545 | K9: 2.832 | M9: =K9+L9+O8 -> 0.01495 | O9: =M9-N9 -> 0.01495 | Q9: 4.135 | S9: =Q9+R9+U8 -> 0.022087 | U9: =S9-T9 -> 0.022087 | W9: 5.89 | Y9: =W9+X9+AA8 -> 0.030576 | AA9: =Y9-Z9 -> 0.030576 | AC9: 5.89 | AE9: =AC9+AD9+AG8 -> 0.030576 | AG9: =AE9-AF9 -> 0.030576 | AI9: 5.8960262 | AK9: =AI9+AJ9+AM8 -> 0.03123001 | AM9: =AK9-AL9 -> 0.03123001 | AO9: =E9+K9+Q9+W9+AC9+AI9 -> 24.983026 | AP9: =F9+L9+R9+X9+AD9+AJ9 -> 0 | AQ9: =AO9+AP9+AS8 -> 0.13097351 | AR9: =H9+N9+T9+Z9+AF9+AL9 -> 0 | AS9: =AQ9-AR9 -> 0.13097351 | AT9: =AR9/AQ9 -> 0
B10: BLUMAR S.A. | C10: 41640 | D10: 42216 | E10: 0.889 | F10: =-0.0044-0.9552455 -> -0.9596455 | G10: =E10+F10 -> -0.0706455 | I10: =G10-H10 -> -0.0706455 | J10: =E10+E11+F10+F11 -> 0.0383545 | K10: 8.167 | L10: =-0.0441-0.044-8.68405 -> -8.77215 | M10: =K10+L10 -> -0.60515 | O10: =M10-N10 -> -0.60515 | P10: =K10+K11+L10+L11 -> 0.30185 | Q10: 11.924 | R10: =-0.0441-0.0584-12.678713 -> -12.781213 | S10: =Q10+R10 -> -0.857213 | U10: =S10-T10 -> -0.857213 | V10: =Q10+Q11+R10+R11 -> 0.467787 | W10: 16.987 | X10: =-0.0441-0.0832-18.062824 -> -18.190124 | Y10: =W10+X10 -> -1.203124 | AA10: =Y10-Z10 -> -1.203124 | AB10: =W10+W11+X10+X11 -> 0.683876 | AC10: 16.987 | AD10: =-0.0441-0.0832-18.062824 -> -18.190124 | AE10: =AC10+AD10 -> -1.203124 | AG10: =AE10-AF10 -> -1.203124 | AH10: =AC10+AC11+AD10+AD11 -> 0.683876 | AI10: 17.00333 | AJ10: =-0.0441-0.08328-18.0801921 -> -18.207572 | AK10: =AI10+AJ10 -> -1.2042424 | AM10: =AK10-AL10 -> -1.2042424 | AN10: =AI10+AI11+AJ10+AJ11 -> 0.68501645 | AO10: =E10+K10+Q10+W10+AC10+AI10 -> 71.95733 | AP10: =F10+L10+R10+X10+AD10+AJ10-0.66106-2.20353 -> -79.965419 | AQ10: =AO10+AP10 -> -8.0080889 | AR10: =H10+N10+T10+Z10+AF10+AL10 -> 0 | AS10: =AQ10-AR10 -> -8.0080889 | AT10: =AR10/AQ10 -> 0 | AU10: =AO10+AO11 -> 79.961589 | AV10: =AP10+AP11 -> -79.965419 | AW10: =AU10+AV10 -> -0.00383005 | AX10: =AR10+AR11 -> 0 | AY10: =AW10-AX10 -> -0.00383005 | AZ10: =AX10/AW10 -> 0
C11: 42278 | D11: 42369 | E11: 0.109 | G11: =E11+F11+I10 -> 0.0383545 | I11: =G11-H11 -> 0.0383545 | K11: 0.907 | M11: =K11+L11+O10 -> 0.30185 | O11: =M11-N11 -> 0.30185 | Q11: 1.325 | S11: =Q11+R11+U10 -> 0.467787 | U11: =S11-T11 -> 0.467787 | W11: 1.887 | Y11: =W11+X11+AA10 -> 0.683876 | AA11: =Y11-Z11 -> 0.683876 | AC11: 1.887 | AE11: =AC11+AD11+AG10 -> 0.683876 | AG11: =AE11-AF11 -> 0.683876 | AI11: 1.8892589 | AK11: =AI11+AJ11+AM10 -> 0.68501645 | AM11: =AK11-AL11 -> 0.68501645 | AO11: =E11+K11+Q11+W11+AC11+AI11 -> 8.0042588 | AP11: =F11+L11+R11+X11+AD11+AJ11 -> 0 | AQ11: =AO11+AP11+AS10 -> -0.00383005 | AR11: =H11+N11+T11+Z11+AF11+AL11 -> 0 | AS11: =AQ11-AR11 -> -0.00383005 | AT11: =AR11/AQ11 -> 0
B12: BRACPESCA S.A. | C12: 41640 | D12: 42216 | E12: =7.147+0.442 -> 7.589 | F12: =0.9552455+0.37125 -> 1.3264955 | G12: =E12+F12 -> 8.9154955 | I12: =G12-H12 -> 8.9154955 | J12: =E12+E13+F12+F13 -> 9.8444955 | K12: =65.634+4.05 -> 69.684 | L12: =21.17-59.82+8.68405+3.375 -> -26.59095 | M12: =K12+L12 -> 43.09305 | N12: 10.776 | O12: =M12-N12 -> 32.31705 | P12: =K12+K13+L12+L13 -> 50.83605 | Q12: =95.826+5.914 -> 101.74 | R12: =12.678713+4.9275 -> 17.606213 | S12: =Q12+R12 -> 119.34621 | T12: 73.648 | U12: =S12-T12 -> 45.698213 | V12: =Q12+Q13+R12+R13 -> 130.65121 | W12: =136.519+8.424 -> 144.943 | X12: =18.062824+7.02 -> 25.082824 | Y12: =W12+X12 -> 170.02582 | Z12: 59.869 | AA12: =Y12-Z12 -> 110.15682 | AB12: =W12+W13+X12+X13 -> 186.13082 | AC12: =136.519+8.424 -> 144.943 | AD12: =18.062824+7.02 -> 25.082824 | AE12: =AC12+AD12 -> 170.02582 | AF12: 135.719 | AG12: =AE12-AF12 -> 34.306824 | AH12: =AC12+AC13+AD12+AD13 -> 186.13082 | AI12: =136.65005+8.4321 -> 145.08215 | AJ12: =18.0801921+7.02675 -> 25.106942 | AK12: =AI12+AJ12 -> 170.18909 | AL12: 133.38 | AM12: =AK12-AL12 -> 36.809092 | AN12: =AI12+AI13+AJ12+AJ13 -> 186.30933 | AO12: =E12+K12+Q12+W12+AC12+AI12 -> 613.98115 | AP12: =F12+L12+R12+X12+AD12+AJ12 -> 67.614349 | AQ12: =AO12+AP12 -> 681.5955 | AR12: =H12+N12+T12+Z12+AF12+AL12 -> 413.392 | AS12: =AQ12-AR12 -> 268.2035 | AT12: =AR12/AQ12 -> 0.60650635 | AU12: =AO12+AO13 -> 682.28839 | AV12: =AP12+AP13 -> 67.614349 | AW12: =AU12+AV12 -> 749.90274 | AX12: =AR12+AR13 -> 481.66 | AY12: =AW12-AX12 -> 268.24274 | AZ12: =AX12/AW12 -> 0.64229663
C13: 42278 | D13: 42369 | E13: =0.875+0.054 -> 0.929 | G13: =E13+F13+I12 -> 9.8444955 | I13: =G13-H13 -> 9.8444955 | K13: =7.293+0.45 -> 7.743 | M13: =K13+L13+O12 -> 40.06005 | N13: 1.106 | O13: =M13-N13 -> 38.95405 | Q13: =10.647+0.658 -> 11.305 | S13: =Q13+R13+U12 -> 57.003213 | U13: =S13-T13 -> 57.003213 | W13: =15.169+0.936 -> 16.105 | Y13: =W13+X13+AA12 -> 126.26182 | Z13: 9.157 | AA13: =Y13-Z13 -> 117.10482 | AC13: =15.169+0.936 -> 16.105 | AE13: =AC13+AD13+AG12 -> 50.411824 | AF13: 41.517 | AG13: =AE13-AF13 -> 8.894824 | AI13: =15.1833389+0.9369 -> 16.120239 | AK13: =AI13+AJ13+AM12 -> 52.929331 | AL13: 16.488 | AM13: =AK13-AL13 -> 36.441331 | AO13: =E13+K13+Q13+W13+AC13+AI13 -> 68.307239 | AP13: =F13+L13+R13+X13+AD13+AJ13 -> 0 | AQ13: =AO13+AP13+AS12 -> 336.51074 | AR13: =H13+N13+T13+Z13+AF13+AL13 -> 68.268 | AS13: =AQ13-AR13 -> 268.24274 | AT13: =AR13/AQ13 -> 0.2028702
B14: CAMANCHACA PESCA SUR S.A. | C14: 41640 | D14: 42216 | E14: =0.037+0.221 -> 0.258 | F14: =-0.0000404*55 -> -0.002222 | G14: =E14+F14 -> 0.255778 | I14: =G14-H14 -> 0.255778 | J14: =E14+E15+F14+F15 -> 0.287778 | K14: =0.341+2.025 -> 2.366 | L14: =-0.0000404*500 -> -0.0202 | M14: =K14+L14 -> 2.3458 | O14: =M14-N14 -> 2.3458 | P14: =K14+K15+L14+L15 -> 2.6088 | Q14: =0.497+2.957 -> 3.454 | R14: =-0.04445-0.0295 -> -0.07395 | S14: =Q14+R14 -> 3.38005 | U14: =S14-T14 -> 3.38005 | V14: =Q14+Q15+R14+R15 -> 3.76405 | W14: =0.708+4.212 -> 4.92 | X14: =-0.04445-0.042 -> -0.08645 | Y14: =W14+X14 -> 4.83355 | AA14: =Y14-Z14 -> 4.83355 | AB14: =W14+W15+X14+X15 -> 5.38055 | AC14: =0.708+4.212 -> 4.92 | AD14: =-0.04445-0.042 -> -0.08645 | AE14: =AC14+AD14 -> 4.83355 | AF14: 1.951 | AG14: =AE14-AF14 -> 2.88255 | AH14: =AC14+AC15+AD14+AD15 -> 5.38055 | AI14: =0.70904592+4.21605 -> 4.9250959 | AJ14: =-0.04445-0.0421 -> -0.08655 | AK14: =AI14+AJ14 -> 4.8385459 | AL14: 2.765 | AM14: =AK14-AL14 -> 2.0735459 | AN14: =AI14+AI15+AJ14+AJ15 -> 5.3857788 | AO14: =E14+K14+Q14+W14+AC14+AI14 -> 20.843096 | AP14: =F14+L14+R14+X14+AD14+AJ14 -> -0.355822 | AQ14: =AO14+AP14 -> 20.487274 | AR14: =H14+N14+T14+Z14+AF14+AL14 -> 4.716 | AS14: =AQ14-AR14 -> 15.771274 | AT14: =AR14/AQ14 -> 0.23019168 | AU14: =AO14+AO15 -> 23.163329 | AV14: =AP14+AP15 -> -0.355822 | AW14: =AU14+AV14 -> 22.807507 | AX14: =AR14+AR15 -> 5.045 | AY14: =AW14-AX14 -> 17.762507 | AZ14: =AX14/AW14 -> 0.2211991
C15: 42278 | D15: 42369 | E15: =0.005+0.027 -> 0.032 | G15: =E15+F15+I14 -> 0.287778 | I15: =G15-H15 -> 0.287778 | K15: =0.038+0.225 -> 0.263 | M15: =K15+L15+O14 -> 2.6088 | O15: =M15-N15 -> 2.6088 | Q15: =0.055+0.329 -> 0.384 | S15: =Q15+R15+U14 -> 3.76405 | U15: =S15-T15 -> 3.76405 | W15: =0.079+0.468 -> 0.547 | Y15: =W15+X15+AA14 -> 5.38055 | AA15: =Y15-Z15 -> 5.38055 | AC15: =0.079+0.468 -> 0.547 | AE15: =AC15+AD15+AG14 -> 3.42955 | AF15: 0.094 | AG15: =AE15-AF15 -> 3.33555 | AI15: =0.07878288+0.46845 -> 0.54723288 | AK15: =AI15+AJ15+AM14 -> 2.6207788 | AL15: 0.235 | AM15: =AK15-AL15 -> 2.3857788 | AO15: =E15+K15+Q15+W15+AC15+AI15 -> 2.3202329 | AP15: =F15+L15+R15+X15+AD15+AJ15 -> 0 | AQ15: =AO15+AP15+AS14 -> 18.091507 | AR15: =H15+N15+T15+Z15+AF15+AL15 -> 0.329 | AS15: =AQ15-AR15 -> 17.762507 | AT15: =AR15/AQ15 -> 0.018185329
B16: COSTA BRAVA LTDA. PESQ. | C16: 41640 | D16: 42216 | E16: 1.015 | F16: =-1.1389785 -> -1.1389785 | G16: =E16+F16 -> -0.1239785 | I16: =G16-H16 -> -0.1239785 | J16: =E16+E17+F16+F17 -> 2.15e-05 | K16: 9.319 | L16: =-10.35435 -> -10.35435 | M16: =K16+L16 -> -1.03535 | O16: =M16-N16 -> -1.03535 | P16: =K16+K17+L16+L17 -> -0.00035 | Q16: 13.606 | R16: =-15.117351 -> -15.117351 | S16: =Q16+R16 -> -1.511351 | U16: =S16-T16 -> -1.511351 | V16: =Q16+Q17+R16+R17 -> 0.000649 | W16: 19.383 | X16: =-21.537048 -> -21.537048 | Y16: =W16+X16 -> -2.154048 | AA16: =Y16-Z16 -> -2.154048 | AB16: =W16+W17+X16+X17 -> -4.8e-05 | AC16: 19.383 | AD16: =-21.537048 -> -21.537048 | AE16: =AC16+AD16 -> -2.154048 | AG16: =AE16-AF16 -> -2.154048 | AH16: =AC16+AC17+AD16+AD17 -> -4.8e-05 | AI16: 19.401981 | AJ16: =-21.5577567 -> -21.557757 | AK16: =AI16+AJ16 -> -2.1557757 | AM16: =AK16-AL16 -> -2.1557757 | AN16: =AI16+AI17+AJ16+AJ17 -> -2.9999999e-08 | AO16: =E16+K16+Q16+W16+AC16+AI16 -> 82.107981 | AP16: =F16+L16+R16+X16+AD16+AJ16 -> -91.242532 | AQ16: =AO16+AP16 -> -9.1345512 | AR16: =H16+N16+T16+Z16+AF16+AL16 -> 0 | AS16: =AQ16-AR16 -> -9.1345512 | AT16: =AR16/AQ16 -> 0 | AU16: =AO16+AO17 -> 91.242757 | AV16: =AP16+AP17 -> -91.242532 | AW16: =AU16+AV16 -> 0.00022447 | AX16: =AR16+AR17 -> 0 | AY16: =AW16-AX16 -> 0.00022447 | AZ16: =AX16/AW16 -> 0
C17: 42278 | D17: 42369 | E17: 0.124 | G17: =E17+F17+I16 -> 2.15e-05 | I17: =G17-H17 -> 2.15e-05 | K17: 1.035 | M17: =K17+L17+O16 -> -0.00035 | O17: =M17-N17 -> -0.00035 | Q17: 1.512 | S17: =Q17+R17+U16 -> 0.000649 | U17: =S17-T17 -> 0.000649 | W17: 2.154 | Y17: =W17+X17+AA16 -> -4.8e-05 | AA17: =Y17-Z17 -> -4.8e-05 | AC17: 2.154 | AE17: =AC17+AD17+AG16 -> -4.8e-05 | AG17: =AE17-AF17 -> -4.8e-05 | AI17: 2.1557757 | AK17: =AI17+AJ17+AM16 -> -2.9999999e-08 | AM17: =AK17-AL17 -> -2.9999999e-08 | AO17: =E17+K17+Q17+W17+AC17+AI17 -> 9.1347757 | AP17: =F17+L17+R17+X17+AD17+AJ17 -> 0 | AQ17: =AO17+AP17+AS16 -> 0.00022447 | AR17: =H17+N17+T17+Z17+AF17+AL17 -> 0 | AS17: =AQ17-AR17 -> 0.00022447 | AT17: =AR17/AQ17 -> 0
B18: GRIMAR S.A. PESQ. | C18: 41640 | D18: 42216 | E18: 0.139 | G18: =E18+F18 -> 0.139 | I18: =G18-H18 -> 0.139 | J18: =E18+E19+F18+F19 -> 0.156 | K18: 1.278 | M18: =K18+L18 -> 1.278 | O18: =M18-N18 -> 1.278 | P18: =K18+K19+L18+L19 -> 1.42 | Q18: 1.865 | S18: =Q18+R18 -> 1.865 | U18: =S18-T18 -> 1.865 | V18: =Q18+Q19+R18+R19 -> 2.072 | W18: 2.657 | Y18: =W18+X18 -> 2.657 | AA18: =Y18-Z18 -> 2.657 | AB18: =W18+W19+X18+X19 -> 2.952 | AC18: 2.657 | AE18: =AC18+AD18 -> 2.657 | AG18: =AE18-AF18 -> 2.657 | AH18: =AC18+AC19+AD18+AD19 -> 2.952 | AI18: 2.6598591 | AK18: =AI18+AJ18 -> 2.6598591 | AM18: =AK18-AL18 -> 2.6598591 | AN18: =AI18+AI19+AJ18+AJ19 -> 2.955399 | AO18: =E18+K18+Q18+W18+AC18+AI18 -> 11.255859 | AP18: =F18+L18+R18+X18+AD18+AJ18 -> 0 | AQ18: =AO18+AP18 -> 11.255859 | AR18: =H18+N18+T18+Z18+AF18+AL18 -> 0 | AS18: =AQ18-AR18 -> 11.255859 | AT18: =AR18/AQ18 -> 0 | AU18: =AO18+AO19 -> 12.507399 | AV18: =AP18+AP19 -> 0 | AW18: =AU18+AV18 -> 12.507399 | AX18: =AR18+AR19 -> 0 | AY18: =AW18-AX18 -> 12.507399 | AZ18: =AX18/AW18 -> 0
C19: 42278 | D19: 42369 | E19: 0.017 | G19: =E19+F19+I18 -> 0.156 | I19: =G19-H19 -> 0.156 | K19: 0.142 | M19: =K19+L19+O18 -> 1.42 | O19: =M19-N19 -> 1.42 | Q19: 0.207 | S19: =Q19+R19+U18 -> 2.072 | U19: =S19-T19 -> 2.072 | W19: 0.295 | Y19: =W19+X19+AA18 -> 2.952 | AA19: =Y19-Z19 -> 2.952 | AC19: 0.295 | AE19: =AC19+AD19+AG18 -> 2.952 | AG19: =AE19-AF19 -> 2.952 | AI19: 0.2955399 | AK19: =AI19+AJ19+AM18 -> 2.955399 | AM19: =AK19-AL19 -> 2.955399 | AO19: =E19+K19+Q19+W19+AC19+AI19 -> 1.2515399 | AP19: =F19+L19+R19+X19+AD19+AJ19 -> 0 | AQ19: =AO19+AP19+AS18 -> 12.507399 | AR19: =H19+N19+T19+Z19+AF19+AL19 -> 0 | AS19: =AQ19-AR19 -> 12.507399 | AT19: =AR19/AQ19 -> 0
B20: ISLADAMAS S.A. PESQ. | C20: 41640 | D20: 42216 | E20: =6.423+0.368 -> 6.791 | F20: =0.0998855+0.561+0.14025+2.5047+1.1389785+2.0301215+0.2475+0.2475+0.12925 -> 7.0991855 | G20: =E20+F20 -> 13.890185 | I20: =G20-H20 -> 13.890185 | J20: =E20+E21+F20+F21 -> 14.721186 | K20: =58.987+3.375 -> 62.362 | L20: =0.90805+5.1+1.275+22.77+10.35435+18.45565+2.25+2.25+1.175 -> 64.53805 | M20: =K20+L20 -> 126.90005 | N20: 13.864 | O20: =M20-N20 -> 113.03605 | P20: =K20+K21+L20+L21 -> 133.82905 | Q20: =86.121+4.928 -> 91.049 | R20: =1.325753+7.446+1.8615+33.2442+15.117351+26.945249+3.285+3.285+1.7155 -> 94.225553 | S20: =Q20+R20 -> 185.27455 | T20: =82.975+3.583 -> 86.558 | U20: =S20-T20 -> 98.716553 | V20: =Q20+Q21+X20+R21 -> 235.40514 | W20: =122.693+7.02 -> 129.713 | X20: =1.888744+10.608+2.652+47.3616+21.537048+38.387752+4.68+4.68+2.444 -> 134.23914 | Y20: =W20+X20 -> 263.95214 | Z20: =82.781+2.723 -> 85.504 | AA20: =Y20-Z20 -> 178.44814 | AB20: =W20+W21+X20+X21 -> 278.36514 | AC20: =122.693+7.02 -> 129.713 | AD20: =1.888744+10.608+2.652+47.3616+21.537048+38.387752+4.68+4.68+2.444 -> 134.23914 | AE20: =AC20+AD20 -> 263.95214 | AF20: =171.553+36.502 -> 208.055 | AG20: =AE20-AF20 -> 55.897144 | AH20: =AC20+AC21+AD20+AD21 -> 278.36514 | AI20: =122.811007+7.02675 -> 129.83776 | AJ20: =1.8905601+10.6182+2.65455+47.40714+21.5577567+38.4246633+4.6845+4.6845+2.44635 -> 134.36822 | AK20: =AI20+AJ20 -> 264.20598 | AL20: =75.292+13.687 -> 88.979 | AM20: =AK20-AL20 -> 175.22698 | AN20: =AI20+AI21+AJ20+AJ21 -> 278.63239 | AO20: =E20+K20+Q20+W20+AC20+AI20 -> 549.46576 | AP20: =F20+L20+R20+X20+AD20+AJ20 -> 568.7093 | AQ20: =AO20+AP20 -> 1118.1751 | AR20: =H20+N20+T20+Z20+AF20+AL20 -> 482.96 | AS20: =AQ20-AR20 -> 635.21505 | AT20: =AR20/AQ20 -> 0.43191806 | AU20: =AO20+AO21 -> 610.59517 | AV20: =AP20+AP21 -> 568.7093 | AW20: =AU20+AV20 -> 1179.3045 | AX20: =AR20+AR21 -> 856.434 | AY20: =AW20-AX20 -> 322.87047 | AZ20: =AX20/AW20 -> 0.72621958
C21: 42278 | D21: 42369 | E21: =0.786+0.045 -> 0.831 | G21: =E21+F21+I20 -> 14.721185 | I21: =G21-H21 -> 14.721185 | K21: =6.554+0.375 -> 6.929 | M21: =K21+L21+O20 -> 119.96505 | N21: =20.92+5.079 -> 25.999 | O21: =M21-N21 -> 93.96605 | Q21: =9.569+0.548 -> 10.117 | S21: =Q21+R21+U20 -> 108.83355 | T21: 73.955 | U21: =S21-T21 -> 34.878553 | W21: =13.633+0.78 -> 14.413 | Y21: =W21+X21+AA20 -> 192.86114 | Z21: 35.686 | AA21: =Y21-Z21 -> 157.17514 | AC21: =13.633+0.78 -> 14.413 | AE21: =AC21+AD21+AG20 -> 70.310144 | AF21: 66.251 | AG21: =AE21-AF21 -> 4.059144 | AI21: =13.6456674+0.78075 -> 14.426417 | AK21: =AI21+AJ21+AM20 -> 189.65339 | AL21: 171.583 | AM21: =AK21-AL21 -> 18.070395 | AO21: =E21+K21+Q21+W21+AC21+AI21 -> 61.129417 | AP21: =F21+L21+R21+X21+AD21+AJ21 -> 0 | AQ21: =AO21+AP21+AS20 -> 696.34447 | AR21: =H21+N21+T21+Z21+AF21+AL21 -> 373.474 | AS21: =AQ21-AR21 -> 322.87047 | AT21: =AR21/AQ21 -> 0.53633513
B22: LANDES S.A. SOC. PESQ. | C22: 41640 | D22: 42216 | E22: 0.076 | G22: =E22+F22 -> 0.076 | I22: =G22-H22 -> 0.076 | J22: =E22+E23+F22+F23 -> 0.085 | K22: 0.697 | M22: =K22+L22 -> 0.697 | O22: =M22-N22 -> 0.697 | P22: =K22+K23+L22+L23 -> 0.774 | Q22: 1.018 | S22: =Q22+R22 -> 1.018 | U22: =S22-T22 -> 1.018 | V22: =Q22+Q23+R22+R23 -> 1.131 | W22: 1.451 | Y22: =W22+X22 -> 1.451 | AA22: =Y22-Z22 -> 1.451 | AB22: =W22+W23+X22+X23 -> 1.612 | AC22: 1.451 | AE22: =AC22+AD22 -> 1.451 | AG22: =AE22-AF22 -> 1.451 | AH22: =AC22+AC23+AD22+AD23 -> 1.612 | AI22: 1.4519139 | AK22: =AI22+AJ22 -> 1.4519139 | AM22: =AK22-AL22 -> 1.4519139 | AN22: =AI22+AI23+AJ22+AJ23 -> 1.6132377 | AO22: =E22+K22+Q22+W22+AC22+AI22 -> 6.1449139 | AP22: =F22+L22+R22+X22+AD22+AJ22 -> 0 | AQ22: =AO22+AP22 -> 6.1449139 | AR22: =H22+N22+T22+Z22+AF22+AL22 -> 0 | AS22: =AQ22-AR22 -> 6.1449139 | AT22: =AR22/AQ22 -> 0 | AU22: =AO22+AO23 -> 6.8272377 | AV22: =AP22+AP23 -> 0 | AW22: =AU22+AV22 -> 6.8272377 | AX22: =AR22+AR23 -> 0 | AY22: =AW22-AX22 -> 6.8272377 | AZ22: =AX22/AW22 -> 0
C23: 42278 | D23: 42369 | E23: 0.009 | G23: =E23+F23+I22 -> 0.085 | I23: =G23-H23 -> 0.085 | K23: 0.077 | M23: =K23+L23+O22 -> 0.774 | O23: =M23-N23 -> 0.774 | Q23: 0.113 | S23: =Q23+R23+U22 -> 1.131 | U23: =S23-T23 -> 1.131 | W23: 0.161 | Y23: =W23+X23+AA22 -> 1.612 | AA23: =Y23-Z23 -> 1.612 | AC23: 0.161 | AE23: =AC23+AD23+AG22 -> 1.612 | AG23: =AE23-AF23 -> 1.612 | AI23: 0.16132377 | AK23: =AI23+AJ23+AM22 -> 1.6132377 | AM23: =AK23-AL23 -> 1.6132377 | AO23: =E23+K23+Q23+W23+AC23+AI23 -> 0.68232377 | AP23: =F23+L23+R23+X23+AD23+AJ23 -> 0 | AQ23: =AO23+AP23+AS22 -> 6.8272377 | AR23: =H23+N23+T23+Z23+AF23+AL23 -> 0 | AS23: =AQ23-AR23 -> 6.8272377 | AT23: =AR23/AQ23 -> 0
B24: MOROZIN BAYCIC MARIA ANA | C24: 41640 | D24: 42216 | E24: 1.592 | F24: =-1.7850635 -> -1.7850635 | G24: =E24+F24 -> -0.1930635 | I24: =G24-H24 -> -0.1930635 | J24: =E24+E25+F24+F25 -> 0.0019365 | K24: 14.619 | L24: =-16.22785 -> -16.22785 | M24: =K24+L24 -> -1.60885 | O24: =M24-N24 -> -1.60885 | P24: =K24+K25+L24+L25 -> 0.01515 | Q24: 21.343 | R24: =-23.692661 -> -23.692661 | S24: =Q24+R24 -> -2.349661 | U24: =S24-T24 -> -2.349661 | V24: =Q24+Q25+R24+R25 -> 0.021339 | W24: 30.407 | X24: =-33.753928 -> -33.753928 | Y24: =W24+X24 -> -3.346928 | AA24: =Y24-Z24 -> -3.346928 | AB24: =W24+W25+X24+X25 -> 0.032072 | AC24: 30.407 | AD24: =-33.753928 -> -33.753928 | AE24: =AC24+AD24 -> -3.346928 | AG24: =AE24-AF24 -> -3.346928 | AH24: =AC24+AC25+AD24+AD25 -> 0.032072 | AI24: 30.435852 | AJ24: =-33.7863837 -> -33.786384 | AK24: =AI24+AJ24 -> -3.3505314 | AM24: =AK24-AL24 -> -3.3505314 | AN24: =AI24+AI25+AJ24+AJ25 -> 0.03122997 | AO24: =E24+K24+Q24+W24+AC24+AI24 -> 128.80385 | AP24: =F24+L24+R24+X24+AD24+AJ24 -> -142.99981 | AQ24: =AO24+AP24 -> -14.195962 | AR24: =H24+N24+T24+Z24+AF24+AL24 -> 0 | AS24: =AQ24-AR24 -> -14.195962 | AT24: =AR24/AQ24 -> 0 | AU24: =AO24+AO25 -> 143.13361 | AV24: =AP24+AP25 -> -142.99981 | AW24: =AU24+AV24 -> 0.13379947 | AX24: =AR24+AR25 -> 0 | AY24: =AW24-AX24 -> 0.13379947 | AZ24: =AX24/AW24 -> 0
C25: 42278 | D25: 42369 | E25: 0.195 | G25: =E25+F25+I24 -> 0.0019365 | I25: =G25-H25 -> 0.0019365 | K25: 1.624 | M25: =K25+L25+O24 -> 0.01515 | O25: =M25-N25 -> 0.01515 | Q25: 2.371 | S25: =Q25+R25+U24 -> 0.021339 | U25: =S25-T25 -> 0.021339 | W25: 3.379 | Y25: =W25+X25+AA24 -> 0.032072 | AA25: =Y25-Z25 -> 0.032072 | AC25: 3.379 | AE25: =AC25+AD25+AG24 -> 0.032072 | AG25: =AE25-AF25 -> 0.032072 | AI25: 3.3817614 | AK25: =AI25+AJ25+AM24 -> 0.03122997 | AM25: =AK25-AL25 -> 0.03122997 | AO25: =E25+K25+Q25+W25+AC25+AI25 -> 14.329761 | AP25: =F25+L25+R25+X25+AD25+AJ25 -> 0 | AQ25: =AO25+AP25+AS24 -> 0.13379947 | AR25: =H25+N25+T25+Z25+AF25+AL25 -> 0 | AS25: =AQ25-AR25 -> 0.13379947 | AT25: =AR25/AQ25 -> 0
B26: MOROZIN YURECIC MARIO | C26: 41640 | D26: 42216 | E26: 3.59 | F26: =-4.0280295 -> -4.0280295 | G26: =E26+F26 -> -0.4380295 | I26: =G26-H26 -> -0.4380295 | J26: =E26+E27+F26+F27 -> 0.0019705 | K26: 32.97 | L26: =-36.61845 -> -36.61845 | M26: =K26+L26 -> -3.64845 | O26: =M26-N26 -> -3.64845 | P26: =K26+K27+L26+L27 -> 0.01455 | Q26: 48.136 | R26: =-53.462937 -> -53.462937 | S26: =Q26+R26 -> -5.326937 | U26: =S26-T26 -> -5.326937 | V26: =Q26+Q27+R26+R27 -> 0.021063 | W26: 68.5778 | X26: =-76.166376 -> -76.166376 | Y26: =W26+X26 -> -7.588576 | AA26: =Y26-Z26 -> -7.588576 | AB26: =W26+W27+X26+X27 -> 0.031424 | AC26: 68.578 | AD26: =-76.166376 -> -76.166376 | AE26: =AC26+AD26 -> -7.588376 | AG26: =AE26-AF26 -> -7.588376 | AH26: =AC26+AC27+AD26+AD27 -> 0.031624 | AI26: 68.643759 | AJ26: =-76.2396129 -> -76.239613 | AK26: =AI26+AJ26 -> -7.5958543 | AM26: =AK26-AL26 -> -7.5958543 | AN26: =AI26+AI27+AJ26+AJ27 -> 0.03122999 | AO26: =E26+K26+Q26+W26+AC26+AI26 -> 290.49556 | AP26: =F26+L26+R26+X26+AD26+AJ26 -> -322.68178 | AQ26: =AO26+AP26 -> -32.186223 | AR26: =H26+N26+T26+Z26+AF26+AL26 -> 0 | AS26: =AQ26-AR26 -> -32.186223 | AT26: =AR26/AQ26 -> 0 | AU26: =AO26+AO27 -> 322.81364 | AV26: =AP26+AP27 -> -322.68178 | AW26: =AU26+AV26 -> 0.13186149 | AX26: =AR26+AR27 -> 0 | AY26: =AW26-AX26 -> 0.13186149 | AZ26: =AX26/AW26 -> 0
C27: 42278 | D27: 42369 | E27: 0.44 | G27: =E27+F27+I26 -> 0.0019705 | I27: =G27-H27 -> 0.0019705 | K27: 3.663 | M27: =K27+L27+O26 -> 0.01455 | O27: =M27-N27 -> 0.01455 | Q27: 5.348 | S27: =Q27+R27+U26 -> 0.021063 | U27: =S27-T27 -> 0.021063 | W27: 7.62 | Y27: =W27+X27+AA26 -> 0.031424 | AA27: =Y27-Z27 -> 0.031424 | AC27: 7.62 | AE27: =AC27+AD27+AG26 -> 0.031624 | AG27: =AE27-AF27 -> 0.031624 | AI27: 7.6270843 | AK27: =AI27+AJ27+AM26 -> 0.03122999 | AM27: =AK27-AL27 -> 0.03122999 | AO27: =E27+K27+Q27+W27+AC27+AI27 -> 32.318084 | AP27: =F27+L27+R27+X27+AD27+AJ27 -> 0 | AQ27: =AO27+AP27+AS26 -> 0.13186149 | AR27: =H27+N27+T27+Z27+AF27+AL27 -> 0 | AS27: =AQ27-AR27 -> 0.13186149 | AT27: =AR27/AQ27 -> 0
B28: QUINTERO LTDA. SOC. PESQ. | C28: 41640 | D28: 42216 | E28: 0.859 | F28: =-0.9636165 -> -0.9636165 | G28: =E28+F28 -> -0.1046165 | I28: =G28-H28 -> -0.1046165 | J28: =E28+E29+F28+F29 -> 0.0003835 | K28: 7.893 | L28: =-8.76015 -> -8.76015 | M28: =K28+L28 -> -0.86715 | O28: =M28-N28 -> -0.86715 | P28: =K28+K29+L28+L29 -> 0.00985 | Q28: 11.524 | R28: =-12.789819 -> -12.789819 | S28: =Q28+R28 -> -1.265819 | U28: =S28-T28 -> -1.265819 | V28: =Q28+Q29+R28+R29 -> 0.014181 | W28: 16.418 | X28: =-18.221112 -> -18.221112 | Y28: =W28+X28 -> -1.803112 | Z28: 0.105 | AA28: =Y28-Z28 -> -1.908112 | AB28: =W28+W29+X28+X29 -> 0.020888 | AC28: 16.418 | AD28: =-18.221112 -> -18.221112 | AE28: =AC28+AD28 -> -1.803112 | AG28: =AE28-AF28 -> -1.803112 | AH28: =AC28+AC29+AD28+AD29 -> 0.020888 | AI28: 16.433507 | AJ28: =-18.2386323 -> -18.238632 | AK28: =AI28+AJ28 -> -1.8051252 | AM28: =AK28-AL28 -> -1.8051252 | AN28: =AI28+AI29+AJ28+AJ29 -> 0.02082003 | AO28: =E28+K28+Q28+W28+AC28+AI28 -> 69.545507 | AP28: =F28+L28+R28+X28+AD28+AJ28 -> -77.194442 | AQ28: =AO28+AP28 -> -7.6489347 | AR28: =H28+N28+T28+Z28+AF28+AL28 -> 0.105 | AS28: =AQ28-AR28 -> -7.7539347 | AT28: =AR28/AQ28 -> -0.013727402 | AU28: =AO28+AO29 -> 77.281452 | AV28: =AP28+AP29 -> -77.194442 | AW28: =AU28+AV28 -> 0.08701053 | AX28: =AR28+AR29 -> 0.105 | AY28: =AW28-AX28 -> -0.01798947 | AZ28: =AX28/AW28 -> 1.2067505
C29: 42278 | D29: 42369 | E29: 0.105 | G29: =E29+F29+I28 -> 0.0003835 | I29: =G29-H29 -> 0.0003835 | K29: 0.877 | M29: =K29+L29+O28 -> 0.00985 | O29: =M29-N29 -> 0.00985 | Q29: 1.28 | S29: =Q29+R29+U28 -> 0.014181 | U29: =S29-T29 -> 0.014181 | W29: 1.824 | Y29: =W29+X29+AA28 -> -0.084112 | AA29: =Y29-Z29 -> -0.084112 | AC29: 1.824 | AE29: =AC29+AD29+AG28 -> 0.020888 | AG29: =AE29-AF29 -> 0.020888 | AI29: 1.8259452 | AK29: =AI29+AJ29+AM28 -> 0.02082003 | AM29: =AK29-AL29 -> 0.02082003 | AO29: =E29+K29+Q29+W29+AC29+AI29 -> 7.7359452 | AP29: =F29+L29+R29+X29+AD29+AJ29 -> 0 | AQ29: =AO29+AP29+AS28 -> -0.01798947 | AR29: =H29+N29+T29+Z29+AF29+AL29 -> 0 | AS29: =AQ29-AR29 -> -0.01798947 | AT29: =AR29/AQ29 -> 0
B30: QUINTERO S.A. PESQ. | C30: 41640 | D30: 42216 | E30: =6.262+2.647 -> 8.909 | F30: =-0.561-0.2145+3.1134455+0.9636165+4.0280295-0.37125+1.7850635-0.01485 -> 8.728555 | G30: =E30+F30 -> 17.637555 | I30: =G30-H30 -> 17.637555 | J30: =E30+E31+F30+F31 -> 18.728555 | K30: =57.511+24.3 -> 81.811 | L30: =135-5.1-1.95+28.30405+8.76015+36.61845-3.375+16.22785-0.135 -> 214.3505 | M30: =K30+L30 -> 296.1615 | N30: 111.572 | O30: =M30-N30 -> 184.5895 | P30: =K30+K31+L30+L31 -> 305.2515 | Q30: =83.966+35.479 -> 119.445 | R30: =-7.446-2.487+41.323913+12.789819+53.462937-4.9275+23.692661-0.1971 -> 116.21173 | S30: =Q30+R30 -> 235.65673 | T30: 138.522 | U30: =S30-T30 -> 97.13473 | V30: =Q30+Q31+R30+R31 -> 248.92973 | W30: =119.622+50.544 -> 170.166 | X30: =-10.608-4.056+58.872424+18.221112+76.166376-7.02+33.753928-0.2808 -> 165.04904 | Y30: =W30+X30 -> 335.21504 | Z30: =229.932-0.105 -> 229.827 | AA30: =Y30-Z30 -> 105.38804 | AB30: =W30+W31+X30+X31 -> 354.12204 | AC30: =119.622+50.544 -> 170.166 | AD30: =-10.608-4.056+58.872424+18.221112+76.166376-7.02+33.753928-0.2808 -> 165.04904 | AE30: =AC30+AD30 -> 335.21504 | AF30: 259.579 | AG30: =AE30-AF30 -> 75.63604 | AH30: =AC30+AC31+AD30+AD31 -> 354.12204 | AI30: =119.737506+50.5926 -> 170.33011 | AJ30: =-10.6182-4.0599+58.9290321+18.2386323+76.2396129-7.02675+33.7863837-0.28107 -> 165.20774 | AK30: =AI30+AJ30 -> 335.53785 | AL30: 199.23 | AM30: =AK30-AL30 -> 136.30785 | AN30: =AI30+AI31+AJ30+AJ31 -> 354.46341 | AO30: =E30+K30+Q30+W30+AC30+AI30 -> 720.82711 | AP30: =F30+L30+R30+X30+AD30+AJ30 -> 834.59661 | AQ30: =AO30+AP30 -> 1555.4237 | AR30: =H30+N30+T30+Z30+AF30+AL30 -> 938.73 | AS30: =AQ30-AR30 -> 616.69371 | AT30: =AR30/AQ30 -> 0.60352044 | AU30: =AO30+AO31 -> 801.02067 | AV30: =AP30+AP31 -> 834.59661 | AW30: =AU30+AV30 -> 1635.6173 | AX30: =AR30+AR31 -> 1507.194 | AY30: =AW30-AX30 -> 128.42328 | AZ30: =AX30/AW30 -> 0.9214833
C31: 42278 | D31: 42369 | E31: =0.767+0.324 -> 1.091 | G31: =E31+F31+I30 -> 18.728555 | I31: =G31-H31 -> 18.728555 | K31: =6.39+2.7 -> 9.09 | M31: =K31+L31+O30 -> 193.6795 | N31: 97.801 | O31: =M31-N31 -> 95.8785 | Q31: =9.33+3.943 -> 13.273 | S31: =Q31+R31+U30 -> 110.40773 | T31: 106.892 | U31: =S31-T31 -> 3.51573 | W31: =13.291+5.616 -> 18.907 | Y31: =W31+X31+AA30 -> 124.29504 | Z31: 120.207 | AA31: =Y31-Z31 -> 4.08804 | AC31: =13.291+5.616 -> 18.907 | AE31: =AC31+AD31+AG30 -> 94.54304 | AF31: 91.685 | AG31: =AE31-AF31 -> 2.85804 | AI31: =13.3041674+5.6214 -> 18.925567 | AK31: =AI31+AJ31+AM30 -> 155.23341 | AL31: 151.879 | AM31: =AK31-AL31 -> 3.3544144 | AO31: =E31+K31+Q31+W31+AC31+AI31 -> 80.193567 | AP31: =F31+L31+R31+X31+AD31+AJ31 -> 0 | AQ31: =AO31+AP31+AS30 -> 696.88728 | AR31: =H31+N31+T31+Z31+AF31+AL31 -> 568.464 | AS31: =AQ31-AR31 -> 128.42328 | AT31: =AR31/AQ31 -> 0.81571872
B32: RUBIO Y MAUAD LTDA. | C32: 41640 | D32: 42216 | E32: =1.527+0.294 -> 1.821 | F32: =-0.14025-1.7136955 -> -1.8539455 | G32: =E32+L32 -> 175.49695 | I32: =G32-H32 -> 175.49695 | J32: =E32+E33+L32+F33 -> 175.71995 | K32: =14.021+2.7 -> 16.721 | L32: =190.53-1.275-15.57905 -> 173.67595 | M32: =K32+L32 -> 190.39695 | N32: 93.188 | O32: =M32-N32 -> 97.20895 | P32: =K32+K33+L32+L33 -> 192.25495 | Q32: =20.471+3.942 -> 24.413 | R32: =-1.8615-22.745413 -> -24.606913 | S32: =Q32+R32 -> -0.193913 | U32: =S32-T32 -> -0.193913 | V32: =Q32+Q33+R32+R33 -> 2.519087 | W32: =29.164+5.616 -> 34.78 | X32: =-2.652-32.404424 -> -35.056424 | Y32: =W32+X32 -> -0.276424 | AA32: =Y32-Z32 -> -0.276424 | AB32: =W32+W33+X32+X33 -> 3.587576 | AC32: =29.164+5.616 -> 34.78 | AD32: =-2.652-32.404424 -> -35.056424 | AE32: =AC32+AD32 -> -0.276424 | AG32: =AE32-AF32 -> -0.276424 | AH32: =AC32+AC33+AD32+AD33 -> 3.587576 | AI32: =29.1920239+5.6214 -> 34.813424 | AJ32: =-2.65455-32.4355821 -> -35.090132 | AK32: =AI32+AJ32 -> -0.2767082 | AM32: =AK32-AL32 -> -0.2767082 | AN32: =AI32+AI33+AJ32+AJ33 -> 3.59145 | AO32: =E32+K32+Q32+W32+AC32+AI32 -> 147.32842 | AP32: =F32+L32+R32+X32+AD32+AJ32 -> 42.012111 | AQ32: =AO32+AP32 -> 189.34054 | AR32: =H32+N32+T32+Z32+AF32+AL32 -> 93.188 | AS32: =AQ32-AR32 -> 96.152535 | AT32: =AR32/AQ32 -> 0.49217142 | AU32: =AO32+AO33 -> 163.71858 | AV32: =AP32+AP33 -> 42.012111 | AW32: =AU32+AV32 -> 205.73069 | AX32: =AR32+AR33 -> 186.931 | AY32: =AW32-AX32 -> 18.799694 | AZ32: =AX32/AW32 -> 0.90861989
C33: 42278 | D33: 42369 | E33: =0.187+0.036 -> 0.223 | G33: =E33+F33+I32 -> 175.71995 | I33: =G33-H33 -> 175.71995 | K33: =1.558+0.3 -> 1.858 | M33: =K33+L33+O32 -> 99.06695 | N33: 93.743 | O33: =M33-N33 -> 5.32395 | Q33: =2.275+0.438 -> 2.713 | S33: =Q33+R33+U32 -> 2.519087 | U33: =S33-T33 -> 2.519087 | W33: =3.24+0.624 -> 3.864 | Y33: =W33+X33+AA32 -> 3.587576 | AA33: =Y33-Z33 -> 3.587576 | AC33: =3.24+0.624 -> 3.864 | AE33: =AC33+AD33+AG32 -> 3.587576 | AG33: =AE33-AF33 -> 3.587576 | AI33: =3.24355821+0.6246 -> 3.8681582 | AK33: =AI33+AJ33+AM32 -> 3.59145 | AM33: =AK33-AL33 -> 3.59145 | AO33: =E33+K33+Q33+W33+AC33+AI33 -> 16.390158 | AP33: =F33+L33+R33+X33+AD33+AJ33 -> 0 | AQ33: =AO33+AP33+AS32 -> 112.54269 | AR33: =H33+N33+T33+Z33+AF33+AL33 -> 93.743 | AS33: =AQ33-AR33 -> 18.799694 | AT33: =AR33/AQ33 -> 0.83295501
B34: SUNRISE S.A. PESQ. | C34: 41640 | D34: 42216 | E34: 1.809 | F34: =-2.0301215 -> -2.0301215 | G34: =E34+F34 -> -0.2211215 | I34: =G34-H34 -> -0.2211215 | J34: =E34+E35+F34+F35 -> -0.0001215 | K34: 16.61 | L34: =-18.45565 -> -18.45565 | M34: =K34+L34 -> -1.84565 | O34: =M34-N34 -> -1.84565 | P34: =K34+K35+L34+L35 -> 0.00035 | Q34: 24.25 | R34: =-26.945249 -> -26.945249 | S34: =Q34+R34 -> -2.695249 | U34: =S34-T34 -> -2.695249 | V34: =Q34+Q35+R34+R35 -> -0.000249 | W34: 34.549 | X34: =-38.387752 -> -38.387752 | Y34: =W34+X34 -> -3.838752 | AA34: =Y34-Z34 -> -3.838752 | AB34: =W34+W35+X34+X35 -> 0.000248 | AC34: 34.549 | AD34: =-38.387752 -> -38.387752 | AE34: =AC34+AD34 -> -3.838752 | AG34: =AE34-AF34 -> -3.838752 | AH34: =AC34+AC35+AD34+AD35 -> 0.000248 | AI34: 34.582197 | AJ34: =-38.4246633 -> -38.424663 | AK34: =AI34+AJ34 -> -3.8424663 | AM34: =AK34-AL34 -> -3.8424663 | AN34: =AI34+AI35+AJ34+AJ35 -> 3.0000002e-08 | AO34: =E34+K34+Q34+W34+AC34+AI34 -> 146.3492 | AP34: =F34+L34+R34+X34+AD34+AJ34 -> -162.63119 | AQ34: =AO34+AP34 -> -16.281991 | AR34: =H34+N34+T34+Z34+AF34+AL34 -> 0 | AS34: =AQ34-AR34 -> -16.281991 | AT34: =AR34/AQ34 -> 0 | AU34: =AO34+AO35 -> 162.63166 | AV34: =AP34+AP35 -> -162.63119 | AW34: =AU34+AV34 -> 0.00047553 | AX34: =AR34+AR35 -> 0 | AY34: =AW34-AX34 -> 0.00047553 | AZ34: =AX34/AW34 -> 0
C35: 42278 | D35: 42369 | E35: 0.221 | G35: =E35+F35+I34 -> -0.0001215 | I35: =G35-H35 -> -0.0001215 | K35: 1.846 | M35: =K35+L35+O34 -> 0.00035 | O35: =M35-N35 -> 0.00035 | Q35: 2.695 | S35: =Q35+R35+U34 -> -0.000249 | U35: =S35-T35 -> -0.000249 | W35: 3.839 | Y35: =W35+X35+AA34 -> 0.000248 | AA35: =Y35-Z35 -> 0.000248 | AC35: 3.839 | AE35: =AC35+AD35+AG34 -> 0.000248 | AG35: =AE35-AF35 -> 0.000248 | AI35: 3.8424663 | AK35: =AI35+AJ35+AM34 -> 3.0000002e-08 | AM35: =AK35-AL35 -> 3.0000002e-08 | AO35: =E35+K35+Q35+W35+AC35+AI35 -> 16.282466 | AP35: =F35+L35+R35+X35+AD35+AJ35 -> 0 | AQ35: =AO35+AP35+AS34 -> 0.00047553 | AR35: =H35+N35+T35+Z35+AF35+AL35 -> 0 | AS35: =AQ35-AR35 -> 0.00047553 | AT35: =AR35/AQ35 -> 0
B36: ANTONIO CRUZ CORDOVA NAKOUZI E.I.R.L | C36: 41640 | D36: 42216 | E36: 0.23 | F36: =-0.0998855 -> -0.0998855 | G36: =E36+F36 -> 0.1301145 | I36: =G36-H36 -> 0.1301145 | J36: =E36+E37+F36+F37 -> 0.1581145 | K36: 2.112 | L36: =-0.90805 -> -0.90805 | M36: =K36+L36 -> 1.20395 | O36: =M36-N36 -> 1.20395 | P36: =K36+K37+L36+L37 -> 1.43895 | Q36: 3.083 | R36: =-1.325753 -> -1.325753 | S36: =Q36+R36 -> 1.757247 | U36: =S36-T36 -> 1.757247 | V36: =Q36+Q37+R36+R37 -> 2.100247 | W36: 4.393 | X36: =-1.888744 -> -1.888744 | Y36: =W36+X36 -> 2.504256 | AA36: =Y36-Z36 -> 2.504256 | AB36: =W36+W37+X36+X37 -> 2.992256 | AC36: 4.393 | AD36: =-1.888744 -> -1.888744 | AE36: =AC36+AD36 -> 2.504256 | AG36: =AE36-AF36 -> 2.504256 | AH36: =AC36+AC37+AD36+AD37 -> 2.992256 | AI36: 4.3968717 | AJ36: =-1.8905601 -> -1.8905601 | AK36: =AI36+AJ36 -> 2.5063116 | AM36: =AK36-AL36 -> 2.5063116 | AN36: =AI36+AI37+AJ36+AJ37 -> 2.9948529 | AO36: =E36+K36+Q36+W36+AC36+AI36 -> 18.607872 | AP36: =F36+L36+R36+X36+AD36+AJ36 -> -8.0017366 | AQ36: =AO36+AP36 -> 10.606135 | AR36: =H36+N36+T36+Z36+AF36+AL36 -> 0 | AS36: =AQ36-AR36 -> 10.606135 | AT36: =AR36/AQ36 -> 0 | AU36: =AO36+AO37 -> 20.678413 | AV36: =AP36+AP37 -> -8.0017366 | AW36: =AU36+AV36 -> 12.676676 | AX36: =AR36+AR37 -> 10.755 | AY36: =AW36-AX36 -> 1.9216764 | AZ36: =AX36/AW36 -> 0.8484085
C37: 42278 | D37: 42369 | E37: 0.028 | G37: =E37+F37+I36 -> 0.1581145 | I37: =G37-H37 -> 0.1581145 | K37: 0.235 | M37: =K37+L37+O36 -> 1.43895 | O37: =M37-N37 -> 1.43895 | Q37: 0.343 | S37: =Q37+R37+U36 -> 2.100247 | T37: 1.348 | U37: =S37-T37 -> 0.752247 | W37: 0.488 | Y37: =W37+X37+AA36 -> 2.992256 | Z37: 2.064 | AA37: =Y37-Z37 -> 0.928256 | AC37: 0.488 | AE37: =AC37+AD37+AG36 -> 2.992256 | AF37: 3.227 | AG37: =AE37-AF37 -> -0.234744 | AI37: 0.4885413 | AK37: =AI37+AJ37+AM36 -> 2.9948529 | AL37: 4.116 | AM37: =AK37-AL37 -> -1.1211471 | AO37: =E37+K37+Q37+W37+AC37+AI37 -> 2.0705413 | AP37: =F37+L37+R37+X37+AD37+AJ37 -> 0 | AQ37: =AO37+AP37+AS36 -> 12.676676 | AR37: =H37+N37+T37+Z37+AF37+AL37 -> 10.755 | AS37: =AQ37-AR37 -> 1.9216764 | AT37: =AR37/AQ37 -> 0.8484085
B38: BIO BIO S.A. PESQ. | C38: 41640 | D38: 42216 | E38: 0.002 | F38: =0.0044 -> 0.0044 | G38: =E38+F38 -> 0.0064 | I38: =G38-H38 -> 0.0064 | J38: =E38+E39+F38+F39 -> 0.0064 | K38: 0.015 | L38: =0.04 -> 0.04 | M38: =K38+L38 -> 0.055 | O38: =M38-N38 -> 0.055 | P38: =K38+K39+L38+L39 -> 0.057 | Q38: 0.022 | R38: =0.0584 -> 0.0584 | S38: =Q38+R38 -> 0.0804 | U38: =S38-T38 -> 0.0804 | V38: =Q38+Q39+R38+R39 -> 0.0824 | W38: 0.032 | X38: =0.0832 -> 0.0832 | Y38: =W38+X38 -> 0.1152 | AA38: =Y38-Z38 -> 0.1152 | AB38: =W38+W39+X38+X39 -> 0.1192 | AC38: 0.032 | AD38: =0.0832 -> 0.0832 | AE38: =AC38+AD38 -> 0.1152 | AG38: =AE38-AF38 -> 0.1152 | AH38: =AC38+AC39+AD38+AD39 -> 0.1192 | AI38: 0.0318546 | AJ38: =0.08328 -> 0.08328 | AK38: =AI38+AJ38 -> 0.1151346 | AM38: =AK38-AL38 -> 0.1151346 | AN38: =AI38+AI39+AJ38+AJ39 -> 0.118674 | AO38: =E38+K38+Q38+W38+AC38+AI38 -> 0.1348546 | AP38: =F38+L38+R38+X38+AD38+AJ38-0.503 -> -0.15052 | AQ38: =AO38+AP38 -> -0.0156654 | AR38: =H38+N38+T38+Z38+AF38+AL38 -> 0 | AS38: =AQ38-AR38 -> -0.0156654 | AT38: =AR38/AQ38 -> 0 | AU38: =AO38+AO39 -> 0.150394 | AV38: =AP38+AP39 -> -0.15052 | AW38: =AU38+AV38 -> -0.000126 | AX38: =AR38+AR39 -> 0 | AY38: =AW38-AX38 -> -0.000126 | AZ38: =AX38/AW38 -> 0
C39: 42278 | D39: 42369 | E39: 0 | G39: =E39+F39+I38 -> 0.0064 | I39: =G39-H39 -> 0.0064 | K39: 0.002 | M39: =K39+L39+O38 -> 0.057 | O39: =M39-N39 -> 0.057 | Q39: 0.002 | S39: =Q39+R39+U38 -> 0.0824 | U39: =S39-T39 -> 0.0824 | W39: 0.004 | Y39: =W39+X39+AA38 -> 0.1192 | AA39: =Y39-Z39 -> 0.1192 | AC39: 0.004 | AE39: =AC39+AD39+AG38 -> 0.1192 | AG39: =AE39-AF39 -> 0.1192 | AI39: 0.0035394 | AK39: =AI39+AJ39+AM38 -> 0.118674 | AM39: =AK39-AL39 -> 0.118674 | AO39: =E39+K39+Q39+W39+AC39+AI39 -> 0.0155394 | AP39: =F39+L39+R39+X39+AD39+AJ39 -> 0 | AQ39: =AO39+AP39+AS38 -> -0.000126 | AR39: =H39+N39+T39+Z39+AF39+AL39 -> 0 | AS39: =AQ39-AR39 -> -0.000126 | AT39: =AR39/AQ39 -> 0
B40: ENFEMAR LTDA. SOC. PESQ | C40: 41640 | D40: 42216 | E40: 0 | F40: =0.01485 -> 0.01485 | G40: =E40+F40 -> 0.01485 | I40: =G40-H40 -> 0.01485 | J40: =E40+E41+F40+F41 -> 0.01485 | K40: 0 | L40: =0.135 -> 0.135 | M40: =K40+L40 -> 0.135 | O40: =M40-N40 -> 0.135 | P40: =K40+K41+L40+L41 -> 0.135 | Q40: 0 | R40: =0.1971 -> 0.1971 | S40: =Q40+R40 -> 0.1971 | U40: =S40-T40 -> 0.1971 | V40: =Q40+Q41+R40+R41 -> 0.1971 | W40: 0 | X40: =0.2808 -> 0.2808 | Y40: =W40+X40 -> 0.2808 | AA40: =Y40-Z40 -> 0.2808 | AB40: =W40+W41+X40+X41 -> 0.2808 | AC40: 0 | AD40: =0.2808 -> 0.2808 | AE40: =AC40+AD40 -> 0.2808 | AG40: =AE40-AF40 -> 0.2808 | AH40: =AC40+AC41+AD40+AD41 -> 0.2808 | AI40: 0 | AJ40: =0.28107 -> 0.28107 | AK40: =AI40+AJ40 -> 0.28107 | AM40: =AK40-AL40 -> 0.28107 | AN40: =AI40+AI41+AJ40+AJ41 -> 0.28107 | AO40: =E40+K40+Q40+W40+AC40+AI40 -> 0 | AP40: =F40+L40+R40+X40+AD40+AJ40 -> 1.18962 | AQ40: =AO40+AP40 -> 1.18962 | AR40: =H40+N40+T40+Z40+AF40+AL40 -> 0 | AS40: =AQ40-AR40 -> 1.18962 | AT40: =AR40/AQ40 -> 0 | AU40: =AO40+AO41 -> 0 | AV40: =AP40+AP41 -> 1.18962 | AW40: =AU40+AV40 -> 1.18962 | AX40: =AR40+AR41 -> 0 | AY40: =AW40-AX40 -> 1.18962 | AZ40: =AX40/AW40 -> 0
C41: 42278 | D41: 42369 | E41: 0 | G41: =E41+F41+I40 -> 0.01485 | I41: =G41-H41 -> 0.01485 | K41: 0 | M41: =K41+L41+O40 -> 0.135 | O41: =M41-N41 -> 0.135 | Q41: 0 | S41: =Q41+R41+U40 -> 0.1971 | U41: =S41-T41 -> 0.1971 | W41: 0 | Y41: =W41+X41+AA40 -> 0.2808 | AA41: =Y41-Z41 -> 0.2808 | AC41: 0 | AE41: =AC41+AD41+AG40 -> 0.2808 | AG41: =AE41-AF41 -> 0.2808 | AI41: 0 | AK41: =AI41+AJ41+AM40 -> 0.28107 | AM41: =AK41-AL41 -> 0.28107 | AO41: =E41+K41+Q41+W41+AC41+AI41 -> 0 | AP41: =F41+L41+R41+X41+AD41+AJ41 -> 0 | AQ41: =AO41+AP41+AS40 -> 1.18962 | AR41: =H41+N41+T41+Z41+AF41+AL41 -> 0 | AS41: =AQ41-AR41 -> 1.18962 | AT41: =AR41/AQ41 -> 0
B42: ALIMENTOS ALSAN LTDA | C42: 41640 | D42: 42216 | E42: 2.797 | F42: =-2.5047-0.2475-0.2475-0.12925 -> -3.12895 | G42: =E42+F42 -> -0.33195 | I42: =G42-H42 -> -0.33195 | J42: =E42+E43+F42+F43 -> 0.01005 | K42: =25.65 -> 25.65 | L42: =-22.77-2.25-2.25-1.175 -> -28.445 | M42: =K42+L42 -> -2.795 | O42: =M42-N42 -> -2.795 | P42: =K42+K43+L42+L43 -> 0.055 | Q42: 37.453 | R42: =-33.2442-3.285-3.285-1.7155 -> -41.5297 | S42: =Q42+R42 -> -4.0767 | U42: =S42-T42 -> -4.0767 | V42: =Q42+Q43+R42+R43 -> 0.0883 | W42: =53.352 -> 53.352 | X42: =-47.3616-4.68-4.68-2.444 -> -59.1656 | Y42: =W42+X42 -> -5.8136 | AA42: =Y42-Z42 -> -5.8136 | AB42: =W42+W43+X42+X43 -> 0.1144 | AC42: =53.352 -> 53.352 | AD42: =-47.3616-4.68-4.68-2.444 -> -59.1656 | AE42: =AC42+AD42 -> -5.8136 | AG42: =AE42-AF42 -> -5.8136 | AH42: =AC42+AC43+AD42+AD43 -> 0.1144 | AI42: =53.4033 -> 53.4033 | AJ42: =-47.40714-4.6845-4.6845-2.44635 -> -59.22249 | AK42: =AI42+AJ42 -> -5.81919 | AM42: =AK42-AL42 -> -5.81919 | AN42: =AI42+AI43+AJ42+AJ43 -> 0.11451 | AO42: =E42+K42+Q42+W42+AC42+AI42 -> 226.0073 | AP42: =F42+L42+R42+X42+AD42+AJ42 -> -250.65734 | AQ42: =AO42+AP42 -> -24.65004 | AR42: =H42+N42+T42+Z42+AF42+AL42 -> 0 | AS42: =AQ42-AR42 -> -24.65004 | AT42: =AR42/AQ42 -> 0 | AU42: =AO42+AO43 -> 251.154 | AV42: =AP42+AP43 -> -250.65734 | AW42: =AU42+AV42 -> 0.49666 | AX42: =AR42+AR43 -> 0 | AY42: =AW42-AX42 -> 0.49666 | AZ42: =AX42/AW42 -> 0
C43: 42278 | D43: 42369 | E43: 0.342 | G43: =E43+F43+I42 -> 0.01005 | I43: =G43-H43 -> 0.01005 | K43: =2.85 -> 2.85 | M43: =K43+L43+O42 -> 0.055 | O43: =M43-N43 -> 0.055 | Q43: =4.165 -> 4.165 | S43: =Q43+R43+U42 -> 0.0883 | U43: =S43-T43 -> 0.0883 | W43: =5.928 -> 5.928 | Y43: =W43+X43+AA42 -> 0.1144 | AA43: =Y43-Z43 -> 0.1144 | AC43: =5.928 -> 5.928 | AE43: =AC43+AD43+AG42 -> 0.1144 | AG43: =AE43-AF43 -> 0.1144 | AI43: =5.9337 -> 5.9337 | AK43: =AI43+AJ43+AM42 -> 0.11451 | AM43: =AK43-AL43 -> 0.11451 | AO43: =E43+K43+Q43+W43+AC43+AI43 -> 25.1467 | AP43: =F43+L43+R43+X43+AD43+AJ43 -> 0 | AQ43: =AO43+AP43+AS42 -> 0.49666 | AR43: =H43+N43+T43+Z43+AF43+AL43 -> 0 | AS43: =AQ43-AR43 -> 0.49666 | AT43: =AR43/AQ43 -> 0
B44: SOC. DISTRIB. PRODUCTOS DEL MAR LTDA. (DISTRIMAR) | C44: 41640 | D44: 42216 | E44: 0 | F44: =0.2475+0.2475+0.12925-0.2475-0.2475-0.12925 -> 0 | G44: =E44+F44 -> 0 | I44: =G44-H44 -> 0 | J44: =E44+E45+F44+F45 -> 0 | K44: 0 | L44: =2.25+2.25+1.175-2.25-2.25-1.175 -> 0 | M44: =K44+L44 -> 0 | O44: =M44-N44 -> 0 | P44: =K44+K45+L44+L45 -> 0 | Q44: 0 | R44: =3.285+3.285+1.7155-3.285-3.285-1.7155 -> 0 | S44: =Q44+R44 -> 0 | U44: =S44-T44 -> 0 | V44: =Q44+Q45+R44+R45 -> 0 | W44: 0 | X44: =4.68+4.68+2.444-4.68-4.68-2.444 -> 0 | Y44: =W44+X44 -> 0 | AA44: =Y44-Z44 -> 0 | AB44: =W44+W45+X44+X45 -> 0 | AC44: 0 | AD44: =4.68+4.68+2.444-4.68-4.68-2.444 -> 0 | AE44: =AC44+AD44 -> 0 | AG44: =AE44-AF44 -> 0 | AH44: =AC44+AC45+AD44+AD45 -> 0 | AI44: 0 | AJ44: =4.6845+4.6845+2.44635-4.6845-4.6845-2.44635 -> 0 | AK44: =AI44+AJ44 -> 0 | AM44: =AK44-AL44 -> 0 | AN44: =AI44+AI45+AJ44+AJ45 -> 0 | AO44: =E44+K44+Q44+W44+AC44+AI44 -> 0 | AP44: =F44+L44+R44+X44+AD44+AJ44 -> 0 | AQ44: =AO44+AP44 -> 0 | AR44: =H44+N44+T44+Z44+AF44+AL44 -> 0 | AS44: =AQ44-AR44 -> 0 | AT44: =AR44/AQ44 -> #DIV/0! | AU44: =AO44+AO45 -> 0 | AV44: =AP44+AP45 -> 0 | AW44: =AU44+AV44 -> 0 | AX44: =AR44+AR45 -> 0 | AY44: =AW44-AX44 -> 0 | AZ44: 0
C45: 42278 | D45: 42369 | E45: 0 | G45: =E45+F45+I44 -> 0 | I45: =G45-H45 -> 0 | K45: 0 | M45: =K45+L45+O44 -> 0 | O45: =M45-N45 -> 0 | Q45: 0 | S45: =Q45+R45+U44 -> 0 | U45: =S45-T45 -> 0 | W45: 0 | Y45: =W45+X45+AA44 -> 0 | AA45: =Y45-Z45 -> 0 | AC45: 0 | AE45: =AC45+AD45+AG44 -> 0 | AG45: =AE45-AF45 -> 0 | AI45: 0 | AK45: =AI45+AJ45+AM44 -> 0 | AM45: =AK45-AL45 -> 0 | AO45: =E45+K45+Q45+W45+AC45+AI45 -> 0 | AP45: =F45+L45+R45+X45+AD45+AJ45 -> 0 | AQ45: =AO45+AP45+AS44 -> 0 | AR45: =H45+N45+T45+Z45+AF45+AL45 -> 0 | AS45: =AQ45-AR45 -> 0 | AT45: =AR45/AQ45 -> #DIV/0!
B46: CONGELADOS PACIFICO S.A. | C46: 41640 | D46: 42216 | E46: 0 | G46: =E46+F46 -> 0 | I46: =G46+H46 -> 0 | J46: =E46+E47+F46+F47 -> 0 | K46: 0 | L46: 0.0441 | M46: =K46+L46 -> 0.0441 | O46: =M46-N46 -> 0.0441 | P46: =K46+K47+L46+L47 -> 0.0441 | Q46: 0 | R46: 0.0441 | S46: =Q46+R46 -> 0.0441 | U46: =S46-T46 -> 0.0441 | V46: =Q46+Q47+R46+R47 -> 0.0441 | W46: 0 | X46: 0.0441 | Y46: =W46+X46 -> 0.0441 | AA46: =Y46-Z46 -> 0.0441 | AB46: =W46+W47+X46+X47 -> 0.0441 | AC46: 0 | AD46: 0.0441 | AE46: =AC46+AD46 -> 0.0441 | AG46: 0.032 | AH46: =AC46+AC47+AD46+AD47 -> 0.0441 | AI46: 0 | AJ46: 0.0441 | AK46: =AI46+AJ46 -> 0.0441 | AM46: =AK46-AL46 -> 0.0441 | AN46: =AI46+AI47+AJ46+AJ47 -> 0.0441 | AO46: =E46+K46+Q46+W46+AC46+AI46 -> 0 | AP46: =F46+L46+R46+X46+AD46+AJ46+0.66106+2.20353+0.5023 -> 3.58739 | AQ46: =AO46+AP46 -> 3.58739 | AR46: =H46+N46+T46+Z46+AF46+AL46 -> 0 | AS46: =AQ46-AR46 -> 3.58739 | AT46: =AR46/AQ46 -> 0 | AU46: =AO46+AO47 -> 0 | AV46: =AP46+AP47 -> 3.58739 | AW46: =AU46+AV46 -> 3.58739 | AX46: =AR46+AR47 -> 0 | AY46: =AW46-AX46 -> 3.58739 | AZ46: =AX46/AW46 -> 0
C47: 42278 | D47: 42369 | E47: 0 | G47: =E47+F47+I46 -> 0 | I47: =G47+H47+K46 -> 0 | K47: 0 | M47: =K47+L47+O46 -> 0.0441 | O47: =M47-N47 -> 0.0441 | Q47: 0 | S47: =Q47+R47+U46 -> 0.0441 | U47: =S47-T47 -> 0.0441 | W47: 0 | Y47: =W47+X47+AA46 -> 0.0441 | AA47: =Y47-Z47 -> 0.0441 | AC47: 0 | AE47: =AC47+AD47+AG46 -> 0.032 | AG47: 0.004 | AI47: 0 | AK47: =AI47+AJ47+AM46 -> 0.0441 | AM47: =AK47-AL47 -> 0.0441 | AO47: =E47+K47+Q47+W47+AC47+AI47 -> 0 | AP47: =F47+L47+R47+X47+AD47+AJ47 -> 0 | AQ47: =AO47+AP47+AS46 -> 3.58739 | AR47: =H47+N47+T47+Z47+AF47+AL47 -> 0 | AS47: =AQ47-AR47 -> 3.58739 | AT47: =AR47/AQ47 -> 0
B48: JORGE ENRIQUE COFRE REYES | C48: 41640 | D48: 42216 | E48: 0 | G48: =E48+F48 -> 0 | I48: =G48-H48 -> 0 | J48: =E48+E49+F48+F49 -> 0 | K48: 0 | M48: =K48+L48 -> 0 | O48: =M48-N48 -> 0 | P48: =K48+K49+L48+L49 -> 0 | Q48: 0 | R48: 0.04445 | S48: =Q48+R48 -> 0.04445 | U48: =S48-T48 -> 0.04445 | V48: =Q48+Q49+R48+R49 -> 0.04445 | W48: 0 | X48: 0.04445 | Y48: =W48+X48 -> 0.04445 | AA48: =Y48-Z48 -> 0.04445 | AB48: =W48+W49+X48+X49 -> 0.04445 | AC48: 0 | AD48: 0.04445 | AE48: =AC48+AD48 -> 0.04445 | AG48: =AE48-AF48 -> 0.04445 | AH48: =AC48+AC49+AD48+AD49 -> 0.04445 | AI48: 0 | AJ48: 0.04445 | AK48: =AI48+AJ48 -> 0.04445 | AM48: =AK48-AL48 -> 0.04445 | AN48: =AI48+AI49+AJ48+AJ49 -> 0.04445 | AO48: =E48+K48+Q48+W48+AC48+AI48 -> 0 | AP48: =F48+L48+R48+X48+AD48+AJ48 -> 0.1778 | AQ48: =AO48+AP48 -> 0.1778 | AR48: =H48+N48+T48+Z48+AF48+AL48 -> 0 | AS48: =AQ48-AR48 -> 0.1778 | AT48: =AR48/AQ48 -> 0 | AU48: =AO48+AO49 -> 0 | AV48: =AP48+AP49 -> 0.1778 | AW48: =AU48+AV48 -> 0.1778 | AX48: =AR48+AR49 -> 0 | AY48: =AW48-AX48 -> 0.1778 | AZ48: =AX48/AW48 -> 0
C49: 42278 | D49: 42369 | E49: 0 | G49: =E49+F49+I48 -> 0 | I49: =G49-H49 -> 0 | K49: 0 | M49: =K49+L49+O48 -> 0 | O49: =M49-N49 -> 0 | Q49: 0 | S49: =Q49+R49+U48 -> 0.04445 | U49: =S49-T49 -> 0.04445 | W49: 0 | Y49: =W49+X49+AA48 -> 0.04445 | AA49: =Y49-Z49 -> 0.04445 | AC49: 0 | AE49: =AC49+AD49+AG48 -> 0.04445 | AG49: =AE49-AF49 -> 0.04445 | AI49: 0 | AK49: =AI49+AJ49+AM48 -> 0.04445 | AM49: =AK49-AL49 -> 0.04445 | AO49: =E49+K49+Q49+W49+AC49+AI49 -> 0 | AP49: =F49+L49+R49+X49+AD49+AJ49 -> 0 | AQ49: =AO49+AP49+AS48 -> 0.1778 | AR49: =H49+N49+T49+Z49+AF49+AL49 -> 0 | AS49: =AQ49-AR49 -> 0.1778 | AT49: =AR49/AQ49 -> 0
B50: PESQUERA CMK LTDA | C50: 41640 | D50: 42216 | E50: 0 | F50: =0.0000404*55 -> 0.002222 | G50: =E50+F50 -> 0.002222 | I50: =G50-H50 -> 0.002222 | J50: =E50+E51+F50+F51 -> 0.002222 | K50: 0 | L50: =0.0000404*500 -> 0.0202 | M50: =K50+L50 -> 0.0202 | O50: =M50-N50 -> 0.0202 | P50: =K50+K51+L50+L51 -> 0.0202 | Q50: 0 | R50: =0.0000404*730 -> 0.029492 | S50: =Q50+R50 -> 0.029492 | U50: =S50-T50 -> 0.029492 | V50: =Q50+Q51+R50+R51 -> 0.029492 | W50: 0 | X50: =0.0000404*1040 -> 0.042016 | Y50: =W50+X50 -> 0.042016 | AA50: =Y50-Z50 -> 0.042016 | AB50: =W50+W51+X50+X51 -> 0.042016 | AC50: 0 | AD50: =0.0000404*1040 -> 0.042016 | AE50: =AC50+AD50 -> 0.042016 | AG50: =AE50-AF50 -> 0.042016 | AH50: =AC50+AC51+AD50+AD51 -> 0.042016 | AI50: 0 | AJ50: =0.0000404*1041 -> 0.0420564 | AK50: =AI48+AJ48 -> 0.04445 | AM50: =AK50-AL50 -> 0.04445 | AN50: =AI50+AI51+AJ50+AJ51 -> 0.0420564 | AO50: =E50+K50+Q50+W50+AC50+AI50 -> 0 | AP50: =F50+L50+R50+X50+AD50+AJ50 -> 0.1780024 | AQ50: =AO50+AP50 -> 0.1780024 | AR50: =H50+N50+T50+Z50+AF50+AJ50 -> 0.0420564 | AS50: =AQ50-AR50 -> 0.135946 | AT50: =AR50/AQ50 -> 0.23626872 | AU50: =AO50+AO51 -> 0 | AV50: =AP50+AP51 -> 0.1780024 | AW50: =AU50+AV50 -> 0.1780024 | AX50: =AR50+AR51 -> 0.0420564 | AY50: =AW50-AX50 -> 0.135946 | AZ50: =AX50/AW50 -> 0.23626872
C51: 42278 | D51: 42369 | E51: 0 | G51: =E51+F51+I50 -> 0.002222 | I51: =G51-H51 -> 0.002222 | K51: 0 | M51: =K51+L51+O50 -> 0.0202 | O51: =M51-N51 -> 0.0202 | Q51: 0 | S51: =Q51+R51+U50 -> 0.029492 | U51: =S51-T51 -> 0.029492 | W51: 0 | Y51: =W51+X51+AA50 -> 0.042016 | AA51: =Y51-Z51 -> 0.042016 | AC51: 0 | AE51: =AC51+AD51+AG50 -> 0.042016 | AG51: =AE51-AF51 -> 0.042016 | AI51: 0 | AK51: =AI51+AJ51+AM50 -> 0.04445 | AM51: =AK51-AL51 -> 0.04445 | AO51: =E51+K51+Q51+W51+AC51+AI51 -> 0 | AP51: =F51+L51+R51+X51+AD51+AJ51 -> 0 | AQ51: =AO51+AP51+AS50 -> 0.135946 | AR51: =H51+N51+T51+Z51+AF51+AL51 -> 0 | AS51: =AQ51-AR51 -> 0.135946 | AT51: =AR51/AQ51 -> 0
F52: =SUM(F6:F51) -> -6.1235739e-16 | H52: =+H6+H8+H10+H12+H14+H16+H18+H20+H22+H24+H26+H28+H30+H32+H34+H36+H38+H40+H42+H44+H46+H48+H50 -> 0 | L52: =SUM(L6:L51) -> 286.876 | N52: =+N6+N8+N10+N12+N14+N16+N18+N20+N22+N24+N26+N28+N30+N32+N34+N36+N38+N40+N42+N44+N46+N48+N50 -> 246.99 | R52: =SUM(R6:R51) -> 0.359992 | T52: =+T6+T8+T10+T12+T14+T16+T18+T20+T22+T24+T26+T28+T30+T32+T34+T36+T38+T40+T42+T44+T46+T48+T50 -> 388.778 | X52: =SUM(X6:X51) -> 1.6e-05 | Z52: =+Z6+Z8+Z10+Z12+Z14+Z16+Z18+Z20+Z22+Z24+Z26+Z28+Z30+Z32+Z34+Z36+Z38+Z40+Z42+Z44+Z46+Z48+Z50 -> 473.386 | AD52: =SUM(AD6:AD51) -> 1.6e-05 | AF52: =+AF6+AF8+AF10+AF12+AF14+AF16+AF18+AF20+AF22+AF24+AF26+AF28+AF30+AF32+AF34+AF36+AF38+AF40+AF42+AF44+AF46+AF48+AF50 -> 796.326 | AJ52: =SUM(AJ6:AJ51) -> -4.36e-05 | AL52: =+AL6+AL8+AL10+AL12+AL14+AL16+AL18+AL20+AL22+AL24+AL26+AL28+AL30+AL32+AL34+AL36+AL38+AL40+AL42+AL44+AL46+AL48+AL50 -> 617.679 | AU52: =SUM(AU6:AU51) -> 4406.0185 | AV52: =SUM(AV6:AV51) -> 287.23528 | AW52: =SUM(AW6:AW51) -> 4693.2538 | AX52: =SUM(AX6:AX51) -> 3855.7171 | AY52: =SUM(AY6:AY51) -> 837.53671 | AZ52: =+AX52/AW52 -> 0.82154455
H53: =+H7+H9+H11+H13+H15+H17+H19+H21+H23+H25+H27+H29+H31+H33+H35+H37+H39+H41+H43+H45+H47+H49+H51 -> 0.208 | N53: =+N7+N9+N11+N13+N15+N17+N19+N21+N23+N25+N27+N29+N31+N33+N35+N37+N39+N41+N43+N45+N47+N49+N51 -> 278.794 | T53: =+T7+T9+T11+T13+T15+T17+T19+T21+T23+T25+T27+T29+T31+T33+T35+T37+T39+T41+T43+T45+T47+T49+T51 -> 231.861 | Z53: =+Z7+Z9+Z11+Z13+Z15+Z17+Z19+Z21+Z23+Z25+Z27+Z29+Z31+Z33+Z35+Z37+Z39+Z41+Z43+Z45+Z47+Z49+Z51 -> 262.093 | AF53: =+AF7+AF9+AF11+AF13+AF15+AF17+AF19+AF21+AF23+AF25+AF27+AF29+AF31+AF33+AF35+AF37+AF39+AF41+AF43+AF45+AF47+AF49+AF51 -> 210.232 | AL53: =+AL7+AL9+AL11+AL13+AL15+AL17+AL19+AL21+AL23+AL25+AL27+AL29+AL31+AL33+AL35+AL37+AL39+AL41+AL43+AL45+AL47+AL49+AL51 -> 349.328
C54: Periodo | E54: Cuota III Región (t) | H54: Operación III región | K54: Cuota IV Región (t) | N54: Operación IV Región | Q54: Cuota y Operación Langostino amarillo III-IV | W54: Resumen Global Anual Langostino amarillo III-IV
A55: Unidad de pesquería | B55: Armador | C55: Inicial | D55: Final | E55: Cuota Asignada | F55: Traspaso, Cesion, Arriendo, etc) | G55: Cuota Efectiva | H55: Desembarque (t) | I55: Saldo (t) | J55: Cuota Total | K55: Cuota Asignada | L55: Traspaso, Cesion, Arriendo, etc) | M55: Cuota Efectiva | N55: Desembarque (t) | O55: Saldo (t) | P55: Cuota Total | Q55: Cuota Asignada III-IV | R55: * Traspaso, Cesion, Arriendo, etc) | S55: Cuota Efectiva | T55: Desembarque (t) III-IV | U55: Saldo (t) | V55: % consumido | W55: Cuota Total | X55: * Traspaso, Cesion, Arriendo, etc) | Y55: Cuota Efectiva | Z55: Desembarque (t) | AA55: Saldo (t) | AB55: % consumido | AG55: =0.021-0.105 -> -0.084
A56: Langostino amarillo III-IV (clase A y B) | B56: ANTARTIC SEAFOOD S.A. | C56: 42064 | D56: 42246 | E56: =49.207+8.547 -> 57.754 | F56: =-2.337-1.271 -> -3.608 | G56: =E56+F56 -> 54.146 | H56: 23.91 | I56: =G56-H56 -> 30.236 | J56: =E56+E57+F56+F57 -> 60.39 | K56: =394.654+68.549 -> 463.203 | L56: =-18.7815-10.2145+10 -> -18.996 | M56: =K56+L56 -> 444.207 | N56: 492.185 | O56: =M56-N56 -> -47.978 | P56: =K56+K57+L56+L57 -> 495.327 | Q56: =E56+K56 -> 520.957 | R56: =F56+L56 -> -22.604 | S56: =Q56+R56 -> 498.353 | T56: =H56+N56 -> 516.095 | U56: =S56-T56 -> -17.742 | V56: =T56/S56 -> 1.0356013 | W56: =Q56+Q57 -> 578.321 | X56: =R56+R57 -> -22.604 | Y56: =W56+X56 -> 555.717 | Z56: =T56+T57 -> 544.573 | AA56: =Y56-Z56 -> 11.144 | AB56: =Z56/Y56 -> 0.97994663 | AG56: =+Z28 -> 0.105
C57: 42278 | D57: 42368 | E57: =5.32+0.924 -> 6.244 | G57: =E57+F57+I56 -> 36.48 | H57: 21.971 | I57: =G57-H57 -> 14.509 | K57: =43.555+7.565 -> 51.12 | M57: =K57+L57+O56 -> 3.142 | N57: 6.507 | O57: =M57-N57 -> -3.365 | Q57: =E57+K57 -> 57.364 | R57: =F57+L57 -> 0 | S57: =Q57+R57+U56 -> 39.622 | T57: =H57+N57 -> 28.478 | U57: =S57-T57 -> 11.144 | V57: =T57/S57 -> 0.71874211
B58: BAYCIC BAYCIC MARIA | C58: 42064 | D58: 42246 | E58: 3.55 | F58: =-3.9286692 -> -3.9286692 | G58: =E58+F58 -> -0.3786692 | I58: =G58-H58 -> -0.3786692 | J58: =E58+E59+F58+F59 -> 0.0053308 | K58: 28.471 | L58: =-31.5730854 -> -31.573085 | M58: =K58+L58 -> -3.1020854 | O58: =M58-N58 -> -3.1020854 | P58: =K58+K59+L58+L59 -> 0.0399146 | Q58: =E58+K58 -> 32.021 | R58: =F58+L58 -> -35.501755 | S58: =Q58+R58 -> -3.4807546 | T58: =H58+N58 -> 0 | U58: =S58-T58 -> -3.4807546 | V58: =T58/S58 -> 0 | W58: =Q58+Q59 -> 35.547 | X58: =R58+R59 -> -35.501755 | Y58: =W58+X58 -> 0.0452454 | Z58: =T58+T59 -> 0 | AA58: =Y58-Z58 -> 0.0452454 | AB58: =Z58/Y58 -> 0
C59: 42278 | D59: 42368 | E59: 0.384 | G59: =E59+F59+I58 -> 0.0053308 | I59: =G59-H59 -> 0.0053308 | K59: 3.142 | M59: =K59+L59+O58 -> 0.0399146 | O59: =M59-N59 -> 0.0399146 | Q59: =E59+K59 -> 3.526 | R59: =F59+L59 -> 0 | S59: =Q59+R59+U58 -> 0.0452454 | T59: =H59+N59 -> 0 | U59: =S59-T59 -> 0.0452454 | V59: =T59/S59 -> 0 | AH59: =+AG56/AG55 -> -1.25
B60: BRACPESCA S.A. | C60: 42064 | D60: 42246 | E60: =51.241+1.665 -> 52.906 | F60: =2.337+1.271+0.04264+0.52316+0.4626276+0.00492 -> 4.6413476 | G60: =E60+F60 -> 57.547348 | I60: =G60-H60 -> 57.547348 | J60: =E60+E61+F60+F61 -> 63.267348 | K60: =410.97+13.354 -> 424.324 | L60: =60+179.7+18.7815+10.2145+0.34268+4.20442+3.7179462+0.03954 -> 277.00059 | M60: =K60+L60 -> 701.32459 | N60: 395.655 | O60: =M60-N60 -> 305.66959 | P60: =K60+K61+L60+L61 -> 748.15459 | Q60: =E60+K60 -> 477.23 | R60: =F60+L60 -> 281.64193 | S60: =Q60+R60 -> 758.87193 | T60: =H60+N60 -> 395.655 | U60: =S60-T60 -> 363.21693 | V60: =T60/S60 -> 0.52137256 | W60: =Q60+Q61 -> 529.78 | X60: =R60+R61 -> 281.64193 | Y60: =W60+X60 -> 811.42193 | Z60: =T60+T61 -> 748.142 | AA60: =Y60-Z60 -> 63.279934 | AB60: =Z60/Y60 -> 0.92201353
C61: 42278 | D61: 42368 | E61: =5.54+0.18 -> 5.72 | G61: =E61+F61+I60 -> 63.267348 | I61: =G61-H61 -> 63.267348 | K61: =45.356+1.474 -> 46.83 | M61: =K61+L61+O60 -> 352.49959 | N61: 352.487 | O61: =M61-N61 -> 0.0125862 | Q61: =E61+K61 -> 52.55 | R61: =F61+L61 -> 0 | S61: =Q61+R61+U60 -> 415.76693 | T61: =H61+N61 -> 352.487 | U61: =S61-T61 -> 63.279934 | V61: =T61/S61 -> 0.8477995
B62: GRIMAR S.A. PESQ. | C62: 42064 | D62: 42246 | E62: 0.026 | G62: =E62+F62 -> 0.026 | I62: =G62-H62 -> 0.026 | J62: =E62+E63+F62+F63 -> 0.029 | K62: 0.205 | M62: =K62+L62 -> 0.205 | O62: =M62-N62 -> 0.205 | P62: =K62+K63+L62+L63 -> 0.228 | Q62: =E62+K62 -> 0.231 | R62: =F62+L62 -> 0 | S62: =Q62+R62 -> 0.231 | T62: =H62+N62 -> 0 | U62: =S62-T62 -> 0.231 | V62: =T62/S62 -> 0 | W62: =Q62+Q63 -> 0.257 | X62: =R62+R63 -> 0 | Y62: =W62+X62 -> 0.257 | Z62: =T62+T63 -> 0 | AA62: =Y62-Z62 -> 0.257 | AB62: =Z62/Y62 -> 0
C63: 42278 | D63: 42368 | E63: 0.003 | G63: =E63+F63+I62 -> 0.029 | I63: =G63-H63 -> 0.029 | K63: 0.023 | M63: =K63+L63+O62 -> 0.228 | O63: =M63-N63 -> 0.228 | Q63: =E63+K63 -> 0.026 | R63: =F63+L63 -> 0 | S63: =Q63+R63+U62 -> 0.257 | T63: =H63+N63 -> 0 | U63: =S63-T63 -> 0.257 | V63: =T63/S63 -> 0
B64: ISLADAMAS S.A. PESQ. | C64: 42064 | D64: 42246 | E64: =6.493+1.665 -> 8.158 | F64: =-0.00984-0.11316-0.04264-0.52316+7.749+3.5525188+1.476+0.369+0.11808 -> 12.575799 | G64: =E64+F64 -> 20.733799 | I64: =G64-H64 -> 20.733799 | J64: =E64+E65+F64+F65 -> 21.615799 | K64: =52.074+13.354 -> 65.428 | L64: =-0.07908-0.90942-0.34268-4.20442+62.2755+28.5501206+11.862+2.9655+0.94896+9.9 -> 110.96648 | M64: =K64+L64 -> 176.39448 | N64: 129.814 | O64: =M64-N64 -> 46.580481 | P64: =K64+K65+L64+L65 -> 183.61548 | Q64: =E64+K64 -> 73.586 | R64: =F64+L64 -> 123.54228 | S64: =Q64+R64 -> 197.12828 | T64: =H64+N64 -> 129.814 | U64: =S64-T64 -> 67.314279 | V64: =T64/S64 -> 0.65852551 | W64: =Q64+Q65 -> 81.689 | X64: =R64+R65 -> 123.54228 | Y64: =W64+X64 -> 205.23128 | Z64: =T64+T65 -> 192.552 | AA64: =Y64-Z64 -> 12.679279 | AB64: =Z64/Y64 -> 0.93821956
C65: 42278 | D65: 42368 | E65: =0.702+0.18 -> 0.882 | G65: =E65+F65+I64 -> 21.615799 | H65: 9.919 | I65: =G65-H65 -> 11.696799 | K65: =5.747+1.474 -> 7.221 | M65: =K65+L65+O64 -> 53.801481 | N65: 52.819 | O65: =M65-N65 -> 0.9824806 | Q65: =E65+K65 -> 8.103 | R65: =F65+L65 -> 0 | S65: =Q65+R65+U64 -> 75.417279 | T65: =H65+N65 -> 62.738 | U65: =S65-T65 -> 12.679279 | V65: =T65/S65 -> 0.83187832
B66: MOROZIN BAYCIC MARIA ANA | C66: 42064 | D66: 42246 | E66: 0.883 | F66: =-0.9615648 -> -0.9615648 | G66: =E66+F66 -> -0.0785648 | I66: =G66-H66 -> -0.0785648 | J66: =E66+E67+F66+F67 -> 0.0164352 | K66: 7.078 | L66: =-7.7276976 -> -7.7276976 | M66: =K66+L66 -> -0.6496976 | O66: =M66-N66 -> -0.6496976 | P66: =K66+K67+L66+L67 -> 0.1313024 | Q66: =E66+K66 -> 7.961 | R66: =F66+L66 -> -8.6892624 | S66: =Q66+R66 -> -0.7282624 | T66: =H66+N66 -> 0 | U66: =S66-T66 -> -0.7282624 | V66: =T66/S66 -> 0 | W66: =Q66+Q67 -> 8.837 | X66: =R66+R67 -> -8.6892624 | Y66: =W66+X66 -> 0.1477376 | Z66: =T66+T67 -> 0 | AA66: =Y66-Z66 -> 0.1477376 | AB66: =Z66/Y66 -> 0
C67: 42278 | D67: 42368 | E67: 0.095 | G67: =E67+F67+I66 -> 0.0164352 | I67: =G67-H67 -> 0.0164352 | K67: 0.781 | M67: =K67+L67+O66 -> 0.1313024 | O67: =M67-N67 -> 0.1313024 | Q67: =E67+K67 -> 0.876 | R67: =F67+L67 -> 0 | S67: =Q67+R67+U66 -> 0.1477376 | T67: =H67+N67 -> 0 | U67: =S67-T67 -> 0.1477376 | V67: =T67/S67 -> 0
B68: MOROZIN YURECIC MARIO | C68: 42064 | D68: 42246 | E68: 0.396 | F68: =-0.4356824 -> -0.4356824 | G68: =E68+F68 -> -0.0396824 | I68: =G68-H68 -> -0.0396824 | J68: =E68+E69+F68+F69 -> 0.0033176 | K68: 3.177 | L68: =-3.5013988 -> -3.5013988 | M68: =K68+L68 -> -0.3243988 | O68: =M68-N68 -> -0.3243988 | P68: =K68+K69+L68+L69 -> 0.0266012 | Q68: =E68+K68 -> 3.573 | R68: =F68+L68 -> -3.9370812 | S68: =Q68+R68 -> -0.3640812 | T68: =H68+N68 -> 0 | U68: =S68-T68 -> -0.3640812 | V68: =T68/S68 -> 0 | W68: =Q68+Q69 -> 3.967 | X68: =R68+R69 -> -3.9370812 | Y68: =W68+X68 -> 0.0299188 | Z68: =T68+T69 -> 0 | AA68: =Y68-Z68 -> 0.0299188 | AB68: =Z68/Y68 -> 0
C69: 42278 | D69: 42368 | E69: 0.043 | G69: =E69+F69+I68 -> 0.0033176 | I69: =G69-H69 -> 0.0033176 | K69: 0.351 | M69: =K69+L69+O68 -> 0.0266012 | O69: =M69-N69 -> 0.0266012 | Q69: =E69+K69 -> 0.394 | R69: =F69+L69 -> 0 | S69: =Q69+R69+U68 -> 0.0299188 | T69: =H69+N69 -> 0 | U69: =S69-T69 -> 0.0299188 | V69: =T69/S69 -> 0
B70: QUINTERO S.A. PESQ. | C70: 42064 | D70: 42246 | E70: =4.221+1.554 -> 5.775 | F70: =-0.6642+3.9286692+0.9615648+0.4356824-0.1328564-0.4626276-0.00492 -> 4.0613124 | G70: =E70+F70 -> 9.8363124 | I70: =G70-H70 -> 9.8363124 | J70: =E70+E71+F70+F71 -> 10.460312 | K70: =33.857+12.464 -> 46.321 | L70: =153.2-5.3379+31.5730854+7.7276976+3.5013988-1.0677118-3.71794662-0.03954 -> 185.83908 | M70: =K70+L70 -> 232.16008 | N70: 165.886 | O70: =M70-N70 -> 66.274083 | P70: =K70+K71+L70+L71 -> 237.27308 | Q70: =E70+K70 -> 52.096 | R70: =F70+L70 -> 189.9004 | S70: =Q70+R70 -> 241.9964 | T70: =H70+N70 -> 165.886 | U70: =S70-T70 -> 76.110396 | V70: =T70/S70 -> 0.68548955 | W70: =Q70+Q71 -> 57.833 | X70: =R70+R71 -> 189.9004 | Y70: =W70+X70 -> 247.7334 | Z70: =T70+T71 -> 224.953 | AA70: =Y70-Z70 -> 22.780396 | AB70: =Z70/Y70 -> 0.90804471
C71: 42278 | D71: 42368 | E71: =0.456+0.168 -> 0.624 | G71: =E71+F71+I70 -> 10.460312 | I71: =G71-H71 -> 10.460312 | K71: =3.737+1.376 -> 5.113 | M71: =K71+L71+O70 -> 71.387083 | N71: 59.067 | O71: =M71-N71 -> 12.320083 | Q71: =E71+K71 -> 5.737 | R71: =F71+L71 -> 0 | S71: =Q71+R71+U70 -> 81.847396 | T71: =H71+N71 -> 59.067 | U71: =S71-T71 -> 22.780396 | V71: =T71/S71 -> 0.72167232
B72: RUBIO Y MAUAD LTDA. | C72: 42064 | D72: 42246 | E72: 6.577 | F72: =0.00984+0.11316+0.6642 -> 0.7872 | G72: =E72+F72 -> 7.3642 | I72: =G72-H72 -> 7.3642 | J72: =E72+E73+F72+F73 -> 8.0752 | K72: 52.751 | L72: =50+0.07908+0.90942+5.3379+4.5 -> 60.8264 | M72: =K72+L72 -> 113.5774 | N72: 100.101 | O72: =M72-N72 -> 13.4764 | P72: =K72+K73+L72+L73 -> 119.3994 | Q72: =E72+K72 -> 59.328 | R72: =F72+L72 -> 61.6136 | S72: =Q72+R72 -> 120.9416 | T72: =H72+N72 -> 100.101 | U72: =S72-T72 -> 20.8406 | V72: =T72/S72 -> 0.82768047 | W72: =Q72+Q73 -> 65.861 | X72: =R72+R73 -> 61.6136 | Y72: =W72+X72 -> 127.4746 | Z72: =T72+T73 -> 119.02 | AA72: =Y72-Z72 -> 8.4546 | AB72: =Z72/Y72 -> 0.9336762
C73: 42278 | D73: 42368 | E73: 0.711 | G73: =E73+F73+I72 -> 8.0752 | I73: =G73-H73 -> 8.0752 | K73: 5.822 | M73: =K73+L73+O72 -> 19.2984 | N73: 18.919 | O73: =M73-N73 -> 0.3794 | Q73: =E73+K73 -> 6.533 | R73: =F73+L73 -> 0 | S73: =Q73+R73+U72 -> 27.3736 | T73: =H73+N73 -> 18.919 | U73: =S73-T73 -> 8.4546 | V73: =T73/S73 -> 0.69114037
B74: SUNRISE S.A. PESQ. | C74: 42064 | D74: 42246 | E74: 3.206 | F74: =-3.5525188 -> -3.5525188 | G74: =E74+F74 -> -0.3465188 | I74: =G74-H74 -> -0.3465188 | J74: =E74+E75+F74+F75 -> 0.0004812 | K74: 25.712 | L74: =-28.5501206 -> -28.550121 | M74: =K74+L74 -> -2.8381206 | O74: =M74-N74 -> -2.8381206 | P74: =K74+K75+L74+L75 -> -0.0001206 | Q74: =E74+K74 -> 28.918 | R74: =F74+L74 -> -32.102639 | S74: =Q74+R74 -> -3.1846394 | T74: =H74+N74 -> 0 | U74: =S74-T74 -> -3.1846394 | V74: =T74/S74 -> 0 | W74: =Q74+Q75 -> 32.103 | X74: =R74+R75 -> -32.102639 | Y74: =W74+X74 -> 0.0003606 | Z74: =T74+T75 -> 0 | AA74: =Y74-Z74 -> 0.0003606 | AB74: =Z74/Y74 -> 0
C75: 42278 | D75: 42368 | E75: 0.347 | G75: =E75+F75+I74 -> 0.0004812 | I75: =G75-H75 -> 0.0004812 | K75: 2.838 | M75: =K75+L75+O74 -> -0.0001206 | O75: =M75-N75 -> -0.0001206 | Q75: =E75+K75 -> 3.185 | R75: =F75+L75 -> 0 | S75: =Q75+R75+U74 -> 0.0003606 | T75: =H75+N75 -> 0 | U75: =S75-T75 -> 0.0003606 | V75: =T75/S75 -> 0
B76: ENFEMAR LTDA. SOC. PESQ. | C76: 42064 | D76: 42246 | E76: 0 | F76: =0.1328564 -> 0.1328564 | G76: =E76+F76 -> 0.1328564 | I76: =G76-H76 -> 0.1328564 | J76: =E76+E77+F76+F77 -> 0.1328564 | K76: 0 | L76: 1.0677118 | M76: =K76+L76 -> 1.0677118 | O76: =M76-N76 -> 1.0677118 | P76: =K76+K77+L76+L77 -> 1.0677118 | Q76: =E76+K76 -> 0 | R76: =F76+L76 -> 1.2005682 | S76: =Q76+R76 -> 1.2005682 | T76: =H76+N76 -> 0 | U76: =S76-T76 -> 1.2005682 | V76: =T76/S76 -> 0 | W76: =Q76+Q77 -> 0 | X76: =R76+R77 -> 1.2005682 | Y76: =W76+X76 -> 1.2005682 | Z76: =T76+T77 -> 0 | AA76: =Y76-Z76 -> 1.2005682 | AB76: =Z76/Y76 -> 0
C77: 42278 | D77: 42368 | E77: 0 | G77: =E77+F77+I76 -> 0.1328564 | I77: =G77-H77 -> 0.1328564 | K77: 0 | M77: =K77+L77+O76 -> 1.0677118 | O77: =M77-N77 -> 1.0677118 | Q77: =E77+K77 -> 0 | R77: =F77+L77 -> 0 | S77: =Q77+R77+U76 -> 1.2005682 | T77: =H77+N77 -> 0 | U77: =S77-T77 -> 1.2005682 | V77: =T77/S77 -> 0
B78: ALIMENTOS ALSAN LIMITADA | C78: 41640 | D78: 42216 | E78: =8.769 -> 8.769 | F78: =-7.749-1.476-0.369-0.11808 -> -9.71208 | G78: =E78+F78 -> -0.94308 | I78: =G78-H78 -> -0.94308 | J78: =E78+E79+F78+F79 -> 0.00492 | K78: =70.33 -> 70.33 | L78: =-62.2755-11.862-2.9655-0.94896 -> -78.05196 | M78: =K78+L78 -> -7.72196 | O78: =M78-N78 -> -7.72196 | P78: =K78+K79+L78+L79 -> 0.04004 | Q78: =E78+K78 -> 79.099 | R78: =F78+L78 -> -87.76404 | S78: =Q78+R78 -> -8.66504 | T78: =H78+N78 -> 0 | U78: =S78-T78 -> -8.66504 | V78: =T78/S78 -> 0 | W78: =Q78+Q79 -> 87.809 | X78: =R78+R79 -> -87.76404 | Y78: =W78+X78 -> 0.04496 | Z78: =T78+T79 -> 0 | AA78: =Y78-Z78 -> 0.04496 | AB78: =Z78/Y78 -> 0
C79: 42278 | D79: 42369 | E79: =0.948 -> 0.948 | G79: =E79+F79+I78 -> 0.00492 | I79: =G79-H79 -> 0.00492 | K79: =7.762 -> 7.762 | M79: =K79+L79+O78 -> 0.04004 | O79: =M79-N79 -> 0.04004 | Q79: =E79+K79 -> 8.71 | R79: =F79+L79 -> 0 | S79: =Q79+R79+U78 -> 0.04496 | T79: =H79+N79 -> 0 | U79: =S79-T79 -> 0.04496 | V79: =T79/S79 -> 0
B80: SOC. DISTRIB. PRODUCTOS DEL MAR LTDA. | C80: 42064 | D80: 42246 | E80: 0 | F80: =1.476+0.369-1.476-0.369 -> 0 | G80: =E80+F80 -> 0 | I80: =G80-H80 -> 0 | J80: =E80+E81+F80+F81 -> 0 | K80: 0 | L80: =11.862+2.9655-11.862-2.9655 -> 0 | M80: =K80+L80 -> 0 | O80: =M80-N80 -> 0 | P80: =K80+K81+L80+L81 -> 0 | Q80: =E80+K80 -> 0 | R80: =F80+L80 -> 0 | S80: =Q80+R80 -> 0 | T80: =H80+N80 -> 0 | U80: =S80-T80 -> 0 | V80: =T80/S80 -> #DIV/0! | W80: =Q80+Q81 -> 0 | X80: =R80+R81 -> 0 | Y80: =W80+X80 -> 0 | Z80: =T80+T81 -> 0 | AA80: =Y80-Z80 -> 0 | AB80: 0
C81: 42278 | D81: 42368 | E81: 0 | G81: =E81+F81+I80 -> 0 | I81: =G81-H81 -> 0 | K81: 0 | M81: =K81+L81+O80 -> 0 | O81: =M81-N81 -> 0 | Q81: =E81+K81 -> 0 | R81: =F81+L81 -> 0 | S81: =Q81+R81+U80 -> 0 | T81: =H81+N81 -> 0 | U81: =S81-T81 -> 0 | V81: =T81/S81 -> #DIV/0!
H82: =+H56+H58+H60+H62+H64+H66+H68+H70+H72+H74+H76+H78+H80 -> 23.91 | I82: =189.597-179.2 -> 10.397 | K82: =SUM(K56:K81) -> 1318.003 | L82: =SUM(L56:L81) -> 467.3 | N82: =+N56+N58+N60+N62+N64+N66+N68+N70+N72+N74+N76+N78+N80 -> 1283.641 | O82: =+O57+O61+O63+O65+O69+O67+O71+O73+O75+O77+O79+O83 -> 11.823085 | Q82: =SUM(Q56:Q81) -> 1482.004 | T82: =+T56+T58+T60+T62+T64+T66+T68+T70+T72+T74+T76+T78+T80 -> 1307.551 | W82: =SUM(W56:W79) -> 1482.004 | X82: =SUM(X56:X79) -> 467.3 | Y82: =SUM(Y56:Y81) -> 1949.304 | Z82: =SUM(Z56:Z79) -> 1829.24 | AA82: =SUM(AA56:AA79) -> 120.064 | AB82: =Z82/Y82 -> 0.93840673
H83: =+H57+H59+H61+H63+H65+H67+H69+H71+H73+H75+H77+H79+H81 -> 31.89 | N83: =+N57+N59+N61+N63+N65+N67+N69+N71+N73+N75+N77+N79+N81 -> 489.799 | P83: =13.354+1.474 -> 14.828 | T83: =+T57+T59+T61+T63+T65+T67+T69+T71+T73+T75+T77+T79+T81 -> 521.689
C84: Periodo | E84: Cuota II y III Región (t) | H84: Operación II y III región | K84: Cuota IV Región (t) | N84: Operación IV Región | Q84: Cuota y Operación Langostino colorado II-IV | W84: Resumen global anual XV-IV
A85: Unidad de pesquería | B85: Armador | C85: Inicial | D85: Final | E85: Cuota Asignada | F85: Traspaso, Cesion, Arriendo, etc) | G85: Cuota Efectiva | H85: Desembarque (t) | I85: Saldo (t) | J85: Cuota Total | K85: Cuota Asignada | L85: Traspaso, Cesion, Arriendo, etc) | M85: Cuota Efectiva | N85: Desembarque (t) | O85: Saldo (t) | P85: Cuota Total efectiva | Q85: Cuota Asignada III-IV | R85: * Traspaso, Cesion, Arriendo, etc) | S85: Cuota Efectiva | T85: Desembarque (t) III-IV | U85: Saldo (t) | V85: % consumido | W85: Cuota Total | X85: * Traspaso, Cesion, Arriendo, etc) | Y85: Cuota Efectiva | Z85: Desembarque (t) | AA85: Saldo (t) | AB85: % consumido
A86: Langostino colorado II-IV | B86: ANTARTIC SEAFOOD S.A. | C86: 42064 | D86: 42246 | E86: =9.447+1.168 -> 10.615 | G86: =E86+F86 -> 10.615 | I86: =G86-H86 -> 10.615 | J86: =E86+E87+F86+F87 -> 11.822 | K86: =23.189+2.867 -> 26.056 | M86: =K86+L86 -> 26.056 | N86: 27.026 | O86: =M86-N86 -> -0.97 | P86: =K86+K87+L86+L87 -> 28.952 | Q86: =E86+K86 -> 36.671 | R86: =F86+L86 -> 0 | S86: =Q86+R86 -> 36.671 | T86: =H86+N86 -> 27.026 | U86: =S86-T86 -> 9.645 | V86: =T86/S86 -> 0.73698563 | W86: =Q86+Q87 -> 40.774 | X86: =R86+R87 -> 0 | Y86: =W86+X86 -> 40.774 | Z86: =T86+T87 -> 36.292 | AA86: =Y86-Z86 -> 4.482 | AB86: =Z86/Y86 -> 0.89007701
C87: 42278 | D87: 42368 | E87: =1.074+0.133 -> 1.207 | G87: =E87+F87+I86 -> 11.822 | H87: 9.266 | I87: =G87-H87 -> 2.556 | K87: =2.577+0.319 -> 2.896 | M87: =K87+L87+O86 -> 1.926 | O87: =M87-N87 -> 1.926 | Q87: =E87+K87 -> 4.103 | R87: =F87+L87 -> 0 | S87: =Q87+R87+U86 -> 13.748 | T87: =H87+N87 -> 9.266 | U87: =S87-T87 -> 4.482 | V87: =T87/S87 -> 0.67398894
B88: BRACPESCA S.A. | C88: 42064 | D88: 42246 | E88: =18.815+0.205+0.482+1.65 -> 21.152 | G88: =E88+F88 -> 21.152 | I88: =G88-H88 -> 21.152 | J88: =E88+E89+F88+F89 -> 23.556 | K88: =46.183+0.502+1.183+4.05 -> 51.918 | L88: 79.99 | M88: =K88+L88 -> 131.908 | N88: 113.704 | O88: =M88-N88 -> 18.204 | P88: =K88+K89+L88+L89 -> 137.676 | Q88: =E88+K88 -> 73.07 | R88: =F88+L88 -> 79.99 | S88: =Q88+R88 -> 153.06 | T88: =H88+N88 -> 113.704 | U88: =S88-T88 -> 39.356 | V88: =T88/S88 -> 0.74287208 | W88: =Q88+Q89 -> 81.242 | X88: =R88+R89 -> 79.99 | Y88: =W88+X88 -> 161.232 | Z88: =T88+T89 -> 129.753 | AA88: =Y88-Z88 -> 31.479 | AB88: =Z88/Y88 -> 0.8047596
C89: 42278 | D89: 42368 | E89: =2.138+0.023+0.055+0.188 -> 2.404 | G89: =E89+F89+I88 -> 23.556 | I89: =G89-H89 -> 23.556 | K89: =5.131+0.056+0.131+0.45 -> 5.768 | M89: =K89+L89+O88 -> 23.972 | N89: 16.049 | O89: =M89-N89 -> 7.923 | Q89: =E89+K89 -> 8.172 | R89: =F89+L89 -> 0 | S89: =Q89+R89+U88 -> 47.528 | T89: =H89+N89 -> 16.049 | U89: =S89-T89 -> 31.479 | V89: =T89/S89 -> 0.33767463
B90: ISLADAMAS S.A. PESQ. | C90: 42064 | D90: 42246 | E90: =4.308+1.016 -> 5.324 | F90: =1.1025+1.0976+4.3850443 -> 6.5851443 | G90: =E90+F90 -> 11.909144 | I90: =G90-H90 -> 11.909144 | J90: =E90+E91+F90+F91 -> 12.515144 | K90: =10.574+2.495 -> 13.069 | L90: =2.7+2.688+10.738884 -> 16.126884 | M90: =K90+L90 -> 29.195884 | N90: 20.688 | O90: =M90-N90 -> 8.507884 | P90: =K90+K91+L90+L91 -> 30.647884 | Q90: =E90+K90 -> 18.393 | R90: =F90+L90 -> 22.712028 | S90: =Q90+R90 -> 41.105028 | T90: =H90+N90 -> 20.688 | U90: =S90-T90 -> 20.417028 | V90: =T90/S90 -> 0.50329609 | W90: =Q90+Q91 -> 20.451 | X90: =R90+R91 -> 22.712028 | Y90: =W90+X90 -> 43.163028 | Z90: =T90+T91 -> 37.737 | AA90: =Y90-Z90 -> 5.4260283 | AB90: =Z90/Y90 -> 0.87428991
C91: 42278 | D91: 42368 | E91: =0.49+0.116 -> 0.606 | G91: =E91+F91+I90 -> 12.515144 | H91: 10.04 | I91: =G91-H91 -> 2.4751443 | K91: =1.175+0.277 -> 1.452 | M91: =K91+L91+O90 -> 9.959884 | N91: 7.009 | O91: =M91-N91 -> 2.950884 | Q91: =E91+K91 -> 2.058 | R91: =F91+L91 -> 0 | S91: =Q91+R91+U90 -> 22.475028 | T91: =H91+N91 -> 17.049 | U91: =S91-T91 -> 5.4260283 | V91: =T91/S91 -> 0.75857524
B92: RUBIO Y MAUAD LTDA. | C92: 42064 | D92: 42246 | E92: =0.795+0.099 -> 0.894 | G92: =E92+F92 -> 0.894 | I92: =G92-H92 -> 0.894 | J92: =E92+E93+F92+F93 -> 0.995 | K92: =1.951+0.243 -> 2.194 | L92: 50 | M92: =K92+L92 -> 52.194 | N92: 52.848 | O92: =M92-N92 -> -0.654 | P92: =K92+K93+L92+L93 -> 52.438 | Q92: =E92+K92 -> 3.088 | R92: =F92+L92 -> 50 | S92: =Q92+R92 -> 53.088 | T92: =H92+N92 -> 52.848 | U92: =S92-T92 -> 0.24 | V92: =T92/S92 -> 0.9954792 | W92: =Q92+Q93 -> 3.433 | X92: =R92+R93 -> 50 | Y92: =W92+X92 -> 53.433 | Z92: =T92+T93 -> 52.848 | AA92: =Y92-Z92 -> 0.585 | AB92: =Z92/Y92 -> 0.98905171
C93: 42278 | D93: 42368 | E93: =0.09+0.011 -> 0.101 | G93: =E93+F93+I92 -> 0.995 | I93: =G93-H93 -> 0.995 | K93: =0.217+0.027 -> 0.244 | M93: =K93+L93+O92 -> -0.41 | O93: =M93-N93 -> -0.41 | Q93: =E93+K93 -> 0.345 | R93: =F93+L93 -> 0 | S93: =Q93+R93+U92 -> 0.585 | T93: =H93+N93 -> 0 | U93: =S93-T93 -> 0.585 | V93: =T93/S93 -> 0
B94: PESQUERA SUNRISE S.A. | C94: 42064 | D94: 42246 | E94: =3.938 -> 3.938 | F94: =-4.3850443 -> -4.3850443 | G94: =E94+F94 -> -0.4470443 | I94: =G94-H94 -> -0.4470443 | J94: =E94+E95+F94+F95 -> -4.43e-05 | K94: =9.665 -> 9.665 | L94: =-10.738884 -> -10.738884 | M94: =K94+L94 -> -1.073884 | O94: =M94-N94 -> -1.073884 | P94: =K94+K95+L94+L95 -> 0.000116 | Q94: =E94+K94 -> 13.603 | R94: =F94+L94 -> -15.123928 | S94: =Q94+R94 -> -1.5209283 | T94: =H94+N94 -> 0 | U94: =S94-T94 -> -1.5209283 | V94: =T94/S94 -> 0 | W94: =Q94+Q95 -> 15.124 | X94: =R94+R95 -> -15.123928 | Y94: =W94+X94 -> 7.17e-05 | Z94: =T94+T95 -> 0 | AA94: =Y94-Z94 -> 7.17e-05 | AB94: =Z94/Y94 -> 0
C95: 42278 | D95: 42368 | E95: =0.447 -> 0.447 | G95: =E95+F95+I94 -> -4.43e-05 | I95: =G95-H95 -> -4.43e-05 | K95: =1.074 -> 1.074 | M95: =K95+L95+O94 -> 0.000116 | O95: =M95-N95 -> 0.000116 | Q95: =E95+K95 -> 1.521 | R95: =F95+L95 -> 0 | S95: =Q95+R95+U94 -> 7.17e-05 | T95: =H95+N95 -> 0 | U95: =S95-T95 -> 7.17e-05 | V95: =T95/S95 -> 0
B96: QUINTERO S.A. PESQ. | C96: 41640 | D96: 42216 | E96: 0.097 | G96: =E96+F96 -> 0.097 | I96: =G96-H96 -> 0.097 | J96: =E96+E97+F96+F97 -> 0.108 | K96: 0.238 | M96: =K96+L96 -> 0.238 | O96: =M96-N96 -> 0.238 | P96: =K96+K97+L96+L97 -> 0.264 | Q96: =E96+K96 -> 0.335 | R96: =F96+L96 -> 0 | S96: =Q96+R96 -> 0.335 | T96: =H96+N96 -> 0 | U96: =S96-T96 -> 0.335 | V96: =T96/S96 -> 0 | W96: =Q96+Q97 -> 0.372 | X96: =R96+R97 -> 0 | Y96: =W96+X96 -> 0.372 | Z96: =T96+T97 -> 0 | AA96: =Y96-Z96 -> 0.372 | AB96: =Z96/Y96 -> 0
C97: 42278 | D97: 42369 | E97: 0.011 | G97: =E97+F97+I96 -> 0.108 | I97: =G97-H97 -> 0.108 | K97: 0.026 | M97: =K97+L97+O96 -> 0.264 | O97: =M97-N97 -> 0.264 | Q97: =E97+K97 -> 0.037 | R97: =F97+L97 -> 0 | S97: =Q97+R97+U96 -> 0.372 | T97: =H97+N97 -> 0 | U97: =S97-T97 -> 0.372 | V97: =T97/S97 -> 0
B98: ALIMENTOS ALSAN LIMITADA | C98: 41640 | D98: 42216 | E98: =0.99+0.99 -> 1.98 | F98: =-1.1025-1.0976 -> -2.2001 | G98: =E98+F98 -> -0.2201 | I98: =G98-H98 -> -0.2201 | J98: =E98+E99+F98+F99 -> 0.0059 | K98: =2.43+2.43 -> 4.86 | L98: =-2.7-2.688 -> -5.388 | M98: =K98+L98 -> -0.528 | O98: =M98-N98 -> -0.528 | P98: =K98+K99+L98+L99 -> 0.012 | Q98: =E98+K98 -> 6.84 | R98: =F98+L98 -> -7.5881 | S98: =Q98+R98 -> -0.7481 | T98: =H98+N98 -> 0 | U98: =S98-T98 -> -0.7481 | V98: =T98/S98 -> 0 | W98: =Q98+Q99 -> 7.606 | X98: =R98+R99 -> -7.5881 | Y98: =W98+X98 -> 0.0179 | Z98: =T98+T99 -> 0 | AA98: =Y98-Z98 -> 0.0179 | AB98: =Z98/Y98 -> 0
C99: 42278 | D99: 42369 | E99: =0.113+0.113 -> 0.226 | G99: =E99+F99+I98 -> 0.0059 | I99: =G99-H99 -> 0.0059 | K99: =0.27+0.27 -> 0.54 | M99: =K99+L99+O98 -> 0.012 | O99: =M99-N99 -> 0.012 | Q99: =E99+K99 -> 0.766 | R99: =F99+L99 -> 0 | S99: =Q99+R99+U98 -> 0.0179 | T99: =H99+N99 -> 0 | U99: =S99-T99 -> 0.0179 | V99: =T99/S99 -> 0
H100: =+H86+H88+H90+H92+H94+H98+H96 -> 0 | N100: =+N86+N88+N90+N92+N94+N98+N96 -> 214.266 | T100: =+T86+T88+T90+T92+T94+T98+T96 -> 214.266 | W100: =SUM(W86:W99) -> 169.002 | X100: =SUM(X86:X99) -> 129.99 | Y100: =SUM(Y86:Y99) -> 298.992 | Z100: =SUM(Z86:Z99) -> 256.63 | AA100: =SUM(AA86:AA99) -> 42.362 | AB100: =Z100/Y100 -> 0.85831728
...

Sheet ORP-PS
A2: CONTROL CUOTAS ORP-PS 2016
A3: actualizado al 27-01-2017
A5: Pesquería | B5: R. Ex N°/Fecha | C5: Titular de cuota | D5: Cuota Tranferida (ORP-PS) | E5: Embarcaciones Autorizadas | F5: Desembarque | G5: Saldo total (t) | H5: % consumido 2016 | N5: Carta ORP
A6: Jurel | B6: 1973/21-06-2016 | C6: BLUMAR S.A. | D6: 1100 | E6: DON ALFONSO | F6: 810.398 | G6: =+F11-D6 -> 0 | H6: =+F11/D6 -> 1 | N6: 104
E7: DON EDMUNDO | F7: 289.602 | N7: 104
E8: COBRA | N8: 81
E9: RAPANUI | N9: 146
E10: YELCHO | N10: 0102-2015
F11: =SUM(F6:F10) -> 1100 | N11: 0104-2015
N12: 074-2016
A13: Pesquería | B13: R. Ex N°/Fecha | C13: Titular de cuota | D13: Cuota Tranferida (ORP-PS) | E13: Embarcaciones Autorizadas | F13: Desembarque | G13: Saldo total (t) | H13: % consumido 2016 | N13: 090-2016
A14: Jurel | B14: 2779/12-09-2016 | C14: BLUMAR S.A. | D14: 4000 | E14: DON ALFONSO | F14: 1238.74 | G14: =+D14-F19 -> 0 | H14: =+F19/D14 -> 1 | N14: 106-2016
E15: DON EDMUNDO | N15: 108-2016
E16: COBRA | N16: 111-2016
E17: RAPANUI | F17: 1810.53 | N17: 126-2016
E18: YELCHO | F18: 950.73 | N18: 127-2016
F19: =SUM(F14:F18) -> 4000 | N19: Pendiente
A21: Pesquería | B21: R. Ex N°/Fecha DO | C21: Titular de cuota | D21: Cuota Tranferida (ORP-PS) | E21: Embarcaciones Autorizadas | F21: Desembarque | G21: Saldo total (t) | H21: % consumido 2016
A22: Jurel | B22: 2965/18-10-2016 | C22: LOTA PROTEIN S.A. | D22: 3000 | E22: SANTA MARIA II | F22: 3000 | G22: =+D22-F27 -> 0 | H22: =+F27/D22 -> 1
E23: DON ALFONSO
F27: =SUM(F22:F26) -> 3000
A30: Pesquería | B30: R. Ex N°/Fecha DO | C30: Titular de cuota | D30: Cuota Tranferida (ORP-PS) | E30: Embarcaciones Autorizadas | F30: Desembarque | G30: Saldo total (t) | H30: % consumido 2016
A31: Jurel | B31: 3293/03-11-2016 | C31: BLUMAR S.A. | D31: 5000 | E31: COBRA | F31: 1520.642 | G31: =+D31-F36 -> 0 | H31: =+F36/D31 -> 1
E32: DON ALFONSO | F32: 1154.695
E33: DON EDMUNDO | F33: 800.88
E34: RAPANUI | F34: 641.175
E35: YELCHO | F35: 882.608
F36: =SUM(F31:F35) -> 5000
A39: Pesquería | B39: R. Ex N°/Fecha DO | C39: Titular de cuota | D39: Cuota Tranferida (ORP-PS) | E39: Embarcaciones Autorizadas | F39: Desembarque | G39: Saldo total (t) | H39: % consumido 2016
A40: Jurel | B40: 3234 | C40: FOODCORP S.A. | D40: 5500 | E40: DON MANUEL | F40: 2213.193 | G40: =+D40-F45 -> 0 | H40: =+F45/D40 -> 1
E41: CAZADOR | F41: 3286.807
F45: =SUM(F40:F44) -> 5500
A48: Pesquería | B48: R. Ex N°/Fecha DO | C48: Titular de cuota | D48: Cuota Tranferida (ORP-PS) | E48: Embarcaciones Autorizadas | F48: Desembarque | G48: Saldo total (t) | H48: % consumido 2016
A49: Jurel | B49: 3551 | C49: LOTA PROTEIN | D49: 3000 | E49: DON TITO | F49: 1049.61 | G49: =+D49-F54 -> 0 | H49: =+F54/D49 -> 1
E50: DON BORIS | F50: 1011.107
E51: CORAL I | F51: 0
E52: SANTA MARIA II | F52: 939.283
F54: =SUM(F49:F53) -> 3000
A57: Pesquería | B57: R. Ex N°/Fecha DO | C57: Titular de cuota | D57: Cuota Tranferida (ORP-PS) | E57: Embarcaciones Autorizadas | F57: Desembarque | G57: Saldo total (t) | H57: % consumido 2016
A58: Jurel | B58: Res N° 3469 | C58: BLUMAR S.A. | D58: 4000 | E58: COBRA | F58: 1651.15 | G58: =+D58-F63 -> 498.685 | H58: =+F63/D58 -> 0.87532875
E59: DON ALFONSO | F59: 836.625
E60: DON EDMUNDO | F60: 545.595
E61: RAPANUI | F61: 467.945
E62: YELCHO I
F63: =SUM(F58:F62) -> 3501.315
A66: Pesquería | B66: R. Ex N°/Fecha DO | C66: Titular de cuota | D66: Cuota Tranferida (ORP-PS) | E66: Embarcaciones Autorizadas | F66: Desembarque | G66: Saldo total (t) | H66: % consumido 2016
A67: Jurel | B67: Res N° 3520 | C67: ORIZON S.A. | D67: 500 | E67: LOANCO | F67: 500 | G67: =+D67-F69 -> 0 | H67: 1
E68: DON JULIO | F68: 0
F69: =SUM(F67:F68) -> 500
F71: =+F63+F54+F45+F36+F27+F19+F11+F69 -> 25601.315
A73: Detalle desembarque Jurel ORP-PS 2016
A76: Año | B76: Mes | C76: Nr_Folio | D76: Nm_Pto | E76: Fc_Zarpe | F76: Fc_Llegada | G76: N° marea | H76: NM_ARMADOR | I76: Cd_Nave | J76: NM_NAVE | K76: Cd_Especie | L76: DESCR1TABL | M76: NM_ARTE | N76: SumaDeNr_Toneladas | O76: Cd_Zona | P76: Región Operacion | Q76: Región desembarque | R76: Cd_Regimen | S76: Nr_Resolucion | T76: dbo_Tb_Pesqueria.Nm_Pesqueria
A77: 2016 | B77: 7 | C77: 415547 | D77: SAN VICENTE | E77: 42553 | F77: 42556 | G77: 4 | H77: BLUMAR S.A. ( EX PESQUERA ITATA S.A.) | I77: 2530 | J77: DON ALFONSO | K77: 234 | L77: JUREL | M77: CERCO | N77: 495.496 | O77: 153 | P77: 8 | Q77: 8 | R77: 3 | S77: 697 | T77: Res N°1973 Transf. cuota Jurel ORPSS, 2016. Jurel
A78: 2016 | B78: 7 | C78: 415629 | D78: SAN VICENTE | E78: 42556 | F78: 42559 | G78: 4 | H78: BLUMAR S.A. ( EX PESQUERA ITATA S.A.) | I78: 1977 | J78: DON EDMUNDO | K78: 234 | L78: JUREL | M78: CERCO | N78: 289.602 | O78: 153 | P78: 8 | Q78: 8 | R78: 3 | S78: 697 | T78: Res N°1973 Transf. cuota Jurel ORPSS, 2016. Jurel
A79: 2016 | B79: 7 | C79: 415889 | D79: SAN VICENTE | E79: 42559 | F79: 42566 | G79: 8 | H79: BLUMAR S.A. ( EX PESQUERA ITATA S.A.) | I79: 2530 | J79: DON ALFONSO | K79: 234 | L79: JUREL | M79: CERCO | N79: 314.902 | O79: 150 | P79: 5 | Q79: 8 | R79: 3 | S79: 697 | T79: Res N°1973 Transf. cuota Jurel ORPSS, 2016. Jurel
A80: 2016 | B80: 10 | C80: 417376 | D80: SAN VICENTE | E80: 42649 | F80: 42655 | G80: 7 | H80: BLUMAR S.A. ( EX PESQUERA ITATA S.A.) | I80: 2530 | J80: DON ALFONSO | K80: 234 | L80: JUREL | M80: CERCO | N80: 195.75 | O80: 115 | P80: 9 | Q80: 8 | R80: 3 | S80: 746 | T80: Res N°2779 Transf. cuota Jurel ORPPS, 2016. Jurel
A81: 2016 | B81: 10 | C81: 417383 | D81: SAN VICENTE | E81: 42649 | F81: 42656 | G81: 8 | H81: BLUMAR S.A. ( EX PESQUERA ITATA S.A.) | I81: 2530 | J81: DON ALFONSO | K81: 234 | L81: JUREL | M81: CERCO | N81: 297.53 | O81: 115 | P81: 9 | Q81: 8 | R81: 3 | S81: 746 | T81: Res N°2779 Transf. cuota Jurel ORPPS, 2016. Jurel
A82: 2016 | B82: 10 | C82: 417413 | D82: SAN VICENTE | E82: 42658 | F82: 42661 | G82: 4 | H82: BLUMAR S.A. ( EX PESQUERA ITATA S.A.) | I82: 2530 | J82: DON ALFONSO | K82: 234 | L82: JUREL | M82: CERCO | N82: 390.68 | O82: 114 | P82: 8 | Q82: 8 | R82: 3 | S82: 746 | T82: Res N°2779 Transf. cuota Jurel ORPPS, 2016. Jurel
A83: 2016 | B83: 10 | C83: 417423 | D83: SAN VICENTE | E83: 42660 | F83: 42662 | G83: 3 | H83: BLUMAR S.A. ( EX PESQUERA ITATA S.A.) | I83: 1954 | J83: RAPANUI | K83: 234 | L83: JUREL | M83: CERCO | N83: 492.95 | O83: 114 | P83: 8 | Q83: 8 | R83: 3 | S83: 746 | T83: Res N°2779 Transf. cuota Jurel ORPPS, 2016. Jurel
A84: 2016 | B84: 10 | C84: 417429 | D84: SAN VICENTE | E84: 42660 | F84: 42663 | G84: 4 | H84: BLUMAR S.A. ( EX PESQUERA ITATA S.A.) | I84: 1954 | J84: RAPANUI | K84: 234 | L84: JUREL | M84: CERCO | N84: 85.1 | O84: 114 | P84: 8 | Q84: 8 | R84: 3 | S84: 746 | T84: Res N°2779 Transf. cuota Jurel ORPPS, 2016. Jurel
A85: 2016 | B85: 10 | C85: 417587 | D85: SAN VICENTE | E85: 42664 | F85: 42668 | G85: 5 | H85: BLUMAR S.A. ( EX PESQUERA ITATA S.A.) | I85: 1954 | J85: RAPANUI | K85: 234 | L85: JUREL | M85: CERCO | N85: 137.16 | O85: 114 | P85: 8 | Q85: 8 | R85: 3 | S85: 746 | T85: Res N°2779 Transf. cuota Jurel ORPPS, 2016. Jurel
A86: 2016 | B86: 10 | C86: 417591 | D86: SAN VICENTE | E86: 42661 | F86: 42668 | G86: 8 | H86: BLUMAR S.A. ( EX PESQUERA ITATA S.A.) | I86: 2530 | J86: DON ALFONSO | K86: 234 | L86: JUREL | M86: CERCO | N86: 133.28 | O86: 114 | P86: 8 | Q86: 8 | R86: 3 | S86: 746 | T86: Res N°2779 Transf. cuota Jurel ORPPS, 2016. Jurel
A87: 2016 | B87: 11 | C87: 417891 | D87: SAN VICENTE | E87: 42676 | F87: 42679 | G87: 4 | H87: BLUMAR S.A. ( EX PESQUERA ITATA S.A.) | I87: 1954 | J87: RAPANUI | K87: 234 | L87: JUREL | M87: CERCO | N87: 348.3 | O87: 114 | P87: 8 | Q87: 8 | R87: 3 | S87: 746 | T87: Res N°2779 Transf. cuota Jurel ORPPS, 2016. Jurel
A88: 2016 | B88: 11 | C88: 417897 | D88: SAN VICENTE | E88: 42677 | F88: 42679 | G88: 3 | H88: BLUMAR S.A. ( EX PESQUERA ITATA S.A.) | I88: 2530 | J88: DON ALFONSO | K88: 234 | L88: JUREL | M88: CERCO | N88: 221.5 | O88: 114 | P88: 8 | Q88: 8 | R88: 3 | S88: 746 | T88: Res N°2779 Transf. cuota Jurel ORPPS, 2016. Jurel
... A136: 2016 | B136: 12 | C136: 418448 | D136: LOTA | E136: 42725 | F136: 42732 | G136: 8 | H136: LOTA PROTEIN S.A. (EX LOTA VEDDE) | I136: 1962 | J136: SANTA MARIA II | K136: 234 | L136: JUREL | M136: CERCO | N136: 188.367 | O136: 153 | P136: 8 | Q136: 8 | R136: 3 | S136: 777 | T136: Res N°3551 Transf. cuota Jurel ORPPS, 2016. Jurel (A. Internac)

Sheet Cuotas Regionales Crustaceos
B3: Estado de Cuotas Regionales Crustaceos Industriales LTP, 2016
B4: al 17-01-2017
B7: Unidad de Pesquería | C7: Zona | D7: Cuota Global (t) | E7: Cuota Período | I7: Desembarque (t) | J7: Saldo (t) | K7: % Consumido | L7: Fecha cierre
E8: Período | F8: autorizada | G8: Cesiones | H8: efectiva
B9: Camarón nailon II-VIII (D.Ex.945/15) | C9: II - III | D9: =F9+F10 -> 55 | E9: Enero - Julio | F9: 49 | H9: =+F9 -> 49 | I9: =+'Crustaceos LTP'!H52 -> 0 | J9: =+H9-I9 -> 49 | K9: =I9/H9 -> 0
E10: Octubre - Diciembre | F10: 6 | H10: =+F10+J9 -> 55 | I10: =+'Crustaceos LTP'!H53 -> 0.208 | J10: =+H10-I10 -> 54.792 | K10: =I10/H10 -> 0.0037818182
C11: IV | D11: =F11+F12 -> 500 | E11: Enero - Julio | F11: 450 | G11: =21.17+190.53-59.82+135 -> 286.88 | H11: =+F11+G11 -> 736.88 | I11: =+'Crustaceos LTP'!N52 -> 246.99 | J11: =+H11-I11 -> 489.89 | K11: =I11/H11 -> 0.33518348
E12: Octubre - Diciembre | F12: 50 | H12: =+F12+J11 -> 539.89 | I12: =+'Crustaceos LTP'!N53 -> 278.794 | J12: =+H12-I12 -> 261.096 | K12: =I12/H12 -> 0.51639038
C13: V | D13: =F13+F14 -> 730 | E13: Enero - Julio | F13: 657 | H13: =+F13 -> 657 | I13: =+'Crustaceos LTP'!T52 -> 388.778 | J13: =+H13-I13 -> 268.222 | K13: =I13/H13 -> 0.59174734
E14: Octubre - Diciembre | F14: 73 | H14: =+F14+J13 -> 341.222 | I14: =+'Crustaceos LTP'!T53 -> 231.861 | J14: =+H14-I14 -> 109.361 | K14: =I14/H14 -> 0.67950191
C15: VI | D15: =F15+F16 -> 1040 | E15: Enero - Julio | F15: 936 | H15: =+F15 -> 936 | I15: =+'Crustaceos LTP'!Z52 -> 473.386 | J15: =+H15-I15 -> 462.614 | K15: =I15/H15 -> 0.50575427
E16: Octubre - Diciembre | F16: 104 | H16: =+F16+J15 -> 566.614 | I16: =+'Crustaceos LTP'!Z53 -> 262.093 | J16: =+H16-I16 -> 304.521 | K16: =I16/H16 -> 0.46256005
C17: VII | D17: =F17+F18 -> 1040 | E17: Enero - Julio | F17: 936 | H17: =+F17 -> 936 | I17: =+'Crustaceos LTP'!AF52 -> 796.326 | J17: =+H17-I17 -> 139.674 | K17: =I17/H17 -> 0.85077564
E18: Octubre - Diciembre | F18: 104 | H18: =+F18+J17 -> 243.674 | I18: =+'Crustaceos LTP'!AF53 -> 210.232 | J18: =+H18-I18 -> 33.442 | K18: =I18/H18 -> 0.86275926
C19: VIII | D19: =F19+F20 -> 1041 | E19: Enero - Julio | F19: 936 | H19: =+F19 -> 936 | I19: =+'Crustaceos LTP'!AL52 -> 617.679 | J19: =+H19-I19 -> 318.321 | K19: =I19/H19 -> 0.65991346
E20: Octubre - Diciembre | F20: 105 | H20: =+F20+J19 -> 423.321 | I20: =+'Crustaceos LTP'!AL53 -> 349.328 | J20: =+H20-I20 -> 73.993 | K20: =I20/H20 -> 0.82520829
B22: Fraccionamiento | D22: Cuota Asignada | E22: Cesiones | F22: efectiva | G22: Desembarque (t) | H22: Saldo (t) | I22: % CONSUMO
B23: Pesca de Investigación | D23: 110 | G23: =+'Pesca de Investigación'!I28+'Pesca de Investigación'!I38+'Pesca de Investigación'!I48 -> 96.727 | I23: =+G23/D23 -> 0.87933636 | K23: =+H33-I33 -> -8.04
B24: Cuota Captura LTP (objetivo) | D24: =SUBTOTAL(9,D9:D20) -> 4406 | E24: =SUBTOTAL(9,G9:G20) -> 286.88 | F24: =+D24+E24 -> 4692.88 | G24: =SUBTOTAL(9,I9:I20) -> 3855.675 | H24: =+F24-G24 -> 837.205 | I24: =+G24/F24 -> 0.82160102 | J24: =+H33-I33 -> -8.04
B27: Unidad de Pesquería | C27: Zona | D27: Cuota Global (t) | E27: Cuota Período | I27: Desembarque (t) | J27: Saldo (t) | K27: % Consumido | L27: Fecha cierre
E28: Período | F28: autorizada | G28: Cesiones | H28: efectiva
B29: Langostino amarillo III-IV (D.Ex.945/15) | C29: III | D29: =+F29+F30 -> 164 | E29: Marzo - Agosto | F29: 148 | H29: =+F29 -> 148 | I29: =+'Crustaceos LTP'!H82 -> 23.91 | J29: =+H29-I29 -> 124.09 | K29: =I29/H29 -> 0.16155405
E30: Octubre - Diciembre | F30: 16 | H30: =+F30+J29 -> 140.09 | I30: =+'Crustaceos LTP'!H83 -> 31.89 | J30: =+H30-I30 -> 108.2 | K30: =I30/H30 -> 0.22763937
C31: IV | D31: =+F31+F32 -> 1318 | E31: Marzo - Agosto | F31: 1187 | G31: =60+179.7+153.2+50+4.5 -> 447.4 | H31: =+F31+G31 -> 1634.4 | I31: =+'Crustaceos LTP'!N82 -> 1283.641 | J31: =+H31-I31 -> 350.759 | K31: =I31/H31 -> 0.78538975 | L31: 42718
E32: Octubre - Diciembre | F32: 131 | H32: =+F32+J31 -> 481.759 | I32: =+'Crustaceos LTP'!N83 -> 489.799 | J32: =+H32-I32 -> -8.04 | K32: =I32/H32 -> 1.0166888
F33: =SUM(F31:F32) -> 1318 | G33: =+G31 -> 447.4 | H33: =+F33+G33 -> 1765.4 | I33: =+I31+I32 -> 1773.44 | J33: =+H33-I33 -> -8.04 | K33: =I33/H33 -> 1.0045542
B34: Fraccionamiento | D34: Cuota Asignada | E34: Cesiones | F34: efectiva | G34: Desembarque (t) | H34: Saldo (t) | I34: % CONSUMO
B35: Pesca de Investigación | D35: 50 | G35: =+'Pesca de Investigación'!I24+'Pesca de Investigación'!I34+'Pesca de Investigación'!I44 -> 35.004 | I35: =+G35/D35 -> 0.70008 | K35: =+G36/D36 -> 1.234305
B36: Cuota Captura LTP (objetivo) | D36: =SUBTOTAL(9,D29:D32) -> 1482 | E36: =SUBTOTAL(9,G29:G32) -> 447.4 | F36: =+D36+E36 -> 1929.4 | G36: =SUBTOTAL(9,I29:I32) -> 1829.24 | H36: =+F36-G36 -> 100.16 | I36: =+G36/F36 -> 0.94808749 | J36: =+F33:G33 -> #VALUE!
B39: Unidad de Pesquería | C39: Zona | D39: Cuota Global (t) | E39: Cuota Período | I39: Desembarque (t) | J39: Saldo (t) | K39: % Consumido | L39: Fecha cierre
E40: Período | F40: autorizada | G40: Cesiones | H40: efectiva
B41: Langostino colorado (D.Ex.945/15 y D.Ex. 147/16) | C41: II-III | D41: =+F41+F42 -> 49 | E41: Marzo - Agosto | F41: 44 | H41: =+F41 -> 44 | I41: =+'Crustaceos LTP'!H100 -> 0 | J41: =+H41-I41 -> 44 | K41: =I41/H41 -> 0
E42: Octubre - Diciembre | F42: 5 | H42: =+F42+J41 -> 49 | I42: =+'Crustaceos LTP'!H101 -> 19.306 | J42: =+H42-I42 -> 29.694 | K42: =I42/H42 -> 0.394
C43: IV | D43: =+F43+F44 -> 120 | E43: Marzo - Agosto | F43: 108 | G43: =79.99+50 -> 129.99 | H43: =+F43+G43 -> 237.99 | I43: =+'Crustaceos LTP'!N100 -> 214.266 | J43: =+H43-I43 -> 23.724 | K43: =I43/H43 -> 0.90031514
E44: Octubre - Diciembre | F44: 12 | H44: =+F44+J43 -> 35.724 | I44: =+'Crustaceos LTP'!N101 -> 23.058 | J44: =+H44-I44 -> 12.666 | K44: =I44/H44 -> 0.64544844
B46: Fraccionamiento | D46: Cuota Asignada | E46: Cesiones | F46: efectiva | G46: Desembarque (t) | H46: Saldo (t) | I46: % CONSUMO
B47: Pesca de Investigación | D47: 19 | G47: =+'Pesca de Investigación'!I26+'Pesca de Investigación'!I36+'Pesca de Investigación'!I46 -> 13.931 | I47: =+G47/D47 -> 0.73321053
B48: Cuota Captura LTP II a IV (objetivo) | D48: =SUBTOTAL(9,D41:D44) -> 169 | E48: =SUBTOTAL(9,G41:G44) -> 129.99 | F48: =+D48+E48 -> 298.99 | G48: =SUBTOTAL(9,I41:I44) -> 256.63 | H48: =+F48-G48 -> 42.36 | I48: =+G48/F48 -> 0.85832302
B52: Estado de Cuotas Cuotas Regionales Crustaceos Industriales, Licitados 2016
B56: Unidad de Pesquería | C56: Zona | D56: Cuota Global (t) | E56: Cuota Período | I56: Desembarque (t) | J56: Saldo (t) | K56: % Consumido | L56: Fecha cierre
E57: Período | F57: autorizada | G57: Cesiones | H57: efectiva
B58: Langostino amarillo Licitado (D.Ex.944/15) | C58: V-VI | D58: =+F58+F59 -> 1190 | E58: Marzo - Agosto | F58: 1071 | H58: =+F58 -> 1071 | I58: 1176.139 | J58: =+H58-I58 -> -105.139 | K58: =I58/H58 -> 1.098169 | L58: 42493
E59: Octubre - Diciembre | F59: 119 | H59: =F59+J58 -> 13.861 | I59: 9.998 | J59: =+H59-I59 -> 3.863 | K59: =I59/H59 -> 0.72130438 | L59: 42643
C60: VII-VIII | D60: =+F60+F61 -> 640 | E60: Marzo - Agosto | F60: 576 | H60: =+F60 -> 576 | I60: 427.062 | J60: =+H60-I60 -> 148.938 | K60: =I60/H60 -> 0.74142708
E61: Octubre - Diciembre | F61: 64 | H61: =F61+J60 -> 212.938 | I61: 172.174 | J61: =+H61-I61 -> 40.764 | K61: =I61/H61 -> 0.808564
D62: =SUM(D58:D61) -> 1830 | I62: =SUM(I58:I61) -> 1785.373 | J62: =+J59+J61 -> 44.627 | K62: =+I62/D62 -> 0.97561366
B64: Unidad de Pesquería | C64: Zona | D64: Cuota Global (t) | E64: Cuota Período | I64: Desembarque (t) | J64: Saldo (t) | K64: % Consumido | L64: Fecha cierre
E65: Período | F65: autorizada | G65: Cesiones | H65: efectiva
B66: Langostino colorado Licitado (D.Ex.944/15 y D.Ex. 148/16) | C66: V | D66: =+F66+F67 -> 770 | E66: Marzo - Agosto | F66: 693 | H66: =+F66 -> 693 | I66: 644.116 | J66: =+H66-I66 -> 48.884 | K66: =I66/H66 -> 0.92946032 | L66: 42526
E67: Octubre - Diciembre | F67: 77 | H67: =+F67+J66 -> 125.884 | I67: 35.261 | J67: =+H67-I67 -> 90.623 | K67: =I67/H67 -> 0.28010708
C68: VI | D68: =+F68+F69 -> 548 | E68: Marzo - Agosto | F68: 494 | H68: =+F68 -> 494 | I68: 590.024 | J68: =+H68-I68 -> -96.024 | K68: =I68/H68 -> 1.1943806 | L68: 42606
E69: Octubre - Diciembre | F69: 54 | H69: =+F69+J68 -> -42.024 | J69: =+H69-I69 -> -42.024 | K69: =I69/H69 -> 0 | L69: 42618
C70: VII | D70: =+F70+F71 -> 1400 | E70: Marzo - Agosto | F70: 1260 | H70: =+F70 -> 1260 | I70: 1166.321 | J70: =+H70-I70 -> 93.679 | K70: =I70/H70 -> 0.92565159
E71: Octubre - Diciembre | F71: 140 | H71: =+F71+J70 -> 233.679 | I71: 98.033 | J71: =+H71-I71 -> 135.646 | K71: =I71/H71 -> 0.41951994
C72: VIII | D72: =+F72+F73 -> 1900 | E72: Marzo - Agosto | F72: 1710 | H72: =+F72 -> 1710 | I72: 1557.737 | J72: =+H72-I72 -> 152.263 | K72: =I72/H72 -> 0.91095731 | L72: 42661
E73: Octubre - Diciembre | F73: 190 | H73: =+F73+J72 -> 342.263 | I73: 337.192 | J73: =+H73-I73 -> 5.071 | K73: =I73/H73 -> 0.98518391
D74: =SUM(D66:D73) -> 4618 | I74: =SUM(I66:I73) -> 4428.684 | J74: =+J67+J69+J71+J73 -> 189.316 | K74: =+I74/D74 -> 0.95900476

Sheet Cuotas Licitadas  
C2: Estado de Cuotas Industriales Licitadas, año 2016
C3: al 27-01-2017
C6: ESTADO CUOTA PERMISOS EXTRAORDINARIOS DE PESCA (PEP), LANGOSTINO AMARILLO V - VIII (D.Ex. N° 944/11.NOV.2015 (modificado por D. Ex. N° 148/15.MAR.2016)
C8: Resumen
C9: Fraccionamiento | D9: Cuota Asignada | E9: Desembarque (t) | F9: Saldo (t) | G9: % CONSUMO
C10: Cuota Global | D10: 1880 | E10: =+E11+E12+E13 -> 1819.225 | F10: =+D10-E10 -> 60.775 | G10: =+E10/D10 -> 0.96767287
C11: Pesca de Investigación | D11: 37 | E11: =+'Pesca de Investigación'!I25+'Pesca de Investigación'!I35+'Pesca de Investigación'!I45 -> 33.662 | F11: =+D11-E11 -> 3.338 | G11: =+E11/D11 -> 0.90978378
C12: Fauna acompañante | D12: 13 | E12: 0.19 | F12: =+D12-E12 -> 12.81 | G12: =+E12/D12 -> 0.014615385
C13: Cuota Captura licitada: | D13: =D10-(D11+D12) -> 1830 | E13: =+I39 -> 1785.373 | F13: =+D13-E13 -> 44.627 | G13: =+E13/D13 -> 0.97561366
C15: Armador | D15: % Licitado | E15: Cuota licitada (t) | F15: Transferencias | H15: Cuota efectiva (t) | I15: Operación
F16: Ingresos (t) | G16: Egresos (t) | I16: Desembarque (t) | J16: Saldo (t) | K16: % Consumo Licitada
C17: CAMANCHACA PESCA SUR | D17: 37.59 | E17: 687.897 | F17: 335.19896 | G17: 472.3096 | H17: 550.78636 | I17: 550.586 | J17: 0.200362 | K17: 0.99963623
C18: BLUMAR S.A. | D18: 18.39038 | E18: 336.54395 | F18: 0 | G18: 336.26814 | H18: 0.27580933 | I18: 0 | J18: 0.27580933 | K18: 0
C19: SUNRISE | D19: 0.5 | E19: 9.15 | F19: 0 | G19: 9.15 | H19: 0 | I19: 0 | J19: 0 | K19: 0
C20: BRACPESCA S.A. | D20: 21.63454 | E20: 395.91208 | F20: 0 | G20: 0 | H20: 395.91208 | I20: 394.195 | J20: 1.717082 | K20: 0.99566297
C21: ISLADAMAS S.A., PESQ. | D21: 10.51 | E21: 192.333 | F21: 163.3458 | G21: 0 | H21: 355.6788 | I21: 352.851 | J21: 2.8278 | K21: 0.99204957
C22: VELIZ Y VELIZ | D22: 0 | E22: 0 | F22: 0 | G22: 0 | H22: 0 | I22: 0 | J22: 0 | K22: 0
C23: DISTRIMAR | D23: 0 | E23: 0 | F23: 0 | G23: 0 | H23: 0 | I23: 0 | J23: 0 | K23: 0
C24: ANTARTIC SEAFOOD | D24: 7.442 | E24: 136.1886 | F24: 0 | G24: 0 | H24: 136.1886 | I24: 136.831 | J24: -0.6424 | K24: 1.004717 | L24: 111
C25: GRIMAR S.A. | D25: 1 | E25: 18.3 | F25: 0 | G25: 0 | H25: 18.3 | I25: 0 | J25: 18.3 | K25: 0
C26: RUBIO Y MAUAD LTDA. | D26: 1.95433 | E26: 35.764239 | F26: 0 | G26: 0 | H26: 35.764239 | I26: 35.577 | J26: 0.187239 | K26: 0.99476463
C27: MARIO MOROZIN YURECIC | D27: 0 | E27: 0 | F27: 0 | G27: 0 | H27: 0 | I27: 0 | J27: 0 | K27: 0
C28: SOC. PESQUERA QUINTERO LTDA. | D28: 0 | E28: 0 | F28: 0 | G28: 0 | H28: 0 | I28: 0 | J28: 0 | K28: 0
C29: PESQUERA QUINTERO S.A. | D29: 0.94 | E29: 17.202 | F29: 0 | G29: 0 | H29: 17.202 | I29: 1.554 | J29: 15.648 | K29: 0.090338333
C30: CONGELADOS PACIFICO S.A. | D30: 0 | E30: 0 | F30: 1.4288967 | G30: 0 | H30: 1.4288967 | I30: 0 | J30: 1.4288967 | K30: 0
C31: PESQUERA BIO BIO S.A. | D31: 0.01962 | E31: 0.359046 | F31: 0 | G31: 0.359046 | H31: 0 | I31: 0 | J31: 0 | K31: 0
C32: PESQUERA ANTONIO CRUZ CORDOVA NAKOUZI E.I.R.L. | D32: 0.01367 | E32: 0.250161 | F32: 0 | G32: 0 | H32: 0.250161 | I32: 0 | J32: 0.250161 | K32: 0
C33: PESQUERA ENFEMAR LTDA. | D33: 0.00546 | E33: 0.099918 | F33: 0 | G33: 0 | H33: 0.099918 | I33: 0 | J33: 0.099918 | K33: 0
C34: ANTONIO DA VENEZIA RETAMALES | D34: 0 | E34: 0 | F34: 0 | G34: 0 | H34: 0 | I34: 0 | J34: 0 | K34: 0
C35: JORGE COFRE REYES | D35: 0 | E35: 0 | F35: 152.402 | G35: 0 | H35: 152.402 | I35: 151.937 | J35: 0.465 | K35: 0.99694886
C36: PESQUERA CMK LTDA. | D36: 0 | E36: 0 | F36: 163.7118 | G36: 0 | H36: 163.7118 | I36: 161.842 | J36: 1.8698 | K36: 0.98857871
C37: PESQUERA LANDES S.A. | D37: 0 | E37: 0 | F37: 2 | G37: 0 | H37: 2 | I37: 0 | J37: 2 | K37: 0
C39: Total | D39: =SUM(D17:D37) -> 100 | E39: =SUM(E17:E37) -> 1830 | F39: =SUM(F17:F37) -> 818.08746 | G39: =SUM(G17:G37) -> 818.08679 | H39: =SUM(H17:H37) -> 1830.0007 | I39: =SUM(I17:I37) -> 1785.373 | J39: =SUM(J17:J37) -> 44.627668 | K39: =+I39/H39 -> 0.97561331
C43: ESTADO CUOTA PERMISOS EXTRAORDINARIOS DE PESCA (PEP),. LANGOSTINO COLORADO V - VIII (D.Ex. N° 944/11.NOV.2015 (modificado por D. Ex. N° 148/15.MAR.2016)
C45: Resumen
C46: Fraccionamiento | D46: Cuota Asignada | E46: Desembarque (t) | F46: Saldo Asignada (t) | G46: % CONSUMO
C47: Cuota Global: | D47: 4750 | E47: =SUM(E48:E50) -> 4494.248 | F47: =+D47-E47 -> 255.752 | G47: =+E47/D47 -> 0.94615747
C48: Pesca de Investigación | D48: 95 | E48: =+'Pesca de Investigación'!I27+'Pesca de Investigación'!I37+'Pesca de Investigación'!I47 -> 62.391 | F48: =+D48-E48 -> 32.609 | G48: =+E48/D48 -> 0.65674737
C49: Fauna acompañante | D49: 37 | E49: 3.173 | F49: =+D49-E49 -> 33.827 | G49: =+E49/D49 -> 0.085756757
C50: Cuota Objetivo: | D50: 4618 | E50: =+I78 -> 4428.684 | F50: =+D50-E50 -> 189.316 | G50: =+E50/D50 -> 0.95900476
C52: Armador | D52: % Licitado | E52: Cuota licitada (t) | F52: Transferencias | H52: Cuota efectiva (t) | I52: Operación
F53: Ingresos (t) | G53: Egresos (t) | I53: Desembarque (t) | J53: Saldo Efectivo(t) | K53: % Consumo Licitada
C54: CAMANCHACA PESCA SUR | D54: 66.3056 | E54: 3061.9926 | F54: 719.17392 | G54: 1359.7701 | H54: =E54+F54-G54 -> 2421.3964 | I54: 2417.373 | J54: 4.023431 | K54: 0.99833838
C55: BLUMAR S.A. | D55: 15.61794 | E55: 721.23647 | F55: 0 | G55: 720.75863 | H55: =E55+F55-G55 -> 0.4778372 | I55: 0 | J55: 0.4778372 | K55: 0
C56: SUNRISE | D56: 0.5 | E56: 23.09 | F56: 0 | G56: 23.09 | H56: =E56+F56-G56 -> 0 | I56: 0 | J56: 0 | K56: 0
C57: BRACPESCA | D57: 6.53885 | E57: 301.96409 | F57: 0 | G57: 0 | H57: =E57+F57-G57 -> 301.96409 | I57: 297.961 | J57: 4.003093 | K57: 0.98674315 | M57: =4618*0.0458 -> 211.5044
C58: ISLADAMAS S.A., PESQ. | D58: 3.039 | E58: 140.34102 | F58: 300.17 | G58: 0 | H58: =E58+F58-G58 -> 440.51102 | I58: 425.686 | J58: 14.82502 | K58: 0.96634586
C59: EMPACADORA DEL PACIFICO | D59: 0 | E59: 0 | F59: 0 | G59: 0 | H59: =E59+F59-G59 -> 0 | I59: 0 | J59: 0 | K59: 0
C60: DISTRIMAR | D60: 0 | E60: 0 | F60: 0 | G60: 0 | H60: =E60+F60-G60 -> 0 | I60: 0 | J60: 0 | K60: 0
C61: ANTARTIC SEAFOOD | D61: 4.61025 | E61: 212.90134 | F61: 0 | G61: 0 | H61: =E61+F61-G61 -> 212.90134 | I61: 205.791 | J61: 7.110345 | K61: 0.96660263
C62: ALIMAR | D62: 0.5 | E62: 23.09 | F62: 0 | G62: 0 | H62: =E62+F62-G62 -> 23.09 | I62: 0 | J62: 23.09 | K62: 0
C63: RUBIO Y MAUAD LTDA. | D63: 0.3015 | E63: 13.92327 | F63: 0 | G63: 0 | H63: =E63+F63-G63 -> 13.92327 | I63: 13.922 | J63: 0.00127 | K63: 0.99990879
C64: ARTIC S.A. ELAB | D64: 0 | E64: 0 | F64: 0 | G64: 0 | H64: =E64+F64-G64 -> 0 | I64: 0 | J64: 0 | K64: 0
C65: MARIO MOROZIN YURECIC | D65: 0 | E65: 0 | F65: 0 | G65: 0 | H65: =E65+F65-G65 -> 0 | I65: 0 | J65: 0 | K65: 0
C66: SOC. PESQUERA QUINTERO LTDA. | D66: 0 | E66: 0 | F66: 0 | G66: 0 | H66: =E66+F66-G66 -> 0 | I66: 0 | J66: 0 | K66: 0
C67: PESQUERA QUINTERO S.A. | D67: 0.06646 | E67: 3.0691228 | F67: 0 | G67: 0 | H67: =E67+F67-G67 -> 3.0691228 | I67: 0 | J67: 3.0691228 | K67: 0
C68: PESQUERA GRIMAR S.A. | D68: 0 | E68: 0 | F68: 0 | G68: 0 | H68: =E68+F68-G68 -> 0 | I68: 0 | J68: 0 | K68: 0
C69: CONGELADOS PACIFICO S.A. | D69: 0 | E69: 0 | F69: 1.9984821 | G69: 0 | H69: =E69+F69-G69 -> 1.9984821 | I69: 0 | J69: 1.9984821 | K69: 0
... C76: SOC. PESQUERA LANDES S.A. | D76: 0 | E76: 0 | F76: 2.0781 | G76: 0 | H76: =E76+F76-G76 -> 2.0781 | I76: 0 | J76: 2.0781 | K76: 0
C78: Total | D78: =SUM(D54:D76) -> 97.500003 | E78: =SUM(E54:E76) -> 4502.5501 | F78: =SUM(F54:F76) -> 2104.0325 | G78: =SUM(G54:G76) -> 2104.0325 | H78: =SUM(H54:H76) -> 4502.5501 | I78: =SUM(I54:I76) -> 4428.684 | J78: =SUM(J54:J76) -> 73.866139 | K78: =+I78/H78 -> 0.9835946
C81: ESTADO CUOTA PERMISOS EXTRAORDINARIOS DE PESCA (PEP), BACALAO DE PROFUNDIDAD 47° L.S. AL 57° L.S.D.
C83: Resumen
C84: Fraccionamiento | E84: Cuota Asignada | F84: Desembarque (t) | G84: Saldo (t) | H84: % CONSUMO Total Cuota
C85: Cuota Global: | E85: 1656 | F85: =SUM(F86:F87) -> 1615.093 | G85: =E85-F85 -> 40.907 | H85: =F85/E85 -> 0.97529771
C86: Pesca de Investigación: | E86: 20 | G86: =E86-F86 -> 20 | H86: =F86/E86 -> 0
C87: Cuota Objetivo: | E87: 1636 | F87: =+I116 -> 1615.093 | G87: =E87-F87 -> 20.907 | H87: =F87/E87 -> 0.98722066
B89: Tipo Titular | C89: Armador | D89: % Licitado | E89: Cuota licitada (t) | F89: Transferencias | H89: Cuota efectiva (t) | I89: Operación
F90: Ingresos (t) | G90: Egresos (t) | I90: Desembarque (t) | J90: Saldo efectivo (t) | K90: % Consumo Licitada
B91: Industrial | C91: BLUE OCEAN SEAFOOD | D91: 0 | E91: 0 | F91: 0 | G91: 0 | H91: 0 | I91: 0 | J91: 0 | K91: 0
C92: DERIS S A | D92: 21.995 | E92: 359.8382 | F92: 0 | G92: 0 | H92: 359.8382 | I92: 355.493 | J92: 4.3452 | K92: =+I92/H92 -> 0.98792457
C93: GLOBALPESCA S A | D93: 42.02047 | E93: 687.45489 | H93: 687.45489 | I93: 687.455 | J93: -0.0001108 | K93: =+I93/H93 -> 1.0000002
C94: PESCA CISNE S A | D94: 15.984523 | E94: 261.5068 | H94: 261.5068 | I94: 259.489 | J94: 2.0177996 | K94: =+I94/H94 -> 0.99228395
B95: Artesanal | C95: ADRIANA DEL PILAR POBLETE ARAVENA | D95: 1.5 | E95: 24.54 | F95: 0 | G95: 8.18 | H95: 16.36 | I95: 15.487 | J95: 0.873 | K95: =+I95/H95 -> 0.94663814
C96: BERNARDO CEBALLOS MANCILLA | D96: 1 | E96: 16.36 | F96: 4 | G96: 0 | H96: 20.36 | I96: 20.326 | J96: 0.034 | K96: =+I96/H96 -> 0.99833006
C97: BOLIVAR GUZMAN ACUÑA | D97: 1.5 | E97: 24.54 | F97: 0 | G97: 16.969 | H97: 7.571 | I97: 7.571 | J97: 0 | K97: =+I97/H97 -> 1
C98: DANIEL ALBERTO MOLINA CISTERNAS | D98: 3.5 | E98: 57.26 | F98: 0.327 | G98: 0 | H98: 57.587 | I98: 57.492 | J98: 0.095 | K98: =+I98/H98 -> 0.99835032
C99: DAVID ALFONSO CISTERNA GARRIDO | D99: 0.5 | E99: 8.18 | F99: 0 | G99: 0 | H99: 8.18 | I99: 8.175 | J99: 0.005 | K99: =+I99/H99 -> 0.99938875
C100: ELSA DEL ROSARIO NEIRA PARRA | D100: 0 | E100: 0 | F100: 4.85 | G100: 0 | H100: 4.85 | I100: 4.846 | J100: 0.004 | K100: =+I100/H100 -> 0.99917526
C101: ISABEL MARGARITA MARQUEZ MOLINA | D101: 0.5 | E101: 8.18 | F101: 0 | G101: 8.18 | H101: 0 | I101: 0 | J101: 0 | K101: 1
C102: JOSE ACEVEDO CORNEJO | D102: 0.5 | E102: 8.18 | F102: 0 | G102: 0.327 | H102: 7.853 | I102: 7.853 | J102: 0 | K102: =+I102/H102 -> 1
C103: JOSE ARMANDO MORA MOYA | D103: 0 | E103: 0 | F103: 40.9 | G103: 0.587 | H103: 40.313 | I103: 40.15 | J103: 0.163 | K103: =+I103/H103 -> 0.99595664
C104: JUAN JOSE GUZMAN ROJAS | D104: 1 | E104: 16.36 | F104: 16.969 | G104: 1.307 | H104: 32.022 | I104: 32.022 | J104: 0 | K104: =+I104/H104 -> 1
C105: LUIS ALFREDO JARAMILLO MERIÑO | D105: 0 | E105: 0 | F105: 8.18 | G105: 0 | H105: 8.18 | I105: 7.269 | J105: 0.911 | K105: =+I105/H105 -> 0.88863081
C106: LUIS ARMANDO POBLETE FERNANDEZ | D106: 0.5 | E106: 8.18 | F106: 0.8 | G106: 0 | H106: 8.98 | I106: 9.021 | J106: -0.041 | K106: =+I106/H106 -> 1.0045657 | M106: al parecer faltaria un ne3gocio traslaticio
C107: MIGUEL SERVANDO SILVA SILVA | D107: 0 | E107: 0 | F107: 7.495 | G107: 0 | H107: 7.495 | I107: 6.567 | J107: 0.928 | K107: =+I107/H107 -> 0.87618412
C108: PAOLA MORA BURGOS | D108: 2.5 | E108: 40.9 | F108: 0 | G108: 40.9 | H108: 0 | I108: 0 | J108: 0 | K108: 1
C109: PESQUERA FRAPOLI LTDA | D109: 1 | E109: 16.36 | F109: 0 | G109: 0 | H109: 16.36 | I109: 15.695 | J109: 0.665 | K109: =+I109/H109 -> 0.95935208
C110: PESQUERA SIGLO XXI LTDA | D110: 0 | E110: 0 | F110: 4.18 | G110: 0 | H110: 4.18 | I110: 0.441 | J110: 3.739 | K110: =+I110/H110 -> 0.10550239
C111: RAUL GONZALEZ HURTADO | D111: 1 | E111: 16.36 | F111: 1.894 | G111: 0 | H111: 18.254 | I111: 18.254 | J111: 0 | K111: =+I111/H111 -> 1
C112: ROBERTO MARCELO GONZALEZ NAVARRO | D112: 2.5 | E112: 40.9 | F112: 0 | G112: 0 | H112: 40.9 | I112: 37.773 | J112: 3.127 | K112: =+I112/H112 -> 0.92354523
C113: SERGIO FERNANDEZ VERGARA | D113: 0.5 | E113: 8.18 | F113: 0 | G113: 0 | H113: 8.18 | I113: 7.821 | J113: 0.359 | K113: =+I113/H113 -> 0.95611247
C114: TOMAS NEIRA PARRA | D114: 1 | E114: 16.36 | F114: 0 | G114: 13.145 | H114: 3.215 | I114: 3.215 | J114: 0 | K114: =+I114/H114 -> 1
C115: VERONICA IVON CAMPOS GUTIERREZ | D115: 1 | E115: 16.36 | F115: 0 | G115: 0 | H115: 16.36 | I115: 12.678 | J115: 3.682 | K115: =+I115/H115 -> 0.77493888
B116: Total | D116: =SUM(D91:D115) -> 99.999993 | E116: =SUM(E91:E115) -> 1635.9999 | F116: =SUM(F91:F115) -> 89.595 | G116: =SUM(G91:G115) -> 89.595 | H116: =SUM(H91:H115) -> 1635.9999 | I116: =SUM(I91:I115) -> 1615.093 | J116: =SUM(J91:J115) -> 20.906889 | K116: =+I116/H116 -> 0.98722073
B118: Capturas Bacalao 47° L.S. AL 57° por zonas y Región de Desembarque:
B119: Area Licitada | C119: Regiión de Desembarque | H119: Total (Ton)
C120: VIII | D120: X | E120: XI | F120: XII | G120: XIV
B121: 119 | C121: 27.505 | D121: 108.605 | E121: 6.786 | F121: 66.235 | G121: 46.262 | H121: =SUM(C121:G121) -> 255.393
B122: 120 | C122: 2.92 | D122: 64.881 | E122: 0.342 | F122: 1237.376 | G122: 54.181 | H122: =SUM(C122:G122) -> 1359.7
B123: Total general | C123: =SUM(C121:C122) -> 30.425 | D123: =SUM(D121:D122) -> 173.486 | E123: =SUM(E121:E122) -> 7.128 | F123: =SUM(F121:F122) -> 1303.611 | G123: =SUM(G121:G122) -> 100.443 | H123: =SUM(H121:H122) -> 1615.093
...

Sheet Pesca de Investigación
B2: Cuotas Pesca de Investigacion, 2016
B3: actualizado al 27-01-2017
B5: Pesca de Investigacion: Resolucion Nº 37. Desde 12-01-2016 hasta 30-04-2016 | M5: Naves Autorizadas | N5: Tipo Flota | O5: Armador
B6: Res. N°/Fecha | C6: Encargado | D6: Proyecto | E6: Especies | F6: Arte | G6: Zona | H6: Cuota PI (ton) | I6: Desembarque (ton) | J6: Saldo (ton) | L6: VIII | M6: TURIMAR II | N6: Artesanal
B7: 37/12-01-2016 | C7: IFOP | D7: MONITOREO DEL PROCESO DE RECLUTAMIENTO DE SARDINA COMUN Y ANCHOVETA DE LA V, VIII, IX Y XIV REGIONES, AÑO 2016 | E7: SARDINA COMUN | F7: CERCO | G7: V-VII-IX-XIV | H7: 14 | I7: 0.46 | J7: =+H7-I7 -> 13.54 | M7: MARCO POLO | N7: Artesanal
M8: DON LUIS ALBERTO | N8: Artesanal
E9: ANCHOVETA | F9: CERCO | G9: V-VII-IX-XIV | H9: 10.5 | I9: 0.436 | J9: =+H9-I9 -> 10.064 | M9: LONQUIMAY | N9: Artesanal
L10: V | M10: NORTHWESTERN | N10: Artesanal | O10: RES. 110 MODIF. RES. 37
L11: IX | M11: LINARES | N11: Artesanal | O11: RES. 110 MODIF. RES. 38
L12: XIV | M12: PUNTA BRAVA | N12: Artesanal | O12: RES. 110 MODIF. RES. 39
B14: Pesca de Investigacion: Resolucion Nº 1336. Desde 02-05-2016 hasta 20-05-2016
B15: Res. N°/Fecha | C15: Encargado | D15: Proyecto | E15: Especies | F15: ARTE | G15: Zona | H15: Cuota PI (ton) | I15: Desembarque (ton) | J15: Saldo (ton) | K15: % Consumo | N15: Naves Autorizadas | O15: Tipo Flota | P15: Armador
B16: 1336/02-05-2016 | C16: IFOP | D16: EVALUACION HIDROACUSTICA DE LOS STOCKS DE ANCHOVETA Y SARDINA COMUN ENTRE LA V Y X REGIONES, AÑO 2016 | E16: SARDINA COMUN | F16: - | G16: IX-XIV | H16: 3 | J16: =H16-I16 -> 3 | K16: =+I16/H16 -> 0 | M16: Naves titulares | N16: L/M PUNTA BRAVA | O16: Artesanal
F17: - | G17: V-X | H17: 20 | J17: =H17-I17 -> 20 | K17: =+I17/H17 -> 0 | N17: B/I ABATE MOLINA | O17: Investigacion
E18: ANCHOVETA | F18: - | G18: IX-XIV | H18: 3 | J18: =H18-I18 -> 3 | K18: =+I18/H18 -> 0
F19: - | G19: V-X | H19: 15 | J19: =H19-I19 -> 15 | K19: =+I19/H19 -> 0
B22: Pesca de Investigacion: Resolucion Nº 1322. Desde 02-05-2016 hasta 31-08-2016 IMPUTA A D.EX. 945
B23: Res. N°/Fecha | C23: Encargado | D23: Proyecto | E23: Especies | F23: Arte | G23: Zona | H23: Cuota PI (ton) | I23: Desembarque (ton) | J23: Saldo (ton) | K23: % Consumo | N23: Naves Autorizadas | O23: Tipo Flota | P23: Armador
B24: 1322/02-05-2016 | C24: Universidad Católica de Vapparaíso | D24: EVALUACION DIRECTA DE LANGOSTINO AMARILLO Y LANGOSTINO COLORADO ENTRE LA II Y VIII REGIONES, AÑO 2016 | E24: Langostino amarillo (objetivo) | F24: Arrastre de fondo | G24: III-IV | H24: 30 | I24: =28.94 -> 28.94 | J24: =H24-I24 -> 1.06 | K24: =+I24/H24 -> 0.96466667 | M24: Naves titulares | N24: Trauwun I | O24: Artesanal | P24: Eric Aravena Aravena
F25: Arrastre de fondo | G25: V-VIII | H25: 25 | I25: 24.256 | J25: =H25-I25 -> 0.744 | K25: =+I25/H25 -> 0.97024 | N25: Don Estefan | O25: Industrial | P25: Pesquera Quintero S.A.
E26: Langostino colorado (Objetivo) | F26: Arrastre de fondo | G26: XV-IV | H26: 16 | I26: 13.867 | J26: =H26-I26 -> 2.133 | K26: =+I26/H26 -> 0.8666875 | N26: Altair I | O26: Industrial | P26: Camanchaca Pesca Sur S.A
F27: Arrastre de fondo | G27: V-VIII | H27: 40 | I27: 38.692 | J27: =H27-I27 -> 1.308 | K27: =+I27/H27 -> 0.9673 | M27: Naves suplentes | N27: Isla Picton | O27: Industrial | P27: Antartic Seafood S.A.
E28: Camaron nailón (Fauna Acompañante) | F28: Arrastre de fondo | G28: II-VIII | H28: 25 | I28: =17.443+4.392 -> 21.835 | J28: =H28-I28 -> 3.165 | K28: =+I28/H28 -> 0.8734 | N28: Eldom | O28: Industrial | P28: Pesquera Quintero S.A.
E29: Merluza Común (Fauna Acompañante) | F29: Arrastre de fondo | G29: IV-VIII | H29: 10 | I29: =3.838+1.402 -> 5.24 | J29: =H29-I29 -> 4.76 | K29: =+I29/H29 -> 0.524 | N29: Nuestra Sr.a de la Tirana II | O29: Industrial | P29: Camanchaca Pesca Sur S.A
B32: Pesca de Investigacion: Resolucion Nº 1759. Desde 06-06-2016 hasta 31-12-2016. IMPUTA A D.EX. 945 Y 944 | M32: Naves Autorizadas
B33: Res. N°/Fecha | C33: Encargado | D33: Proyecto | E33: Especies | F33: Arte | G33: Zona | H33: Cuota PI (ton) | I33: Desembarque (ton) | J33: Saldo (ton) | K33: % Consumo
B34: 1759/06-06-2016 | C34: Cimar | D34: Res. Ex. N° 1759-2016 Evaluación directa de Camarón nailon II-VIII Regiones. | E34: Langostino amarillo (objetivo) | F34: Arrastre de fondo | G34: III-IV | H34: 10 | I34: 6.064 | J34: =H34-I34 -> 3.936 | K34: =+I34/H34 -> 0.6064
F35: Arrastre de fondo | G35: V-VIII | H35: 10 | I35: 8.382 | J35: =H35-I35 -> 1.618 | K35: =+I35/H35 -> 0.8382
E36: Langostino colorado (Objetivo) | F36: Arrastre de fondo | G36: XV-IV | H36: 2 | I36: 0.032 | J36: =H36-I36 -> 1.968 | K36: =+I36/H36 -> 0.016
F37: Arrastre de fondo | G37: V-VIII | H37: 20 | I37: =19.684+0.017+0.022 -> 19.723 | J37: =H37-I37 -> 0.277 | K37: =+I37/H37 -> 0.98615
E38: Camaron nailón (Fauna Acompañante) | F38: Arrastre de fondo | G38: II-VIII | H38: 75 | I38: =69.002+0.235 -> 69.237 | J38: =H38-I38 -> 5.763 | K38: =+I38/H38 -> 0.92316
E39: Merluza Común (Fauna Acompañante) | F39: Arrastre de fondo | G39: IV-VIII | H39: 10 | I39: 7.611 | J39: =H39-I39 -> 2.389 | K39: =+I39/H39 -> 0.7611
B42: Pesca de Investigacion: Resolucion Nº 2213. Desde 04-08-2016 hasta 31-12-2016. IMPUTA A D.EX. 945-944-1186
B43: Res. N°/Fecha | C43: FECHA DIARIO OFICIAL | D43: Encargado/Proyecto | E43: Especies | F43: Arte | G43: Zona | H43: Cuota PI (ton) | I43: Desembarque (ton) | J43: Saldo (ton) | K43: % Consumo
B44: 2213/15-07-2016 | C44: 42586 | D44: UNIVERSIDAD CATOLICA DE VALPARAISO - Pesca Industrial - Autoriza, Aprueba, Acoge o Reconoce--Pesca Industrial-Autorizaciones Especiales-Pesca Investigaci?n-ANALISIS COMPARATIVO DE LA CAPTURABILIDAD Y SELECTIVIDAD DE REDES DE ARRASTRE EN PESQUERIAS DE CRUSTACEOS DEMERSALES | E44: Langostino amarillo (objetivo) | F44: Arrastre de fondo | G44: III-IV | H44: 5 | J44: =H44-I44 -> 5 | K44: =+I44/H44 -> 0
F45: Arrastre de fondo | G45: V-VIII | H45: 1 | I45: 1.024 | J45: =H45-I45 -> -0.024 | K45: =+I45/H45 -> 1.024
E46: Langostino colorado (Objetivo) | F46: Arrastre de fondo | G46: XV-IV | H46: 1 | I46: 0.032 | J46: =H46-I46 -> 0.968 | K46: =+I46/H46 -> 0.032
F47: Arrastre de fondo | G47: V-VIII | H47: 4 | I47: 3.976 | J47: =H47-I47 -> 0.024 | K47: =+I47/H47 -> 0.994
E48: Camaron nailón (Fauna Acompañante) | F48: Arrastre de fondo | G48: II-VIII | H48: 9 | I48: 5.655 | J48: =H48-I48 -> 3.345 | K48: =+I48/H48 -> 0.62833333
E49: Merluza Común (Fauna Acompañante) | F49: Arrastre de fondo | G49: IV-VIII | H49: 1 | J49: =H49-I49 -> 1 | K49: =+I49/H49 -> 0

Sheet Cuota Bacalao XV-47° L.S
B2: Cuota Anual de Captura para la pesquerías Bacalao de profundidad XV-47° L.S., año 2016
B3: actualizado al 27-01-2017
B6: Unidad de Pesquería | C6: Fraccionamiento | D6: Período | E6: Cuota asignada (t) | F6: Cuota Efectiva (t) | G6: Captura (t) | H6: Saldo (t) | I6: % CONSUMO | J6: Fecha de Cierre | K6: Cuota Anual | L6: Capturas 2016 | M6: Saldo | N6: % Consumido
B7: Bacalao de profundidad XV hasta paralelo 47º LS D ex. N°946-15. | C7: Investigación | D7: Ene-Dic | E7: 8 | F7: =E7 -> 8 | H7: =F7-G7 -> 8 | I7: =G7/F7 -> 0
C8: Cuota Objetivo | D8: Feb-May | E8: 741 | F8: =E8 -> 741 | G8: =+O38 -> 789.096 | H8: =F8-G8 -> -48.096 | I8: =+G8/F8 -> 1.0649069 | J8: 42452 | K8: =E8+E9 -> 1483 | L8: =G8+G9 -> 1525.763 | M8: =K8-L8 -> -42.763 | N8: =L8/K8 -> 1.0288355
D9: Sep-Dic | E9: 742 | F9: =+E9+H8 -> 693.904 | G9: =+O72 -> 736.667 | H9: =F9-G9 -> -42.763 | I9: =+G9/F9 -> 1.0616267 | J9: 42642
B12: Desembarque Bacalao de Profundidad por zonas de capturas y Región desembarque de la XV al 47°L.S. periodo Feb-May Año 2016
B15: Región Operación | C15: Zona Captura | D15: REGION DESEMBARQUE | O15: Total general
D16: I | E16: II | F16: III | G16: IV | H16: V | I16: VII | J16: VIII | K16: X | L16: XIV | M16: XI | N16: XV
B17: I | C17: 102 | D17: 7.305 | O17: =SUM(D17:N17) -> 7.305
C18: 103 | D18: 4.608 | O18: =SUM(D18:N18) -> 4.608
B19: II | C19: 104 | D19: 13.615 | E19: 2.634 | O19: =SUM(D19:N19) -> 16.249
C20: 105 | D20: 0.91 | E20: 6.262 | F20: 2.141 | O20: =SUM(D20:N20) -> 9.313
C21: 106 | D21: 0.184 | F21: 4.603 | O21: =SUM(D21:N21) -> 4.787
B22: III | C22: 107 | F22: 11.416 | O22: =SUM(D22:N22) -> 11.416
C23: 108 | F23: 6.074 | O23: =SUM(D23:N23) -> 6.074
B24: IV | C24: 109 | F24: 0.25 | G24: 9.751 | O24: =SUM(D24:N24) -> 10.001
C25: 110 | G25: 3.682 | H25: 12.855 | I25: 0.2 | O25: =SUM(D25:N25) -> 16.737
B26: V | C26: 111 | H26: 25.191 | I26: 1.333 | O26: =SUM(D26:N26) -> 26.524
B27: VI | C27: 112 | H27: 5.424 | I27: 6.631 | O27: =SUM(D27:N27) -> 12.055
B28: VII | C28: 113 | I28: 26.479 | J28: 1.447 | O28: =SUM(D28:N28) -> 27.926
B29: VIII | C29: 114 | H29: 1.175 | I29: 0.783 | J29: 79.954 | L29: 0.269 | O29: =SUM(D29:N29) -> 82.181
B30: IX | C30: 115 | I30: 0.428 | J30: 11.626 | L30: 1.241 | O30: =SUM(D30:N30) -> 13.295
B31: X | C31: 117 | J31: 37.753 | K31: 97.041 | L31: 42.608 | O31: =SUM(D31:N31) -> 177.402
B32: XI | C32: 118 | J32: 20.246 | K32: 224.067 | L32: 20.965 | M32: 0.31 | O32: =SUM(D32:N32) -> 265.588
B33: XIV | C33: 116 | J33: 10.593 | K33: 5.671 | L33: 50.254 | O33: =SUM(D33:N33) -> 66.518
C34: 161 | L34: 17.654 | O34: =SUM(D34:N34) -> 17.654
C35: 163 | J35: 0.416 | K35: 4.599 | O35: =SUM(D35:N35) -> 5.015
B36: XV | C36: 101 | D36: 0.996 | N36: 5.609 | O36: =SUM(D36:N36) -> 6.605
C37: 140 | N37: 1.843 | O37: =SUM(D37:N37) -> 1.843
B38: Total general | D38: =SUM(D17:D37) -> 27.618 | E38: =SUM(E17:E37) -> 8.896 | F38: =SUM(F17:F37) -> 24.484 | G38: =SUM(G17:G37) -> 13.433 | H38: =SUM(H17:H37) -> 44.645 | I38: =SUM(I17:I37) -> 35.854 | J38: =SUM(J17:J37) -> 162.035 | K38: =SUM(K17:K37) -> 331.378 | ... O38: =SUM(O17:O37) -> 789.096
B42: Desembarque Bacalao de Profundidad por zonas de capturas y desembarque de la XV al 47°L.S. periodo Sep-Dic Año 2016
B46: Región Operación | C46: Zona Captura | D46: REGION DESEMBARQUE | O46: Total general
D47: I | E47: II | F47: III | G47: IV | H47: V | I47: VII | J47: VIII | K47: X | L47: XI | M47: XIV | N47: XV
B48: I | C48: 102 | D48: 10.096 | N48: 1.067 | O48: =SUM(D48:N48) -> 11.163
C49: 103 | D49: 4.129 | O49: =SUM(D49:N49) -> 4.129
B50: II | C50: 104 | D50: 10.76 | E50: 0.389 | O50: =SUM(D50:N50) -> 11.149
C51: 105 | E51: 10.889 | F51: 7.88 | G51: 1.364 | O51: =SUM(D51:N51) -> 20.133
C52: 106 | E52: 0.612 | F52: 12.467 | O52: =SUM(D52:N52) -> 13.079
B53: III | C53: 107 | F53: 8.143 | O53: =SUM(D53:N53) -> 8.143
C54: 108 | F54: 9.95 | O54: =SUM(D54:N54) -> 9.95
B55: IV | C55: 109 | G55: 0.88 | O55: =SUM(D55:N55) -> 0.88
C56: 110 | H56: 5.253 | I56: 0.611 | O56: =SUM(D56:N56) -> 5.864
B57: V | C57: 111 | H57: 18.92 | I57: 0.999 | O57: =SUM(D57:N57) -> 19.919
B58: VI | C58: 112 | H58: 3.005 | I58: 9.12 | O58: =SUM(D58:N58) -> 12.125
B59: VII | C59: 113 | I59: 23.967 | J59: 11.452 | O59: =SUM(D59:N59) -> 35.419
C60: 152 | J60: 1.093 | O60: =SUM(D60:N60) -> 1.093
B61: VIII | C61: 114 | I61: 3.12 | J61: 80.784 | M61: 5.859 | O61: =SUM(D61:N61) -> 89.763
B62: IX | C62: 115 | J62: 7.868 | M62: 6.267 | O62: =SUM(D62:N62) -> 14.135
B63: X | C63: 117 | J63: 36.485 | K63: 101.537 | M63: 28.939 | O63: =SUM(D63:N63) -> 166.961
C64: 121 | K64: 0.017 | O64: =SUM(D64:N64) -> 0.017
C65: 162 | J65: 4.552 | K65: 8.489 | O65: =SUM(D65:N65) -> 13.041
B66: XI | C66: 118 | J66: 13.001 | K66: 192.073 | M66: 6.184 | O66: =SUM(D66:N66) -> 211.258
C67: 122 | J67: 2.92 | L67: 0.2 | O67: =SUM(D67:N67) -> 3.12
C68: 116 | J68: 0.684 | O68: =SUM(D68:N68) -> 0.684
B69: XIV | C69: 161 | J69: 3.996 | K69: 6.568 | M69: 62.815 | O69: =SUM(D69:N69) -> 73.379
B70: XV | C70: 101 | D70: 1.322 | N70: 8.423 | O70: =SUM(D70:N70) -> 9.745
C71: 140 | N71: 1.518 | O71: =SUM(D71:N71) -> 1.518
B72: Total general | D72: =SUM(D48:D71) -> 26.307 | E72: 11.89 | F72: 38.44 | G72: 2.244 | H72: 27.178 | I72: 37.817 | J72: =SUM(J48:J71) -> 162.835 | K72: =SUM(K48:K71) -> 308.684 | L72: 0.2 | M72: 110.064 | N72: 11.008 | O72: =SUM(O48:O71) -> 736.667

Sheet Cuota Jibia
A2: Cuotas Anual de Captura para la pesquería Jibia XV-XII, AÑO 2016.
A3: D Ex. N° 1176-15; modificado por D Ex. N° 20-2016 y DTO EX. 559 DE 20-07-2016
A4: actualizado al 27-01-2017
A7: Unidad de Pesquería | B7: Fraccionamiento | C7: Período | D7: Cuota asignada (t) | E7: Cuota Efectiva (t) | F7: Captura (t) | G7: Saldo (t) | H7: % CONSUMO | I7: Fecha de Cierre | J7: Apertura | K7: Fecha de Cierre2
A8: Jibia o calamar rojo XV-XII D Ex. N` 1176-15. Mod por D. Ex N°20-16 y DTO EX. 559 DE 20-07-2016 | B8: Investigación | C8: Ene-Dic | D8: 1000 | E8: =D8 -> 1000 | F8: 0 | G8: =D8-F8 -> 1000 | H8: =F8/E8 -> 0
B9: Imprevistos | C9: Ene-Dic | D9: 2000 | E9: =D9 -> 2000 | F9: 0 | G9: =D9-F9 -> 2000 | H9: =F9/E9 -> 0
B10: F. Acompañante Artesanal | C10: Ene-Dic | D10: 1576 | E10: =D10 -> 1576 | F10: 0 | G10: =D10-F10 -> 1576 | H10: =F10/E10 -> 0
B11: Cuota Objetivo Artesanal | C11: Ene-Dic | D11: 156024 | E11: =D11 -> 156024 | F11: 144128.73 | G11: =D11-F11 -> 11895.275 | H11: =F11/E11 -> 0.92375997
B12: Cuota Objetivo Industrial | C12: Ene | D12: 4916 | E12: =D12 -> 4916 | F12: 5116.718 | G12: =E12-F12 -> -200.718 | H12: =F12/E12 -> 1.0408295 | I12: 42382 | J12: 42388 | K12: 42394 | L12: =+F12/13 -> 393.59369 | M12: enero
C13: Feb | D13: 4912 | E13: =D13+G12 -> 4711.282 | F13: 4665.934 | G13: =E13-F13 -> 45.348 | H13: =F13/E13 -> 0.99037459 | I13: 42413 | L13: =+F13/13 -> 358.918 | M13: febrero
C14: Mar | D14: 4912 | E14: =D14+G13 -> 4957.348 | F14: 5209.027 | G14: =E14-F14 -> -251.679 | H14: =F14/E14 -> 1.0507689 | I14: 42440 | L14: =+F14/11 -> 473.54791 | M14: marzo
C15: Abr | D15: 4912 | E15: =D15+G14 -> 4660.321 | F15: 4986.079 | G15: =E15-F15 -> -325.758 | H15: =F15/E15 -> 1.0699003 | I15: 42472 | L15: =+F15/12 -> 415.50658 | M15: abril
C16: May | D16: 4912 | E16: =D16+G15 -> 4586.242 | F16: 5205.342 | G16: =E16-F16 -> -619.1 | H16: =F16/E16 -> 1.1349907 | I16: 42500 | L16: =+F16/10 -> 520.5342 | M16: mayo
C17: Jun | D17: 4912 | E17: =D17+G16 -> 4292.9 | F17: 5027.972 | G17: =E17-F17 -> -735.072 | H17: =F17/E17 -> 1.1712297 | I17: 42529 | L17: =+F17/8 -> 628.4965 | M17: junio
C18: Jul | D18: 4912 | E18: =D18+G17 -> 4176.928 | F18: 4757.769 | G18: =E18-F18 -> -580.841 | H18: =F18/E18 -> 1.1390594 | I18: 42571 | L18: =+F18/20 -> 237.88845 | M18: julio
C19: Ago | D19: 4958 | E19: =D19+G18 -> 4377.159 | F19: 4362.24 | G19: =E19-F19 -> 14.919 | H19: =F19/E19 -> 0.99659162 | I19: 42591 | L19: =+F19/9 -> 484.69333 | M19: agosto
C20: Sep | D20: 1 | E20: =D20+G19 -> 15.919 | G20: =E20-F20 -> 15.919 | H20: =F20/E20 -> 0 | I20: 42613
C21: Oct | D21: 1 | E21: =D21+G20 -> 16.919 | G21: =E21-F21 -> 16.919 | H21: =F21/E21 -> 0
C22: Nov | D22: 1 | E22: =D22+G21 -> 17.919 | G22: =E22-F22 -> 17.919 | H22: =F22/E22 -> 0
C23: Dic | D23: 1 | E23: =D23+G22 -> 18.919 | G23: =E23-F23 -> 18.919 | H23: =F23/E23 -> 0
B24: Reserva Fauna Acompañante | C24: agosto-dic | D24: 50 | E24: 50 | F24: =4.81+0.006+0.011 -> 4.827 | G24: =E24-F24 -> 45.173 | H24: =F24/E24 -> 0.09654
B27: Operación Jibia Industrial AÑO 2016
D29: REGION DESEMBARQUE | I29: Total (Ton)
B30: Región Operación | C30: Cd_Zona | D30: I | E30: V | F30: VIII | G30: XI | H30: XII
B31: I | C31: 102 | D31: 0.544 | I31: =SUM(D31:H31) -> 0.544
B32: I | C32: 141 | D32: 2.113 | I32: =SUM(D32:H32) -> 2.113
B33: IV | C33: 110 | E33: 0.064 | F33: 0.638 | I33: =SUM(D33:H33) -> 0.702
B34: IX | C34: 115 | F34: 251.074 | I34: =SUM(D34:H34) -> 251.074
B35: IX | C35: 154 | F35: 1.636 | I35: =SUM(D35:H35) -> 1.636
B36: V | C36: 111 | E36: =26.823+0.011 -> 26.834 | F36: 35.316 | I36: =SUM(D36:H36) -> 62.15
B37: VI | C37: 112 | E37: 0.041 | F37: 7.448 | I37: =SUM(D37:H37) -> 7.489
B38: VI | C38: 151 | F38: 1.59 | I38: =SUM(D38:H38) -> 1.59
B39: VII | C39: 113 | E39: 0.025 | F39: 380.085 | I39: =SUM(D39:H39) -> 380.11
B40: VIII | C40: 114 | E40: 5.263 | F40: 38618.288 | I40: =SUM(D40:H40) -> 38623.551
B41: VIII | C41: 153 | F41: 2.947 | I41: =SUM(D41:H41) -> 2.947
B42: X | C42: 156 | F42: 0.16 | I42: =SUM(D42:H42) -> 0.16
B43: X | C43: 162 | F43: 0.399 | I43: =SUM(D43:H43) -> 0.399
B44: X | C44: 164 | F44: 0.267 | I44: =SUM(D44:H44) -> 0.267
B45: XI | C45: 118 | F45: 0.006 | G45: 0.094 | H45: 0.009 | I45: =SUM(D45:H45) -> 0.109
B46: XI | C46: 119 | G46: 0.009 | I46: =SUM(D46:H46) -> 0.009
B47: XI | C47: 161 | F47: 0.963 | I47: =SUM(D47:H47) -> 0.963
B48: XII | C48: 120 | H48: 0.012 | I48: =SUM(D48:H48) -> 0.012
B49: XIV | C49: 163 | F49: 0.083 | I49: =SUM(D49:H49) -> 0.083
B50: Total general | D50: =SUM(D31:D49) -> 2.657 | E50: =SUM(E31:E49) -> 32.227 | F50: =SUM(F31:F49) -> 39300.9 | G50: =SUM(G31:G49) -> 0.103 | H50: =SUM(H31:H49) -> 0.021 | I50: =SUM(D50:H50) -> 39335.908
B53: Operación Industrial Jibia - Zona operación y Mes
B55: Región Operación | C55: Cd_Zona | D55: Enero | E55: Febrero | F55: Marzo | G55: Abril | H55: Mayo | I55: Junio | J55: Julio | K55: Agosto | L55: Septiembre | M55: Octubre | N55: Noviembre | O55: Diciembre | P55: Total
B56: I | C56: 102 | H56: 0.544 | P56: =SUM(D56:O56) -> 0.544
B57: IV | C57: 110 | E57: 0.228 | F57: 0.41 | G57: 0.032 | H57: 0.032 | P57: =SUM(D57:O57) -> 0.702
B58: V | C58: 111 | D58: 14.314 | E58: 1.97 | F58: 34.075 | G58: 6.927 | H58: 0.008 | I58: 0.011 | J58: 0.029 | M58: 0.012 | N58: =0.048+0.01 -> 0.058 | O58: 4.746 | P58: =SUM(D58:O58) -> 62.15
B59: VI | C59: 112 | D59: 7.448 | F59: 0.015 | G59: 0.014 | H59: 0.012 | P59: =SUM(D59:O59) -> 7.489
B60: VII | C60: 113 | E60: 0.114 | I60: 0.025 | J60: 379.971 | P60: =SUM(D60:O60) -> 380.11
B61: VIII | C61: 114 | D61: 5094.956 | E61: 4662.027 | F61: 5174.516 | G61: 4976.784 | H61: 5203.024 | I61: 5022.386 | J61: 4129.216 | K61: 4360.642 | P61: =SUM(D61:O61) -> 38623.551
B62: IX | C62: 115 | G62: 0.147 | I62: 4.508 | J62: 246.419 | P62: =SUM(D62:O62) -> 251.074
B63: XI | C63: 118 | F63: 0.003 | I63: 0.072 | J63: 0.015 | K63: 0.008 | L63: 0.005 | O63: 0.006 | P63: =SUM(D63:O63) -> 0.109
B64: XI | C64: 119 | I64: 0.007 | J64: 0.002 | P64: =SUM(D64:O64) -> 0.009
B65: XII | C65: 120 | F65: 0.008 | J65: 0.004 | P65: =SUM(D65:O65) -> 0.012
B66: I | C66: 141 | J66: 2.113 | P66: =SUM(D66:O66) -> 2.113
B67: VI | C67: 151 | K67: 1.59 | P67: =SUM(D67:O67) -> 1.59
B68: VIII | C68: 153 | E68: 1.595 | H68: 1.352 | P68: =SUM(D68:O68) -> 2.947
B69: IX | C69: 154 | G69: 1.636 | P69: =SUM(D69:O69) -> 1.636
B70: X | C70: 156 | H70: 0.16 | P70: =SUM(D70:O70) -> 0.16
B71: XIV | C71: 161 | I71: 0.963 | P71: =SUM(D71:O71) -> 0.963
B72: X | C72: 162 | G72: 0.399 | P72: =SUM(D72:O72) -> 0.399
B73: XIV | C73: 163 | H73: 0.083 | P73: =SUM(D73:O73) -> 0.083
B74: X | C74: 164 | G74: 0.14 | H74: 0.127 | P74: =SUM(D74:O74) -> 0.267
B75: Total | D75: =SUM(D56:D74) -> 5116.718 | E75: =SUM(E56:E74) -> 4665.934 | F75: =SUM(F56:F74) -> 5209.027 | G75: =SUM(G56:G74) -> 4986.079 | H75: =SUM(H56:H74) -> 5205.342 | I75: =SUM(I56:I74) -> 5027.972 | J75: =SUM(J56:J74) -> 4757.769 | K75: =SUM(K56:K74) -> 4362.24 | ... P75: =SUM(P56:P74) -> 39335.908
B78: Operación Jibia Artesanal zona operación y región de desembarque AÑO 2016
B80: REGION DESEMBARQUE
B81: Región captura | C81: zona captura | D81: I | E81: II | F81: III | G81: IV | H81: V | I81: VI | J81: VII | K81: VIII | L81: IX | M81: XIV | N81: XV | O81: Total general
B82: I | C82: 103 | D82: 0.22 | O82: =SUM(D82:N82) -> 0.22
B83: II | C83: 104 | E83: 0.116 | K83: 6 | O83: =SUM(D83:N83) -> 6.116
B84: II | C84: 105 | E84: 0.201 | O84: =SUM(D84:N84) -> 0.201
B85: II | C85: 106 | E85: 0.064 | O85: =SUM(D85:N85) -> 0.064
B86: II | C86: 144 | K86: 2.74 | O86: =SUM(D86:N86) -> 2.74
B87: II | C87: 145 | H87: 1.594 | O87: =SUM(D87:N87) -> 1.594
B88: III | C88: 107 | F88: 8.839 | O88: =SUM(D88:N88) -> 8.839
B89: III | C89: 108 | F89: 6.871 | G89: 9.832 | O89: =SUM(D89:N89) -> 16.703
B90: IV | C90: 109 | G90: 19118.193 | O90: =SUM(D90:N90) -> 19118.193
B91: IV | C91: 110 | G91: 2135.023 | H91: 19.831 | O91: =SUM(D91:N91) -> 2154.854
B92: IV | C92: 149 | G92: 3 | O92: =SUM(D92:N92) -> 3
B93: V | C93: 111 | H93: 68102.007 | O93: =SUM(D93:N93) -> 68102.007
B94: V | C94: 130 | H94: 14.847 | O94: =SUM(D94:N94) -> 14.847
B95: V | C95: 131 | H95: 1.738 | O95: =SUM(D95:N95) -> 1.738
B96: V | C96: 132 | H96: 2.195 | O96: =SUM(D96:N96) -> 2.195
B97: V | C97: 150 | H97: 8.774 | O97: =SUM(D97:N97) -> 8.774
B98: VI | C98: 112 | H98: 5.483 | I98: 0.648 | O98: =SUM(D98:N98) -> 6.131
B99: VII | C99: 113 | H99: 5.967 | J99: 136.723 | O99: =SUM(D99:N99) -> 142.69
B100: VIII | C100: 114 | K100: 54508.096 | O100: =SUM(D100:N100) -> 54508.096
B101: VIII | C101: 153 | K101: 3.926 | O101: =SUM(D101:N101) -> 3.926
B102: IX | C102: 115 | K102: 6 | L102: 3.535 | O102: =SUM(D102:N102) -> 9.535
B103: X | C103: 117 | K103: 7.387 | O103: =SUM(D103:N103) -> 7.387
B104: XI | C104: 119 | G104: 1.55 | O104: =SUM(D104:N104) -> 1.55
B105: XIV | C105: 116 | M105: 0.702 | O105: =SUM(D105:N105) -> 0.702
B106: XIV | C106: 161 | M106: 0.788 | O106: =SUM(D106:N106) -> 0.788
B107: XV | C107: 140 | N107: 0.105 | O107: =SUM(D107:N107) -> 0.105
B108: V | C108: 133 | H108: 5.73 | O108: =SUM(D108:N108) -> 5.73
B109: Total general | D109: 0.22 | E109: =SUM(E82:E108) -> 0.381 | F109: =SUM(F82:F108) -> 15.71 | G109: =SUM(G82:G108) -> 21267.598 | H109: =SUM(H82:H108) -> 68168.166 | I109: =SUM(I82:I108) -> 0.648 | J109: =SUM(J82:J108) -> 136.723 | K109: =SUM(K82:K108) -> 54534.149 | L109: =SUM(L82:L108) -> 3.535 | ... N109: =SUM(N82:N108) -> 0.105 | O109: =SUM(D109:N109) -> 144128.73
B112: Región captura | C112: Meses de Captura
C113: enero | D113: febrero | E113: marzo | F113: abril | G113: mayo | H113: junio | I113: julio | J113: agosto | K113: septiembre | L113: octubre | M113: noviembre | N113: diciembre | O113: Total general
B114: I | K114: 0.22 | O114: =SUM(C114:N114) -> 0.22
...

Sheet Cuotas Fuera UP 
B2: Cuotas Anuales de Captura Recursos Demersales Fuera de Unidades de Pesquería, año 2016
B3: actualizado al 27-01-2017
B6: Unidad de Pesquería | C6: Sector/Fracción | D6: Período | E6: Cuota Global asignada (t) | F6: Desembarques | H6: Desembarque total (t) | I6: Saldo (t) | J6: % Consumo | K6: Fecha cierre
F7: Industrial | G7: Artesanal
B8: Merluza común (D Ex N°103-19/02/2016) | C8: Industrial - Artesanal | D8: Ene-Dic | E8: 40 | F8: 0 | G8: 1.421 | H8: =+F8+G8 -> 1.421 | I8: =+E8-H8 -> 38.579 | J8: =H8/E8 -> 0.035525
B9: Merluza del sur (DS 24/14-01-2016) | C9: Industrial - Artesanal | D9: Ene-Dic | E9: 108 | F9: 310.333 | G9: 0.28 | H9: =+F9+G9 -> 310.613 | I9: =+E9-H9 -> -202.613 | J9: =H9/E9 -> 2.8760463 | K9: 42390
B10: Congrio Dorado (DS 24/14-01-2016) | C10: Investigación | D10: Ene-Dic | E10: 2 | H10: =+F10+G10 -> 0 | I10: =+E10-H10 -> 2 | J10: =H10/E10 -> 0
C11: Industrial - Artesanal | D11: Ene-Jun | E11: 52 | G11: =53.263-6.65 -> 46.613 | H11: =+F11+G11 -> 46.613 | I11: =+E11-H11 -> 5.387 | J11: =H11/E11 -> 0.89640385 | K11: 42487
D12: Jul-Dic | E12: 53 | G12: =43.513-3.709 -> 39.804 | H12: =+F12+G12 -> 39.804 | I12: =+E12-H12 -> 13.196 | J12: =H12/E12 -> 0.75101887
C13: Fauna Acompañante | D13: Ene-Dic | E13: 11 | F13: 0 | G13: 10.359 | H13: =+F13+G13 -> 10.359 | I13: =+E13-H13 -> 0.641 | J13: =H13/E13 -> 0.94172727
B14: Congrio Dorado | C14: Aguas Internacionales | F14: 12.158 | H14: =+F14+G14 -> 12.158
B18: Operación sobre algunos Recursos sin Cuota, año 2016
B21: Unidad de Pesquería | C21: Sector | D21: Período | E21: Desem. (ton) | F21: Total Desem. (ton)
B22: ALBACORA O PEZ ESPADA / IVI HEHEU | C22: Insustrial | D22: Ene Dic | E22: 301.629 | F22: =+E22+E23 -> 7598.574
B23: ALBACORA O PEZ ESPADA / IVI HEHEU | C23: Artesanal | D23: Ene Dic | E23: 7296.945
B24: CABALLA | C24: Insustrial | D24: Ene Dic | E24: 31718.648 | F24: =+E24+E25 -> 56798.062
B25: CABALLA | C25: Artesanal | D25: Ene Dic | E25: 25079.414
B26: REINETA | C26: Insustrial | D26: Ene Dic | E26: 2588.894 | F26: =+E26+E27 -> 27607.597
B27: REINETA | C27: Artesanal | D27: Ene Dic | E27: 25018.703

Sheet Cuota Rayas
A2: Cuota Anual de Captura para las pesquerías Raya volantín y Raya espinosa, año 2016
A3: al 27-12-2016
A7: Unidad de Pesquería | B7: Área | C7: Período | D7: Fraccionamiento | E7: Cuota asignada (t) | F7: Cuota Efectiva (t) | G7: Desembarque (t) | H7: Saldo (t) | I7: % CONSUMO | J7: Fecha de Cierre | K7: Apertura | L7: Fecha de Cierre2
A8: Raya espinosa D Ex. N°201-2016 | B8: V-VII | C8: Abril - Dic | D8: Investigacion | E8: 0.2 | F8: =E8 -> 0.2 | H8: =F8-G8 -> 0.2 | I8: =G8/F8 -> 0
D9: Fauna Acompañante | E9: 0.8 | F9: =E9 -> 0.8 | G9: 0.032 | H9: =F9-G9 -> 0.768 | I9: =G9/F9 -> 0.04
D10: Cuota Objetivo | E10: 9 | F10: =E10 -> 9 | G10: 9.407 | H10: =F10-G10 -> -0.407 | I10: =G10/F10 -> 1.0452222 | J10: 42507
B11: VIII-41°28.6 L.S. | C11: Abril - Dic | D11: Investigacion | E11: 0.6 | F11: =E11 -> 0.6 | H11: =F11-G11 -> 0.6 | I11: =G11/F11 -> 0
D12: Fauna Acompañante | E12: 1.4 | F12: =E12 -> 1.4 | G12: 2.096 | H12: =F12-G12 -> -0.696 | I12: =G12/F12 -> 1.4971429 | J12: 42495
D13: Cuota Objetivo | E13: 28 | F13: =E13 -> 28 | G13: 6.674 | H13: =F13-G13 -> 21.326 | I13: =G13/F13 -> 0.23835714
B14: 41°28.6 L.S. al límite Sur X Región | C14: Abril - Dic | D14: Investigacion | E14: 0.18 | F14: =E14 -> 0.18 | H14: =F14-G14 -> 0.18 | I14: =G14/F14 -> 0
D15: Fauna Acompañante | E15: 1 | F15: =E15 -> 1 | H15: =F15-G15 -> 1 | I15: =G15/F15 -> 0
D16: Cuota Objetivo | E16: 7.82 | F16: =E16 -> 7.82 | G16: 9.366 | H16: =F16-G16 -> -1.546 | I16: =G16/F16 -> 1.1976982 | J16: 42465
B17: XI | C17: Abril - Dic | D17: Investigacion | E17: 0.13 | F17: =E17 -> 0.13 | H17: =F17-G17 -> 0.13 | I17: =G17/F17 -> 0
D18: Fauna Acompañante | E18: 1 | F18: =E18 -> 1 | H18: =F18-G18 -> 1 | I18: =G18/F18 -> 0
D19: Cuota Objetivo | E19: 5.47 | F19: =E19 -> 5.47 | G19: 0.606 | H19: =F19-G19 -> 4.864 | I19: =G19/F19 -> 0.11078611 | J19: 42468
B20: XII | C20: Abril - Dic | D20: Investigacion | E20: 0 | F20: =E20 -> 0 | H20: =F20-G20 -> 0 | I20: =G20/F20 -> #DIV/0!
D21: Fauna Acompañante | E21: 0.4 | F21: =E21 -> 0.4 | H21: =F21-G21 -> 0.4 | I21: =G21/F21 -> 0
D22: Cuota Objetivo | E22: 4 | F22: =E22 -> 4 | G22: 4.48 | H22: =F22-G22 -> -0.48 | I22: =G22/F22 -> 1.12 | J22: 42489
E23: =SUM(E8:E22) -> 60 | F23: =SUM(F8:F22) -> 60 | G23: =SUM(G8:G22) -> 32.661 | I23: =G23/F23 -> 0.54435
A25: Unidad de Pesquería | B25: Área | C25: Período | D25: Fraccionamiento | E25: Cuota asignada (t) | F25: Cuota Efectiva (t) | G25: Desembarque (t) | H25: Saldo (t) | I25: % CONSUMO | J25: Fecha de Cierre | K25: Apertura | L25: Fecha de Cierre2
A26: Raya volantin D Ex. N°201-2016 | B26: V-VII | C26: Abril - Dic | D26: Investigacion | E26: 0.6 | F26: =E26 -> 0.6 | H26: =F26-G26 -> 0.6 | I26: =G26/F26 -> 0
D27: Fauna Acompañante | E27: 1.4 | F27: =E27 -> 1.4 | G27: 0.06 | H27: =F27-G27 -> 1.34 | I27: =G27/F27 -> 0.042857143
D28: Cuota Objetivo | E28: 28 | F28: =E28 -> 28 | G28: =31.296+0.119 -> 31.415 | H28: =F28-G28 -> -3.415 | I28: =G28/F28 -> 1.1219643 | J28: 42545
B29: VIII-41°28.6 L.S. | C29: Abril - Dic | D29: Investigacion | E29: 3 | F29: =E29 -> 3 | H29: =F29-G29 -> 3 | I29: =G29/F29 -> 0
D30: Fauna Acompañante | E30: 10 | F30: =E30 -> 10 | G30: 1.232 | H30: =F30-G30 -> 8.768 | I30: =G30/F30 -> 0.1232
D31: Cuota Objetivo | E31: 146 | F31: =E31 -> 146 | G31: 245.139 | H31: =F31-G31 -> -99.139 | I31: =G31/F31 -> 1.6790342 | J31: 42479
B32: 41°28.6 L.S. al límite Sur X Región | C32: Abril - Dic | D32: Investigacion | E32: 0.5 | F32: =E32 -> 0.5 | H32: =F32-G32 -> 0.5 | I32: =G32/F32 -> 0
D33: Fauna Acompañante | E33: 2 | F33: =E33 -> 2 | G33: 0.02 | H33: =F33-G33 -> 1.98 | I33: =G33/F33 -> 0.01
D34: Cuota Objetivo | E34: 44.3 | F34: =E34 -> 44.3 | G34: 235.349 | H34: =F34-G34 -> -191.049 | I34: =G34/F34 -> 5.3126185 | J34: 42465
B35: XI | C35: Abril - Dic | D35: Investigacion | E35: 0.32 | F35: =E35 -> 0.32 | H35: =F35-G35 -> 0.32 | I35: =G35/F35 -> 0
D36: Fauna Acompañante | E36: 2 | F36: =E36 -> 2 | G36: 0.045 | H36: =F36-G36 -> 1.955 | I36: =G36/F36 -> 0.0225
D37: Cuota Objetivo | E37: 32 | F37: =E37 -> 32 | G37: 47.8 | H37: =F37-G37 -> -15.8 | I37: =G37/F37 -> 1.49375 | J37: 42468
B38: XII | C38: Ene - Dic | D38: Investigacion | E38: 0 | F38: =E38 -> 0 | H38: =F38-G38 -> 0 | I38: 0
D39: Fauna Acompañante | E39: 1 | F39: =E39 -> 1 | H39: =F39-G39 -> 1 | I39: =G39/F39 -> 0
D40: Cuota Objetivo | E40: 21.88 | F40: =E40 -> 21.88 | G40: 25.452 | H40: =F40-G40 -> -3.572 | I40: =G40/F40 -> 1.1632541 | J40: 42489
E41: =SUM(E26:E40) -> 293 | F41: =SUM(F26:F40) -> 293 | G41: =SUM(G26:G40) -> 586.512 | I41: =G41/F41 -> 2.0017474

Sheet CUANTIFICACIÓN CUOTAS IND-ART
A2: NUMERO DE CUOTAS INDUSTRIALES
A3: Considera LTP y PEP
B5: Pelagicos | C5: 148
B6: Demersales | C6: 82
B7: Crustaceos | C7: 41
B8: PEP | C8: 66
B9: TOTAL | C9: 337
