Workbook

Sheet Resumen
A2: Resumen Artesanal por unidad de pesquería, 2012
A3: Al 24 ENERO de 2013
A4: Recurso | B4: Unidad de pesquería | C4: Cuota Global (t) | D4: Desembarque total (t) | E4: Saldo total (t) | F4: % consumido 2012 | G4: % consumido 2011
A5: Jurel | B5: III | C5: =+Global!C29 -> 1141 | D5: =+Global!D29 -> 1116.061 | E5: =+C5-D5 -> 24.939 | F5: =+D5/C5 -> 0.97814286
B6: IV | C6: =+Global!C30 -> 2662 | D6: =+Global!D30 -> 2464.378 | E6: =+C6-D6 -> 197.622 | F6: =+D6/C6 -> 0.92576183
B7: V (RAE por Org) | C7: =+Global!C31 -> 1253 | D7: =+Global!D31 -> 395.985 | E7: =+C7-D7 -> 857.015 | F7: =+D7/C7 -> 0.31602953
B8: VIII | C8: =+Global!C34 -> 2671 | D8: =+Global!D34 -> 2670.063 | E8: =+C8-D8 -> 0.937 | F8: =+D8/C8 -> 0.9996492
B9: Otras regiones (XV,I, II, VI, VII, IX, XIV y X) | C9: =+Global!C27+Global!C28+Global!C32+Global!C33+Global!C35+Global!C36+Global!C37 -> 4258 | D9: =+Global!D27+Global!D28+Global!D32+Global!D33+Global!D35+Global!D36+Global!D37 -> 740.049 | E9: =+C9-D9 -> 3517.951 | F9: =+D9/C9 -> 0.17380202
A10: Jibia | B10: XV- XII regs. | C10: =+SUM(Global!C38) -> 138240 | D10: =+SUM(Global!D38) -> 100599.54 | E10: =+C10-D10 -> 37640.461 | F10: =+D10/C10 -> 0.72771657
A11: Anchoveta | B11: V (RAE por Org) | C11: =+Global!C10 -> 2410 | D11: =+Global!D10 -> 2409.701 | E11: =+C11-D11 -> 0.299 | F11: =+D11/C11 -> 0.99987593
B12: VI | C12: =+Global!C11 -> 15 | D12: =+Global!D11 -> 0 | E12: =+C12-D12 -> 15 | F12: =+D12/C12 -> 0
B13: VII | C13: =+Global!C12 -> 258 | D13: =+Global!D12 -> 580.084 | E13: =+C13-D13 -> -322.084 | F13: =+D13/C13 -> 2.2483876
B14: VIII (RAE por Org) | C14: =+Global!C13 -> 30884 | D14: =+Global!D13 -> 44144.653 | E14: =+C14-D14 -> -13260.653 | F14: =+D14/C14 -> 1.4293697
B15: XIV (RAE por Org) | C15: =+Global!C15 -> 2900 | D15: =+Global!D15 -> 751.229 | E15: =+C15-D15 -> 2148.771 | F15: =+D15/C15 -> 0.25904448
B16: X (RAE por Org) | C16: =+Global!C16 -> 1787 | D16: =+Global!D16 -> 98.712 | E16: =+C16-D16 -> 1688.288 | F16: =+D16/C16 -> 0.055238948
B17: Otras regiones (XV a IV, VI, VII y IX) | C17: =+Global!C6+Global!C7+Global!C8+Global!C9+Global!C11+Global!C12+Global!C14 -> 126151 | D17: =+Global!D6+Global!D7+Global!D8+Global!D9+Global!D11+Global!D12+Global!D14 -> 122066.11 | E17: =+C17-D17 -> 4084.891 | F17: =+D17/C17 -> 0.96761904
A18: Sardina común | B18: V (RAE por Org) | C18: =+Global!C57 -> 10352 | D18: =+Global!D57 -> 9712.112 | E18: =+C18-D18 -> 639.888 | F18: =+D18/C18 -> 0.93818702
B19: VIII (RAE por Org) | C19: =+Global!C60 -> 588550.23 | D19: =+Global!D60 -> 475542.87 | E19: =+C19-D19 -> 113007.36 | F19: =+D19/C19 -> 0.80799028
B20: XIV (RAE por Org) | C20: =+Global!C62 -> 88434.014 | D20: =+Global!D62 -> 88025.842 | E20: =+C20-D20 -> 408.172 | F20: =+D20/C20 -> 0.99538445
B21: X (RAE por Org) | C21: =+Global!C63 -> 39582 | D21: =+Global!D63 -> 17754.391 | E21: =+C21-D21 -> 21827.609 | F21: =+D21/C21 -> 0.44854709
B22: Otras regiones (VI, VII y IX) | C22: =+Global!C58+Global!C59+Global!C61 -> 12627 | D22: =+Global!D58+Global!D59+Global!D61 -> 10573.352 | E22: =+C22-D22 -> 2053.648 | F22: =+D22/C22 -> 0.83736058
A23: Merluza común | B23: V | C23: =+Global!C45 -> 4024.331 | D23: =+Global!D45 -> 3475.033 | E23: =+C23-D23 -> 549.298 | F23: =+D23/C23 -> 0.86350576
B24: VII | C24: =+Global!C47 -> 5408.818 | D24: =+Global!D47 -> 4698.305 | E24: =+C24-D24 -> 710.513 | F24: =+D24/C24 -> 0.86863803
B25: VIII (RAE por Org) | C25: =+Global!C48 -> 4867.214 | D25: =+Global!D48 -> 3372.11 | E25: =+C25-D25 -> 1495.104 | F25: =+D25/C25 -> 0.6928214
B26: Otras regiones (IV, VI, IX, XIV y X) | C26: =+Global!C44+Global!C46+Global!C49+Global!C50 -> 1808.992 | D26: =+Global!D44+Global!D46+Global!D49+Global!D50 -> 1486.91 | E26: =+C26-D26 -> 322.082 | F26: =+D26/C26 -> 0.82195499
A27: Merluza del sur | B27: X | C27: =+Global!C51 -> 6000 | D27: =+Global!D51 -> 4089.0716 | E27: =+C27-D27 -> 1910.9284 | F27: =+D27/C27 -> 0.68151193
B28: XI | C28: =+Global!C52 -> 3298.824 | D28: =+Global!D52 -> 1954.593 | E28: =+C28-D28 -> 1344.231 | F28: =+D28/C28 -> 0.59251206
B29: XII | C29: =+Global!C53 -> 1664 | D29: =+Global!D53 -> 1369.8015 | E29: =+C29-D29 -> 294.19851 | F29: =+D29/C29 -> 0.82319801
A30: Camarón nailon | B30: IV | C30: =+Global!C19 -> 430 | D30: =+Global!D19 -> 437.99 | E30: =+C30-D30 -> -7.99 | F30: =+D30/C30 -> 1.0185814
B31: V | C31: =+Global!C20 -> 430 | D31: =+Global!D20 -> 432.292 | E31: =+C31-D31 -> -2.292 | F31: =+D31/C31 -> 1.0053302
B32: Otras regiones (II, III, VI a VIII) | C32: =+Global!C17+Global!C18+Global!C21+Global!C22+Global!C23 -> 129 | D32: =+Global!D17+Global!D18+Global!D21+Global!D22+Global!D23 -> 1.083 | E32: =+C32-D32 -> 127.917 | F32: =+D32/C32 -> 0.0083953488
A33: Congrio dorado | B33: X - XII | C33: =+Global!C24+Global!C25+Global!C26 -> 405 | D33: =+Global!D24+Global!D25+Global!D26 -> 410.69119 | E33: =+C33-D33 -> -5.6911944 | F33: =+D33/C33 -> 1.0140523
A34: Langostino amarillo | B34: III | C34: =+Global!C39 -> 196 | D34: =+Global!D39 -> 13.638 | E34: =+C34-D34 -> 182.362 | F34: =+D34/C34 -> 0.069581633
B35: IV | C35: =+Global!C40 -> 781 | D35: =+Global!D40 -> 817.722 | E35: =+C35-D35 -> -36.722 | F35: =+D35/C35 -> 1.0470192
A36: Langostino colorado | B36: II | C36: =+Global!C41 -> 20 | D36: =+Global!D41 -> 0 | E36: =+C36-D36 -> 20 | F36: =+D36/C36 -> 0
B37: III | C37: =+Global!C42 -> 150 | D37: =+Global!D42 -> 0 | E37: =+C37-D37 -> 150 | F37: =+D37/C37 -> 0
B38: IV | C38: =+Global!C43 -> 515 | D38: =+Global!D43 -> 516.566 | E38: =+C38-D38 -> -1.566 | F38: =+D38/C38 -> 1.0030408
A39: Sardina española | B39: XV y I | C39: =+Global!C54 -> 525 | D39: =+Global!D54 -> 12.128 | E39: =+C39-D39 -> 512.872 | F39: =+D39/C39 -> 0.023100952
B40: II | C40: =+Global!C55 -> 1975 | D40: =+Global!D55 -> 172.922 | E40: =+C40-D40 -> 1802.078 | F40: =+D40/C40 -> 0.087555443
B41: III - IV | C41: =+Global!C56 -> 625 | D41: =+Global!D56 -> 8.426 | E41: =+C41-D41 -> 616.574 | F41: =+D41/C41 -> 0.0134816
A42: Sardina austral | B42: X | C42: =+SUM(Global!C64) -> 1800 | D42: =+SUM(Global!D64) -> 2459.86 | E42: =+C42-D42 -> -659.86 | F42: =+D42/C42 -> 1.3665889
B43: XI | C43: =+SUM(Global!C65) -> 4000 | D43: =+SUM(Global!D65) -> 1586.11 | E43: =+C43-D43 -> 2413.89 | F43: =+D43/C43 -> 0.3965275

Sheet Global
A2: Resumen Global Cuotas Artesanales 2012
A3: Al 24 ENERO de 2013
A5: Recurso | B5: Unidad de pesquería | C5: Cuota Global (t) | D5: Desembarque total (t) | E5: Saldo total (t) | F5: % consumido 2012 | G5: % consumido 2011
A6: Anchoveta | B6: XV y I | C6: =+'Res. Global'!E7+'Res. Global'!E8 -> 73879 | D6: =+SUM('Res. Global'!G7:G8) -> 73839.434 | E6: =+C6-D6 -> 39.566 | F6: =+D6/C6 -> 0.99946445 | G6: 1.0004208
A7: Anchoveta | B7: II | C7: =+SUM('Res. Global'!E9:E10) -> 22068 | D7: =+SUM('Res. Global'!G9:G10) -> 20013.479 | E7: =+C7-D7 -> 2054.521 | F7: =+D7/C7 -> 0.90690044 | G7: 0.72571316
A8: Anchoveta | B8: III | C8: =+SUM('Res. Global'!E11:E12) -> 20615 | D8: =+SUM('Res. Global'!G11:G12) -> 19012.21 | E8: =+C8-D8 -> 1602.79 | F8: =+D8/C8 -> 0.92225127 | G8: 1.011722
A9: Anchoveta | B9: IV | C9: =+SUM('Res. Global'!E13:E14) -> 8835 | D9: =+SUM('Res. Global'!G13:G14) -> 8530.777 | E9: =+C9-D9 -> 304.223 | F9: =+D9/C9 -> 0.96556616 | G9: 0.9212029
A10: Anchoveta | B10: V (RAE por Org) | C10: =+SUM('Res. Global'!E15:E17) -> 2410 | D10: =+SUM('Res. Global'!G15:G17) -> 2409.701 | E10: =+C10-D10 -> 0.299 | F10: =+D10/C10 -> 0.99987593 | G10: 1.0024192
A11: Anchoveta | B11: VI | C11: =+SUM('Res. Global'!E18:E20) -> 15 | D11: =+SUM('Res. Global'!G18:G20) -> 0 | E11: =+C11-D11 -> 15 | F11: =+D11/C11 -> 0 | G11: 0
A12: Anchoveta | B12: VII | C12: =+SUM('Res. Global'!E21:E23) -> 258 | D12: =+SUM('Res. Global'!G21:G23) -> 580.084 | E12: =+C12-D12 -> -322.084 | F12: =+D12/C12 -> 2.2483876 | G12: 2.3895703
A13: Anchoveta | B13: VIII (RAE por Org) | C13: =+SUM('Res. Global'!E24:E25) -> 30884 | D13: =+SUM('Res. Global'!G24:G25) -> 44144.653 | E13: =+C13-D13 -> -13260.653 | F13: =+D13/C13 -> 1.4293697 | G13: 2.6155879
A14: Anchoveta | B14: IX | C14: =+SUM('Res. Global'!E26:E28) -> 481 | D14: =+SUM('Res. Global'!G26:G28) -> 90.125 | E14: =+C14-D14 -> 390.875 | F14: =+D14/C14 -> 0.18737006 | G14: 0.13915665
A15: Anchoveta | B15: XIV (RAE por Org) | C15: =+SUM('Res. Global'!E29:E31) -> 2900 | D15: =+SUM('Res. Global'!G29:G31) -> 751.229 | E15: =+C15-D15 -> 2148.771 | F15: =+D15/C15 -> 0.25904448 | G15: 0.15908861
A16: Anchoveta | B16: X (RAE por Org) | C16: =+SUM('Res. Global'!E32:E33) -> 1787 | D16: =+SUM('Res. Global'!G32:G33) -> 98.712 | E16: =+C16-D16 -> 1688.288 | F16: =+D16/C16 -> 0.055238948 | G16: 0.75441022
A17: Camarón nailon | B17: II | C17: =+SUM('Res. Global'!E34:E36) -> 15 | D17: =+SUM('Res. Global'!G34:G36) -> 0 | E17: =+C17-D17 -> 15 | F17: =+D17/C17 -> 0 | G17: 0
A18: Camarón nailon | B18: III | C18: =+SUM('Res. Global'!E37:E39) -> 90 | D18: =+SUM('Res. Global'!G37:G39) -> 1.083 | E18: =+C18-D18 -> 88.917 | F18: =+D18/C18 -> 0.012033333 | G18: 0.36196667
A19: Camarón nailon | B19: IV | C19: =+SUM('Res. Global'!E40:E42) -> 430 | D19: =+SUM('Res. Global'!G40:G42) -> 437.99 | E19: =+C19-D19 -> -7.99 | F19: =+D19/C19 -> 1.0185814 | G19: 1.017014
A20: Camarón nailon | B20: V | C20: =+SUM('Res. Global'!E43:E45) -> 430 | D20: =+SUM('Res. Global'!G43:G45) -> 432.292 | E20: =+C20-D20 -> -2.292 | F20: =+D20/C20 -> 1.0053302 | G20: 0.99819488
A21: Camarón nailon | B21: VI | C21: =+SUM('Res. Global'!E46:E48) -> 8 | D21: =+SUM('Res. Global'!G46:G48) -> 0 | E21: =+C21-D21 -> 8 | F21: =+D21/C21 -> 0 | G21: 0
A22: Camarón nailon | B22: VII | C22: =+SUM('Res. Global'!E49:E51) -> 8 | D22: =+SUM('Res. Global'!G49:G51) -> 0 | E22: =+C22-D22 -> 8 | F22: =+D22/C22 -> 0 | G22: 0
A23: Camarón nailon | B23: VIII | C23: =+SUM('Res. Global'!E52:E54) -> 8 | D23: =+SUM('Res. Global'!G52:G54) -> 0 | E23: =+C23-D23 -> 8 | F23: =+D23/C23 -> 0 | G23: 0
A24: Congrio dorado | B24: X | C24: =+SUM('Res. Global'!E55:E56) -> 259 | D24: =+SUM('Res. Global'!G55:G56) -> 261.83689 | E24: =+C24-D24 -> -2.8368944 | F24: =+D24/C24 -> 1.0109533 | G24: 1.0958585
A25: Congrio dorado | B25: XI | C25: =+SUM('Res. Global'!E57:E58) -> 85 | D25: =+SUM('Res. Global'!G57:G58) -> 86.108 | E25: =+C25-D25 -> -1.108 | F25: =+D25/C25 -> 1.0130353 | G25: 0.83410703
A26: Congrio dorado | B26: XII | C26: =+SUM('Res. Global'!E59:E60) -> 61 | D26: =+SUM('Res. Global'!G59:G60) -> 62.7463 | E26: =+C26-D26 -> -1.7463 | F26: =+D26/C26 -> 1.0286279 | G26: 1.0086484
A27: Jurel | B27: XV y I | C27: =+SUM('Res. Global'!E61:E62) -> 875 | D27: =+SUM('Res. Global'!G61:G62) -> 8.449 | E27: =+C27-D27 -> 866.551 | F27: =+D27/C27 -> 0.009656 | G27: 0.0065688073
A28: Jurel | B28: II | C28: =+SUM('Res. Global'!E63:E64) -> 875 | D28: =+SUM('Res. Global'!G63:G64) -> 107.57 | E28: =+C28-D28 -> 767.43 | F28: =+D28/C28 -> 0.12293714 | G28: 0.1650581
A29: Jurel | B29: III | C29: =+SUM('Res. Global'!E65:E66) -> 1141 | D29: =+SUM('Res. Global'!G65:G66) -> 1116.061 | E29: =+C29-D29 -> 24.939 | F29: =+D29/C29 -> 0.97814286 | G29: 1.0173142
A30: Jurel | B30: IV | C30: =+SUM('Res. Global'!E67:E68) -> 2662 | D30: =+SUM('Res. Global'!G67:G68) -> 2464.378 | E30: =+C30-D30 -> 197.622 | F30: =+D30/C30 -> 0.92576183 | G30: 0.89670094
A31: Jurel | B31: V (RAE por Org) | C31: =+SUM('Res. Global'!E69:E70) -> 1253 | D31: =+SUM('Res. Global'!G69:G70) -> 395.985 | E31: =+C31-D31 -> 857.015 | F31: =+D31/C31 -> 0.31602953 | G31: 0.13618447
A32: Jurel | B32: VI | C32: =+SUM('Res. Global'!E71:E72) -> 5 | D32: =+SUM('Res. Global'!G71:G72) -> 0.463 | E32: =+C32-D32 -> 4.537 | F32: =+D32/C32 -> 0.0926 | G32: 0.014
A33: Jurel | B33: VII | C33: =+SUM('Res. Global'!E73:E74) -> 41 | D33: =+SUM('Res. Global'!G73:G74) -> 14.818 | E33: =+C33-D33 -> 26.182 | F33: =+D33/C33 -> 0.36141463 | G33: 0.65481395
A34: Jurel | B34: VIII | C34: =+SUM('Res. Global'!E75:E76) -> 2671 | D34: =+SUM('Res. Global'!G75:G76) -> 2670.063 | E34: =+C34-D34 -> 0.937 | F34: =+D34/C34 -> 0.9996492 | G34: 0.89481054
A35: Jurel | B35: IX | C35: =+SUM('Res. Global'!E77:E78) -> 60 | D35: =+SUM('Res. Global'!G77:G78) -> 0 | E35: =+C35-D35 -> 60 | F35: =+D35/C35 -> 0 | G35: 0
A36: Jurel | B36: XIV (RAE por Org) | C36: =+SUM('Res. Global'!E79:E80) -> 312 | D36: =+SUM('Res. Global'!G79:G80) -> 0.528 | E36: =+C36-D36 -> 311.472 | F36: =+D36/C36 -> 0.0016923077 | G36: 0
A37: Jurel | B37: X (RAE por Org) | C37: =+SUM('Res. Global'!E81:E82) -> 2090 | D37: =+SUM('Res. Global'!G81:G82) -> 608.221 | E37: =+C37-D37 -> 1481.779 | F37: =+D37/C37 -> 0.29101483 | G37: 0
A38: Jibia | B38: XV- XII regs. | C38: =+SUM('Res. Global'!C83) -> 138240 | D38: =+SUM('Res. Global'!G83) -> 100599.54 | E38: =+C38-D38 -> 37640.461 | F38: =+D38/C38 -> 0.72771657 | G38: 0
A39: Langostino amarillo | B39: III | C39: =+SUM('Res. Global'!E84:E86) -> 196 | D39: =+SUM('Res. Global'!G84:G86) -> 13.638 | E39: =+C39-D39 -> 182.362 | F39: =+D39/C39 -> 0.069581633 | G39: 0.56482133
A40: Langostino amarillo | B40: IV | C40: =+SUM('Res. Global'!E87:E89) -> 781 | D40: =+SUM('Res. Global'!G87:G89) -> 817.722 | E40: =+C40-D40 -> -36.722 | F40: =+D40/C40 -> 1.0470192 | G40: 1.0077206
A41: Langostino colorado | B41: II | C41: =+SUM('Res. Global'!E90:E92) -> 20 | D41: =+SUM('Res. Global'!G90:G92) -> 0 | E41: =+C41-D41 -> 20 | F41: =+D41/C41 -> 0 | G41: 0
A42: Langostino colorado | B42: III | C42: =+SUM('Res. Global'!E93:E95) -> 150 | D42: =+SUM('Res. Global'!G93:G95) -> 0 | E42: =+C42-D42 -> 150 | F42: =+D42/C42 -> 0 | G42: 8.2352941e-05
A43: Langostino colorado | B43: IV | C43: =+SUM('Res. Global'!E96:E98) -> 515 | D43: =+SUM('Res. Global'!G96:G98) -> 516.566 | E43: =+C43-D43 -> -1.566 | F43: =+D43/C43 -> 1.0030408 | G43: 0.99385532
A44: Merluza común | B44: IV | C44: =+SUM('Res. Global'!E99:E104) -> 665.964 | D44: =+SUM('Res. Global'!G99:G104) -> 514.3 | E44: =+C44-D44 -> 151.664 | F44: =+D44/C44 -> 0.77226397 | G44: 0.67642708
A45: Merluza común | B45: V | C45: =+SUM('Res. Global'!E105:E110) -> 4024.331 | D45: =+SUM('Res. Global'!G105:G110) -> 3475.033 | E45: =+C45-D45 -> 549.298 | F45: =+D45/C45 -> 0.86350576 | G45: 0.92744061
A46: Merluza común | B46: VI | C46: =+SUM('Res. Global'!E111:E114) -> 1095.208 | D46: =+SUM('Res. Global'!G111:G114) -> 972.075 | E46: =+C46-D46 -> 123.133 | F46: =+D46/C46 -> 0.88757113 | G46: 1.0182538
A47: Merluza común | B47: VII | C47: =+SUM('Res. Global'!E115:E122) -> 5408.818 | D47: =+SUM('Res. Global'!G115:G122) -> 4698.305 | E47: =+C47-D47 -> 710.513 | F47: =+D47/C47 -> 0.86863803 | G47: 1.0021741
A48: Merluza común | B48: VIII | C48: =+SUM('Res. Global'!E123:E128) -> 4867.214 | D48: =+SUM('Res. Global'!G123:G128) -> 3372.11 | E48: =+C48-D48 -> 1495.104 | F48: =+D48/C48 -> 0.6928214 | G48: 0.97623271
A49: Merluza común | B49: IX | C49: =+SUM('Res. Global'!E129:E130) -> 24.841 | D49: =+SUM('Res. Global'!G129:G130) -> 0 | E49: =+C49-D49 -> 24.841 | F49: =+D49/C49 -> 0 | G49: 0.069244085
A50: Merluza común | B50: XIV-X | C50: =+SUM('Res. Global'!E131:E132) -> 22.979 | D50: =+SUM('Res. Global'!G131:G132) -> 0.535 | E50: =+C50-D50 -> 22.444 | F50: =+D50/C50 -> 0.023282127 | G50: 0.16804591
A51: Merluza del sur | B51: X | C51: =+SUM('Res. Global'!E133:E134) -> 6000 | D51: =+SUM('Res. Global'!G133:G134) -> 4089.0716 | E51: =+C51-D51 -> 1910.9284 | F51: =+D51/C51 -> 0.68151193 | G51: 0.72267764
A52: Merluza del sur | B52: XI | C52: =+SUM('M.sur XI'!K24) -> 3298.824 | D52: =+SUM('M.sur XI'!M24) -> 1954.593 | E52: =+C52-D52 -> 1344.231 | F52: =+D52/C52 -> 0.59251206 | G52: 0.99605076
A53: Merluza del sur | B53: XII | C53: =+SUM('Res. Global'!E137:E138) -> 1664 | D53: =+SUM('Res. Global'!G137:G138) -> 1369.8015 | E53: =+C53-D53 -> 294.19851 | F53: =+D53/C53 -> 0.82319801 | G53: 0.39997582
A54: Sardina española | B54: XV y I | C54: =+SUM('Res. Global'!E139:E140) -> 525 | D54: =+SUM('Res. Global'!G139:G140) -> 12.128 | E54: =+C54-D54 -> 512.872 | F54: =+D54/C54 -> 0.023100952 | G54: 0.0074534161
A55: Sardina española | B55: II | C55: =+SUM('Res. Global'!E141:E142) -> 1975 | D55: =+SUM('Res. Global'!G141:G142) -> 172.922 | E55: =+C55-D55 -> 1802.078 | F55: =+D55/C55 -> 0.087555443 | G55: 0.0063241607
A56: Sardina española | B56: III - IV | C56: =+SUM('Res. Global'!E143:E144) -> 625 | D56: =+SUM('Res. Global'!G143:G144) -> 8.426 | E56: =+C56-D56 -> 616.574 | F56: =+D56/C56 -> 0.0134816 | G56: 0.0086784
A57: Sardina común | B57: V (RAE por Org) | C57: =+SUM('Res. Global'!E145:E147) -> 10352 | D57: =+SUM('Res. Global'!G145:G147) -> 9712.112 | E57: =+C57-D57 -> 639.888 | F57: =+D57/C57 -> 0.93818702 | G57: 1.0426918
A58: Sardina común | B58: VI | C58: =+SUM('Res. Global'!E148:E150) -> 244 | D58: =+SUM('Res. Global'!G148:G150) -> 0 | E58: =+C58-D58 -> 244 | F58: =+D58/C58 -> 0 | G58: 0
A59: Sardina común | B59: VII | C59: =+SUM('Res. Global'!E151:E153) -> 3743 | D59: =+SUM('Res. Global'!G151:G153) -> 1907.988 | E59: =+C59-D59 -> 1835.012 | F59: =+D59/C59 -> 0.50974833 | G59: 0.84854097
A60: Sardina común | B60: VIII (RAE por Org) | C60: =+SUM('Res. Global'!E154:E155) -> 588550.23 | D60: =+SUM('Res. Global'!G154:G155) -> 475542.87 | E60: =+C60-D60 -> 113007.36 | F60: =+D60/C60 -> 0.80799028 | G60: 0.88391437
A61: Sardina común | B61: IX | C61: =+SUM('Res. Global'!E156:E158) -> 8640 | D61: =+SUM('Res. Global'!G156:G158) -> 8665.364 | E61: =+C61-D61 -> -25.364 | F61: =+D61/C61 -> 1.0029356 | G61: 1.0630971
A62: Sardina común | B62: XIV (RAE por Org) | C62: =+SUM('Res. Global'!E159:E161) -> 88434.014 | D62: =+SUM('Res. Global'!G159:G161) -> 88025.842 | E62: =+C62-D62 -> 408.172 | F62: =+D62/C62 -> 0.99538445 | G62: 0.89727586
A63: Sardina común | B63: X (RAE por Org) | C63: =+SUM('Res. Global'!E162:E163) -> 39582 | D63: =+SUM('Res. Global'!G162:G163) -> 17754.391 | E63: =+C63-D63 -> 21827.609 | F63: =+D63/C63 -> 0.44854709 | G63: 0.23348242
A64: Sardina Austral | B64: X | C64: =+SUM('Res. Global'!E164:E165) -> 1800 | D64: =+SUM('Res. Global'!G164:G165) -> 2459.86 | E64: =+C64-D64 -> -659.86 | F64: =+D64/C64 -> 1.3665889 | G64: 0
A65: Sardina Austral | B65: XI | C65: =+SUM('Res. Global'!C166) -> 4000 | D65: =+SUM('Res. Global'!G166) -> 1586.11 | E65: =+C65-D65 -> 2413.89 | F65: =+D65/C65 -> 0.3965275 | G65: 0
C66: =SUM(C6:C65) -> 1092955.4 | D66: =SUM(D6:D65) -> 906380.3
B67: XI dif. Cuota real | C67: 357.18 | D67: =+D66/C66 -> 0.82929301
B68: total: | C68: =SUM(C66:C67) -> 1093312.6

Sheet Res. Global
A2: Resumen por Periodo Cuota Artesanal 2012
A3: Al 24 ENERO 2013
E5: Cuota (t) | G5: Desembarque (t) | I5: Saldo (t) | K5: Saldo % | M5: Fecha de Cierre
A6: Recurso | B6: Unidad de Pesquería | C6: Cuota Global (t) | D6: Período | E6: Asignada | F6: Efectiva | G6: Período | H6: Global | I6: Período | J6: Global | K6: Período | L6: Global | O6: Datos Access
A7: Anchoveta | B7: XV y I | C7: =SUM(E7:E8) -> 73879 | D7: Ene - Jun | E7: 54045 | F7: =+E7 -> 54045 | G7: =+SUM(Anchoveta!B7:B12) -> 61617.402 | H7: =SUM(G7:G8) -> 73839.434 | I7: =+F7-G7 -> -7572.402 | J7: =+C7-H7 -> 39.566 | K7: =1-G7/F7 -> -0.14011291 | L7: =1-H7/C7 -> 0.00053555137 | M7: 41054 | N7: Desmbarque XV-I incluye cesiones | O7: 135764.65
D8: Jul - Dic | E8: 19834 | F8: =+E8+I7 -> 12261.598 | G8: =+SUM(Anchoveta!B13:B18) -> 12222.032 | I8: =+F8-G8 -> 39.566 | K8: =1-G8/F8 -> 0.0032268225 | M8: 41123
A9: Anchoveta | B9: II | C9: =SUM(E9:E10) -> 22068 | D9: Ene - Jun | E9: 16144 | F9: =+E9 -> 16144 | G9: =+SUM(Anchoveta!B23:B28) -> 11195.23 | H9: =SUM(G9:G10) -> 20013.479 | I9: =+F9-G9 -> 4948.77 | J9: =+C9-H9 -> 2054.521 | K9: =1-G9/F9 -> 0.30653927 | L9: =1-H9/C9 -> 0.093099556 | N9: Desmbarque II incluye cesiones | O9: 20451.727
D10: Jul - Dic | E10: 5924 | F10: =+E10+I9 -> 10872.77 | G10: =+SUM(Anchoveta!B29:B34) -> 8818.249 | I10: =+F10-G10 -> 2054.521 | K10: =1-G10/F10 -> 0.18896022
A11: Anchoveta | B11: III | C11: =SUM(E11:E12) -> 20615 | D11: Ene - Oct | E11: 19584 | F11: =+E11 -> 19584 | G11: =+SUM(Anchoveta!B39:B48) -> 16350.21 | H11: =SUM(G11:G12) -> 19012.21 | I11: =+F11-G11 -> 3233.79 | J11: =+C11-H11 -> 1602.79 | K11: =1-G11/F11 -> 0.16512408 | L11: =1-H11/C11 -> 0.077748727
D12: Nov - Dic | E12: 1031 | F12: =+E12+I11 -> 4264.79 | G12: =+SUM(Anchoveta!B49:B50) -> 2662 | I12: =+F12-G12 -> 1602.79 | K12: =1-G12/F12 -> 0.37581921
A13: Anchoveta | B13: IV | C13: =SUM(E13:E14) -> 8835 | D13: Ene - Oct | E13: =+'Resumen RAE Anchoveta'!C10 -> 8393 | F13: =+E13 -> 8393 | G13: =+SUM('Resumen RAE Anchoveta'!F10) -> 8483.687 | H13: =SUM(G13:G14) -> 8530.777 | I13: =+F13-G13 -> -90.687 | J13: =+C13-H13 -> 304.223 | K13: =1-G13/F13 -> -0.010805076 | L13: =1-H13/C13 -> 0.034433843
D14: Nov - Dic | E14: =+'Resumen RAE Anchoveta'!C16 -> 442 | F14: =+E14+I13 -> 351.313 | G14: =+SUM('Resumen RAE Anchoveta'!F16) -> 47.09 | I14: =+F14-G14 -> 304.223 | K14: =1-G14/F14 -> 0.86595998
A15: Anchoveta | B15: V (RAE por Org) | C15: =SUM(E15:E17) -> 2410 | D15: Ene-Abr | E15: =+SUM('Resumen RAE Anchoveta'!C23) -> 2049 | F15: =+E15 -> 2049 | G15: =+'Resumen RAE Anchoveta'!F23 -> 742.536 | H15: =SUM(G15:G17) -> 2409.701 | I15: =+F15-G15 -> 1306.464 | J15: =+C15-H15 -> 0.299 | K15: =1-G15/F15 -> 0.63761054 | L15: =1-H15/C15 -> 0.00012406639
D16: May-Ago | E16: =+SUM('Resumen RAE Anchoveta'!C28) -> 241 | F16: =+E16+I15 -> 1547.464 | G16: =+'Resumen RAE Anchoveta'!F28 -> 865.055 | I16: =+F16-G16 -> 682.409 | K16: =1-G16/F16 -> 0.44098538
D17: Sep-Dic | E17: =+SUM('Resumen RAE Anchoveta'!C33) -> 120 | F17: =+E17+I16 -> 802.409 | G17: =+'Resumen RAE Anchoveta'!F33 -> 802.11 | I17: =+F17-G17 -> 0.299 | K17: =1-G17/F17 -> 0.00037262792
A18: Anchoveta | B18: VI | C18: =SUM(E18:E20) -> 15 | D18: Ene-Abr | E18: 12 | F18: =+E18 -> 12 | G18: =+SUM(Anchoveta!B55:B58) -> 0 | H18: =SUM(G18:G20) -> 0 | I18: =+F18-G18 -> 12 | J18: =+C18-H18 -> 15 | K18: =1-G18/F18 -> 1 | L18: =1-H18/C18 -> 1
D19: May-Ago | E19: 2 | F19: =+E19+I18 -> 14 | G19: =+SUM(Anchoveta!B59:B62) -> 0 | I19: =+F19-G19 -> 14 | K19: =1-G19/F19 -> 1
D20: Sep-Dic | E20: 1 | F20: =+E20+I19 -> 15 | G20: =+SUM(Anchoveta!B63:B66) -> 0 | I20: =+F20-G20 -> 15 | K20: =1-G20/F20 -> 1
A21: Anchoveta | B21: VII | C21: =SUM(E21:E23) -> 258 | D21: Ene-Abr | E21: 219 | F21: =+E21 -> 219 | G21: =+SUM('Resumen RAE Anchoveta'!F40) -> 453.152 | H21: =SUM(G21:G23) -> 580.084 | I21: =+F21-G21 -> -234.152 | J21: =+C21-H21 -> -322.084 | K21: =1-G21/F21 -> -1.0691872 | L21: =1-H21/C21 -> -1.2483876 | M21: 41031
D22: May-Ago | E22: 26 | F22: =+E22+I21 -> -208.152 | G22: =+SUM('Resumen RAE Anchoveta'!F45+'Resumen RAE Anchoveta'!F45) -> 126.932 | I22: =+F22-G22 -> -335.084 | K22: 0
D23: Sep-Dic | E23: 13 | F23: =+E23+I22 -> -322.084 | G23: =+SUM('Resumen RAE Anchoveta'!F50) -> 0 | I23: =+F23-G23 -> -322.084 | K23: 0
A24: Anchoveta | B24: VIII (RAE por Org) | C24: =SUM(E24:E25) -> 30884 | D24: Ene- Ago | E24: 29340 | F24: =+E24 -> 29340 | G24: =SUM('Resumen RAE Anchoveta'!F116)+-SUM('Resumen RAE Anchoveta'!D116) -> 42783.287 | H24: =SUM(G24:G25) -> 44144.653 | I24: =+F24-G24 -> -13443.287 | J24: =+C24-H24 -> -13260.653 | K24: =1-G24/F24 -> -0.45818974 | L24: =1-H24/C24 -> -0.42936967 | M24: 41031
D25: Sep - Dic | E25: 1544 | F25: =+E25+I24 -> -11899.287 | G25: =+SUM('Resumen RAE Anchoveta'!F180)+-SUM('Resumen RAE Anchoveta'!D180) -> 1361.366 | I25: =+F25-G25 -> -13260.653 | K25: =1-G25/F25 -> 1.1144074
A26: Anchoveta | B26: IX | C26: =SUM(E26:E28) -> 481 | D26: Ene-Abr | E26: 409 | F26: =+E26 -> 409 | G26: =+SUM(Anchoveta!B72:B75) -> 7.864 | H26: =SUM(G26:G28) -> 90.125 | I26: =+F26-G26 -> 401.136 | J26: =+C26-H26 -> 390.875 | K26: =1-G26/F26 -> 0.98077262 | L26: =1-H26/C26 -> 0.81262994 | M26: 41014
D27: May-Ago | E27: 48 | F27: =+E27+I26 -> 449.136 | G27: =+SUM(Anchoveta!B76:B79) -> 82.261 | I27: =+F27-G27 -> 366.875 | K27: =1-G27/F27 -> 0.81684612
D28: Sep-Dic | E28: 24 | F28: =+E28+I27 -> 390.875 | G28: =+SUM(Anchoveta!B80:B83) -> 0 | I28: =+F28-G28 -> 390.875 | K28: =1-G28/F28 -> 1
A29: Anchoveta | B29: XIV (RAE por Org) | C29: =SUM(E29:E31) -> 2900 | D29: Ene-Abr | E29: 2465 | F29: =+E29 -> 2465 | G29: =+'Resumen RAE Anchoveta'!F202 -> 280.681 | H29: =SUM(G29:G31) -> 751.229 | I29: =+F29-G29 -> 2184.319 | J29: =+C29-H29 -> 2148.771 | K29: =1-G29/F29 -> 0.88613347 | L29: =1-H29/C29 -> 0.74095552
D30: May-Ago | E30: 290 | F30: =+E30+I29 -> 2474.319 | G30: =+'Resumen RAE Anchoveta'!F222 -> 143.832 | I30: =+F30-G30 -> 2330.487 | K30: =1-G30/F30 -> 0.94187007
D31: Sep-Dic | E31: 145 | F31: =+E31+I30 -> 2475.487 | G31: =+'Resumen RAE Anchoveta'!F242 -> 326.716 | I31: =+F31-G31 -> 2148.771 | K31: =1-G31/F31 -> 0.8680195
A32: Anchoveta | B32: X (RAE por Org) | C32: =SUM(E32:E33) -> 1787 | D32: Ene-Jun | E32: 1430 | F32: =+E32 -> 1430 | G32: =+SUM('Resumen RAE Anchoveta'!F257) -> 97.512 | H32: =SUM(G32:G33) -> 98.712 | I32: =+F32-G32 -> 1332.488 | J32: =+C32-H32 -> 1688.288 | K32: =1-G32/F32 -> 0.93180979 | L32: =1-H32/C32 -> 0.94476105
D33: Jul-Dic | E33: 357 | F33: =+E33+I32 -> 1689.488 | G33: =+'Resumen RAE Anchoveta'!F270 -> 1.2 | I33: =+F33-G33 -> 1688.288 | K33: =1-G33/F33 -> 0.99928973
A34: Camarón nailon | B34: II | C34: =SUM(E34:E36) -> 15 | D34: Ene - Mar | E34: 6 | F34: =+E34 -> 6 | G34: =+SUM(C.Nailon!B7:B9) -> 0 | H34: =SUM(G34:G36) -> 0 | I34: =+F34-G34 -> 6 | J34: =+C34-H34 -> 15 | K34: =1-G34/F34 -> 1 | L34: =1-H34/C34 -> 1
D35: Abr - Ago | E35: 4 | F35: =+E35+I34 -> 10 | G35: =+SUM(C.Nailon!B10:B14) -> 0 | I35: =+F35-G35 -> 10 | K35: =1-G35/F35 -> 1
D36: Sep - Dic | E36: 5 | F36: =+E36+I35 -> 15 | G36: =+SUM(C.Nailon!B15:B18) -> 0 | I36: =+F36-G36 -> 15 | K36: =1-G36/F36 -> 1
A37: Camarón nailon | B37: III | C37: =SUM(E37:E39) -> 90 | D37: Ene - Mar | E37: 41 | F37: =+E37 -> 41 | G37: =+SUM(C.Nailon!B23:B25) -> 0 | H37: =SUM(G37:G39) -> 1.083 | I37: =+F37-G37 -> 41 | J37: =+C37-H37 -> 88.917 | K37: =1-G37/F37 -> 1 | L37: =1-H37/C37 -> 0.98796667
D38: Abr - Ago | E38: 23 | F38: =+E38+I37 -> 64 | G38: =+SUM(C.Nailon!B26:B30) -> 0 | I38: =+F38-G38 -> 64 | K38: =1-G38/F38 -> 1
D39: Sep - Dic | E39: 26 | F39: =+E39+I38 -> 90 | G39: =+SUM(C.Nailon!B31:B34) -> 1.083 | I39: =+F39-G39 -> 88.917 | K39: =1-G39/F39 -> 0.98796667
A40: Camarón nailon | B40: IV | C40: =SUM(E40:E42) -> 430 | D40: Ene - Mar | E40: 193 | F40: =+E40 -> 193 | G40: =+SUM(C.Nailon!B39:B41) -> 203.868 | H40: =SUM(G40:G42) -> 437.99 | I40: =+F40-G40 -> -10.868 | J40: =+C40-H40 -> -7.99 | K40: =1-G40/F40 -> -0.056310881 | L40: =1-H40/C40 -> -0.018581395 | M40: 40980
D41: Abr - Ago | E41: 107 | F41: =+E41+I40 -> 96.132 | G41: =+SUM(C.Nailon!B42:B46) -> 103.271 | I41: =+F41-G41 -> -7.139 | K41: =1-G41/F41 -> -0.074262472 | M41: 41081
D42: Sep - Dic | E42: 130 | F42: =+E42+I41 -> 122.861 | G42: =+SUM(C.Nailon!B47:B50) -> 130.851 | I42: =+F42-G42 -> -7.99 | K42: =1-G42/F42 -> -0.065032842 | M42: 41225
A43: Camarón nailon | B43: V | C43: =SUM(E43:E45) -> 430 | D43: Ene - Mar | E43: 193 | F43: =+E43 -> 193 | G43: =+SUM(C.Nailon!B55:B57) -> 190.357 | H43: =SUM(G43:G45) -> 432.292 | I43: =+F43-G43 -> 2.643 | J43: =+C43-H43 -> -2.292 | K43: =1-G43/F43 -> 0.013694301 | L43: =1-H43/C43 -> -0.0053302326 | M43: 40986
D44: Abr - Ago | E44: 107 | F44: =+E44+I43 -> 109.643 | G44: =+SUM(C.Nailon!B58:B62) -> 100.791 | I44: =+F44-G44 -> 8.852 | K44: =1-G44/F44 -> 0.080734748 | M44: 41065
D45: Sep - Dic | E45: 130 | F45: =+E45+I44 -> 138.852 | G45: =+SUM(C.Nailon!B63:B66) -> 141.144 | I45: =+F45-G45 -> -2.292 | K45: =1-G45/F45 -> -0.016506784 | M45: 41213
A46: Camarón nailon | B46: VI | C46: =SUM(E46:E48) -> 8 | D46: Ene - Mar | E46: 4 | F46: =+E46 -> 4 | G46: =+SUM(C.Nailon!B71:B73) -> 0 | H46: =SUM(G46:G48) -> 0 | I46: =+F46-G46 -> 4 | J46: =+C46-H46 -> 8 | K46: =1-G46/F46 -> 1 | L46: =1-H46/C46 -> 1
D47: Abr - Ago | E47: 2 | F47: =+E47+I46 -> 6 | G47: =+SUM(C.Nailon!B74:B78) -> 0 | I47: =+F47-G47 -> 6 | K47: =1-G47/F47 -> 1
D48: Sep - Dic | E48: 2 | F48: =+E48+I47 -> 8 | G48: =+SUM(C.Nailon!B79:B82) -> 0 | I48: =+F48-G48 -> 8 | K48: =1-G48/F48 -> 1
A49: Camarón nailon | B49: VII | C49: =SUM(E49:E51) -> 8 | D49: Ene - Mar | E49: 4 | F49: =+E49 -> 4 | G49: =+SUM(C.Nailon!B87:B89) -> 0 | H49: =SUM(G49:G51) -> 0 | I49: =+F49-G49 -> 4 | J49: =+C49-H49 -> 8 | K49: =1-G49/F49 -> 1 | L49: =1-H49/C49 -> 1
D50: Abr - Ago | E50: 2 | F50: =+E50+I49 -> 6 | G50: =+SUM(C.Nailon!B90:B94) -> 0 | I50: =+F50-G50 -> 6 | K50: =1-G50/F50 -> 1
D51: Sep - Dic | E51: 2 | F51: =+E51+I50 -> 8 | G51: =+SUM(C.Nailon!B95:B98) -> 0 | I51: =+F51-G51 -> 8 | K51: =1-G51/F51 -> 1
A52: Camarón nailon | B52: VIII | C52: =SUM(E52:E54) -> 8 | D52: Ene - Mar | E52: 4 | F52: =+E52 -> 4 | G52: =+SUM(C.Nailon!B103:B105) -> 0 | H52: =SUM(G52:G54) -> 0 | I52: =+F52-G52 -> 4 | J52: =+C52-H52 -> 8 | K52: =1-G52/F52 -> 1 | L52: =1-H52/C52 -> 1
D53: Abr - Ago | E53: 2 | F53: =+E53+I52 -> 6 | G53: =+SUM(C.Nailon!B106:B110) -> 0 | I53: =+F53-G53 -> 6 | K53: =1-G53/F53 -> 1
D54: Sep - Dic | E54: 2 | F54: =+E54+I53 -> 8 | G54: 0 | I54: =+F54-G54 -> 8 | K54: =1-G54/F54 -> 1
A55: Congrio dorado | B55: X | C55: =SUM(E55:E56) -> 259 | D55: Ene-Feb | E55: 188 | F55: =+E55 -> 188 | G55: =+SUM('C.Dorado y fauna ac.'!B7:B8) -> 188.80143 | H55: =SUM(G55:G56) -> 261.83689 | I55: =+F55-G55 -> -0.80143111 | J55: =+C55-H55 -> -2.8368944 | K55: =1-G55/F55 -> -0.0042629314 | L55: =1-H55/C55 -> -0.01095326 | M55: 40942
D56: Mar-Dic | E56: 71 | F56: =+E56+I55 -> 70.198569 | G56: =+SUM('C.Dorado y fauna ac.'!B9:B18) -> 73.035463 | I56: =+F56-G56 -> -2.8368944 | K56: =1-G56/F56 -> -0.040412426 | M56: 41008
A57: Congrio dorado | B57: XI | C57: =SUM(E57:E58) -> 85 | D57: Ene-Feb | E57: 8 | F57: =+E57 -> 8 | G57: =+SUM('C.Dorado y fauna ac.'!B23:B24) -> 18.479 | H57: =SUM(G57:G58) -> 86.108 | I57: =+F57-G57 -> -10.479 | J57: =+C57-H57 -> -1.108 | K57: =1-G57/F57 -> -1.309875 | L57: =1-H57/C57 -> -0.013035294
D58: Mar-Dic | E58: 77 | F58: =+E58+I57 -> 66.521 | G58: =+SUM('C.Dorado y fauna ac.'!B25:B34) -> 67.629 | I58: =+F58-G58 -> -1.108 | K58: =1-G58/F58 -> -0.016656394 | M58: 41204
A59: Congrio dorado | B59: XII | C59: =SUM(E59:E60) -> 61 | D59: Ene-Feb | E59: 46 | F59: =+E59 -> 46 | G59: =+SUM('C.Dorado y fauna ac.'!B39:B40) -> 46.0955 | H59: =SUM(G59:G60) -> 62.7463 | I59: =+F59-G59 -> -0.0955 | J59: =+C59-H59 -> -1.7463 | K59: =1-G59/F59 -> -0.002076087 | L59: =1-H59/C59 -> -0.028627869 | M59: 40942
D60: Mar-Dic | E60: 15 | F60: =+E60+I59 -> 14.9045 | G60: =+SUM('C.Dorado y fauna ac.'!B41:B50) -> 16.6508 | I60: =+F60-G60 -> -1.7463 | K60: =1-G60/F60 -> -0.11716596 | M60: 41017
A61: Jurel | B61: XV y I | C61: =SUM(E61:E62) -> 875 | D61: Ene-Sept | E61: 831 | F61: =+E61 -> 831 | G61: =+SUM(Jurel!B7:B15) -> 6.95 | H61: =SUM(G61:G62) -> 8.449 | I61: =+F61-G61 -> 824.05 | J61: =+C61-H61 -> 866.551 | K61: =1-G61/F61 -> 0.99163658 | L61: =1-H61/C61 -> 0.990344
A62: JUREL | D62: Oct-Dic | E62: 44 | F62: =+E62+I61 -> 868.05 | G62: =+SUM(Jurel!B16:B18) -> 1.499 | I62: =+F62-G62 -> 866.551 | K62: =1-G62/F62 -> 0.99827314
A63: Jurel | B63: II | C63: =SUM(E63:E64) -> 875 | D63: Ene-Sept | E63: 831 | F63: =+E63 -> 831 | G63: =+SUM(Jurel!B23:B31) -> 77.795 | H63: =SUM(G63:G64) -> 107.57 | I63: =+F63-G63 -> 753.205 | J63: =+C63-H63 -> 767.43 | K63: =1-G63/F63 -> 0.90638387 | L63: =1-H63/C63 -> 0.87706286
A64: JUREL | D64: Oct-Dic | E64: 44 | F64: =+E64+I63 -> 797.205 | G64: =+SUM(Jurel!B32:B34) -> 29.775 | I64: =+F64-G64 -> 767.43 | K64: =1-G64/F64 -> 0.96265076
A65: Jurel | B65: III | C65: =SUM(E65:E66) -> 1141 | D65: Ene-Oct | E65: 1084 | F65: =+E65 -> 1084 | G65: =+SUM(Jurel!B39:B48) -> 1104.823 | H65: =SUM(G65:G66) -> 1116.061 | I65: =+F65-G65 -> -20.823 | J65: =+C65-H65 -> 24.939 | K65: =1-G65/F65 -> -0.01920941 | L65: =1-H65/C65 -> 0.021857143 | M65: 40973
A66: JUREL | D66: Nov-Dic | E66: 57 | F66: =+E66+I65 -> 36.177 | G66: =+SUM(Jurel!B49:B50) -> 11.238 | I66: =+F66-G66 -> 24.939 | K66: =1-G66/F66 -> 0.68936064
A67: Jurel | B67: IV | C67: =SUM(E67:E68) -> 2662 | D67: Ene-Oct | E67: 2529 | F67: =+E67 -> 2529 | G67: =+'Resumen RAE Jurel'!F10 -> 2322.183 | H67: =SUM(G67:G68) -> 2464.378 | I67: =+F67-G67 -> 206.817 | J67: =+C67-H67 -> 197.622 | K67: =1-G67/F67 -> 0.081778173 | L67: =1-H67/C67 -> 0.074238167
A68: JUREL | D68: Nov-Dic | E68: 133 | F68: =+E68+I67 -> 339.817 | G68: =+'Resumen RAE Jurel'!F16 -> 142.195 | I68: =+F68-G68 -> 197.622 | K68: =1-G68/F68 -> 0.58155419
A69: Jurel | B69: V (RAE por ORG) | C69: =SUM(E69:E70) -> 1253 | D69: Ene-Sept | E69: 1190 | F69: =+E69 -> 1190 | G69: =+'Resumen RAE Jurel'!F23 -> 383.892 | H69: =SUM(G69:G70) -> 395.985 | I69: =+F69-G69 -> 806.108 | J69: =+C69-H69 -> 857.015 | K69: =1-G69/F69 -> 0.67740168 | L69: =1-H69/C69 -> 0.68397047
A70: JUREL | D70: Oct-Dic | E70: 63 | F70: =+E70+I69 -> 869.108 | G70: =+'Resumen RAE Jurel'!F28 -> 12.093 | I70: =+F70-G70 -> 857.015 | K70: =1-G70/F70 -> 0.98608573
A71: Jurel | B71: VI | C71: =SUM(E71:E72) -> 5 | D71: Ene-Sept | E71: 4 | F71: =+E71 -> 4 | G71: =+SUM(Jurel!B55:B63) -> 0.413 | H71: =SUM(G71:G72) -> 0.463 | I71: =+F71-G71 -> 3.587 | J71: =+C71-H71 -> 4.537 | K71: =1-G71/F71 -> 0.89675 | L71: =1-H71/C71 -> 0.9074
A72: JUREL | D72: Oct-Dic | E72: 1 | F72: =+E72+I71 -> 4.587 | G72: =+SUM(Jurel!B64:B66) -> 0.05 | I72: =+F72-G72 -> 4.537 | K72: =1-G72/F72 -> 0.98909963
A73: Jurel | B73: VII | C73: =SUM(E73:E74) -> 41 | D73: Ene-Sept | E73: 39 | F73: =+E73 -> 39 | G73: =+SUM(Jurel!B71:B79) -> 14.568 | H73: =SUM(G73:G74) -> 14.818 | I73: =+F73-G73 -> 24.432 | J73: =+C73-H73 -> 26.182 | K73: =1-G73/F73 -> 0.62646154 | L73: =1-H73/C73 -> 0.63858537
A74: JUREL | D74: Oct-Dic | E74: 2 | F74: =+E74+I73 -> 26.432 | G74: =+SUM(Jurel!B80:B82) -> 0.25 | I74: =+F74-G74 -> 26.182 | K74: =1-G74/F74 -> 0.99054177
A75: Jurel | B75: VIII | C75: =SUM(E75:E76) -> 2671 | D75: Ene-Sept | E75: 2537 | F75: =+E75 -> 2537 | G75: =+SUM(Jurel!B87:B95) -> 2495.13 | H75: =SUM(G75:G76) -> 2670.063 | I75: =+F75-G75 -> 41.87 | J75: =+C75-H75 -> 0.937 | K75: =1-G75/F75 -> 0.016503745 | L75: =1-H75/C75 -> 0.00035080494 | M75: 41164
A76: JUREL | D76: Oct-Dic | E76: 134 | F76: =+E76+I75 -> 175.87 | G76: =+SUM(Jurel!B96:B98) -> 174.933 | I76: =+F76-G76 -> 0.937 | K76: =1-G76/F76 -> 0.0053277989 | M76: 41267
A77: Jurel | B77: IX | C77: =SUM(E77:E78) -> 60 | D77: Ene-Sept | E77: 57 | F77: =+E77 -> 57 | G77: =+SUM(Jurel!B112:B114) -> 0 | H77: =SUM(G77:G78) -> 0 | I77: =+F77-G77 -> 57 | J77: =+C77-H77 -> 60 | K77: =1-G77/F77 -> 1 | L77: =1-H77/C77 -> 1
A78: JUREL | D78: Oct-Dic | E78: 3 | F78: =+E78+I77 -> 60 | G78: =+SUM(Jurel!B106:B108) -> 0 | I78: =+F78-G78 -> 60 | K78: =1-G78/F78 -> 1
A79: Jurel | B79: XIV (RAE por Org) | C79: =SUM(E79:E80) -> 312 | D79: Ene-Sept | E79: 296 | F79: =+E79 -> 296 | G79: =+'Resumen RAE Jurel'!F51 -> 0.528 | H79: =SUM(G79:G80) -> 0.528 | I79: =+F79-G79 -> 295.472 | J79: =+C79-H79 -> 311.472 | K79: =1-G79/F79 -> 0.99821622 | L79: =1-H79/C79 -> 0.99830769
A80: JUREL | D80: Oct-Dic | E80: 16 | F80: =+E80+I79 -> 311.472 | G80: =+'Resumen RAE Jurel'!F71 -> 0 | I80: =+F80-G80 -> 311.472 | K80: =1-G80/F80 -> 1
A81: Jurel | B81: X (RAE por Org) | C81: =SUM(E81:E82) -> 2090 | D81: Ene-Sept | E81: 1985 | F81: =+E81 -> 1985 | G81: =+SUM('Resumen RAE Jurel'!F86) -> 608.221 | H81: =SUM(G81:G82) -> 608.221 | I81: =+F81-G81 -> 1376.779 | J81: =+C81-H81 -> 1481.779 | K81: =1-G81/F81 -> 0.69359144 | L81: =1-H81/C81 -> 0.70898517
A82: JUREL | D82: Oct-Dic | E82: 105 | F82: =+E82+I81 -> 1481.779 | G82: =+SUM('Resumen RAE Jurel'!F99) -> 0 | I82: =+F82-G82 -> 1481.779 | K82: =1-G82/F82 -> 1
A83: Jibia | B83: XV- XII regs. | C83: =+E83 -> 138240 | D83: Ene-dic | E83: 138240 | F83: =+E83 -> 138240 | G83: =+SUM('resumen Jibia XV a XII'!E19) -> 100599.54 | H83: =+G83 -> 100599.54 | I83: =+F83-G83 -> 37640.461 | J83: =+C83-G83 -> 37640.461 | K83: =1-G83/F83 -> 0.27228343 | L83: =1-H83/C83 -> 0.27228343
A84: Langostino amarillo | B84: III | C84: =SUM(E84:E86) -> 196 | D84: Abr - Jun | E84: 98 | F84: =+E84 -> 98 | G84: =+SUM(L.Amarillo!B10:B12) -> 0 | H84: =SUM(G84:G86) -> 13.638 | I84: =+F84-G84 -> 98 | J84: =+C84-H84 -> 182.362 | K84: =1-G84/F84 -> 1 | L84: =1-H84/C84 -> 0.93041837
D85: Jul - Sep | E85: 59 | F85: =+E85+I84 -> 157 | G85: =+SUM(L.Amarillo!B13:B15) -> 13.638 | I85: =+F85-G85 -> 143.362 | K85: =1-G85/F85 -> 0.91313376
D86: Oct - Dic | E86: 39 | F86: =+E86+I85 -> 182.362 | G86: =+SUM(L.Amarillo!B16:B18) -> 0 | I86: =+F86-G86 -> 182.362 | K86: =1-G86/F86 -> 1
A87: Langostino amarillo | B87: IV | C87: =SUM(E87:E89) -> 781 | D87: Abr - Jun | E87: 391 | F87: =+E87 -> 391 | G87: =+SUM(L.Amarillo!B26:B28) -> 404.573 | H87: =SUM(G87:G89) -> 817.722 | I87: =+F87-G87 -> -13.573 | J87: =+C87-H87 -> -36.722 | K87: =1-G87/F87 -> -0.034713555 | L87: =1-H87/C87 -> -0.047019206 | M87: 41048
D88: Jul - Sep | E88: 234 | F88: =+E88+I87 -> 220.427 | G88: =+SUM(L.Amarillo!B29:B31) -> 237.848 | I88: =+F88-G88 -> -17.421 | K88: =1-G88/F88 -> -0.079032968 | M88: 41115
D89: Oct - Dic | E89: 156 | F89: =+E89+I88 -> 138.579 | G89: =+SUM(L.Amarillo!B32:B34) -> 175.301 | I89: =+F89-G89 -> -36.722 | K89: =1-G89/F89 -> -0.26498964 | M89: 41206
A90: Langostino colorado | B90: II | C90: =SUM(E90:E92) -> 20 | D90: Abr - Jun | E90: 10 | F90: =+E90 -> 10 | G90: =+SUM(L.colorado!B10:B12) -> 0 | H90: =SUM(G90:G92) -> 0 | I90: =+F90-G90 -> 10 | J90: =+C90-H90 -> 20 | K90: =1-G90/F90 -> 1 | L90: =1-H90/C90 -> 1
D91: Jul - Sep | E91: 7 | F91: =+E91+I90 -> 17 | G91: =+SUM(L.colorado!B13:B15) -> 0 | I91: =+F91-G91 -> 17 | K91: =1-G91/F91 -> 1
D92: Oct - Dic | E92: 3 | F92: =+E92+I91 -> 20 | G92: =+SUM(L.colorado!B16:B18) -> 0 | I92: =+F92-G92 -> 20 | K92: =1-G92/F92 -> 1
A93: Langostino colorado | B93: III | C93: =SUM(E93:E95) -> 150 | D93: Abr - Jun | E93: 75 | F93: =+E93 -> 75 | G93: =+SUM(L.colorado!B26:B28) -> 0 | H93: =SUM(G93:G95) -> 0 | I93: =+F93-G93 -> 75 | J93: =+C93-H93 -> 150 | K93: =1-G93/F93 -> 1 | L93: =1-H93/C93 -> 1
D94: Jul - Sep | E94: 53 | F94: =+E94+I93 -> 128 | G94: =+SUM(L.colorado!B29:B31) -> 0 | I94: =+F94-G94 -> 128 | K94: =1-G94/F94 -> 1
D95: Oct - Dic | E95: 22 | F95: =+E95+I94 -> 150 | G95: =+SUM(L.colorado!B32:B34) -> 0 | I95: =+F95-G95 -> 150 | K95: =1-G95/F95 -> 1
A96: Langostino colorado | B96: IV | C96: =SUM(E96:E98) -> 515 | D96: Abr - Jun | E96: 258 | F96: =+E96 -> 258 | G96: =+SUM(L.colorado!B42:B44) -> 264.566 | H96: =SUM(G96:G98) -> 516.566 | I96: =+F96-G96 -> -6.566 | J96: =+C96-H96 -> -1.566 | K96: =1-G96/F96 -> -0.025449612 | L96: =1-H96/C96 -> -0.0030407767 | M96: 41080
D97: Jul - Sep | E97: 180 | F97: =+E97+I96 -> 173.434 | G97: =+SUM(L.colorado!B45:B47) -> 182.489 | I97: =+F97-G97 -> -9.055 | K97: =1-G97/F97 -> -0.052210063 | M97: 41141
D98: Oct - Dic | E98: 77 | F98: =+E98+I97 -> 67.945 | G98: =+SUM(L.colorado!B48:B50) -> 69.511 | I98: =+F98-G98 -> -1.566 | K98: =1-G98/F98 -> -0.023048054 | M98: 41213
A99: Merluza común | B99: IV Norte | C99: =SUM(E99:E104) -> 665.964 | D99: Ene - Jun | E99: =+'Resumen RAE Merluza'!C8 -> 19.345 | F99: =+E99 -> 19.345 | G99: =+'Resumen RAE Merluza'!E8 -> 3.416 | H99: =SUM(G99:G100) -> 3.416 | I99: =+F99-G99 -> 15.929 | J99: =+C99-H99 -> 662.548 | K99: =1-G99/F99 -> 0.8234169 | L99: =1-H99/C99 -> 0.99487059
D100: Jul - Dic | E100: =+'Resumen RAE Merluza'!C14 -> 6.448 | F100: =+E100+I99 -> 22.377 | G100: =+'Resumen RAE Merluza'!E14 -> 0 | I100: =+F100-G100 -> 22.377 | K100: =1-G100/F100 -> 1
B101: IV Centro | D101: Ene - Jun | E101: =+'Resumen RAE Merluza'!C9 -> 415.619 | F101: =+E101+I100 -> 437.996 | G101: =+'Resumen RAE Merluza'!E9 -> 307.387 | H101: =SUM(G101:G102) -> 510.266 | I101: =+F101-G101 -> 130.609 | K101: =1-G101/F101 -> 0.29819679
D102: Jul - Dic | E102: =+'Resumen RAE Merluza'!C15 -> 138.54 | F102: =+E102+I101 -> 269.149 | G102: =+'Resumen RAE Merluza'!E15 -> 202.879 | I102: =+F102-G102 -> 66.27 | K102: =1-G102/F102 -> 0.24622049
...

Sheet Resumen RAE Anchoveta
A2: Resumen RAE Anchoveta 2012
A4: IV Región, de Coquimbo
A6: Organización | B6: Periodo | C6: Cuota asignada (t) | D6: TRAPASOS | E6: Cuota efectiva (t) | F6: Desembarque (t) | G6: Saldo (t) | H6: % | I6: Fecha de Cierre
A7: Cooperativa de Armadores Cerqueros IV Región | B7: Ene-Oct | C7: 8321 | E7: =+C7 -> 8321 | F7: =+SUM('RAE Anchoveta'!B8:B17) -> 8387.066 | G7: =+E7-F7 -> -66.066 | H7: =+G7/E7 -> -0.0079396707 | I7: 41207
A8: A.G. de pescadores Art. Y Buzos Marisc. De Coquimbo IV Región | B8: Ene-Oct | C8: 56 | E8: =+C8 -> 56 | F8: =+SUM('RAE Anchoveta'!B24:B33) -> 2.92 | G8: =+E8-F8 -> 53.08 | H8: =+G8/E8 -> 0.94785714
A9: Cuota Residual - Bolson | B9: Ene-Oct | C9: 16 | E9: =+C9 -> 16 | F9: =+SUM('RAE Anchoveta'!B40:B49) -> 93.701 | G9: =+E9-F9 -> -77.701 | H9: =+G9/E9 -> -4.8563125 | I9: 41033
A10: Total | B10: Ene-Oct | C10: =SUM(C7:C9) -> 8393 | E10: =SUM(E7:E9) -> 8393 | F10: =SUM(F7:F9) -> 8483.687 | G10: =+E10-F10 -> -90.687
A12: Organización | B12: Periodo | C12: Cuota asignada (t) | E12: Cuota efectiva (t) | F12: Desembarque (t) | G12: Saldo (t) | H12: % | I12: Fecha de Cierre
A13: Cooperativa de Armadores Cerqueros IV Región | B13: Nov-Dic | C13: 438 | E13: =+C13+G7 -> 371.934 | F13: =+SUM('RAE Anchoveta'!B18:B19) -> 45.09 | G13: =+E13-F13 -> 326.844 | H13: =+G13/E13 -> 0.87876881
A14: A.G. de pescadores Art. Y Buzos Marisc. De Coquimbo IV Región | B14: Nov-Dic | C14: 3 | E14: =+C14+G8 -> 56.08 | F14: =+SUM('RAE Anchoveta'!B34:B35) -> 2 | G14: =+E14-F14 -> 54.08 | H14: =+G14/E14 -> 0.96433666
A15: Cuota Residual - Bolson | B15: Nov-Dic | C15: 1 | E15: =+C15+G9 -> -76.701 | F15: =+SUM('RAE Anchoveta'!B50:B51) -> 0 | G15: =+E15-F15 -> -76.701 | H15: =+G15/E15 -> 1 | I15: 41218
A16: Total | B16: Nov-Dic | C16: =SUM(C13:C15) -> 442 | E16: =+C16+G10 -> 351.313 | F16: =SUM(F13:F15) -> 47.09 | G16: =+E16-F16 -> 304.223
A18: V Región, de Valparaíso
A20: Organización | B20: Periodo | C20: Cuota asignada (t) | E20: Cuota efectiva (t) | F20: Desembarque (t) | G20: Saldo (t) | H20: % | I20: Fecha de Cierre
A21: A.G. Armadores Artesanales San Antonio R.A.G. 2510 | B21: Ene-Abr | C21: 2026 | E21: =+C21 -> 2026 | F21: =+SUM('RAE Anchoveta'!B58:B61) -> 706.441 | G21: =+E21-F21 -> 1319.559 | H21: =+G21/E21 -> 0.65131244
A22: Pescadores artesanales no afiliados | B22: Ene-Abr | C22: 23 | E22: =+C22 -> 23 | F22: =+SUM('RAE Anchoveta'!B74:B77) -> 36.095 | G22: =+E22-F22 -> -13.095 | H22: =+G22/E22 -> -0.56934783 | I22: 41031
A23: Total | B23: Ene-Abr | C23: =SUM(C21:C22) -> 2049 | E23: =SUM(E21:E22) -> 2049 | F23: =SUM(F21:F22) -> 742.536 | G23: =+E23-F23 -> 1306.464
A25: Organización | B25: Periodo | C25: Cuota asignada (t) | E25: Cuota efectiva (t) | F25: Desembarque (t) | G25: Saldo (t) | H25: % | I25: Fecha de Cierre
A26: A.G. Armadores Artesanales San Antonio R.A.G. 2510 | B26: May-Ago | C26: 238 | E26: =+C26+G21 -> 1557.559 | F26: =+SUM('RAE Anchoveta'!B62:B65) -> 865.055 | G26: =+E26-F26 -> 692.504 | H26: =+G26/E26 -> 0.44460852
A27: Pescadores artesanales no afiliados | B27: May-Ago | C27: 3 | E27: =+C27+G22 -> -10.095 | F27: =+SUM('RAE Anchoveta'!B78:B81) -> 0 | G27: =+E27-F27 -> -10.095 | H27: 0 | I27: 41031
A28: Total | B28: May-Ago | C28: =SUM(C26:C27) -> 241 | E28: =+C28+G23 -> 1547.464 | F28: =SUM(F26:F27) -> 865.055 | G28: =+E28-F28 -> 682.409
A30: Organización | B30: Periodo | C30: Cuota asignada (t) | E30: Cuota efectiva (t) | F30: Desembarque (t) | G30: Saldo (t) | H30: % | I30: Fecha de Cierre
A31: A.G. Armadores Artesanales San Antonio R.A.G. 2510 | B31: Sep-Dic | C31: 119 | E31: =+C31+G26 -> 811.504 | F31: =+SUM('RAE Anchoveta'!B66:B69) -> 802.11 | G31: =+E31-F31 -> 9.394 | H31: =+G31/E31 -> 0.011576037 | J31: atención
A32: Pescadores artesanales no afiliados | B32: Sep-Dic | C32: 1 | E32: =+C32+G27 -> -9.095 | F32: =+SUM('RAE Anchoveta'!B82:B85) -> 0 | G32: =+E32-F32 -> -9.095 | H32: 0 | I32: 41031
A33: Total | B33: Sep-Dic | C33: =SUM(C31:C32) -> 120 | E33: =+C33+G28 -> 802.409 | F33: =SUM(F31:F32) -> 802.11 | G33: =+E33-F33 -> 0.299
C34: =+C21+C26+C31 -> 2383 | E34: =+C34 -> 2383 | F34: =+F21+F26+F31 -> 2373.606 | G34: =+C34-F34 -> 9.394 | H34: =+G34/E34 -> 0.0039420898
A35: VII Región, deL Maule
A37: Organización | B37: Periodo | C37: Cuota asignada (t) | D37: TRASPASOS | E37: Cuota efectiva (t) | F37: Desembarque (t) | G37: Saldo (t) | H37: % | I37: Fecha de Cierre
A38: STI:.de Pescadores "Pelágicos del Maule" Constitución, R.S.U. N° 07050150 | B38: Ene-Abr | C38: 206.1 | E38: =+C38 -> 206.1 | F38: =+SUM('RAE Anchoveta'!B91:B94) -> 333.606 | G38: =+E38-F38 -> -127.506 | H38: =+G38/E38 -> -0.61866084 | I38: 41029
A39: Cuota Residual | B39: Ene-Abr | C39: 12.9 | E39: =+C39 -> 12.9 | F39: =+SUM('RAE Anchoveta'!B107:B110) -> 119.546 | G39: =+E39-F39 -> -106.646 | H39: =+G39/E39 -> -8.2671318 | I39: 41031
A40: Total | B40: Ene-Abr | C40: =SUM(C38:C39) -> 219 | E40: =SUM(E38:E39) -> 219 | F40: =SUM(F38:F39) -> 453.152 | G40: =+E40-F40 -> -234.152
A42: Organización | B42: Periodo | C42: Cuota asignada (t) | E42: Cuota efectiva (t) | F42: Desembarque (t) | G42: Saldo (t) | H42: % | I42: Fecha de Cierre
A43: STI:.de Pescadores "Pelágicos del Maule" Constitución, R.S.U. N° 07050150 | B43: May-Ago | C43: 24.5 | E43: =+C43+G38 -> -103.006 | F43: =+SUM('RAE Anchoveta'!B95:B98) -> 61.3 | G43: =+E43-F43 -> -164.306 | H43: 0 | I43: 41029
A44: Cuota Residual | B44: May-Ago | C44: 1.5 | E44: =+C44+G39 -> -105.146 | F44: =+SUM('RAE Anchoveta'!B111:B114) -> 2.166 | G44: =+E44-F44 -> -107.312 | H44: 0 | I44: 41031
A45: Total | B45: May-Ago | C45: =SUM(C43:C44) -> 26 | E45: =+C45+G40 -> -208.152 | F45: =SUM(F43:F44) -> 63.466 | G45: =+E45-F45 -> -271.618
A47: Organización | B47: Periodo | C47: Cuota asignada (t) | E47: Cuota efectiva (t) | F47: Desembarque (t) | G47: Saldo (t) | H47: % | I47: Fecha de Cierre
A48: STI:.de Pescadores "Pelágicos del Maule" Constitución, R.S.U. N° 07050150 | B48: Sep-Dic | C48: 12.2 | E48: =+C48+G43 -> -152.106 | F48: =+SUM('RAE Anchoveta'!B99:B102) -> 0 | G48: =+E48-F48 -> -152.106 | H48: 0 | I48: 41029
A49: Cuota Residual | B49: Sep-Dic | C49: 0.8 | E49: =+C49+G44 -> -106.512 | F49: =+SUM('RAE Anchoveta'!B115:B118) -> 0 | G49: =+E49-F49 -> -106.512 | H49: 0 | I49: 41031
A50: Total | B50: Sep-Dic | C50: =SUM(C48:C49) -> 13 | E50: =+C50+G45 -> -258.618 | F50: =SUM(F48:F49) -> 0 | G50: =+E50-F50 -> -258.618
A52: VIII Región, del Bio Bio | G52: 41011
A54: Organización | B54: Periodo | C54: Cuota asignada (t) | D54: traspasos | E54: Cuota efectiva (t) | F54: Desembarque (t) | G54: Saldo (t) | H54: % | I54: Fecha de Cierre
A55: Caleta Tubul.R.O.Comunitaria Funcional 478-2007 | B55: Ene-Ago | C55: 92 | D55: -20.2 | E55: =+C55+D55 -> 71.8 | F55: 16.838 | G55: =+E55-F55 -> 54.962 | H55: =+G55/E55 -> 0.76548747 | J55: 1
A56: AGREPAR BIO BIO A.G 468-8 | B56: Ene-Ago | C56: 204 | E56: =+C56 -> 204 | F56: 438.668 | G56: =+E56-F56 -> -234.668 | H56: =+G56/E56 -> -1.1503333 | I56: 41031 | J56: =+J55+1 -> 2
A57: ARPESCA R.A.G. 429-8 | B57: Ene-Ago | C57: 463 | E57: =+C57 -> 463 | F57: 219.601 | G57: =+E57-F57 -> 243.399 | H57: =+G57/E57 -> 0.52569978 | J57: =+J56+1 -> 3
A58: ARPES BIO BIO R.A.G.445-8 | B58: Ene-Ago | C58: 1137 | E58: =+C58 -> 1137 | F58: 1628.876 | G58: =+E58-F58 -> -491.876 | H58: =+G58/E58 -> -0.43260862 | I58: 41031 | J58: =+J57+1 -> 4
A59: SIARPAR R.A.G.448-8 | B59: Ene-Ago | C59: 88 | E59: =+C59 -> 88 | F59: 252.738 | G59: =+E59-F59 -> -164.738 | H59: =+G59/E59 -> -1.8720227 | I59: 41016 | J59: =+J58+1 -> 5
A60: ARMAR R.A.G. 384-8 | B60: Ene-Ago | C60: 859 | E60: =+C60 -> 859 | F60: 1262.93 | G60: =+E60-F60 -> -403.93 | H60: =+G60/E60 -> -0.47023283 | I60: 41031 | J60: =+J59+1 -> 6
A61: AGEMAPAR R.A.G.376-8 | B61: Ene-Ago | C61: 898 | E61: =+C61 -> 898 | F61: 1071.92 | G61: =+E61-F61 -> -173.92 | H61: =+G61/E61 -> -0.19367483 | I61: 41038 | J61: =+J60+1 -> 7
A62: ARPROPELAR R.A.G.353-8 | B62: Ene-Ago | C62: 703 | E62: =+C62 -> 703 | F62: 2112.964 | G62: =+E62-F62 -> -1409.964 | H62: =+G62/E62 -> -2.0056387 | I62: 41031 | J62: =+J61+1 -> 8
A63: ITALMAR R.A.G.392-8 | B63: Ene-Ago | C63: 274 | E63: =+C63 -> 274 | F63: 309.115 | G63: =+E63-F63 -> -35.115 | H63: =+G63/E63 -> -0.12815693 | I63: 41036 | J63: =+J62+1 -> 9
A64: A.G. Pescadores Artesanales de Coronel R.A.G.5-8 | B64: Ene-Ago | C64: 2528 | E64: =+C64 -> 2528 | F64: 2356.701 | G64: =+E64-F64 -> 171.299 | H64: =+G64/E64 -> 0.06776068 | J64: =+J63+1 -> 10
A65: A.G.APESCA R.A.G. 428-8 | B65: Ene-Ago | C65: 154 | E65: =+C65 -> 154 | F65: 194.886 | G65: =+E65-F65 -> -40.886 | H65: =+G65/E65 -> -0.26549351 | I65: 41038 | J65: =+J64+1 -> 11
A66: A.G. Pescadores Artesanales de San Vicente R.A.G.18-8 | B66: Ene-Ago | C66: 464 | E66: =+C66 -> 464 | F66: 818.061 | G66: =+E66-F66 -> -354.061 | H66: =+G66/E66 -> -0.7630625 | I66: 41031 | J66: =+J65+1 -> 12
A67: A.G. Pesc. Art. VIII reg. AGREPESCA R.A.G. N° 396-8 | B67: Ene-Ago | C67: 0 | E67: =+C67 -> 0 | F67: 0 | G67: =+E67-F67 -> 0 | H67: =+G67/E67 -> #DIV/0! | J67: =+J66+1 -> 13
A68: PESCA MAR R.A.G. 450-8 | B68: Ene-Ago | C68: 860 | E68: =+C68 -> 860 | F68: 1692.225 | G68: =+E68-F68 -> -832.225 | H68: =+G68/E68 -> -0.96770349 | I68: 41031 | J68: =+J67+1 -> 14
A69: GEMAR R.A.G.464-8 | B69: Ene-Ago | C69: 514 | E69: =+C69 -> 514 | F69: 1102.167 | G69: =+E69-F69 -> -588.167 | H69: =+G69/E69 -> -1.1442938 | I69: 41031 | J69: =+J68+1 -> 15
A70: ARPESCA R.A.G.447-8 | B70: Ene-Ago | C70: 1673 | E70: =+C70 -> 1673 | F70: 1328.149 | G70: =+E70-F70 -> 344.851 | H70: =+G70/E70 -> 0.20612732 | J70: =+J69+1 -> 16
A71: Cooperativa Pelilleros Isla Sta. María Ltda. Rol 1826 | B71: Ene-Ago | C71: 29 | E71: =+C71 -> 29 | F71: 13.728 | G71: =+E71-F71 -> 15.272 | H71: =+G71/E71 -> 0.52662069 | J71: =+J70+1 -> 17
A72: Cooperativa GEVIMAR. Rol 4465 | B72: Ene-Ago | C72: =455 -> 455 | E72: =+C72 -> 455 | F72: 343.074 | G72: =+E72-F72 -> 111.926 | H72: =+G72/E72 -> 0.24599121 | J72: =+J71+1 -> 18
A73: STI.Lo Rojas y Caletas del Golfo de Arauco.R.S.U.08.07.0307 | B73: Ene-Ago | C73: 917 | D73: =-137-3.74 -> -140.74 | E73: =+C73+D73 -> 776.26 | F73: 868.257 | G73: =+E73-F73 -> -91.997 | H73: =+G73/E73 -> -0.11851313 | I73: 41036 | J73: =+J72+1 -> 19
A74: STI. SPAADA. R.S.U. 08.05.0339 | B74: Ene-Ago | C74: 1156 | E74: =+C74 -> 1156 | F74: 1604.179 | G74: =+E74-F74 -> -448.179 | H74: =+G74/E74 -> -0.3876981 | I74: 41031 | J74: =+J73+1 -> 20
A75: STI. Pesc. Art. AR: Pelg. Y Act. Caleta Coliumo Reg. 08.06.0113 | B75: Ene-Ago | C75: 248 | E75: =+C75 -> 248 | F75: 519.556 | G75: =+E75-F75 -> -271.556 | H75: =+G75/E75 -> -1.0949839 | I75: 41031 | J75: =+J74+1 -> 21
A76: STI. SIPARMAR R.S.U.08.05.0399 | B76: Ene-Ago | C76: 444.9 | E76: =+C76 -> 444.9 | F76: 1094.708 | G76: =+E76-F76 -> -649.808 | H76: =+G76/E76 -> -1.4605709 | I76: 41031 | J76: =+J75+1 -> 22
A77: STI. Brisas del Mar R.S.U.08.04.0115 | B77: Ene-Ago | C77: 0 | E77: =+C77 -> 0 | F77: 0 | G77: =+E77-F77 -> 0 | H77: =+G77/E77 -> #DIV/0! | J77: =+J76+1 -> 23
A78: SIARPEMAR R.S.U.08.05.0459 | B78: Ene-Ago | C78: 182 | E78: =+C78 -> 182 | F78: 564.493 | G78: =+E78-F78 -> -382.493 | H78: =+G78/E78 -> -2.1016099 | I78: 41031 | J78: =+J77+1 -> 24
A79: STI. SARPAR BIO BIO. R.S.U. 08.05.0378 | B79: Ene-Ago | C79: 144 | E79: =+C79 -> 144 | F79: 158.89 | G79: =+E79-F79 -> -14.89 | H79: =+G79/E79 -> -0.10340278 | I79: 41039 | J79: =+J78+1 -> 25
A80: STI. SITRAL. R.S.U.08.07.0322 | B80: Ene-Ago | C80: 268 | E80: =+C80 -> 268 | F80: 47.917 | G80: =+E80-F80 -> 220.083 | H80: =+G80/E80 -> 0.82120522 | J80: =+J79+1 -> 26
A81: STI. Arm. Pes. Art. Y Ramas . Reg. 08.05.0512 | B81: Ene-Ago | C81: 297 | E81: =+C81 -> 297 | F81: 580.762 | G81: =+E81-F81 -> -283.762 | H81: =+G81/E81 -> -0.95542761 | I81: 41031 | J81: =+J80+1 -> 27
A82: STI. Hermandad de la Costa. R.S.U. 08.05.0404 | B82: Ene-Ago | C82: 55 | E82: =+C82 -> 55 | F82: 69.47 | G82: =+E82-F82 -> -14.47 | H82: =+G82/E82 -> -0.26309091 | I82: 41031 | J82: =+J81+1 -> 28
A83: STI. MAR AZUL. R.S.U. 08.05.0434 | B83: Ene-Ago | C83: 330 | E83: =+C83 -> 330 | F83: 514.54 | G83: =+E83-F83 -> -184.54 | H83: =+G83/E83 -> -0.55921212 | I83: 41031 | J83: =+J82+1 -> 29
A84: STI. Sindicato Tsunami R.S.U. 08.05.0428 | B84: Ene-Ago | C84: =474 -> 474 | E84: =+C84 -> 474 | F84: 982.182 | G84: =+E84-F84 -> -508.182 | H84: =+G84/E84 -> -1.0721139 | I84: 41031 | J84: =+J83+1 -> 30
A85: STI. Caleta Lo Rojas R.S.U 08.07.0287 | B85: Ene-Ago | C85: 29 | E85: =+C85 -> 29 | F85: 3.248 | G85: =+E85-F85 -> 25.752 | H85: =+G85/E85 -> 0.888 | J85: =+J84+1 -> 31
A86: STI. Merluceros y afines Caleta Lo Rojas. R.S.U.08.07.0227 | B86: Ene-Ago | C86: 38 | E86: =+C86 -> 38 | F86: 4.582 | G86: =+E86-F86 -> 33.418 | H86: =+G86/E86 -> 0.87942105 | J86: =+J85+1 -> 32
A87: STI. SIPARMARCEA. R.S.U.08.05.0430 | B87: Ene-Ago | C87: 443 | E87: =+C87 -> 443 | F87: 935.197 | G87: =+E87-F87 -> -492.197 | H87: =+G87/E87 -> -1.1110542 | I87: 41031 | J87: =+J86+1 -> 33
A88: STI. APAT. R.S.U.08.05.0380 | B88: Ene-Ago | C88: 186 | E88: =+C88 -> 186 | F88: 123.503 | G88: =+E88-F88 -> 62.497 | H88: =+G88/E88 -> 0.33600538 | J88: =+J87+1 -> 34
A89: STI. Caleta Tumbes. R.S.U.08.05.0057 | B89: Ene-Ago | C89: 1320 | E89: =+C89 -> 1320 | F89: 1828.17 | G89: =+E89-F89 -> -508.17 | H89: =+G89/E89 -> -0.38497727 | I89: 41031 | J89: =+J88+1 -> 35
A90: STI. SPARHITAL. R.S.U.08.05.0382 | B90: Ene-Ago | C90: 209 | E90: =+C90 -> 209 | F90: 228.435 | G90: =+E90-F90 -> -19.435 | H90: =+G90/E90 -> -0.092990431 | I90: 41039 | J90: =+J89+1 -> 36
A91: STI. Peninsula de Tumbes. R.S.U.08.05.0391 | B91: Ene-Ago | C91: 498 | E91: =+C91 -> 498 | F91: 632.925 | G91: =+E91-F91 -> -134.925 | H91: =+G91/E91 -> -0.27093373 | I91: 41031 | J91: =+J90+1 -> 37
A92: STI. Los Bagres.R.S.U.08.06.0024 | B92: Ene-Ago | C92: 38 | D92: -18 | E92: =+C92+D92 -> 20 | F92: 1.909 | G92: =+E92-F92 -> 18.091 | H92: =+G92/E92 -> 0.90455 | J92: =+J91+1 -> 38
A93: STI. Patrones y tripulantes Caleta Cocholgüe R.S.U08.0601.06 | B93: Ene-Ago | C93: 211 | D93: -50 | E93: =+C93+D93 -> 161 | F93: 35.957 | G93: =+E93-F93 -> 125.043 | H93: =+G93/E93 -> 0.7766646 | J93: =+J92+1 -> 39
A94: STI. Puerto de Coronel y el Golfo de Arauco. R.S.U.08.07.0183 | B94: Ene-Ago | C94: 816 | D94: -1 | E94: =+C94+D94 -> 815 | F94: 902.716 | G94: =+E94-F94 -> -87.716 | H94: =+G94/E94 -> -0.10762699 | I94: 41052 | J94: =+J93+1 -> 40
A95: STI. Caleta Lota Bajo. R.S.U.08.07.0106 | B95: Ene-Ago | C95: 583 | E95: =+C95 -> 583 | F95: 619.723 | G95: =+E95-F95 -> -36.723 | H95: =+G95/E95 -> -0.062989708 | I95: 41031 | J95: =+J94+1 -> 41
A96: STI. Caleta Cocholgüe. R.S.U.08.06.0023 | B96: Ene-Ago | C96: 38 | E96: =+C96 -> 38 | F96: 10.887 | G96: =+E96-F96 -> 27.113 | H96: =+G96/E96 -> 0.7135 | J96: =+J95+1 -> 42
A97: STI. Caleta Coliumo. R.S.U.08.06.0027 | B97: Ene-Ago | C97: 1399 | E97: =+C97 -> 1399 | F97: 2909.728 | G97: =+E97-F97 -> -1510.728 | H97: =+G97/E97 -> -1.0798628 | I97: 41031 | J97: =+J96+1 -> 43
A98: STI. SIPARMA LOTA. R.S.U.08.07.0306 | B98: Ene-Ago | C98: 527 | E98: =+C98 -> 527 | F98: 1252.932 | G98: =+E98-F98 -> -725.932 | H98: =+G98/E98 -> -1.3774801 | I98: 41010 | J98: =+J97+1 -> 44
A99: STI. Comuna Talcahuano R.S.U.08.05.0487 | B99: Ene-Ago | C99: 120 | E99: =+C99 -> 120 | F99: 166.953 | G99: =+E99-F99 -> -46.953 | H99: =+G99/E99 -> -0.391275 | I99: 41012 | J99: =+J98+1 -> 45
A100: STI.SIPESMAFESA. R.S.U. 08.07.0332 | B100: Ene-Ago | C100: 439 | E100: =+C100 -> 439 | F100: 732.892 | G100: =+E100-F100 -> -293.892 | H100: =+G100/E100 -> -0.66945786 | I100: 41031 | J100: =+J99+1 -> 46
A101: STI. SIPARMA CORONEL. R.S.U.08.07.0271 | B101: Ene-Ago | C101: 416 | E101: =+C101 -> 416 | F101: 514.915 | G101: =+E101-F101 -> -98.915 | H101: =+G101/E101 -> -0.23777644 | I101: 41064 | J101: =+J100+1 -> 47
A102: STI. SIPEAYRAS. R.S.U.08.07.0296 | B102: Ene-Ago | C102: 904 | E102: =+C102 -> 904 | F102: 912.927 | G102: =+E102-F102 -> -8.927 | H102: =+G102/E102 -> -0.009875 | I102: 41052 | J102: =+J101+1 -> 48
A103: STI. Arm. ,Buzos Acui. Y ram . SIPEARBUCOR Reg. 08.07.0376 | B103: Ene-Ago | C103: 36 | D103: -15 | E103: =+C103+D103 -> 21 | F103: 0 | G103: =+E103-F103 -> 21 | H103: =+G103/E103 -> 1 | J103: =+J102+1 -> 49
A104: STI. Caletas Tomé y Quichiuto. R.S.U.08.06.0043 | B104: Ene-Ago | C104: 288 | E104: =+C104 -> 288 | F104: 570.816 | G104: =+E104-F104 -> -282.816 | H104: =+G104/E104 -> -0.982 | I104: 41036 | J104: =+J103+1 -> 50
A105: STI. Pecs. Arm. Pelg. Pat. De Com. Talcahuano Reg. 08-05-0474 | B105: Ene-Ago | C105: 556 | E105: =+C105 -> 556 | F105: 912.285 | G105: =+E105-F105 -> -356.285 | H105: =+G105/E105 -> -0.64080036 | I105: 41031 | J105: =+J104+1 -> 51
A106: STI. Río Maipo R.S.U.08.05.0488 | B106: Ene-Ago | C106: 168 | E106: =+C106 -> 168 | F106: 238.035 | G106: =+E106-F106 -> -70.035 | H106: =+G106/E106 -> -0.416875 | I106: 41031 | J106: =+J105+1 -> 52
A107: STI.Isla Maria Puerto Sur R.S.U.08.07.0364 | B107: Ene-Ago | C107: 55 | E107: =+C107 -> 55 | F107: 79.271 | G107: =+E107-F107 -> -24.271 | H107: =+G107/E107 -> -0.44129091 | I107: 41031 | J107: =+J106+1 -> 53
A108: STI. SIPAR GENTE DE MAR. R.S.U. 08.07.0326 | B108: Ene-Ago | C108: =1104+148.476 -> 1252.476 | E108: =+C108 -> 1252.476 | F108: 2056.497 | G108: =+E108-F108 -> -804.021 | H108: =+G108/E108 -> -0.64194523 | I108: 41036 | J108: =+J107+1 -> 54
A109: STI. SIPARBUM. R.S.U. 08.05.0424 | B109: Ene-Ago | C109: 909 | E109: =+C109 -> 909 | F109: 1838.267 | G109: =+E109-F109 -> -929.267 | H109: =+G109/E109 -> -1.0222959 | I109: 41031 | J109: =+J108+1 -> 55
A110: STI. SARPE. R.S.U. 08.05.0398 | B110: Ene-Ago | C110: 1054 | E110: =+C110 -> 1054 | F110: 2085.879 | G110: =+E110-F110 -> -1031.879 | H110: =+G110/E110 -> -0.97901233 | I110: 41031 | J110: =+J109+1 -> 56
A111: STI. Comuna de Lota R.S.U.08.07.0220 | B111: Ene-Ago | C111: 197 | E111: =+C111 -> 197 | F111: 316.086 | G111: =+E111-F111 -> -119.086 | H111: =+G111/E111 -> -0.60449746 | I111: 41031 | J111: =+J110+1 -> 57
A112: Cuota bolsón | B112: Ene-Ago | C112: 14 | E112: =+C112 -> 14 | F112: 146.399 | G112: =+E112-F112 -> -132.399 | H112: =+G112/E112 -> -9.4570714 | I112: 41019 | J112: =+J111+1 -> 58
A113: Embarcaciones Tipo Bote sin historia real de desembarque | B113: Ene-Ago | C113: 816 | E113: =+C113 -> 816 | F113: 252.618 | G113: =+E113-F113 -> 563.382 | H113: =+G113/E113 -> 0.69041912 | I113: parciales | J113: =+J112+1 -> 59
...

Sheet Resumen RAE S.Común
A2: Resumen RAE Sardina común 2012
A5: V Región, de Valparaíso
A7: Organización | B7: Periodo | C7: Cuota asignada (t) | D7: TRASPASOS | E7: Cuota efectiva (t) | F7: Desembarque (t) | G7: Saldo (t) | H7: Saldo % | I7: Fecha de Cierre
A8: A.G. Armadores Artesanales San Antonio R.A.G. 2510 | B8: Ene-Abr | C8: 6561 | E8: =+C8 -> 6561 | F8: =+SUM('RAE S.común'!B8:B11) -> 2409.39 | G8: =+E8-F8 -> 4151.61 | H8: =+G8/E8 -> 0.63277092
A9: Pescadores artesanales no afiliados | B9: Ene-Abr | C9: 2239 | E9: =+C9 -> 2239 | F9: =+SUM('RAE S.común'!B24:B27) -> 657.93 | G9: =+E9-F9 -> 1581.07 | H9: =+G9/E9 -> 0.70615007
A10: Total | B10: Ene-Abr | C10: =SUM(C8:C9) -> 8800 | E10: =SUM(E8:E9) -> 8800 | F10: =SUM(F8:F9) -> 3067.32 | G10: =+E10-F10 -> 5732.68
A12: Organización | B12: Periodo | C12: Cuota asignada (t) | E12: Cuota efectiva (t) | F12: Desembarque (t) | G12: Saldo (t) | H12: Saldo % | I12: Fecha de Cierre
A13: A.G. Armadores Artesanales San Antonio R.A.G. 2510 | B13: May-Ago | C13: 772 | E13: =+C13+G8 -> 4923.61 | F13: =+SUM('RAE S.común'!B12:B15) -> 2975.781 | G13: =+E13-F13 -> 1947.829 | H13: =+G13/E13 -> 0.39560993
A14: Pescadores artesanales no afiliados | B14: May-Ago | C14: 263 | E14: =+C14+G9 -> 1844.07 | F14: =+SUM('RAE S.común'!B28:B31) -> 932.071 | G14: =+E14-F14 -> 911.999 | H14: =+G14/E14 -> 0.49455769
A15: Total | B15: May-Ago | C15: =SUM(C13:C14) -> 1035 | E15: =+C15+G10 -> 6767.68 | F15: =SUM(F13:F14) -> 3907.852 | G15: =+E15-F15 -> 2859.828
A17: Organización | B17: Periodo | C17: Cuota asignada (t) | E17: Cuota efectiva (t) | F17: Desembarque (t) | G17: Saldo (t) | H17: Saldo % | I17: 2
A18: A.G. Armadores Artesanales San Antonio R.A.G. 2510 | B18: Sep-Dic | C18: 385 | E18: =+C18+G13 -> 2332.829 | F18: =+SUM('RAE S.común'!B16:B19) -> 2329.965 | G18: =+E18-F18 -> 2.864 | H18: =+G18/E18 -> 0.0012276939 | I18: 41240
A19: Pescadores artesanales no afiliados | B19: Sep-Dic | C19: 132 | E19: =+C19+G14 -> 1043.999 | F19: =+SUM('RAE S.común'!B32:B35) -> 406.975 | G19: =+E19-F19 -> 637.024 | H19: =+G19/E19 -> 0.61017683
A20: Total | B20: Sep-Dic | C20: =SUM(C18:C19) -> 517 | E20: =+C20+G15 -> 3376.828 | F20: =SUM(F18:F19) -> 2736.94 | G20: =+E20-F20 -> 639.888
A22: VII Región, deL Maule
A24: Organización | B24: Periodo | C24: Cuota asignada (t) | D24: TRASPASOS | E24: Cuota efectiva (t) | F24: Desembarque (t) | G24: Saldo (t) | H24: Saldo % | I24: Fecha de Cierre
A25: STI:.de Pescadores "Pelágicos del Maule" Constitución, R.S.U. N° 07050150 | B25: Ene-Abr | C25: 2994 | D25: -303 | E25: =+C25+D25 -> 2691 | F25: 961.5 | G25: =+E25-F25 -> 1729.5 | H25: =+G25/E25 -> 0.64269788
A26: Cuota Residual | B26: Ene-Abr | C26: 188 | E26: =+C26 -> 188 | F26: =+SUM('RAE S.común'!B57:B60) -> 390.361 | G26: =+E26-F26 -> -202.361 | H26: =G26/E26 -> -1.0763883 | I26: 41031
A27: Total | B27: Ene-Abr | C27: =SUM(C25:C26) -> 3182 | E27: =SUM(E25:E26) -> 2879 | F27: =SUM(F25:F26) -> 1351.861 | G27: =+E27-F27 -> 1527.139
A29: Organización | B29: Periodo | C29: Cuota asignada (t) | E29: Cuota efectiva (t) | F29: Desembarque (t) | G29: Saldo (t) | H29: Saldo % | I29: Fecha de Cierre
A30: STI:.de Pescadores "Pelágicos del Maule" Constitución, R.S.U. N° 07050150 | B30: May-Ago | C30: 352 | E30: =+C30+G25 -> 2081.5 | F30: =+SUM('RAE S.común'!B45:B48) -> 435.957 | G30: =+E30-F30 -> 1645.543 | H30: =+G30/E30 -> 0.79055633
A31: Cuota Residual | B31: May-Ago | C31: 22 | E31: =+C31+G26 -> -180.361 | F31: =+SUM('RAE S.común'!B61:B64) -> 0 | G31: =+E31-F31 -> -180.361 | H31: =+F31/E31 -> 0 | I31: 41031
A32: Total | B32: May-Ago | C32: =SUM(C30:C31) -> 374 | E32: =+C32+G27 -> 1901.139 | F32: =SUM(F30:F31) -> 435.957 | G32: =+E32-F32 -> 1465.182
A34: Organización | B34: Periodo | C34: Cuota asignada (t) | E34: Cuota efectiva (t) | F34: Desembarque (t) | G34: Saldo (t) | H34: Saldo % | I34: Fecha de Cierre
A35: STI:.de Pescadores "Pelágicos del Maule" Constitución, R.S.U. N° 07050150 | B35: Sep-Dic | C35: 176 | E35: =+C35+G30 -> 1821.543 | F35: =+SUM('RAE S.común'!B49:B52) -> 120.17 | G35: =+E35-F35 -> 1701.373 | H35: =+G35/E35 -> 0.93402846
A36: Cuota Residual | B36: Sep-Dic | C36: 11 | E36: =+C36+G31 -> -169.361 | F36: =+SUM('RAE S.común'!B65:B68) -> 0 | G36: =+E36-F36 -> -169.361 | H36: =+F36/E36 -> 0 | I36: 41031
A37: Total | B37: Sep-Dic | C37: =SUM(C35:C36) -> 187 | E37: =+C37+G32 -> 1652.182 | F37: =SUM(F35:F36) -> 120.17 | G37: =+E37-F37 -> 1532.012
A38: VIII Región, del Bio Bio | G38: 40995
A40: Organización | B40: Periodo | C40: Cuota asignada (t) | D40: traspaso | E40: Cuota efectiva (t) | F40: Desembarque (t) | G40: Saldo (t) | H40: Saldo % | I40: Fecha de Cierre
A41: Caleta Tubul.R.O.Comunitaria Funcional 478-2007 | B41: Ene-Ago | C41: 1736 | D41: -481.8 | E41: =+C41+D41 -> 1254.2 | F41: 558.151 | G41: =+E41-F41 -> 696.049 | H41: =+G41/E41 -> 0.55497449
A42: AGREPAR BIO BIO A.G 468-8 | B42: Ene-Ago | C42: 3848 | E42: =+C42 -> 3848 | F42: 3456.179 | G42: =+E42-F42 -> 391.821 | H42: =+G42/E42 -> 0.10182458
A43: ARPESCA.R.A.G. 429-8 | B43: Ene-Ago | C43: =8752-1000-500-500-1000-500 -> 5252 | E43: =+C43 -> 5252 | F43: 2328.675 | G43: =+E43-F43 -> 2923.325 | H43: =+G43/E43 -> 0.55661177
A44: ARPES BIO BIO R.A.G.445-8 | B44: Ene-Ago | C44: 21488 | E44: =+C44 -> 21488 | F44: 15504.651 | G44: =+E44-F44 -> 5983.349 | H44: =+G44/E44 -> 0.27845072
A45: SIARPAR R.A.G.448-8 | B45: Ene-Ago | C45: =1555+700 -> 2255 | E45: =+C45 -> 2255 | F45: 1449.176 | G45: =+E45-F45 -> 805.824 | H45: =+G45/E45 -> 0.35734989
A46: ARMAR R.A.G. 384-8 | B46: Ene-Ago | C46: 16244 | E46: =+C46 -> 16244 | F46: 9716.54 | G46: =+E46-F46 -> 6527.46 | H46: =+G46/E46 -> 0.40183822
A47: AGEMAPAR R.A.G.376-8 | B47: Ene-Ago | C47: 16977 | E47: =+C47 -> 16977 | F47: 12364.192 | G47: =+E47-F47 -> 4612.808 | H47: =+G47/E47 -> 0.27170925
A48: ARPROPELAR R.A.G.353-8 | B48: Ene-Ago | C48: =13291+500+500 -> 14291 | E48: =+C48 -> 14291 | F48: 11245.472 | G48: =+E48-F48 -> 3045.528 | H48: =+G48/E48 -> 0.21310811
A49: ITALMAR R.A.G.392-8 | B49: Ene-Ago | C49: 5176 | E49: =+C49 -> 5176 | F49: 3875.912 | G49: =+E49-F49 -> 1300.088 | H49: =+G49/E49 -> 0.2511762
A50: A.G. Pescadores Artesanales de Coronel R.A.G.5-8 | B50: Ene-Ago | C50: =47781+180 -> 47961 | E50: =+C50 -> 47961 | F50: 36640.021 | G50: =+E50-F50 -> 11320.979 | H50: =+G50/E50 -> 0.23604552
A51: A.G.APESCA R.A.G. 428-8 | B51: Ene-Ago | C51: 2905 | E51: =+C51 -> 2905 | F51: 2609.005 | G51: =+E51-F51 -> 295.995 | H51: =+G51/E51 -> 0.10189157
A52: A.G. Pescadores Artesanales de San Vicente R.A.G.18-8 | B52: Ene-Ago | C52: 8772 | E52: =+C52 -> 8772 | F52: 5813.846 | G52: =+E52-F52 -> 2958.154 | H52: =+G52/E52 -> 0.33722686
A53: A.G. Pesc. Art. VIII reg. AGREPESCA R.A.G. N° 396-8 | B53: Ene-Ago | C53: =112+6 -> 118 | D53: =-112+-6 -> -118 | E53: =+C53+D53 -> 0 | F53: 0 | G53: =+E53-F53 -> 0 | H53: =+G53/E53 -> #DIV/0!
A54: PESCA MAR R.A.G. 450-8 | B54: Ene-Ago | C54: 17257 | E54: =+C54 -> 17257 | F54: 14803.259 | G54: =+E54-F54 -> 2453.741 | H54: =+G54/E54 -> 0.14218816
A55: GEMAR R.A.G.464-8 | B55: Ene-Ago | C55: 9708 | E55: =+C55 -> 9708 | F55: 7917.143 | G55: =+E55-F55 -> 1790.857 | H55: =+G55/E55 -> 0.18447229
A56: ARPESCA R.A.G.447-8 | B56: Ene-Ago | C56: 31618 | E56: =+C56 -> 31618 | F56: 21826.145 | G56: =+E56-F56 -> 9791.855 | H56: =+G56/E56 -> 0.30969242
A57: Cooperativa Pelilleros Isla Sta. María Ltda. Rol 1826 | B57: Ene-Ago | C57: 543 | E57: =+C57 -> 543 | F57: 380.63 | G57: =+E57-F57 -> 162.37 | H57: =+G57/E57 -> 0.29902394
A58: Cooperativa GEVIMAR. Rol 4465 | B58: Ene-Ago | C58: =8606-1400 -> 7206 | E58: =+C58 -> 7206 | F58: 7090.165 | G58: =+E58-F58 -> 115.835 | H58: =+G58/E58 -> 0.016074799
A59: STI.Lo Rojas y Caletas del Golfo de Arauco.R.S.U.08.07.0307 | B59: Ene-Ago | C59: =9933+5869+1525 -> 17327 | D59: =-1479+-46.26 -> -1525.26 | E59: =+C59+D59 -> 15801.74 | F59: 13390.731 | G59: =+E59-F59 -> 2411.009 | H59: =+G59/E59 -> 0.1525787
A60: STI. SPAADA. R.S.U. 08.05.0339 | B60: Ene-Ago | C60: =21854-1000 -> 20854 | D60: -400 | E60: =+C60+D60 -> 20454 | F60: 12817.147 | G60: =+E60-F60 -> 7636.853 | H60: =+G60/E60 -> 0.37336721
A61: STI. Pesc. Art. AR: Pelg. Y Act. Caleta Coliumo Reg. 08.06.0113 | B61: Ene-Ago | C61: 4693 | E61: =+C61 -> 4693 | F61: 2532.643 | G61: =+E61-F61 -> 2160.357 | H61: =+G61/E61 -> 0.46033603
A62: STI. SIPARMAR R.S.U.08.05.0399 | B62: Ene-Ago | C62: =8414.9+1000 -> 9414.9 | E62: =+C62 -> 9414.9 | F62: 6121.596 | G62: =+E62-F62 -> 3293.304 | H62: =+G62/E62 -> 0.34979702
A63: STI. Brisas del Mar R.S.U.08.04.0115 | B63: Ene-Ago | C63: =476+25 -> 501 | D63: =-476+-25 -> -501 | E63: =+D63+C63 -> 0 | F63: 0 | G63: =+E63-F63 -> 0 | H63: =+G63/E63 -> #DIV/0!
A64: SIARPEMAR R.S.U.08.05.0459 | B64: Ene-Ago | C64: 3444 | E64: =+C64 -> 3444 | F64: 2904.571 | G64: =+E64-F64 -> 539.429 | H64: =+G64/E64 -> 0.15662863 | I64: 41246
A65: STI. SARPAR BIO BIO. R.S.U. 08.05.0378 | B65: Ene-Ago | C65: 2714 | E65: =+C65 -> 2714 | F65: 829.744 | G65: =+E65-F65 -> 1884.256 | H65: =+G65/E65 -> 0.69427266
A66: STI. SITRAL. R.S.U.08.07.0322 | B66: Ene-Ago | C66: 5070 | E66: =+C66 -> 5070 | F66: 3515.845 | G66: =+E66-F66 -> 1554.155 | H66: =+G66/E66 -> 0.30653945
A67: STI. Arm. Pes. Art. Y Ramas . Reg. 08.05.0512 | B67: Ene-Ago | C67: 5613 | E67: =+C67 -> 5613 | F67: 3720.037 | G67: =+E67-F67 -> 1892.963 | H67: N
A68: STI. Hermandad de la Costa. R.S.U. 08.05.0404 | B68: Ene-Ago | C68: 1041 | E68: =+C68 -> 1041 | F68: 1109.906 | G68: =+E68-F68 -> -68.906 | H68: =+G68/E68 -> -0.066192123 | I68: 41031
A69: STI. MAR AZUL. R.S.U. 08.05.0434 | B69: Ene-Ago | C69: 6231 | E69: =+C69 -> 6231 | F69: 3794.351 | G69: =+E69-F69 -> 2436.649 | H69: =+G69/E69 -> 0.39105264
A70: STI. Sindicato Tsunami R.S.U. 08.05.0428 | B70: Ene-Ago | C70: =8956-400 -> 8556 | E70: =+C70 -> 8556 | F70: 5595.591 | G70: =+E70-F70 -> 2960.409 | H70: =+G70/E70 -> 0.34600386
A71: STI. Caleta Lo Rojas R.S.U 08.07.0287 | B71: Ene-Ago | C71: 543 | E71: =+C71 -> 543 | F71: 334.758 | G71: =+E71-F71 -> 208.242 | H71: =+G71/E71 -> 0.38350276
A72: STI. Merluceros y afines Caleta Lo Rojas. R.S.U.08.07.0227 | B72: Ene-Ago | C72: 724 | E72: =+C72 -> 724 | F72: 428.242 | G72: =+E72-F72 -> 295.758 | H72: =+G72/E72 -> 0.40850552
A73: STI. SIPARMARCEA. R.S.U.08.05.0430 | B73: Ene-Ago | C73: 8379 | E73: =+C73 -> 8379 | F73: 6535.559 | G73: =+E73-F73 -> 1843.441 | H73: =+G73/E73 -> 0.22000728
A74: STI. APAT. R.S.U.08.05.0380 | B74: Ene-Ago | C74: 3512 | E74: =+C74 -> 3512 | F74: 2795.76 | G74: =+E74-F74 -> 716.24 | H74: =+G74/E74 -> 0.20394077
A75: STI. Caleta Tumbes. R.S.U.08.05.0057 | B75: Ene-Ago | C75: 24944 | D75: -2800 | E75: =+C75+D75 -> 22144 | F75: 17773.49 | G75: =+E75-F75 -> 4370.51 | H75: =+G75/E75 -> 0.19736768
A76: STI. SPARHITAL. R.S.U.08.05.0382 | B76: Ene-Ago | C76: 3950 | E76: =+C76 -> 3950 | F76: 2844.932 | G76: =+E76-F76 -> 1105.068 | H76: =+G76/E76 -> 0.27976405
A77: STI. Peninsula de Tumbes. R.S.U.08.05.0391 | B77: Ene-Ago | C77: 9407 | E77: =+C77 -> 9407 | F77: 6631.791 | G77: =+E77-F77 -> 2775.209 | H77: =+G77/E77 -> 0.29501531
A78: STI. Los Bagres.R.S.U.08.06.0024 | B78: Ene-Ago | C78: =724-367 -> 357 | D78: -329 | E78: =+C78+D78 -> 28 | F78: 65.761 | G78: =+E78-F78 -> -37.761 | H78: =+G78/E78 -> -1.3486071
A79: STI. Patrones y tripulantes Caleta Cocholgüe R.S.U08.0601.06 | B79: Ene-Ago | C79: =3983-620 -> 3363 | D79: -529 | E79: =+C79+D79 -> 2834 | F79: 2263.055 | G79: =+E79-F79 -> 570.945 | H79: =+G79/E79 -> 0.2014626
A80: STI. Puerto de Coronel y el Golfo de Arauco. R.S.U.08.07.0183 | B80: Ene-Ago | C80: =15320+99-180 -> 15239 | D80: -99 | E80: =+C80+D80 -> 15140 | F80: 12300.119 | G80: =+E80-F80 -> 2839.881 | H80: =+G80/E80 -> 0.1875747
A81: STI. Caleta Lota Bajo. R.S.U.08.07.0106 | B81: Ene-Ago | C81: 11011 | E81: =+C81 -> 11011 | F81: 8252.75 | G81: =+E81-F81 -> 2758.25 | H81: =+G81/E81 -> 0.2504995
A82: STI. Caleta Cocholgüe. R.S.U.08.06.0023 | B82: Ene-Ago | C82: 724 | E82: =+C82 -> 724 | F82: 566.456 | G82: =+E82-F82 -> 157.544 | H82: =+G82/E82 -> 0.21760221
A83: STI. Caleta Coliumo. R.S.U.08.06.0027 | B83: Ene-Ago | C83: 25448 | D83: =-614+-1297 -> -1911 | E83: =+C83+D83 -> 23537 | F83: 14616.639 | G83: =+E83-F83 -> 8920.361 | H83: =+G83/E83 -> 0.37899312
A84: STI. SIPARMA LOTA. R.S.U.08.07.0306 | B84: Ene-Ago | C84: =9357+5297+600 -> 15254 | D84: =-1500+-600 -> -2100 | E84: =+C84+D84 -> 13154 | F84: 10377.538 | G84: =+E84-F84 -> 2776.462 | H84: =+G84/E84 -> 0.21107359
A85: STI. Comuna Talcahuano R.S.U.08.05.0487 | B85: Ene-Ago | C85: 2260 | E85: =+C85 -> 2260 | F85: 2007.389 | G85: =+E85-F85 -> 252.611 | H85: =+G85/E85 -> 0.11177478
A86: STI.SIPESMAFESA. R.S.U. 08.07.0332 | B86: Ene-Ago | C86: 8307 | E86: =+C86 -> 8307 | F86: 7404.656 | G86: =+E86-F86 -> 902.344 | H86: =+G86/E86 -> 0.10862453
A87: STI. SIPARMA CORONEL. R.S.U.08.07.0271 | B87: Ene-Ago | C87: 7384 | E87: =+C87 -> 7384 | F87: 5639.244 | G87: =+E87-F87 -> 1744.756 | H87: =+G87/E87 -> 0.23628873
A88: STI. SIPEAYRAS. R.S.U.08.07.0296 | B88: Ene-Ago | C88: =17079-500 -> 16579 | E88: =+C88 -> 16579 | F88: 12905.313 | G88: =+E88-F88 -> 3673.687 | H88: =+G88/E88 -> 0.22158677
A89: STI. Arm. ,Buzos Acui. Y ram . SIPEARBUCOR Reg. 08.07.0376 | B89: Ene-Ago | C89: 679 | D89: -185 | E89: =+C89+D89 -> 494 | F89: 543.439 | G89: =+E89-F89 -> -49.439 | H89: =+G89/E89 -> -0.10007895
A90: STI. Caletas Tomé y Quichiuto. R.S.U.08.06.0043 | B90: Ene-Ago | C90: =5439+303+1000 -> 6742 | D90: =-200+-300 -> -500 | E90: =+C90+D90 -> 6242 | F90: 4948.967 | G90: =+E90-F90 -> 1293.033 | H90: =+G90/E90 -> 0.20715043
A91: STI. Pecs. Arm. Pelg. Pat. De Com. Talcahuano Reg. 08-05-0474 Aspas | B91: Ene-Ago | C91: =10508-700 -> 9808 | D91: =-600+-500 -> -1100 | E91: =+C91+D91 -> 8708 | F91: 6068.296 | G91: =+E91-F91 -> 2639.704 | H91: =+G91/E91 -> 0.30313551
A92: STI. Río Maipo R.S.U.08.05.0488 | B92: Ene-Ago | C92: 3171 | E92: =+C92 -> 3171 | F92: 2161.862 | G92: =+E92-F92 -> 1009.138 | H92: =+G92/E92 -> 0.31823967
A93: STI.Isla Maria Puerto Sur R.S.U.08.07.0364 | B93: Ene-Ago | C93: 1041 | E93: =+C93 -> 1041 | F93: 1130.433 | G93: =+E93-F93 -> -89.433 | H93: =+G93/E93 -> -0.085910663 | I93: 41108
A94: STI. SIPAR GENTE DE MAR. R.S.U. 08.07.0326 | B94: Ene-Ago | C94: =20876+500+2806.52+1000 -> 25182.52 | D94: -200 | E94: =+C94+D94 -> 24982.52 | F94: 15530.888 | G94: =+E94-F94 -> 9451.632 | H94: =+G94/E94 -> 0.37832981
A95: STI. SIPARBUM. R.S.U. 08.05.0424 | B95: Ene-Ago | C95: =17180-500 -> 16680 | D95: =-2400+-500 -> -2900 | E95: =+C95+D95 -> 13780 | F95: 12380.733 | G95: =+E95-F95 -> 1399.267 | H95: =+G95/E95 -> 0.10154332
A96: STI. SARPE. R.S.U. 08.05.0398 | B96: Ene-Ago | C96: 19925 | E96: =+C96 -> 19925 | F96: 13773.978 | G96: =+E96-F96 -> 6151.022 | H96: =+G96/E96 -> 0.30870876
A97: STI. Comuna de Lota R.S.U.08.07.0220 | B97: Ene-Ago | C97: 3724 | E97: =+C97 -> 3724 | F97: 2902.491 | G97: =+E97-F97 -> 821.509 | H97: =+G97/E97 -> 0.22059855
A98: Cuota residual | B98: Ene-Ago | C98: 272 | E98: =+C98 -> 272 | F98: 1240.017 | G98: =+E98-F98 -> -968.017 | H98: =+G98/E98 -> -3.558886 | I98: 41019
A99: Embarcaciones Tipo Bote sin historia real de desembarque | B99: Ene-Ago | C99: 15092 | E99: =+C99 -> 15092 | F99: 12629.057 | G99: =+E99-F99 -> 2462.943 | H99: =+G99/E99 -> 0.16319527 | I99: parciales
A100: AG. Pescadores de pescadores Art. De caleta INFIERNILLO Rag. 98-8 | B100: Ene-Ago | C100: 1086 | D100: -743 | E100: =+C100+D100 -> 343 | F100: 218.16 | G100: =+E100-F100 -> 124.84 | H100: =+G100/E100 -> 0.36396501
A101: S.I. de Pequeños Arm. Y Pesc. Art. De Cerco y Otras Act. Af. Coronel y Lota RSU.08.07.0373 | B101: Ene-Ago | C101: 81.1 | E101: =+C101 -> 81.1 | F101: 0 | G101: =+E101-F101 -> 81.1 | H101: =+G101/E101 -> 1
A102: Total | B102: Ene-Ago | C102: =SUM(C41:C101) -> 559682.52 | D102: =+D63+D53+D95+D89+D90+D91+D94+D84+D80+D59+D83+D100 -> -11882.26 | E102: =SUM(E41:E101) -> 543260.46 | F102: =SUM(F41:F101) -> 401183.1 | G102: =+E102-F102 -> 142077.36 | H102: =+G102/E102 -> 0.26152716
J103: total anual | L103: 2° periodo | M103: capturado
A104: Organización | B104: Periodo | C104: Cuota asignada (t) | E104: Cuota efectiva (t) | F104: Desembarque (t) | G104: Saldo (t) | H104: % | I104: Fecha de Cierre | J104: 2do per. | K104: 1er per. | L104: dif. | M104: anual | N104: correlativo
A105: Caleta Tubul.R.O.Comunitaria Funcional 478-2007 | B105: Sep-Dic | C105: 91 | E105: =+C105+G41 -> 787.049 | F105: =L105 -> 28.721 | G105: =+E105-F105 -> 758.328 | H105: =+G105/E105 -> 0.96350799 | J105: 586.872 | K105: 558.151 | L105: =+M105-K105 -> 28.721 | M105: 586.872 | N105: 1
A106: AGREPAR BIO BIO A.G 468-8 | B106: Sep-Dic | C106: 203 | E106: =+C106+G42 -> 594.821 | F106: =L106 -> 374.126 | G106: =+E106-F106 -> 220.695 | H106: =+G106/E106 -> 0.37102759 | I106: 41233 | J106: 3830.305 | K106: 3456.179 | L106: =+M106-K106 -> 374.126 | M106: 3830.305 | N106: 2
A107: ARPESCA.R.A.G. 429-8 | B107: Sep-Dic | C107: 461 | E107: =+C107+G43 -> 3384.325 | F107: =L107 -> 171.634 | G107: =+E107-F107 -> 3212.691 | H107: =+G107/E107 -> 0.9492856 | J107: 2500.309 | K107: 2328.675 | L107: =+M107-K107 -> 171.634 | M107: 2500.309 | N107: 3
A108: ARPES BIO BIO R.A.G.445-8 | B108: Sep-Dic | C108: 1131 | E108: =+C108+G44 -> 7114.349 | F108: =L108 -> 2609.72 | G108: =+E108-F108 -> 4504.629 | H108: =+G108/E108 -> 0.63317515 | J108: 18114.371 | K108: 15504.651 | L108: =+M108-K108 -> 2609.72 | M108: 18114.371 | N108: 4
A109: SIARPAR R.A.G.448-8 | B109: Sep-Dic | C109: 82 | E109: =+C109+G45 -> 887.824 | F109: =L109 -> 0 | G109: =+E109-F109 -> 887.824 | H109: =+G109/E109 -> 1 | J109: 1449.176 | K109: 1449.176 | L109: =+M109-K109 -> 0 | M109: 1449.176 | N109: 5
A110: ARMAR R.A.G. 384-8 | B110: Sep-Dic | C110: 855 | E110: =+C110+G46 -> 7382.46 | F110: =L110 -> 908.979 | G110: =+E110-F110 -> 6473.481 | H110: =+G110/E110 -> 0.87687316 | J110: 10625.519 | K110: 9716.54 | L110: =+M110-K110 -> 908.979 | M110: 10625.519 | N110: 6
A111: AGEMAPAR R.A.G.376-8 | B111: Sep-Dic | C111: 894 | E111: =+C111+G47 -> 5506.808 | F111: =L111 -> 2089.56 | G111: =+E111-F111 -> 3417.248 | H111: =+G111/E111 -> 0.62054969 | J111: 14453.752 | K111: 12364.192 | L111: =+M111-K111 -> 2089.56 | M111: 14453.752 | N111: 7
...

Sheet RAE Anchoveta
A2: RAE Anchoveta 2012
A4: IV REGIÓN
A6: Cooperativa de Armadores Cerqueros IV región | K6: ok¡
A7: Mes | B7: Total mes | C7: 1 | D7: 2 | E7: 3 | F7: 4 | G7: 5 | H7: 6 | I7: 7 | J7: 8 | K7: 9 | L7: 10 | M7: 11 | N7: 12 | O7: 13 | P7: 14 | Q7: 15 | R7: 16 | S7: 17 | T7: 18 | U7: 19 | V7: 20 | W7: 21 | X7: 22 | Y7: 23 | Z7: 24 | AA7: 25 | AB7: 26 | AC7: 27 | AD7: 28 | AE7: 29 | AF7: 30 | AG7: 31 | AH7: TOTAL
A8: Enero | B8: =+AH8 -> 947.513 | C8: 0 | D8: 85.807 | E8: 335.518 | F8: 156.985 | G8: 111.137 | H8: 35.574 | I8: 120.214 | J8: 0 | K8: 0 | L8: 0 | M8: 0 | N8: 0 | O8: 0 | P8: 25.44 | Q8: 0 | R8: 0 | S8: 0 | T8: 22.165 | U8: 27.163 | V8: 4.81 | W8: 7.2 | X8: 0 | Y8: 5.35 | Z8: 3.75 | AA8: 5.35 | AB8: 1.05 | AC8: 0 | AD8: 0 | AE8: 0 | AF8: 0 | AG8: 0 | AH8: =SUM(C8:AG8) -> 947.513
A9: Febrero | B9: =+AH9 -> 1186.794 | C9: 0 | D9: 0 | E9: 0 | F9: 1.01 | G9: 0 | H9: 89.771 | I9: 147.764 | J9: 121.628 | K9: 6.98 | L9: 3.639 | M9: 2.74 | N9: 0 | O9: 57.453 | P9: 9.565 | Q9: 93.379 | R9: 0.95 | S9: 2.8 | T9: 5.31 | U9: 0 | V9: 43.687 | W9: 141.54 | X9: 148.991 | Y9: 23.959 | Z9: 57.662 | AA9: 56.49 | AB9: 0 | AC9: 50.218 | AD9: 107.907 | AE9: 13.351 | AH9: =SUM(C9:AG9) -> 1186.794
A10: Marzo | B10: =+AH10 -> 3499.127 | C10: 0 | D10: 101.2 | E10: 1.3 | F10: 0 | G10: 304.271 | H10: 149.917 | I10: 0 | J10: 0 | K10: 27.448 | L10: 3.6 | M10: 0 | N10: 0 | O10: 369.442 | P10: 159.574 | Q10: 167.656 | R10: 0 | S10: 3.995 | T10: 0 | U10: 0 | V10: 19.296 | W10: 2.82 | X10: 21.81 | Y10: 546.182 | Z10: 241.327 | AA10: 0 | AB10: 290.917 | AC10: 0 | AD10: 441.28 | AE10: 573.188 | AF10: 69.982 | AG10: 3.922 | AH10: =SUM(C10:AG10) -> 3499.127
A11: Abril | B11: =+AH11 -> 560.978 | C11: 0 | D11: 249.825 | E11: 73.562 | F11: 0 | G11: 0 | H11: 0 | I11: 0 | J11: 0 | K11: 60.207 | L11: 0 | M11: 43.513 | N11: 0 | O11: 42.788 | P11: 0 | Q11: 0 | R11: 0 | S11: 28.053 | T11: 0 | U11: 0 | V11: 0 | W11: 0 | X11: 0 | Y11: 0 | Z11: 58.03 | AA11: 5 | AB11: 0 | AC11: 0 | AD11: 0 | AE11: 0 | AF11: 0 | AH11: =SUM(C11:AG11) -> 560.978
A12: Mayo | B12: =+AH12 -> 106.122 | C12: 0 | D12: 0 | E12: 0 | F12: 0 | G12: 0 | H12: 0 | I12: 0 | J12: 0 | K12: 0 | L12: 0 | M12: 0 | N12: 0 | O12: 0 | P12: 0 | Q12: 0 | R12: 0 | S12: 0 | T12: 0 | U12: 0 | V12: 0 | W12: 0 | X12: 0 | Y12: 0 | Z12: 0 | AA12: 0.587 | AB12: 0 | AC12: 0 | AD12: 0 | AE12: 0 | AF12: 0 | AG12: 105.535 | AH12: =SUM(C12:AG12) -> 106.122
A13: Junio | B13: =+AH13 -> 1269.159 | C13: 5.104 | D13: 68.215 | E13: 0 | F13: 70.753 | G13: 9.162 | H13: 194.52 | I13: 0 | J13: 0 | K13: 97.01 | L13: 0 | M13: 65.742 | N13: 106.972 | O13: 62.65 | P13: 61.676 | Q13: 60.506 | R13: 8.174 | S13: 0 | T13: 3.7 | U13: 6.7 | V13: 9.1 | W13: 1.1 | X13: 0 | Y13: 0 | Z13: 0 | AA13: 13.352 | AB13: 144.572 | AC13: 135.616 | AD13: 134.96 | AE13: 1.513 | AF13: 8.062 | AH13: =SUM(C13:AG13) -> 1269.159
A14: Julio | B14: =+AH14 -> 54.93 | C14: 0 | D14: 0 | E14: 0 | F14: 0 | G14: 0 | H14: 0 | I14: 0 | J14: 0 | K14: 3.8 | L14: 21.83 | M14: 0 | N14: 0.85 | O14: 0 | P14: 0 | Q14: 0 | R14: 0 | S14: 2.54 | T14: 12.01 | U14: 3.83 | V14: 5.2 | W14: 1.3 | X14: 0 | Y14: 0 | Z14: 3.57 | AA14: 0 | AB14: 0 | AC14: 0 | AD14: 0 | AE14: 0 | AF14: 0 | AH14: =SUM(C14:AG14) -> 54.93
A15: Agosto | B15: =+AH15 -> 13.79 | C15: 0 | D15: 0 | E15: 0 | F15: 0 | G15: 0 | H15: 0 | I15: 3.03 | J15: 3.04 | K15: 0 | L15: 0 | M15: 2.4 | N15: 0 | O15: 0 | P15: 0 | Q15: 0 | R15: 0 | S15: 0 | T15: 5.32 | U15: 0 | V15: 0 | W15: 0 | X15: 0 | Y15: 0 | Z15: 0 | AA15: veda | AB15: veda | AC15: veda | AD15: veda | AE15: veda | AF15: veda | AG15: veda | AH15: =SUM(C15:AG15) -> 13.79
A16: Septiembre | B16: =+AH16 -> 352.492 | C16: veda | D16: veda | E16: veda | F16: veda | G16: veda | H16: veda | I16: veda | J16: veda | K16: veda | L16: veda | M16: veda | N16: veda | O16: veda | P16: veda | Q16: veda | R16: veda | S16: veda | T16: veda | U16: veda | V16: veda | W16: veda | X16: veda | Y16: veda | Z16: 37.92 | AA16: 114.594 | AB16: 151.845 | AC16: 48.133 | AD16: 0 | AE16: 0 | AF16: 0 | AH16: =SUM(C16:AG16) -> 352.492
A17: Octubre | B17: =+AH17 -> 396.161 | C17: 0 | D17: 5.08 | E17: 0 | F17: 0 | G17: 0 | H17: 0 | I17: 0 | J17: 0 | K17: 0 | L17: 0 | M17: 0 | N17: 0 | O17: 0 | P17: 0 | Q17: 0 | R17: 0 | S17: 0 | T17: 0 | U17: 164.997 | V17: 56.543 | W17: 65.425 | X17: 88.666 | Y17: 15.45 | Z17: 0 | AA17: 0 | AB17: 0 | AH17: =SUM(C17:AG17) -> 396.161
A18: Noviembre | B18: =+AH18 -> 40.45 | C18: 0 | D18: 0 | E18: 0 | F18: 0 | G18: 0 | H18: 0 | I18: 0 | J18: 0 | K18: 0 | L18: 0 | M18: 0 | N18: 0 | O18: 0 | P18: 0 | Q18: 37.35 | R18: 0 | S18: 0.7 | T18: 0 | U18: 1.2 | V18: 0 | W18: 1.2 | X18: 0 | Y18: 0 | Z18: 0 | AA18: 0 | AB18: 0 | AC18: 0 | AD18: 0 | AE18: 0 | AF18: 0 | AH18: =SUM(C18:AG18) -> 40.45
A19: Diciembre | B19: =+AH19 -> 4.64 | C19: 0 | D19: 0 | E19: 0 | F19: 0 | G19: 4.64 | H19: 0 | I19: 0 | J19: 0 | K19: 0 | L19: 0 | M19: 0 | N19: 0 | O19: 0 | P19: 0 | Q19: 0 | R19: 0 | S19: 0 | T19: 0 | U19: 0 | V19: 0 | W19: 0 | X19: 0 | Y19: 0 | Z19: 0 | AA19: 0 | AB19: 0 | AC19: 0 | AD19: 0 | AE19: 0 | AF19: 0 | AG19: 0 | AH19: =SUM(C19:AG19) -> 4.64
A20: TOTAL | B20: =SUM(B8:B19) -> 8432.156 | C20: =SUM(C8:C19) -> 5.104 | D20: =SUM(D8:D19) -> 510.127 | E20: =SUM(E8:E19) -> 410.38 | F20: =SUM(F8:F19) -> 228.748 | G20: =SUM(G8:G19) -> 429.21 | H20: =SUM(H8:H19) -> 469.782 | I20: =SUM(I8:I19) -> 271.008 | ... AH20: =SUM(AH8:AH19) -> 8432.156
A22: A.G. de pescadores Artesanales y Buzos Mariscadores de Coquimbo - IV Región
A23: Mes | B23: Total mes | C23: 1 | D23: 2 | E23: 3 | F23: 4 | G23: 5 | H23: 6 | I23: 7 | J23: 8 | K23: 9 | L23: 10 | M23: 11 | N23: 12 | O23: 13 | P23: 14 | Q23: 15 | R23: 16 | S23: 17 | T23: 18 | U23: 19 | V23: 20 | W23: 21 | X23: 22 | Y23: 23 | Z23: 24 | AA23: 25 | AB23: 26 | AC23: 27 | AD23: 28 | AE23: 29 | AF23: 30 | AG23: 31 | AH23: TOTAL
A24: Enero | B24: =+AH24 -> 0 | C24: 0 | D24: 0 | E24: 0 | F24: 0 | G24: 0 | H24: 0 | I24: 0 | J24: 0 | K24: 0 | L24: 0 | M24: 0 | N24: 0 | O24: 0 | P24: 0 | Q24: 0 | R24: 0 | S24: 0 | T24: 0 | U24: 0 | V24: 0 | W24: 0 | X24: 0 | Y24: 0 | Z24: 0 | AA24: 0 | AB24: 0 | AC24: 0 | AD24: 0 | AE24: 0 | AF24: 0 | AG24: 0 | AH24: =SUM(C24:AG24) -> 0
A25: Febrero | B25: =+AH25 -> 0 | C25: 0 | D25: 0 | E25: 0 | F25: 0 | G25: 0 | H25: 0 | I25: 0 | J25: 0 | K25: 0 | L25: 0 | M25: 0 | N25: 0 | O25: 0 | P25: 0 | Q25: 0 | R25: 0 | S25: 0 | T25: 0 | U25: 0 | V25: 0 | W25: 0 | X25: 0 | Y25: 0 | Z25: 0 | AA25: 0 | AB25: 0 | AC25: 0 | AD25: 0 | AE25: 0 | AH25: =SUM(C25:AG25) -> 0
A26: Marzo | B26: =+AH26 -> 0 | C26: 0 | D26: 0 | E26: 0 | F26: 0 | G26: 0 | H26: 0 | I26: 0 | J26: 0 | K26: 0 | L26: 0 | M26: 0 | N26: 0 | O26: 0 | P26: 0 | Q26: 0 | R26: 0 | S26: 0 | T26: 0 | U26: 0 | V26: 0 | W26: 0 | X26: 0 | Y26: 0 | Z26: 0 | AA26: 0 | AB26: 0 | AC26: 0 | AD26: 0 | AE26: 0 | AF26: 0 | AG26: 0 | AH26: =SUM(C26:AG26) -> 0
A27: Abril | B27: =+AH27 -> 0.1 | C27: 0 | D27: 0 | E27: 0 | F27: 0 | G27: 0 | H27: 0 | I27: 0 | J27: 0 | K27: 0 | L27: 0 | M27: 0 | N27: 0 | O27: 0 | P27: 0 | Q27: 0 | R27: 0 | S27: 0 | T27: 0 | U27: 0 | V27: 0 | W27: 0 | X27: 0 | Y27: 0 | Z27: 0 | AA27: 0 | AB27: 0 | AC27: 0 | AD27: 0.1 | AE27: 0 | AF27: 0 | AH27: =SUM(C27:AG27) -> 0.1
A28: Mayo | B28: =+AH28 -> 0.37 | C28: 0 | D28: 0 | E28: 0 | F28: 0 | G28: 0 | H28: 0 | I28: 0 | J28: 0 | K28: 0 | L28: 0 | M28: 0 | N28: 0 | O28: 0 | P28: 0 | Q28: 0 | R28: 0 | S28: 0 | T28: 0 | U28: 0 | V28: 0 | W28: 0 | X28: 0 | Y28: 0 | Z28: 0 | AA28: 0 | AB28: 0 | AC28: 0 | AD28: 0 | AE28: 0 | AF28: 0.37 | AG28: 0 | AH28: =SUM(C28:AG28) -> 0.37
A29: Junio | B29: =+AH29 -> 2.45 | C29: 0 | D29: 0 | E29: 0 | F29: 0 | G29: 0 | H29: 0 | I29: 0.45 | J29: 1.2 | K29: 0.8 | L29: 0 | M29: 0 | N29: 0 | O29: 0 | P29: 0 | Q29: 0 | R29: 0 | S29: 0 | T29: 0 | U29: 0 | V29: 0 | W29: 0 | X29: 0 | Y29: 0 | Z29: 0 | AA29: 0 | AB29: 0 | AC29: 0 | AD29: 0 | AE29: 0 | AF29: 0 | AH29: =SUM(C29:AG29) -> 2.45
A30: Julio | B30: =+AH30 -> 0 | AH30: =SUM(C30:AG30) -> 0
A31: Agosto | B31: =+AH31 -> 0
A32: Septiembre | B32: =+AH32 -> 0 | C32: veda | D32: veda | E32: veda | F32: veda | G32: veda | H32: veda | I32: veda | J32: veda | K32: veda | L32: veda | M32: veda | N32: veda | O32: veda | P32: veda | Q32: veda | R32: veda | S32: veda | T32: veda | U32: veda | V32: veda | W32: veda | X32: veda | Y32: veda
A33: Octubre | B33: =+AH33 -> 0 | C33: 0 | D33: 0 | E33: 0 | F33: 0 | G33: 0 | H33: 0 | I33: 0 | J33: 0 | K33: 0 | L33: 0 | M33: 0 | N33: 0 | O33: 0 | P33: 0 | Q33: 0 | R33: 0 | S33: 0 | T33: 0 | U33: 0 | V33: 0 | W33: 0 | X33: 0 | Y33: 0 | Z33: 0 | AA33: 0 | AB33: 0 | AC33: 0 | AD33: 0 | AE33: 0 | AF33: 0 | AG33: 0 | AH33: =SUM(C33:AG33) -> 0
A34: Noviembre | B34: =+AH34 -> 0 | C34: 0 | D34: 0 | E34: 0 | F34: 0 | G34: 0 | H34: 0 | I34: 0 | J34: 0 | K34: 0 | L34: 0 | M34: 0 | N34: 0 | O34: 0 | P34: 0 | Q34: 0 | R34: 0 | S34: 0 | T34: 0 | U34: 0 | V34: 0 | W34: 0 | X34: 0 | Y34: 0 | Z34: 0 | AA34: 0 | AB34: 0 | AC34: 0 | AD34: 0 | AE34: 0 | AF34: 0 | AH34: =SUM(C34:AG34) -> 0
A35: Diciembre | B35: =+AH35 -> 2 | C35: 0 | D35: 0 | E35: 0 | F35: 0 | G35: 0 | H35: 0 | I35: 2 | J35: 0 | K35: 0 | L35: 0 | M35: 0 | N35: 0 | O35: 0 | P35: 0 | Q35: 0 | R35: 0 | S35: 0 | T35: 0 | U35: 0 | V35: 0 | W35: 0 | X35: 0 | Y35: 0 | Z35: 0 | AA35: 0 | AB35: 0 | AC35: 0 | AD35: 0 | AE35: 0 | AF35: 0 | AG35: 0 | AH35: =SUM(C35:AG35) -> 2
A36: TOTAL | B36: =SUM(B24:B35) -> 4.92 | C36: =SUM(C24:C35) -> 0 | D36: =SUM(D24:D35) -> 0 | E36: =SUM(E24:E35) -> 0 | F36: =SUM(F24:F35) -> 0 | G36: =SUM(G24:G35) -> 0 | H36: =SUM(H24:H35) -> 0 | I36: =SUM(I24:I35) -> 2.45 | ... AH36: =SUM(AH24:AH35) -> 4.92
A38: Cuota residual - Bolson
A39: Mes | B39: Total mes | C39: 1 | D39: 2 | E39: 3 | F39: 4 | G39: 5 | H39: 6 | I39: 7 | J39: 8 | K39: 9 | L39: 10 | M39: 11 | N39: 12 | O39: 13 | P39: 14 | Q39: 15 | R39: 16 | S39: 17 | T39: 18 | U39: 19 | V39: 20 | W39: 21 | X39: 22 | Y39: 23 | Z39: 24 | AA39: 25 | AB39: 26 | AC39: 27 | AD39: 28 | AE39: 29 | AF39: 30 | AG39: 31 | AH39: TOTAL
A40: Enero | B40: =+AH40 -> 3.12 | C40: 0 | D40: 0 | E40: 3.02 | F40: 0 | G40: 0 | H40: 0 | I40: 0 | J40: 0 | K40: 0.1 | L40: 0 | M40: 0 | N40: 0 | O40: 0 | P40: 0 | Q40: 0 | R40: 0 | S40: 0 | T40: 0 | U40: 0 | V40: 0 | W40: 0 | X40: 0 | Y40: 0 | Z40: 0 | AA40: 0 | AB40: 0 | AC40: 0 | AD40: 0 | AE40: 0 | AF40: 0 | AG40: 0 | AH40: =SUM(C40:AG40) -> 3.12
A41: Febrero | B41: =+AH41 -> 0 | C41: 0 | D41: 0 | E41: 0 | F41: 0 | G41: 0 | H41: 0 | I41: 0 | J41: 0 | K41: 0 | L41: 0 | M41: 0 | N41: 0 | O41: 0 | P41: 0 | Q41: 0 | R41: 0 | S41: 0 | T41: 0 | U41: 0 | V41: 0 | W41: 0 | X41: 0 | Y41: 0 | Z41: 0 | AA41: 0 | AB41: 0 | AC41: 0 | AD41: 0 | AE41: 0 | AH41: =SUM(C41:AG41) -> 0
A42: Marzo | B42: =+AH42 -> 0.3 | C42: 0 | D42: 0 | E42: 0 | F42: 0 | G42: 0 | H42: 0 | I42: 0 | J42: 0 | K42: 0 | L42: 0 | M42: 0 | N42: 0 | O42: 0 | P42: 0 | Q42: 0 | R42: 0.3 | S42: 0 | T42: 0 | U42: 0 | V42: 0 | W42: 0 | X42: 0 | Y42: 0 | Z42: 0 | AA42: 0 | AB42: 0 | AC42: 0 | AD42: 0 | AE42: 0 | AF42: 0 | AG42: 0 | AH42: =SUM(C42:AG42) -> 0.3
A43: Abril | B43: =+AH43 -> 12.48 | C43: 0 | D43: 0 | E43: 0 | F43: 0 | G43: 0 | H43: 0 | I43: 0 | J43: 0 | K43: 0.019 | L43: 0 | M43: 0 | N43: 0 | O43: 0.026 | P43: 0 | Q43: 0 | R43: 0 | S43: 0 | T43: 0 | U43: 0 | V43: 0 | W43: 0 | X43: 0 | Y43: 0.03 | Z43: 0 | AA43: 0 | AB43: 0 | AC43: 12.405 | AD43: 0 | AE43: 0 | AF43: 0 | AH43: =SUM(C43:AG43) -> 12.48
A44: Mayo | B44: =+AH44 -> 0.013 | C44: 0 | D44: 0.013 | E44: 0 | F44: 0 | G44: 0 | H44: 0 | I44: 0 | J44: 0 | K44: 0 | L44: 0 | M44: 0 | N44: 0 | O44: 0 | P44: 0 | Q44: 0 | R44: 0 | S44: 0 | T44: 0 | U44: 0 | V44: 0 | W44: 0 | X44: 0 | Y44: 0 | Z44: 0 | AA44: 0 | AB44: 0 | AC44: 0 | AD44: 0 | AE44: 0 | AF44: 0 | AG44: 0 | AH44: =SUM(C44:AG44) -> 0.013
A45: Junio | B45: =+AH45 -> 77.476 | C45: 0 | D45: 0 | E45: 0 | F45: 0 | G45: 0 | H45: 0 | I45: 22.13 | J45: 5.225 | K45: 23.546 | L45: 0 | M45: 0 | N45: 0.01 | O45: 0 | P45: 0 | Q45: 0 | R45: 0 | S45: 0 | T45: 0.025 | U45: 0 | V45: 0 | W45: 0 | X45: 0 | Y45: 0 | Z45: 0 | AA45: 0 | AB45: 0 | AC45: 26.54 | AD45: 0 | AE45: 0 | AF45: 0 | AH45: =SUM(C45:AG45) -> 77.476
A46: Julio | B46: =+AH46 -> 0.312 | C46: 0 | D46: 0 | E46: 0 | F46: 0 | G46: 0 | H46: 0 | I46: 0.012 | J46: 0 | K46: 0 | L46: 0 | M46: 0 | N46: 0 | O46: 0 | P46: 0 | Q46: 0 | R46: 0 | S46: 0 | T46: 0 | U46: 0 | V46: 0 | W46: 0.3 | X46: 0 | Y46: 0 | Z46: 0 | AA46: 0 | AB46: 0 | AC46: 0 | AD46: 0 | AE46: 0 | AF46: 0 | AG46: 0 | AH46: =SUM(C46:AG46) -> 0.312
A47: Agosto | B47: =+AH47 -> 0 | AH47: =SUM(C47:AG47) -> 0
A48: Septiembre | B48: =+AH48 -> 0 | C48: veda | D48: veda | E48: veda | F48: veda | G48: veda | H48: veda | I48: veda | J48: veda | K48: veda | L48: veda | M48: veda | N48: veda | O48: veda | P48: veda | Q48: veda | R48: veda | S48: veda | T48: veda | U48: veda | V48: veda | W48: veda | X48: veda | Y48: veda | AH48: =SUM(C48:AG48) -> 0
A49: Octubre | B49: =+AH49 -> 0 | AH49: =SUM(C49:AG49) -> 0
A50: Noviembre | B50: =+AH50 -> 0 | AH50: =SUM(C50:AG50) -> 0
A51: Diciembre | B51: =+AH51 -> 0 | P51: VEDA | Q51: VEDA | R51: VEDA | S51: VEDA | T51: VEDA | U51: VEDA | V51: VEDA | W51: VEDA | X51: VEDA | Y51: VEDA | Z51: VEDA | AA51: VEDA | AB51: VEDA | AC51: VEDA | AD51: VEDA | AE51: VEDA | AF51: VEDA | AG51: VEDA | AH51: =SUM(C51:AG51) -> 0
A52: TOTAL | B52: =SUM(B40:B51) -> 93.701 | C52: =SUM(C40:C50) -> 0 | D52: =SUM(D40:D50) -> 0.013 | E52: 0 | F52: =SUM(F40:F50) -> 0 | G52: =SUM(G40:G50) -> 0 | H52: =SUM(H40:H50) -> 0 | I52: =SUM(I40:I50) -> 22.142 | J52: =SUM(J40:J50) -> 5.225 | K52: =SUM(K40:K50) -> 23.665 | L52: =SUM(L40:L50) -> 0 | M52: =SUM(M40:M50) -> 0 | ... AC52: =SUM(AC40:AC50) -> 38.945 | AD52: 0 | AE52: =SUM(AE40:AE50) -> 0 | AF52: =SUM(AF40:AF50) -> 0 | AG52: =SUM(AG40:AG50) -> 0 | AH52: =SUM(AH40:AH50) -> 93.701
A54: V región
A56: V Región A.G. Armadores artesanales del Puerto de San Antonio R.A.G. N° 2510
A57: Mes | B57: Total mes | C57: 1 | D57: 2 | E57: 3 | F57: 4 | G57: 5 | H57: 6 | I57: 7 | J57: 8 | K57: 9 | L57: 10 | M57: 11 | N57: 12 | O57: 13 | P57: 14 | Q57: 15 | R57: 16 | S57: 17 | T57: 18 | U57: 19 | V57: 20 | W57: 21 | X57: 22 | Y57: 23 | Z57: 24 | AA57: 25 | AB57: 26 | AC57: 27 | AD57: 28 | AE57: 29 | AF57: 30 | AG57: 31 | AH57: TOTAL
A58: Enero | B58: =+AH58 -> 0 | C58: VEDA | D58: VEDA | E58: VEDA | F58: VEDA | G58: VEDA | H58: VEDA | I58: VEDA | J58: VEDA | K58: VEDA | L58: VEDA | M58: VEDA | N58: VEDA | O58: VEDA | P58: VEDA | Q58: VEDA | R58: VEDA | S58: VEDA | T58: VEDA | U58: VEDA | V58: VEDA | W58: VEDA | X58: VEDA | Y58: VEDA | Z58: VEDA | AA58: VEDA | AB58: VEDA | AC58: VEDA | AD58: VEDA | AE58: VEDA | AF58: VEDA | AG58: VEDA | AH58: =SUM(C58:AG58) -> 0
A59: Febrero | B59: =+AH59 -> 0 | C59: VEDA | D59: VEDA | E59: VEDA | F59: VEDA | G59: VEDA | H59: VEDA | I59: VEDA | J59: VEDA | K59: VEDA | L59: VEDA | M59: VEDA | N59: VEDA | O59: VEDA | P59: VEDA | Q59: VEDA | R59: VEDA | S59: VEDA | T59: VEDA | U59: VEDA | V59: VEDA | W59: VEDA | X59: VEDA | Y59: VEDA | Z59: VEDA | AA59: VEDA | AB59: VEDA | AC59: VEDA | AD59: VEDA | AE59: VEDA | AF59: VEDA | AG59: VEDA | AH59: =SUM(C59:AG59) -> 0
A60: Marzo | B60: =+AH60 -> 7 | C60: VEDA | D60: VEDA | E60: VEDA | F60: VEDA | G60: VEDA | H60: 0 | I60: 0 | J60: 0 | K60: 0 | L60: 0 | M60: 0 | N60: 0 | O60: 0 | P60: 0 | Q60: 7 | R60: 0 | S60: 0 | T60: 0 | U60: 0 | V60: 0 | W60: 0 | X60: 0 | Y60: 0 | Z60: 0 | AA60: 0 | AB60: 0 | AC60: 0 | AD60: 0 | AE60: 0 | AF60: 0 | AG60: 0 | AH60: =SUM(C60:AG60) -> 7
A61: Abril | B61: =+AH61 -> 699.441 | C61: VEDA | D61: VEDA | E61: VEDA | F61: VEDA | G61: VEDA | H61: VEDA | I61: VEDA | J61: VEDA | K61: VEDA | L61: 60.33 | M61: 8.685 | N61: 0 | O61: 39.3 | P61: 36.425 | Q61: 20.185 | R61: 31.455 | S61: 0 | T61: 43 | U61: 14.675 | V61: 21.375 | W61: 54.005 | X61: 36.915 | Y61: 63.69 | Z61: 48.265 | AA61: 57 | AB61: 0 | AC61: 26.316 | AD61: 57.175 | AE61: 29.455 | AF61: 51.19 | AG61: 0 | AH61: =SUM(C61:AG61) -> 699.441
A62: Mayo | B62: =+AH62 -> 570.205 | C62: 0 | D62: 0 | E62: 15.07 | F62: 50.41 | G62: 52.965 | H62: 0 | I62: 35.025 | J62: 39.915 | K62: 23.26 | L62: 65.96 | M62: 0 | N62: 49.63 | O62: 30.95 | P62: 18.625 | Q62: 45.52 | R62: 43.67 | S62: 2.375 | T62: 0 | U62: 0 | V62: 0 | W62: 0 | X62: 17.315 | Y62: 37.325 | Z62: 0 | AA62: 0 | AB62: 0 | AC62: 0 | AD62: 0 | AE62: 42.19 | AF62: 0 | AG62: 0 | AH62: =SUM(C62:AG62) -> 570.205
A63: Junio | B63: =+AH63 -> 191.14 | C63: 48.67 | D63: 29.615 | E63: 0 | F63: 0 | G63: 0 | H63: VEDA | I63: VEDA | J63: VEDA | K63: VEDA | L63: VEDA | M63: VEDA | N63: VEDA | O63: VEDA | P63: VEDA | Q63: VEDA | R63: VEDA | S63: VEDA | T63: VEDA | U63: VEDA | V63: VEDA | W63: VEDA | X63: VEDA | Z63: 16.06 | AA63: 65.645 | AB63: 31.15 | AC63: 0 | AD63: 0 | AE63: 0 | AF63: 0 | AG63: 0 | AH63: =SUM(C63:AG63) -> 191.14
A64: Julio | B64: =+AH64 -> 103.71 | C64: 0 | D64: 0 | E64: 0 | F64: 0 | G64: 25.5 | H64: 0 | I64: 0 | J64: 0 | K64: 0 | L64: 0 | M64: 0 | N64: 0 | O64: 30.11 | P64: 45.1 | Q64: 0 | R64: 0 | S64: 3 | T64: 0 | U64: 0 | V64: 0 | W64: 0 | X64: 0 | Y64: 0 | Z64: 0 | AA64: 0 | AB64: 0 | AC64: 0 | AD64: 0 | AE64: 0 | AF64: 0 | AG64: 0 | AH64: =SUM(C64:AG64) -> 103.71
A65: Agosto | B65: =+AH65 -> 0 | J65: veda | K65: veda | L65: veda | M65: veda | N65: veda | O65: veda | P65: veda | Q65: veda | R65: veda | S65: veda | T65: veda | U65: veda | V65: veda | W65: veda | X65: veda | Y65: veda | Z65: veda | AA65: veda | AB65: veda | AC65: veda | AD65: veda | AE65: veda | AF65: veda | AG65: veda | AH65: =SUM(C65:AG65) -> 0
A66: Septiembre | B66: =+AH66 -> 0 | C66: veda | D66: veda | E66: veda | F66: veda | G66: veda | H66: veda | I66: veda | J66: veda | K66: veda | L66: veda | M66: veda | N66: veda | O66: veda | P66: veda | Q66: veda | R66: veda | S66: veda | T66: veda | U66: veda | V66: veda | W66: veda | X66: veda | Y66: veda | Z66: veda | AA66: veda | AB66: veda | AC66: veda | AD66: veda | AE66: veda | AF66: veda | AG66: veda | AH66: =SUM(C66:AG66) -> 0
A67: Octubre | B67: =+AH67 -> 339.03 | C67: veda | D67: veda | E67: veda | F67: veda | G67: veda | H67: veda | I67: veda | J67: veda | K67: veda | L67: veda | M67: veda | N67: veda | O67: veda | P67: veda | Q67: veda | R67: veda | S67: veda | T67: veda | U67: veda | V67: veda | W67: veda | X67: 45.765 | Y67: 121.87 | Z67: 92.49 | AA67: 14.1 | AB67: 10.34 | AC67: 7.895 | AD67: 0 | AE67: 46.57 | AF67: 0 | AG67: 0 | AH67: =SUM(C67:AG67) -> 339.03
A68: Noviembre | B68: =+AH68 -> 463.08 | G68: 18.94 | H68: 17.34 | I68: 12.4 | J68: 12.625 | M68: 14.16 | N68: 34.71 | O68: 52.465 | P68: 100.255 | Q68: 63.88 | R68: 61.285 | S68: 18.38 | W68: 34.28 | AC68: 22.36 | AH68: =SUM(C68:AG68) -> 463.08
A69: Diciembre | B69: =+AH69 -> 0 | P69: VEDA | Q69: VEDA | R69: VEDA | S69: VEDA | T69: VEDA | U69: VEDA | V69: VEDA | W69: VEDA | X69: VEDA | Y69: VEDA | Z69: VEDA | AA69: VEDA | AB69: VEDA | AC69: VEDA | AD69: VEDA | AE69: VEDA | AF69: VEDA | AG69: VEDA | AH69: =SUM(C69:AG69) -> 0
A70: TOTAL | B70: =SUM(B58:B69) -> 2373.606 | C70: =SUM(C58:C68) -> 48.67 | D70: =SUM(D58:D68) -> 29.615 | E70: 0 | F70: =SUM(F58:F68) -> 50.41 | G70: =SUM(G58:G68) -> 97.405 | H70: =SUM(H58:H68) -> 17.34 | I70: =SUM(I58:I68) -> 47.425 | J70: =SUM(J58:J68) -> 52.54 | K70: =SUM(K58:K68) -> 23.26 | L70: =SUM(L58:L68) -> 126.29 | M70: =SUM(M58:M68) -> 22.845 | ... AC70: =SUM(AC58:AC68) -> 56.571 | AD70: 0 | AE70: =SUM(AE58:AE68) -> 118.215 | AF70: =SUM(AF58:AF68) -> 51.19 | AG70: =SUM(AG58:AG68) -> 0 | AH70: =SUM(AH58:AH68) -> 2373.606
A72: Cuota bolsón o residual
A73: Mes | B73: Total mes | C73: 1 | D73: 2 | E73: 3 | F73: 4 | G73: 5 | H73: 6 | I73: 7 | J73: 8 | K73: 9 | L73: 10 | M73: 11 | N73: 12 | O73: 13 | P73: 14 | Q73: 15 | R73: 16 | S73: 17 | T73: 18 | U73: 19 | V73: 20 | W73: 21 | X73: 22 | Y73: 23 | Z73: 24 | AA73: 25 | AB73: 26 | AC73: 27 | AD73: 28 | AE73: 29 | AF73: 30 | AG73: 31 | AH73: TOTAL
A74: Enero | B74: =+AH74 -> 0 | C74: VEDA | D74: VEDA | E74: VEDA | F74: VEDA | G74: VEDA | H74: VEDA | I74: VEDA | J74: VEDA | K74: VEDA | L74: VEDA | M74: VEDA | N74: VEDA | O74: VEDA | P74: VEDA | Q74: VEDA | R74: VEDA | S74: VEDA | T74: VEDA | U74: VEDA | V74: VEDA | W74: VEDA | X74: VEDA | Y74: VEDA | Z74: VEDA | AA74: VEDA | AB74: VEDA | AC74: VEDA | AD74: VEDA | AE74: VEDA | AF74: VEDA | AG74: VEDA | AH74: =SUM(C74:AG74) -> 0
A75: Febrero | B75: =+AH75 -> 0 | C75: VEDA | D75: VEDA | E75: VEDA | F75: VEDA | G75: VEDA | H75: VEDA | I75: VEDA | J75: VEDA | K75: VEDA | L75: VEDA | M75: VEDA | N75: VEDA | O75: VEDA | P75: VEDA | Q75: VEDA | R75: VEDA | S75: VEDA | T75: VEDA | U75: VEDA | V75: VEDA | W75: VEDA | X75: VEDA | Y75: VEDA | Z75: VEDA | AA75: VEDA | AB75: VEDA | AC75: VEDA | AD75: VEDA | AE75: VEDA | AF75: VEDA | AG75: VEDA | AH75: =SUM(C75:AG75) -> 0
A76: Marzo | B76: =+AH76 -> 0 | C76: VEDA | D76: VEDA | E76: VEDA | F76: VEDA | G76: VEDA | AC76: VEDA | AD76: VEDA | AE76: VEDA | AF76: VEDA | AG76: VEDA | AH76: =SUM(C76:AG76) -> 0
A77: Abril | B77: =+AH77 -> 36.095 | C77: VEDA | D77: VEDA | E77: VEDA | F77: VEDA | G77: VEDA | H77: VEDA | I77: VEDA | J77: VEDA | K77: VEDA | L77: 16.315 | M77: 0 | N77: 0 | O77: 0 | P77: 0 | Q77: 0 | R77: 0 | S77: 0 | T77: 0 | U77: 0 | V77: 0 | W77: 0 | X77: 0 | Y77: 0 | Z77: 0 | AA77: 0 | AB77: 0 | AC77: 8.24 | AD77: 0 | AE77: 11.54 | AF77: 0 | AG77: 0 | AH77: =SUM(C77:AG77) -> 36.095
A78: Mayo | B78: =+AH78 -> 0 | C78: 0 | D78: 0 | E78: 0 | F78: 0 | G78: 0 | H78: 0 | I78: 0 | J78: 0 | K78: 0 | L78: 0 | M78: 0 | N78: 0 | O78: 0 | P78: 0 | Q78: 0 | R78: 0 | S78: 0 | AH78: =SUM(C78:AG78) -> 0
A79: Junio | B79: =+AH79 -> 0 | H79: veda | I79: veda | J79: veda | K79: veda | L79: veda | M79: veda | N79: veda | O79: veda | P79: veda | Q79: veda | R79: veda | S79: veda | T79: veda | U79: veda | V79: veda | W79: veda | X79: veda | AH79: =SUM(C79:AG79) -> 0
A80: Julio | B80: =+AH80 -> 0 | AH80: =SUM(C80:AG80) -> 0
A81: Agosto | B81: =+AH81 -> 0 | J81: veda | K81: veda | L81: veda | M81: veda | N81: veda | O81: veda | P81: veda | Q81: veda | R81: veda | S81: veda | T81: veda | U81: veda | V81: veda | W81: veda | X81: veda | Y81: veda | Z81: veda | AA81: veda | AB81: veda | AC81: veda | AD81: veda | AE81: veda | AF81: veda | AG81: veda | AH81: =SUM(C81:AG81) -> 0
A82: Septiembre | B82: =+AH82 -> 0 | C82: veda | D82: veda | E82: veda | F82: veda | G82: veda | H82: veda | I82: veda | J82: veda | K82: veda | L82: veda | M82: veda | N82: veda | O82: veda | P82: veda | Q82: veda | R82: veda | S82: veda | T82: veda | U82: veda | V82: veda | W82: veda | X82: veda | Y82: veda | Z82: veda | AA82: veda | AB82: veda | AC82: veda | AD82: veda | AE82: veda | AF82: veda | AG82: veda | AH82: =SUM(C82:AG82) -> 0
A83: Octubre | B83: =+AH83 -> 0 | C83: veda | D83: veda | E83: veda | F83: veda | G83: veda | H83: veda | I83: veda | J83: veda | K83: veda | L83: veda | M83: veda | N83: veda | O83: veda | P83: veda | Q83: veda | R83: veda | S83: veda | T83: veda | U83: veda | V83: veda | W83: veda | AH83: =SUM(C83:AG83) -> 0
A84: Noviembre | B84: =+AH84 -> 0 | AH84: =SUM(C84:AG84) -> 0
A85: Diciembre | B85: =+AH85 -> 0 | C85: 0 | P85: VEDA | Q85: VEDA | R85: VEDA | S85: VEDA | T85: VEDA | U85: VEDA | V85: VEDA | W85: VEDA | X85: VEDA | Y85: VEDA | Z85: VEDA | AA85: VEDA | AB85: VEDA | AC85: VEDA | AD85: VEDA | AE85: VEDA | AF85: VEDA | AG85: VEDA | AH85: =SUM(C85:AG85) -> 0
A86: TOTAL | B86: =SUM(B74:B85) -> 36.095 | C86: =SUM(C74:C84) -> 0 | D86: =SUM(D74:D84) -> 0 | E86: 0 | F86: =SUM(F74:F84) -> 0 | G86: =SUM(G74:G84) -> 0 | H86: =SUM(H74:H84) -> 0 | I86: =SUM(I74:I84) -> 0 | J86: =SUM(J74:J84) -> 0 | K86: =SUM(K74:K84) -> 0 | L86: =SUM(L74:L84) -> 16.315 | M86: =SUM(M74:M84) -> 0 | ... AC86: =SUM(AC74:AC84) -> 8.24 | AD86: 0 | AE86: =SUM(AE74:AE84) -> 11.54 | AF86: =SUM(AF74:AF84) -> 0 | AG86: =SUM(AG74:AG84) -> 0 | AH86: =SUM(AH74:AH84) -> 36.095
A88: VII Región, del Maule
A89: STI. De Pesc. Pelagícos del Maule, Constitución RSU. N° 07050150
A90: Mes | B90: Total mes | C90: 1 | D90: 2 | E90: 3 | F90: 4 | G90: 5 | H90: 6 | I90: 7 | J90: 8 | K90: 9 | L90: 10 | M90: 11 | N90: 12 | O90: 13 | P90: 14 | Q90: 15 | R90: 16 | S90: 17 | T90: 18 | U90: 19 | V90: 20 | W90: 21 | X90: 22 | Y90: 23 | Z90: 24 | AA90: 25 | AB90: 26 | AC90: 27 | AD90: 28 | AE90: 29 | AF90: 30 | AG90: 31 | AH90: TOTAL
A91: Enero | B91: =+AH91 -> 0 | C91: veda | D91: veda | E91: veda | F91: veda | G91: veda | H91: veda | I91: veda | J91: veda | K91: veda | L91: veda | M91: veda | N91: veda | O91: veda | P91: veda | Q91: veda | R91: veda | S91: veda | T91: veda | U91: veda | V91: veda | W91: veda | X91: veda | Y91: veda | Z91: veda | AA91: veda | AB91: veda | AC91: veda | AD91: veda | AE91: veda | AF91: veda | AG91: veda | AH91: =SUM(C91:AG91) -> 0
A92: Febrero | B92: =+AH92 -> 0 | C92: veda | D92: veda | E92: veda | F92: veda | G92: veda | H92: veda | I92: veda | J92: veda | K92: veda | L92: veda | M92: veda | N92: veda | O92: veda | P92: veda | Q92: veda | R92: veda | S92: veda | T92: veda | U92: veda | V92: veda | W92: veda | X92: veda | Y92: veda | Z92: veda | AA92: veda | AB92: veda | AC92: veda | AD92: veda | AE92: veda | AF92: veda | AG92: veda | AH92: =SUM(C92:AG92) -> 0
A93: Marzo | B93: =+AH93 -> 8.762 | C93: veda | D93: veda | E93: veda | F93: veda | G93: veda | U93: 4.841 | X93: 3.921 | AC93: veda | AD93: veda | AE93: veda | AF93: veda | AG93: veda | AH93: =SUM(C93:AG93) -> 8.762
A94: Abril | B94: =+AH94 -> 324.844 | C94: veda | D94: veda | E94: veda | F94: veda | G94: veda | H94: veda | I94: veda | J94: veda | K94: veda | Q94: 28.256 | R94: 10.76 | S94: 8.066 | T94: 12.452 | U94: 33.511 | V94: 8.352 | W94: 25.314 | X94: 87.291 | Z94: 16.428 | AA94: 42.647 | AC94: 51.767 | AH94: =SUM(C94:AG94) -> 324.844
A95: Mayo | B95: =+AH95 -> 61.3 | C95: 25.562 | F95: 15.155 | G95: 20.583 | AH95: =SUM(C95:AG95) -> 61.3
A96: Junio | B96: =+AH96 -> 0 | H96: veda | I96: veda | J96: veda | K96: veda | L96: veda | M96: veda | N96: veda | O96: veda | P96: veda | Q96: veda | R96: veda | S96: veda | T96: veda | U96: veda | V96: veda | W96: veda | X96: veda | AH96: =SUM(C96:AG96) -> 0
A97: Julio | B97: =+AH97 -> 0 | AH97: =SUM(C97:AG97) -> 0
A98: Agosto | B98: =+AH98 -> 0 | J98: VEDA | K98: VEDA | L98: VEDA | M98: VEDA | N98: VEDA | O98: VEDA | P98: VEDA | Q98: VEDA | R98: VEDA | S98: VEDA | T98: VEDA | U98: VEDA | V98: VEDA | W98: VEDA | X98: VEDA | Y98: VEDA | Z98: VEDA | AA98: VEDA | AB98: VEDA | AC98: VEDA | AD98: VEDA | AE98: VEDA | AF98: VEDA | AG98: VEDA | AH98: =SUM(C98:AG98) -> 0
A99: Septiembre | B99: =+AH99 -> 0 | C99: VEDA | D99: VEDA | E99: VEDA | F99: VEDA | G99: VEDA | H99: VEDA | I99: VEDA | J99: VEDA | K99: VEDA | L99: VEDA | M99: VEDA | N99: VEDA | O99: VEDA | P99: VEDA | Q99: VEDA | R99: VEDA | S99: VEDA | T99: VEDA | U99: VEDA | V99: VEDA | W99: VEDA | X99: VEDA | Y99: VEDA | Z99: VEDA | AA99: VEDA | AB99: VEDA | AC99: VEDA | AD99: VEDA | AE99: VEDA | AF99: VEDA | AG99: VEDA | AH99: =SUM(C99:AG99) -> 0
A100: Octubre | B100: =+AH100 -> 0 | C100: VEDA | D100: VEDA | E100: VEDA | F100: VEDA | G100: VEDA | H100: VEDA | I100: VEDA | J100: VEDA | K100: VEDA | L100: VEDA | M100: VEDA | N100: VEDA | O100: VEDA | P100: VEDA | Q100: VEDA | R100: VEDA | S100: VEDA | T100: VEDA | U100: VEDA | V100: VEDA | W100: VEDA | AH100: =SUM(C100:AG100) -> 0
A101: Noviembre | B101: =+AH101 -> 0 | AH101: =SUM(C101:AG101) -> 0
A102: Diciembre | B102: =+AH102 -> 0 | P102: VEDA | Q102: VEDA | R102: VEDA | S102: VEDA | T102: VEDA | U102: VEDA | V102: VEDA | W102: VEDA | X102: VEDA | Y102: VEDA | Z102: VEDA | AA102: VEDA | AB102: VEDA | AC102: VEDA | AD102: VEDA | AE102: VEDA | AF102: VEDA | AG102: VEDA | AH102: =SUM(C102:AG102) -> 0
A103: TOTAL | B103: =SUM(B91:B102) -> 394.906 | C103: =SUM(C91:C102) -> 25.562 | D103: =SUM(D91:D102) -> 0 | E103: =SUM(E91:E102) -> 0 | F103: =SUM(F91:F102) -> 15.155 | G103: =SUM(G91:G102) -> 20.583 | H103: =SUM(H91:H102) -> 0 | I103: =SUM(I91:I102) -> 0 | ... AH103: =SUM(AH91:AH102) -> 394.906
A105: Cuota Residual
A106: Mes | B106: Total mes | C106: 1 | D106: 2 | E106: 3 | F106: 4 | G106: 5 | H106: 6 | I106: 7 | J106: 8 | K106: 9 | L106: 10 | M106: 11 | N106: 12 | O106: 13 | P106: 14 | Q106: 15 | R106: 16 | S106: 17 | T106: 18 | U106: 19 | V106: 20 | W106: 21 | X106: 22 | Y106: 23 | Z106: 24 | AA106: 25 | AB106: 26 | AC106: 27 | AD106: 28 | AE106: 29 | AF106: 30 | AG106: 31 | AH106: TOTAL
A107: Enero | B107: =+AH107 -> 0 | C107: VEDA | D107: VEDA | E107: VEDA | F107: VEDA | G107: VEDA | H107: VEDA | I107: VEDA | J107: VEDA | K107: VEDA | L107: VEDA | M107: VEDA | N107: VEDA | O107: VEDA | P107: VEDA | Q107: VEDA | R107: VEDA | S107: VEDA | T107: VEDA | U107: VEDA | V107: VEDA | W107: VEDA | X107: VEDA | Y107: VEDA | Z107: VEDA | AA107: VEDA | AB107: VEDA | AC107: VEDA | AD107: VEDA | AE107: VEDA | AF107: VEDA | AG107: VEDA | AH107: =SUM(C107:AG107) -> 0
A108: Febrero | B108: =+AH108 -> 0 | C108: VEDA | D108: VEDA | E108: VEDA | F108: VEDA | G108: VEDA | H108: VEDA | I108: VEDA | J108: VEDA | K108: VEDA | L108: VEDA | M108: VEDA | N108: VEDA | O108: VEDA | P108: VEDA | Q108: VEDA | R108: VEDA | S108: VEDA | T108: VEDA | U108: VEDA | V108: VEDA | W108: VEDA | X108: VEDA | Y108: VEDA | Z108: VEDA | AA108: VEDA | AB108: VEDA | AC108: VEDA | AD108: VEDA | AE108: VEDA | AF108: VEDA | AG108: VEDA | AH108: =SUM(C108:AG108) -> 0
A109: Marzo | B109: =+AH109 -> 28.649 | C109: VEDA | D109: VEDA | E109: VEDA | F109: VEDA | G109: VEDA | W109: 28.649 | AH109: =SUM(C109:AG109) -> 28.649
A110: Abril | B110: =+AH110 -> 90.897 | C110: VEDA | D110: VEDA | E110: VEDA | F110: VEDA | G110: VEDA | H110: VEDA | I110: VEDA | J110: VEDA | K110: 0.09 | O110: 1.647 | P110: 14.852 | R110: 20.152 | U110: 10.709 | W110: 11.479 | X110: 17.538 | AA110: 14.43 | AH110: =SUM(C110:AG110) -> 90.897
...

Sheet Anchoveta
A2: Anchoveta 2012
A5: XV y I Región, Arica e Iquique
A6: Mes | B6: Total mes | C6: 1 | D6: 2 | E6: 3 | F6: 4 | G6: 5 | H6: 6 | I6: 7 | J6: 8 | K6: 9 | L6: 10 | M6: 11 | N6: 12 | O6: 13 | P6: 14 | Q6: 15 | R6: 16 | S6: 17 | T6: 18 | U6: 19 | V6: 20 | W6: 21 | X6: 22 | Y6: 23 | Z6: 24 | AA6: 25 | AB6: 26 | AC6: 27 | AD6: 28 | AE6: 29 | AF6: 30 | AG6: 31 | AH6: TOTAL
A7: Enero | B7: =+AH7 -> 1544.695 | AF7: 1073.91 | AG7: 470.785 | AH7: =SUM(C7:AG7) -> 1544.695
A8: Febrero | B8: =+AH8 -> 11241.526 | C8: 516.4 | D8: 893.625 | E8: 631.695 | F8: 264.525 | H8: 823.493 | I8: 450.095 | J8: 585.83 | K8: 375.055 | L8: 304.375 | M8: 72.24 | O8: 80.05 | P8: 541.025 | Q8: 231.585 | R8: 102.97 | S8: 839.878 | T8: 7.41 | V8: 325.655 | W8: 419.785 | X8: 384.675 | Y8: 362.014 | Z8: 304.513 | AA8: 512.777 | AC8: 456.496 | AD8: 930.226 | AE8: 825.134 | AH8: =SUM(C8:AG8) -> 11241.526
A9: Marzo | B9: =+AH9 -> 19300.05 | C9: 785.221 | D9: 870.064 | E9: 870.505 | G9: 1327.445 | H9: 989.355 | I9: 410 | J9: 775.912 | K9: 36.817 | L9: 917.3 | N9: 1549.513 | O9: 202.895 | P9: 727.93 | Q9: 661.997 | R9: 863.34 | U9: 1344.19 | V9: 1145.971 | W9: 1433.695 | X9: 1797.045 | Y9: 135.07 | Z9: 170.505 | AB9: 1139.07 | AC9: 385.515 | AD9: 513.445 | AF9: 4.07 | AG9: 243.18 | AH9: =SUM(C9:AG9) -> 19300.05
A10: Abril | B10: =+AH10 -> 14562.886 | D10: 18.34 | E10: 323.25 | F10: 461.55 | G10: 1239.49 | K10: 1452.015 | L10: 1060.53 | M10: 1517.385 | N10: 1334.03 | O10: 1398.051 | P10: 838.555 | R10: 18.03 | S10: 1297.69 | T10: 28.645 | U10: 377.515 | V10: 558.095 | Y10: 251 | Z10: 875.88 | AA10: 659.855 | AB10: 280.71 | AC10: 316.425 | AD10: 255.845 | AH10: =SUM(C10:AG10) -> 14562.886
A11: Mayo | B11: =+AH11 -> 14968.245 | D11: 1369.18 | E11: 510.605 | I11: 1506.08 | J11: 1298.33 | K11: 796.165 | L11: 1125.4 | M11: 1853.24 | N11: 1059.185 | P11: 1512.955 | Q11: 1504.645 | R11: 898.265 | S11: 97.48 | T11: 84.31 | X11: 103.41 | Y11: 828.855 | Z11: 399.5 | AD11: 20.64 | AH11: =SUM(C11:AG11) -> 14968.245
A12: Junio | B12: =+AH12 -> 0 | AH12: =SUM(C12:AG12) -> 0
A13: Julio | B13: =+AH13 -> 9433.058 | E13: 19.94 | F13: 199.484 | K13: 1430.97 | L13: 1003.52 | M13: 1256.123 | N13: 925.621 | O13: 787.008 | P13: 351.533 | T13: 260.775 | U13: 658.155 | V13: 4.46 | Y13: 773.005 | Z13: 259.891 | AA13: 378.5 | AB13: 83.25 | AC13: 21.11 | AD13: 417.77 | AF13: 572.503 | AG13: 29.44 | AH13: =SUM(C13:AG13) -> 9433.058
A14: Agosto | B14: =+AH14 -> 330.261 | C14: 176.946 | D14: 93.734 | F14: 54.56 | AE14: 5.021 | AH14: =SUM(C14:AG14) -> 330.261 | AI14: 116.94TON DE DESEMBARQUE DE DIA 25/11, SE IMPUTA A FRACCION ARTESANAL POR SOBREPASE DE CUOTA DE TRASPASO RES. EX. Nº 2883/2012.
A15: Septiembre | B15: =+AH15 -> 3.812 | C15: veda | D15: veda | E15: veda | F15: veda | G15: veda | H15: veda | I15: veda | J15: veda | K15: veda | L15: 3.812 | M15: veda | N15: veda | O15: veda | P15: veda | Q15: veda | R15: veda | S15: veda | T15: veda | U15: veda | V15: veda | W15: veda | X15: veda | Y15: veda | Z15: 0 | AA15: 0 | AB15: 0 | AC15: 0 | AD15: 0 | AE15: 0 | AF15: 0 | AG15: 0 | AH15: =SUM(C15:AG15) -> 3.812 | AI15: 564.18 TON DE DESEMBARQUE DE DIA 27/11, SE IMPUTA A FRACCION ARTESANAL POR SOBREPASE DE CUOTA DE TRASPASO RES. EX. Nº 2883/2012.
A16: Octubre | B16: =+AH16 -> 0 | AH16: =SUM(C16:AG16) -> 0 | AI16: 855.15 TON DE DESEMBARQUE DE DIA 28/11, SE IMPUTA A FRACCION ARTESANAL POR SOBREPASE DE CUOTA DE TRASPASO RES. EX. Nº 2883/2012.
A17: Noviembre | B17: =+AH17 -> 1540.102 | M17: 3.832 | N17: 0 | O17: 0 | AA17: 116.94 | AC17: 564.18 | AD17: 855.15 | AH17: =SUM(C17:AG17) -> 1540.102 | AI17: 341.434 TON DE DESEMBARQUE DE DIA 06/12, SE IMPUTA A FRACCION ARTESANAL
A18: Diciembre | B18: =+AH18 -> 914.799 | C18: 0 | D18: 0 | E18: 0 | F18: 0 | G18: 1 | H18: 341.434 | I18: 168.97 | J18: 0 | K18: 0 | L18: 398.215 | M18: 0 | N18: 0 | O18: 0 | P18: 0 | Q18: 0 | R18: 0 | S18: 0 | T18: 1.53 | U18: 0 | V18: 0 | W18: 0 | X18: 0 | Y18: 0 | Z18: 0 | AA18: 0 | AD18: 1.65 | AG18: 2 | AH18: =SUM(C18:AG18) -> 914.799 | AI18: 168.97 TON DE DESEMBARQUE DE DIA 07/12, SE IMPUTA A FRACCION ARTESANAL
A19: TOTAL | B19: =SUM(B7:B18) -> 73839.434 | C19: 0 | D19: 0 | E19: 0 | F19: 0 | G19: 0 | H19: 0 | I19: 0 | J19: 0 | K19: 0 | L19: 0 | M19: 0 | N19: 0 | O19: 0 | P19: 0 | Q19: 0 | R19: 0 | S19: 0 | T19: 0 | U19: 0 | V19: 0 | W19: 0 | X19: 0 | Y19: 0 | Z19: 0 | AA19: 0 | AB19: 0 | AC19: 0 | AD19: 0 | AE19: 0 | AF19: 0 | AG19: 0 | AH19: =SUM(AH7:AH18) -> 73839.434 | AI19: 398.215 TON DE DESEMBARQUE DE DIA 10/12, SE IMPUTA A FRACCION ARTESANAL
A21: II Región, de Antofasta | I21: ok
A22: Mes | B22: Total mes | C22: 1 | D22: 2 | E22: 3 | F22: 4 | G22: 5 | H22: 6 | I22: 7 | J22: 8 | K22: 9 | L22: 10 | M22: 11 | N22: 12 | O22: 13 | P22: 14 | Q22: 15 | R22: 16 | S22: 17 | T22: 18 | U22: 19 | V22: 20 | W22: 21 | X22: 22 | Y22: 23 | Z22: 24 | AA22: 25 | AB22: 26 | AC22: 27 | AD22: 28 | AE22: 29 | AF22: 30 | AG22: 31 | AH22: TOTAL
A23: Enero | B23: =+AH23 -> 0.5 | C23: veda | D23: veda | E23: veda | F23: veda | G23: veda | H23: veda | I23: veda | J23: veda | K23: veda | L23: veda | M23: veda | N23: veda | O23: veda | P23: veda | Q23: veda | R23: veda | S23: veda | T23: veda | U23: veda | V23: 0.5 | W23: veda | X23: veda | Y23: veda | Z23: veda | AA23: veda | AB23: veda | AC23: veda | AD23: veda | AE23: veda | AH23: =+V23 -> 0.5
A24: Febrero | B24: =SUM(AH24) -> 1449.015 | T24: 336.29 | U24: 101.73 | V24: 150.5 | W24: 50.785 | X24: 22.47 | Y24: 134.555 | Z24: 306.14 | AA24: 107.495 | AB24: 239.05 | AH24: =SUM(C24:AG24) -> 1449.015
A25: Marzo | B25: =SUM(AH25) -> 3734.9 | D25: 217.33 | E25: 162.425 | G25: 127.31 | H25: 227.81 | I25: 250.24 | J25: 8.365 | K25: 256.995 | L25: 225.025 | P25: 330.035 | Q25: 344.085 | R25: 111.895 | S25: 121.365 | T25: 375.935 | U25: 329.15 | V25: 179.68 | W25: 297.71 | X25: 15.635 | Y25: 15.635 | AB25: 29.39 | AC25: 11.12 | AE25: 97.765 | AH25: =SUM(C25:AG25) -> 3734.9
A26: Abril | B26: =SUM(AH26) -> 2182.99 | N26: 95.645 | O26: 8.79 | P26: 256.365 | Q26: 381.75 | R26: 291.995 | T26: 2.13 | V26: 325.175 | W26: 425.41 | X26: 116.475 | Y26: 77.51 | AB26: 80.205 | AD26: 121.54 | AH26: =SUM(C26:AG26) -> 2182.99
A27: Mayo | B27: =SUM(AH27) -> 1558.13 | E27: 207.27 | F27: 107.145 | G27: 93.995 | K27: 110.45 | L27: 27.055 | R27: 203.43 | T27: 457.455 | Z27: 120.155 | AA27: 85.06 | AB27: 38.75 | AC27: 107.065 | AE27: 0.3 | AH27: =SUM(C27:AG27) -> 1558.13
A28: Junio | B28: =SUM(AH28) -> 2269.695 | D28: 1 | G28: 182.82 | H28: 81.44 | I28: 104.18 | N28: 106.64 | O28: 168.455 | P28: 118.815 | Q28: 142.685 | R28: 83.71 | T28: 22.325 | U28: 251.215 | V28: 95.2 | W28: 171.21 | X28: 143.225 | Y28: 191.305 | Z28: 250.205 | AA28: 27.9 | AC28: 91.52 | AD28: 35.845 | AH28: =SUM(C28:AG28) -> 2269.695
A29: Julio | B29: =SUM(AH29) -> 1522.288 | G29: 104.685 | H29: 69.29 | K29: 0.023 | O29: 56.705 | S29: 214.7 | T29: 342.215 | U29: 203.385 | V29: 116.94 | X29: 161.95 | Z29: 197.465 | AE29: 54.93 | AH29: =SUM(C29:AG29) -> 1522.288
A30: Agosto | B30: =SUM(AH30) -> 849.08 | J30: 0.04 | S30: 157.125 | T30: 182.155 | U30: 101.075 | V30: 140.465 | W30: 107.92 | X30: 160 | AE30: 0.3 | AH30: =SUM(C30:AG30) -> 849.08
A31: Septiembre | B31: =SUM(AH31) -> 0.3 | C31: veda | D31: veda | E31: veda | F31: veda | G31: veda | H31: veda | I31: veda | J31: veda | K31: veda | L31: veda | M31: veda | N31: veda | O31: veda | P31: veda | Q31: veda | R31: veda | S31: veda | T31: veda | U31: veda | V31: veda | W31: veda | X31: veda | Y31: veda | AD31: 0.3 | AH31: =SUM(C31:AG31) -> 0.3
A32: Octubre | B32: =SUM(AH32) -> 744.636 | D32: 199.155 | J32: 0.15 | L32: 0.2 | T32: 0.11 | Y32: 183.335 | AA32: 143.52 | AC32: 108.9 | AE32: 57.88 | AF32: 28.39 | AG32: 22.996 | AH32: =SUM(C32:AG32) -> 744.636
A33: Noviembre | B33: =SUM(AH33) -> 2144.73 | I33: 221.34 | J33: 111.455 | K33: 188.165 | L33: 11.865 | N33: 189.57 | O33: 240.57 | P33: 110.53 | Q33: 241.285 | R33: 177.885 | S33: 139.15 | U33: 238.68 | V33: 106.385 | W33: 62.085 | X33: 70.245 | Y33: 34.3 | Z33: 1.2 | AB33: 0.02 | AH33: =SUM(C33:AG33) -> 2144.73
A34: Diciembre | B34: =SUM(AH34) -> 3557.215 | F34: 275.465 | G34: 137.68 | H34: 400.56 | L34: 286.79 | M34: 227.89 | N34: 360.845 | O34: 148.335 | P34: 245.17 | Q34: 268.375 | R34: 196.8 | T34: 35.88 | U34: 160.465 | V34: 290.375 | X34: 0.5 | Y34: 0.3 | AB34: 182.535 | AC34: 178.32 | AD34: 160.93 | AH34: =SUM(C34:AG34) -> 3557.215
A35: TOTAL | B35: =SUM(B23:B34) -> 20013.479 | AH35: =SUM(AH23:AH34) -> 20013.479
A37: III Región, de Atacama
A38: Mes | B38: Total mes | C38: 1 | D38: 2 | E38: 3 | F38: 4 | G38: 5 | H38: 6 | I38: 7 | J38: 8 | K38: 9 | L38: 10 | M38: 11 | N38: 12 | O38: 13 | P38: 14 | Q38: 15 | R38: 16 | S38: 17 | T38: 18 | U38: 19 | V38: 20 | W38: 21 | X38: 22 | Y38: 23 | Z38: 24 | AA38: 25 | AB38: 26 | AC38: 27 | AD38: 28 | AE38: 29 | AF38: 30 | AG38: 31 | AH38: TOTAL
A39: Enero | B39: =+AH39 -> 252 | G39: 120 | H39: 55 | I39: 6 | J39: 0 | K39: 0 | L39: 0 | M39: 14 | N39: 0 | O39: 0 | P39: 3 | Q39: 26 | R39: 15 | S39: 0 | T39: 0 | U39: 0 | V39: 0 | W39: 0 | X39: 0 | Y39: 0 | Z39: 0 | AA39: 0 | AB39: 0 | AC39: 0 | AD39: 0 | AE39: 0 | AF39: 0 | AG39: 13 | AH39: =SUM(C39:AG39) -> 252
A40: Febrero | B40: =+AH40 -> 1331 | C40: 0 | D40: 0 | E40: 0 | F40: 0 | G40: 0 | H40: 0 | I40: 0 | J40: 0 | K40: 0 | L40: 18 | O40: 2 | P40: 35 | Q40: 155 | R40: 137 | S40: 15 | T40: 79 | U40: 10 | V40: 148 | W40: 512 | X40: 62 | Y40: 51 | Z40: 2 | AA40: 22 | AD40: 75 | AE40: 8 | AH40: =SUM(C40:AG40) -> 1331
A41: Marzo | B41: =+AH41 -> 300 | D41: 1 | E41: 3 | I41: 16 | J41: 4 | N41: 2 | P41: 16 | R41: 23 | S41: 13 | X41: 22 | Y41: 14 | AE41: 94 | AF41: 27 | AG41: 65 | AH41: =SUM(C41:AG41) -> 300
A42: Abril | B42: =+AH42 -> 4981 | C42: 34 | D42: 38 | E42: 128 | F42: 436 | G42: 189 | K42: 132 | L42: 466 | M42: 142 | N42: 89 | O42: 23 | P42: 6 | R42: 61 | S42: 20 | T42: 438 | U42: 51 | V42: 519 | W42: 242 | X42: 619 | Y42: 469 | Z42: 216 | AA42: 257 | AB42: 238 | AC42: 31 | AD42: 137 | AH42: =SUM(C42:AG42) -> 4981
A43: Mayo | B43: =+AH43 -> 6233 | E43: 419 | F43: 188 | G43: 360 | H43: 145 | I43: 686 | J43: 1450 | K43: 324 | L43: 79 | M43: 58 | N43: 5 | O43: 0 | P43: 308 | Q43: 177 | R43: 231 | S43: 132 | T43: 24 | Z43: 467 | AA43: 316 | AB43: 216 | AC43: 345 | AD43: 138 | AG43: 165 | AH43: =SUM(C43:AG43) -> 6233
A44: Junio | B44: =+AH44 -> 1558 | C44: 96 | D44: 167 | E44: 2 | F44: 8 | I44: 126 | J44: 236 | K44: 126 | L44: 232 | M44: 435 | N44: 48 | O44: 25 | P44: 0 | Q44: 0 | R44: 0 | S44: 0 | T44: 0 | U44: 0 | V44: 0 | W44: 0 | X44: 0 | Y44: 0 | Z44: 0 | AA44: 0 | AC44: 57 | AH44: =SUM(C44:AG44) -> 1558
A45: Julio | B45: =+AH45 -> 0.21 | AC45: 0.21 | AH45: =SUM(C45:AG45) -> 0.21
A46: Agosto | B46: =+AH46 -> 0 | AA46: veda | AB46: veda | AC46: veda | AD46: veda | AE46: veda | AF46: veda | AG46: veda | AH46: =SUM(C46:AG46) -> 0
A47: Septiembre | B47: =+AH47 -> 0 | C47: veda | D47: veda | E47: veda | F47: veda | G47: veda | H47: veda | I47: veda | J47: veda | K47: veda | L47: veda | M47: veda | N47: veda | O47: veda | P47: veda | Q47: veda | R47: veda | S47: veda | T47: veda | U47: veda | V47: veda | W47: veda | X47: veda | Y47: veda | AH47: =SUM(C47:AG47) -> 0
A48: Octubre | B48: =+AH48 -> 1695 | Q48: 10 | S48: 83 | T48: 222 | U48: 323 | V48: 75 | W48: 192 | X48: 15 | Y48: 188 | Z48: 129 | AA48: 117 | AF48: 224 | AG48: 117 | AH48: =SUM(C48:AG48) -> 1695
A49: Noviembre | B49: =+AH49 -> 2662 | E49: 12 | F49: 17 | H49: 404 | I49: 623 | J49: 228 | K49: 31 | O49: 82 | P49: 8 | Q49: 281 | R49: 58 | S49: 287 | U49: 416 | V49: 132 | W49: 83 | AH49: =SUM(C49:AG49) -> 2662
A50: Diciembre | B50: =+AH50 -> 0 | AH50: =SUM(C50:AG50) -> 0
A51: TOTAL | B51: =SUM(B39:B50) -> 19012.21
A53: VI Región, de O'higgins
A54: Mes | B54: Total mes | C54: 1 | D54: 2 | E54: 3 | F54: 4 | G54: 5 | H54: 6 | I54: 7 | J54: 8 | K54: 9 | L54: 10 | M54: 11 | N54: 12 | O54: 13 | P54: 14 | Q54: 15 | R54: 16 | S54: 17 | T54: 18 | U54: 19 | V54: 20 | W54: 21 | X54: 22 | Y54: 23 | Z54: 24 | AA54: 25 | AB54: 26 | AC54: 27 | AD54: 28 | AE54: 29 | AF54: 30 | AG54: 31 | AH54: TOTAL
A55: Enero | B55: =+AH55 -> 0 | C55: VEDA | D55: VEDA | E55: VEDA | F55: VEDA | G55: VEDA | H55: VEDA | I55: VEDA | J55: VEDA | K55: VEDA | L55: VEDA | M55: VEDA | N55: VEDA | O55: VEDA | P55: VEDA | Q55: VEDA | R55: VEDA | S55: VEDA | T55: VEDA | U55: VEDA | V55: VEDA | W55: VEDA | X55: VEDA | Y55: VEDA | Z55: VEDA | AA55: VEDA | AB55: VEDA | AC55: VEDA | AD55: VEDA | AE55: VEDA | AF55: VEDA | AG55: VEDA | AH55: =SUM(C55:AG55) -> 0
A56: Febrero | B56: =+AH56 -> 0 | C56: VEDA | D56: VEDA | E56: VEDA | F56: VEDA | G56: VEDA | H56: VEDA | I56: VEDA | J56: VEDA | K56: VEDA | L56: VEDA | M56: VEDA | N56: VEDA | O56: VEDA | P56: VEDA | Q56: VEDA | R56: VEDA | S56: VEDA | T56: VEDA | U56: VEDA | V56: VEDA | W56: VEDA | X56: VEDA | Y56: VEDA | Z56: VEDA | AA56: VEDA | AB56: VEDA | AC56: VEDA | AD56: VEDA | AE56: VEDA | AF56: VEDA | AG56: VEDA | AH56: =SUM(C56:AG56) -> 0
A57: Marzo | B57: =+AH57 -> 0 | C57: VEDA | D57: VEDA | E57: VEDA | F57: VEDA | G57: VEDA | AC57: VEDA | AD57: VEDA | AE57: VEDA | AF57: VEDA | AG57: VEDA | AH57: =SUM(C57:AG57) -> 0
A58: Abril | B58: =+AH58 -> 0 | C58: VEDA | D58: VEDA | E58: VEDA | F58: VEDA | G58: VEDA | H58: VEDA | I58: VEDA | J58: VEDA | K58: VEDA | AH58: =SUM(C58:AG58) -> 0
A59: Mayo | B59: =+AH59 -> 0 | AH59: =SUM(C59:AG59) -> 0
A60: Junio | B60: =+AH60 -> 0 | H60: veda | I60: veda | J60: veda | K60: veda | L60: veda | M60: veda | N60: veda | O60: veda | P60: veda | Q60: veda | R60: veda | S60: veda | T60: veda | U60: veda | V60: veda | W60: veda | X60: veda | AH60: =SUM(C60:AG60) -> 0
A61: Julio | B61: =+AH61 -> 0 | AH61: =SUM(C61:AG61) -> 0
A62: Agosto | B62: =+AH62 -> 0 | J62: veda | K62: veda | L62: veda | M62: veda | N62: veda | O62: veda | P62: veda | Q62: veda | R62: veda | S62: veda | T62: veda | U62: veda | V62: veda | W62: veda | X62: veda | Y62: veda | Z62: veda | AA62: veda | AB62: veda | AC62: veda | AD62: veda | AE62: veda | AF62: veda | AG62: veda | AH62: =SUM(C62:AG62) -> 0
A63: Septiembre | B63: =+AH63 -> 0 | C63: veda | D63: veda | E63: veda | F63: veda | G63: veda | H63: veda | I63: veda | J63: veda | K63: veda | L63: veda | M63: veda | N63: veda | O63: veda | P63: veda | Q63: veda | R63: veda | S63: veda | T63: veda | U63: veda | V63: veda | W63: veda | X63: veda | Y63: veda | Z63: veda | AA63: veda | AB63: veda | AC63: veda | AD63: veda | AE63: veda | AF63: veda | AG63: veda | AH63: =SUM(C63:AG63) -> 0
A64: Octubre | B64: =+AH64 -> 0 | C64: veda | D64: veda | E64: veda | F64: veda | G64: veda | H64: veda | I64: veda | J64: veda | K64: veda | L64: veda | M64: veda | N64: veda | O64: veda | P64: veda | Q64: veda | R64: veda | S64: veda | T64: veda | U64: veda | V64: veda | W64: veda | AH64: =SUM(C64:AG64) -> 0
A65: Noviembre | B65: =+AH65 -> 0 | AH65: =SUM(C65:AG65) -> 0
A66: Diciembre | B66: =+AH66 -> 0 | P66: VEDA | Q66: VEDA | R66: VEDA | S66: VEDA | T66: VEDA | U66: VEDA | V66: VEDA | W66: VEDA | X66: VEDA | Y66: VEDA | Z66: VEDA | AA66: VEDA | AB66: VEDA | AC66: VEDA | AD66: VEDA | AE66: VEDA | AF66: VEDA | AG66: VEDA | AH66: =SUM(C66:AG66) -> 0
A67: TOTAL | B67: =SUM(B55:B66) -> 0 | C67: =SUM(C55:C66) -> 0 | D67: =SUM(D55:D66) -> 0 | E67: =SUM(E55:E66) -> 0 | F67: =SUM(F55:F66) -> 0 | G67: =SUM(G55:G66) -> 0 | H67: =SUM(H55:H66) -> 0 | I67: =SUM(I55:I66) -> 0 | ... AH67: =SUM(AH55:AH66) -> 0
A70: IX Región, de la Araucanía
A71: Mes | B71: Total mes | C71: 1 | D71: 2 | E71: 3 | F71: 4 | G71: 5 | H71: 6 | I71: 7 | J71: 8 | K71: 9 | L71: 10 | M71: 11 | N71: 12 | O71: 13 | P71: 14 | Q71: 15 | R71: 16 | S71: 17 | T71: 18 | U71: 19 | V71: 20 | W71: 21 | X71: 22 | Y71: 23 | Z71: 24 | AA71: 25 | AB71: 26 | AC71: 27 | AD71: 28 | AE71: 29 | AF71: 30 | AG71: 31 | AH71: TOTAL
A72: Enero | B72: =+AH72 -> 0 | C72: VEDA | D72: VEDA | E72: VEDA | F72: VEDA | G72: VEDA | H72: VEDA | I72: VEDA | J72: VEDA | K72: VEDA | L72: VEDA | M72: VEDA | N72: VEDA | O72: VEDA | P72: VEDA | Q72: VEDA | R72: VEDA | S72: VEDA | T72: VEDA | U72: VEDA | V72: VEDA | W72: VEDA | X72: VEDA | Y72: VEDA | Z72: VEDA | AA72: VEDA | AB72: VEDA | AC72: VEDA | AD72: VEDA | AE72: VEDA | AF72: VEDA | AG72: VEDA | AH72: =SUM(C72:AG72) -> 0
A73: Febrero | B73: =+AH73 -> 0 | C73: VEDA | D73: VEDA | E73: VEDA | F73: VEDA | G73: VEDA | H73: VEDA | I73: VEDA | J73: VEDA | K73: VEDA | L73: VEDA | M73: VEDA | N73: VEDA | O73: VEDA | P73: VEDA | Q73: VEDA | R73: VEDA | S73: VEDA | T73: VEDA | U73: VEDA | V73: VEDA | W73: VEDA | X73: VEDA | Y73: VEDA | Z73: VEDA | AA73: VEDA | AB73: VEDA | AC73: VEDA | AD73: VEDA | AE73: VEDA | AF73: VEDA | AG73: VEDA | AH73: =SUM(C73:AG73) -> 0
A74: Marzo | B74: =+AH74 -> 0 | C74: VEDA | D74: VEDA | E74: VEDA | F74: VEDA | G74: VEDA | AH74: =SUM(C74:AG74) -> 0
A75: Abril | B75: =+AH75 -> 7.864 | C75: VEDA | D75: VEDA | E75: VEDA | F75: VEDA | G75: VEDA | H75: VEDA | I75: VEDA | J75: VEDA | K75: VEDA | AB75: 7.864 | AH75: =SUM(C75:AG75) -> 7.864
A76: Mayo | B76: =+AH76 -> 42.787 | O76: 11.03 | X76: 16.931 | Y76: 6.037 | Z76: 8.789 | AH76: =SUM(C76:AG76) -> 42.787
A77: Junio | B77: =+AH77 -> 36.831 | H77: veda | I77: veda | J77: veda | K77: veda | L77: veda | M77: veda | N77: veda | O77: veda | P77: veda | Q77: veda | R77: veda | S77: veda | T77: veda | U77: veda | V77: veda | W77: veda | X77: veda | AA77: 36.831 | AH77: =SUM(C77:AG77) -> 36.831
A78: Julio | B78: =+AH78 -> 2.643 | L78: 2.643 | AH78: =SUM(C78:AG78) -> 2.643
A79: Agosto | B79: =+AH79 -> 0 | J79: veda | K79: veda | L79: veda | M79: veda | N79: veda | O79: veda | P79: veda | Q79: veda | R79: veda | S79: veda | T79: veda | U79: veda | V79: veda | W79: veda | X79: veda | Y79: veda | Z79: veda | AA79: veda | AB79: veda | AC79: veda | AD79: veda | AE79: veda | AF79: veda | AG79: veda | AH79: =SUM(C79:AG79) -> 0
A80: Septiembre | B80: =+AH80 -> 0 | C80: veda | D80: veda | E80: veda | F80: veda | G80: veda | H80: veda | I80: veda | J80: veda | K80: veda | L80: veda | M80: veda | N80: veda | O80: veda | P80: veda | Q80: veda | R80: veda | S80: veda | T80: veda | U80: veda | V80: veda | W80: veda | X80: veda | Y80: veda | Z80: veda | AA80: veda | AB80: veda | AC80: veda | AD80: veda | AE80: veda | AF80: veda | AG80: veda | AH80: =SUM(C80:AG80) -> 0
A81: Octubre | B81: =+AH81 -> 0 | C81: veda | D81: veda | E81: veda | F81: veda | G81: veda | H81: veda | I81: veda | J81: veda | K81: veda | L81: veda | M81: veda | N81: veda | O81: veda | P81: veda | Q81: veda | R81: veda | S81: veda | T81: veda | U81: veda | V81: veda | W81: veda | AH81: =SUM(C81:AG81) -> 0
A82: Noviembre | B82: =+AH82 -> 0 | AH82: =SUM(C82:AG82) -> 0
A83: Diciembre | B83: =+AH83 -> 0 | P83: VEDA | Q83: VEDA | R83: VEDA | S83: VEDA | T83: VEDA | U83: VEDA | V83: VEDA | W83: VEDA | X83: VEDA | Y83: VEDA | Z83: VEDA | AA83: VEDA | AB83: VEDA | AC83: VEDA | AD83: VEDA | AE83: VEDA | AF83: VEDA | AG83: VEDA | AH83: =SUM(C83:AG83) -> 0
A84: TOTAL | B84: =SUM(B72:B83) -> 90.125 | C84: =SUM(C72:C83) -> 0 | D84: =SUM(D72:D83) -> 0 | E84: =SUM(E72:E83) -> 0 | F84: =SUM(F72:F83) -> 0 | G84: =SUM(G72:G83) -> 0 | H84: =SUM(H72:H83) -> 0 | I84: =SUM(I72:I83) -> 0 | ... AH84: =SUM(AH72:AH83) -> 90.125

Sheet RAE S.común
A2: RAE Sardina común 2012
A4: V región
A6: V Región A.G. Armadores artesanales del Puerto de San Antonio R.A.G. N° 2510
A7: Mes | B7: Total mes | C7: 1 | D7: 2 | E7: 3 | F7: 4 | G7: 5 | H7: 6 | I7: 7 | J7: 8 | K7: 9 | L7: 10 | M7: 11 | N7: 12 | O7: 13 | P7: 14 | Q7: 15 | R7: 16 | S7: 17 | T7: 18 | U7: 19 | V7: 20 | W7: 21 | X7: 22 | Y7: 23 | Z7: 24 | AA7: 25 | AB7: 26 | AC7: 27 | AD7: 28 | AE7: 29 | AF7: 30 | AG7: 31 | AH7: TOTAL
A8: Enero | B8: =+AH8 -> 0 | C8: VEDA | D8: VEDA | E8: VEDA | F8: VEDA | G8: VEDA | H8: VEDA | I8: VEDA | J8: VEDA | K8: VEDA | L8: VEDA | M8: VEDA | N8: VEDA | O8: VEDA | P8: VEDA | Q8: VEDA | R8: VEDA | S8: VEDA | T8: VEDA | U8: VEDA | V8: VEDA | W8: VEDA | X8: VEDA | Y8: VEDA | Z8: VEDA | AA8: VEDA | AB8: VEDA | AC8: VEDA | AD8: VEDA | AE8: VEDA | AF8: VEDA | AG8: VEDA | AH8: =SUM(C8:AG8) -> 0
A9: Febrero | B9: =+AH9 -> 0 | C9: VEDA | D9: VEDA | E9: VEDA | F9: VEDA | G9: VEDA | H9: VEDA | I9: VEDA | J9: VEDA | K9: VEDA | L9: VEDA | M9: VEDA | N9: VEDA | O9: VEDA | P9: VEDA | Q9: VEDA | R9: VEDA | S9: VEDA | T9: VEDA | U9: VEDA | V9: VEDA | W9: VEDA | X9: VEDA | Y9: VEDA | Z9: VEDA | AA9: VEDA | AB9: VEDA | AC9: VEDA | AD9: VEDA | AE9: VEDA | AF9: VEDA | AG9: VEDA | AH9: =SUM(C9:AG9) -> 0
A10: Marzo | B10: =+AH10 -> 23.855 | C10: VEDA | D10: VEDA | E10: VEDA | F10: VEDA | G10: VEDA | L10: 0 | M10: 0 | N10: 0 | O10: 0 | P10: 0 | Q10: 23.855 | R10: 0 | S10: 0 | T10: 0 | U10: 0 | V10: 0 | W10: 0 | X10: 0 | Y10: 0 | Z10: 0 | AA10: 0 | AB10: 0 | AC10: 0 | AD10: 0 | AE10: 0 | AF10: 0 | AG10: 0 | AH10: =SUM(C10:AG10) -> 23.855
A11: Abril | B11: =+AH11 -> 2385.535 | C11: VEDA | D11: VEDA | E11: VEDA | F11: VEDA | G11: VEDA | H11: VEDA | I11: VEDA | J11: VEDA | K11: VEDA | L11: 184.625 | M11: 39.055 | N11: 0 | O11: 117.92 | P11: 109.12 | Q11: 60.555 | R11: 168.815 | S11: 0 | T11: 129.52 | U11: 44.025 | V11: 213.12 | W11: 185.565 | X11: 110.745 | Y11: 192.06 | Z11: 141 | AA11: 177.1 | AB11: 0 | AC11: 81.745 | AD11: 179.27 | AE11: 86.5 | AF11: 164.795 | AG11: 0 | AH11: =SUM(C11:AG11) -> 2385.535
A12: Mayo | B12: =+AH12 -> 1896.845 | C12: 0 | D12: 0 | E12: 46.2 | F12: 176.77 | G12: 158.88 | H12: 0 | I12: 200.865 | J12: 132.995 | K12: 68.77 | L12: 212.575 | M12: 0 | N12: 147.4 | O12: 97.435 | P12: 66.2 | Q12: 156.18 | R12: 132.8 | S12: 14.82 | T12: 45.98 | U12: 0 | V12: 0 | W12: 0 | X12: 58.62 | Y12: 124.285 | Z12: 38.695 | AA12: 0 | AB12: 0 | AC12: 0 | AD12: 0 | AE12: 17.375 | AF12: 0 | AG12: 0 | AH12: =SUM(C12:AG12) -> 1896.845
A13: Junio | B13: =+AH13 -> 647.661 | C13: 152.985 | D13: 103.58 | E13: 0 | F13: 0 | G13: 0 | H13: Veda | I13: Veda | J13: Veda | K13: Veda | L13: Veda | M13: Veda | N13: Veda | O13: Veda | P13: Veda | Q13: Veda | R13: Veda | S13: Veda | T13: Veda | U13: Veda | V13: Veda | W13: Veda | X13: Veda | Y13: 3.795 | Z13: 46.675 | AA13: 213.77 | AB13: 124.81 | AC13: 2.046 | AD13: 0 | AE13: 0 | AF13: 0 | AG13: 0 | AH13: =SUM(C13:AG13) -> 647.661
A14: Julio | B14: =+AH14 -> 427.34 | C14: 0 | D14: 0 | E14: 0 | F14: 0 | G14: 89.465 | H14: 41.2 | I14: 10.56 | J14: 0 | K14: 4.265 | L14: 0 | M14: 0 | N14: 0 | O14: 59.73 | P14: 139.995 | Q14: 29.495 | R14: 0 | S14: 10.69 | T14: 39.225 | U14: 2.715 | V14: 0 | W14: 0 | X14: 0 | Y14: 0 | Z14: 0 | AA14: 0 | AB14: 0 | AC14: 0 | AD14: 0 | AE14: 0 | AF14: 0 | AG14: 0 | AH14: =SUM(C14:AG14) -> 427.34
A15: Agosto | B15: =+AH15 -> 3.935 | C15: 0 | D15: 0 | E15: 0 | F15: 0 | G15: 0 | H15: 0 | I15: 3.935 | J15: veda | K15: veda | L15: veda | M15: veda | N15: veda | O15: veda | P15: veda | Q15: veda | R15: veda | S15: veda | T15: veda | U15: veda | V15: veda | W15: veda | X15: veda | Y15: veda | Z15: veda | AA15: veda | AB15: veda | AC15: veda | AD15: veda | AE15: veda | AF15: veda | AG15: veda | AH15: =SUM(C15:AG15) -> 3.935
A16: Septiembre | B16: =+AH16 -> 0 | C16: veda | D16: veda | E16: veda | F16: veda | G16: veda | H16: veda | I16: veda | J16: veda | K16: veda | L16: veda | M16: veda | N16: veda | O16: veda | P16: veda | Q16: veda | R16: veda | S16: veda | T16: veda | U16: veda | V16: veda | W16: veda | X16: veda | Y16: veda | Z16: veda | AA16: veda | AB16: veda | AC16: veda | AD16: veda | AE16: veda | AF16: veda | AG16: veda | AH16: =SUM(C16:AG16) -> 0
A17: Octubre | B17: =+AH17 -> 1180.975 | C17: veda | D17: veda | E17: veda | F17: veda | G17: veda | H17: veda | I17: veda | J17: veda | K17: veda | L17: veda | M17: veda | N17: veda | O17: veda | P17: veda | Q17: veda | R17: veda | S17: veda | T17: veda | U17: veda | V17: veda | W17: veda | X17: 139.145 | Y17: 363.92 | Z17: 279.16 | AA17: 112.965 | AB17: 31.02 | AC17: 48.47 | AD17: 0 | AE17: 171.605 | AF17: 34.69 | AG17: 0 | AH17: =SUM(C17:AG17) -> 1180.975
A18: Noviembre | B18: =+AH18 -> 1148.99 | C18: 0 | D18: 0 | E18: 0 | F18: 0 | G18: 72.38 | H18: 50.78 | I18: 20.63 | J18: 22.675 | K18: 0 | L18: 0 | M18: 45.365 | N18: 129.885 | O18: 156.955 | P18: 304.19 | Q18: 52.97 | R18: 42.57 | S18: 5.275 | T18: 0 | U18: 2.5 | V18: 8.345 | W18: 14.97 | X18: 0 | Y18: 0 | Z18: 0 | AA18: 0 | AB18: 17.08 | AC18: 202.42 | AD18: 0 | AE18: 0 | AF18: 0 | AG18: 0 | AH18: =SUM(C18:AG18) -> 1148.99
A19: Diciembre | B19: =+AH19 -> 0 | C19: 0 | D19: 0 | E19: 0 | F19: 0 | G19: 0 | H19: 0 | I19: 0 | J19: 0 | K19: 0 | L19: 0 | M19: 0 | N19: 0 | O19: 0 | P19: VEDA | Q19: VEDA | R19: VEDA | S19: VEDA | T19: VEDA | U19: VEDA | V19: VEDA | W19: VEDA | X19: VEDA | Y19: VEDA | Z19: VEDA | AA19: VEDA | AB19: VEDA | AC19: VEDA | AD19: VEDA | AE19: VEDA | AF19: VEDA | AG19: VEDA | AH19: =SUM(C19:AG19) -> 0
A20: Total | B20: =SUM(B8:B19) -> 7715.136 | C20: =SUM(C8:C18) -> 152.985 | D20: =SUM(D8:D18) -> 103.58 | E20: 0 | F20: =SUM(F8:F18) -> 176.77 | G20: =SUM(G8:G18) -> 320.725 | H20: =SUM(H8:H18) -> 91.98 | I20: =SUM(I8:I18) -> 235.99 | J20: =SUM(J8:J18) -> 155.67 | K20: =SUM(K8:K18) -> 73.035 | L20: =SUM(L8:L18) -> 397.2 | M20: =SUM(M8:M18) -> 84.42 | ... AC20: =SUM(AC8:AC18) -> 334.681 | AD20: 0 | AE20: =SUM(AE8:AE18) -> 275.48 | AF20: =SUM(AF8:AF18) -> 199.485 | AG20: =SUM(AG8:AG18) -> 0 | AH20: =SUM(AH8:AH18) -> 7715.136
A22: Cuota bolsón o residual
A23: Mes | B23: Total mes | C23: 1 | D23: 2 | E23: 3 | F23: 4 | G23: 5 | H23: 6 | I23: 7 | J23: 8 | K23: 9 | L23: 10 | M23: 11 | N23: 12 | O23: 13 | P23: 14 | Q23: 15 | R23: 16 | S23: 17 | T23: 18 | U23: 19 | V23: 20 | W23: 21 | X23: 22 | Y23: 23 | Z23: 24 | AA23: 25 | AB23: 26 | AC23: 27 | AD23: 28 | AE23: 29 | AF23: 30 | AG23: 31 | AH23: TOTAL
A24: Enero | B24: =+AH24 -> 13.13 | C24: veda | D24: veda | E24: veda | F24: veda | G24: veda | H24: 0.3 | I24: veda | J24: veda | K24: veda | L24: 0.2 | M24: 0.1 | N24: 0.9 | O24: 0.35 | P24: 0.2 | Q24: 0.4 | R24: 0.5 | S24: 0.4 | T24: 1.3 | U24: 1.2 | V24: 1.1 | W24: 0.5 | X24: 1 | Y24: veda | Z24: veda | AA24: veda | AB24: 0.08 | AC24: 1.8 | AD24: 0.8 | AE24: 1 | AF24: veda | AG24: 1 | AH24: =SUM(C24:AG24) -> 13.13
A25: Febrero | B25: =+AH25 -> 19.13 | C25: 1 | D25: veda | E25: 0.4 | F25: 0.35 | G25: veda | H25: veda | I25: 0.5 | J25: 0.4 | K25: 1.25 | L25: 1.6 | M25: veda | N25: veda | O25: veda | P25: veda | Q25: 0.02 | R25: veda | S25: veda | T25: 0.8 | U25: 1 | V25: veda | W25: 0.6 | X25: 1 | Y25: 1.6 | Z25: 4 | AA25: 2.61 | AB25: veda | AC25: veda | AD25: 1 | AE25: 1 | AF25: veda | AG25: veda | AH25: =SUM(C25:AG25) -> 19.13
A26: Marzo | B26: =+AH26 -> 20.195 | C26: vada | D26: 0.8 | E26: 0.5 | F26: veda | G26: veda | H26: 0 | I26: 0 | J26: 0.3 | K26: 0 | L26: 1 | M26: 0.8 | N26: 0 | O26: 0.8 | P26: 0 | Q26: 0.5 | R26: 13.795 | S26: 0 | T26: 0 | U26: 0 | V26: 1 | W26: 0.5 | X26: 0 | Y26: 0 | Z26: 0.2 | AA26: 0 | AB26: 0 | AC26: veda | AD26: veda | AE26: veda | AF26: veda | AG26: veda | AH26: =SUM(C26:AG26) -> 20.195
A27: Abril | B27: =+AH27 -> 605.475 | C27: vada | D27: veda | E27: veda | F27: veda | G27: veda | H27: veda | I27: veda | J27: veda | K27: veda | L27: 52.27 | M27: 0 | N27: 0 | O27: 13.005 | P27: 18.05 | Q27: 40.785 | R27: 15.98 | S27: 0 | T27: 0 | U27: 61.16 | V27: 83.96 | W27: 40.455 | X27: 83.83 | Y27: 21 | Z27: 93.565 | AA27: 12 | AB27: 0 | AC27: 24.72 | AD27: 3.45 | AE27: 41.245 | AF27: 0 | AG27: 0 | AH27: =SUM(C27:AG27) -> 605.475
A28: Mayo | B28: =+AH28 -> 507.161 | C28: 0 | D28: 0 | E28: 7.47 | F28: 45.41 | G28: 66.435 | H28: 0 | I28: 20 | J28: 128.536 | K28: 32.68 | L28: 28.28 | M28: 0 | N28: 5.51 | O28: 45.91 | P28: 0 | Q28: 44.07 | R28: 43.535 | S28: 8.32 | T28: 0 | U28: 0 | V28: 0 | W28: 0 | X28: 13.43 | Y28: 7.255 | Z28: 10.32 | AA28: 0 | AB28: 0 | AC28: 0 | AD28: 0 | AE28: 0 | AF28: 0 | AG28: 0 | AH28: =SUM(C28:AG28) -> 507.161
A29: Junio | B29: =+AH29 -> 262.28 | C29: 42 | D29: 27.825 | E29: 0 | F29: 0 | G29: 0 | H29: Veda | I29: Veda | J29: Veda | K29: Veda | L29: Veda | M29: Veda | N29: Veda | O29: Veda | P29: Veda | Q29: Veda | R29: Veda | S29: Veda | T29: Veda | U29: Veda | V29: Veda | W29: Veda | X29: Veda | Y29: 34.36 | Z29: 21.9 | AA29: 74.115 | AB29: 62.08 | AC29: 0 | AD29: 0 | AE29: 0 | AF29: 0 | AG29: 0 | AH29: =SUM(C29:AG29) -> 262.28
A30: Julio | B30: =+AH30 -> 162.63 | C30: 0 | D30: 0 | E30: 0 | F30: 50 | G30: 16.905 | H30: 8 | I30: 0 | J30: 0 | K30: 4.38 | L30: 0 | M30: 0 | N30: 0 | O30: 28.415 | P30: 23.1 | Q30: 4.855 | R30: 5.74 | S30: 0 | T30: 18.975 | U30: 0 | V30: 0 | W30: 0 | X30: 0 | Y30: 1 | Z30: 0 | AA30: 0 | AB30: 0 | AC30: 0 | AD30: 0 | AE30: 0 | AF30: 0 | AG30: 1.26 | AH30: =SUM(C30:AG30) -> 162.63
A31: Agosto | B31: =+AH31 -> 0 | C31: 0 | D31: 0 | E31: 0 | F31: 0 | G31: 0 | H31: 0 | I31: 0 | J31: veda | K31: veda | L31: veda | M31: veda | N31: veda | O31: veda | P31: veda | Q31: veda | R31: veda | S31: veda | T31: veda | U31: veda | V31: veda | W31: veda | X31: veda | Y31: veda | Z31: veda | AA31: veda | AB31: veda | AC31: veda | AD31: veda | AE31: veda | AF31: veda | AG31: veda | AH31: =SUM(C31:AG31) -> 0
A32: Septiembre | B32: =+AH32 -> 6.45 | C32: 0 | D32: 0 | E32: 0 | F32: 0.2 | G32: 0 | H32: 0.3 | I32: 0 | J32: 1.8 | K32: 0 | L32: 0 | M32: 0 | N32: 0.35 | O32: 0.3 | P32: 2 | Q32: 0 | R32: 0 | S32: 0 | T32: 0 | U32: 0 | V32: 0 | W32: 0 | X32: 0 | Y32: 0 | Z32: 1.5 | AA32: 0 | AB32: 0 | AC32: 0 | AD32: 0 | AE32: 0 | AF32: 0 | AG32: 0 | AH32: =SUM(C32:AG32) -> 6.45
A33: Octubre | B33: =+AH33 -> 123.21 | C33: 0 | D33: 0 | E33: 0 | F33: 0 | G33: 0 | H33: 0 | I33: 0 | J33: 0 | K33: 0 | L33: 0 | M33: 3.4 | N33: 0 | O33: 0 | P33: 0 | Q33: 0 | R33: 0 | S33: 0 | T33: 0.4 | U33: 2.5 | V33: 0 | W33: 0 | X33: 13.115 | Y33: 0 | Z33: 53.19 | AA33: 5 | AB33: 0 | AC33: 7.905 | AD33: 0 | AE33: 17.7 | AF33: 20 | AG33: 0 | AH33: =SUM(C33:AG33) -> 123.21
A34: Noviembre | B34: =+AH34 -> 224.665 | C34: 0 | D34: 0 | E34: 0 | F34: 0 | G34: 20.245 | H34: 6.205 | I34: 0 | J34: 0 | K34: 0 | L34: 0 | M34: 0 | N34: 7.275 | O34: 38.43 | P34: 33.91 | Q34: 9.465 | R34: 15.22 | S34: 15.31 | T34: 0 | U34: 0 | V34: 0.08 | W34: 0.06 | X34: 1.2 | Y34: 0 | Z34: 0 | AA34: 0 | AB34: 0 | AC34: 29.315 | AD34: 23.955 | AE34: 4 | AF34: 19.995 | AG34: 0 | AH34: =SUM(C34:AG34) -> 224.665
A35: Diciembre | B35: =+AH35 -> 52.65 | C35: 0 | D35: 5.75 | E35: 0 | F35: 8.97 | G35: 0 | H35: 0 | I35: 3.71 | J35: 0 | K35: 2.5 | L35: 2.25 | M35: 0 | N35: 0 | O35: 22.29 | P35: 2.2 | Q35: 0 | R35: 0 | S35: 0 | T35: 0 | U35: 0 | V35: 0 | W35: 4.68 | X35: 0 | Y35: 0 | Z35: 0 | AA35: 0 | AB35: 0 | AC35: 0 | AD35: 0.3 | AE35: 0 | AF35: 0 | AG35: 0 | AH35: =SUM(C35:AG35) -> 52.65
A36: TOTAL | B36: =SUM(B24:B35) -> 1996.976 | C36: =SUM(C24:C34) -> 43 | D36: =SUM(D24:D34) -> 28.625 | E36: 0 | F36: =SUM(F24:F34) -> 95.96 | G36: =SUM(G24:G34) -> 103.585 | H36: =SUM(H24:H34) -> 14.805 | I36: =SUM(I24:I34) -> 20.5 | J36: =SUM(J24:J34) -> 131.036 | K36: =SUM(K24:K34) -> 38.31 | L36: =SUM(L24:L34) -> 83.35 | M36: =SUM(M24:M34) -> 4.3 | ... AC36: =SUM(AC24:AC34) -> 63.74 | AD36: 0 | AE36: =SUM(AE24:AE34) -> 64.945 | AF36: =SUM(AF24:AF34) -> 39.995 | AG36: =SUM(AG24:AG34) -> 2.26 | AH36: =SUM(AH24:AH34) -> 1944.326
A38: VII Región, del Maule
A39: STI. De Pesc. Pelagícos del Maule, Constitución RSU. N° 07050150
A40: Mes | B40: Total mes | C40: 1 | D40: 2 | E40: 3 | F40: 4 | G40: 5 | H40: 6 | I40: 7 | J40: 8 | K40: 9 | L40: 10 | M40: 11 | N40: 12 | O40: 13 | P40: 14 | Q40: 15 | R40: 16 | S40: 17 | T40: 18 | U40: 19 | V40: 20 | W40: 21 | X40: 22 | Y40: 23 | Z40: 24 | AA40: 25 | AB40: 26 | AC40: 27 | AD40: 28 | AE40: 29 | AF40: 30 | AG40: 31 | AH40: TOTAL
A41: Enero | B41: =+AH41 -> 0 | C41: VEDA | D41: VEDA | E41: VEDA | F41: VEDA | G41: VEDA | H41: VEDA | I41: VEDA | J41: VEDA | K41: VEDA | L41: VEDA | M41: VEDA | N41: VEDA | O41: VEDA | P41: VEDA | Q41: VEDA | R41: VEDA | S41: VEDA | T41: VEDA | U41: VEDA | V41: VEDA | W41: VEDA | X41: VEDA | Y41: VEDA | Z41: VEDA | AA41: VEDA | AB41: VEDA | AC41: VEDA | AD41: VEDA | AE41: VEDA | AF41: VEDA | AG41: VEDA | AH41: =SUM(C41:AG41) -> 0
A42: Febrero | B42: =+AH42 -> 0 | C42: VEDA | D42: VEDA | E42: VEDA | F42: VEDA | G42: VEDA | H42: VEDA | I42: VEDA | J42: VEDA | K42: VEDA | L42: VEDA | M42: VEDA | N42: VEDA | O42: VEDA | P42: VEDA | Q42: VEDA | R42: VEDA | S42: VEDA | T42: VEDA | U42: VEDA | V42: VEDA | W42: VEDA | X42: VEDA | Y42: VEDA | Z42: VEDA | AA42: VEDA | AB42: VEDA | AC42: VEDA | AD42: VEDA | AE42: VEDA | AF42: VEDA | AG42: VEDA | AH42: =SUM(C42:AG42) -> 0
A43: Marzo | B43: =+AH43 -> 224.813 | C43: VEDA | D43: VEDA | E43: VEDA | F43: VEDA | G43: VEDA | K43: 40.86 | M43: 49.7 | R43: 54.46 | T43: 4.505 | U43: 43.569 | X43: 31.719 | AH43: =SUM(C43:AG43) -> 224.813
A44: Abril | B44: =+AH44 -> 751.458 | C44: VEDA | D44: VEDA | E44: VEDA | F44: VEDA | G44: VEDA | H44: VEDA | I44: VEDA | J44: VEDA | K44: VEDA | M44: 15.61 | O44: 48.72 | Q44: 36.786 | R44: 157.63 | S44: 59.144 | T44: 100.978 | U44: 10.009 | V44: 20.888 | W44: 1.616 | X44: 4.529 | Z44: 113.952 | AA44: 79.073 | AC44: 102.523 | AH44: =SUM(C44:AG44) -> 751.458
A45: Mayo | B45: =+AH45 -> 211.445 | C45: 114.648 | F45: 81.705 | G45: 15.092 | AH45: =SUM(C45:AG45) -> 211.445
A46: Junio | B46: =+AH46 -> 0 | H46: Veda | I46: Veda | J46: Veda | K46: Veda | L46: Veda | M46: Veda | N46: Veda | O46: Veda | P46: Veda | Q46: Veda | R46: Veda | S46: Veda | T46: Veda | U46: Veda | V46: Veda | W46: Veda | X46: Veda | AH46: =SUM(C46:AG46) -> 0
A47: Julio | B47: =+AH47 -> 224.512 | I47: 31.1 | K47: 65.1 | R47: 105.289 | U47: 7.157 | W47: 15.866 | AH47: =SUM(C47:AG47) -> 224.512
A48: Agosto | B48: =+AH48 -> 0 | J48: veda | K48: veda | L48: veda | M48: veda | N48: veda | O48: veda | P48: veda | Q48: veda | R48: veda | S48: veda | T48: veda | U48: veda | V48: veda | W48: veda | X48: veda | Y48: veda | Z48: veda | AA48: veda | AB48: veda | AC48: veda | AD48: veda | AE48: veda | AF48: veda | AG48: veda | AH48: =SUM(C48:AG48) -> 0
A49: Septiembre | B49: =+AH49 -> 0 | C49: veda | D49: veda | E49: veda | F49: veda | G49: veda | H49: veda | I49: veda | J49: veda | K49: veda | L49: veda | M49: veda | N49: veda | O49: veda | P49: veda | Q49: veda | R49: veda | S49: veda | T49: veda | U49: veda | V49: veda | W49: veda | X49: veda | Y49: veda | Z49: veda | AA49: veda | AB49: veda | AC49: veda | AD49: veda | AE49: veda | AF49: veda | AG49: veda | AH49: =SUM(C49:AG49) -> 0
A50: Octubre | B50: =+AH50 -> 120.17 | C50: veda | D50: veda | E50: veda | F50: veda | G50: veda | H50: veda | I50: veda | J50: veda | K50: veda | L50: veda | M50: veda | N50: veda | O50: veda | P50: veda | Q50: veda | R50: veda | S50: veda | T50: veda | U50: veda | V50: veda | W50: veda | Z50: 80.749 | AD50: 39.421 | AH50: =SUM(C50:AG50) -> 120.17
A51: Noviembre | B51: =+AH51 -> 0 | AH51: =SUM(C51:AG51) -> 0
A52: Diciembre | B52: =+AH52 -> 0 | P52: VEDA | Q52: VEDA | R52: VEDA | S52: VEDA | T52: VEDA | U52: VEDA | V52: VEDA | W52: VEDA | X52: VEDA | Y52: VEDA | Z52: VEDA | AA52: VEDA | AB52: VEDA | AC52: VEDA | AD52: VEDA | AE52: VEDA | AF52: VEDA | AG52: VEDA | AH52: =SUM(C52:AG52) -> 0
A53: TOTAL | B53: =SUM(B41:B52) -> 1532.398 | C53: =SUM(C41:C52) -> 114.648 | D53: =SUM(D41:D52) -> 0 | E53: =SUM(E41:E52) -> 0 | F53: =SUM(F41:F52) -> 81.705 | G53: =SUM(G41:G52) -> 15.092 | H53: =SUM(H41:H52) -> 0 | I53: =SUM(I41:I52) -> 31.1 | ... R53: =SUM(R41:R52) -> 317.379 | S53: =SUM(S41:S51) -> 59.144 | T53: =SUM(T41:T51) -> 105.483 | U53: =SUM(U41:U51) -> 60.735 | V53: =SUM(V41:V51) -> 20.888 | W53: =SUM(W41:W51) -> 17.482 | X53: =SUM(X41:X51) -> 36.248 | Y53: =SUM(Y41:Y51) -> 0 | Z53: =SUM(Z41:Z51) -> 194.701 | ... AC53: =SUM(AC41:AC51) -> 102.523 | AD53: 0 | AE53: =SUM(AE41:AE51) -> 0 | AF53: =SUM(AF41:AF51) -> 0 | AG53: =SUM(AG41:AG51) -> 0 | AH53: =SUM(AH41:AH51) -> 1532.398
A55: Cuota Residual
A56: Mes | B56: Total mes | C56: 1 | D56: 2 | E56: 3 | F56: 4 | G56: 5 | H56: 6 | I56: 7 | J56: 8 | K56: 9 | L56: 10 | M56: 11 | N56: 12 | O56: 13 | P56: 14 | Q56: 15 | R56: 16 | S56: 17 | T56: 18 | U56: 19 | V56: 20 | W56: 21 | X56: 22 | Y56: 23 | Z56: 24 | AA56: 25 | AB56: 26 | AC56: 27 | AD56: 28 | AE56: 29 | AF56: 30 | AG56: 31 | AH56: TOTAL
A57: Enero | B57: =+AH57 -> 0 | C57: VEDA | D57: VEDA | E57: VEDA | F57: VEDA | G57: VEDA | H57: VEDA | I57: VEDA | J57: VEDA | K57: VEDA | L57: VEDA | M57: VEDA | N57: VEDA | O57: VEDA | P57: VEDA | Q57: VEDA | R57: VEDA | S57: VEDA | T57: VEDA | U57: VEDA | V57: VEDA | W57: VEDA | X57: VEDA | Y57: VEDA | Z57: VEDA | AA57: VEDA | AB57: VEDA | AC57: VEDA | AD57: VEDA | AE57: VEDA | AF57: VEDA | AG57: VEDA | AH57: =SUM(C57:AG57) -> 0
A58: Febrero | B58: =+AH58 -> 0 | C58: VEDA | D58: VEDA | E58: VEDA | F58: VEDA | G58: VEDA | H58: VEDA | I58: VEDA | J58: VEDA | K58: VEDA | L58: VEDA | M58: VEDA | N58: VEDA | O58: VEDA | P58: VEDA | Q58: VEDA | R58: VEDA | S58: VEDA | T58: VEDA | U58: VEDA | V58: VEDA | W58: VEDA | X58: VEDA | Y58: VEDA | Z58: VEDA | AA58: VEDA | AB58: VEDA | AC58: VEDA | AD58: VEDA | AE58: VEDA | AF58: VEDA | AG58: VEDA | AH58: =SUM(C58:AG58) -> 0
A59: Marzo | B59: =+AH59 -> 33.631 | C59: VEDA | D59: VEDA | E59: VEDA | F59: VEDA | G59: VEDA | W59: 33.631 | AC59: VEDA | AD59: VEDA | AE59: VEDA | AF59: VEDA | AG59: VEDA | AH59: =SUM(C59:AG59) -> 33.631
A60: Abril | B60: =+AH60 -> 356.73 | C60: VEDA | D60: VEDA | E60: VEDA | F60: VEDA | G60: VEDA | H60: VEDA | I60: VEDA | J60: VEDA | K60: VEDA | L60: 0.2 | M60: 62.1 | O60: 39.533 | P60: 1.118 | R60: 51.818 | U60: 35.851 | W60: 31.788 | X60: 24.552 | Z60: 68.7 | AA60: 41.07 | AH60: =SUM(C60:AG60) -> 356.73
A61: Mayo | B61: =+AH61 -> 0 | AH61: =SUM(C61:AG61) -> 0
A62: Junio | B62: =+AH62 -> 0 | H62: Veda | I62: Veda | J62: Veda | K62: Veda | L62: Veda | M62: Veda | N62: Veda | O62: Veda | P62: Veda | Q62: Veda | R62: Veda | S62: Veda | T62: Veda | U62: Veda | V62: Veda | W62: Veda | X62: Veda | AH62: =SUM(C62:AG62) -> 0
A63: Julio | B63: =+AH63 -> 0 | AH63: =SUM(C63:AG63) -> 0
A64: Agosto | B64: =+AH64 -> 0 | J64: veda | K64: veda | L64: veda | M64: veda | N64: veda | O64: veda | P64: veda | Q64: veda | R64: veda | S64: veda | T64: veda | U64: veda | V64: veda | W64: veda | X64: veda | Y64: veda | Z64: veda | AA64: veda | AB64: veda | AC64: veda | AD64: veda | AE64: veda | AF64: veda | AG64: veda | AH64: =SUM(C64:AG64) -> 0
A65: Septiembre | B65: =+AH65 -> 0 | C65: veda | D65: veda | E65: veda | F65: veda | G65: veda | H65: veda | I65: veda | J65: veda | K65: veda | L65: veda | M65: veda | N65: veda | O65: veda | P65: veda | Q65: veda | R65: veda | S65: veda | T65: veda | U65: veda | V65: veda | W65: veda | X65: veda | Y65: veda | Z65: veda | AA65: veda | AB65: veda | AC65: veda | AD65: veda | AE65: veda | AF65: veda | AG65: veda | AH65: =SUM(C65:AG65) -> 0
A66: Octubre | B66: =+AH66 -> 0 | C66: veda | D66: veda | E66: veda | F66: veda | G66: veda | H66: veda | I66: veda | J66: veda | K66: veda | L66: veda | M66: veda | N66: veda | O66: veda | P66: veda | Q66: veda | R66: veda | S66: veda | T66: veda | U66: veda | V66: veda | W66: veda | AH66: =SUM(C66:AG66) -> 0
A67: Noviembre | B67: =+AH67 -> 0 | AH67: =SUM(C67:AG67) -> 0
A68: Diciembre | B68: =+AH68 -> 0 | P68: VEDA | Q68: VEDA | R68: VEDA | S68: VEDA | T68: VEDA | U68: VEDA | V68: VEDA | W68: VEDA | X68: VEDA | Y68: VEDA | Z68: VEDA | AA68: VEDA | AB68: VEDA | AC68: VEDA | AD68: VEDA | AE68: VEDA | AF68: VEDA | AG68: VEDA | AH68: =SUM(C68:AG68) -> 0
A69: TOTAL | B69: =SUM(B57:B68) -> 390.361 | C69: =SUM(C57:C68) -> 0 | D69: =SUM(D57:D68) -> 0 | E69: =SUM(E57:E68) -> 0 | F69: =SUM(F57:F68) -> 0 | G69: =SUM(G57:G68) -> 0 | H69: =SUM(H57:H68) -> 0 | I69: =SUM(I57:I68) -> 0 | ... R69: =SUM(R57:R68) -> 51.818 | S69: =SUM(S57:S67) -> 0 | T69: =SUM(T57:T67) -> 0 | U69: =SUM(U57:U67) -> 35.851 | V69: =SUM(V57:V67) -> 0 | W69: =SUM(W57:W67) -> 65.419 | X69: =SUM(X57:X67) -> 24.552 | Y69: =SUM(Y57:Y67) -> 0 | Z69: =SUM(Z57:Z67) -> 68.7 | ... AC69: =SUM(AC57:AC67) -> 0 | AD69: 0 | AE69: =SUM(AE57:AE67) -> 0 | AF69: =SUM(AF57:AF67) -> 0 | AG69: =SUM(AG57:AG67) -> 0 | AH69: =SUM(AH57:AH67) -> 390.361
A71: XIV Región, de Los Ríos
A73: ACERVAL., R.A.G. 207-10
A74: Mes | B74: Total mes | C74: 1 | D74: 2 | E74: 3 | F74: 4 | G74: 5 | H74: 6 | I74: 7 | J74: 8 | K74: 9 | L74: 10 | M74: 11 | N74: 12 | O74: 13 | P74: 14 | Q74: 15 | R74: 16 | S74: 17 | T74: 18 | U74: 19 | V74: 20 | W74: 21 | X74: 22 | Y74: 23 | Z74: 24 | AA74: 25 | AB74: 26 | AC74: 27 | AD74: 28 | AE74: 29 | AF74: 30 | AG74: 31 | AH74: TOTAL
A75: Enero | B75: =+AH75 -> 0 | C75: VEDA | D75: VEDA | E75: VEDA | F75: VEDA | G75: VEDA | H75: VEDA | I75: VEDA | AH75: =SUM(C75:AG75) -> 0
A76: Febrero | B76: =+AH76 -> 3487.026 | J76: 357.195 | K76: 20.21 | N76: 397.118 | P76: 415.265 | R76: 434.11 | V76: 429.18 | X76: 479.795 | Y76: 62.575 | AA76: 610.113 | AC76: 281.465 | AH76: =SUM(C76:AG76) -> 3487.026
A77: Marzo | B77: =+AH77 -> 7462.343 | C77: 332.265 | E77: 429.2 | J77: 417.262 | L77: 757.714 | N77: 708.305 | O77: 352.148 | P77: 404.05 | R77: 434.845 | S77: 419.44 | T77: 142.575 | U77: 485.114 | V77: 332.575 | W77: 341.6 | Y77: 387.835 | Z77: 393.355 | AA77: 409.365 | AB77: 218.485 | AC77: 371.8 | AD77: 124.41 | AE77: VEDA | AF77: VEDA | AG77: VEDA | AH77: =SUM(C77:AG77) -> 7462.343
A78: Abril | B78: =+AH78 -> 6815.25 | C78: VEDA | D78: VEDA | E78: VEDA | F78: VEDA | G78: VEDA | H78: VEDA | I78: VEDA | J78: VEDA | K78: VEDA | L78: 224.025 | M78: 196.785 | N78: 426.65 | O78: 353.065 | P78: 278.905 | Q78: 636.66 | R78: 359.15 | S78: 410.755 | T78: 131.08 | U78: 267.265 | V78: 271.985 | W78: 619.645 | X78: 415.24 | Y78: 477.65 | Z78: 327.925 | AA78: 232.6 | AB78: 365.23 | AC78: 333.135 | AD78: 487.5 | AH78: =SUM(C78:AG78) -> 6815.25
A79: Mayo | B79: =+AH79 -> 3625.914 | F79: 187.889 | G79: 497.305 | H79: 306.258 | I79: 59.935 | J79: 328.305 | K79: 399.315 | L79: 72.275 | M79: 59.835 | N79: 140.64 | O79: 256.45 | V79: 64.525 | W79: 519.996 | X79: 123.748 | Y79: 17.41 | AF79: 244.634 | AG79: 347.394 | AH79: =SUM(C79:AG79) -> 3625.914
A80: Junio | B80: =+AH80 -> 482.485 | C80: 202.965 | D80: 154.885 | E80: 90.46 | F80: 34.175 | H80: Veda | I80: Veda | J80: Veda | K80: Veda | L80: Veda | M80: Veda | N80: Veda | O80: Veda | P80: Veda | Q80: Veda | R80: Veda | S80: Veda | T80: Veda | U80: Veda | V80: Veda | W80: Veda | X80: Veda | AH80: =SUM(C80:AG80) -> 482.485
A81: Julio | B81: =+AH81 -> 698.235 | E81: 164.965 | AA81: 53.12 | AB81: 62.925 | AC81: 74.23 | AF81: 118.98 | AG81: 224.015 | AH81: =SUM(C81:AG81) -> 698.235
A82: Agosto | B82: =+AH82 -> 2013.671 | E82: 417.383 | F82: 411.25 | G82: 343.235 | H82: 580.564 | I82: 217.699 | J82: 43.54 | K82: veda | L82: veda | M82: veda | N82: veda | O82: veda | P82: veda | Q82: veda | R82: veda | S82: veda | T82: veda | U82: veda | V82: veda | W82: veda | X82: veda | Y82: veda | Z82: veda | AA82: veda | AB82: veda | AC82: veda | AD82: veda | AE82: veda | AF82: veda | AG82: veda | AH82: =SUM(C82:AG82) -> 2013.671
A83: Septiembre | B83: =+AH83 -> 0 | C83: veda | D83: veda | E83: veda | F83: veda | G83: veda | H83: veda | I83: veda | J83: veda | K83: veda | L83: veda | M83: veda | N83: veda | O83: veda | P83: veda | Q83: veda | R83: veda | S83: veda | T83: veda | U83: veda | V83: veda | W83: veda | X83: veda | Y83: veda | Z83: veda | AA83: veda | AB83: veda | AC83: veda | AD83: veda | AE83: veda | AF83: veda | AG83: veda | AH83: =SUM(C83:AG83) -> 0
A84: Octubre | B84: =+AH84 -> 3693.712 | C84: veda | D84: veda | E84: veda | F84: veda | G84: veda | H84: veda | I84: veda | J84: veda | K84: veda | L84: veda | M84: veda | N84: veda | O84: veda | P84: veda | Q84: veda | R84: veda | S84: veda | T84: veda | U84: veda | V84: veda | W84: veda | X84: 490.365 | Y84: 489.84 | Z84: 513.425 | AA84: 327.41 | AC84: 448.245 | AD84: 345.97 | AE84: 422.365 | AF84: 309.99 | AG84: 346.102 | AH84: =SUM(C84:AG84) -> 3693.712
A85: Noviembre | B85: =+AH85 -> 3661.824 | C85: 483.01 | D85: 232.908 | E85: 351.223 | F85: 421.239 | G85: 249.93 | H85: 226.369 | I85: 174.47 | K85: 174.87 | L85: 123.465 | M85: 375.801 | N85: 71.31 | P85: 95.115 | R85: 114.2 | U85: 43.52 | V85: 52.59 | W85: 10.93 | X85: 40.488 | Y85: 27.275 | Z85: 60.375 | AA85: 59.815 | AB85: 27.745 | AC85: 59.14 | AE85: 116.112 | AF85: 69.924 | AH85: =SUM(C85:AG85) -> 3661.824
A86: Diciembre | B86: =+AH86 -> 667.172 | C86: 46.82 | P86: 44.485 | Q86: 72.74 | R86: 18.647 | S86: 0 | T86: 0 | U86: 0 | V86: 0 | W86: 67.591 | X86: 11.822 | Y86: 0 | Z86: 0 | AA86: 0 | AB86: 80.325 | AC86: 125.287 | AD86: 69.84 | AE86: 0 | AF86: 0 | AG86: 129.615 | AH86: =SUM(C86:AG86) -> 667.172
A87: TOTAL | B87: =SUM(B75:B86) -> 32607.632 | C87: =SUM(C75:C85) -> 1018.24 | D87: =SUM(D75:D85) -> 387.793 | E87: 0 | F87: =SUM(F75:F85) -> 1054.553 | G87: =SUM(G75:G85) -> 1090.47 | H87: =SUM(H75:H85) -> 1113.191 | I87: =SUM(I75:I85) -> 452.104 | J87: =SUM(J75:J85) -> 1146.302 | K87: =SUM(K75:K85) -> 594.395 | L87: =SUM(L75:L85) -> 1177.479 | M87: =SUM(M75:M85) -> 632.421 | ... AC87: =SUM(AC75:AC85) -> 1568.015 | AD87: 0 | AE87: =SUM(AE75:AE85) -> 538.477 | AF87: =SUM(AF75:AF85) -> 743.528 | AG87: =SUM(AG75:AG85) -> 917.511 | AH87: =SUM(AH75:AH85) -> 31940.46
A89: ACER., R.A.G. 3793 de 2007
A90: Mes | B90: Total mes | C90: 1 | D90: 2 | E90: 3 | F90: 4 | G90: 5 | H90: 6 | I90: 7 | J90: 8 | K90: 9 | L90: 10 | M90: 11 | N90: 12 | O90: 13 | P90: 14 | Q90: 15 | R90: 16 | S90: 17 | T90: 18 | U90: 19 | V90: 20 | W90: 21 | X90: 22 | Y90: 23 | Z90: 24 | AA90: 25 | AB90: 26 | AC90: 27 | AD90: 28 | AE90: 29 | AF90: 30 | AG90: 31 | AH90: TOTAL
A91: Enero | B91: =+AH91 -> 0 | C91: VEDA | D91: VEDA | E91: VEDA | F91: VEDA | G91: VEDA | H91: VEDA | I91: VEDA | AH91: =SUM(C91:AG91) -> 0
A92: Febrero | B92: =+AH92 -> 2079.23 | J92: 96.79 | K92: 119.14 | L92: 68.4 | N92: 160.99 | O92: 70.95 | P92: 85.98 | Q92: 163.64 | R92: 134.86 | S92: 63.19 | T92: 69.07 | U92: 131.77 | V92: 40.38 | W92: 60.68 | X92: 179.56 | Y92: 185.11 | Z92: 103.42 | AA92: 135.51 | AB92: 66.57 | AE92: 143.22 | AH92: =SUM(C92:AG92) -> 2079.23
A93: Marzo | B93: =+AH93 -> 1319.4 | C93: 134.03 | D93: 169.03 | E93: 243.84 | F93: 53.26 | G93: 134.91 | H93: 166.25 | J93: 65.86 | M93: 14.58 | N93: 59.66 | O93: 53.25 | P93: 55.63 | Q93: 57.44 | R93: 111.66 | AC93: VEDA | AD93: VEDA | AE93: VEDA | AF93: VEDA | AG93: VEDA | AH93: =SUM(C93:AG93) -> 1319.4
A94: Abril | B94: =+AH94 -> 252.28 | C94: VEDA | D94: VEDA | E94: VEDA | F94: VEDA | G94: VADA | H94: VEDA | I94: VEDA | J94: VEDA | K94: VADA | AA94: 54.73 | AB94: =69.25+58.75 -> 128 | AC94: 69.55 | AH94: =SUM(C94:AG94) -> 252.28
A95: Mayo | B95: =+AH95 -> 1343.354 | G95: 236.45 | H95: 141.72 | J95: 131.49 | K95: 78.41 | L95: 82.68 | N95: 152.45 | O95: 87.98 | V95: 47.21 | W95: 172.42 | AA95: 14.85 | AG95: 197.694 | AH95: =SUM(C95:AG95) -> 1343.354
A96: Junio | B96: =+AH96 -> 61.97 | E96: 46.09 | F96: 15.88 | H96: Veda | I96: Veda | J96: Veda | K96: Veda | L96: Veda | M96: Veda | N96: Veda | O96: Veda | P96: Veda | Q96: Veda | R96: Veda | S96: Veda | T96: Veda | U96: Veda | V96: Veda | W96: Veda | X96: Veda | AH96: =SUM(C96:AG96) -> 61.97
A97: Julio | B97: =+AH97 -> 7.82 | AC97: 7.82 | AH97: =SUM(C97:AG97) -> 7.82
A98: Agosto | B98: =+AH98 -> 97.88 | F98: 2.2 | G98: 95.68 | J98: veda | K98: veda | L98: veda | M98: veda | N98: veda | O98: veda | P98: veda | Q98: veda | R98: veda | S98: veda | T98: veda | U98: veda | V98: veda | W98: veda | X98: veda | Y98: veda | Z98: veda | AA98: veda | AB98: veda | AC98: veda | AD98: veda | AE98: veda | AF98: veda | AG98: veda | AH98: =SUM(C98:AG98) -> 97.88
A99: Septiembre | B99: =+AH99 -> 0 | C99: veda | D99: veda | E99: veda | F99: veda | G99: veda | H99: veda | I99: veda | J99: veda | K99: veda | L99: veda | M99: veda | N99: veda | O99: veda | P99: veda | Q99: veda | R99: veda | S99: veda | T99: veda | U99: veda | V99: veda | W99: veda | X99: veda | Y99: veda | Z99: veda | AA99: veda | AB99: veda | AC99: veda | AD99: veda | AE99: veda | AF99: veda | AG99: veda | AH99: =SUM(C99:AG99) -> 0
A100: Octubre | B100: =+AH100 -> 231.75 | C100: veda | D100: veda | E100: veda | F100: veda | G100: veda | H100: veda | I100: veda | J100: veda | K100: veda | L100: veda | M100: veda | N100: veda | O100: veda | P100: veda | Q100: veda | R100: veda | S100: veda | T100: veda | U100: veda | V100: veda | W100: veda | Z100: 66.43 | AC100: 65.79 | AD100: 34.46 | AE100: 25.41 | AF100: 39.66 | AH100: =SUM(C100:AG100) -> 231.75
A101: Noviembre | B101: =+AH101 -> 1001.144 | C101: 193.87 | D101: 39.224 | E101: 15.35 | F101: 39.66 | H101: 98.75 | K101: 124.24 | L101: 107.53 | M101: 124.94 | N101: 7.85 | R101: 68.03 | W101: 29.09 | X101: 49.05 | Z101: 79.13 | AA101: 24.43 | AH101: =SUM(C101:AG101) -> 1001.144
A102: Diciembre | B102: =+AH102 -> 18.22 | P102: 0 | Q102: 0 | R102: 0 | S102: 0 | T102: 0 | U102: 0 | V102: 0 | W102: 0 | X102: 18.22 | Y102: 0 | Z102: 0 | AA102: 0 | AB102: 0 | AC102: 0 | AD102: 0 | AE102: 0 | AF102: 0 | AG102: 0 | AH102: =SUM(C102:AG102) -> 18.22
A103: TOTAL | B103: =SUM(B91:B102) -> 6413.048 | C103: =SUM(C91:C101) -> 327.9 | D103: =SUM(D91:D101) -> 208.254 | E103: 0 | F103: =SUM(F91:F101) -> 111 | G103: =SUM(G91:G101) -> 467.04 | H103: =SUM(H91:H101) -> 406.72 | I103: =SUM(I91:I101) -> 0 | J103: =SUM(J91:J101) -> 294.14 | K103: =SUM(K91:K101) -> 321.79 | L103: =SUM(L91:L101) -> 258.61 | M103: =SUM(M91:M101) -> 139.52 | ... AC103: =SUM(AC91:AC101) -> 143.16 | AD103: 0 | AE103: =SUM(AE91:AE101) -> 168.63 | AF103: =SUM(AF91:AF101) -> 39.66 | AG103: =SUM(AG91:AG101) -> 197.694 | AH103: =SUM(AH91:AH101) -> 6394.828
A105: ARMAPES., R.A.G. 264-10
A106: Mes | B106: Total mes | C106: 1 | D106: 2 | E106: 3 | F106: 4 | G106: 5 | H106: 6 | I106: 7 | J106: 8 | K106: 9 | L106: 10 | M106: 11 | N106: 12 | O106: 13 | P106: 14 | Q106: 15 | R106: 16 | S106: 17 | T106: 18 | U106: 19 | V106: 20 | W106: 21 | X106: 22 | Y106: 23 | Z106: 24 | AA106: 25 | AB106: 26 | AC106: 27 | AD106: 28 | AE106: 29 | AF106: 30 | AG106: 31 | AH106: TOTAL
A107: Enero | B107: =+AH107 -> 0 | C107: VEDA | D107: VEDA | E107: VEDA | F107: VEDA | G107: VEDA | H107: VEDA | I107: VEDA | AH107: =SUM(C107:AG107) -> 0
A108: Febrero | B108: =+AH108 -> 0 | AH108: =SUM(C108:AG108) -> 0
A109: Marzo | B109: =+AH109 -> 256.92 | V109: 46.775 | Y109: 45.08 | Z109: 27.23 | AA109: 41.53 | AC109: 50.25 | AD109: 46.055 | AE109: VEDA | AF109: VEDA | AG109: VEDA | AH109: =SUM(C109:AG109) -> 256.92
A110: Abril | B110: =+AH110 -> 628.168 | C110: VEDA | D110: VEDA | E110: VEDA | F110: VEDA | G110: VEDA | H110: VEDA | I110: VEDA | J110: VEDA | K110: VEDA | L110: 50.095 | N110: 53.98 | O110: 55.185 | P110: 51.085 | R110: 23.57 | S110: 71.123 | U110: 28.755 | V110: 30.755 | W110: 53.39 | X110: 43.635 | Y110: 47.425 | Z110: 22.115 | AA110: 28.595 | AB110: 15.73 | AD110: 52.73 | AH110: =SUM(C110:AG110) -> 628.168
...

Sheet S.común
A2: Sardina común 2012
A5: VI Región, de O'higgins
A6: Mes | B6: Total mes | C6: 1 | D6: 2 | E6: 3 | F6: 4 | G6: 5 | H6: 6 | I6: 7 | J6: 8 | K6: 9 | L6: 10 | M6: 11 | N6: 12 | O6: 13 | P6: 14 | Q6: 15 | R6: 16 | S6: 17 | T6: 18 | U6: 19 | V6: 20 | W6: 21 | X6: 22 | Y6: 23 | Z6: 24 | AA6: 25 | AB6: 26 | AC6: 27 | AD6: 28 | AE6: 29 | AF6: 30 | AG6: 31 | AH6: TOTAL
A7: Enero | B7: =+AH7 -> 0 | C7: VEDA | D7: VEDA | E7: VEDA | F7: VEDA | G7: VEDA | H7: VEDA | I7: VEDA | J7: VEDA | K7: VEDA | L7: VEDA | M7: VEDA | N7: VEDA | O7: VEDA | P7: VEDA | Q7: VEDA | R7: VEDA | S7: VEDA | T7: VEDA | U7: VEDA | V7: VEDA | W7: VEDA | X7: VEDA | Y7: VEDA | Z7: VEDA | AA7: VEDA | AB7: VEDA | AC7: VEDA | AD7: VEDA | AE7: VEDA | AF7: VEDA | AG7: VEDA | AH7: =SUM(C7:AG7) -> 0
A8: Febrero | B8: =+AH8 -> 0 | C8: VEDA | D8: VEDA | E8: VEDA | F8: VEDA | G8: VEDA | H8: VEDA | I8: VEDA | J8: VEDA | K8: VEDA | L8: VEDA | M8: VEDA | N8: VEDA | O8: VEDA | P8: VEDA | Q8: VEDA | R8: VEDA | S8: VEDA | T8: VEDA | U8: VEDA | V8: VEDA | W8: VEDA | X8: VEDA | Y8: VEDA | Z8: VEDA | AA8: VEDA | AB8: VEDA | AC8: VEDA | AD8: VEDA | AE8: VEDA | AF8: VEDA | AG8: VEDA | AH8: =SUM(C8:AG8) -> 0
A9: Marzo | B9: =+AH9 -> 0 | C9: VEDA | D9: VEDA | E9: VEDA | F9: VEDA | G9: VEDA | AC9: VEDA | AD9: VEDA | AE9: VEDA | AF9: VEDA | AG9: VEDA | AH9: =SUM(C9:AG9) -> 0
A10: Abril | B10: =+AH10 -> 0 | C10: VEDA | D10: VEDA | E10: VEDA | F10: VEDA | G10: VEDA | H10: VEDA | I10: VEDA | J10: VEDA | K10: VEDA | AH10: =SUM(C10:AG10) -> 0
A11: Mayo | B11: =+AH11 -> 0 | AH11: =SUM(C11:AG11) -> 0
A12: Junio | B12: =+AH12 -> 0 | H12: Veda | I12: Veda | J12: Veda | K12: Veda | L12: Veda | M12: Veda | N12: Veda | O12: Veda | P12: Veda | Q12: Veda | R12: Veda | S12: Veda | T12: Veda | U12: Veda | V12: Veda | W12: Veda | X12: Veda | AH12: =SUM(C12:AG12) -> 0
A13: Julio | B13: =+AH13 -> 0 | AH13: =SUM(C13:AG13) -> 0
A14: Agosto | B14: =+AH14 -> 0 | J14: veda | K14: veda | L14: veda | M14: veda | N14: veda | O14: veda | P14: veda | Q14: veda | R14: veda | S14: veda | T14: veda | U14: veda | V14: veda | W14: veda | X14: veda | Y14: veda | Z14: veda | AA14: veda | AB14: veda | AC14: veda | AD14: veda | AE14: veda | AF14: veda | AG14: veda | AH14: =SUM(C14:AG14) -> 0
A15: Septiembre | B15: =+AH15 -> 0 | C15: veda | D15: veda | E15: veda | F15: veda | G15: veda | H15: veda | I15: veda | J15: veda | K15: veda | L15: veda | M15: veda | N15: veda | O15: veda | P15: veda | Q15: veda | R15: veda | S15: veda | T15: veda | U15: veda | V15: veda | W15: veda | X15: veda | Y15: veda | Z15: veda | AA15: veda | AB15: veda | AC15: veda | AD15: veda | AE15: veda | AF15: veda | AG15: veda | AH15: =SUM(C15:AG15) -> 0
A16: Octubre | B16: =+AH16 -> 0 | C16: veda | D16: veda | E16: veda | F16: veda | G16: veda | H16: veda | I16: veda | J16: veda | K16: veda | L16: veda | M16: veda | N16: veda | O16: veda | P16: veda | Q16: veda | R16: veda | S16: veda | T16: veda | U16: veda | V16: veda | W16: veda | AH16: =SUM(C16:AG16) -> 0
A17: Noviembre | B17: =+AH17 -> 0 | AH17: =SUM(C17:AG17) -> 0
A18: Diciembre | B18: =+AH18 -> 0 | P18: VEDA | Q18: VEDA | R18: VEDA | S18: VEDA | T18: VEDA | U18: VEDA | V18: VEDA | W18: VEDA | X18: VEDA | Y18: VEDA | Z18: VEDA | AA18: VEDA | AB18: VEDA | AC18: VEDA | AD18: VEDA | AE18: VEDA | AF18: VEDA | AG18: VEDA | AH18: =SUM(C18:AG18) -> 0
A19: Total | B19: =SUM(B7:B18) -> 0 | C19: =SUM(C7:C18) -> 0 | D19: =SUM(D7:D18) -> 0 | E19: =SUM(E7:E18) -> 0 | F19: =SUM(F7:F18) -> 0 | G19: =SUM(G7:G18) -> 0 | H19: =SUM(H7:H18) -> 0 | I19: =SUM(I7:I18) -> 0 | ... AH19: =SUM(AH7:AH18) -> 0
A21: IX Región, de la Araucanía
A22: Mes | B22: Total mes | C22: 1 | D22: 2 | E22: 3 | F22: 4 | G22: 5 | H22: 6 | I22: 7 | J22: 8 | K22: 9 | L22: 10 | M22: 11 | N22: 12 | O22: 13 | P22: 14 | Q22: 15 | R22: 16 | S22: 17 | T22: 18 | U22: 19 | V22: 20 | W22: 21 | X22: 22 | Y22: 23 | Z22: 24 | AA22: 25 | AB22: 26 | AC22: 27 | AD22: 28 | AE22: 29 | AF22: 30 | AG22: 31 | AH22: TOTAL
A23: Enero | B23: =+AH23 -> 0 | C23: VEDA | D23: VEDA | E23: VEDA | F23: VEDA | G23: VEDA | H23: VEDA | I23: VEDA | J23: VEDA | K23: VEDA | L23: VEDA | M23: VEDA | N23: VEDA | O23: VEDA | P23: VEDA | Q23: VEDA | R23: VEDA | S23: VEDA | T23: VEDA | U23: VEDA | V23: VEDA | W23: VEDA | X23: VEDA | Y23: VEDA | Z23: VEDA | AA23: VEDA | AB23: VEDA | AC23: VEDA | AD23: VEDA | AE23: VEDA | AF23: VEDA | AG23: VEDA
A24: Febrero | B24: =+AH24 -> 0 | C24: VEDA | D24: VEDA | E24: VEDA | F24: VEDA | G24: VEDA | H24: VEDA | I24: VEDA | J24: VEDA | K24: VEDA | L24: VEDA | M24: VEDA | N24: VEDA | O24: VEDA | P24: VEDA | Q24: VEDA | R24: VEDA | S24: VEDA | T24: VEDA | U24: VEDA | V24: VEDA | W24: VEDA | X24: VEDA | Y24: VEDA | Z24: VEDA | AA24: VEDA | AB24: VEDA | AC24: VEDA | AD24: VEDA | AE24: VEDA | AF24: VEDA | AG24: VEDA
A25: Marzo | B25: =+AH25 -> 3361.134 | C25: VEDA | D25: VEDA | E25: VEDA | F25: VEDA | G25: VEDA | H25: 74.92 | I25: 72.69 | J25: 242.975 | K25: 96.29 | L25: 263.46 | M25: 79.18 | N25: 202.04 | O25: 275.54 | P25: 293.18 | Q25: 75.18 | R25: 110.694 | S25: 157.3 | T25: 319.47 | U25: 267.08 | V25: 96.02 | W25: 98.01 | Z25: 105.5 | AA25: 95.78 | AB25: 195.63 | AC25: 138.85 | AD25: 101.345 | AE25: VEDA | AF25: VEDA | AG25: VEDA | AH25: =SUM(H25:AG25) -> 3361.134
A26: Abril | B26: =+AH26 -> 2222.691 | C26: VEDA | D26: VEDA | E26: VEDA | F26: VEDA | G26: VEDA | H26: VEDA | I26: VEDA | J26: VEDA | K26: VEDA | L26: 178.22 | M26: 195.245 | N26: 134.74 | O26: 220.795 | P26: 126.06 | Q26: 299.738 | R26: 8.64 | Z26: 153 | AA26: 250.995 | AB26: 282.041 | AC26: 195.16 | AD26: 178.057 | AH26: =SUM(C26:AG26) -> 2222.691
A27: Mayo | B27: =+AH27 -> 1597.513 | G27: 54.96 | J27: 153.63 | K27: 249.5 | L27: 84.005 | N27: 25.7 | O27: 156.175 | W27: 69.17 | X27: 225.314 | Y27: 292.818 | Z27: 201.851 | AA27: 84.39 | AH27: =SUM(C27:AG27) -> 1597.513
A28: Junio | B28: =+AH28 -> 597.974 | F28: 217.065 | H28: Veda | I28: Veda | J28: Veda | K28: Veda | L28: Veda | M28: Veda | N28: Veda | O28: Veda | P28: Veda | Q28: Veda | R28: Veda | S28: Veda | T28: Veda | U28: Veda | V28: Veda | W28: Veda | X28: Veda | AA28: 231.609 | AB28: 149.3 | AH28: =SUM(C28:AG28) -> 597.974
A29: Julio | B29: =+AH29 -> 546.217 | E29: 109.955 | K29: 210.91 | L29: 225.352 | AH29: =SUM(C29:AG29) -> 546.217
A30: Agosto | B30: =+AH30 -> 0 | J30: veda | K30: veda | L30: veda | M30: veda | N30: veda | O30: veda | P30: veda | Q30: veda | R30: veda | S30: veda | T30: veda | U30: veda | V30: veda | W30: veda | X30: veda | Y30: veda | Z30: veda | AA30: veda | AB30: veda | AC30: veda | AD30: veda | AE30: veda | AF30: veda | AG30: veda | AH30: =SUM(C30:AG30) -> 0
A31: Septiembre | B31: =+AH31 -> 0 | C31: veda | D31: veda | E31: veda | F31: veda | G31: veda | H31: veda | I31: veda | J31: veda | K31: veda | L31: veda | M31: veda | N31: veda | O31: veda | P31: veda | Q31: veda | R31: veda | S31: veda | T31: veda | U31: veda | V31: veda | W31: veda | X31: veda | Y31: veda | Z31: veda | AA31: veda | AB31: veda | AC31: veda | AD31: veda | AE31: veda | AF31: veda | AG31: veda | AH31: =SUM(C31:AG31) -> 0
A32: Octubre | B32: =+AH32 -> 339.835 | C32: veda | D32: veda | E32: veda | F32: veda | G32: veda | H32: veda | I32: veda | J32: veda | K32: veda | L32: veda | M32: veda | N32: veda | O32: veda | P32: veda | Q32: veda | R32: veda | S32: veda | T32: veda | U32: veda | V32: veda | W32: veda | X32: 199.89 | Y32: 139.945 | AH32: =SUM(C32:AG32) -> 339.835
A33: Noviembre | B33: =+AH33 -> 0 | AH33: =SUM(C33:AG33) -> 0
A34: Diciembre | B34: =+AH34 -> 0 | P34: VEDA | Q34: VEDA | R34: VEDA | S34: VEDA | T34: VEDA | U34: VEDA | V34: VEDA | W34: VEDA | X34: VEDA | Y34: VEDA | Z34: VEDA | AA34: VEDA | AB34: VEDA | AC34: VEDA | AD34: VEDA | AE34: VEDA | AF34: VEDA | AG34: VEDA | AH34: =SUM(C34:AG34) -> 0
A35: Total | B35: =SUM(B23:B34) -> 8665.364 | C35: =SUM(C23:C34) -> 0 | D35: =SUM(D23:D34) -> 0 | E35: =SUM(E23:E34) -> 109.955 | F35: =SUM(F23:F34) -> 217.065 | G35: =SUM(G23:G34) -> 54.96 | H35: =SUM(H23:H34) -> 74.92 | I35: =SUM(I23:I34) -> 72.69 | ... AH35: =SUM(AH23:AH34) -> 8665.364

Sheet Resumen RAE Merluza
A2: Resumen RAE Merluza común 2012
A5: IV Región, de Coquimbo
A7: Area | B7: Periodo | C7: Cuota asignada (t) | D7: Cuota efectiva (t) | E7: Desembarque (t) | F7: Saldo (t) | G7: % consumido | H7: Fecha de Cierre
A8: Norte | B8: Ene-Jun | C8: 19.345 | D8: =+C8 -> 19.345 | E8: =+SUM(M.Común!B9:B14) -> 3.416 | F8: =+D8-E8 -> 15.929 | G8: =+E8/D8 -> 0.1765831
A9: Centro | B9: Ene-Jun | C9: 415.619 | D9: =+C9 -> 415.619 | E9: =+SUM(M.Común!B25:B30) -> 307.387 | F9: =+D9-E9 -> 108.232 | G9: =+E9/D9 -> 0.73958842
A10: Sur | B10: Ene-Jun | C10: 64.509 | D10: =+C10 -> 64.509 | E10: =+SUM(M.Común!B41:B46) -> 0.21 | F10: =+D10-E10 -> 64.299 | G10: =+E10/D10 -> 0.0032553597
A11: Total | B11: Ene-Jun | C11: =SUM(C8:C10) -> 499.473 | D11: =SUM(D8:D10) -> 499.473 | E11: =SUM(E8:E10) -> 311.013 | F11: =SUM(F8:F10) -> 188.46
A13: Area | B13: Periodo | C13: Cuota asignada (t) | D13: Cuota efectiva (t) | E13: Desembarque (t) | F13: Saldo (t) | G13: % consumido | H13: Fecha de Cierre
A14: Norte | B14: Jul-Dic | C14: 6.448 | D14: =+C14+F8 -> 22.377 | E14: =+SUM(M.Común!B15:B20) -> 0 | F14: =+D14-E14 -> 22.377 | G14: =+E14/D14 -> 0
A15: Centro | B15: Jul-Dic | C15: 138.54 | D15: =+C15+F9 -> 246.772 | E15: =+SUM(M.Común!B31:B36) -> 202.879 | F15: =+D15-E15 -> 43.893 | G15: =+E15/D15 -> 0.82213136
A16: Sur | B16: Jul-Dic | C16: 21.503 | D16: =+C16+F10 -> 85.802 | E16: =+SUM(M.Común!B47:B52) -> 0.408 | F16: =+D16-E16 -> 85.394 | G16: =+E16/D16 -> 0.0047551339
A17: Total | B17: Jul-Dic | C17: =SUM(C14:C16) -> 166.491 | D17: =SUM(D14:D16) -> 354.951 | E17: =SUM(E14:E16) -> 203.287 | F17: =SUM(F14:F16) -> 151.664
A19: V Región, de Valparaíso
A21: Area | B21: Periodo | C21: Cuota asignada (t) | D21: Cuota efectiva (t) | E21: Desembarque (t) | F21: Saldo (t) | G21: % consumido | H21: Fecha de Cierre | I21: Traspaso
A22: Norte | B22: Ene-Jun | C22: =643.757-500 -> 143.757 | D22: =+C22 -> 143.757 | E22: =+SUM(M.Común!B59:B64) -> 13.964 | F22: =+D22-E22 -> 129.793 | G22: =+E22/D22 -> 0.097136139
A23: Centro hasta el 15 de febrero RES. 431 /12 | B23: Ene-Feb | C23: 174.757 | D23: =+C23 -> 174.757 | E23: =+SUM(M.Común!B107:B108) -> 174.757 | F23: =+D23-E23 -> 0 | G23: =+E23/D23 -> 1 | H23: Consumido
A24: STI. Caleta Portales (Centro) | B24: Feb-Jun | C24: 617.733 | D24: =+C24 -> 617.733 | E24: =+SUM(M.Común!B75:B80) -> 241.067 | F24: =+D24-E24 -> 376.666 | G24: =+E24/D24 -> 0.39024465
A25: STI. Concón ( Centro) | B25: Feb-Jun | C25: =109.816-75 -> 34.816 | D25: =+C25 -> 34.816 | E25: =+SUM(M.Común!B91:B96) -> 29.16 | F25: =+D25-E25 -> 5.656 | G25: =+E25/D25 -> 0.83754596
A26: Bolson ( Centro) | B26: Feb-Jun | C26: =716.163-500 -> 216.163 | D26: =+C26 -> 216.163 | E26: =+SUM(M.Común!B123:B128) -> 183.97 | F26: =+D26-E26 -> 32.193 | G26: =+E26/D26 -> 0.85107072
A27: Sur | B27: Ene-Jun | C27: 1477.272 | D27: =+C27 -> 1477.272 | E27: =+SUM(M.Común!B139:B144) -> 434.303 | F27: =+D27-E27 -> 1042.969 | G27: =+E27/D27 -> 0.29398987
A28: Total | B28: Ene-Jul | C28: =SUM(C22:C27) -> 2664.498 | D28: =SUM(D22:D27) -> 2664.498 | E28: =SUM(E22:E27) -> 1077.221 | F28: =SUM(F22:F27) -> 1587.277
A30: Area | B30: Periodo | C30: Cuota asignada (t) | D30: Cuota efectiva (t) | E30: Desembarque (t) | F30: Saldo (t) | G30: % consumido | H30: Fecha de Cierre | I30: Traspaso
A31: Norte | B31: Jul-Dic | C31: 81.252 | D31: =+C31+F22 -> 211.045 | E31: =+SUM(M.Común!B65:B70) -> 44.909 | F31: =+D31-E31 -> 166.136 | G31: =+E31/D31 -> 0.21279348
A32: STI. Caleta Portales (Centro) | B32: Jul-Dic | C32: 1.825 | D32: =+C32+F24 -> 378.491 | E32: =+SUM(M.Común!B81:B86) -> 278.791 | F32: =D32-E32 -> 99.7 | G32: =+E32/D32 -> 0.73658555
A33: STI. Concón ( Centro) | B33: Jul-Dic | C33: 19.997 | D33: =+C33+F25 -> 25.653 | E33: =+SUM(M.Común!B97:B102) -> 22.062 | F33: =D33-E33 -> 3.591 | G33: =+E33/D33 -> 0.86001637
A34: Bolson ( Centro) | B34: Jul-Dic | C34: 264.335 | D34: =+C34+F26 -> 296.528 | E34: =+SUM(M.Común!B129:B134) -> 265.991 | F34: =D34-E34 -> 30.537 | G34: =+E34/D34 -> 0.89701816
A35: Sur | B35: Jul-Dic | C35: =492.424+200+300 -> 992.424 | D35: =+C35+F27 -> 2035.393 | E35: =+SUM(M.Común!B145:B150) -> 1786.059 | F35: =+D35-E35 -> 249.334 | G35: =+E35/D35 -> 0.87750081 | H35: 31/10/2012 y 29-11-2012
A36: Total | B36: Jul-Dic | C36: =SUM(C31:C35) -> 1359.833 | D36: =SUM(D31:D35) -> 2947.11 | E36: =SUM(E31:E35) -> 2397.812 | F36: =SUM(F31:F35) -> 549.298
A39: VI Región, de O'higgins
A41: Area | B41: Periodo | C41: Cuota asignada (t) | D41: Cuota efectiva (t) | E41: Desembarque (t) | F41: Saldo (t) | G41: % consumido | H41: Fecha de Cierre
A42: Norte | B42: Ene-Jun | C42: 23.349 | D42: =+C42 -> 23.349 | E42: =+SUM(M.Común!B157:B162) -> 1.948 | F42: =+D42-E42 -> 21.401 | G42: =+E42/D42 -> 0.083429697
A43: Sur | B43: Ene-Jun | C43: 423.057 | D43: =+C43 -> 423.057 | E43: =+SUM(M.Común!B173:B178) -> 426.371 | F43: =+D43-E43 -> -3.314 | G43: =+E43/D43 -> 1.0078335 | H43: NO SE CERRO
A44: Total | B44: Ene-Jun | C44: =SUM(C42:C43) -> 446.406 | D44: =SUM(D42:D43) -> 446.406 | E44: =SUM(E42:E43) -> 428.319 | F44: =SUM(F42:F43) -> 18.087
A46: Area | B46: Periodo | C46: Cuota asignada (t) | D46: Cuota efectiva (t) | E46: Desembarque (t) | F46: Saldo (t) | G46: % consumido | H46: Fecha de Cierre
A47: Norte | B47: Jul-Dic | C47: 7.783 | D47: =+C47+F42 -> 29.184 | E47: =+SUM(M.Común!B163:B168) -> 1.568 | F47: =+D47-E47 -> 27.616 | G47: =+E47/D47 -> 0.05372807
A48: Sur | B48: Jul-Dic | C48: =241.019+150+150+100 -> 641.019 | D48: =+C48+F43 -> 637.705 | E48: =+SUM(M.Común!B179:B184) -> 542.188 | F48: =+D48-E48 -> 95.517 | G48: =+E48/D48 -> 0.85021758 | H48: 01/10/2012 , 05-11-2012
A49: Total | B49: Jul-Dic | C49: =SUM(C47:C48) -> 648.802 | D49: =SUM(D47:D48) -> 666.889 | E49: =SUM(E47:E48) -> 543.756 | F49: =SUM(F47:F48) -> 123.133
A51: VII Región, del Maule
A53: Area | B53: Periodo | C53: Cuota asignada (t) | D53: Cuota efectiva (t) | E53: Desembarque (t) | F53: Saldo (t) | G53: % consumido | H53: Fecha de Cierre
A54: Norte I | B54: Ene-Jun | C54: 376.866 | D54: =+C54 -> 376.866 | E54: =+SUM(M.Común!B191:B196) -> 377.483 | F54: =+D54-E54 -> -0.617 | G54: =+E54/D54 -> 1.0016372 | H54: 13/04/2012 y 21-06-2012
A55: STI. Proacentro de Duao (Norte II) | B55: Ene-Jun | C55: 410.152 | D55: =+C55 -> 410.152 | E55: =+SUM(M.Común!B207:B212) -> 288.539 | F55: =+D55-E55 -> 121.613 | G55: =+E55/D55 -> 0.70349285
A56: STI. Pescadores Art. Mar Brava de Duao (Norte II) | B56: Ene-Jun | C56: 771.342 | D56: =+C56 -> 771.342 | E56: =+SUM(M.Común!B223:B228) -> 550.281 | F56: =+D56-E56 -> 221.061 | G56: =+E56/D56 -> 0.71340728
A57: STI. Buzos Pesc. Art. Ac. Mataquito de La Pesca (Norte II) | B57: Ene-Jun | C57: 131.652 | D57: =+C57 -> 131.652 | E57: =+SUM(M.Común!B239:B244) -> 110.744 | F57: =+D57-E57 -> 20.908 | G57: =+E57/D57 -> 0.84118737
A58: Cuota residual (Norte II)Hasta el 07-02-2012 | B58: Ene-Jun | C58: 144.416 | D58: =+C58 -> 144.416 | E58: =+M.Común!B268 -> 144.416 | F58: =+D58-E58 -> 0 | G58: =+E58/D58 -> 1 | H58: consumido
A59: Cuota residual (Norte II)Desde el 08-02-2012 | B59: Ene-Jun | C59: 14.628 | D59: =+C59 -> 14.628 | E59: =+SUM(M.Común!B273:B277) -> 10.708 | F59: =+D59-E59 -> 3.92 | G59: =+E59/D59 -> 0.73202078
A60: Centro | B60: Ene-Jun | C60: 92.11 | D60: =+C60 -> 92.11 | E60: =+SUM(M.Común!B288:B293) -> 79.636 | F60: =+D60-E60 -> 12.474 | G60: =+E60/D60 -> 0.86457496 | H60: 40590
A61: S.T.I. Pes. Art. Pelluhue R. 07.04.0026 (Sur) | B61: Ene-Jun | C61: 383.921 | D61: =+C61 -> 383.921 | E61: =+SUM(M.Común!B304:B309) -> 378.541 | F61: =+D61-E61 -> 5.38 | G61: =+E61/D61 -> 0.9859867
A62: STI. Pesc. Art. Maguillines R. 07.05.0046 (Sur) | B62: Ene-Jun | C62: 349.019 | D62: =+C62 -> 349.019 | E62: =+SUM(M.Común!B320:B325) -> 288.032 | F62: =+D62-E62 -> 60.987 | G62: =+E62/D62 -> 0.82526166
A63: STI. Curanipe N° 1 Pro. Cauquenes R.07.04.0029 (Sur) | B63: Ene-Jun | C63: 104.706 | D63: =+C63 -> 104.706 | E63: =+SUM(M.Común!B336:B341) -> 99.69 | F63: =+D63-E63 -> 5.016 | G63: =+E63/D63 -> 0.95209444
A64: STI. N°2 Curanipe - Com-Pelluhue R.07.04.0048 (Sur) | B64: Ene-Jun | C64: 52.353 | D64: =+C64 -> 52.353 | E64: =+SUM(M.Común!B352:B357) -> 55.131 | F64: =+D64-E64 -> -2.778 | G64: =+E64/D64 -> 1.0530629 | H64: 41080
A65: STI. Loanco - Com-Chanco R.07.04.0022 (Sur) | B65: Ene-Jun | C65: 158.431 | D65: =+C65 -> 158.431 | E65: =+SUM(M.Común!B368:B373) -> 119.073 | F65: =+D65-E65 -> 39.358 | G65: =+E65/D65 -> 0.7515764 | H65: 41066
A66: STI. Pellines R. 07.05.0061 (Sur) | B66: Ene-Jun | C66: 133.98 | D66: =+C66 -> 133.98 | E66: =+SUM(M.Común!B384:B389) -> 108.153 | F66: =+D66-E66 -> 25.827 | G66: =+E66/D66 -> 0.80723242
A67: Sur residual hasta el 15-02-2012 | B67: Ene - Feb | C67: 253.119 | D67: =+C67 -> 253.119 | E67: =+SUM(M.Común!B400:B401) -> 253.119 | F67: =+D67-E67 -> 0 | G67: =+E67/D67 -> 1 | H67: consumido
A68: Sur residual desde el 16-02-2012 | B68: Ene-Jun | C68: 69.804 | D68: =+C68 -> 69.804 | E68: =+SUM(M.Común!B416:B421) -> 66.3 | F68: =+D68-E68 -> 3.504 | G68: =+E68/D68 -> 0.9498023
A69: Total | B69: Ene-Jun | C69: =SUM(C54:C68) -> 3446.499 | D69: =SUM(D54:D68) -> 3446.499 | E69: =SUM(E54:E68) -> 2929.846 | F69: =+D69-E69 -> 516.653 | G69: =+E69/D69 -> 0.85009338
A71: Area | B71: Periodo | C71: Cuota asignada (t) | D71: Cuota efectiva (t) | E71: Desembarque (t) | F71: Saldo (t) | G71: % consumido | H71: Fecha de Cierre
A72: Norte I | B72: Jul-Dic | C72: =115.622+100+150 -> 365.622 | D72: =+C72+F54 -> 365.005 | E72: =+SUM(M.Común!B197:B202) -> 388.001 | F72: =+D72-E72 -> -22.996 | G72: =+E72/D72 -> 1.0630019 | H72: 17/07/2012 , 01-09-2012 y 31-10-2012 Y 18-12-2012
A73: STI. Proacentro de Duao (Norte II) | B73: Jul-Dic | C73: =187.144+13.703 -> 200.847 | D73: =+C73+F55 -> 322.46 | E73: =+SUM(M.Común!B213:B218) -> 323.151 | F73: =+D73-E73 -> -0.691 | G73: =+E73/D73 -> 1.0021429
A74: STI. Pescadores Art. Mar Brava de Duao (Norte II) | B74: Jul-Dic | C74: =407.337+30.262 -> 437.599 | D74: =+C74+F56 -> 658.66 | E74: =+SUM(M.Común!B229:B234) -> 665.034 | F74: =+D74-E74 -> -6.374 | G74: =+E74/D74 -> 1.0096772 | H74: 03 12 2012
A75: STI. Buzos Pesc. Art. Ac. Mataquito de La Pesca (Norte II) | B75: Jul-Dic | C75: =69.524+5.139 -> 74.663 | D75: =+C75+F57 -> 95.571 | E75: =+SUM(M.Común!B245:B250) -> 95.203 | F75: =+D75-E75 -> 0.368 | G75: =+E75/D75 -> 0.99614946 | H75: 41240
A76: Cuota residual (Norte II) | B76: Jul-Dic | C76: =7.725+4.1+0.571 -> 12.396 | D76: =+C76+F59 -> 16.316 | E76: =+SUM(M.Común!B278:B283) -> 14.429 | F76: =+D76-E76 -> 1.887 | G76: =+E76/D76 -> 0.88434665 | H76: 11/10/2012 (habra otro cierre) | I76: atencion
A77: Centro | B77: Jul-Dic | C77: =9.037+2.05+2.332 -> 13.419 | D77: =+C77+F60 -> 25.893 | E77: =+SUM(M.Común!B294:B299) -> 27.772 | F77: =+D77-E77 -> -1.879 | G77: =+E77/D77 -> 1.0725679 | H77: 24/10/2012 y 27-12-2012
A78: S.T.I. Pes. Art. Pelluhue R. 07.04.0026 (Sur) | B78: Jul-Dic | C78: =258.241+15.759 -> 274 | D78: =+C78+F61 -> 279.38 | E78: =+SUM(M.Común!B310:B315) -> 288.975 | F78: =+D78-E78 -> -9.595 | G78: =+E78/D78 -> 1.0343439 | H78: 41227
A79: STI. Pesc. Art. Maguillines R. 07.05.0046 (Sur) | B79: Jul-Dic | C79: =234.764+14.326 -> 249.09 | D79: =+C79+F62 -> 310.077 | E79: =+SUM(M.Común!B326:B331) -> 352.384 | F79: =+D79-E79 -> -42.307 | G79: =+E79/D79 -> 1.1364403 | H79: 41258
A80: STI. Curanipe N° 1 Pro. Cauquenes R.07.04.0029 (Sur) | B80: Jul-Dic | C80: =70.429+4.298 -> 74.727 | D80: =+C80+F63 -> 79.743 | E80: =+SUM(M.Común!B342:B347) -> 72.758 | F80: =+D80-E80 -> 6.985 | G80: =+E80/D80 -> 0.9124061 | I80: atención
A81: STI. N°2 Curanipe - Com-Pelluhue R.07.04.0048 (Sur) | B81: Jul-Dic | C81: =35.215+2.149 -> 37.364 | D81: =+C81+F64 -> 34.586 | E81: =+SUM(M.Común!B358:B363) -> 31.257 | F81: =+D81-E81 -> 3.329 | G81: =+E81/D81 -> 0.90374718 | I81: atención
A82: STI. Loanco - Com-Chanco R.07.04.0022 (Sur) | B82: Jul-Dic | C82: =31.298+4.656 -> 35.954 | D82: =+C82+F65 -> 75.312 | E82: =+SUM(M.Común!B374:B379) -> 73.574 | F82: =+D82-E82 -> 1.738 | G82: =+E82/D82 -> 0.97692267 | I82: ATENCIÓN
A83: STI. Pellines R. 07.05.0061 (Sur) | B83: Jul-Dic | C83: =26.56+3.94 -> 30.5 | D83: =+C83+F66 -> 56.327 | E83: =+SUM(M.Común!B390:B395) -> 56.491 | F83: =+D83-E83 -> -0.164 | G83: =+E83/D83 -> 1.0029116
A84: Cuota residual Sur | B84: Jul-Dic | C84: =38.753+114.7+2.685 -> 156.138 | D84: =+C84+F68 -> 159.642 | E84: =+SUM(M.Común!B422:B427) -> 139.667 | F84: =+D84-E84 -> 19.975 | G84: =+E84/D84 -> 0.87487629 | H84: 09/08/2012 y 30-08-2012
A85: Total | B85: Jul-Dic | C85: =SUM(C72:C84) -> 1962.319 | D85: =SUM(D72:D84) -> 2478.972 | E85: =SUM(E72:E84) -> 2528.696 | F85: =+D85-E85 -> -49.724
A87: VIII Región, del Bio Bio
A89: Area | B89: Periodo | C89: Cuota asignada (t) | D89: Cuota efectiva (t) | E89: Desembarque (t) | F89: Saldo (t) | G89: % consumido | H89: Fecha de Cierre
A90: STI. Arm y Pat. Cocholgue Com. Tomé R.08.06.0106 (Norte) | B90: Ene-Jun | C90: 1053 | D90: =+C90 -> 1053 | E90: 397.259 | F90: =+D90-E90 -> 655.741 | G90: =+E90/D90 -> 0.37726401
A91: STI. Caleta Cocholgue R. 08.06.0023 (Norte) | B91: Ene-Jun | C91: 52.266 | D91: =+C91 -> 52.266 | E91: 9.127 | F91: =+D91-E91 -> 43.139 | G91: =+E91/D91 -> 0.17462595
A92: STI. Buzos y Algueros Cocholgue R. 08.03.0042 (Norte) | B92: Ene-Jun | C92: 1.343 | D92: =+C92 -> 1.343 | E92: 0.455 | F92: =+D92-E92 -> 0.888 | G92: =+E92/D92 -> 0.33879375
A93: STI. Caleta Coliumo R. 08.06.0027 (Norte) | B93: Ene-Jun | C93: 192.619 | D93: =+C93 -> 192.619 | E93: 35.878 | F93: =+D93-E93 -> 156.741 | G93: =+E93/D93 -> 0.18626408
A94: STI. Del mar Caleta Dichato R. 08.06.0030 (Norte) | B94: Ene-Jun | C94: 88.058 | D94: =+C94 -> 88.058 | E94: 91.282 | F94: =+D94-E94 -> -3.224 | G94: =+E94/D94 -> 1.0366122 | H94: 41071
A95: STI. Los Bagres R.08-06-0024 (Norte) | B95: Ene-Jun | C95: 76.239 | D95: =+C95 -> 76.239 | E95: 28.06 | F95: =+D95-E95 -> 48.179 | G95: =+E95/D95 -> 0.3680531
A96: STI. Tomé y Quichuito R. 08.06.0043 (Norte) | B96: Ene-Jun | C96: 12.434 | D96: =+C96 -> 12.434 | E96: 0.028 | F96: =+D96-E96 -> 12.406 | G96: =+E96/D96 -> 0.00225189
A97: STI. Coliumo - Purema 08.06.0049 (Norte) | B97: Ene-Jun | C97: 16.967 | D97: =+C97 -> 16.967 | E97: 24.465 | F97: =+D97-E97 -> -7.498 | G97: =+E97/D97 -> 1.4419167 | H97: 41024
A98: STI. Pesc. Art. Y Ra. Afin. De pa Pesc. Art. R.08.05.0380 (Norte) | B98: Ene-Jun | C98: 7.112 | D98: =+C98 -> 7.112 | E98: 0.15 | F98: =+D98-E98 -> 6.962 | G98: =+E98/D98 -> 0.021091114
A99: STI. Hualpen R.08.05.0502 (Norte) | B99: Ene-Jun | C99: 1.907 | D99: =+C99 -> 1.907 | E99: 7.37 | F99: =+D99-E99 -> -5.463 | G99: =+E99/D99 -> 3.864709 | H99: 16.03.2011
A100: AG. Menor Coliumo Rag. N° 507-8 (Norte) | B100: Ene-Jun | C100: 3.497 | D100: =+C100 -> 3.497 | E100: 4.358 | F100: =+D100-E100 -> -0.861 | G100: =+E100/D100 -> 1.246211
A101: AG. Caleta Infiernillo Rag. N° 98-8 (Norte) | B101: Ene-Jun | C101: 28.382 | D101: =+C101 -> 28.382 | E101: 1.444 | F101: =+D101-E101 -> 26.938 | G101: =+E101/D101 -> 0.050877317
A102: STI. Caleta Tumbes R.08.05.0495 (Norte) | B102: Ene-Jun | C102: 9.04 | D102: =+C102 -> 9.04 | E102: 2.06 | F102: =+D102-E102 -> 6.98 | G102: =+E102/D102 -> 0.22787611
A103: AG. ITALMAR AG. Rag. N° 392-08 (Norte) | B103: Ene-Jun | C103: 33.2 | D103: =+C103 -> 33.2 | E103: 6.855 | F103: =+D103-E103 -> 26.345 | G103: =+E103/D103 -> 0.2064759 | H103: 40968
A104: No asociados ( Norte ) desde el 15-02-2012 | B104: Ene-Jun | C104: 256.024 | D104: =+C104 -> 256.024 | E104: 256.024 | F104: 0 | G104: =+E104/D104 -> 1 | H104: consumido
A105: No asociados ( Norte ) desde el 16-02-2012 | B105: Ene-Jun | C105: 364.027 | D105: =+C105 -> 364.027 | E105: 281.609 | F105: =+D105-E105 -> 82.418 | G105: =+E105/D105 -> 0.77359372 | H105: 41067
A106: Centro | B106: Ene-Jun | C106: 1140.141 | D106: =+C106 -> 1140.141 | E106: 108.502 | F106: =+D106-E106 -> 1031.639 | G106: =+E106/D106 -> 0.095165423
A107: Sur | B107: Ene-Jun | C107: 347.279 | D107: =+C107 -> 347.279 | E107: 245.487 | F107: =+D107-E107 -> 101.792 | G107: =+E107/D107 -> 0.70688697
A108: Total | B108: Ene-Jun | C108: =SUM(C90:C107) -> 3683.535 | D108: =SUM(D90:D107) -> 3683.535 | E108: =SUM(E90:E107) -> 1500.413 | F108: =SUM(F90:F107) -> 2183.122
C109: =+C108-C104 -> 3427.511
A111: Area | B111: Periodo | C111: Cuota asignada (t) | D111: Cuota efectiva (t) | E111: Desembarque (t) | F111: Saldo (t) | G111: % consumido | H111: Fecha de Cierre | I111: 1ER Per. | J111: Año | K111: 2o periodo
A112: STI. Arm y Pat. Cocholgue Com. Tomé R.08.06.0106 (Norte) | B112: Jul-Dic | C112: =340+50 -> 390 | D112: =+C112+F90 -> 1045.741 | E112: =+K112 -> 965.129 | F112: =+D112-E112 -> 80.612 | G112: =+E112/D112 -> 0.92291399 | I112: 397.259 | J112: 1362.388 | K112: =+J112-I112 -> 965.129 | M112: 1
A113: STI. Caleta Cocholgue R. 08.06.0023 (Norte) | B113: Jul-Dic | C113: 19.846 | D113: =+C113+F91 -> 62.985 | E113: =+K113 -> 50.668 | F113: =+D113-E113 -> 12.317 | G113: =+E113/D113 -> 0.8044455 | I113: 9.127 | J113: 59.795 | K113: =+J113-I113 -> 50.668 | M113: 2
A114: STI. Buzos y Algueros Cocholgue R. 08.03.0042 (Norte) | B114: Jul-Dic | C114: =0.51+2 -> 2.51 | D114: =+C114+F92 -> 3.398 | E114: =+K114 -> 1.5 | F114: =+D114-E114 -> 1.898 | G114: =+E114/D114 -> 0.44143614 | H114: 41220 | I114: 0.455 | J114: 1.955 | K114: =+J114-I114 -> 1.5 | M114: 3
A115: STI. Caleta Coliumo R. 08.06.0027 (Norte) | B115: Jul-Dic | C115: 73.141 | D115: =+C115+F93 -> 229.882 | E115: =+K115 -> 197.534 | F115: =+D115-E115 -> 32.348 | G115: =+E115/D115 -> 0.85928433 | I115: 35.878 | J115: 233.412 | K115: =+J115-I115 -> 197.534 | M115: 4
A116: STI. Del mar Caleta Dichato R. 08.06.0030 (Norte) | B116: Jul-Dic | C116: 33.437 | D116: =+C116+F94 -> 30.213 | E116: =+K116 -> 30.218 | F116: =+D116-E116 -> -0.005 | G116: =+E116/D116 -> 1.0001655 | I116: 91.282 | J116: 121.5 | K116: =+J116-I116 -> 30.218 | L116: atención | M116: 5
A117: STI. Los Bagres R.08-06-0024 (Norte) | B117: Jul-Dic | C117: 28.949 | D117: =+C117+F95 -> 77.128 | E117: =+K117 -> 76.495 | F117: =+D117-E117 -> 0.633 | G117: =+E117/D117 -> 0.99179286 | I117: 28.06 | J117: 104.555 | K117: =+J117-I117 -> 76.495 | M117: 6
A118: STI. Tomé y Quichuito R. 08.06.0043 (Norte) | B118: Jul-Dic | C118: 4.721 | D118: =+C118+F96 -> 17.127 | E118: =+K118 -> 15.426 | F118: =+D118-E118 -> 1.701 | G118: =+E118/D118 -> 0.90068313 | I118: 0.028 | J118: 15.454 | K118: =+J118-I118 -> 15.426 | M118: 7
...

Sheet M.Común
A2: RAE Merluza común 2012
A5: IV Región, de Coquimbo
A7: Norte
A8: Mes | B8: Total mes | C8: 1 | D8: 2 | E8: 3 | F8: 4 | G8: 5 | H8: 6 | I8: 7 | J8: 8 | K8: 9 | L8: 10 | M8: 11 | N8: 12 | O8: 13 | P8: 14 | Q8: 15 | R8: 16 | S8: 17 | T8: 18 | U8: 19 | V8: 20 | W8: 21 | X8: 22 | Y8: 23 | Z8: 24 | AA8: 25 | AB8: 26 | AC8: 27 | AD8: 28 | AE8: 29 | AF8: 30 | AG8: 31 | AH8: TOTAL
A9: Enero | B9: =+AH9 -> 0.719 | C9: 0 | D9: 0 | E9: 0 | F9: 0 | G9: 0 | H9: 0 | I9: 0.015 | J9: 0.021 | K9: 0.099 | L9: 0.033 | M9: 0.038 | N9: 0.032 | O9: 0 | P9: 0.032 | Q9: 0 | R9: 0.072 | S9: 0.054 | T9: 0.04 | U9: 0 | V9: 0 | W9: 0 | X9: 0 | Y9: 0.06 | Z9: 0.065 | AA9: 0.068 | AB9: 0 | AC9: 0 | AD9: 0.021 | AE9: 0.028 | AF9: 0.041 | AG9: 0 | AH9: =SUM(C9:AG9) -> 0.719
A10: Febrero | B10: =+AH10 -> 0.493 | C10: 0 | D10: 0 | E10: 0 | F10: 0.064 | G10: 0.047 | H10: 0.022 | I10: 0 | J10: 0 | K10: 0 | L10: 0 | M10: 0 | N10: 0 | O10: 0 | P10: 0 | Q10: 0.063 | R10: 0 | S10: 0 | T10: 0.2 | U10: 0 | V10: 0 | W10: 0 | X10: 0 | Y10: 0 | Z10: 0 | AA10: 0.043 | AB10: 0 | AC10: 0 | AD10: 0.054 | AE10: 0 | AH10: =SUM(C10:AG10) -> 0.493
A11: Marzo | B11: =+AH11 -> 0.796 | C11: 0.012 | D11: 0 | E11: 0.028 | F11: 0 | G11: 0.017 | H11: 0 | I11: 0 | J11: 0.077 | K11: 0.031 | L11: 0 | M11: 0.034 | N11: 0.043 | O11: 0.063 | P11: 0.083 | Q11: 0.066 | R11: 0 | S11: 0 | T11: 0 | U11: 0 | V11: 0 | W11: 0 | X11: 0 | Y11: 0.091 | Z11: 0 | AA11: 0.033 | AB11: 0.027 | AC11: 0.014 | AD11: 0.051 | AE11: 0.039 | AF11: 0.087 | AG11: 0 | AH11: =SUM(C11:AG11) -> 0.796
A12: Abril | B12: =+AH12 -> 0.051 | C12: 0 | D12: 0.051 | E12: 0 | F12: 0 | G12: 0 | H12: 0 | I12: 0 | J12: 0 | K12: 0 | L12: 0 | M12: 0 | N12: 0 | O12: 0 | P12: 0 | Q12: 0 | R12: 0 | S12: 0 | T12: 0 | U12: 0 | V12: 0 | W12: 0 | X12: 0 | Y12: 0 | Z12: 0 | AA12: 0 | AB12: 0 | AC12: 0 | AD12: 0 | AE12: 0 | AF12: 0 | AH12: =SUM(C12:AG12) -> 0.051
A13: Mayo | B13: =+AH13 -> 1.077 | C13: 0.058 | D13: 0 | E13: 0 | F13: 0 | G13: 0.057 | H13: 0 | I13: 0 | J13: 0.07 | K13: 0.053 | L13: 0 | M13: 0 | N13: 0 | O13: 0 | P13: 0.1 | Q13: 0 | R13: 0.372 | S13: 0 | T13: 0 | U13: 0 | V13: 0 | W13: 0 | X13: 0 | Y13: 0.05 | Z13: 0.03 | AA13: 0 | AB13: 0 | AC13: 0.07 | AD13: 0.067 | AE13: 0 | AF13: 0.15 | AG13: 0 | AH13: =SUM(C13:AG13) -> 1.077
A14: Junio | B14: =+AH14 -> 0.28 | C14: 0 | D14: 0 | E14: 0 | F14: 0 | G14: 0 | H14: 0.054 | I14: 0 | J14: 0 | K14: 0 | L14: 0 | M14: 0.06 | N14: 0 | O14: 0 | P14: 0 | Q14: 0 | R14: 0 | S14: 0 | T14: 0 | U14: 0.028 | V14: 0.089 | W14: 0 | X14: 0 | Y14: 0 | Z14: 0 | AA14: 0 | AB14: 0 | AC14: 0 | AD14: 0.015 | AE14: 0.034 | AF14: 0 | AH14: =SUM(C14:AG14) -> 0.28
A15: Julio | B15: =+AH15 -> 0 | C15: 0 | D15: 0 | E15: 0 | F15: 0 | G15: 0 | H15: 0 | I15: 0 | J15: 0 | K15: 0 | L15: 0 | M15: 0 | N15: 0 | O15: 0 | P15: 0 | Q15: 0 | R15: 0 | S15: 0 | T15: 0 | U15: 0 | V15: 0 | W15: 0 | AH15: =SUM(C15:AG15) -> 0
A16: Agosto | B16: =+AH16 -> 0 | AH16: =SUM(C16:AG16) -> 0
A17: Septiembre | B17: =+AH17 -> 0 | C17: Veda | D17: Veda | E17: Veda | F17: Veda | G17: Veda | H17: Veda | I17: Veda | J17: Veda | K17: Veda | L17: Veda | M17: Veda | N17: Veda | O17: Veda | P17: Veda | Q17: Veda | R17: Veda | S17: Veda | T17: Veda | U17: Veda | V17: Veda | W17: Veda | X17: Veda | Y17: Veda | Z17: Veda | AA17: Veda | AB17: Veda | AC17: Veda | AD17: Veda | AE17: Veda | AF17: Veda | AG17: Veda | AH17: =SUM(C17:AG17) -> 0
A18: Octubre | B18: =+AH18 -> 0 | AH18: =SUM(C18:AG18) -> 0
A19: Noviembre | B19: =+AH19 -> 0 | AH19: =SUM(C19:AG19) -> 0
A20: Diciembre | B20: =+AH20 -> 0 | AH20: =SUM(C20:AG20) -> 0
A21: Total | B21: =SUM(B9:B20) -> 3.416 | C21: =SUM(C9:C20) -> 0.07 | D21: =SUM(D9:D20) -> 0.051 | E21: =SUM(E9:E20) -> 0.028 | F21: =SUM(F9:F20) -> 0.064 | G21: =SUM(G9:G20) -> 0.121 | H21: =SUM(H9:H20) -> 0.076 | I21: =SUM(I9:I20) -> 0.015 | ... AH21: =SUM(AH9:AH20) -> 3.416
A23: Centro
A24: Mes | B24: Total mes | C24: 1 | D24: 2 | E24: 3 | F24: 4 | G24: 5 | H24: 6 | I24: 7 | J24: 8 | K24: 9 | L24: 10 | M24: 11 | N24: 12 | O24: 13 | P24: 14 | Q24: 15 | R24: 16 | S24: 17 | T24: 18 | U24: 19 | V24: 20 | W24: 21 | X24: 22 | Y24: 23 | Z24: 24 | AA24: 25 | AB24: 26 | AC24: 27 | AD24: 28 | AE24: 29 | AF24: 30 | AG24: 31 | AH24: TOTAL
A25: Enero | B25: =+AH25 -> 70.131 | C25: 0 | D25: 1.185 | E25: 2.727 | F25: 3.013 | G25: 4.36 | H25: 2.865 | I25: 3.254 | J25: 1.41 | K25: 1.154 | L25: 2.215 | M25: 3.45 | N25: 2.695 | O25: 3.267 | P25: 3.64 | Q25: 1.605 | R25: 1.32 | S25: 2.04 | T25: 3.95 | U25: 3.139 | V25: 2.711 | W25: 4.212 | X25: 2.045 | Y25: 0.576 | Z25: 2.045 | AA25: 1.75 | AB25: 1.746 | AC25: 1.755 | AD25: 1.965 | AE25: 1.595 | AF25: 0.95 | AG25: 1.492 | AH25: =SUM(C25:AG25) -> 70.131
A26: Febrero | B26: =+AH26 -> 71.669 | C26: 1.83 | D26: 2.57 | E26: 2 | F26: 1.789 | G26: 1.55 | H26: 0.158 | I26: 3.195 | J26: 2.21 | K26: 4.866 | L26: 2.997 | M26: 4.187 | N26: 2.32 | O26: 0.538 | P26: 3.768 | Q26: 2.725 | R26: 2.827 | S26: 3.712 | T26: 3.169 | U26: 1.95 | V26: 0.735 | W26: 2.91 | X26: 2.008 | Y26: 3.179 | Z26: 3.102 | AA26: 2.465 | AB26: 2.34 | AC26: 0.708 | AD26: 4.347 | AE26: 1.514 | AH26: =SUM(C26:AG26) -> 71.669
A27: Marzo | B27: =+AH27 -> 48.091 | C27: 2.6 | D27: 2.709 | E27: 3.47 | F27: 2.2 | G27: 1.195 | H27: 2.251 | I27: 0.91 | J27: 2.187 | K27: 1.935 | L27: 2.811 | M27: 0.447 | N27: 0.817 | O27: 0.75 | P27: 1.463 | Q27: 0.63 | R27: 1.486 | S27: 0.55 | T27: 1.1 | U27: 0.53 | V27: 1.505 | W27: 1.21 | X27: 2.41 | Y27: 1.62 | Z27: 2.448 | AA27: 0.697 | AB27: 1.05 | AC27: 1.205 | AD27: 1.767 | AE27: 1.358 | AF27: 2.1 | AG27: 0.68 | AH27: =SUM(C27:AG27) -> 48.091
A28: Abril | B28: =+AH28 -> 29.41 | C28: 1.022 | D28: 0.46 | E28: 1.345 | F28: 1.446 | G28: 1.547 | H28: 2.272 | I28: 0.915 | J28: 0.635 | K28: 0.54 | L28: 1.692 | M28: 0.438 | N28: 1.565 | O28: 0.544 | P28: 1.27 | Q28: 0.145 | R28: 0.475 | S28: 1.28 | T28: 1.099 | U28: 1.082 | V28: 0.753 | W28: 1.163 | X28: 0.753 | Y28: 0.445 | Z28: 0.815 | AA28: 1.103 | AB28: 1.054 | AC28: 1.262 | AD28: 1.56 | AE28: 0.44 | AF28: 0.29 | AH28: =SUM(C28:AG28) -> 29.41
A29: Mayo | B29: =+AH29 -> 40.616 | C29: 1.234 | D29: 0.68 | E29: 1.405 | F29: 0.83 | G29: 1.622 | H29: 0.823 | I29: 0.67 | J29: 1.62 | K29: 1.861 | L29: 1.663 | M29: 2.447 | N29: 1.354 | O29: 0.63 | P29: 0.488 | Q29: 2.386 | R29: 1.07 | S29: 2.186 | T29: 1.087 | U29: 2.164 | V29: 1.705 | W29: 0.676 | X29: 0.359 | Y29: 1.947 | Z29: 1.81 | AA29: 1.138 | AB29: 0.82 | AC29: 1.35 | AD29: 0.425 | AE29: 1.26 | AF29: 1.376 | AG29: 1.53 | AH29: =SUM(C29:AG29) -> 40.616
A30: Junio | B30: =+AH30 -> 47.47 | C30: 1.466 | D30: 1.41 | E30: 1.642 | F30: 0.567 | G30: 2.174 | H30: 2.01 | I30: 2.164 | J30: 3.008 | K30: 1.435 | L30: 1.87 | M30: 1.324 | N30: 2 | O30: 1.915 | P30: 2.89 | Q30: 1.88 | R30: 2.057 | S30: 0.23 | T30: 0.217 | U30: 2.475 | V30: 1.451 | W30: 1.602 | X30: 2.272 | Y30: 1.359 | Z30: 0.085 | AA30: 0.18 | AB30: 1.62 | AC30: 1.345 | AD30: 1.922 | AE30: 0.811 | AF30: 2.089 | AH30: =SUM(C30:AG30) -> 47.47
A31: Julio | B31: =+AH31 -> 39.219 | C31: 0.29 | D31: 0.48 | E31: 1.43 | F31: 1.68 | G31: 1.189 | H31: 1.947 | I31: 2.786 | J31: 1.33 | K31: 0.924 | L31: 2.078 | M31: 1.425 | N31: 2.05 | O31: 1.445 | P31: 1.415 | Q31: 0.94 | R31: 0.59 | S31: 0.669 | T31: 2.371 | U31: 1.931 | V31: 1.553 | W31: 1.811 | X31: 1.645 | Y31: 0.08 | Z31: 0.988 | AA31: 0.795 | AB31: 1.07 | AC31: 0.905 | AD31: 1.04 | AE31: 0.242 | AF31: 0.87 | AG31: 1.25 | AH31: =SUM(C31:AG31) -> 39.219
A32: Agosto | B32: =+AH32 -> 22.026 | C32: 1.31 | D32: 0.875 | E32: 1.635 | F32: 0.66 | G32: 0 | H32: 0.51 | I32: 1.531 | J32: 1.837 | K32: 1.92 | L32: 0.709 | M32: 1.685 | N32: 0.63 | O32: 0 | P32: 0.907 | Q32: 0.03 | R32: 0.842 | S32: 0.625 | T32: 1.2 | U32: 0.635 | V32: 0.225 | W32: 0.77 | X32: 0.877 | Y32: 0.342 | Z32: 0.405 | AA32: 0.935 | AB32: 0.06 | AC32: 0.231 | AD32: 0.3 | AE32: 0.13 | AF32: 0 | AG32: 0.21 | AH32: =SUM(C32:AG32) -> 22.026
A33: Septiembre | B33: =+AH33 -> 0 | C33: vada | D33: vada | E33: vada | F33: vada | G33: vada | H33: vada | I33: vada | J33: vada | K33: vada | L33: vada | M33: vada | N33: vada | O33: vada | P33: vada | Q33: vada | R33: vada | S33: vada | T33: vada | U33: vada | V33: vada | W33: vada | X33: vada | Y33: vada | Z33: vada | AA33: vada | AB33: vada | AC33: vada | AD33: vada | AE33: vada | AF33: vada | AG33: vada | AH33: =SUM(C33:AG33) -> 0
A34: Octubre | B34: =+AH34 -> 48.224 | C34: 0.06 | D34: 2.634 | E34: 1.495 | F34: 2.45 | G34: 1.815 | H34: 2.795 | I34: 0.406 | J34: 0.708 | K34: 2.387 | L34: 2.079 | M34: 1.991 | N34: 3.07 | O34: 2.534 | P34: 0.704 | Q34: 0.579 | R34: 1.459 | S34: 1.947 | T34: 1.651 | U34: 1.504 | V34: 1.65 | W34: 0.03 | X34: 0.424 | Y34: 1.084 | Z34: 0.844 | AA34: 2.134 | AB34: 2.111 | AC34: 2.025 | AD34: 1.005 | AE34: 1.424 | AF34: 1.575 | AG34: 1.65 | AH34: =SUM(C34:AG34) -> 48.224
A35: Noviembre | B35: =+AH35 -> 55.538 | C35: 3.76 | D35: 1.885 | E35: 2.625 | F35: 0.26 | G35: 0.789 | H35: 1.11 | I35: 2.408 | J35: 2.379 | K35: 1.722 | L35: 1.468 | M35: 0 | N35: 0.074 | O35: 1.035 | P35: 1.08 | Q35: 1.492 | R35: 1.795 | S35: 1.665 | T35: 0.853 | U35: 0.322 | V35: 2.423 | W35: 1.54 | X35: 3.476 | Y35: 2.58 | Z35: 2.671 | AA35: 0.71 | AB35: 0.7 | AC35: 3.686 | AD35: 6.162 | AE35: 2.931 | AF35: 1.937 | AH35: =SUM(C35:AG35) -> 55.538
A36: Diciembre | B36: =+AH36 -> 37.872 | C36: 1.552 | D36: 0.659 | E36: 3.761 | F36: 1.525 | G36: 2.925 | H36: 1.88 | I36: 1.787 | J36: 0.94 | K36: 0.392 | L36: 0.549 | M36: 1.19 | N36: 2.175 | O36: 2.277 | P36: 1.825 | Q36: 1.57 | R36: 0.465 | S36: 0.543 | T36: 1.48 | U36: 1.65 | V36: 1.48 | W36: 1.53 | X36: 1.84 | Y36: 1.287 | Z36: 0.13 | AA36: 0.25 | AB36: 0.15 | AC36: 0 | AD36: 0.9 | AE36: 0.25 | AF36: 0.3 | AG36: 0.61 | AH36: =SUM(C36:AG36) -> 37.872
A37: Total | B37: =SUM(B25:B36) -> 510.266 | C37: =SUM(C25:C36) -> 15.124 | D37: =SUM(D25:D36) -> 15.547 | E37: =SUM(E25:E36) -> 23.535 | F37: =SUM(F25:F36) -> 16.42 | G37: =SUM(G25:G36) -> 19.166 | H37: =SUM(H25:H36) -> 18.621 | I37: =SUM(I25:I36) -> 20.026 | ... AH37: =SUM(AH25:AH36) -> 510.266
A39: Sur
A40: Mes | B40: Total mes | C40: 1 | D40: 2 | E40: 3 | F40: 4 | G40: 5 | H40: 6 | I40: 7 | J40: 8 | K40: 9 | L40: 10 | M40: 11 | N40: 12 | O40: 13 | P40: 14 | Q40: 15 | R40: 16 | S40: 17 | T40: 18 | U40: 19 | V40: 20 | W40: 21 | X40: 22 | Y40: 23 | Z40: 24 | AA40: 25 | AB40: 26 | AC40: 27 | AD40: 28 | AE40: 29 | AF40: 30 | AG40: 31 | AH40: TOTAL
A41: Enero | B41: =+AH41 -> 0 | C41: 0 | D41: 0 | E41: 0 | F41: 0 | G41: 0 | H41: 0 | I41: 0 | J41: 0 | K41: 0 | L41: 0 | M41: 0 | N41: 0 | O41: 0 | P41: 0 | Q41: 0 | R41: 0 | S41: 0 | T41: 0 | U41: 0 | V41: 0 | W41: 0 | X41: 0 | Y41: 0 | Z41: 0 | AA41: 0 | AB41: 0 | AC41: 0 | AD41: 0 | AE41: 0 | AF41: 0 | AG41: 0 | AH41: =SUM(C41:AG41) -> 0
A42: Febrero | B42: =+AH42 -> 0.051 | C42: 0 | D42: 0 | E42: 0 | F42: 0 | G42: 0 | H42: 0 | I42: 0 | J42: 0 | K42: 0 | L42: 0 | M42: 0 | N42: 0 | O42: 0 | P42: 0 | Q42: 0 | R42: 0.026 | S42: 0 | T42: 0 | U42: 0 | V42: 0 | W42: 0 | X42: 0.025 | Y42: 0 | Z42: 0 | AA42: 0 | AB42: 0 | AC42: 0 | AD42: 0 | AE42: 0 | AH42: =SUM(C42:AG42) -> 0.051
A43: Marzo | B43: =+AH43 -> 0.026 | C43: 0 | D43: 0 | E43: 0 | F43: 0 | G43: 0 | H43: 0 | I43: 0 | J43: 0 | K43: 0 | L43: 0 | M43: 0 | N43: 0.008 | O43: 0 | P43: 0 | Q43: 0 | R43: 0 | S43: 0 | T43: 0.018 | U43: 0 | V43: 0 | W43: 0 | X43: 0 | Y43: 0 | Z43: 0 | AA43: 0 | AB43: 0 | AC43: 0 | AD43: 0 | AE43: 0 | AF43: 0 | AG43: 0 | AH43: =SUM(C43:AG43) -> 0.026
A44: Abril | B44: =+AH44 -> 0.07 | C44: 0 | D44: 0 | E44: 0 | F44: 0 | G44: 0 | H44: 0 | I44: 0 | J44: 0 | K44: 0 | L44: 0 | M44: 0 | N44: 0 | O44: 0 | P44: 0 | Q44: 0 | R44: 0 | S44: 0 | T44: 0 | U44: 0.003 | V44: 0.005 | W44: 0.036 | X44: 0 | Y44: 0.01 | Z44: 0 | AA44: 0 | AB44: 0 | AC44: 0 | AD44: 0.016 | AE44: 0 | AF44: 0 | AH44: =SUM(C44:AG44) -> 0.07
A45: Mayo | B45: =+AH45 -> 0 | C45: 0 | D45: 0 | E45: 0 | F45: 0 | G45: 0 | H45: 0 | I45: 0 | J45: 0 | K45: 0 | L45: 0 | M45: 0 | N45: 0 | O45: 0 | P45: 0 | Q45: 0 | R45: 0 | S45: 0 | T45: 0 | U45: 0 | V45: 0 | W45: 0 | X45: 0 | Y45: 0 | Z45: 0 | AA45: 0 | AB45: 0 | AC45: 0 | AD45: 0 | AE45: 0 | AF45: 0 | AG45: 0 | AH45: =SUM(C45:AG45) -> 0
A46: Junio | B46: =+AH46 -> 0.063 | C46: 0 | D46: 0 | E46: 0 | F46: 0 | G46: 0 | H46: 0 | I46: 0 | J46: 0 | K46: 0 | L46: 0 | M46: 0 | N46: 0 | O46: 0 | P46: 0.036 | Q46: 0 | R46: 0.021 | S46: 0 | T46: 0 | U46: 0 | V46: 0 | W46: 0.006 | X46: 0 | Y46: 0 | Z46: 0 | AA46: 0 | AB46: 0 | AC46: 0 | AD46: 0 | AE46: 0 | AF46: 0 | AH46: =SUM(C46:AG46) -> 0.063
A47: Julio | B47: =+AH47 -> 0.142 | C47: 0 | D47: 0 | E47: 0 | F47: 0 | G47: 0 | H47: 0 | I47: 0 | J47: 0 | K47: 0 | L47: 0 | M47: 0 | N47: 0 | O47: 0 | P47: 0 | Q47: 0 | R47: 0 | S47: 0 | T47: 0 | U47: 0 | V47: 0.042 | W47: 0 | X47: 0 | Y47: 0 | Z47: 0 | AA47: 0 | AB47: 0 | AC47: 0 | AD47: 0.1 | AE47: 0 | AF47: 0 | AG47: 0 | AH47: =SUM(C47:AG47) -> 0.142
A48: Agosto | B48: =+AH48 -> 0.062 | C48: 0 | D48: 0 | E48: 0 | F48: 0 | G48: 0 | H48: 0 | I48: 0 | J48: 0.056 | K48: 0 | L48: 0.006 | M48: 0 | N48: 0 | O48: 0 | P48: 0 | Q48: 0 | R48: 0 | S48: 0 | T48: 0 | U48: 0 | V48: 0 | W48: 0 | X48: 0 | Y48: 0 | Z48: 0 | AA48: 0 | AB48: 0 | AC48: 0 | AD48: 0 | AE48: 0 | AF48: 0 | AG48: 0 | AH48: =SUM(C48:AG48) -> 0.062
A49: Septiembre | B49: =+AH49 -> 0 | C49: Veda | D49: Veda | E49: Veda | F49: Veda | G49: Veda | H49: Veda | I49: Veda | J49: Veda | K49: Veda | L49: Veda | M49: Veda | N49: Veda | O49: Veda | P49: Veda | Q49: Veda | R49: Veda | S49: Veda | T49: Veda | U49: Veda | V49: Veda | W49: Veda | X49: Veda | Y49: Veda | Z49: Veda | AA49: Veda | AB49: Veda | AC49: Veda | AD49: Veda | AE49: Veda | AF49: Veda | AG49: Veda | AH49: =SUM(C49:AG49) -> 0
A50: Octubre | B50: =+AH50 -> 0.022 | C50: 0 | D50: 0 | E50: 0 | F50: 0 | G50: 0 | H50: 0 | I50: 0 | J50: 0 | K50: 0 | L50: 0 | M50: 0 | N50: 0 | O50: 0.022 | P50: 0 | Q50: 0 | R50: 0 | S50: 0 | T50: 0 | U50: 0 | V50: 0 | W50: 0 | X50: 0 | Y50: 0 | Z50: 0 | AA50: 0 | AB50: 0 | AC50: 0 | AD50: 0 | AE50: 0 | AF50: 0 | AH50: =SUM(C50:AG50) -> 0.022
A51: Noviembre | B51: =+AH51 -> 0.144 | C51: 0 | D51: 0 | E51: 0 | F51: 0 | G51: 0 | H51: 0.005 | I51: 0 | J51: 0.012 | K51: 0.014 | L51: 0 | M51: 0 | N51: 0.005 | O51: 0.035 | P51: 0 | Q51: 0.031 | R51: 0 | S51: 0 | T51: 0 | U51: 0 | V51: 0.008 | W51: 0.006 | X51: 0.005 | Y51: 0.006 | Z51: 0 | AA51: 0 | AB51: 0 | AC51: 0 | AD51: 0.01 | AE51: 0.007 | AF51: 0 | AH51: =SUM(C51:AG51) -> 0.144
A52: Diciembre | B52: =+AH52 -> 0.038 | C52: 0 | D52: 0 | E52: 0 | F52: 0.003 | G52: 0 | H52: 0 | I52: 0 | J52: 0 | K52: 0 | L52: 0 | M52: 0 | N52: 0 | O52: 0 | P52: 0 | Q52: 0 | R52: 0 | S52: 0 | T52: 0.015 | U52: 0 | V52: 0 | W52: 0 | X52: 0 | Y52: 0.02 | Z52: 0 | AA52: 0 | AB52: 0 | AC52: 0 | AD52: 0 | AE52: 0 | AF52: 0 | AG52: 0 | AH52: =SUM(C52:AG52) -> 0.038
A53: Total | B53: =SUM(B41:B52) -> 0.618 | C53: =SUM(C41:C52) -> 0 | D53: =SUM(D41:D52) -> 0 | E53: =SUM(E41:E52) -> 0 | F53: =SUM(F41:F52) -> 0.003 | G53: =SUM(G41:G52) -> 0 | H53: =SUM(H41:H52) -> 0.005 | I53: =SUM(I41:I52) -> 0 | ... AH53: =SUM(AH41:AH52) -> 0.618
A55: V Región, de Valparaíso
A57: Norte
A58: Mes | B58: Total mes | C58: 1 | D58: 2 | E58: 3 | F58: 4 | G58: 5 | H58: 6 | I58: 7 | J58: 8 | K58: 9 | L58: 10 | M58: 11 | N58: 12 | O58: 13 | P58: 14 | Q58: 15 | R58: 16 | S58: 17 | T58: 18 | U58: 19 | V58: 20 | W58: 21 | X58: 22 | Y58: 23 | Z58: 24 | AA58: 25 | AB58: 26 | AC58: 27 | AD58: 28 | AE58: 29 | AF58: 30 | AG58: 31 | AH58: TOTAL
A59: Enero | B59: =+AH59 -> 3.368 | C59: 0 | D59: 0 | E59: 0.086 | F59: 0.07 | G59: 0.026 | H59: 0.104 | I59: 0.159 | J59: 0.012 | K59: 0.101 | L59: 0 | M59: 0.386 | N59: 0.097 | O59: 0.021 | P59: 0.046 | Q59: 0.022 | R59: 0.163 | S59: 0.196 | T59: 0.257 | U59: 0.173 | V59: 0.185 | W59: 0.276 | X59: 0.086 | Y59: 0.168 | Z59: 0.096 | AA59: 0.107 | AB59: 0.11 | AC59: 0.146 | AD59: 0.092 | AE59: 0.038 | AF59: 0.06 | AG59: 0.085 | AH59: =SUM(C59:AG59) -> 3.368
A60: Febrero | B60: =+AH60 -> 5.104 | C60: 0.085 | D60: 0.097 | E60: 0.066 | F60: 0.153 | G60: 0.036 | H60: 0.28 | I60: 0.265 | J60: 0.245 | K60: 0.42 | L60: 0.217 | M60: 0.195 | N60: 0.084 | O60: 0.455 | P60: 0.549 | Q60: 0.328 | R60: 0.269 | S60: 0.325 | T60: 0.192 | U60: 0.072 | V60: 0.109 | W60: 0.097 | X60: 0.076 | Y60: 0.076 | Z60: 0.203 | AA60: 0.037 | AB60: 0.035 | AC60: 0.048 | AD60: 0.023 | AE60: 0.067 | AF60: 0 | AG60: 0 | AH60: =SUM(C60:AG60) -> 5.104
A61: Marzo | B61: =+AH61 -> 3.448 | C61: 0.266 | D61: 0.174 | E61: 0.15 | F61: 0 | G61: 0.4 | H61: 0.225 | I61: 0.575 | J61: 0.378 | K61: 0.112 | L61: 0.16 | M61: 0.01 | N61: 0.05 | O61: 0.06 | P61: 0.03 | Q61: 0.136 | R61: 0.092 | S61: 0.115 | T61: 0.094 | U61: 0.172 | V61: 0.02 | W61: 0.022 | X61: 0.055 | Y61: 0 | Z61: 0.04 | AA61: 0 | AB61: 0 | AC61: 0 | AD61: 0.01 | AE61: 0.051 | AF61: 0.045 | AG61: 0.006 | AH61: =SUM(C61:AG61) -> 3.448
A62: Abril | B62: =+AH62 -> 1.055 | C62: 0 | D62: 0.064 | E62: 0.004 | F62: 0 | G62: 0 | H62: 0 | I62: 0 | J62: 0 | K62: 0 | L62: 0.01 | M62: 0.004 | N62: 0.062 | O62: 0.26 | P62: 0.034 | Q62: 0.028 | R62: 0.037 | S62: 0.031 | T62: 0 | U62: 0.043 | V62: 0.012 | W62: 0.011 | X62: 0 | Y62: 0.204 | Z62: 0.035 | AA62: 0.03 | AB62: 0.045 | AC62: 0.048 | AD62: 0.034 | AE62: 0.034 | AF62: 0.025 | AG62: 0 | AH62: =SUM(C62:AG62) -> 1.055
