Workbook

Sheet Resumen LTP
A2: Informe
A3: Resumen LTP 2014
A4: Al 31 de Diciembre de 2014
A5: Unidad de Pesquería | B5: Zona | C5: Cuota LTP D.Ex Nº 3789 | D5: Arriendos u otro | E5: Cuota Final | F5: Desembarque total (t) | G5: Aguas internacionales | H5: Saldo total (t) | I5: % consumido 2014
A6: Anchoveta | B6: XV- I - II | C6: =SUM('Pelagicos LTP '!E6:E13) -> 622449 | D6: =SUM('Pelagicos LTP '!F6:F13) -> -34427.978 | E6: =C6+D6 -> 588021.02 | F6: =SUM('Pelagicos LTP '!H6:H13) -> 582421.98 | H6: =E6-F6 -> 5599.04 | I6: =F6/E6 -> 0.99047816
A7: Anchoveta | B7: III - IV | C7: =SUM('Pelagicos LTP '!E16:E35) -> 25787.999 | D7: =SUM('Pelagicos LTP '!F16:F35) -> -12328.369 | E7: =C7+D7 -> 13459.63 | F7: =SUM('Pelagicos LTP '!H16:H35) -> 855.235 | H7: =E7-F7 -> 12604.395 | I7: =F7/E7 -> 0.063540752
A8: Anchoveta | B8: V - X | C8: =SUM('Pelagicos LTP '!E38:E91) -> 9091 | D8: =SUM('Pelagicos LTP '!F38:F91) -> -3909.1671 | E8: =C8+D8 -> 5181.8329 | F8: =SUM('Pelagicos LTP '!H38:H91) -> 3714.964 | H8: =E8-F8 -> 1466.8689 | I8: =F8/E8 -> 0.71692084
A9: Camarón nailon | B9: II-VIII | C9: =SUM('Crustaceos LTP'!AU6:AU49) -> 3656.047 | D9: =SUM('Crustaceos LTP'!AV6:AV49,'Crustaceos LTP'!AW6:AW49) -> 29.91324 | E9: =C9+D9 -> 3685.9602 | F9: =SUM('Crustaceos LTP'!AY6:AY49) -> 3457.254 | H9: =E9-F9 -> 228.70624 | I9: =F9/E9 -> 0.93795206
A10: Congrio dorado | B10: NE F + H | C10: =SUM('Demersales LTP '!E7:E18) -> 371 | D10: =SUM('Demersales LTP '!F7:F18) -> -1.2434498e-14 | E10: =C10+D10 -> 371 | F10: =SUM('Demersales LTP '!H7:H18) -> 142.107 | H10: =E10-F10 -> 228.893 | I10: =F10/E10 -> 0.38303774
A11: Congrio dorado | B11: SE | C11: =SUM('Demersales LTP '!E20:E31) -> 132 | D11: =SUM('Demersales LTP '!F20:F31) -> 0 | E11: =C11+D11 -> 132 | F11: =SUM('Demersales LTP '!H20:H31) -> 112.515 | H11: =E11-F11 -> 19.485 | I11: =F11/E11 -> 0.85238636
A12: Jurel | B12: XV - I - II | C12: =SUM('Pelagicos LTP '!E94:E101) -> 40541.004 | D12: =SUM('Pelagicos LTP '!F94:F101) -> -20087.134 | E12: =C12+D12 -> 20453.87 | F12: =SUM('Pelagicos LTP '!H94:H101) -> 16609.319 | H12: =E12-F12 -> 3844.551 | I12: =F12/E12 -> 0.81203797
A13: Jurel | B13: III - IV | C13: =SUM('Pelagicos LTP '!E104:E133) -> 8566.999 | D13: =SUM('Pelagicos LTP '!F104:F133) -> -2133.466 | E13: =C13+D13 -> 6433.533 | F13: =SUM('Pelagicos LTP '!H104:H133) -> 5818.638 | G13: 1131.25 | H13: =E13-F13 -> 614.895 | I13: =F13/E13 -> 0.90442343
A14: Jurel | B14: V - IX | C14: =SUM('Pelagicos LTP '!E136:E199) -> 183371 | D14: =SUM('Pelagicos LTP '!F136:F199) -> 31218.147 | E14: =C14+D14 -> 214589.15 | F14: =SUM('Pelagicos LTP '!H136:H199) -> 203757.62 | G14: 2008.341 | H14: =E14-F14 -> 10831.53 | I14: =F14/E14 -> 0.94952433
A15: Jurel | B15: XIV - X | C15: =SUM('Pelagicos LTP '!E202:E251) -> 25706.997 | D15: =SUM('Pelagicos LTP '!F202:F251) -> -3963.787 | E15: =C15+D15 -> 21743.21 | F15: =SUM('Pelagicos LTP '!H202:H251) -> 20825.237 | G15: 843.352 | H15: =E15-F15 -> 917.973 | I15: =F15/E15 -> 0.95778116
A16: Langostino amarillo | B16: III-IV | C16: =SUM('Crustaceos LTP'!Q55:Q93) -> 1198.001 | D16: =SUM('Crustaceos LTP'!R55:R93,'Crustaceos LTP'!S55:S93) -> 0 | E16: =C16+D16 -> 1198.001 | F16: =SUM('Crustaceos LTP'!U55:U93) -> 1025.012 | H16: =E16-F16 -> 172.989 | I16: =F16/E16 -> 0.85560196
A17: Langostino colorado | B17: I -IV | C17: =SUM('Crustaceos LTP'!W98:W127) -> 43.001 | D17: =SUM('Crustaceos LTP'!X98:X127,'Crustaceos LTP'!Y98:Y127) -> 157.842 | E17: =C17+D17 -> 200.843 | F17: =SUM('Crustaceos LTP'!AA98:AA127) -> 159.847 | H17: =E17-F17 -> 40.996 | I17: =F17/E17 -> 0.79588036
A18: Merluza común | B18: IV- 41º 28, 6 | C18: =SUM('Demersales LTP '!E156:E215) -> 11166 | D18: =SUM('Demersales LTP '!F156:F215) -> 13.246 | E18: =C18+D18 -> 11179.246 | F18: =SUM('Demersales LTP '!H156:H215) -> 10886.994 | H18: =E18-F18 -> 292.252 | I18: =F18/E18 -> 0.97385763
A19: Merluza de cola | B19: V -X | C19: =SUM('Demersales LTP '!E72:E137) -> 23909.996 | D19: =SUM('Demersales LTP '!F72:F137) -> -10977.963 | E19: =C19+D19 -> 12932.033 | F19: =SUM('Demersales LTP '!H72:H137) -> 12566 | H19: =E19-F19 -> 366.033 | I19: =F19/E19 -> 0.97169563
A20: Merluza de cola | B20: XI -XII | C20: =SUM('Demersales LTP '!E139:E154) -> 15939.928 | D20: =SUM('Demersales LTP '!F139:F154) -> 10977.964 | E20: =C20+D20 -> 26917.892 | F20: =SUM('Demersales LTP '!H139:H154) -> 26551.647 | H20: =E20-F20 -> 366.245 | I20: =F20/E20 -> 0.98639399
A21: Merluza de tres aletas | B21: 41º28,6 - XII | C21: =SUM('Demersales LTP '!E61:E70) -> 14300 | D21: =SUM('Demersales LTP '!F61:F70) -> -3.4083847e-14 | E21: =C21+D21 -> 14300 | F21: =SUM('Demersales LTP '!H61:H70) -> 9942.857 | H21: =E21-F21 -> 4357.143 | I21: =F21/E21 -> 0.69530469
A22: Merluza del sur | B22: NE F + H | C22: =SUM('Demersales LTP '!E33:E46) -> 2913.001 | D22: =SUM('Demersales LTP '!F33:F46) -> 2495.247 | E22: =C22+D22 -> 5408.248 | F22: =SUM('Demersales LTP '!H33:H46) -> 5381.7 | H22: =E22-F22 -> 26.548 | I22: =F22/E22 -> 0.9950912
A23: Merluza del sur | B23: SE | C23: =SUM('Demersales LTP '!E48:E59) -> 1863 | D23: =SUM('Demersales LTP '!F48:F59) -> -475.805 | E23: =C23+D23 -> 1387.195 | F23: =SUM('Demersales LTP '!H48:H59) -> 1224.733 | H23: =E23-F23 -> 162.462 | I23: =F23/E23 -> 0.88288453
A24: Sardina común | B24: V -X | C24: =SUM('Pelagicos LTP '!E254:E313) -> 123307 | D24: =SUM('Pelagicos LTP '!F254:F313) -> -46600.667 | E24: =C24+D24 -> 76706.332 | F24: =SUM('Pelagicos LTP '!H254:H313) -> 75206.881 | H24: =E24-F24 -> 1499.451 | I24: =F24/E24 -> 0.98045206
A25: Sardina española | B25: XV- I - II | C25: =SUM('Pelagicos LTP '!E316:E323) -> 588 | D25: =SUM('Pelagicos LTP '!F316:F323) -> -1.932 | E25: =C25+D25 -> 586.068 | F25: =SUM('Pelagicos LTP '!H316:H323) -> 0 | H25: =E25-F25 -> 586.068 | I25: =F25/E25 -> 0
A26: Sardina española | B26: III - IV | C26: =SUM('Pelagicos LTP '!E326:E347) -> 700 | D26: =SUM('Pelagicos LTP '!F326:F347) -> -99.90997 | E26: =C26+D26 -> 600.09003 | F26: =SUM('Pelagicos LTP '!H326:H347) -> 8.446 | H26: =E26-F26 -> 591.64403 | I26: =F26/E26 -> 0.014074555
A28: Nota: desembarque aguas internacionales Jurel desde III a X regiones, esta incorporado en la columna de desembarque total, solo se incorpora el dato para tenerlo de referencia

Sheet Pelagicos LTP 
B1: 2014. CUOTAS LTP Y SU CONSUMO DE RECURSOS PELÁGICOS al 31 de diciembre de 2014
C4: Periodo | E4: Cuota (t) | H4: Operación | K4: Global
A5: Unidad de pesquería | B5: Titular de cuota LTP | C5: Inicial | D5: Final | E5: Cuota Asignada | F5: Traspaso, Cesion, Arriendo, etc) | G5: Cuota Efectiva | H5: Desembarque (t) | I5: Saldo (t) | J5: % consumido | K5: Cuota (t) | L5: Desembarque (t) | M5: Saldo (t) | N5: % consumido
A6: Anchoveta XV - I - II | B6: Arica Seafood Producer S.A. | C6: 39083 | D6: 39263 | E6: 3320.985 | F6: =-3320.985 -> -3320.985 | G6: =E6+F6 -> 0 | I6: =G6-H6 -> 0 | J6: =H6/G6 -> #DIV/0! | K6: =E6+E7+F6+F7 -> 0 | L6: =H6+H7 -> 0 | M6: =K6-L6 -> 0 | N6: =L6/K6 -> #DIV/0!
C7: 39264 | D7: 39447 | E7: 1106.993 | F7: =-1106.993 -> -1106.993 | G7: =E7+F7+I6 -> 0 | I7: =G7-H7 -> 0 | J7: =H7/G7 -> #DIV/0!
B8: Camanchaca S.A. Cia. Pesq. | C8: 39083 | D8: 39263 | E8: 92144.847 | G8: =+E8+F8 -> 92144.847 | H8: 64993.394 | I8: =G8-H8 -> 27151.453 | J8: =H8/G8 -> 0.70533943 | K8: =E8+E9+F8+F9 -> 122859.73 | L8: =H8+H9 -> 122770.28 | M8: =K8-L8 -> 89.45 | N8: =L8/K8 -> 0.99927193
C9: 39264 | D9: 39447 | E9: 30714.883 | G9: =E9+F9+I8 -> 57866.336 | H9: 57776.886 | I9: =G9-H9 -> 89.45 | J9: =H9/G9 -> 0.9984542 | O9: 32728
B10: Corpesca S.A. | C10: 39083 | D10: 39263 | E10: 371371.17 | G10: =E10+F10 -> 371371.17 | H10: 223426.06 | I10: =G10-H10 -> 147945.11 | J10: =H10/G10 -> 0.60162469 | K10: =E10+E11+F10+F11 -> 465161.29 | L10: =H10+H11 -> 459651.7 | M10: =K10-L10 -> 5509.59 | N10: =L10/K10 -> 0.98815553 | O10: =+O9-H9 -> -25048.886
C11: 39264 | D11: 39447 | E11: 123790.12 | F11: =-20000-5000-5000 -> -30000 | G11: =E11+F11+I10 -> 241735.23 | H11: 236225.64 | I11: =G11-H11 -> 5509.59 | J11: =H11/G11 -> 0.97720816
B12: Orizón S.A | C12: 39083 | D12: 39263 | E12: 0 | G12: =E12+F12 -> 0 | I12: =G12-H12 -> 0 | J12: =H12/G12 -> #DIV/0! | K12: =E12+E13+F12+F13 -> 0 | L12: =H12+H13 -> 0 | M12: =K12-L12 -> 0 | N12: =L12/K12 -> #DIV/0!
C13: 39264 | D13: 39447 | E13: 0 | G13: =E13+F13+I12 -> 0 | I13: =G13-H13 -> 0 | J13: =H13/G13 -> #DIV/0!
A16: Anchoveta III - IV | B16: Alimentos Marinos S.A., | C16: 39083 | D16: 39386 | E16: 858.817 | F16: =777.446-554 -> 223.446 | G16: =E16+F16 -> 1082.263 | I16: =G16-H16 -> 1082.263 | J16: =H16/G16 -> 0 | K16: =E16+E17+F16+F17 -> 1144.887 | L16: =H16+H17 -> 855.235 | M16: =K16-L16 -> 289.652 | N16: =L16/K16 -> 0.74700385
C17: 39387 | D17: 39447 | E17: 45.186 | F17: =17.438 -> 17.438 | G17: =E17+F17+I16 -> 1144.887 | H17: 855.235 | I17: =G17-H17 -> 289.652 | J17: =H17/G17 -> 0.74700385
B18: Bahia Caldera S.A. Pesq. | C18: 39083 | D18: 39386 | E18: 6808.598 | F18: =-3166.828-2641.77 -> -5808.598 | G18: =E18+F18 -> 1000 | I18: =G18-H18 -> 1000 | J18: =H18/G18 -> 0 | K18: =E18+E19+F18+F19 -> 0 | L18: =H18+H19 -> 0 | M18: =K18-L18 -> 0 | N18: =L18/K18 -> #DIV/0!
C19: 39387 | D19: 39447 | E19: 358.23 | F19: =-358.23-1000 -> -1358.23 | G19: =E19+F19+I18 -> 0 | I19: =G19-H19 -> 0 | J19: =H19/G19 -> #DIV/0!
B20: Blumar S.A. | C20: 39083 | D20: 39386 | E20: 5319.902 | F20: =-3.09-5316.812 -> -5319.902 | G20: =E20+F20 -> 0 | I20: =G20-H20 -> 0 | J20: =H20/G20 -> #DIV/0! | K20: =E20+E21+F20+F21 -> 1000 | L20: =H20+H21 -> 0 | M20: =K20-L20 -> 1000 | N20: =L20/K20 -> 0
C21: 39387 | D21: 39447 | E21: 279.903 | F21: =-279.903+1000 -> 720.097 | G21: =E21+F21+I20 -> 1000 | I21: =G21-H21 -> 1000 | J21: =H21/G21 -> 0
B22: Camanchaca S.A. Cia. Pesq. | C22: 39083 | D22: 39386 | E22: 777.446 | F22: =-777.446 -> -777.446 | G22: =E22+F22 -> 0 | I22: =G22-H22 -> 0 | J22: =H22/G22 -> #DIV/0! | K22: =E22+E23+F22+F23 -> 23.466846 | L22: =H22+H23 -> 0 | M22: =K22-L22 -> 23.466846 | N22: =L22/K22 -> 0
C23: 39387 | D23: 39447 | E23: 40.905 | F23: =-17.4381544 -> -17.438154 | G23: =E23+F23+I22 -> 23.466846 | I23: =G23-H23 -> 23.466846 | J23: =H23/G23 -> 0
B24: Corpesca S.A., | C24: 39083 | D24: 39386 | E24: 0 | G24: =E24+F24 -> 0 | I24: =G24-H24 -> 0 | J24: =H24/G24 -> #DIV/0! | K24: =E24+E25+F24+F25 -> 0 | L24: =H24+H25 -> 0 | M24: =K24-L24 -> 0 | N24: =L24/K24 -> #DIV/0!
C25: 39387 | D25: 39447 | E25: 0 | G25: =E25+F25+I24 -> 0 | I25: =G25-H25 -> 0 | J25: =H25/G25 -> #DIV/0!
B26: Inversiones Pesqueras S.A. | C26: 39083 | D26: 39386 | E26: 279.921 | F26: =-0.258 -> -0.258 | G26: =E26+F26 -> 279.663 | I26: =G26-H26 -> 279.663 | J26: =H26/G26 -> 0 | K26: =E26+E27+F26+F27 -> 294.391 | L26: =H26+H27 -> 0 | M26: =K26-L26 -> 294.391 | N26: =L26/K26 -> 0
C27: 39387 | D27: 39447 | E27: 14.728 | G27: =E27+F27+I26 -> 294.391 | I27: =G27-H27 -> 294.391 | J27: =H27/G27 -> 0
B28: Orizón S.A. | C28: 39083 | D28: 39386 | E28: 10380.341 | F28: =-10.826 -> -10.826 | G28: =E28+F28 -> 10369.515 | I28: =G28-H28 -> 10369.515 | J28: =H28/G28 -> 0 | K28: =E28+E29+F28+F29 -> 10915.67 | L28: =H28+H29 -> 0 | M28: =K28-L28 -> 10915.67 | N28: =L28/K28 -> 0
C29: 39387 | D29: 39447 | E29: 546.155 | G29: =E29+F29+I28 -> 10915.67 | I29: =G29-H29 -> 10915.67 | J29: =H29/G29 -> 0
B30: Camanchaca Pesca Sur S.A. | C30: 39083 | D30: 39386 | E30: 73.975 | G30: =E30+F30 -> 73.975 | I30: =G30-H30 -> 73.975 | J30: =H30/G30 -> 0 | K30: =E30+E31+F30+F31 -> 77.867 | L30: =H30+H31 -> 0 | M30: =K30-L30 -> 77.867 | N30: =L30/K30 -> 0
C31: 39387 | D31: 39447 | E31: 3.892 | G31: =E31+F31+I30 -> 77.867 | I31: =G31-H31 -> 77.867 | J31: =H31/G31 -> 0
B32: Centro Sur Pesq. S.A. | C32: 39083 | D32: 39386 | E32: 0 | F32: =0.258 -> 0.258 | G32: =E32+F32 -> 0.258 | I32: =G32-H32 -> 0.258 | J32: =H32/G32 -> 0 | K32: =E32+E33+F32+F33 -> 0.258 | L32: =H32+H33 -> 0 | M32: =K32-L32 -> 0.258 | N32: =L32/K32 -> 0
C33: 39387 | D33: 39447 | E33: 0 | G33: =E33+F33+I32 -> 0.258 | I33: =G33-H33 -> 0.258 | J33: =H33/G33 -> 0
B34: Landes S.A. | C34: 39083 | D34: 39386 | E34: 0 | F34: =3.09 -> 3.09 | G34: =E34+F34 -> 3.09 | I34: =G34-H34 -> 3.09 | J34: =H34/G34 -> 0 | K34: =E34+E35+F34+F35 -> 3.09 | L34: =H34+H35 -> 0 | M34: =K34-L34 -> 3.09 | N34: =L34/K34 -> 0
C35: 39387 | D35: 39447 | E35: 0 | G35: =E35+F35+I34 -> 3.09 | I35: =G35-H35 -> 3.09 | J35: =H35/G35 -> 0
A38: Anchoveta V-X | B38: Alimentos Marinos S.A. | C38: 39083 | D38: 39202 | E38: 1438.139 | F38: =-70-950-70-70-315-40-40+207.961+2.492+15.329+8.0655352 -> -1321.1525 | G38: =E38+F38 -> 116.98654 | I38: =G38-H38 -> 116.98654 | J38: =H38/G38 -> 0 | K38: =E38+E39+E40+F38+F39+F40 -> 250.85254 | L38: =H38+H39+H40 -> 81.328 | M38: =K38-L38 -> 169.52454 | N38: =L38/K38 -> 0.32420641
C39: 39203 | D39: 39691 | E39: 169.182 | F39: =-120 -> -120 | G39: =E39+F39+I38 -> 166.16854 | H39: 31.313 | I39: =G39-H39 -> 134.85554 | J39: =H39/G39 -> 0.18844121
C40: 39692 | D40: 39813 | E40: 84.684 | G40: =E40+F40+I39 -> 219.53954 | H40: 50.015 | I40: =G40-H40 -> 169.52454 | J40: =H40/G40 -> 0.22781774
B41: Berta Elena Ltda. Soc. Pesq. | C41: 39083 | D41: 39202 | E41: 27.075 | F41: =-27.075 -> -27.075 | G41: =E41+F41 -> 0 | I41: =G41-H41 -> 0 | J41: =H41/G41 -> #DIV/0! | K41: =E41+E42+E43+F41+F42+F43 -> 0 | L41: =H41+H42+H43 -> 0 | M41: =K41-L41 -> 0 | N41: =L41/K41 -> #DIV/0!
C42: 39203 | D42: 39691 | E42: 3.185 | F42: =-3.185 -> -3.185 | G42: =E42+F42+I41 -> 0 | I42: =G42-H42 -> 0 | J42: =H42/G42 -> #DIV/0!
C43: 39692 | D43: 39813 | E43: 1.594 | F43: =-1.594 -> -1.594 | G43: =E43+F43+I42 -> 0 | I43: =G43-H43 -> 0 | J43: =H43/G43 -> #DIV/0!
B44: Blumar S.A. | C44: 39083 | D44: 39202 | E44: 1816.775 | F44: =-680-340-70-160-20 -> -1270 | G44: =E44+F44 -> 546.775 | I44: =G44-H44 -> 546.775 | J44: =H44/G44 -> 0 | K44: =E44+E45+E46+F44+F45+F46 -> 867.479 | L44: =H44+H45+H46 -> 66.287 | M44: =K44-L44 -> 801.192 | N44: =L44/K44 -> 0.076413377
C45: 39203 | D45: 39691 | E45: 213.724 | G45: =E45+F45+I44 -> 760.499 | H45: 66.287 | I45: =G45-H45 -> 694.212 | J45: =H45/G45 -> 0.087162508
C46: 39692 | D46: 39813 | E46: 106.98 | G46: =E46+F46+I45 -> 801.192 | I46: =G46-H46 -> 801.192 | J46: =H46/G46 -> 0
B47: Camanchaca Pesca Sur S.A. | C47: 39083 | D47: 39202 | E47: 1196.218 | F47: =-130-30-5 -> -165 | G47: =E47+F47 -> 1031.218 | H47: 639.487 | I47: =G47-H47 -> 391.731 | J47: =H47/G47 -> 0.62012785 | K47: =E47+E48+E49+F47+F48+F49 -> 1185.379 | L47: =H47+H48+H49 -> 1174.957 | M47: =K47-L47 -> 10.422 | N47: =L47/K47 -> 0.99120788
C48: 39203 | D48: 39691 | E48: 140.722 | G48: =E48+F48+I47 -> 532.453 | H48: 465.093 | I48: =G48-H48 -> 67.36 | J48: =H48/G48 -> 0.87349118
C49: 39692 | D49: 39813 | E49: 70.439 | F49: =-37-20 -> -57 | G49: =E49+F49+I48 -> 80.799 | H49: 70.377 | I49: =G49-H49 -> 10.422 | J49: =H49/G49 -> 0.87101326
B50: Camanchaca S.A. Cia. Pesq. | C50: 39083 | D50: 39202 | E50: 66.817 | F50: =-8.0655352 -> -8.0655352 | G50: =E50+F50 -> 58.751465 | I50: =G50-H50 -> 58.751465 | J50: =H50/G50 -> 0 | K50: =E50+E51+E52+F50+F51+F52 -> 70.545465 | L50: =H50+H51+H52 -> 0 | M50: =K50-L50 -> 70.545465 | N50: =L50/K50 -> 0
C51: 39203 | D51: 39691 | E51: 7.86 | G51: =E51+F51+I50 -> 66.611465 | I51: =G51-H51 -> 66.611465 | J51: =H51/G51 -> 0
C52: 39692 | D52: 39813 | E52: 3.934 | G52: =E52+F52+I51 -> 70.545465 | I52: =G52-H52 -> 70.545465 | J52: =H52/G52 -> 0
B53: Centro Sur S.A. Pesq. | C53: 39083 | D53: 39202 | E53: 164.053 | F53: =-46.272-22.364-64.547-40.181 -> -173.364 | G53: =E53+F53 -> -9.311 | I53: =G53-H53 -> -9.311 | J53: =H53/G53 -> 0 | K53: =E53+E54+E55+F53+F54+F55 -> 24.194 | L53: =H53+H54+H55 -> 0 | M53: =K53-L53 -> 24.194 | N53: =L53/K53 -> 0
C54: 39203 | D54: 39691 | E54: 19.299 | G54: =E54+F54+I53 -> 9.988 | I54: =G54-H54 -> 9.988 | J54: =H54/G54 -> 0
C55: 39692 | D55: 39813 | E55: 9.66 | F55: =4.546 -> 4.546 | G55: =E55+F55+I54 -> 24.194 | I55: =G55-H55 -> 24.194 | J55: =H55/G55 -> 0
B56: Foodcorp S.A. | C56: 39083 | D56: 39202 | E56: 307.235 | F56: =-40-80 -> -120 | G56: =E56+F56 -> 187.235 | I56: =G56-H56 -> 187.235 | J56: =H56/G56 -> 0 | K56: =E56+E57+E58+F56+F57+F58 -> 135.469 | L56: =H56+H57+H58 -> 3.987 | M56: =K56-L56 -> 131.482 | N56: =L56/K56 -> 0.029431088
C57: 39203 | D57: 39691 | E57: 36.143 | F57: =-40-13-13-40 -> -106 | G57: =E57+F57+I56 -> 117.378 | H57: 3.987 | I57: =G57-H57 -> 113.391 | J57: =H57/G57 -> 0.033967183
C58: 39692 | D58: 39813 | E58: 18.091 | G58: =E58+F58+I57 -> 131.482 | I58: =G58-H58 -> 131.482 | J58: =H58/G58 -> 0
B59: Genmar Ltda. Soc. Pesq. | C59: 39083 | D59: 39202 | E59: 2.342 | F59: =-2.342 -> -2.342 | G59: =E59+F59 -> 0 | I59: =G59-H59 -> 0 | J59: =H59/G59 -> #DIV/0! | K59: =E59+E60+E61+F59+F60+F61 -> 0 | L59: =H59+H60+H61 -> 0 | M59: =K59-L59 -> 0 | N59: =L59/K59 -> #DIV/0!
C60: 39203 | D60: 39691 | E60: 0.276 | F60: =-0.276 -> -0.276 | G60: =E60+F60+I59 -> 0 | I60: =G60-H60 -> 0 | J60: =H60/G60 -> #DIV/0!
C61: 39692 | D61: 39813 | E61: 0.138 | F61: =-0.138 -> -0.138 | G61: =E61+F61+I60 -> 0 | I61: =G61-H61 -> 0 | J61: =H61/G61 -> #DIV/0!
B62: Inostroza Concha Pelantaro | C62: 39083 | D62: 39202 | E62: 7.252 | F62: =-7.252 -> -7.252 | G62: =E62+F62 -> 0 | I62: =G62-H62 -> 0 | J62: =H62/G62 -> #DIV/0! | K62: =E62+E63+E64+F62+F63+F64 -> 0 | L62: =H62+H63+H64 -> 0 | M62: =K62-L62 -> 0 | N62: =L62/K62 -> #DIV/0!
C63: 39203 | D63: 39691 | E63: 0.853 | F63: =-0.853 -> -0.853 | G63: =E63+F63+I62 -> 0 | I63: =G63-H63 -> 0 | J63: =H63/G63 -> #DIV/0!
C64: 39692 | D64: 39813 | E64: 0.427 | F64: =-0.427 -> -0.427 | G64: =E64+F64+I63 -> 0 | I64: =G64-H64 -> 0 | J64: =H64/G64 -> #DIV/0!
B65: Inversiones Pesqueras S.A. | C65: 39083 | D65: 39202 | E65: 120.234 | F65: =-71.637-48.597 -> -120.234 | G65: =E65+F65 -> 0 | I65: =G65-H65 -> 0 | J65: =H65/G65 -> #DIV/0! | K65: =E65+E66+E67+F65+F66+F67 -> 2.638 | L65: =H65+H66+H67 -> 0 | M65: =K65-L65 -> 2.638 | N65: =L65/K65 -> 0
C66: 39203 | D66: 39691 | E66: 14.144 | F66: =-14.04 -> -14.04 | G66: =E66+F66+I65 -> 0.104 | I66: =G66-H66 -> 0.104 | J66: =H66/G66 -> 0
C67: 39692 | D67: 39813 | E67: 7.08 | F67: =-4.546 -> -4.546 | G67: =E67+F67+I66 -> 2.638 | I67: =G67-H67 -> 2.638 | J67: =H67/G67 -> 0
B68: Isla Quihua S.A. Pesq. | C68: 39083 | D68: 39202 | E68: 64.027 | F68: =-20-40-15.329 -> -75.329 | G68: =E68+F68 -> -11.302 | I68: =G68-H68 -> -11.302 | J68: =H68/G68 -> 0 | K68: =E68+E69+E70+F68+F69+F70 -> 0 | L68: =H68+H69+H70 -> 0 | M68: =K68-L68 -> 0 | N68: =L68/K68 -> #DIV/0!
C69: 39203 | D69: 39691 | E69: 7.532 | G69: =E69+F69+I68 -> -3.77 | I69: =G69-H69 -> -3.77 | J69: =H69/G69 -> 0
C70: 39692 | D70: 39813 | E70: 3.77 | G70: =E70+F70+I69 -> 0 | I70: =G70-H70 -> 0 | J70: =H70/G70 -> #DIV/0!
B71: Landes S.A. Soc. Pesq. | C71: 39083 | D71: 39202 | E71: 541.056 | F71: =50.728 -> 50.728 | G71: =E71+F71 -> 591.784 | H71: 28.902 | I71: =G71-H71 -> 562.882 | J71: =H71/G71 -> 0.048838765 | K71: =E71+E72+E73+F71+F72+F73 -> 737.294 | L71: =H71+H72+H73 -> 641.811 | M71: =K71-L71 -> 95.483 | N71: =L71/K71 -> 0.87049535
C72: 39203 | D72: 39691 | E72: 63.65 | F72: =50 -> 50 | G72: =E72+F72+I71 -> 676.532 | H72: 214.377 | I72: =G72-H72 -> 462.155 | J72: =H72/G72 -> 0.31687636
C73: 39692 | D73: 39813 | E73: 31.86 | G73: =E73+F73+I72 -> 494.015 | H73: 398.532 | I73: =G73-H73 -> 95.483 | J73: =H73/G73 -> 0.80672044
B74: Lota Protein S.A. | C74: 39083 | D74: 39202 | E74: 89.343 | F74: =2.342+27.075+7.252+93.335 -> 130.004 | G74: =E74+F74 -> 219.347 | H74: 32.771 | I74: =G74-H74 -> 186.576 | J74: =H74/G74 -> 0.14940254 | K74: =E74+E75+E76+F74+F75+F76 -> 268.591 | L74: =H74+H75+H76 -> 144.795 | M74: =K74-L74 -> 123.796 | N74: =L74/K74 -> 0.53909103
C75: 39203 | D75: 39691 | E75: 10.51 | F75: =0.276+3.185+0.853+27 -> 31.314 | G75: =E75+F75+I74 -> 228.4 | H75: 87.318 | I75: =G75-H75 -> 141.082 | J75: =H75/G75 -> 0.38230298
C76: 39692 | D76: 39813 | E76: 5.261 | F76: =0.138+1.594+0.427 -> 2.159 | G76: =E76+F76+I75 -> 148.502 | H76: 24.706 | I76: =G76-H76 -> 123.796 | J76: =H76/G76 -> 0.16636813
B77: Mar profundo S.A. Soc. Pesq. | C77: 39083 | D77: 39202 | E77: 31.867 | F77: =-35-2.492 -> -37.492 | G77: =E77+F77 -> -5.625 | I77: =G77-H77 -> -5.625 | J77: =H77/G77 -> 0 | K77: =E77+E78+E79+F77+F78+F79 -> 0 | L77: =H77+H78+H79 -> 0 | M77: =K77-L77 -> 0 | N77: =L77/K77 -> #DIV/0!
C78: 39203 | D78: 39691 | E78: 3.749 | G78: =E78+F78+I77 -> -1.876 | I78: =G78-H78 -> -1.876 | J78: =H78/G78 -> 0
C79: 39692 | D79: 39813 | E79: 1.876 | G79: =E79+F79+I78 -> 0 | I79: =G79-H79 -> 0 | J79: =H79/G79 -> #DIV/0!
B80: Orizón S.A. | C80: 39083 | D80: 39202 | E80: 1646.597 | F80: =-298.955 -> -298.955 | G80: =E80+F80 -> 1347.642 | H80: 8.29 | I80: =G80-H80 -> 1339.352 | J80: =H80/G80 -> 0.0061514853 | K80: =E80+E81+E82+F80+F81+F82 -> 1638.306 | L80: =H80+H81+H82 -> 1601.799 | M80: =K80-L80 -> 36.507 | N80: =L80/K80 -> 0.97771662
C81: 39203 | D81: 39691 | E81: 193.705 | G81: =E81+F81+I80 -> 1533.057 | H81: 1588.432 | I81: =G81-H81 -> -55.375 | J81: =H81/G81 -> 1.0361206
C82: 39692 | D82: 39813 | E82: 96.959 | G82: =E82+F82+I81 -> 41.584 | H82: 5.077 | I82: =G82-H82 -> 36.507 | J82: =H82/G82 -> 0.12209023
B83: Salmoalimentos S.A. | C83: 39083 | D83: 39202 | E83: 31.211 | F83: =-31.211 -> -31.211 | G83: =E83+F83 -> 0 | I83: =G83-H83 -> 0 | J83: =H83/G83 -> #DIV/0! | K83: =E83+E84+E85+F83+F84+F85 -> 0 | L83: =H83+H84+H85 -> 0 | M83: =K83-L83 -> 0 | N83: =L83/K83 -> #DIV/0!
C84: 39203 | D84: 39691 | E84: 3.672 | F84: =-3.672 -> -3.672 | G84: =E84+F84+I83 -> 0 | I84: =G84-H84 -> 0 | J84: =H84/G84 -> #DIV/0!
C85: 39692 | D85: 39813 | E85: 1.838 | F85: =-1.838 -> -1.838 | G85: =E85+F85+I84 -> 0 | I85: =G85-H85 -> 0 | J85: =H85/G85 -> #DIV/0!
B86: San Antonio S.A. Pesq. | C86: 39083 | D86: 39202 | E86: 176.76 | F86: =-207.9621 -> -207.9621 | G86: =E86+F86 -> -31.2021 | I86: =G86-H86 -> -31.2021 | J86: =H86/G86 -> 0 | K86: =E86+E87+E88+F86+F87+F88 -> -0.0001 | L86: =H86+H87+H88 -> 0 | M86: =K86-L86 -> -0.0001 | N86: =L86/K86 -> 0
C87: 39203 | D87: 39691 | E87: 20.794 | G87: =E87+F87+I86 -> -10.4081 | I87: =G87-H87 -> -10.4081 | J87: =H87/G87 -> 0
C88: 39692 | D88: 39813 | E88: 10.408 | G88: =E88+F88+I87 -> -0.0001 | I88: =G88-H88 -> -0.0001 | J88: =H88/G88 -> 0
B89: Inversiones Santana SpA. | C89: 39083 | D89: 39202 | E89: 0 | F89: =31.211-31.211 -> 0 | G89: =E89+F89 -> 0 | I89: =G89-H89 -> 0 | J89: =H89/G89 -> #DIV/0! | K89: =E89+E90+E91+F89+F90+F91 -> 1.085 | L89: =H89+H90+H91 -> 0 | M89: =K89-L89 -> 1.085 | N89: =L89/K89 -> 0
C90: 39203 | D90: 39691 | E90: 0 | F90: =3.672-3.672 -> 0 | G90: =E90+F90+I89 -> 0 | I90: =G90-H90 -> 0 | J90: =H90/G90 -> #DIV/0!
C91: 39692 | D91: 39813 | E91: 0 | F91: =1.838-0.753 -> 1.085 | G91: =E91+F91+I90 -> 1.085 | I91: =G91-H91 -> 1.085 | J91: =H91/G91 -> 0
A94: Jurel XV-I-II | B94: Arica Seafood Producer S.A. | C94: 39083 | D94: 39355 | E94: 158.878 | F94: =-158.878 -> -158.878 | G94: =E94+F94 -> 0 | I94: =G94-H94 -> 0 | J94: =H94/G94 -> #DIV/0! | K94: =E94+E95+F94+F95 -> 0 | L94: =H94+H95 -> 0 | M94: =K94-L94 -> 0 | N94: =L94/K94 -> #DIV/0!
C95: 39356 | D95: 39447 | E95: 8.362 | F95: =-8.362 -> -8.362 | G95: =E95+F95+I94 -> 0 | I95: =G95-H95 -> 0 | J95: =H95/G95 -> #DIV/0!
B96: Camanchaca S.A. Cia. Pesq. | C96: 39083 | D96: 39355 | E96: 6731.119 | F96: =-1520.294 -> -1520.294 | G96: =E96+F96 -> 5210.825 | H96: 3160.315 | I96: =G96-H96 -> 2050.51 | J96: =H96/G96 -> 0.60649034 | K96: =E96+E97+F96+F97 -> 3165.485 | L96: =H96+H97 -> 3160.315 | M96: =K96-L96 -> 5.17 | N96: =L96/K96 -> 0.99836676
C97: 39356 | D97: 39447 | E97: 354.26 | F97: =-300-399.6-1700 -> -2399.6 | G97: =E97+F97+I96 -> 5.17 | I97: =G97-H97 -> 5.17 | J97: =H97/G97 -> 0
B98: Corpesca S.A. | C98: 39083 | D98: 39355 | E98: 31624.007 | F98: =-1000 -> -1000 | G98: =E98+F98 -> 30624.007 | H98: 13248.485 | I98: =G98-H98 -> 17375.522 | J98: =H98/G98 -> 0.43261762 | K98: =E98+E99+F98+F99 -> 17288.385 | L98: =H98+H99 -> 13449.004 | M98: =K98-L98 -> 3839.381 | N98: =L98/K98 -> 0.77792136
C99: 39356 | D99: 39447 | E99: 1664.378 | F99: =-3000-3000-2000-1000-1500-1500-3000 -> -15000 | G99: =E99+F99+I98 -> 4039.9 | H99: 200.519 | I99: =G99-H99 -> 3839.381 | J99: =H99/G99 -> 0.049634644
B100: Orizón S.A. | C100: 39083 | D100: 39355 | E100: 0 | G100: =E100+F100 -> 0 | I100: =G100-H100 -> 0 | J100: =H100/G100 -> #DIV/0! | K100: =E100+E101+F100+F101 -> 0 | L100: =H100+H101 -> 0 | M100: =K100-L100 -> 0 | N100: =L100/K100 -> #DIV/0!
C101: 39356 | D101: 39447 | E101: 0 | G101: =E101+F101+I100 -> 0 | I101: =G101-H101 -> 0 | J101: =H101/G101 -> #DIV/0!
A104: Jurel III - IV | B104: Alimentos Marinos S.A. | C104: 39083 | D104: 39355 | E104: 680.901 | F104: =114.463 -> 114.463 | G104: =E104+F104 -> 795.364 | H104: 715.707 | I104: =G104-H104 -> 79.657 | J104: =H104/G104 -> 0.89984837 | K104: =E104+E105+F104+F105 -> 716.844 | L104: =H104+H105 -> 715.707 | M104: =K104-L104 -> 1.137 | N104: =L104/K104 -> 0.99841388
C105: 39356 | D105: 39447 | E105: 35.806 | F105: =13.921-128.247 -> -114.326 | G105: =E105+F105+I104 -> 1.137 | I105: =G105-H105 -> 1.137 | J105: =H105/G105 -> 0
B106: Arica Seafood Producer S.A | C106: 39083 | D106: 39355 | E106: 2.476 | G106: =E106+F106 -> 2.476 | I106: =G106-H106 -> 2.476 | J106: =H106/G106 -> 0 | K106: =E106+E107+F106+F107 -> 2.606 | L106: =H106+H107 -> 0 | M106: =K106-L106 -> 2.606 | N106: =L106/K106 -> 0
C107: 39356 | D107: 39447 | E107: 0.13 | G107: =E107+F107+I106 -> 2.606 | I107: =G107-H107 -> 2.606 | J107: =H107/G107 -> 0
B108: Bahia Caldera S.A. Pesq. | C108: 39083 | D108: 39355 | E108: 36.079 | G108: =E108+F108 -> 36.079 | I108: =G108-H108 -> 36.079 | J108: =H108/G108 -> 0 | K108: =E108+E109+F108+F109 -> 37.976 | L108: =H108+H109 -> 0 | M108: =K108-L108 -> 37.976 | N108: =L108/K108 -> 0
C109: 39356 | D109: 39447 | E109: 1.897 | G109: =E109+F109+I108 -> 37.976 | I109: =G109-H109 -> 37.976 | J109: =H109/G109 -> 0
B110: Blumar S.A. | C110: 39083 | D110: 39355 | E110: 2185.5 | F110: =-1100 -> -1100 | G110: =E110+F110 -> 1085.5 | H110: 1066.718 | I110: =G110-H110 -> 18.782 | J110: =H110/G110 -> 0.98269737 | K110: =E110+E111+F110+F111 -> 1200.427 | L110: =H110+H111 -> 1066.718 | M110: =K110-L110 -> 133.709 | N110: =L110/K110 -> 0.88861547
...

Sheet Crustaceos  LTP
B1: 2014. CUOTAS LTP Y SU CONSUMO DE RECURSOS CRUSTÁCEOS al 31 de diciembre 2014 | AV1: * registra la sumatoria de los traspasos en todas las regiones
AV2: ** registra los traspasos realizados en toda la unidad de pesqueria. Certificados que no identifican la región.
C4: Periodo | E4: Cuota II Región (t) | H4: Operación II región | K4: Cuota III Región (t) | N4: Operación III Región | Q4: Cuota IV Región (t) | T4: Operación IV Región | W4: Cuota V Región (t) | Z4: Operación V Región | AC4: Cuota VI Región (t) | AF4: Operación VI Región | AI4: Cuota VII Región (t) | AL4: Operación VII Región | AO4: Cuota VIII Región (t) | AR4: Operación VIII Región | AU4: Cuota y Operación Camaron Nailon II-VIII | AY4: Operación II-VIII | BB4: Global II-VIII
A5: Unidad de pesquería | B5: Armador | C5: Inicial | D5: Final | E5: Cuota Asignada | F5: Traspaso, Cesion, Arriendo, etc) | G5: Cuota Efectiva | H5: Desembarque (t) | I5: Saldo (t) | J5: Cuota Total | K5: Cuota Asignada | L5: Traspaso, Cesion, Arriendo, etc) | M5: Cuota Efectiva | N5: Desembarque (t) | O5: Saldo (t) | P5: Cuota Total | Q5: Cuota Asignada | R5: Traspaso, Cesion, Arriendo, etc) | S5: Cuota Efectiva | T5: Desembarque (t) | U5: Saldo (t) | V5: Cuota Total | W5: Cuota Asignada | X5: Traspaso, Cesion, Arriendo, etc) | Y5: Cuota Efectiva | Z5: Desembarque (t) | AA5: Saldo (t) | AB5: Cuota Total | AC5: Cuota Asignada | AD5: Traspaso, Cesion, Arriendo, etc) | AE5: Cuota Efectiva | AF5: Desembarque (t) | AG5: Saldo (t) | AH5: Cuota Total | AI5: Cuota Asignada | AJ5: Traspaso, Cesion, Arriendo, etc) | AK5: Cuota Efectiva | AL5: Desembarque (t) | AM5: Saldo (t) | AN5: Cuota Total | AO5: Cuota Asignada | AP5: Traspaso, Cesion, Arriendo, etc) | AQ5: Cuota Efectiva | AR5: Desembarque (t) | AS5: Saldo (t) | AT5: Cuota Total | AU5: Cuota Asignada II-VIII | AV5: * Traspaso, Cesion, Arriendo, etc) | AW5: **Traspaso, Cesion, Arriendo, etc) | AX5: Cuota Efectiva | AY5: Desembarque (t) II-VIII | AZ5: Saldo (t) | BA5: % consumido | BB5: Cuota Total | BC5: Desembarque (t) | BD5: Saldo (t) | BE5: % consumido
A6: Camarón nailon II-VIII | B6: Antarctic Seafood S.A. | C6: 41640 | D6: 41882 | E6: 0.699 | G6: =E6+F6 -> 0.699 | I6: =G6-H6 -> 0.699 | J6: =E6+E7+F6+F7 -> 1.048 | K6: 0.349 | L6: =4.216 -> 4.216 | M6: =K6+L6 -> 4.565 | O6: =M6-N6 -> 4.565 | P6: =K6+K7+L6+L7 -> 0.698 | Q6: 36.696 | R6: =6.817 -> 6.817 | S6: =Q6+R6 -> 43.513 | T6: 55.117 | U6: =S6-T6 -> -11.604 | V6: =Q6+Q7+R6+R7 -> 87.73216 | W6: 66.752 | Y6: =W6+X6 -> 66.752 | Z6: 75.722 | AA6: =Y6-Z6 -> -8.97 | AB6: =W6+W7+X6+X7 -> 121.7834 | AC6: 113.059 | AD6: =0.8 -> 0.8 | AE6: =AC6+AD6 -> 113.859 | AF6: 135.871 | AG6: =AE6-AF6 -> -22.012 | AH6: =AC6+AC7+AD6+AD7 -> 178.243 | AI6: 95.235 | AJ6: =19.978 -> 19.978 | AK6: =AI6+AJ6 -> 115.213 | AL6: 110.47 | AM6: =AK6-AL6 -> 4.743 | AN6: =AI6+AI7+AJ6+AJ7 -> 186.472 | AO6: 92.964 | AP6: =19.502 -> 19.502 | AQ6: =AO6+AP6 -> 112.466 | AR6: 115.094 | AS6: =AQ6-AR6 -> -2.628 | AT6: =AO6+AO7+AP6+AP7 -> 188.6594 | AU6: =E6+K6+Q6+W6+AC6+AI6+AO6 -> 405.754 | AV6: =F6+L6+R6+X6+AD6+AJ6+AP6 -> 51.313 | AW6: =13.444 -> 13.444 | AX6: =AU6+AV6+AW6 -> 470.511 | AY6: =H6+N6+T6+Z6+AF6+AL6+AR6 -> 492.274 | AZ6: =AX6-AY6 -> -21.763 | BA6: =AY6/AX6 -> 1.046254 | BB6: =AU6+AU7+AV6+AV7+AW6+AW7 -> 782.63596 | BC6: =AY6+AY7 -> 762.388 | BD6: =BB6-BC6 -> 20.24796 | BE6: =BC6/BB6 -> 0.97412851
C7: 41883 | D7: 42004 | E7: 0.349 | G7: =E7+F7+I6 -> 1.048 | I7: =G7-H7 -> 1.048 | K7: 0.349 | L7: =1.488-5.704 -> -4.216 | M7: =K7+L7+O6 -> 0.698 | O7: =M7-N7 -> 0.698 | Q7: 35.298 | R7: =6.417+2.50416 -> 8.92116 | S7: =Q7+R7+U6 -> 32.61516 | T7: 32.517 | U7: =S7-T7 -> 0.09816 | W7: 39.143 | X7: =11.68+4.2084 -> 15.8884 | Y7: =W7+X7+AA6 -> 46.0614 | Z7: 45.906 | AA7: =Y7-Z7 -> 0.1554 | AC7: 58.889 | AD7: =5.495 -> 5.495 | AE7: =AC7+AD7+AG6 -> 42.372 | AF7: 42.311 | AG7: =AE7-AF7 -> 0.061 | AI7: 51.375 | AJ7: =8.124+16.664-4.904 -> 19.884 | AK7: =AI7+AJ7+AM6 -> 76.002 | AL7: 75.989 | AM7: =AK7-AL7 -> 0.013 | AO7: 47.705 | AP7: =8.044+16.236+4.2084 -> 28.4884 | AQ7: =AO7+AP7+AS6 -> 73.5654 | AR7: 73.391 | AS7: =AQ7-AR7 -> 0.1744 | AU7: =E7+K7+Q7+W7+AC7+AI7+AO7 -> 233.108 | AV7: =F7+L7+R7+X7+AD7+AJ7+AP7 -> 74.46096 | AW7: =4.556 -> 4.556 | AX7: =AU7+AV7+AZ6+AW7 -> 290.36196 | AY7: =H7+N7+T7+Z7+AF7+AL7+AR7 -> 270.114 | AZ7: =AX7-AY7 -> 20.24796 | BA7: =AY7/AX7 -> 0.93026649
B8: Baycic Baycic Maria | C8: 41640 | D8: 41882 | E8: 0.267 | F8: =-0.267 -> -0.267 | G8: =E8+F8 -> 0 | I8: =G8-H8 -> 0 | J8: =E8+E9+F8+F9 -> 0 | K8: 0.133 | L8: =-0.133 -> -0.133 | M8: =K8+L8 -> 0 | O8: =M8-N8 -> 0 | P8: =K8+K9+L8+L9 -> 0 | Q8: 13.993 | R8: =-13.993 -> -13.993 | S8: =Q8+R8 -> 0 | U8: =S8-T8 -> 0 | V8: =Q8+Q9+R8+R9 -> 0 | W8: 25.454 | X8: =-25.454 -> -25.454 | Y8: =W8+X8 -> 0 | AA8: =Y8-Z8 -> 0 | AB8: =W8+W9+X8+X9 -> 0 | AC8: 43.112 | AD8: =-43.112 -> -43.112 | AE8: =AC8+AD8 -> 0 | AG8: =AE8-AF8 -> 0 | AH8: =AC8+AC9+AD8+AD9 -> 0 | AI8: 36.315 | AJ8: =-36.315 -> -36.315 | AK8: =AI8+AJ8 -> 0 | AM8: =AK8-AL8 -> 0 | AN8: =AI8+AI9+AJ8+AJ9 -> 0 | AO8: 35.449 | AP8: =-35.449 -> -35.449 | AQ8: =AO8+AP8 -> 0 | AS8: =AQ8-AR8 -> 0 | AT8: =AO8+AO9+AP8+AP9 -> 0 | AU8: =E8+K8+Q8+W8+AC8+AI8+AO8 -> 154.723 | AV8: =F8+L8+R8+X8+AD8+AJ8+AP8 -> -154.723 | AX8: =AU8+AV8+AW8 -> 0 | AY8: =H8+N8+T8+Z8+AF8+AL8+AR8 -> 0 | AZ8: =AX8-AY8 -> 0 | BA8: =AY8/AX8 -> #DIV/0! | BB8: =AU8+AU9+AV8+AV9+AW8+AW9 -> 0 | BC8: =AY8+AY9 -> 0 | BD8: =BB8-BC8 -> 0 | BE8: =BC8/BB8 -> #DIV/0!
C9: 41883 | D9: 42004 | E9: 0.133 | F9: =-0.133 -> -0.133 | G9: =E9+F9+I8 -> 0 | I9: =G9-H9 -> 0 | K9: 0.133 | L9: =-0.133 -> -0.133 | M9: =K9+L9+O8 -> 0 | O9: =M9-N9 -> 0 | Q9: 13.46 | R9: =-13.46 -> -13.46 | S9: =Q9+R9+U8 -> 0 | U9: =S9-T9 -> 0 | W9: 14.926 | X9: =-14.926 -> -14.926 | Y9: =W9+X9+AA8 -> 0 | AA9: =Y9-Z9 -> 0 | AC9: 22.455 | AD9: =-22.455 -> -22.455 | AE9: =AC9+AD9+AG8 -> 0 | AG9: =AE9-AF9 -> 0 | AI9: 19.59 | AJ9: =-19.59 -> -19.59 | AK9: =AI9+AJ9+AM8 -> 0 | AM9: =AK9-AL9 -> 0 | AO9: 18.191 | AP9: =-18.191 -> -18.191 | AQ9: =AO9+AP9+AS8 -> 0 | AS9: =AQ9-AR9 -> 0 | AU9: =E9+K9+Q9+W9+AC9+AI9+AO9 -> 88.888 | AV9: =F9+L9+R9+X9+AD9+AJ9+AP9 -> -88.888 | AX9: =AU9+AV9+AZ8+AW9 -> 0 | AY9: =H9+N9+T9+Z9+AF9+AL9+AR9 -> 0 | AZ9: =AX9-AY9 -> 0 | BA9: =AY9/AX9 -> #DIV/0!
B10: Blumar S.A. | C10: 41640 | D10: 41882 | E10: 0.086 | G10: =E10+F10 -> 0.086 | I10: =G10-H10 -> 0.086 | J10: =E10+E11+F10+F11 -> 0.129 | K10: 0.043 | M10: =K10+L10 -> 0.043 | O10: =M10-N10 -> 0.043 | P10: =K10+K11+L10+L11 -> 0.086 | Q10: 4.492 | S10: =Q10+R10 -> 4.492 | U10: =S10-T10 -> 4.492 | V10: =Q10+Q11+R10+R11 -> 2.396 | W10: 8.171 | Y10: =W10+X10 -> 8.171 | AA10: =Y10-Z10 -> 8.171 | AB10: =W10+W11+X10+X11 -> 1.283 | AC10: 13.84 | AE10: =AC10+AD10 -> 13.84 | AG10: =AE10-AF10 -> 13.84 | AH10: =AC10+AC11+AD10+AD11 -> 15.554 | AI10: 11.658 | AK10: =AI10+AJ10 -> 11.658 | AM10: =AK10-AL10 -> 11.658 | AN10: =AI10+AI11+AJ10+AJ11 -> 1.283 | AO10: 11.38 | AQ10: =AO10+AP10 -> 11.38 | AS10: =AQ10-AR10 -> 11.38 | AT10: =AO10+AO11+AP10+AP11 -> 0.984 | AU10: =E10+K10+Q10+W10+AC10+AI10+AO10 -> 49.67 | AV10: =F10+L10+R10+X10+AD10+AJ10+AP10 -> 0 | AW10: =-0.7652 -> -0.7652 | AX10: =AU10+AV10+AW10 -> 48.9048 | AY10: =H10+N10+T10+Z10+AF10+AL10+AR10 -> 0 | AZ10: =AX10-AY10 -> 48.9048 | BA10: =AY10/AX10 -> 0 | BB10: =AU10+AU11+AV10+AV11+AW10+AW11 -> 20.9498 | BC10: =AY10+AY11 -> 0 | BD10: =BB10-BC10 -> 20.9498 | BE10: =BC10/BB10 -> 0
C11: 41883 | D11: 42004 | E11: 0.043 | G11: =E11+F11+I10 -> 0.129 | I11: =G11-H11 -> 0.129 | K11: 0.043 | M11: =K11+L11+O10 -> 0.086 | O11: =M11-N11 -> 0.086 | Q11: 4.321 | R11: =-6.417 -> -6.417 | S11: =Q11+R11+U10 -> 2.396 | U11: =S11-T11 -> 2.396 | W11: 4.792 | X11: =-11.68 -> -11.68 | Y11: =W11+X11+AA10 -> 1.283 | AA11: =Y11-Z11 -> 1.283 | AC11: 7.209 | AD11: =-5.495 -> -5.495 | AE11: =AC11+AD11+AG10 -> 15.554 | AG11: =AE11-AF11 -> 15.554 | AI11: 6.289 | AJ11: =-16.664 -> -16.664 | AK11: =AI11+AJ11+AM10 -> 1.283 | AM11: =AK11-AL11 -> 1.283 | AO11: 5.84 | AP11: =-16.236 -> -16.236 | AQ11: =AO11+AP11+AS10 -> 0.984 | AS11: =AQ11-AR11 -> 0.984 | AU11: =E11+K11+Q11+W11+AC11+AI11+AO11 -> 28.537 | AV11: =F11+L11+R11+X11+AD11+AJ11+AP11 -> -56.492 | AX11: =AU11+AV11+AZ10+AW11 -> 20.9498 | AY11: =H11+N11+T11+Z11+AF11+AL11+AR11 -> 0 | AZ11: =AX11-AY11 -> 20.9498 | BA11: =AY11/AX11 -> 0
B12: Bracpesca S.A | C12: 41640 | D12: 41882 | E12: 0.686 | G12: =E12+F12 -> 0.686 | I12: =G12-H12 -> 0.686 | J12: =E12+E13+F12+F13 -> 1.029 | K12: 0.343 | M12: =K12+L12 -> 0.343 | O12: =M12-N12 -> 0.343 | P12: =K12+K13+L12+L13 -> 0.686 | Q12: 36.034 | S12: =Q12+R12 -> 36.034 | T12: 29.525 | U12: =S12-T12 -> 6.509 | V12: =Q12+Q13+R12+R13 -> 70.696 | W12: 65.548 | Y12: =W12+X12 -> 65.548 | Z12: 61.918 | AA12: =Y12-Z12 -> 3.63 | AB12: =W12+W13+X12+X13 -> 93.985 | AC12: 111.02 | AE12: =AC12+AD12 -> 111.02 | AF12: 105.275 | AG12: =AE12-AF12 -> 5.745 | AH12: =AC12+AC13+AD12+AD13 -> 168.847 | AI12: 93.518 | AK12: =AI12+AJ12 -> 93.518 | AL12: 119.225 | AM12: =AK12-AL12 -> -25.707 | AN12: =AI12+AI13+AJ12+AJ13 -> 153.966 | AO12: 91.287 | AQ12: =AO12+AP12 -> 91.287 | AR12: 52.106 | AS12: =AQ12-AR12 -> 39.181 | AT12: =AO12+AO13+AP12+AP13 -> 138.132 | AU12: =E12+K12+Q12+W12+AC12+AI12+AO12 -> 398.436 | AV12: =F12+L12+R12+X12+AD12+AJ12+AP12 -> 0 | AX12: =AU12+AV12+AW12 -> 398.436 | AY12: =H12+N12+T12+Z12+AF12+AL12+AR12 -> 368.049 | AZ12: =AX12-AY12 -> 30.387 | BA12: =AY12/AX12 -> 0.9237343 | BB12: =AU12+AU13+AV12+AV13+AW12+AW13 -> 627.341 | BC12: =AY12+AY13 -> 622.842 | BD12: =BB12-BC12 -> 4.499 | BE12: =BC12/BB12 -> 0.99282846
C13: 41883 | D13: 42004 | E13: 0.343 | G13: =E13+F13+I12 -> 1.029 | I13: =G13-H13 -> 1.029 | K13: 0.343 | M13: =K13+L13+O12 -> 0.686 | O13: =M13-N13 -> 0.686 | Q13: 34.662 | S13: =Q13+R13+U12 -> 41.171 | T13: 39.033 | U13: =S13-T13 -> 2.138 | W13: 38.437 | X13: =-10 -> -10 | Y13: =W13+X13+AA12 -> 32.067 | Z13: 31.877 | AA13: =Y13-Z13 -> 0.19 | AC13: 57.827 | AE13: =AC13+AD13+AG12 -> 63.572 | AF13: 63.183 | AG13: =AE13-AF13 -> 0.389 | AI13: 50.448 | AJ13: =10 -> 10 | AK13: =AI13+AJ13+AM12 -> 34.741 | AL13: 34.692 | AM13: =AK13-AL13 -> 0.049 | AO13: 46.845 | AQ13: =AO13+AP13+AS12 -> 86.026 | AR13: 86.008 | AS13: =AQ13-AR13 -> 0.018 | AU13: =E13+K13+Q13+W13+AC13+AI13+AO13 -> 228.905 | AV13: =F13+L13+R13+X13+AD13+AJ13+AP13 -> 0 | AX13: =AU13+AV13+AZ12+AW13 -> 259.292 | AY13: =H13+N13+T13+Z13+AF13+AL13+AR13 -> 254.793 | AZ13: =AX13-AY13 -> 4.499 | BA13: =AY13/AX13 -> 0.98264891
B14: Camanchaca Pesca Sur S.A. | C14: 41640 | D14: 41882 | E14: 0.004 | G14: =E14+F14 -> 0.004 | I14: =G14-H14 -> 0.004 | J14: =E14+E15+F14+F15 -> 0.006 | K14: 0.002 | M14: =K14+L14 -> 0.002 | O14: =M14-N14 -> 0.002 | P14: =K14+K15+L14+L15 -> 0.004 | Q14: 0.187 | S14: =Q14+R14 -> 0.187 | U14: =S14-T14 -> 0.187 | V14: =Q14+Q15+R14+R15 -> 0.367 | W14: 0.34 | Y14: =W14+X14 -> 0.34 | AA14: =Y14-Z14 -> 0.34 | AB14: =W14+W15+X14+X15 -> 0.539 | AC14: 0.576 | AE14: =AC14+AD14 -> 0.576 | AG14: =AE14-AF14 -> 0.576 | AH14: =AC14+AC15+AD14+AD15 -> 0.876 | AI14: 0.486 | AK14: =AI14+AJ14 -> 0.486 | AM14: =AK14-AL14 -> 0.486 | AN14: =AI14+AI15+AJ14+AJ15 -> 0.748 | AO14: 0.474 | AQ14: =AO14+AP14 -> 0.474 | AS14: =AQ14-AR14 -> 0.474 | AT14: =AO14+AO15+AP14+AP15 -> 0.717 | AU14: =E14+K14+Q14+W14+AC14+AI14+AO14 -> 2.069 | AV14: =F14+L14+R14+X14+AD14+AJ14+AP14 -> 0 | AW14: =-0.06964-0.06964 -> -0.13928 | AX14: =AU14+AV14+AW14 -> 1.92972 | AY14: =H14+N14+T14+Z14+AF14+AL14+AR14 -> 0 | AZ14: =AX14-AY14 -> 1.92972 | BA14: =AY14/AX14 -> 0 | BB14: =AU14+AU15+AV14+AV15+AW14+AW15 -> 2.42132 | BC14: =AY14+AY15 -> 0.603 | BD14: =BB14-BC14 -> 1.81832 | BE14: =BC14/BB14 -> 0.24903771
C15: 41883 | D15: 42004 | E15: 0.002 | G15: =E15+F15+I14 -> 0.006 | I15: =G15-H15 -> 0.006 | K15: 0.002 | M15: =K15+L15+O14 -> 0.004 | O15: =M15-N15 -> 0.004 | Q15: 0.18 | S15: =Q15+R15+U14 -> 0.367 | U15: =S15-T15 -> 0.367 | W15: 0.199 | Y15: =W15+X15+AA14 -> 0.539 | AA15: =Y15-Z15 -> 0.539 | AC15: 0.3 | AE15: =AC15+AD15+AG14 -> 0.876 | AG15: =AE15-AF15 -> 0.876 | AI15: 0.262 | AK15: =AI15+AJ15+AM14 -> 0.748 | AL15: 0.486 | AM15: =AK15-AL15 -> 0.262 | AO15: 0.243 | AQ15: =AO15+AP15+AS14 -> 0.717 | AR15: 0.117 | AS15: =AQ15-AR15 -> 0.6 | AU15: =E15+K15+Q15+W15+AC15+AI15+AO15 -> 1.188 | AV15: =F15+L15+R15+X15+AD15+AJ15+AP15 -> 0 | AW15: =-0.6964 -> -0.6964 | AX15: =AU15+AV15+AZ14+AW15 -> 2.42132 | AY15: =H15+N15+T15+Z15+AF15+AL15+AR15 -> 0.603 | AZ15: =AX15-AY15 -> 1.81832 | BA15: =AY15/AX15 -> 0.24903771
B16: Antonio Cruz Cordova nakouzi E.I.R.L. | C16: 41640 | D16: 41882 | E16: 0.022 | G16: =E16+F16 -> 0.022 | I16: =G16-H16 -> 0.022 | J16: =E16+E17+F16+F17 -> 0.033 | K16: 0.011 | M16: =K16+L16 -> 0.011 | O16: =M16-N16 -> 0.011 | P16: =K16+K17+L16+L17 -> 0.022 | Q16: 1.159 | S16: =Q16+R16 -> 1.159 | U16: =S16-T16 -> 1.159 | V16: =Q16+Q17+R16+R17 -> 2.274 | W16: 2.109 | Y16: =W16+X16 -> 2.109 | AA16: =Y16-Z16 -> 2.109 | AB16: =W16+W17+X16+X17 -> 3.346 | AC16: 3.572 | AE16: =AC16+AD16 -> 3.572 | AG16: =AE16-AF16 -> 3.572 | AH16: =AC16+AC17+AD16+AD17 -> 5.433 | AI16: 3.009 | AK16: =AI16+AJ16 -> 3.009 | AM16: =AK16-AL16 -> 3.009 | AN16: =AI16+AI17+AJ16+AJ17 -> 4.632 | AO16: 2.937 | AQ16: =AO16+AP16 -> 2.937 | AS16: =AQ16-AR16 -> 2.937 | AT16: =AO16+AO17+AP16+AP17 -> 4.444 | AU16: =E16+K16+Q16+W16+AC16+AI16+AO16 -> 12.819 | AV16: =F16+L16+R16+X16+AD16+AJ16+AP16 -> 0 | AW16: =-13.444 -> -13.444 | AX16: =AU16+AV16+AW16 -> -0.625 | AY16: =H16+N16+T16+Z16+AF16+AL16+AR16 -> 0 | AZ16: =AX16-AY16 -> -0.625 | BA16: =AY16/AX16 -> 0 | BB16: =AU16+AU17+AV16+AV17+AW16+AW17 -> 2.184 | BC16: =AY16+AY17 -> 0 | BD16: =BB16-BC16 -> 2.184 | BE16: =BC16/BB16 -> 0
C17: 41883 | D17: 42004 | E17: 0.011 | G17: =E17+F17+I16 -> 0.033 | I17: =G17-H17 -> 0.033 | K17: 0.011 | M17: =K17+L17+O16 -> 0.022 | O17: =M17-N17 -> 0.022 | Q17: 1.115 | S17: =Q17+R17+U16 -> 2.274 | U17: =S17-T17 -> 2.274 | W17: 1.237 | Y17: =W17+X17+AA16 -> 3.346 | AA17: =Y17-Z17 -> 3.346 | AC17: 1.861 | AE17: =AC17+AD17+AG16 -> 5.433 | AG17: =AE17-AF17 -> 5.433 | AI17: 1.623 | AK17: =AI17+AJ17+AM16 -> 4.632 | AM17: =AK17-AL17 -> 4.632 | AO17: 1.507 | AQ17: =AO17+AP17+AS16 -> 4.444 | AS17: =AQ17-AR17 -> 4.444 | AU17: =E17+K17+Q17+W17+AC17+AI17+AO17 -> 7.365 | AV17: =F17+L17+R17+X17+AD17+AJ17+AP17 -> 0 | AW17: =-4.556 -> -4.556 | AX17: =AU17+AV17+AZ16+AW17 -> 2.184 | AY17: =H17+N17+T17+Z17+AF17+AL17+AR17 -> 0 | AZ17: =AX17-AY17 -> 2.184 | BA17: =AY17/AX17 -> 0
B18: Costa Brava Ltda. Pesq. | C18: 41640 | D18: 41882 | E18: 0.097 | F18: =-0.097 -> -0.097 | G18: =E18+F18 -> 0 | I18: =G18-H18 -> 0 | J18: =E18+E19+F18+F19 -> 0 | K18: 0.049 | L18: =-0.049 -> -0.049 | M18: =K18+L18 -> 0 | O18: =M18-N18 -> 0 | P18: =K18+K19+L18+L19 -> 0 | Q18: 5.116 | R18: =-5.116 -> -5.116 | S18: =Q18+R18 -> 0 | U18: =S18-T18 -> 0 | V18: =Q18+Q19+R18+R19 -> 0 | W18: 9.307 | X18: =-9.307 -> -9.307 | Y18: =W18+X18 -> 0 | AA18: =Y18-Z18 -> 0 | AB18: =W18+W19+X18+X19 -> 0 | AC18: 15.763 | AD18: =-15.763 -> -15.763 | AE18: =AC18+AD18 -> 0 | AG18: =AE18-AF18 -> 0 | AH18: =AC18+AC19+AD18+AD19 -> 0 | AI18: 13.278 | AJ18: =-13.278 -> -13.278 | AK18: =AI18+AJ18 -> 0 | AM18: =AK18-AL18 -> 0 | AN18: =AI18+AI19+AJ18+AJ19 -> 0 | AO18: 12.961 | AP18: =-12.961 -> -12.961 | AQ18: =AO18+AP18 -> 0 | AS18: =AQ18-AR18 -> 0 | AT18: =AO18+AO19+AP18+AP19 -> 0 | AU18: =E18+K18+Q18+W18+AC18+AI18+AO18 -> 56.571 | AV18: =F18+L18+R18+X18+AD18+AJ18+AP18 -> -56.571 | AX18: =AU18+AV18+AW18 -> 0 | AY18: =H18+N18+T18+Z18+AF18+AL18+AR18 -> 0 | AZ18: =AX18-AY18 -> 0 | BA18: =AY18/AX18 -> #DIV/0! | BB18: =AU18+AU19+AV18+AV19+AW18+AW19 -> 0 | BC18: =AY18+AY19 -> 0 | BD18: =BB18-BC18 -> 0 | BE18: =BC18/BB18 -> #DIV/0!
C19: 41883 | D19: 42004 | E19: 0.049 | F19: =-0.049 -> -0.049 | G19: =E19+F19+I18 -> 0 | I19: =G19-H19 -> 0 | K19: 0.049 | L19: =-0.049 -> -0.049 | M19: =K19+L19+O18 -> 0 | O19: =M19-N19 -> 0 | Q19: 4.921 | R19: =-4.921 -> -4.921 | S19: =Q19+R19+U18 -> 0 | U19: =S19-T19 -> 0 | W19: 5.457 | X19: =-5.457 -> -5.457 | Y19: =W19+X19+AA18 -> 0 | AA19: =Y19-Z19 -> 0 | AC19: 8.21 | AD19: =-8.21 -> -8.21 | AE19: =AC19+AD19+AG18 -> 0 | AG19: =AE19-AF19 -> 0 | AI19: 7.163 | AJ19: =-7.163 -> -7.163 | AK19: =AI19+AJ19+AM18 -> 0 | AM19: =AK19-AL19 -> 0 | AO19: 6.651 | AP19: =-6.651 -> -6.651 | AQ19: =AO19+AP19+AS18 -> 0 | AS19: =AQ19-AR19 -> 0 | AU19: =E19+K19+Q19+W19+AC19+AI19+AO19 -> 32.5 | AV19: =F19+L19+R19+X19+AD19+AJ19+AP19 -> -32.5 | AX19: =AU19+AV19+AZ18+AW19 -> 0 | AY19: =H19+N19+T19+Z19+AF19+AL19+AR19 -> 0 | AZ19: =AX19-AY19 -> 0 | BA19: =AY19/AX19 -> #DIV/0!
B20: Grimar S.A. Pesq. | C20: 41640 | D20: 41882 | E20: 0.013 | G20: =E20+F20 -> 0.013 | I20: =G20-H20 -> 0.013 | J20: =E20+E21+F20+F21 -> 0.02 | K20: 0.007 | M20: =K20+L20 -> 0.007 | O20: =M20-N20 -> 0.007 | P20: =K20+K21+L20+L21 -> 0.014 | Q20: 0.701 | S20: =Q20+R20 -> 0.701 | U20: =S20-T20 -> 0.701 | V20: =Q20+Q21+R20+R21 -> 1.376 | W20: 1.276 | Y20: =W20+X20 -> 1.276 | AA20: =Y20-Z20 -> 1.276 | AB20: =W20+W21+X20+X21 -> 2.024 | AC20: 2.161 | AE20: =AC20+AD20 -> 2.161 | AG20: =AE20-AF20 -> 2.161 | AH20: =AC20+AC21+AD20+AD21 -> 3.287 | AI20: 1.82 | AK20: =AI20+AJ20 -> 1.82 | AM20: =AK20-AL20 -> 1.82 | AN20: =AI20+AI21+AJ20+AJ21 -> 2.802 | AO20: 1.777 | AQ20: =AO20+AP20 -> 1.777 | AS20: =AQ20-AR20 -> 1.777 | AT20: =AO20+AO21+AP20+AP21 -> 2.689 | AU20: =E20+K20+Q20+W20+AC20+AI20+AO20 -> 7.755 | AV20: =F20+L20+R20+X20+AD20+AJ20+AP20 -> 0 | AX20: =AU20+AV20+AW20 -> 7.755 | AY20: =H20+N20+T20+Z20+AF20+AL20+AR20 -> 0 | AZ20: =AX20-AY20 -> 7.755 | BA20: =AY20/AX20 -> 0 | BB20: =AU20+AU21+AV20+AV21+AW20+AW21 -> 12.212 | BC20: =AY20+AY21 -> 0 | BD20: =BB20-BC20 -> 12.212 | BE20: =BC20/BB20 -> 0
C21: 41883 | D21: 42004 | E21: 0.007 | G21: =E21+F21+I20 -> 0.02 | I21: =G21-H21 -> 0.02 | K21: 0.007 | M21: =K21+L21+O20 -> 0.014 | O21: =M21-N21 -> 0.014 | Q21: 0.675 | S21: =Q21+R21+U20 -> 1.376 | U21: =S21-T21 -> 1.376 | W21: 0.748 | Y21: =W21+X21+AA20 -> 2.024 | AA21: =Y21-Z21 -> 2.024 | AC21: 1.126 | AE21: =AC21+AD21+AG20 -> 3.287 | AG21: =AE21-AF21 -> 3.287 | AI21: 0.982 | AK21: =AI21+AJ21+AM20 -> 2.802 | AM21: =AK21-AL21 -> 2.802 | AO21: 0.912 | AQ21: =AO21+AP21+AS20 -> 2.689 | AS21: =AQ21-AR21 -> 2.689 | AU21: =E21+K21+Q21+W21+AC21+AI21+AO21 -> 4.457 | AV21: =F21+L21+R21+X21+AD21+AJ21+AP21 -> 0 | AX21: =AU21+AV21+AZ20+AW21 -> 12.212 | AY21: =H21+N21+T21+Z21+AF21+AL21+AR21 -> 0 | AZ21: =AX21-AY21 -> 12.212 | BA21: =AY21/AX21 -> 0
B22: Isladamas S.A. Pesq. | C22: 41640 | D22: 41882 | E22: 0.617 | F22: =0.097+0.173 -> 0.27 | G22: =E22+F22 -> 0.887 | I22: =G22-H22 -> 0.887 | J22: =E22+E23+F22+F23 -> 1.331 | K22: 0.308 | L22: =0.049+0.087 -> 0.136 | M22: =K22+L22 -> 0.444 | O22: =M22-N22 -> 0.444 | P22: =K22+K23+L22+L23 -> 0.888 | Q22: 32.385 | R22: =5.116+9.119 -> 14.235 | S22: =Q22+R22 -> 46.62 | T22: 27.99 | U22: =S22-T22 -> 18.63 | V22: =Q22+Q23+R22+R23 -> 88.95984 | W22: 58.91 | X22: =9.307+16.588 -> 25.895 | Y22: =W22+X22 -> 84.805 | Z22: 81.978 | AA22: =Y22-Z22 -> 2.827 | AB22: =W22+W23+X22+X23 -> 130.3246 | AC22: 99.777 | AD22: =15.763+28.096 -> 43.859 | AE22: =AC22+AD22 -> 143.636 | AF22: 135.505 | AG22: =AE22-AF22 -> 8.131 | AH22: =AC22+AC23+AD22+AD23 -> 218.45 | AI22: 84.047 | AJ22: =13.278+23.667 -> 36.945 | AK22: =AI22+AJ22 -> 120.992 | AL22: 109.482 | AM22: =AK22-AL22 -> 11.51 | AN22: =AI22+AI23+AJ22+AJ23 -> 191.165 | AO22: 82.042 | AP22: =12.961+23.102 -> 36.063 | AQ22: =AO22+AP22 -> 118.105 | AR22: 88.767 | AS22: =AQ22-AR22 -> 29.338 | AT22: =AO22+AO23+AP22+AP23 -> 174.5036 | AU22: =E22+K22+Q22+W22+AC22+AI22+AO22 -> 358.086 | AV22: =F22+L22+R22+X22+AD22+AJ22+AP22 -> 157.403 | AW22: =-0.03478 -> -0.03478 | AX22: =AU22+AV22+AW22 -> 515.45422 | AY22: =H22+N22+T22+Z22+AF22+AL22+AR22 -> 443.722 | AZ22: =AX22-AY22 -> 71.73222 | BA22: =AY22/AX22 -> 0.86083688 | BB22: =AU22+AU23+AV22+AV23+AW22+AW23 -> 805.58726 | BC22: =AY22+AY23 -> 711.607 | BD22: =BB22-BC22 -> 93.98026 | BE22: =BC22/BB22 -> 0.88333944
C23: 41883 | D23: 42004 | E23: 0.308 | F23: =0.049+0.087 -> 0.136 | G23: =E23+F23+I22 -> 1.331 | I23: =G23-H23 -> 1.331 | K23: 0.308 | L23: =0.049+0.087 -> 0.136 | M23: =K23+L23+O22 -> 0.888 | O23: =M23-N23 -> 0.888 | Q23: 31.151 | R23: =4.921+8.772-2.50416 -> 11.18884 | S23: =Q23+R23+U22 -> 60.96984 | T23: 13.972 | U23: =S23-T23 -> 46.99784 | W23: 34.544 | X23: =5.457+9.727-4.2084 -> 10.9756 | Y23: =W23+X23+AA22 -> 48.3466 | Z23: 35.731 | AA23: =Y23-Z23 -> 12.6156 | AC23: 51.97 | AD23: =8.21+14.634 -> 22.844 | AE23: =AC23+AD23+AG22 -> 82.945 | AF23: 77.344 | AG23: =AE23-AF23 -> 5.601 | AI23: 45.339 | AJ23: =7.163+12.767+4.904 -> 24.834 | AK23: =AI23+AJ23+AM22 -> 81.683 | AL23: 81.769 | AM23: =AK23-AL23 -> -0.086 | AO23: 42.101 | AP23: =6.651+11.855-4.2084 -> 14.2976 | AQ23: =AO23+AP23+AS22 -> 85.7366 | AR23: 59.069 | AS23: =AQ23-AR23 -> 26.6676 | AU23: =E23+K23+Q23+W23+AC23+AI23+AO23 -> 205.721 | AV23: =F23+L23+R23+X23+AD23+AJ23+AP23 -> 84.41204 | AX23: =AU23+AV23+AZ22+AW23 -> 361.86526 | AY23: =H23+N23+T23+Z23+AF23+AL23+AR23 -> 267.885 | AZ23: =AX23-AY23 -> 93.98026 | BA23: =AY23/AX23 -> 0.74028936
B24: Landes S.A. Soc. Pesq. | C24: 41640 | D24: 41882 | E24: 0.007 | G24: =E24+F24 -> 0.007 | I24: =G24-H24 -> 0.007 | J24: =E24+E25+F24+F25 -> 0.011 | K24: 0.004 | M24: =K24+L24 -> 0.004 | O24: =M24-N24 -> 0.004 | P24: =K24+K25+L24+L25 -> 0.008 | Q24: 0.383 | S24: =Q24+R24 -> 0.383 | U24: =S24-T24 -> 0.383 | V24: =Q24+Q25+R24+R25 -> 0.751 | W24: 0.696 | Y24: =W24+X24 -> 0.696 | AA24: =Y24-Z24 -> 0.696 | AB24: =W24+W25+X24+X25 -> 1.104 | AC24: 1.18 | AE24: =AC24+AD24 -> 1.18 | AG24: =AE24-AF24 -> 1.18 | AH24: =AC24+AC25+AD24+AD25 -> 1.794 | AI24: 0.994 | AK24: =AI24+AJ24 -> 0.994 | AM24: =AK24-AL24 -> 0.994 | AN24: =AI24+AI25+AJ24+AJ25 -> 1.53 | AO24: 0.97 | AQ24: =AO24+AP24 -> 0.97 | AS24: =AQ24-AR24 -> 0.97 | AT24: =AO24+AO25+AP24+AP25 -> 1.468 | AU24: =E24+K24+Q24+W24+AC24+AI24+AO24 -> 4.234 | AV24: =F24+L24+R24+X24+AD24+AJ24+AP24 -> 0 | AX24: =AU24+AV24+AW24 -> 4.234 | AY24: =H24+N24+T24+Z24+AF24+AL24+AR24 -> 0 | AZ24: =AX24-AY24 -> 4.234 | BA24: =AY24/AX24 -> 0 | BB24: =AU24+AU25+AV24+AV25+AW24+AW25 -> 6.666 | BC24: =AY24+AY25 -> 0 | BD24: =BB24-BC24 -> 6.666 | BE24: =BC24/BB24 -> 0
C25: 41883 | D25: 42004 | E25: 0.004 | G25: =E25+F25+I24 -> 0.011 | I25: =G25-H25 -> 0.011 | K25: 0.004 | M25: =K25+L25+O24 -> 0.008 | O25: =M25-N25 -> 0.008 | Q25: 0.368 | S25: =Q25+R25+U24 -> 0.751 | U25: =S25-T25 -> 0.751 | W25: 0.408 | Y25: =W25+X25+AA24 -> 1.104 | AA25: =Y25-Z25 -> 1.104 | AC25: 0.614 | AE25: =AC25+AD25+AG24 -> 1.794 | AG25: =AE25-AF25 -> 1.794 | AI25: 0.536 | AK25: =AI25+AJ25+AM24 -> 1.53 | AM25: =AK25-AL25 -> 1.53 | AO25: 0.498 | AQ25: =AO25+AP25+AS24 -> 1.468 | AS25: =AQ25-AR25 -> 1.468 | AU25: =E25+K25+Q25+W25+AC25+AI25+AO25 -> 2.432 | AV25: =F25+L25+R25+X25+AD25+AJ25+AP25 -> 0 | AX25: =AU25+AV25+AZ24+AW25 -> 6.666 | AY25: =H25+N25+T25+Z25+AF25+AL25+AR25 -> 0 | AZ25: =AX25-AY25 -> 6.666 | BA25: =AY25/AX25 -> 0
B26: Morozin Baycic Maria Ana | C26: 41640 | D26: 41882 | E26: 0.153 | F26: =-0.153 -> -0.153 | G26: =E26+F26 -> 0 | I26: =G26-H26 -> 0 | J26: =E26+E27+F26+F27 -> 0 | K26: 0.076 | L26: =-0.076 -> -0.076 | M26: =K26+L26 -> 0 | O26: =M26-N26 -> 0 | P26: =K26+K27+L26+L27 -> 0 | Q26: 8.026 | R26: =-8.026 -> -8.026 | S26: =Q26+R26 -> 0 | U26: =S26-T26 -> 0 | V26: =Q26+Q27+R26+R27 -> 0 | W26: 14.599 | X26: =-14.599 -> -14.599 | Y26: =W26+X26 -> 0 | AA26: =Y26-Z26 -> 0 | AB26: =W26+W27+X26+X27 -> 0 | AC26: 24.727 | AD26: =-24.727 -> -24.727 | AE26: =AC26+AD26 -> 0 | AG26: =AE26-AF26 -> 0 | AH26: =AC26+AC27+AD26+AD27 -> 0 | AI26: 20.829 | AJ26: =-20.829 -> -20.829 | AK26: =AI26+AJ26 -> 0 | AM26: =AK26-AL26 -> 0 | AN26: =AI26+AI27+AJ26+AJ27 -> 0 | AO26: 20.332 | AP26: =-20.332 -> -20.332 | AQ26: =AO26+AP26 -> 0 | AS26: =AQ26-AR26 -> 0 | AT26: =AO26+AO27+AP26+AP27 -> 0 | AU26: =E26+K26+Q26+W26+AC26+AI26+AO26 -> 88.742 | AV26: =F26+L26+R26+X26+AD26+AJ26+AP26 -> -88.742 | AX26: =AU26+AV26+AW26 -> 0 | AY26: =H26+N26+T26+Z26+AF26+AL26+AR26 -> 0 | AZ26: =AX26-AY26 -> 0 | BA26: =AY26/AX26 -> #DIV/0! | BB26: =AU26+AU27+AV26+AV27+AW26+AW27 -> 0 | BC26: =AY26+AY27 -> 0 | BD26: =BB26-BC26 -> 0 | BE26: =BC26/BB26 -> #DIV/0!
C27: 41883 | D27: 42004 | E27: 0.076 | F27: =-0.076 -> -0.076 | G27: =E27+F27+I26 -> 0 | I27: =G27-H27 -> 0 | K27: 0.076 | L27: =-0.076 -> -0.076 | M27: =K27+L27+O26 -> 0 | O27: =M27-N27 -> 0 | Q27: 7.72 | R27: =-7.72 -> -7.72 | S27: =Q27+R27+U26 -> 0 | U27: =S27-T27 -> 0 | W27: 8.561 | X27: =-8.561 -> -8.561 | Y27: =W27+X27+AA26 -> 0 | AA27: =Y27-Z27 -> 0 | AC27: 12.88 | AD27: =-12.88 -> -12.88 | AE27: =AC27+AD27+AG26 -> 0 | AG27: =AE27-AF27 -> 0 | AI27: 11.236 | AJ27: =-11.236 -> -11.236 | AK27: =AI27+AJ27+AM26 -> 0 | AM27: =AK27-AL27 -> 0 | AO27: 10.434 | AP27: =-10.434 -> -10.434 | AQ27: =AO27+AP27+AS26 -> 0 | AS27: =AQ27-AR27 -> 0 | AU27: =E27+K27+Q27+W27+AC27+AI27+AO27 -> 50.983 | AV27: =F27+L27+R27+X27+AD27+AJ27+AP27 -> -50.983 | AX27: =AU27+AV27+AZ26+AW27 -> 0 | AY27: =H27+N27+T27+Z27+AF27+AL27+AR27 -> 0 | AZ27: =AX27-AY27 -> 0 | BA27: =AY27/AX27 -> #DIV/0!
B28: Morozin Yurecic Mario | C28: 41640 | D28: 41882 | E28: 0.345 | F28: =-0.345 -> -0.345 | G28: =E28+F28 -> 0 | I28: =G28-H28 -> 0 | J28: =E28+E29+F28+F29 -> 0 | K28: 0.172 | L28: =-0.172 -> -0.172 | M28: =K28+L28 -> 0 | O28: =M28-N28 -> 0 | P28: =K28+K29+L28+L29 -> 0 | Q28: 18.101 | R28: =-18.101 -> -18.101 | S28: =Q28+R28 -> 0 | U28: =S28-T28 -> 0 | V28: =Q28+Q29+R28+R29 -> 0 | W28: 32.927 | X28: =-32.927 -> -32.927 | Y28: =W28+X28 -> 0 | AA28: =Y28-Z28 -> 0 | AB28: =W28+W29+X28+X29 -> 0 | AC28: 55.769 | AD28: =-55.769 -> -55.769 | AE28: =AC28+AD28 -> 0 | AG28: =AE28-AF28 -> 0 | AH28: =AC28+AC29+AD28+AD29 -> 0 | AI28: 46.977 | AJ28: =-46.977 -> -46.977 | AK28: =AI28+AJ28 -> 0 | AM28: =AK28-AL28 -> 0 | AN28: =AI28+AI29+AJ28+AJ29 -> 0 | AO28: 45.856 | AP28: =-45.856 -> -45.856 | AQ28: =AO28+AP28 -> 0 | AS28: =AQ28-AR28 -> 0 | AT28: =AO28+AO29+AP28+AP29 -> 0 | AU28: =E28+K28+Q28+W28+AC28+AI28+AO28 -> 200.147 | AV28: =F28+L28+R28+X28+AD28+AJ28+AP28 -> -200.147 | AX28: =AU28+AV28+AW28 -> 0 | AY28: =H28+N28+T28+Z28+AF28+AL28+AR28 -> 0 | AZ28: =AX28-AY28 -> 0 | BA28: =AY28/AX28 -> #DIV/0! | BB28: =AU28+AU29+AV28+AV29+AW28+AW29 -> 0 | BC28: =AY28+AY29 -> 0 | BD28: =BB28-BC28 -> 0 | BE28: =BC28/BB28 -> #DIV/0!
C29: 41883 | D29: 42004 | E29: 0.172 | F29: =-0.172 -> -0.172 | G29: =E29+F29+I28 -> 0 | I29: =G29-H29 -> 0 | K29: 0.172 | L29: =-0.172 -> -0.172 | M29: =K29+L29+O28 -> 0 | O29: =M29-N29 -> 0 | Q29: 17.412 | R29: =-17.412 -> -17.412 | S29: =Q29+R29+U28 -> 0 | U29: =S29-T29 -> 0 | W29: 19.308 | X29: =-19.308 -> -19.308 | Y29: =W29+X29+AA28 -> 0 | AA29: =Y29-Z29 -> 0 | AC29: 29.048 | AD29: =-29.048 -> -29.048 | AE29: =AC29+AD29+AG28 -> 0 | AG29: =AE29-AF29 -> 0 | AI29: 25.342 | AJ29: =-25.342 -> -25.342 | AK29: =AI29+AJ29+AM28 -> 0 | AM29: =AK29-AL29 -> 0 | AO29: 23.532 | AP29: =-23.532 -> -23.532 | AQ29: =AO29+AP29+AS28 -> 0 | AS29: =AQ29-AR29 -> 0 | AU29: =E29+K29+Q29+W29+AC29+AI29+AO29 -> 114.986 | AV29: =F29+L29+R29+X29+AD29+AJ29+AP29 -> -114.986 | AX29: =AU29+AV29+AZ28+AW29 -> 0 | AY29: =H29+N29+T29+Z29+AF29+AL29+AR29 -> 0 | AZ29: =AX29-AY29 -> 0 | BA29: =AY29/AX29 -> #DIV/0!
B30: Quintero Ltda. Soc. Pesq. | C30: 41640 | D30: 41882 | E30: 0.083 | F30: =-0.083 -> -0.083 | G30: =E30+F30 -> 0 | I30: =G30-H30 -> 0 | J30: =E30+E31+F30+F31 -> 0 | K30: 0.041 | L30: =-0.041 -> -0.041 | M30: =K30+L30 -> 0 | O30: =M30-N30 -> 0 | P30: =K30+K31+L30+L31 -> 0 | Q30: 4.333 | R30: =-4.333 -> -4.333 | S30: =Q30+R30 -> 0 | U30: =S30-T30 -> 0 | V30: =Q30+Q31+R30+R31 -> 0 | W30: 7.883 | X30: =-7.883 -> -7.883 | Y30: =W30+X30 -> 0 | AA30: =Y30-Z30 -> 0 | AB30: =W30+W31+X30+X31 -> 0 | AC30: 13.351 | AD30: =-13.351 -> -13.351 | AE30: =AC30+AD30 -> 0 | AG30: =AE30-AF30 -> 0 | AH30: =AC30+AC31+AD30+AD31 -> 0 | AI30: 11.246 | AJ30: =-11.246 -> -11.246 | AK30: =AI30+AJ30 -> 0 | AM30: =AK30-AL30 -> 0 | AN30: =AI30+AI31+AJ30+AJ31 -> 0 | AO30: 10.978 | AP30: =-10.978 -> -10.978 | AQ30: =AO30+AP30 -> 0 | AS30: =AQ30-AR30 -> 0 | AT30: =AO30+AO31+AP30+AP31 -> 0 | AU30: =E30+K30+Q30+W30+AC30+AI30+AO30 -> 47.915 | AV30: =F30+L30+R30+X30+AD30+AJ30+AP30 -> -47.915 | AX30: =AU30+AV30+AW30 -> 0 | AY30: =H30+N30+T30+Z30+AF30+AL30+AR30 -> 0 | AZ30: =AX30-AY30 -> 0 | BA30: =AY30/AX30 -> #DIV/0! | BB30: =AU30+AU31+AV30+AV31+AW30+AW31 -> 0 | BC30: =AY30+AY31 -> 0 | BD30: =BB30-BC30 -> 0 | BE30: =BC30/BB30 -> #DIV/0!
C31: 41883 | D31: 42004 | E31: 0.041 | F31: =-0.041 -> -0.041 | G31: =E31+F31+I30 -> 0 | I31: =G31-H31 -> 0 | K31: 0.041 | L31: =-0.041 -> -0.041 | M31: =K31+L31+O30 -> 0 | O31: =M31-N31 -> 0 | Q31: 4.168 | R31: =-4.168 -> -4.168 | S31: =Q31+R31+U30 -> 0 | U31: =S31-T31 -> 0 | W31: 4.622 | X31: =-4.622 -> -4.622 | Y31: =W31+X31+AA30 -> 0 | AA31: =Y31-Z31 -> 0 | AC31: 6.954 | AD31: =-6.954 -> -6.954 | AE31: =AC31+AD31+AG30 -> 0 | AG31: =AE31-AF31 -> 0 | AI31: 6.067 | AJ31: =-6.067 -> -6.067 | AK31: =AI31+AJ31+AM30 -> 0 | AM31: =AK31-AL31 -> 0 | AO31: 5.634 | AP31: =-5.634 -> -5.634 | AQ31: =AO31+AP31+AS30 -> 0 | AS31: =AQ31-AR31 -> 0 | AU31: =E31+K31+Q31+W31+AC31+AI31+AO31 -> 27.527 | AV31: =F31+L31+R31+X31+AD31+AJ31+AP31 -> -27.527 | AX31: =AU31+AV31+AZ30+AW31 -> 0 | AY31: =H31+N31+T31+Z31+AF31+AL31+AR31 -> 0 | AZ31: =AX31-AY31 -> 0 | BA31: =AY31/AX31 -> #DIV/0!
B32: Quintero S.A., Pesquera | C32: 41640 | D32: 41882 | E32: 0.601 | F32: =0.267+0.153+0.345+0.083 -> 0.848 | G32: =E32+F32 -> 1.449 | I32: =G32-H32 -> 1.449 | J32: =E32+E33+F32+F33 -> 2.172 | K32: 0.301 | L32: =0.133+0.076+0.172+0.041 -> 0.422 | M32: =K32+L32 -> 0.723 | O32: =M32-N32 -> 0.723 | P32: =K32+K33+L32+L33 -> 1.986 | Q32: 31.575 | R32: =13.993+8.026+18.101+4.333 -> 44.453 | S32: =Q32+R32 -> 76.028 | T32: 74.98 | U32: =S32-T32 -> 1.048 | V32: =Q32+Q33+R32+R33 -> 149.16 | W32: 57.436 | X32: =25.454+14.599+32.927+7.883-17.529 -> 63.334 | Y32: =W32+X32 -> 120.77 | Z32: 132.99 | AA32: =Y32-Z32 -> -12.22 | AB32: =W32+W33+X32+X33 -> 211.867 | AC32: 97.28 | AD32: =43.112+24.727+55.769+13.351+7.529 -> 144.488 | AE32: =AC32+AD32 -> 241.768 | AF32: 233.312 | AG32: =AE32-AF32 -> 8.456 | AH32: =AC32+AC33+AD32+AD33 -> 373.775 | AI32: 81.994 | AJ32: =36.315+20.829+46.977+11.246 -> 115.367 | AK32: =AI32+AJ32 -> 197.361 | AL32: 196.628 | AM32: =AK32-AL32 -> 0.733 | AN32: =AI32+AI33+AJ32+AJ33 -> 293.8 | AO32: 79.989 | AP32: =35.449+20.332+45.856+10.978 -> 112.615 | AQ32: =AO32+AP32 -> 192.604 | AR32: 190.931 | AS32: =AQ32-AR32 -> 1.673 | AT32: =AO32+AO33+AP32+AP33 -> 291.442 | AU32: =E32+K32+Q32+W32+AC32+AI32+AO32 -> 349.176 | AV32: =F32+L32+R32+X32+AD32+AJ32+AP32 -> 481.527 | AW32: =-0.0348 -> -0.0348 | AX32: =AU32+AV32+AW32 -> 830.6682 | AY32: =H32+N32+T32+Z32+AF32+AL32+AR32 -> 828.841 | AZ32: =AX32-AY32 -> 1.8272 | BA32: =AY32/AX32 -> 0.99780033 | BB32: =AU32+AU33+AV32+AV33+AW32+AW33 -> 1324.1672 | BC32: =AY32+AY33 -> 1309.204 | BD32: =BB32-BC32 -> 14.9632 | BE32: =BC32/BB32 -> 0.98869992
C33: 41883 | D33: 42004 | E33: 0.301 | F33: =0.133+0.076+0.172+0.041 -> 0.422 | G33: =E33+F33+I32 -> 2.172 | I33: =G33-H33 -> 2.172 | K33: 0.301 | L33: =0.133+0.076+0.712+0.041 -> 0.962 | M33: =K33+L33+O32 -> 1.986 | O33: =M33-N33 -> 1.986 | Q33: 30.372 | R33: =13.46+7.72+17.412+4.168 -> 42.76 | S33: =Q33+R33+U32 -> 74.18 | T33: 72.669 | U33: =S33-T33 -> 1.511 | W33: 33.68 | X33: =14.926+8.561+19.308+4.622+10 -> 57.417 | Y33: =W33+X33+AA32 -> 78.877 | Z33: 78.839 | AA33: =Y33-Z33 -> 0.038 | AC33: 50.67 | AD33: =22.455+12.88+29.048+6.954+10 -> 81.337 | AE33: =AC33+AD33+AG32 -> 140.463 | AF33: 137.606 | AG33: =AE33-AF33 -> 2.857 | AI33: 44.204 | AJ33: =19.59+11.236+25.342+6.067-10 -> 52.235 | AK33: =AI33+AJ33+AM32 -> 97.172 | AL33: 95.687 | AM33: =AK33-AL33 -> 1.485 | AO33: 41.047 | AP33: =18.191+10.434+23.532+5.634 -> 57.791 | AQ33: =AO33+AP33+AS32 -> 100.511 | AR33: 95.562 | AS33: =AQ33-AR33 -> 4.949 | AU33: =E33+K33+Q33+W33+AC33+AI33+AO33 -> 200.575 | AV33: =F33+L33+R33+X33+AD33+AJ33+AP33 -> 292.924 | AX33: =AU33+AV33+AZ32+AW33 -> 495.3262 | AY33: =H33+N33+T33+Z33+AF33+AL33+AR33 -> 480.363 | AZ33: =AX33-AY33 -> 14.9632 | BA33: =AY33/AX33 -> 0.96979122
B34: Rubio y Mauad Ltda. | C34: 41640 | D34: 41882 | E34: 0.147 | G34: =E34+F34 -> 0.147 | I34: =G34-H34 -> 0.147 | J34: =E34+E35+F34+F35 -> 0.22 | K34: 0.073 | L34: =-4.216 -> -4.216 | M34: =K34+L34 -> -4.143 | O34: =M34-N34 -> -4.143 | P34: =K34+K35+L34+L35 -> 0.146 | Q34: 7.698 | R34: =-6.817 -> -6.817 | S34: =Q34+R34 -> 0.881 | T34: 3.665 | U34: =S34-T34 -> -2.784 | V34: =Q34+Q35+R34+R35 -> 38.286 | W34: 14.003 | X34: =17.529 -> 17.529 | Y34: =W34+X34 -> 31.532 | Z34: 25.802 | AA34: =Y34-Z34 -> 5.73 | AB34: =W34+W35+X34+X35 -> 39.743 | AC34: 23.717 | AD34: =-0.8-7.529 -> -8.329 | AE34: =AC34+AD34 -> 15.388 | AF34: 14.889 | AG34: =AE34-AF34 -> 0.499 | AH34: =AC34+AC35+AD34+AD35 -> 17.741 | AI34: 19.978 | AJ34: =-19.978 -> -19.978 | AK34: =AI34+AJ34 -> 0 | AM34: =AK34-AL34 -> 0 | AN34: =AI34+AI35+AJ34+AJ35 -> 2.653 | AO34: 19.501 | AP34: =-19.502 -> -19.502 | AQ34: =AO34+AP34 -> -0.001 | AS34: =AQ34-AR34 -> -0.001 | AT34: =AO34+AO35+AP34+AP35 -> 1.962 | AU34: =E34+K34+Q34+W34+AC34+AI34+AO34 -> 85.117 | AV34: =F34+L34+R34+X34+AD34+AJ34+AP34 -> -41.313 | AX34: =AU34+AV34+AW34 -> 43.804 | AY34: =H34+N34+T34+Z34+AF34+AL34+AR34 -> 44.356 | AZ34: =AX34-AY34 -> -0.552 | BA34: =AY34/AX34 -> 1.0126016 | BB34: =AU34+AU35+AV34+AV35+AW34+AW35 -> 100.751 | BC34: =AY34+AY35 -> 50.579 | BD34: =BB34-BC34 -> 50.172 | BE34: =BC34/BB34 -> 0.50201983
C35: 41883 | D35: 42004 | E35: 0.073 | G35: =E35+F35+I34 -> 0.22 | I35: =G35-H35 -> 0.22 | K35: 0.073 | L35: =-1.488+5.704 -> 4.216 | M35: =K35+L35+O34 -> 0.146 | O35: =M35-N35 -> 0.146 | Q35: 7.405 | R35: =30 -> 30 | S35: =Q35+R35+U34 -> 34.621 | T35: 6.223 | U35: =S35-T35 -> 28.398 | W35: 8.211 | Y35: =W35+X35+AA34 -> 13.941 | AA35: =Y35-Z35 -> 13.941 | AC35: 12.353 | AD35: =-10 -> -10 | AE35: =AC35+AD35+AG34 -> 2.852 | AG35: =AE35-AF35 -> 2.852 | AI35: 10.777 | AJ35: =-8.124 -> -8.124 | AK35: =AI35+AJ35+AM34 -> 2.653 | AM35: =AK35-AL35 -> 2.653 | AO35: 10.007 | AP35: =-8.044 -> -8.044 | AQ35: =AO35+AP35+AS34 -> 1.962 | AS35: =AQ35-AR35 -> 1.962 | AU35: =E35+K35+Q35+W35+AC35+AI35+AO35 -> 48.899 | AV35: =F35+L35+R35+X35+AD35+AJ35+AP35 -> 8.048 | AX35: =AU35+AV35+AZ34+AW35 -> 56.395 | AY35: =H35+N35+T35+Z35+AF35+AL35+AR35 -> 6.223 | AZ35: =AX35-AY35 -> 50.172 | BA35: =AY35/AX35 -> 0.11034666
B36: Sunrise S.A. Pesq. | C36: 41640 | D36: 41882 | E36: 0.174 | F36: =-0.173 -> -0.173 | G36: =E36+F36 -> 0.001 | I36: =G36-H36 -> 0.001 | J36: =E36+E37+F36+F37 -> 0.001 | K36: 0.087 | L36: =-0.087 -> -0.087 | M36: =K36+L36 -> 0 | O36: =M36-N36 -> 0 | P36: =K36+K37+L36+L37 -> 0 | Q36: 9.119 | R36: =-9.119 -> -9.119 | S36: =Q36+R36 -> 0 | U36: =S36-T36 -> 0 | V36: =Q36+Q37+R36+R37 -> 0 | W36: 16.588 | X36: =-16.588 -> -16.588 | Y36: =W36+X36 -> 0 | AA36: =Y36-Z36 -> 0 | AB36: =W36+W37+X36+X37 -> 0 | AC36: 28.096 | AD36: =-28.096 -> -28.096 | AE36: =AC36+AD36 -> 0 | AG36: =AE36-AF36 -> 0 | AH36: =AC36+AC37+AD36+AD37 -> 0 | AI36: 23.667 | AJ36: =-23.667 -> -23.667 | AK36: =AI36+AJ36 -> 0 | AM36: =AK36-AL36 -> 0 | AN36: =AI36+AI37+AJ36+AJ37 -> 0 | AO36: 23.102 | AP36: =-23.102 -> -23.102 | AQ36: =AO36+AP36 -> 0 | AS36: =AQ36-AR36 -> 0 | AT36: =AO36+AO37+AP36+AP37 -> 0 | AU36: =E36+K36+Q36+W36+AC36+AI36+AO36 -> 100.833 | AV36: =F36+L36+R36+X36+AD36+AJ36+AP36 -> -100.832 | AX36: =AU36+AV36+AW36 -> 0.001 | AY36: =H36+N36+T36+Z36+AF36+AL36+AR36 -> 0 | AZ36: =AX36-AY36 -> 0.001 | BA36: =AY36/AX36 -> 0 | BB36: =AU36+AU37+AV36+AV37+AW36+AW37 -> 0.001 | BC36: =AY36+AY37 -> 0.031 | BD36: =BB36-BC36 -> -0.03 | BE36: =BC36/BB36 -> 31
C37: 41883 | D37: 42004 | E37: 0.087 | F37: =-0.087 -> -0.087 | G37: =E37+F37+I36 -> 0.001 | I37: =G37-H37 -> 0.001 | K37: 0.087 | L37: =-0.087 -> -0.087 | M37: =K37+L37+O36 -> 0 | O37: =M37-N37 -> 0 | Q37: 8.772 | R37: =-8.772 -> -8.772 | S37: =Q37+R37+U36 -> 0 | U37: =S37-T37 -> 0 | W37: 9.727 | X37: =-9.727 -> -9.727 | Y37: =W37+X37+AA36 -> 0 | AA37: =Y37-Z37 -> 0 | AC37: 14.634 | AD37: =-14.634 -> -14.634 | AE37: =AC37+AD37+AG36 -> 0 | AG37: =AE37-AF37 -> 0 | AI37: 12.767 | AJ37: =-12.767 -> -12.767 | AK37: =AI37+AJ37+AM36 -> 0 | AM37: =AK37-AL37 -> 0 | AO37: 11.855 | AP37: =-11.855 -> -11.855 | AQ37: =AO37+AP37+AS36 -> 0 | AR37: 0.031 | AS37: =AQ37-AR37 -> -0.031 | AU37: =E37+K37+Q37+W37+AC37+AI37+AO37 -> 57.929 | AV37: =F37+L37+R37+X37+AD37+AJ37+AP37 -> -57.929 | AX37: =AU37+AV37+AZ36+AW37 -> 0.001 | AY37: =H37+N37+T37+Z37+AF37+AL37+AR37 -> 0.031 | AZ37: =AX37-AY37 -> -0.03 | BA37: =AY37/AX37 -> 31
B38: Congelados del Pacifico | C38: 41640 | D38: 41882 | E38: 0 | G38: =E38+F38 -> 0 | I38: =G38-H38 -> 0 | J38: =E38+E39+F38+F39 -> 0 | K38: 0 | M38: =K38+L38 -> 0 | O38: =M38-N38 -> 0 | P38: =K38+K39+L38+L39 -> 0 | Q38: 0 | S38: =Q38+R38 -> 0 | U38: =S38-T38 -> 0 | V38: =Q38+Q39+R38+R39 -> 0 | W38: 0 | Y38: =W38+X38 -> 0 | AA38: =Y38-Z38 -> 0 | AB38: =W38+W39+X38+X39 -> 0 | AC38: 0 | AE38: =AC38+AD38 -> 0 | AG38: =AE38-AF38 -> 0 | AH38: =AC38+AC39+AD38+AD39 -> 0 | AI38: 0 | AK38: =AI38+AJ38 -> 0 | AM38: =AK38-AL38 -> 0 | AN38: =AI38+AI39+AJ38+AJ39 -> 0 | AO38: 0 | AQ38: =AO38+AP38 -> 0 | AS38: =AQ38-AR38 -> 0 | AT38: =AO38+AO39+AP38+AP39 -> 0 | AU38: =E38+K38+Q38+W38+AC38+AI38+AO38 -> 0 | AV38: =F38+L38+R38+X38+AD38+AJ38+AP38 -> 0 | AW38: =0.7652 -> 0.7652 | AX38: =AU38+AV38+AW38 -> 0.7652 | AY38: =H38+N38+T38+Z38+AF38+AL38+AR38 -> 0 | AZ38: =AX38-AY38 -> 0.7652 | BA38: =AY38/AX38 -> 0 | BB38: =AU38+AU39+AV38+AV39+AW38+AW39 -> 0.7652 | BC38: =AY38+AY39 -> 0 | BD38: =BB38-BC38 -> 0.7652 | BE38: =BC38/BB38 -> 0
C39: 41883 | D39: 42004 | E39: 0 | G39: =E39+F39+I38 -> 0 | I39: =G39-H39 -> 0 | K39: 0 | M39: =K39+L39+O38 -> 0 | O39: =M39-N39 -> 0 | Q39: 0 | S39: =Q39+R39+U38 -> 0 | U39: =S39-T39 -> 0 | W39: 0 | Y39: =W39+X39+AA38 -> 0 | AA39: =Y39-Z39 -> 0 | AC39: 0 | AE39: =AC39+AD39+AG38 -> 0 | AG39: =AE39-AF39 -> 0 | AI39: 0 | AK39: =AI39+AJ39+AM38 -> 0 | AM39: =AK39-AL39 -> 0 | AO39: 0 | AQ39: =AO39+AP39+AS38 -> 0 | AS39: =AQ39-AR39 -> 0 | AU39: =E39+K39+Q39+W39+AC39+AI39+AO39 -> 0 | AV39: =F39+L39+R39+X39+AD39+AJ39+AP39 -> 0 | AX39: =AU39+AV39+AZ38+AW39 -> 0.7652 | AY39: =H39+N39+T39+Z39+AF39+AL39+AR39 -> 0 | AZ39: =AX39-AY39 -> 0.7652 | BA39: =AY39/AX39 -> 0
B40: Enfemar Ltda. Soc. Pesq. | C40: 41640 | D40: 41882 | E40: 0 | G40: =E40+F40 -> 0 | I40: =G40-H40 -> 0 | J40: =E40+E41+F40+F41 -> 0 | K40: 0 | M40: =K40+L40 -> 0 | O40: =M40-N40 -> 0 | P40: =K40+K41+L40+L41 -> 0 | Q40: 0 | S40: =Q40+R40 -> 0 | U40: =S40-T40 -> 0 | V40: =Q40+Q41+R40+R41 -> 0 | W40: 0 | Y40: =W40+X40 -> 0 | AA40: =Y40-Z40 -> 0 | AB40: =W40+W41+X40+X41 -> 0 | AC40: 0 | AE40: =AC40+AD40 -> 0 | AG40: =AE40-AF40 -> 0 | AH40: =AC40+AC41+AD40+AD41 -> 0 | AI40: 0 | AK40: =AI40+AJ40 -> 0 | AM40: =AK40-AL40 -> 0 | AN40: =AI40+AI41+AJ40+AJ41 -> 0 | AO40: 0 | AQ40: =AO40+AP40 -> 0 | AS40: =AQ40-AR40 -> 0 | AT40: =AO40+AO41+AP40+AP41 -> 0 | AU40: =E40+K40+Q40+W40+AC40+AI40+AO40 -> 0 | AV40: =F40+L40+R40+X40+AD40+AJ40+AP40 -> 0 | AW40: =0.0348 -> 0.0348 | AX40: =AU40+AV40+AW40 -> 0.0348 | AY40: =H40+N40+T40+Z40+AF40+AL40+AR40 -> 0 | AZ40: =AX40-AY40 -> 0.0348 | BA40: =AY40/AX40 -> 0 | BB40: =AU40+AU41+AV40+AV41+AW40+AW41 -> 0.0348 | BC40: =AY40+AY41 -> 0 | BD40: =BB40-BC40 -> 0.0348 | BE40: =BC40/BB40 -> 0
C41: 41883 | D41: 42004 | E41: 0 | G41: =E41+F41+I40 -> 0 | I41: =G41-H41 -> 0 | K41: 0 | M41: =K41+L41+O40 -> 0 | O41: =M41-N41 -> 0 | Q41: 0 | S41: =Q41+R41+U40 -> 0 | U41: =S41-T41 -> 0 | W41: 0 | Y41: =W41+X41+AA40 -> 0 | AA41: =Y41-Z41 -> 0 | AC41: 0 | AE41: =AC41+AD41+AG40 -> 0 | AG41: =AE41-AF41 -> 0 | AI41: 0 | AK41: =AI41+AJ41+AM40 -> 0 | AM41: =AK41-AL41 -> 0 | AO41: 0 | AQ41: =AO41+AP41+AS40 -> 0 | AS41: =AQ41-AR41 -> 0 | AU41: =E41+K41+Q41+W41+AC41+AI41+AO41 -> 0 | AV41: =F41+L41+R41+X41+AD41+AJ41+AP41 -> 0 | AX41: =AU41+AV41+AZ40+AW41 -> 0.0348 | AY41: =H41+N41+T41+Z41+AF41+AL41+AR41 -> 0 | AZ41: =AX41-AY41 -> 0.0348 | BA41: =AY41/AX41 -> 0
B42: Da venezia Retamales Antonio | C42: 41640 | D42: 41882 | E42: 0 | G42: =E42+F42 -> 0 | I42: =G42-H42 -> 0 | J42: =E42+E43+F42+F43 -> 0 | K42: 0 | M42: =K42+L42 -> 0 | O42: =M42-N42 -> 0 | P42: =K42+K43+L42+L43 -> 0 | Q42: 0 | S42: =Q42+R42 -> 0 | U42: =S42-T42 -> 0 | V42: =Q42+Q43+R42+R43 -> 0 | W42: 0 | Y42: =W42+X42 -> 0 | AA42: =Y42-Z42 -> 0 | AB42: =W42+W43+X42+X43 -> 0 | AC42: 0 | AE42: =AC42+AD42 -> 0 | AG42: =AE42-AF42 -> 0 | AH42: =AC42+AC43+AD42+AD43 -> 0 | AI42: 0 | AK42: =AI42+AJ42 -> 0 | AM42: =AK42-AL42 -> 0 | AN42: =AI42+AI43+AJ42+AJ43 -> 0 | AO42: 0 | AQ42: =AO42+AP42 -> 0 | AS42: =AQ42-AR42 -> 0 | AT42: =AO42+AO43+AP42+AP43 -> 0 | AU42: =E42+K42+Q42+W42+AC42+AI42+AO42 -> 0 | AV42: =F42+L42+R42+X42+AD42+AJ42+AP42 -> 0 | AW42: =0.03478 -> 0.03478 | AX42: =AU42+AV42+AW42 -> 0.03478 | AY42: =H42+N42+T42+Z42+AF42+AL42+AR42 -> 0 | AZ42: =AX42-AY42 -> 0.03478 | BA42: =AY42/AX42 -> 0 | BB42: =AU42+AU43+AV42+AV43+AW42+AW43 -> 0.03478 | BC42: =AY42+AY43 -> 0 | BD42: =BB42-BC42 -> 0.03478 | BE42: =BC42/BB42 -> 0
C43: 41883 | D43: 42004 | E43: 0 | G43: =E43+F43+I42 -> 0 | I43: =G43-H43 -> 0 | K43: 0 | M43: =K43+L43+O42 -> 0 | O43: =M43-N43 -> 0 | Q43: 0 | S43: =Q43+R43+U42 -> 0 | U43: =S43-T43 -> 0 | W43: 0 | Y43: =W43+X43+AA42 -> 0 | AA43: =Y43-Z43 -> 0 | AC43: 0 | AE43: =AC43+AD43+AG42 -> 0 | AG43: =AE43-AF43 -> 0 | AI43: 0 | AK43: =AI43+AJ43+AM42 -> 0 | AM43: =AK43-AL43 -> 0 | AO43: 0 | AQ43: =AO43+AP43+AS42 -> 0 | AS43: =AQ43-AR43 -> 0 | AU43: =E43+K43+Q43+W43+AC43+AI43+AO43 -> 0 | AV43: =F43+L43+R43+X43+AD43+AJ43+AP43 -> 0 | AX43: =AU43+AV43+AZ42+AW43 -> 0.03478 | AY43: =H43+N43+T43+Z43+AF43+AL43+AR43 -> 0 | AZ43: =AX43-AY43 -> 0.03478 | BA43: =AY43/AX43 -> 0
B44: Pesquera CMK Ltda. | C44: 41640 | D44: 41882 | E44: 0 | G44: =E44+F44 -> 0 | I44: =G44-H44 -> 0 | J44: =E44+E45+F44+F45 -> 0 | K44: 0 | M44: =K44+L44 -> 0 | O44: =M44-N44 -> 0 | P44: =K44+K45+L44+L45 -> 0 | Q44: 0 | S44: =Q44+R44 -> 0 | U44: =S44-T44 -> 0 | V44: =Q44+Q45+R44+R45 -> 0 | W44: 0 | Y44: =W44+X44 -> 0 | AA44: =Y44-Z44 -> 0 | AB44: =W44+W45+X44+X45 -> 0 | AC44: 0 | AE44: =AC44+AD44 -> 0 | AG44: =AE44-AF44 -> 0 | AH44: =AC44+AC45+AD44+AD45 -> 0 | AI44: 0 | AK44: =AI44+AJ44 -> 0 | AM44: =AK44-AL44 -> 0 | AN44: =AI44+AI45+AJ44+AJ45 -> 0 | AO44: 0 | AQ44: =AO44+AP44 -> 0 | AS44: =AQ44-AR44 -> 0 | AT44: =AO44+AO45+AP44+AP45 -> 0 | AU44: =E44+K44+Q44+W44+AC44+AI44+AO44 -> 0 | AV44: =F44+L44+R44+X44+AD44+AJ44+AP44 -> 0 | AW44: =0.06964 -> 0.06964 | AX44: =AU44+AV44+AW44 -> 0.06964 | AY44: =H44+N44+T44+Z44+AF44+AL44+AR44 -> 0 | AZ44: =AX44-AY44 -> 0.06964 | BA44: =AY44/AX44 -> 0 | BB44: =AU44+AU45+AV44+AV45+AW44+AW45 -> 0.06964 | BC44: =AY44+AY45 -> 0 | BD44: =BB44-BC44 -> 0.06964 | BE44: =BC44/BB44 -> 0
C45: 41883 | D45: 42004 | E45: 0 | G45: =E45+F45+I44 -> 0 | I45: =G45-H45 -> 0 | K45: 0 | M45: =K45+L45+O44 -> 0 | O45: =M45-N45 -> 0 | Q45: 0 | S45: =Q45+R45+U44 -> 0 | U45: =S45-T45 -> 0 | W45: 0 | Y45: =W45+X45+AA44 -> 0 | AA45: =Y45-Z45 -> 0 | AC45: 0 | AE45: =AC45+AD45+AG44 -> 0 | AG45: =AE45-AF45 -> 0 | AI45: 0 | AK45: =AI45+AJ45+AM44 -> 0 | AM45: =AK45-AL45 -> 0 | AO45: 0 | AQ45: =AO45+AP45+AS44 -> 0 | AS45: =AQ45-AR45 -> 0 | AU45: =E45+K45+Q45+W45+AC45+AI45+AO45 -> 0 | AV45: =F45+L45+R45+X45+AD45+AJ45+AP45 -> 0 | AX45: =AU45+AV45+AZ44+AW45 -> 0.06964 | AY45: =H45+N45+T45+Z45+AF45+AL45+AR45 -> 0 | AZ45: =AX45-AY45 -> 0.06964 | BA45: =AY45/AX45 -> 0
B46: Jorge Cofre Reyes | C46: 41640 | D46: 41882 | E46: 0 | G46: =E46+F46 -> 0 | I46: =G46-H46 -> 0 | J46: =E46+E47+F46+F47 -> 0 | K46: 0 | M46: =K46+L46 -> 0 | O46: =M46-N46 -> 0 | P46: =K46+K47+L46+L47 -> 0 | Q46: 0 | S46: =Q46+R46 -> 0 | U46: =S46-T46 -> 0 | V46: =Q46+Q47+R46+R47 -> 0 | W46: 0 | Y46: =W46+X46 -> 0 | AA46: =Y46-Z46 -> 0 | AB46: =W46+W47+X46+X47 -> 0 | AC46: 0 | AE46: =AC46+AD46 -> 0 | AG46: =AE46-AF46 -> 0 | AH46: =AC46+AC47+AD46+AD47 -> 0 | AI46: 0 | AK46: =AI46+AJ46 -> 0 | AM46: =AK46-AL46 -> 0 | AN46: =AI46+AI47+AJ46+AJ47 -> 0 | AO46: 0 | AQ46: =AO46+AP46 -> 0 | AS46: =AQ46-AR46 -> 0 | AT46: =AO46+AO47+AP46+AP47 -> 0 | AU46: =E46+K46+Q46+W46+AC46+AI46+AO46 -> 0 | AV46: =F46+L46+R46+X46+AD46+AJ46+AP46 -> 0 | AW46: =0.06964 -> 0.06964 | AX46: =AU46+AV46+AW46 -> 0.06964 | AY46: =H46+N46+T46+Z46+AF46+AL46+AR46 -> 0 | AZ46: =AX46-AY46 -> 0.06964 | BA46: =AY46/AX46 -> 0 | BB46: =AU46+AU47+AV46+AV47+AW46+AW47 -> 0.06964 | BC46: =AY46+AY47 -> 0 | BD46: =BB46-BC46 -> 0.06964 | BE46: =BC46/BB46 -> 0
C47: 41883 | D47: 42004 | E47: 0 | G47: =E47+F47+I46 -> 0 | I47: =G47-H47 -> 0 | K47: 0 | M47: =K47+L47+O46 -> 0 | O47: =M47-N47 -> 0 | Q47: 0 | S47: =Q47+R47+U46 -> 0 | U47: =S47-T47 -> 0 | W47: 0 | Y47: =W47+X47+AA46 -> 0 | AA47: =Y47-Z47 -> 0 | AC47: 0 | AE47: =AC47+AD47+AG46 -> 0 | AG47: =AE47-AF47 -> 0 | AI47: 0 | AK47: =AI47+AJ47+AM46 -> 0 | AM47: =AK47-AL47 -> 0 | AO47: 0 | AQ47: =AO47+AP47+AS46 -> 0 | AS47: =AQ47-AR47 -> 0 | AU47: =E47+K47+Q47+W47+AC47+AI47+AO47 -> 0 | AV47: =F47+L47+R47+X47+AD47+AJ47+AP47 -> 0 | AX47: =AU47+AV47+AZ46+AW47 -> 0.06964 | AY47: =H47+N47+T47+Z47+AF47+AL47+AR47 -> 0 | AZ47: =AX47-AY47 -> 0.06964 | BA47: =AY47/AX47 -> 0
B48: Genmar Ltda | C48: 41640 | D48: 41882 | E48: 0 | G48: =E48+F48 -> 0 | I48: =G48-H48 -> 0 | J48: =E48+E49+F48+F49 -> 0 | K48: 0 | M48: =K48+L48 -> 0 | O48: =M48-N48 -> 0 | P48: =K48+K49+L48+L49 -> 0 | Q48: 0 | S48: =Q48+R48 -> 0 | U48: =S48-T48 -> 0 | V48: =Q48+Q49+R48+R49 -> 0 | W48: 0 | Y48: =W48+X48 -> 0 | AA48: =Y48-Z48 -> 0 | AB48: =W48+W49+X48+X49 -> 0 | AC48: 0 | AE48: =AC48+AD48 -> 0 | AG48: =AE48-AF48 -> 0 | AH48: =AC48+AC49+AD48+AD49 -> 0 | AI48: 0 | AK48: =AI48+AJ48 -> 0 | AM48: =AK48-AL48 -> 0 | AN48: =AI48+AI49+AJ48+AJ49 -> 0 | AO48: 0 | AQ48: =AO48+AP48 -> 0 | AS48: =AQ48-AR48 -> 0 | AT48: =AO48+AO49+AP48+AP49 -> 0 | AU48: =E48+K48+Q48+W48+AC48+AI48+AO48 -> 0 | AV48: =F48+L48+R48+X48+AD48+AJ48+AP48 -> 0 | AW48: =0.06964 -> 0.06964 | AX48: =AU48+AV48+AW48 -> 0.06964 | AY48: =H48+N48+T48+Z48+AF48+AL48+AR48 -> 0 | AZ48: =AX48-AY48 -> 0.06964 | BA48: =AY48/AX48 -> 0 | BB48: =AU48+AU49+AV48+AV49+AW48+AW49 -> 0.06964 | BC48: =AY48+AY49 -> 0 | BD48: =BB48-BC48 -> 0.06964 | BE48: =BC48/BB48 -> 0
C49: 41883 | D49: 42004 | E49: 0 | G49: =E49+F49+I48 -> 0 | I49: =G49-H49 -> 0 | K49: 0 | M49: =K49+L49+O48 -> 0 | O49: =M49-N49 -> 0 | Q49: 0 | S49: =Q49+R49+U48 -> 0 | U49: =S49-T49 -> 0 | W49: 0 | Y49: =W49+X49+AA48 -> 0 | AA49: =Y49-Z49 -> 0 | AC49: 0 | AE49: =AC49+AD49+AG48 -> 0 | AG49: =AE49-AF49 -> 0 | AI49: 0 | AK49: =AI49+AJ49+AM48 -> 0 | AM49: =AK49-AL49 -> 0 | AO49: 0 | AQ49: =AO49+AP49+AS48 -> 0 | AS49: =AQ49-AR49 -> 0 | AU49: =E49+K49+Q49+W49+AC49+AI49+AO49 -> 0 | AV49: =F49+L49+R49+X49+AD49+AJ49+AP49 -> 0 | AX49: =AU49+AV49+AZ48+AW49 -> 0.06964 | AY49: =H49+N49+T49+Z49+AF49+AL49+AR49 -> 0 | AZ49: =AX49-AY49 -> 0.06964 | BA49: =AY49/AX49 -> 0
C53: Periodo | E53: Cuota III Región (t) | H53: Operación III región | K53: Cuota IV Región (t) | N53: Operación IV Región | Q53: Cuota y Operación Langostino amarillo III-IV | U53: Operación III-IV | X53: Global III-IV
B54: Armador | C54: Inicial | D54: Final | E54: Cuota Asignada | F54: Traspaso, Cesion, Arriendo, etc) | G54: Cuota Efectiva | H54: Desembarque (t) | I54: Saldo (t) | J54: Cuota Total | K54: Cuota Asignada | L54: Traspaso, Cesion, Arriendo, etc) | M54: Cuota Efectiva | N54: Desembarque (t) | O54: Saldo (t) | P54: Cuota Total | Q54: Cuota Asignada III-IV | R54: * Traspaso, Cesion, Arriendo, etc) | S54: ** Traspaso, Cesion, Arriendo, etc) | T54: Cuota Efectiva | U54: Desembarque (t) III-IV | V54: Saldo (t) | W54: % consumido | X54: Cuota Total | Y54: Desembarque (t) | Z54: Saldo (t) | AA54: % consumido
A55: Langostino amarillo III-IV | B55: Antarctic Seafood S.A | C55: 41730 | D55: 41820 | E55: 53.197 | G55: =E55+F55 -> 53.197 | I55: =G55-H55 -> 53.197 | J55: =E55+E56+E57+F55+F56+F57 -> 106.394 | K55: 181.104 | M55: =K55+L55 -> 181.104 | N55: 245.909 | O55: =M55-N55 -> -64.805 | P55: =K55+K56+K57+L55+L56+L57 -> 369.20332 | Q55: =E55+K55 -> 234.301 | R55: =F55+L55 -> 0 | T55: =Q55+R55+S55 -> 234.301 | U55: =H55+N55 -> 245.909 | V55: =T55-U55 -> -11.608 | W55: =U55/T55 -> 1.0495431 | X55: =Q55+Q56+Q57+R55+R56+R57+S55+S56+S57 -> 475.59732 | Y55: =U55+U56+U57 -> 468.79 | Z55: =X55-Y55 -> 6.80732 | AA55: =Y55/X55 -> 0.9856868
C56: 41821 | D56: 41912 | E56: 32.075 | G56: =E56+F56+I55 -> 85.272 | H56: 21.629 | I56: =G56-H56 -> 63.643 | K56: 108.74 | M56: =K56+L56+O55 -> 43.935 | N56: 116.208 | O56: =M56-N56 -> -72.273 | Q56: =E56+K56 -> 140.815 | R56: =F56+L56 -> 0 | T56: =Q56+R56+V55+S56 -> 129.207 | U56: =H56+N56 -> 137.837 | V56: =T56-U56 -> -8.63 | W56: =U56/T56 -> 1.066792
C57: 41913 | D57: 42004 | E57: 21.122 | G57: =E57+F57+I56 -> 84.765 | H57: 85.044 | I57: =G57-H57 -> -0.279 | K57: 72.363 | L57: =6.99632 -> 6.99632 | M57: =K57+L57+O56 -> 7.08632 | N57: 0 | O57: =M57-N57 -> 7.08632 | Q57: =E57+K57 -> 93.485 | R57: =F57+L57 -> 6.99632 | T57: =Q57+R57+V56+S57 -> 91.85132 | U57: =H57+N57 -> 85.044 | V57: =T57-U57 -> 6.80732 | W57: =U57/T57 -> 0.92588762
B58: Baycic Baycic Maria | C58: 41730 | D58: 41820 | E58: 3.838 | F58: =-3.838 -> -3.838 | G58: =E58+F58 -> 0 | I58: =G58-H58 -> 0 | J58: =E58+E59+E60+F58+F59+F60 -> 0 | K58: 13.065 | L58: =-13.065 -> -13.065 | M58: =K58+L58 -> 0 | O58: =M58-N58 -> 0 | P58: =K58+K59+K60+L58+L59+L60 -> 0 | Q58: =E58+K58 -> 16.903 | R58: =F58+L58 -> -16.903 | T58: =Q58+R58+S58 -> 0 | U58: =H58+N58 -> 0 | V58: =T58-U58 -> 0 | W58: =U58/T58 -> #DIV/0! | X58: =Q58+Q59+Q60+R58+R59+R60+S58+S59+S60 -> 0 | Y58: =U58+U59+U60 -> 0 | Z58: =X58-Y58 -> 0 | AA58: =Y58/X58 -> #DIV/0!
C59: 41821 | D59: 41912 | E59: 2.314 | F59: =-2.314 -> -2.314 | G59: =E59+F59+I58 -> 0 | I59: =G59-H59 -> 0 | K59: 7.845 | L59: =-7.845 -> -7.845 | M59: =K59+L59+O58 -> 0 | O59: =M59-N59 -> 0 | Q59: =E59+K59 -> 10.159 | R59: =F59+L59 -> -10.159 | T59: =Q59+R59+V58+S59 -> 0 | U59: =H59+N59 -> 0 | V59: =T59-U59 -> 0 | W59: =U59/T59 -> #DIV/0!
C60: 41913 | D60: 42004 | E60: 1.524 | F60: =-1.524 -> -1.524 | G60: =E60+F60+I59 -> 0 | I60: =G60-H60 -> 0 | K60: 5.22 | L60: =-5.22 -> -5.22 | M60: =K60+L60+O59 -> 0 | O60: =M60-N60 -> 0 | Q60: =E60+K60 -> 6.744 | R60: =F60+L60 -> -6.744 | T60: =Q60+R60+V59+S60 -> 0 | U60: =H60+N60 -> 0 | V60: =T60-U60 -> 0 | W60: =U60/T60 -> #DIV/0!
B61: Bracpesca S.A | C61: 41730 | D61: 41820 | E61: 55.396 | G61: =E61+F61 -> 55.396 | H61: 18.76 | I61: =G61-H61 -> 36.636 | J61: =E61+E62+E63+F61+F62+F63 -> 110.793 | K61: 188.591 | M61: =K61+L61 -> 188.591 | N61: 169.59 | O61: =M61-N61 -> 19.001 | P61: =K61+K62+K63+L61+L62+L63 -> 377.182 | Q61: =E61+K61 -> 243.987 | R61: =F61+L61 -> 0 | S61: =-1-0.755 -> -1.755 | T61: =Q61+R61+S61 -> 242.232 | U61: =H61+N61 -> 188.35 | V61: =T61-U61 -> 53.882 | W61: =U61/T61 -> 0.77756036 | X61: =Q61+Q62+Q63+R61+R62+R63+S61+S62+S63 -> 486.22 | Y61: =U61+U62+U63 -> 394.369 | Z61: =X61-Y61 -> 91.851 | AA61: =Y61/X61 -> 0.81109169
C62: 41821 | D62: 41912 | E62: 33.401 | G62: =E62+F62+I61 -> 70.037 | H62: 18.643 | I62: =G62-H62 -> 51.394 | K62: 113.236 | M62: =K62+L62+O61 -> 132.237 | N62: 112.109 | O62: =M62-N62 -> 20.128 | Q62: =E62+K62 -> 146.637 | R62: =F62+L62 -> 0 | T62: =Q62+R62+V61+S62 -> 200.519 | U62: =H62+N62 -> 130.752 | V62: =T62-U62 -> 69.767 | W62: =U62/T62 -> 0.65206788
C63: 41913 | D63: 42004 | E63: 21.996 | G63: =E63+F63+I62 -> 73.39 | I63: =G63-H63 -> 73.39 | K63: 75.355 | M63: =K63+L63+O62 -> 95.483 | N63: 75.267 | O63: =M63-N63 -> 20.216 | Q63: =E63+K63 -> 97.351 | R63: =F63+L63 -> 0 | T63: =Q63+R63+V62+S63 -> 167.118 | U63: =H63+N63 -> 75.267 | V63: =T63-U63 -> 91.851 | W63: =U63/T63 -> 0.45038236
B64: Grimar S.A. Pesq. | C64: 41730 | D64: 41820 | E64: 0.028 | G64: =E64+F64 -> 0.028 | I64: =G64-H64 -> 0.028 | J64: =E64+E65+E66+F64+F65+F66 -> 0.056 | K64: 0.094 | M64: =K64+L64 -> 0.094 | O64: =M64-N64 -> 0.094 | P64: =K64+K65+K66+L64+L65+L66 -> 0.189 | Q64: =E64+K64 -> 0.122 | R64: =F64+L64 -> 0 | S64: =1 -> 1 | T64: =Q64+R64+S64 -> 1.122 | U64: =H64+N64 -> 0 | V64: =T64-U64 -> 1.122 | W64: =U64/T64 -> 0 | X64: =Q64+Q65+Q66+R64+R65+R66+S64+S65+S66 -> 1.245 | Y64: =U64+U65+U66 -> 0 | Z64: =X64-Y64 -> 1.245 | AA64: =Y64/X64 -> 0
C65: 41821 | D65: 41912 | E65: 0.017 | G65: =E65+F65+I64 -> 0.045 | I65: =G65-H65 -> 0.045 | K65: 0.057 | M65: =K65+L65+O64 -> 0.151 | O65: =M65-N65 -> 0.151 | Q65: =E65+K65 -> 0.074 | R65: =F65+L65 -> 0 | T65: =Q65+R65+V64+S65 -> 1.196 | U65: =H65+N65 -> 0 | V65: =T65-U65 -> 1.196 | W65: =U65/T65 -> 0
C66: 41913 | D66: 42004 | E66: 0.011 | G66: =E66+F66+I65 -> 0.056 | I66: =G66-H66 -> 0.056 | K66: 0.038 | M66: =K66+L66+O65 -> 0.189 | O66: =M66-N66 -> 0.189 | Q66: =E66+K66 -> 0.049 | R66: =F66+L66 -> 0 | T66: =Q66+R66+V65+S66 -> 1.245 | U66: =H66+N66 -> 0 | V66: =T66-U66 -> 1.245 | W66: =U66/T66 -> 0
B67: Isladamas S.A. Pesq. | C67: 41730 | D67: 41820 | E67: 7.019 | F67: =3.466 -> 3.466 | G67: =E67+F67 -> 10.485 | I67: =G67-H67 -> 10.485 | J67: =E67+E68+E69+F67+F68+F69 -> 20.97 | K67: 23.897 | L67: =11.799 -> 11.799 | M67: =K67+L67 -> 35.696 | O67: =M67-N67 -> 35.696 | P67: =K67+K68+K69+L67+L68+L69 -> 64.39568 | Q67: =E67+K67 -> 30.916 | R67: =F67+L67 -> 15.265 | T67: =Q67+R67+S67 -> 46.181 | U67: =H67+N67 -> 0 | V67: =T67-U67 -> 46.181 | W67: =U67/T67 -> 0 | X67: =Q67+Q68+Q69+R67+R68+R69+S67+S68+S69 -> 85.36568 | Y67: =U67+U68+U69 -> 63.589 | Z67: =X67-Y67 -> 21.77668 | AA67: =Y67/X67 -> 0.74490123
C68: 41821 | D68: 41912 | E68: 4.232 | F68: =2.09 -> 2.09 | G68: =E68+F68+I67 -> 16.807 | I68: =G68-H68 -> 16.807 | K68: 14.348 | L68: =7.085 -> 7.085 | M68: =K68+L68+O67 -> 57.129 | N68: 56.733 | O68: =M68-N68 -> 0.396 | Q68: =E68+K68 -> 18.58 | R68: =F68+L68 -> 9.175 | T68: =Q68+R68+V67+S68 -> 73.936 | U68: =H68+N68 -> 56.733 | V68: =T68-U68 -> 17.203 | W68: =U68/T68 -> 0.7673258
C69: 41913 | D69: 42004 | E69: 2.787 | F69: =1.376 -> 1.376 | G69: =E69+F69+I68 -> 20.97 | I69: =G69-H69 -> 20.97 | K69: 9.548 | L69: =4.715-6.99632 -> -2.28132 | M69: =K69+L69+O68 -> 7.66268 | N69: 6.856 | O69: =M69-N69 -> 0.80668 | Q69: =E69+K69 -> 12.335 | R69: =F69+L69 -> -0.90532 | T69: =Q69+R69+V68+S69 -> 28.63268 | U69: =H69+N69 -> 6.856 | V69: =T69-U69 -> 21.77668 | W69: =U69/T69 -> 0.23944667
B70: Morozin Baycic Maria Ana | C70: 41730 | D70: 41820 | E70: 0.954 | F70: =-0.954 -> -0.954 | G70: =E70+F70 -> 0 | I70: =G70-H70 -> 0 | J70: =E70+E71+E72+F70+F71+F72 -> 0 | K70: 3.248 | L70: =-3.248 -> -3.248 | M70: =K70+L70 -> 0 | O70: =M70-N70 -> 0 | P70: =K70+K71+K72+L70+L71+L72 -> 0 | Q70: =E70+K70 -> 4.202 | R70: =F70+L70 -> -4.202 | T70: =Q70+R70+S70 -> 0 | U70: =H70+N70 -> 0 | V70: =T70-U70 -> 0 | W70: =U70/T70 -> #DIV/0! | X70: =Q70+Q71+Q72+R70+R71+R72+S70+S71+S72 -> 0 | Y70: =U70+U71+U72 -> 0 | Z70: =X70-Y70 -> 0 | AA70: =Y70/X70 -> #DIV/0!
C71: 41821 | D71: 41912 | E71: 0.575 | F71: =-0.575 -> -0.575 | G71: =E71+F71+I70 -> 0 | I71: =G71-H71 -> 0 | K71: 1.95 | L71: =-1.95 -> -1.95 | M71: =K71+L71+O70 -> 0 | O71: =M71-N71 -> 0 | Q71: =E71+K71 -> 2.525 | R71: =F71+L71 -> -2.525 | T71: =Q71+R71+V70+S71 -> 0 | U71: =H71+N71 -> 0 | V71: =T71-U71 -> 0 | W71: =U71/T71 -> #DIV/0!
C72: 41913 | D72: 42004 | E72: 0.379 | F72: =-0.379 -> -0.379 | G72: =E72+F72+I71 -> 0 | I72: =G72-H72 -> 0 | K72: 1.298 | L72: =-1.298 -> -1.298 | M72: =K72+L72+O71 -> 0 | O72: =M72-N72 -> 0 | Q72: =E72+K72 -> 1.677 | R72: =F72+L72 -> -1.677 | T72: =Q72+R72+V71+S72 -> 0 | U72: =H72+N72 -> 0 | V72: =T72-U72 -> 0 | W72: =U72/T72 -> #DIV/0!
B73: Mororzin Yurecic Mario | C73: 41730 | D73: 41820 | E73: 0.428 | F73: =-0.428 -> -0.428 | G73: =E73+F73 -> 0 | I73: =G73-H73 -> 0 | J73: =E73+E74+E75+F73+F74+F75 -> 0 | K73: 1.458 | L73: =-1.458 -> -1.458 | M73: =K73+L73 -> 0 | O73: =M73-N73 -> 0 | P73: =K73+K74+K75+L73+L74+L75 -> 0 | Q73: =E73+K73 -> 1.886 | R73: =F73+L73 -> -1.886 | T73: =Q73+R73+S73 -> 0 | U73: =H73+N73 -> 0 | V73: =T73-U73 -> 0 | W73: =U73/T73 -> #DIV/0! | X73: =Q73+Q74+Q75+R73+R74+R75+S73+S74+S75 -> 0 | Y73: =U73+U74+U75 -> 0 | Z73: =X73-Y73 -> 0 | AA73: =Y73/X73 -> #DIV/0!
C74: 41821 | D74: 41912 | E74: 0.258 | F74: =-0.258 -> -0.258 | G74: =E74+F74+I73 -> 0 | I74: =G74-H74 -> 0 | K74: 0.875 | L74: =-0.875 -> -0.875 | M74: =K74+L74+O73 -> 0 | O74: =M74-N74 -> 0 | Q74: =E74+K74 -> 1.133 | R74: =F74+L74 -> -1.133 | T74: =Q74+R74+V73+S74 -> 0 | U74: =H74+N74 -> 0 | V74: =T74-U74 -> 0 | W74: =U74/T74 -> #DIV/0!
C75: 41913 | D75: 42004 | E75: 0.17 | F75: =-0.17 -> -0.17 | G75: =E75+F75+I74 -> 0 | I75: =G75-H75 -> 0 | K75: 0.583 | L75: =-0.583 -> -0.583 | M75: =K75+L75+O74 -> 0 | O75: =M75-N75 -> 0 | Q75: =E75+K75 -> 0.753 | R75: =F75+L75 -> -0.753 | T75: =Q75+R75+V74+S75 -> 0 | U75: =H75+N75 -> 0 | V75: =T75-U75 -> 0 | W75: =U75/T75 -> #DIV/0!
B76: Quinteros S.A. Pesq. | C76: 41730 | D76: 41820 | E76: 4.564 | F76: =3.838+0.954+0.428 -> 5.22 | G76: =E76+F76 -> 9.784 | I76: =G76-H76 -> 9.784 | J76: =E76+E77+E78+F76+F77+F78 -> 19.568 | K76: 15.537 | L76: =13.065+3.248+1.458 -> 17.771 | M76: =K76+L76 -> 33.308 | N76: 26.954 | O76: =M76-N76 -> 6.354 | P76: =K76+K77+K78+L76+L77+L78 -> 66.616 | Q76: =E76+K76 -> 20.101 | R76: =F76+L76 -> 22.991 | S76: =-0.03-0.01198 -> -0.04198 | T76: =Q76+R76+S76 -> 43.05002 | U76: =H76+N76 -> 26.954 | V76: =T76-U76 -> 16.09602 | W76: =U76/T76 -> 0.62610888 | X76: =Q76+Q77+Q78+R76+R77+R78+S76+S77+S78 -> 86.14202 | Y76: =U76+U77+U78 -> 39.115 | Z76: =X76-Y76 -> 47.02702 | AA76: =Y76/X76 -> 0.45407572
C77: 41821 | D77: 41912 | E77: 2.752 | F77: =2.314+0.575+0.258 -> 3.147 | G77: =E77+F77+I76 -> 15.683 | I77: =G77-H77 -> 15.683 | K77: 9.329 | L77: =7.845+1.95+0.875 -> 10.67 | M77: =K77+L77+O76 -> 26.353 | O77: =M77-N77 -> 26.353 | Q77: =E77+K77 -> 12.081 | R77: =F77+L77 -> 13.817 | T77: =Q77+R77+V76+S77 -> 41.99402 | U77: =H77+N77 -> 0 | V77: =T77-U77 -> 41.99402 | W77: =U77/T77 -> 0
C78: 41913 | D78: 42004 | E78: 1.812 | F78: =1.524+0.379+0.17 -> 2.073 | G78: =E78+F78+I77 -> 19.568 | I78: =G78-H78 -> 19.568 | K78: 6.208 | L78: =5.22+1.298+0.583 -> 7.101 | M78: =K78+L78+O77 -> 39.662 | N78: 12.161 | O78: =M78-N78 -> 27.501 | Q78: =E78+K78 -> 8.02 | R78: =F78+L78 -> 9.174 | T78: =Q78+R78+V77+S78 -> 59.18802 | U78: =H78+N78 -> 12.161 | V78: =T78-U78 -> 47.02702 | W78: =U78/T78 -> 0.20546388
B79: Rubio y Mauad Ltda. | C79: 41730 | D79: 41820 | E79: 7.11 | G79: =E79+F79 -> 7.11 | I79: =G79-H79 -> 7.11 | J79: =E79+E80+E81+F79+F80+F81 -> 14.22 | K79: 24.207 | M79: =K79+L79 -> 24.207 | O79: =M79-N79 -> 24.207 | P79: =K79+K80+K81+L79+L80+L81 -> 48.414 | Q79: =E79+K79 -> 31.317 | R79: =F79+L79 -> 0 | T79: =Q79+R79+S79 -> 31.317 | U79: =H79+N79 -> 0 | V79: =T79-U79 -> 31.317 | W79: =U79/T79 -> 0 | X79: =Q79+Q80+Q81+R79+R80+R81+S79+S80+S81 -> 62.634 | Y79: =U79+U80+U81 -> 59.149 | Z79: =X79-Y79 -> 3.485 | AA79: =Y79/X79 -> 0.94435929
C80: 41821 | D80: 41912 | E80: 4.287 | G80: =E80+F80+I79 -> 11.397 | I80: =G80-H80 -> 11.397 | K80: 14.535 | M80: =K80+L80+O79 -> 38.742 | O80: =M80-N80 -> 38.742 | Q80: =E80+K80 -> 18.822 | R80: =F80+L80 -> 0 | T80: =Q80+R80+V79+S80 -> 50.139 | U80: =H80+N80 -> 0 | V80: =T80-U80 -> 50.139 | W80: =U80/T80 -> 0
C81: 41913 | D81: 42004 | E81: 2.823 | G81: =E81+F81+I80 -> 14.22 | H81: 11.123 | I81: =G81-H81 -> 3.097 | K81: 9.672 | M81: =K81+L81+O80 -> 48.414 | N81: 48.026 | O81: =M81-N81 -> 0.388 | Q81: =E81+K81 -> 12.495 | R81: =F81+L81 -> 0 | T81: =Q81+R81+V80+S81 -> 62.634 | U81: =H81+N81 -> 59.149 | V81: =T81-U81 -> 3.485 | W81: =U81/T81 -> 0.94435929
B82: Sunrise S.A. Pesq. | C82: 41730 | D82: 41820 | E82: 3.466 | F82: =-3.466 -> -3.466 | G82: =E82+F82 -> 0 | I82: =G82-H82 -> 0 | J82: =E82+E83+E84+F82+F83+F84 -> 0 | K82: 11.799 | L82: =-11.799 -> -11.799 | M82: =K82+L82 -> 0 | O82: =M82-N82 -> 0 | P82: =K82+K83+K84+L82+L83+L84 -> 0 | Q82: =E82+K82 -> 15.265 | R82: =F82+L82 -> -15.265 | T82: =Q82+R82+S82 -> 0 | U82: =H82+N82 -> 0 | V82: =T82-U82 -> 0 | W82: =U82/T82 -> #DIV/0! | X82: =Q82+Q83+Q84+R82+R83+R84+S82+S83+S84 -> 0 | Y82: =U82+U83+U84 -> 0 | Z82: =X82-Y82 -> 0 | AA82: =Y82/X82 -> #DIV/0!
C83: 41821 | D83: 41912 | E83: 2.09 | F83: =-2.09 -> -2.09 | G83: =E83+F83+I82 -> 0 | I83: =G83-H83 -> 0 | K83: 7.085 | L83: =-7.085 -> -7.085 | M83: =K83+L83+O82 -> 0 | O83: =M83-N83 -> 0 | Q83: =E83+K83 -> 9.175 | R83: =F83+L83 -> -9.175 | T83: =Q83+R83+V82+S83 -> 0 | U83: =H83+N83 -> 0 | V83: =T83-U83 -> 0 | W83: =U83/T83 -> #DIV/0!
C84: 41913 | D84: 42004 | E84: 1.376 | F84: =-1.376 -> -1.376 | G84: =E84+F84+I83 -> 0 | I84: =G84-H84 -> 0 | K84: 4.715 | L84: =-4.715 -> -4.715 | M84: =K84+L84+O83 -> 0 | O84: =M84-N84 -> 0 | Q84: =E84+K84 -> 6.091 | R84: =F84+L84 -> -6.091 | T84: =Q84+R84+V83+S84 -> 0 | U84: =H84+N84 -> 0 | V84: =T84-U84 -> 0 | W84: =U84/T84 -> #DIV/0!
B85: Quintero Ltda. | C85: 41730 | D85: 41820 | E85: 0 | G85: =E85+F85 -> 0 | I85: =G85-H85 -> 0 | J85: =E85+E86+E87+F85+F86+F87 -> 0 | K85: 0 | M85: =K85+L85 -> 0 | O85: =M85-N85 -> 0 | P85: =K85+K86+K87+L85+L86+L87 -> 0 | Q85: =E85+K85 -> 0 | R85: =F85+L85 -> 0 | S85: =0.03 -> 0.03 | T85: =Q85+R85+S85 -> 0.03 | U85: =H85+N85 -> 0 | V85: =T85-U85 -> 0.03 | W85: =U85/T85 -> 0 | X85: =Q85+Q86+Q87+R85+R86+R87+S85+S86+S87 -> 0.03 | Y85: =U85+U86+U87 -> 0 | Z85: =X85-Y85 -> 0.03 | AA85: =Y85/X85 -> 0
C86: 41821 | D86: 41912 | E86: 0 | G86: =E86+F86+I85 -> 0 | I86: =G86-H86 -> 0 | K86: 0 | M86: =K86+L86+O85 -> 0 | O86: =M86-N86 -> 0 | Q86: =E86+K86 -> 0 | R86: =F86+L86 -> 0 | T86: =Q86+R86+V85+S86 -> 0.03 | U86: =H86+N86 -> 0 | V86: =T86-U86 -> 0.03 | W86: =U86/T86 -> 0
C87: 41913 | D87: 42004 | E87: 0 | G87: =E87+F87+I86 -> 0 | I87: =G87-H87 -> 0 | K87: 0 | M87: =K87+L87+O86 -> 0 | O87: =M87-N87 -> 0 | Q87: =E87+K87 -> 0 | R87: =F87+L87 -> 0 | T87: =Q87+R87+V86+S87 -> 0.03 | U87: =H87+N87 -> 0 | V87: =T87-U87 -> 0.03 | W87: =U87/T87 -> 0
B88: Congelados del Pacifico | C88: 41730 | D88: 41820 | E88: 0 | G88: =E88+F88 -> 0 | I88: =G88-H88 -> 0 | J88: =E88+E89+E90+F88+F89+F90 -> 0 | K88: 0 | M88: =K88+L88 -> 0 | O88: =M88-N88 -> 0 | P88: =K88+K89+K90+L88+L89+L90 -> 0 | Q88: =E88+K88 -> 0 | R88: =F88+L88 -> 0 | S88: =0.755 -> 0.755 | T88: =Q88+R88+S88 -> 0.755 | U88: =H88+N88 -> 0 | V88: =T88-U88 -> 0.755 | W88: =U88/T88 -> 0 | X88: =Q88+Q89+Q90+R88+R89+R90+S88+S89+S90 -> 0.755 | Y88: =U88+U89+U90 -> 0 | Z88: =X88-Y88 -> 0.755 | AA88: =Y88/X88 -> 0
C89: 41821 | D89: 41912 | E89: 0 | G89: =E89+F89+I88 -> 0 | I89: =G89-H89 -> 0 | K89: 0 | M89: =K89+L89+O88 -> 0 | O89: =M89-N89 -> 0 | Q89: =E89+K89 -> 0 | R89: =F89+L89 -> 0 | T89: =Q89+R89+V88+S89 -> 0.755 | U89: =H89+N89 -> 0 | V89: =T89-U89 -> 0.755 | W89: =U89/T89 -> 0
C90: 41913 | D90: 42004 | E90: 0 | G90: =E90+F90+I89 -> 0 | I90: =G90-H90 -> 0 | K90: 0 | M90: =K90+L90+O89 -> 0 | O90: =M90-N90 -> 0 | Q90: =E90+K90 -> 0 | R90: =F90+L90 -> 0 | T90: =Q90+R90+V89+S90 -> 0.755 | U90: =H90+N90 -> 0 | V90: =T90-U90 -> 0.755 | W90: =U90/T90 -> 0
B91: Enfemar Pesq. | C91: 41730 | D91: 41820 | E91: 0 | G91: =E91+F91 -> 0 | I91: =G91-H91 -> 0 | J91: =E91+E92+E93+F91+F92+F93 -> 0 | K91: 0 | M91: =K91+L91 -> 0 | O91: =M91-N91 -> 0 | P91: =K91+K92+K93+L91+L92+L93 -> 0 | Q91: =E91+K91 -> 0 | R91: =F91+L91 -> 0 | S91: =0.01198 -> 0.01198 | T91: =Q91+R91+S91 -> 0.01198 | U91: =H91+N91 -> 0 | V91: =T91-U91 -> 0.01198 | W91: =U91/T91 -> 0 | X91: =Q91+Q92+Q93+R91+R92+R93+S91+S92+S93 -> 0.01198 | Y91: =U91+U92+U93 -> 0 | Z91: =X91-Y91 -> 0.01198 | AA91: =Y91/X91 -> 0
C92: 41821 | D92: 41912 | E92: 0 | G92: =E92+F92+I91 -> 0 | I92: =G92-H92 -> 0 | K92: 0 | M92: =K92+L92+O91 -> 0 | O92: =M92-N92 -> 0 | Q92: =E92+K92 -> 0 | R92: =F92+L92 -> 0 | T92: =Q92+R92+V91+S92 -> 0.01198 | U92: =H92+N92 -> 0 | V92: =T92-U92 -> 0.01198 | W92: =U92/T92 -> 0
C93: 41913 | D93: 42004 | E93: 0 | G93: =E93+F93+I92 -> 0 | I93: =G93-H93 -> 0 | K93: 0 | M93: =K93+L93+O92 -> 0 | O93: =M93-N93 -> 0 | Q93: =E93+K93 -> 0 | R93: =F93+L93 -> 0 | T93: =Q93+R93+V92+S93 -> 0.01198 | U93: =H93+N93 -> 0 | V93: =T93-U93 -> 0.01198 | W93: =U93/T93 -> 0
C96: Periodo | E96: Cuota II Región (t) | H96: Operación II región | K96: Cuota III Región (t) | N96: Operación III Región | Q96: Cuota IV Región (t) | T96: Operación IV Región | W96: Cuota y Operación Langostino colorado XV-II | AA96: Operación XV-II | AD96: Global XV-II
B97: Armador | C97: Inicial | D97: Final | E97: Cuota Asignada | F97: Traspaso, Cesion, Arriendo, etc) | G97: Cuota Efectiva | H97: Desembarque (t) | I97: Saldo (t) | J97: Cuota Total | K97: Cuota Asignada | L97: Traspaso, Cesion, Arriendo, etc) | M97: Cuota Efectiva | N97: Desembarque (t) | O97: Saldo (t) | P97: Cuota Total | Q97: Cuota Asignada | R97: Traspaso, Cesion, Arriendo, etc) | S97: Cuota Efectiva | T97: Desembarque (t) | U97: Saldo (t) | V97: Cuota Total | W97: Cuota Asignada III-IV | X97: * Traspaso, Cesion, Arriendo, etc) | Y97: ** Traspaso, Cesion, Arriendo, etc) | Z97: Cuota Efectiva | AA97: Desembarque (t) III-IV | AB97: Saldo (t) | AC97: % consumido | AD97: Cuota Total | AE97: Desembarque (t) | AF97: Saldo (t) | AG97: % consumido
A98: Langostino coloradoXV- IV | B98: Antarctic Seafood S.A | C98: 41730 | D98: 41820 | E98: 0.758 | G98: =E98+F98 -> 0.758 | I98: =G98-H98 -> 0.758 | J98: =E98+E99+E100+F98+F99+F100 -> 1.516 | K98: 3.031 | M98: =K98+L98 -> 3.031 | O98: =M98-N98 -> 3.031 | P98: =K98+K99+K100+L98+L99+L100 -> 6.062 | Q98: 1.516 | R98: =157.842 -> 157.842 | S98: =Q98+R98 -> 159.358 | T98: 22.113 | U98: =S98-T98 -> 137.245 | V98: =Q98+Q99+Q100+R98+R99+R100 -> 161.126 | W98: =E98+K98+Q98 -> 5.305 | X98: =L98+R98+F98 -> 157.842 | Z98: =W98+X98+Y98 -> 163.147 | AA98: =H98+N98+T98 -> 22.113 | AB98: =Z98-AA98 -> 141.034 | AC98: =AA98/Z98 -> 0.13554034 | AD98: =W98+W99+W100+X98+X99+X100+Y98+Y99+Y100 -> 168.704 | AE98: =AA98+AA99+AA100 -> 158.958 | AF98: =AD98-AE98 -> 9.746 | AG98: =AE98/AD98 -> 0.94223018
C99: 41821 | D99: 41912 | E99: 0.505 | G99: =E99+F99+I98 -> 1.263 | I99: =G99-H99 -> 1.263 | K99: 1.768 | M99: =K99+L99+O98 -> 4.799 | O99: =M99-N99 -> 4.799 | Q99: 1.01 | S99: =Q99+R99+U98 -> 138.255 | T99: 120.111 | U99: =S99-T99 -> 18.144 | W99: =E99+K99+Q99 -> 3.283 | X99: =L99+R99+F99 -> 0 | Z99: =W99+X99+AB98+Y99 -> 144.317 | AA99: =H99+N99+T99 -> 120.111 | AB99: =Z99-AA99 -> 24.206 | AC99: =AA99/Z99 -> 0.83227201
C100: 41913 | D100: 42004 | E100: 0.253 | G100: =E100+F100+I99 -> 1.516 | I100: =G100-H100 -> 1.516 | K100: 1.263 | M100: =K100+L100+O99 -> 6.062 | O100: =M100-N100 -> 6.062 | Q100: 0.758 | S100: =Q100+R100+U99 -> 18.902 | T100: 16.734 | U100: =S100-T100 -> 2.168 | W100: =E100+K100+Q100 -> 2.274 | X100: =L100+R100+F100 -> 0 | Z100: =W100+X100+AB99+Y100 -> 26.48 | AA100: =H100+N100+T100 -> 16.734 | AB100: =Z100-AA100 -> 9.746 | AC100: =AA100/Z100 -> 0.63194864
B101: Bracpesca S.A | C101: 41730 | D101: 41820 | E101: 1.517 | G101: =E101+F101 -> 1.517 | I101: =G101-H101 -> 1.517 | J101: =E101+E102+E103+F101+F102+F103 -> 3.034 | K101: 6.068 | M101: =K101+L101 -> 6.068 | O101: =M101-N101 -> 6.068 | P101: =K101+K102+K103+L101+L102+L103 -> 12.136 | Q101: 3.034 | S101: =Q101+R101 -> 3.034 | T101: 0.88 | U101: =S101-T101 -> 2.154 | V101: =Q101+Q102+Q103+R101+R102+R103 -> 6.574 | W101: =E101+K101+Q101 -> 10.619 | X101: =L101+R101+F101 -> 0 | Y101: =-1-0.36-0.7504-0.11-0.03 -> -2.2504 | Z101: =W101+X101+Y101 -> 8.3686 | AA101: =H101+N101+T101 -> 0.88 | AB101: =Z101-AA101 -> 7.4886 | AC101: =AA101/Z101 -> 0.10515498 | AD101: =W101+W102+W103+X101+X102+X103+Y101+Y102+Y103 -> 19.4936 | AE101: =AA101+AA102+AA103 -> 0.88 | AF101: =AD101-AE101 -> 18.6136 | AG101: =AE101/AD101 -> 0.045143021
C102: 41821 | D102: 41912 | E102: 1.011 | G102: =E102+F102+I101 -> 2.528 | I102: =G102-H102 -> 2.528 | K102: 3.54 | M102: =K102+L102+O101 -> 9.608 | O102: =M102-N102 -> 9.608 | Q102: 2.023 | S102: =Q102+R102+U101 -> 4.177 | U102: =S102-T102 -> 4.177 | W102: =E102+K102+Q102 -> 6.574 | X102: =L102+R102+F102 -> 0 | Z102: =W102+X102+AB101+Y102 -> 14.0626 | AA102: =H102+N102+T102 -> 0 | AB102: =Z102-AA102 -> 14.0626 | AC102: =AA102/Z102 -> 0
C103: 41913 | D103: 42004 | E103: 0.506 | G103: =E103+F103+I102 -> 3.034 | I103: =G103-H103 -> 3.034 | K103: 2.528 | M103: =K103+L103+O102 -> 12.136 | O103: =M103-N103 -> 12.136 | Q103: 1.517 | S103: =Q103+R103+U102 -> 5.694 | U103: =S103-T103 -> 5.694 | W103: =E103+K103+Q103 -> 4.551 | X103: =L103+R103+F103 -> 0 | Z103: =W103+X103+AB102+Y103 -> 18.6136 | AA103: =H103+N103+T103 -> 0 | AB103: =Z103-AA103 -> 18.6136 | AC103: =AA103/Z103 -> 0
B104: Isladamas S.A. | C104: 41730 | D104: 41820 | E104: 0.346 | F104: =0.316 -> 0.316 | G104: =E104+F104 -> 0.662 | I104: =G104-H104 -> 0.662 | J104: =E104+E105+E106+F104+F105+F106 -> 1.323 | K104: 1.382 | L104: =1.263 -> 1.263 | M104: =K104+L104 -> 2.645 | O104: =M104-N104 -> 2.645 | P104: =K104+K105+K106+L104+L105+L106 -> 5.29 | Q104: 0.691 | R104: =0.632 -> 0.632 | S104: =Q104+R104 -> 1.323 | U104: =S104-T104 -> 1.323 | V104: =Q104+Q105+Q106+R104+R105+R106 -> 2.867 | W104: =E104+K104+Q104 -> 2.419 | X104: =L104+R104+F104 -> 2.211 | Z104: =W104+X104+Y104 -> 4.63 | AA104: =H104+N104+T104 -> 0 | AB104: =Z104-AA104 -> 4.63 | AC104: =AA104/Z104 -> 0 | AD104: =W104+W105+W106+X104+X105+X106+Y104+Y105+Y106 -> 9.48 | AE104: =AA104+AA105+AA106 -> 0.009 | AF104: =AD104-AE104 -> 9.471 | AG104: =AE104/AD104 -> 0.00094936709
C105: 41821 | D105: 41912 | E105: 0.23 | F105: =0.211 -> 0.211 | G105: =E105+F105+I104 -> 1.103 | I105: =G105-H105 -> 1.103 | K105: 0.806 | L105: =0.737 -> 0.737 | M105: =K105+L105+O104 -> 4.188 | O105: =M105-N105 -> 4.188 | Q105: 0.461 | R105: =0.421 -> 0.421 | S105: =Q105+R105+U104 -> 2.205 | U105: =S105-T105 -> 2.205 | W105: =E105+K105+Q105 -> 1.497 | X105: =L105+R105+F105 -> 1.369 | Z105: =W105+X105+AB104+Y105 -> 7.496 | AA105: =H105+N105+T105 -> 0 | AB105: =Z105-AA105 -> 7.496 | AC105: =AA105/Z105 -> 0
C106: 41913 | D106: 42004 | E106: 0.115 | F106: =0.105 -> 0.105 | G106: =E106+F106+I105 -> 1.323 | I106: =G106-H106 -> 1.323 | K106: 0.576 | L106: =0.526 -> 0.526 | M106: =K106+L106+O105 -> 5.29 | O106: =M106-N106 -> 5.29 | Q106: 0.346 | R106: =0.316 -> 0.316 | S106: =Q106+R106+U105 -> 2.867 | T106: 0.009 | U106: =S106-T106 -> 2.858 | W106: =E106+K106+Q106 -> 1.037 | X106: =L106+R106+F106 -> 0.947 | Z106: =W106+X106+AB105+Y106 -> 9.48 | AA106: =H106+N106+T106 -> 0.009 | AB106: =Z106-AA106 -> 9.471 | AC106: =AA106/Z106 -> 0.00094936709
...

Sheet Demersales LTP 
B2: 2014. CUOTAS LTP Y SU CONSUMO DE RECURSOS PECES DEMERSALES al 31 de Diciembre de 2014.
C5: Periodo | E5: Cuota (t) | H5: Operación | K5: Global
A6: Unidad de pesquería | B6: Armador | C6: Inicial | D6: Final | E6: Cuota Asignada | F6: Traspaso, Cesion, Arriendo, etc) | G6: Cuota Efectiva | H6: Desembarque (t) | I6: Saldo (t) | J6: % consumido | K6: Cuota Total | L6: Desembarque (t) | M6: Saldo (t) | N6: % consumido
A7: Congrio dorado NE H/F (41º28,6 LS hasta 47º) | B7: Emdepes S.A. | C7: 41640 | D7: 41698 | E7: 0.469 | F7: =0.949 -> 0.949 | G7: =E7+F7 -> 1.418 | I7: =G7-H7 -> 1.418 | J7: =H7/G7 -> 0 | K7: =E7+E8+F7+F8 -> 1.887 | L7: =H7+H8 -> 0 | M7: =K7-L7 -> 1.887 | N7: =L7/K7 -> 0
C8: 41699 | D8: 42004 | E8: 0.469 | G8: =E8+F8+I7 -> 1.887 | I8: =G8-H8 -> 1.887 | J8: =H8/G8 -> 0
B9: Pesca Chile S.A. | C9: 41640 | D9: 41698 | E9: 128.862 | F9: =-0.949-192.308 -> -193.257 | G9: =E9+F9 -> -64.395 | I9: =G9-H9 -> -64.395 | J9: =H9/G9 -> 0 | K9: =E9+E10+F9+F10 -> 64.467 | L9: =H9+H10 -> 64.467 | M9: =K9-L9 -> 0 | N9: =L9/K9 -> 1
C10: 41699 | D10: 42004 | E10: 128.862 | G10: =E10+F10+I9 -> 64.467 | H10: 64.467 | I10: =G10-H10 -> 0 | J10: =H10/G10 -> 1
B11: Pesca Cisne S.A | C11: 41640 | D11: 41698 | E11: 10.992 | G11: =E11+F11 -> 10.992 | I11: =G11-H11 -> 10.992 | J11: =H11/G11 -> 0 | K11: =E11+E12+F11+F12 -> 21.984 | L11: =H11+H12 -> 18.157 | M11: =K11-L11 -> 3.827 | N11: =L11/K11 -> 0.82591885
C12: 41699 | D12: 42004 | E12: 10.992 | G12: =E12+F12+I11 -> 21.984 | H12: 18.157 | I12: =G12-H12 -> 3.827 | J12: =H12/G12 -> 0.82591885
B13: Grimar S.A.Pesq. | C13: 41640 | D13: 41698 | E13: 6.847 | F13: =95 -> 95 | G13: =E13+F13 -> 101.847 | H13: 2.476 | I13: =G13-H13 -> 99.371 | J13: =H13/G13 -> 0.024310976 | K13: =E13+E14+F13+F14 -> 108.694 | L13: =H13+H14 -> 14.261 | M13: =K13-L13 -> 94.433 | N13: =L13/K13 -> 0.13120319
C14: 41699 | D14: 42004 | E14: 6.847 | G14: =E14+F14+I13 -> 106.218 | H14: 11.785 | I14: =G14-H14 -> 94.433 | J14: =H14/G14 -> 0.11095106
B15: Sur Austral S.A. Pesq. | C15: 41640 | D15: 41698 | E15: 38.33 | F15: =95 -> 95 | G15: =E15+F15 -> 133.33 | H15: 1.162 | I15: =G15-H15 -> 132.168 | J15: =H15/G15 -> 0.0087152179 | K15: =E15+E16+F15+F16 -> 171.66 | L15: =H15+H16 -> 45.222 | M15: =K15-L15 -> 126.438 | N15: =L15/K15 -> 0.26343936
C16: 41699 | D16: 42004 | E16: 38.33 | G16: =E16+F16+I15 -> 170.498 | H16: 44.06 | I16: =G16-H16 -> 126.438 | J16: =H16/G16 -> 0.25841945
B17: Deris S.A. | C17: 41640 | D17: 41698 | E17: 0 | F17: =192.308-95-95 -> 2.308 | G17: =E17+F17 -> 2.308 | I17: =G17-H17 -> 2.308 | J17: =H17/G17 -> 0 | K17: =E17+E18+F17+F18 -> 2.308 | L17: =H17+H18 -> 0 | M17: =K17-L17 -> 2.308 | N17: =L17/K17 -> 0
C18: 41699 | D18: 42004 | E18: 0 | G18: =E18+F18+I17 -> 2.308 | I18: =G18-H18 -> 2.308 | J18: =H18/G18 -> 0
A20: Congrio dorado SE (47º hasta 57º) | B20: Emdepes S.A., | C20: 41640 | D20: 41698 | E20: 11.461 | G20: =E20+F20 -> 11.461 | I20: =G20-H20 -> 11.461 | J20: =H20/G20 -> 0 | K20: =E20+E21+F20+F21 -> 22.922 | L20: =H20+H21 -> 22.549 | M20: =K20-L20 -> 0.373 | N20: =L20/K20 -> 0.98372742
C21: 41699 | D21: 42004 | E21: 11.461 | G21: =E21+F21+I20 -> 22.922 | H21: 22.549 | I21: =G21-H21 -> 0.373 | J21: =H21/G21 -> 0.98372742
B22: Grimar S.A.Pesq. | C22: 41640 | D22: 41698 | E22: 0.034 | G22: =E22+F22 -> 0.034 | I22: =G22-H22 -> 0.034 | J22: =H22/G22 -> 0 | K22: =E22+E23+F22+F23 -> 0.068 | L22: =H22+H23 -> 0 | M22: =K22-L22 -> 0.068 | N22: =L22/K22 -> 0
C23: 41699 | D23: 42004 | E23: 0.034 | G23: =E23+F23+I22 -> 0.068 | I23: =G23-H23 -> 0.068 | J23: =H23/G23 -> 0
B24: Pesca Chile S.A. | C24: 41640 | D24: 41698 | E24: 39.244 | F24: =0.285-18.688 -> -18.403 | G24: =E24+F24 -> 20.841 | H24: 41.942 | I24: =G24-H24 -> -21.101 | J24: =H24/G24 -> 2.0124754 | K24: =E24+E25+F24+F25 -> 60.085 | L24: =H24+H25 -> 60.085 | M24: =K24-L24 -> 0 | N24: =L24/K24 -> 1
C25: 41699 | D25: 42004 | E25: 39.244 | G25: =E25+F25+I24 -> 18.143 | H25: 18.143 | I25: =G25-H25 -> 0 | J25: =H25/G25 -> 1
B26: Pesca Cisne S.A | C26: 41640 | D26: 41698 | E26: 15.244 | F26: =-0.285 -> -0.285 | G26: =E26+F26 -> 14.959 | I26: =G26-H26 -> 14.959 | J26: =H26/G26 -> 0 | K26: =E26+E27+F26+F27 -> 30.203 | L26: =H26+H27 -> 29.881 | M26: =K26-L26 -> 0.322 | N26: =L26/K26 -> 0.98933881
C27: 41699 | D27: 42004 | E27: 15.244 | G27: =E27+F27+I26 -> 30.203 | H27: 29.881 | I27: =G27-H27 -> 0.322 | J27: =H27/G27 -> 0.98933881
B28: Sur Austral S.A. Pesq. | C28: 41640 | D28: 41698 | E28: 0.017 | G28: =E28+F28 -> 0.017 | I28: =G28-H28 -> 0.017 | J28: =H28/G28 -> 0 | K28: =E28+E29+F28+F29 -> 0.034 | L28: =H28+H29 -> 0 | M28: =K28-L28 -> 0.034 | N28: =L28/K28 -> 0
C29: 41699 | D29: 42004 | E29: 0.017 | G29: =E29+F29+I28 -> 0.034 | I29: =G29-H29 -> 0.034 | J29: =H29/G29 -> 0
B30: Deris S.A. | C30: 41640 | D30: 41698 | E30: 0 | F30: =18.688 -> 18.688 | G30: =E30+F30 -> 18.688 | I30: =G30-H30 -> 18.688 | J30: =H30/G30 -> 0 | K30: =E30+E31+F30+F31 -> 18.688 | L30: =H30+H31 -> 0 | M30: =K30-L30 -> 18.688 | N30: =L30/K30 -> 0
C31: 41699 | D31: 42004 | E31: 0 | G31: =E31+F31+I30 -> 18.688 | I31: =G31-H31 -> 18.688 | J31: =H31/G31 -> 0
A33: Merluza del sur NE F/H (41º28,6 LS al 47º LS) | B33: Emdepes S.A. | C33: 41640 | D33: 41670 | E33: 130.067 | F33: =189.512+192.829+276.77+195.151+164.278+26.13 -> 1044.67 | G33: =E33+F33 -> 1174.737 | I33: =G33-H33 -> 1174.737 | J33: =H33/G33 -> 0 | K33: =E33+E34+F33+F34 -> 1565.19 | L33: =H33+H34 -> 1565.182 | M33: =K33-L33 -> 0.008 | N33: =L33/K33 -> 0.99999489
C34: 41671 | D34: 41851 | E34: 241.39 | F34: =110.488+38.575 -> 149.063 | G34: =E34+F34+I33 -> 1565.19 | H34: 1565.182 | I34: =G34-H34 -> 0.008 | J34: =H34/G34 -> 0.99999489
B35: Pesca Chile S.A. | C35: 41640 | D35: 41670 | E35: 472.435 | F35: =276.798-276.77-106.195+200-93.833 -> 0 | G35: =E35+F35 -> 472.435 | I35: =G35-H35 -> 472.435 | J35: =H35/G35 -> 0 | K35: =E35+E36+F35+F36 -> 1276.89 | L35: =H35+H36 -> 1276.89 | M35: =K35-L35 -> 0 | N35: =L35/K35 -> 1
C36: 41671 | D36: 41851 | E36: 876.784 | F36: =-72.329 -> -72.329 | G36: =E36+F36+I35 -> 1276.89 | H36: 1276.89 | I36: =G36-H36 -> 0 | J36: =H36/G36 -> 1
B37: Pesca Cisne S.A. | C37: 41640 | D37: 41670 | E37: 30.339 | G37: =E37+F37 -> 30.339 | I37: =G37-H37 -> 30.339 | J37: =H37/G37 -> 0 | K37: =E37+E38+F37+F38 -> 86.645 | L37: =H37+H38 -> 86.436 | M37: =K37-L37 -> 0.209 | N37: =L37/K37 -> 0.99758786
C38: 41671 | D38: 41851 | E38: 56.306 | G38: =E38+F38+I37 -> 86.645 | H38: 86.436 | I38: =G38-H38 -> 0.209 | J38: =H38/G38 -> 0.99758786
B39: Grimar S.A. Pesq. | C39: 41640 | D39: 41670 | E39: 30.204 | F39: =450+22.13+79.516+32.373+39.11 -> 623.129 | G39: =E39+F39 -> 653.333 | H39: 63.912 | I39: =G39-H39 -> 589.421 | J39: =H39/G39 -> 0.09782454 | K39: =E39+E40+F39+F40 -> 900.404 | L39: =H39+H40 -> 892.944 | M39: =K39-L39 -> 7.46 | N39: =L39/K39 -> 0.99171483
C40: 41671 | D40: 41851 | E40: 56.054 | F40: =28.017+163 -> 191.017 | G40: =E40+F40+I39 -> 836.492 | H40: 829.032 | I40: =G40-H40 -> 7.46 | J40: =H40/G40 -> 0.9910818
B41: Sur Austral S.A. Pesq. | C41: 41640 | D41: 41670 | E41: 356.955 | F41: =-356.955+137.588+166.633+627.822-0.75+18.622-26.13 -> 566.83 | G41: =E41+F41 -> 923.785 | H41: 49.261 | I41: =G41-H41 -> 874.524 | J41: =H41/G41 -> 0.053325178 | K41: =E41+E42+F41+F42 -> 1575.207 | L41: =H41+H42 -> 1560.248 | M41: =K41-L41 -> 14.959 | N41: =L41/K41 -> 0.99050347
C42: 41671 | D42: 41851 | E42: 662.467 | F42: =-93.045-10+92 -> -11.045 | G42: =E42+F42+I41 -> 1525.946 | H42: 1510.987 | I42: =G42-H42 -> 14.959 | J42: =H42/G42 -> 0.9901969
B43: Congelados del Pacifico | C43: 41640 | D43: 41670 | E43: 0 | F43: =0.75 -> 0.75 | G43: =E43+F43 -> 0.75 | I43: =G43-H43 -> 0.75 | J43: =H43/G43 -> 0 | K43: =E43+E44+F43+F44 -> 0.75 | L43: =H43+H44 -> 0 | M43: =K43-L43 -> 0.75 | N43: =L43/K43 -> 0
C44: 41671 | D44: 41851 | E44: 0 | F44: 0 | G44: =E44+F44+I43 -> 0.75 | I44: =G44-H44 -> 0.75 | J44: =H44/G44 -> 0
B45: Deris S.A. | C45: 41640 | D45: 41670 | E45: 0 | F45: =93.833 -> 93.833 | G45: =E45+F45 -> 93.833 | I45: =G45-H45 -> 93.833 | J45: =H45/G45 -> 0 | K45: =E45+E46+F45+F46 -> 3.162 | L45: =H45+H46 -> 0 | M45: =K45-L45 -> 3.162 | N45: =L45/K45 -> 0
C46: 41671 | D46: 41851 | E46: 0 | F46: =72.329-163 -> -90.671 | G46: =E46+F46+I45 -> 3.162 | I46: =G46-H46 -> 3.162 | J46: =H46/G46 -> 0
A48: Merluza Del Sur SE Fabrica (47º LS al 57º LS) | B48: Emdepes S.A. | C48: 41640 | D48: 41670 | E48: 189.512 | F48: =-189.512+106.195 -> -83.317 | G48: =E48+F48 -> 106.195 | I48: =G48-H48 -> 106.195 | J48: =H48/G48 -> 0 | K48: =E48+E49+F48+F49 -> 357.699 | L48: =H48+H49 -> 357.12 | M48: =K48-L48 -> 0.579 | N48: =L48/K48 -> 0.99838132
C49: 41671 | D49: 41851 | E49: 351.992 | F49: =-110.488+10 -> -100.488 | G49: =E49+F49+I48 -> 357.699 | H49: 357.12 | I49: =G49-H49 -> 0.579 | J49: =H49/G49 -> 0.99838132
B50: Grimar S.A. Pesq. | C50: 41640 | D50: 41670 | E50: 0.366 | G50: =E50+F50 -> 0.366 | I50: =G50-H50 -> 0.366 | J50: =H50/G50 -> 0 | K50: =E50+E51+F50+F51 -> 1.046 | L50: =H50+H51 -> 0 | M50: =K50-L50 -> 1.046 | N50: =L50/K50 -> 0
C51: 41671 | D51: 41851 | E51: 0.68 | G51: =E51+F51+I50 -> 1.046 | I51: =G51-H51 -> 1.046 | J51: =H51/G51 -> 0
B52: Pesca Chile S.A. | C52: 41640 | D52: 41670 | E52: 352.691 | F52: =-200-152.663 -> -352.663 | G52: =E52+F52 -> 0.028 | H52: 0.028 | I52: =G52-H52 -> -3.6835118e-14 | J52: =H52/G52 -> 1 | K52: =E52+E53+F52+F53 -> 582.117 | L52: =H52+H53 -> 582.117 | M52: =K52-L52 -> 0 | N52: =L52/K52 -> 1
C53: 41671 | D53: 41851 | E53: 655.075 | F53: =-72.986 -> -72.986 | G53: =E53+F53+I52 -> 582.089 | H53: 582.089 | I53: =G53-H53 -> 0 | J53: =H53/G53 -> 1
B54: Pesca Cisne S.A. | C54: 41640 | D54: 41670 | E54: 106.703 | G54: =E54+F54 -> 106.703 | I54: =G54-H54 -> 106.703 | J54: =H54/G54 -> 0 | K54: =E54+E55+F54+F55 -> 304.889 | L54: =H54+H55 -> 280.078 | M54: =K54-L54 -> 24.811 | N54: =L54/K54 -> 0.91862284
C55: 41671 | D55: 41851 | E55: 198.186 | G55: =E55+F55+I54 -> 304.889 | H55: 280.078 | I55: =G55-H55 -> 24.811 | J55: =H55/G55 -> 0.91862284
B56: Sur Austral S.A. Pesq. | C56: 41640 | D56: 41670 | E56: 2.728 | G56: =E56+F56 -> 2.728 | I56: =G56-H56 -> 2.728 | J56: =H56/G56 -> 0 | K56: =E56+E57+F56+F57 -> 7.795 | L56: =H56+H57 -> 5.418 | M56: =K56-L56 -> 2.377 | N56: =L56/K56 -> 0.69506094
C57: 41671 | D57: 41851 | E57: 5.067 | G57: =E57+F57+I56 -> 7.795 | H57: 5.418 | I57: =G57-H57 -> 2.377 | J57: =H57/G57 -> 0.69506094
B58: Deris S.A. | C58: 41640 | D58: 41670 | E58: 0 | F58: =152.663 -> 152.663 | G58: =E58+F58 -> 152.663 | I58: =G58-H58 -> 152.663 | J58: =H58/G58 -> 0 | K58: =E58+E59+F58+F59 -> 133.649 | L58: =H58+H59 -> 0 | M58: =K58-L58 -> 133.649 | N58: =L58/K58 -> 0
C59: 41671 | D59: 41851 | E59: 0 | F59: =72.986-92 -> -19.014 | G59: =E59+F59+I58 -> 133.649 | I59: =G59-H59 -> 133.649 | J59: =H59/G59 -> 0
A61: Merluza tres aletas NE/SE (41º28,6 LS hasta 57º) | B61: Emdepes S.A. | C61: 41640 | D61: 41670 | E61: 5241.956 | F61: =-144.345-714.215-714.215 -> -1572.775 | G61: =E61+F61 -> 3669.181 | I61: =G61-H61 -> 3669.181 | J61: =H61/G61 -> 0 | K61: =E61+E62+F61+F62 -> 12711 | L61: =H61+H62 -> 8700.712 | M61: =K61-L61 -> 4010.288 | N61: =L61/K61 -> 0.68450256
C62: 41671 | D62: 42004 | E62: 9041.819 | G62: =E62+F62+I61 -> 12711 | H62: 8700.712 | I62: =G62-H62 -> 4010.288 | J62: =H62/G62 -> 0.68450256
B63: Grimar S.A. Pesq. | C63: 41640 | D63: 41670 | E63: 0.154 | F63: =714.215 -> 714.215 | G63: =E63+F63 -> 714.369 | I63: =G63-H63 -> 714.369 | J63: =H63/G63 -> 0 | K63: =E63+E64+F63+F64 -> 714.635 | L63: =H63+H64 -> 606.649 | M63: =K63-L63 -> 107.986 | N63: =L63/K63 -> 0.84889349
C64: 41671 | D64: 42004 | E64: 0.266 | G64: =E64+F64+I63 -> 714.635 | H64: 606.649 | I64: =G64-H64 -> 107.986 | J64: =H64/G64 -> 0.84889349
B65: Pesca Chile S.A. | C65: 41640 | D65: 41670 | E65: 5.378 | F65: =-0.4+144.345 -> 143.945 | G65: =E65+F65 -> 149.323 | I65: =G65-H65 -> 149.323 | J65: =H65/G65 -> 0 | K65: =E65+E66+F65+F66 -> 158.6 | L65: =H65+H66 -> 115.248 | M65: =K65-L65 -> 43.352 | N65: =L65/K65 -> 0.72665826
C66: 41671 | D66: 42004 | E66: 9.277 | G66: =E66+F66+I65 -> 158.6 | H66: 115.248 | I66: =G66-H66 -> 43.352 | J66: =H66/G66 -> 0.72665826
B67: Sur Austral S.A. Pesq. | C67: 41640 | D67: 41670 | E67: 0.422 | F67: =714.215 -> 714.215 | G67: =E67+F67 -> 714.637 | I67: =G67-H67 -> 714.637 | J67: =H67/G67 -> 0 | K67: =E67+E68+F67+F68 -> 715.365 | L67: =H67+H68 -> 520.248 | M67: =K67-L67 -> 195.117 | N67: =L67/K67 -> 0.72724833
C68: 41671 | D68: 42004 | E68: 0.728 | G68: =E68+F68+I67 -> 715.365 | H68: 520.248 | I68: =G68-H68 -> 195.117 | J68: =H68/G68 -> 0.72724833
B69: Pesca Cisne | C69: 41640 | D69: 41670 | E69: 0 | F69: =0.4 -> 0.4 | G69: =E69+F69 -> 0.4 | I69: =G69-H69 -> 0.4 | J69: =H69/G69 -> 0 | K69: =E69+E70+F69+F70 -> 0.4 | L69: =H69+H70 -> 0 | M69: =K69-L69 -> 0.4 | N69: =L69/K69 -> 0
C70: 41671 | D70: 42004 | E70: 0 | G70: =E70+F70+I69 -> 0.4 | I70: =G70-H70 -> 0.4 | J70: =H70/G70 -> 0
A72: Merluza cola V-X | B72: Alimentos Marinos S.A. | C72: 41640 | D72: 41729 | E72: 1235.136 | F72: =-1235.136+6.442 -> -1228.694 | G72: =E72+F72 -> 6.442 | I72: =G72-H72 -> 6.442 | J72: =H72/G72 -> 0 | K72: =E72+E73+F72+F73 -> 16.105 | L72: =H72+H73 -> 0 | M72: =K72-L72 -> 16.105 | N72: =L72/K72 -> 0
C73: 41365 | D73: 42004 | E73: 1852.704 | F73: =-1852.704+9.663 -> -1843.041 | G73: =E73+F73+I72 -> 16.105 | I73: =G73-H73 -> 16.105 | J73: =H73/G73 -> 0
B74: Bio Bio S.A.Pesq. | C74: 41640 | D74: 41729 | E74: 895.068 | F74: =-260.858-634.21+0.294 -> -894.774 | G74: =E74+F74 -> 0.294 | H74: 0 | I74: =G74-H74 -> 0.294 | J74: =H74/G74 -> 0 | K74: =E74+E75+F74+F75 -> 0.7054 | L74: =H74+H75 -> 0 | M74: =K74-L74 -> 0.7054 | N74: =L74/K74 -> 0
C75: 41365 | D75: 42004 | E75: 1342.602 | F75: =-1342.1906 -> -1342.1906 | G75: =E75+F75+I74 -> 0.7054 | I75: =G75-H75 -> 0.7054 | J75: =H75/G75 -> 0
B76: Blumar S.A. | C76: 41640 | D76: 41729 | E76: 2147.343 | F76: =-0.239-2147.104+0.24 -> -2147.103 | G76: =E76+F76 -> 0.24 | H76: 0 | I76: =G76-H76 -> 0.24 | J76: =H76/G76 -> 0 | K76: =E76+E77+F76+F77 -> 0.24 | L76: =H76+H77 -> 0 | M76: =K76-L76 -> 0.24 | N76: =L76/K76 -> 0
C77: 41365 | D77: 42004 | E77: 3221.014 | F77: =-3221.014 -> -3221.014 | G77: =E77+F77+I76 -> 0.24 | I77: =G77-H77 -> 0.24 | J77: =H77/G77 -> 0
B78: Camanchaca S.A. CIA. Pesq. | C78: 41640 | D78: 41729 | E78: 6.442 | F78: =-6.442 -> -6.442 | G78: =E78+F78 -> 0 | I78: =G78-H78 -> 0 | J78: =H78/G78 -> #DIV/0! | K78: =E78+E79+F78+F79 -> 0 | L78: =H78+H79 -> 0 | M78: =K78-L78 -> 0 | N78: =L78/K78 -> #DIV/0!
C79: 41365 | D79: 42004 | E79: 9.663 | F79: =-9.663 -> -9.663 | G79: =E79+F79+I78 -> 0 | I79: =G79-H79 -> 0 | J79: =H79/G79 -> #DIV/0!
B80: Centro Sur S.A. Pesq. | C80: 41640 | D80: 41729 | E80: 317.636 | F80: =-317.636 -> -317.636 | G80: =E80+F80 -> 0 | I80: =G80-H80 -> 0 | J80: =H80/G80 -> #DIV/0! | K80: =E80+E81+F80+F81 -> 0.517 | L80: =H80+H81 -> 0 | M80: =K80-L80 -> 0.517 | N80: =L80/K80 -> 0
C81: 41365 | D81: 42004 | E81: 476.454 | F81: =-475.937 -> -475.937 | G81: =E81+F81+I80 -> 0.517 | I81: =G81-H81 -> 0.517 | J81: =H81/G81 -> 0
B82: Foodcorp S.A. | C82: 41640 | D82: 41729 | E82: 1043.678 | F82: =-1239.368-1239.368-130.46 -> -2609.196 | G82: =E82+F82 -> -1565.518 | I82: =G82-H82 -> -1565.518 | J82: =H82/G82 -> 0 | K82: =E82+E83+F82+F83 -> -0.001 | L82: =H82+H83 -> 0 | M82: =K82-L82 -> -0.001 | N82: =L82/K82 -> 0
C83: 41365 | D83: 42004 | E83: 1565.517 | G83: =E83+F83+I82 -> -0.001 | I83: =G83-H83 -> -0.001 | J83: =H83/G83 -> 0
B84: Grimar S.A.Pesq. | C84: 41640 | D84: 41729 | E84: 36.173 | F84: =-1+1239.368-0.24-0.24-0.24+51.001+317.636+24.596+2000-1100-680 -> 1850.881 | G84: =E84+F84 -> 1887.054 | H84: 449.351 | I84: =G84-H84 -> 1437.703 | J84: =H84/G84 -> 0.23812302 | K84: =E84+E85+F84+F85 -> 3100.105 | L84: =H84+H85 -> 3098.105 | M84: =K84-L84 -> 2 | N84: =L84/K84 -> 0.99935486
C85: 41365 | D85: 42004 | E85: 54.259 | F85: =75.961+475.937+36.894+290+400-200+80 -> 1158.792 | G85: =E85+F85+I84 -> 2650.754 | H85: 2648.754 | I85: =G85-H85 -> 2 | J85: =H85/G85 -> 0.9992455
B86: Inostroza Concha Pelantaro. | C86: 41640 | D86: 41729 | E86: 2.889 | F86: =-2.889 -> -2.889 | G86: =E86+F86 -> 0 | I86: =G86-H86 -> 0 | J86: =H86/G86 -> #DIV/0! | K86: =E86+E87+F86+F87 -> 0 | L86: =H86+H87 -> 0 | M86: =K86-L86 -> 0 | N86: =L86/K86 -> #DIV/0!
C87: 41365 | D87: 42004 | E87: 4.334 | F87: =-4.334 -> -4.334 | G87: =E87+F87+I86 -> 0 | I87: =G87-H87 -> 0 | J87: =H87/G87 -> #DIV/0!
B88: Inversiones Pesqueras S.A. | C88: 41640 | D88: 41729 | E88: 51.001 | F88: =-51.001 -> -51.001 | G88: =E88+F88 -> 0 | I88: =G88-H88 -> 0 | J88: =H88/G88 -> #DIV/0! | K88: =E88+E89+F88+F89 -> 0.54 | L88: =H88+H89 -> 0 | M88: =K88-L88 -> 0.54 | N88: =L88/K88 -> 0
C89: 41365 | D89: 42004 | E89: 76.501 | F89: =-75.961 -> -75.961 | G89: =E89+F89+I88 -> 0.54 | I89: =G89-H89 -> 0.54 | J89: =H89/G89 -> 0
B90: Isla Quihua S.A. Pesq. | C90: 41640 | D90: 41729 | E90: 90.501 | F90: -226.253 | G90: =E90+F90 -> -135.752 | I90: =G90-H90 -> -135.752 | J90: =H90/G90 -> 0 | K90: =E90+E91+F90+F91 -> 0 | L90: =H90+H91 -> 0 | M90: =K90-L90 -> 0 | N90: =L90/K90 -> #DIV/0!
C91: 41365 | D91: 42004 | E91: 135.752 | G91: =E91+F91+I90 -> 0 | I91: =G91-H91 -> 0 | J91: =H91/G91 -> #DIV/0!
B92: Landes S.A. Pesq. | C92: 41640 | D92: 41729 | E92: 451.187 | F92: =-451.187 -> -451.187 | G92: =E92+F92 -> 0 | I92: =G92-H92 -> 0 | J92: =H92/G92 -> #DIV/0! | K92: =E92+E93+F92+F93 -> 50.968 | L92: =H92+H93 -> 0.017 | M92: =K92-L92 -> 50.951 | N92: =L92/K92 -> 0.00033354261
C93: 41365 | D93: 42004 | E93: 676.781 | F93: =-625.813 -> -625.813 | G93: =E93+F93+I92 -> 50.968 | H93: 0.017 | I93: =G93-H93 -> 50.951 | J93: =H93/G93 -> 0.00033354261
B94: Lota Protein S.A. | C94: 41640 | D94: 41729 | E94: 282.707 | F94: =2.889-285.596 -> -282.707 | G94: =E94+F94 -> 0 | I94: =G94-H94 -> 0 | J94: =H94/G94 -> #DIV/0! | K94: =E94+E95+F94+F95 -> 13.18389 | L94: =H94+H95 -> 0 | M94: =K94-L94 -> 13.18389 | N94: =L94/K94 -> 0
C95: 41365 | D95: 42004 | E95: 424.061 | F95: =4.334-414.4888-0.24077-0.24077-0.24077 -> -410.87711 | G95: =E95+F95+I94 -> 13.18389 | I95: =G95-H95 -> 13.18389 | J95: =H95/G95 -> 0
B96: Mar Profundo S.A. Soc. Pesq. | C96: 41640 | D96: 41729 | E96: 68.29 | F96: -170.725 | G96: =E96+F96 -> -102.435 | I96: =G96-H96 -> -102.435 | J96: =H96/G96 -> 0 | K96: =E96+E97+F96+F97 -> 0 | L96: =H96+H97 -> 0 | M96: =K96-L96 -> 0 | N96: =L96/K96 -> #DIV/0!
C97: 41365 | D97: 42004 | E97: 102.435 | G97: =E97+F97+I96 -> 0 | I97: =G97-H97 -> 0 | J97: =H97/G97 -> #DIV/0!
B98: Orizón S.A. | C98: 41640 | D98: 41729 | E98: 2015.115 | F98: =-2015.115 -> -2015.115 | G98: =E98+F98 -> 0 | I98: =G98-H98 -> 0 | J98: =H98/G98 -> #DIV/0! | K98: =E98+E99+F98+F99 -> 37.787 | L98: =H98+H99 -> 0 | M98: =K98-L98 -> 37.787 | N98: =L98/K98 -> 0
C99: 41365 | D99: 42004 | E99: 3022.672 | F99: =-2984.885 -> -2984.885 | G99: =E99+F99+I98 -> 37.787 | I99: =G99-H99 -> 37.787 | J99: =H99/G99 -> 0
B100: Pesca Chile S.A. | C100: 41640 | D100: 41729 | E100: 34.609 | F100: =-34.609 -> -34.609 | G100: =E100+F100 -> 0 | I100: =G100-H100 -> 0 | J100: =H100/G100 -> #DIV/0! | K100: =E100+E101+F100+F101 -> 0 | L100: =H100+H101 -> 0 | M100: =K100-L100 -> 0 | N100: =L100/K100 -> #DIV/0!
C101: 41365 | D101: 42004 | E101: 51.914 | F101: =-51.914 -> -51.914 | G101: =E101+F101+I100 -> 0 | I101: =G101-H101 -> 0 | J101: =H101/G101 -> #DIV/0!
B102: Salmoalimentos S.A. | C102: 41640 | D102: 41729 | E102: 24.596 | F102: =-24.596 -> -24.596 | G102: =E102+F102 -> 0 | I102: =G102-H102 -> 0 | J102: =H102/G102 -> #DIV/0! | K102: =E102+E103+F102+F103 -> 0 | L102: =H102+H103 -> 0 | M102: =K102-L102 -> 0 | N102: =L102/K102 -> #DIV/0!
C103: 41365 | D103: 42004 | E103: 36.894 | F103: =-36.894 -> -36.894 | G103: =E103+F103+I102 -> 0 | I103: =G103-H103 -> 0 | J103: =H103/G103 -> #DIV/0!
B104: San Antonio S.A. Pesq. | C104: 41640 | D104: 41729 | E104: 25.533 | F104: -63.833 | G104: =E104+F104 -> -38.3 | I104: =G104-H104 -> -38.3 | J104: =H104/G104 -> 0 | K104: =E104+E105+F104+F105 -> 0 | L104: =H104+H105 -> 0 | M104: =K104-L104 -> 0 | N104: =L104/K104 -> #DIV/0!
C105: 41365 | D105: 42004 | E105: 38.3 | G105: =E105+F105+I104 -> 0 | I105: =G105-H105 -> 0 | J105: =H105/G105 -> #DIV/0!
B106: Sur Austral S.A. Pesq. | C106: 41640 | D106: 41729 | E106: 41.784 | F106: =1239.368+1700+680 -> 3619.368 | G106: =E106+F106 -> 3661.152 | H106: 1486.907 | I106: =G106-H106 -> 2174.245 | J106: =H106/G106 -> 0.40613091 | K106: =E106+E107+F106+F107 -> 4613.828 | L106: =H106+H107 -> 4966.7 | M106: =K106-L106 -> -352.872 | N106: =L106/K106 -> 1.0764814
C107: 41365 | D107: 42004 | E107: 62.676 | F107: =290+400+200 -> 890 | G107: =E107+F107+I106 -> 3126.921 | H107: 3479.793 | I107: =G107-H107 -> -352.872 | J107: =H107/G107 -> 1.1128497
B108: Camanchaca Pesca Sur S.A. | C108: 41640 | D108: 41729 | E108: 794.31 | F108: =-0.23913-0.23913-1784.885 -> -1785.3633 | G108: =E108+F108 -> -991.05326 | I108: =G108-H108 -> -991.05326 | J108: =H108/G108 -> 0 | K108: =E108+E109+F108+F109 -> 200.41174 | L108: =H108+H109 -> 0 | M108: =K108-L108 -> 200.41174 | N108: =L108/K108 -> 0
...

Sheet Cuotas Regionales Crustaceos
A3: Cuotas Regionales Crustaceos Industriales, 2014
A4: Del 1 de enero al 31 de diciembre 2014
A6: Unidad de Pesquería | B6: Zona | C6: Cuota Global (t) | D6: Cuota Período | G6: Desembarque (t) | H6: Saldo (t) | I6: % Disponible | J6: Fecha cierre /Prom (t/día)
D7: Período | E7: autorizada | F7: efectiva
A8: Camarón nailon | B8: II | C8: =E8+E9 -> 6 | D8: Enero - Agosto | E8: 4 | F8: =+E8 -> 4 | H8: =+F8-G8 -> 4 | I8: =1-G8/F8 -> 1
D9: Septiembre - diciembre | E9: 2 | F9: =+E9+H8 -> 6 | H9: =+F9-G9 -> 6 | I9: =1-G9/F9 -> 1
B10: III | C10: =E10+E11 -> 4 | D10: Enero - Agosto | E10: 2 | F10: =+E10 -> 2 | H10: =+F10-G10 -> 2 | I10: =1-G10/F10 -> 1
D11: Septiembre - diciembre | E11: 2 | F11: =+E11+H10 -> 4 | H11: =+F11-G11 -> 4 | I11: =1-G11/F11 -> 1
B12: IV | C12: =E12+E13 -> 412 | D12: Enero - Agosto | E12: 210 | F12: =+E12 -> 210 | G12: 191.277 | H12: =+F12-G12 -> 18.723 | I12: =1-G12/F12 -> 0.089157143
D13: Septiembre - diciembre | E13: 202 | F13: =+E13+H12 -> 220.723 | G13: 164.414 | H13: =+F13-G13 -> 56.309 | I13: =1-G13/F13 -> 0.25511161
B14: V | C14: =E14+E15 -> 606 | D14: Enero - Agosto | E14: 382 | F14: =+E14 -> 382 | G14: 378.41 | H14: =+F14-G14 -> 3.59 | I14: =1-G14/F14 -> 0.0093979058 | J14: 23.05.14
D15: Septiembre - diciembre | E15: 224 | F15: =+E15+H14 -> 227.59 | G15: 192.353 | H15: =+F15-G15 -> 35.237 | I15: =1-G15/F15 -> 0.15482666
B16: VI | C16: =E16+E17 -> 984 | D16: Enero - Agosto | E16: 647 | F16: =+E16 -> 647 | G16: 624.852 | H16: =+F16-G16 -> 22.148 | I16: =1-G16/F16 -> 0.034231839 | J16: 20.06.14
D17: Septiembre - diciembre | E17: 337 | F17: =+E17+H16 -> 359.148 | G17: 320.444 | H17: =+F17-G17 -> 38.704 | I17: =1-G17/F17 -> 0.10776616
B18: VII | C18: =E18+E19 -> 839 | D18: Enero - Agosto | E18: 545 | F18: =+E18 -> 545 | G18: 535.805 | H18: =+F18-G18 -> 9.195 | I18: =1-G18/F18 -> 0.01687156 | J18: 30.06.14
D19: Septiembre - diciembre | E19: 294 | F19: =+E19+H18 -> 303.195 | G19: 288.623 | H19: =+F19-G19 -> 14.572 | I19: =1-G19/F19 -> 0.048061479
B20: VIII | C20: =E20+E21 -> 805 | D20: Enero - Agosto | E20: 532 | F20: =+E20 -> 532 | G20: 446.898 | H20: =+F20-G20 -> 85.102 | I20: =1-G20/F20 -> 0.15996617
D21: Septiembre - diciembre | E21: 273 | F21: =+E21+H20 -> 358.102 | G21: 314.178 | H21: =+F21-G21 -> 43.924 | I21: =1-G21/F21 -> 0.12265779
A22: Langostino amarillo | B22: III | C22: =+E22+E23+E24 -> 272 | D22: abril - junio | E22: 136 | F22: =+E22 -> 136 | G22: 18.76 | H22: =+F22-G22 -> 117.24 | I22: =1-G22/F22 -> 0.86205882
D23: julio - septiembre | E23: 82 | F23: =+E23+H22 -> 199.24 | G23: 40.272 | H23: =+F23-G23 -> 158.968 | I23: =1-G23/F23 -> 0.79787191
D24: octubre - diciembre | E24: 54 | F24: =+E24+H23 -> 212.968 | G24: 96.167 | H24: =+F24-G24 -> 116.801 | I24: =1-G24/F24 -> 0.5484439
B25: IV | C25: =+E25+E26+E27 -> 926 | D25: abril - junio | E25: 463 | F25: =+E25 -> 463 | G25: 442.453 | H25: =+F25-G25 -> 20.547 | I25: =1-G25/F25 -> 0.04437797
D26: julio - septiembre | E26: 278 | F26: =+E26+H25 -> 298.547 | G26: 285.05 | H26: =+F26-G26 -> 13.497 | I26: =1-G26/F26 -> 0.045208962
D27: octubre - diciembre | E27: 185 | F27: =+E27+H26 -> 198.497 | G27: 142.31 | H27: =+F27-G27 -> 56.187 | I27: =1-G27/F27 -> 0.28306221
A28: Langostino amarillo Licitado | B28: V | C28: =+E28+E30+E29 -> 870 | D28: abril - junio | E28: 435 | F28: =+E28 -> 435 | G28: 447.987 | H28: =+F28-G28 -> -12.987 | I28: =1-G28/F28 -> -0.029855172 | J28: 10.05.14 | K28: 424.175 | L28: 23.812 | M28: Chafic
D29: julio - septiembre | E29: 305 | F29: =E29+H28 -> 292.013 | G29: 445.394 | H29: =+F29-G29 -> -153.381 | I29: =1-G29/F29 -> -0.52525401 | J29: 21.07.14
D30: octubre - noviembre | E30: 130 | F30: =+E30+H29 -> -23.381 | G30: 0 | H30: =+F30-G30 -> -23.381 | I30: =(1-(G28+G29+G30))/C28 -> -1.0257253 | J30: 23.07.14
B31: VI-VII-VIII | C31: =+E31+E32+E33 -> 290 | D31: abril - junio | E31: 145 | F31: =+E31 -> 145 | G31: 0 | H31: =+F31-G31 -> 145 | I31: =1-G31/F31 -> 1
D32: julio - septiembre | E32: 101 | F32: =E32+H31 -> 246 | G32: 44.5 | H32: =+F32-G32 -> 201.5 | I32: =1-G32/F32 -> 0.81910569
D33: octubre - noviembre | E33: 44 | F33: =+E33+H32 -> 245.5 | G33: 147.837 | H33: =+F33-G33 -> 97.663 | I33: =1-G33/F33 -> 0.39781263
A34: Langostino colorado | B34: II | C34: =+E34+E35+E36 -> 6 | D34: abril - junio | E34: 3 | F34: =+E34 -> 3 | H34: =+F34-G34 -> 3 | I34: =1-G34/F34 -> 1
D35: julio - septiembre | E35: 2 | F35: =+E35+H34 -> 5 | H35: =+F35-G35 -> 5 | I35: =1-G35/F35 -> 1
D36: octubre - diciembre | E36: 1 | F36: =+E36+H35 -> 6 | H36: =+F36-G36 -> 6 | I36: =1-G36/F36 -> 1
B37: III | C37: =+E37+E38+E39 -> 24 | D37: abril - junio | E37: 12 | F37: =+E37 -> 12 | H37: =+F37-G37 -> 12 | I37: =1-G37/F37 -> 1
D38: julio - septiembre | E38: 7 | F38: =+E38+H37 -> 19 | H38: =+F38-G38 -> 19 | I38: =1-G38/F38 -> 1
D39: octubre - diciembre | E39: 5 | F39: =+E39+H38 -> 24 | H39: =+F39-G39 -> 24 | I39: =1-G39/F39 -> 1
B40: IV | C40: =+E40+E41+E42 -> 13 | D40: abril - junio | E40: 6 | F40: =+E40 -> 6 | G40: 4.458 | H40: =+F40-G40 -> 1.542 | I40: =1-G40/F40 -> 0.257 | J40: 09.06.14 | K40: 18.535 | L40: Antartic Seafood
D41: julio - septiembre | E41: 4 | F41: =+E41+H40 -> 5.542 | G41: 0 | H41: =+F41-G41 -> 5.542 | I41: =1-G41/F41 -> 1 | K41: 120.111 | L41: Antartic Seafood
D42: octubre - diciembre | E42: 3 | F42: =+E42+H41 -> 8.542 | G42: 0.009 | H42: =+F42-G42 -> 8.533 | I42: =1-G42/F42 -> 0.99894638 | K42: 16.734 | L42: Antartic Seafood
A43: Langostino colorado Licitado | B43: V | C43: =+E43+E44+E45 -> 700 | D43: abril - junio | E43: 350 | F43: =+E43 -> 350 | G43: 366.522 | H43: =+F43-G43 -> -16.522 | I43: =1-G43/F43 -> -0.047205714 | J43: 16.05.14 | K43: 317.456 | L43: 49.066 | M43: Chafic
D44: julio - septiembre | E44: 245 | F44: =+E44+H43 -> 228.478 | G44: 159.124 | H44: =+F44-G44 -> 69.354 | I44: =1-G44/F44 -> 0.30354783
D45: octubre - noviembre | E45: 105 | F45: =+E45+H44 -> 174.354 | G45: 143.61 | H45: =+F45-G45 -> 30.744 | I45: =1-G45/F45 -> 0.17633091 | J45: 18.10.14
B46: VI | C46: =+E46+E47+E48 -> 1250 | D46: abril - junio | E46: 625 | F46: =+E46 -> 625 | G46: 608.34 | H46: =+F46-G46 -> 16.66 | I46: =1-G46/F46 -> 0.026656
D47: julio - septiembre | E47: 438 | F47: =+E47+H46 -> 454.66 | G47: 448.242 | H47: =+F47-G47 -> 6.418 | I47: =1-G47/F47 -> 0.014116043 | J47: 22.08.14
D48: octubre - noviembre | E48: 187 | F48: =+E48+H47 -> 193.418 | G48: 87.841 | H48: =+F48-G48 -> 105.577 | I48: =1-G48/F48 -> 0.54584889
B49: VII | C49: =+E49+E50+E51 -> 2800 | D49: abril - junio | E49: 1400 | F49: =+E49 -> 1400 | G49: 496.445 | H49: =+F49-G49 -> 903.555 | I49: =1-G49/F49 -> 0.64539643
D50: julio - septiembre | E50: 980 | F50: =+E50+H49 -> 1883.555 | G50: 839.536 | H50: =+F50-G50 -> 1044.019 | I50: =1-G50/F50 -> 0.55428113
D51: octubre - noviembre | E51: 420 | F51: =+E51+H50 -> 1464.019 | G51: 1410.531 | H51: =+F51-G51 -> 53.488 | I51: =1-G51/F51 -> 0.036535045
B52: VIII | C52: =+E52+E53+E54 -> 3050 | D52: abril - junio | E52: 1525 | F52: =+E52 -> 1525 | G52: 998.653 | H52: =+F52-G52 -> 526.347 | I52: =1-G52/F52 -> 0.34514557
D53: julio - septiembre | E53: 1067 | F53: =+E53+H52 -> 1593.347 | G53: 1440.581 | H53: =+F53-G53 -> 152.766 | I53: =1-G53/F53 -> 0.09587742
D54: octubre - noviembre | E54: 458 | F54: =+E54+H53 -> 610.766 | G54: 547.603 | H54: =+F54-G54 -> 63.163 | I54: =1-G54/F54 -> 0.10341604

Sheet Cuotas Globales 
A2: Cuotas globales Sin LTP (en conjunto con artesanales), 2014
A3: Al 31 de diciembre de 2014
A6: Cuotas globales Fuera Unidad de Pesquería
A7: Unidad de Pesquería | B7: Fracción | C7: Cuota Global (t) | D7: Cuota Período | G7: Desembarque total (t) | H7: Saldo (t) | I7: % Disponible | J7: Fecha cierre | K7: Desembarques
D8: Período | E8: autorizada | F8: efectiva | K8: Industrial | L8: Artesanal
A9: Merluza común | B9: Objetivo | C9: 40 | D9: Ene- Dic. | E9: 40 | F9: =+E9 -> 40 | G9: =K9+L9 -> 4.123 | H9: =+F9-G9 -> 35.877 | I9: =1-G9/F9 -> 0.896925 | K9: 0.142 | L9: 3.981
A10: Merluza de cola | B10: Objetivo | D10: Ene -Dic. | F10: =+E10 -> 0 | H10: =+F10-G10 -> 0 | I10: =1-G10/F10 -> #DIV/0!
B11: F. Acompañante | F11: =+E11 -> 0
A12: Merluza del sur | B12: Objetivo | C12: 87 | D12: Ene -Dic. | E12: 87 | F12: =+E12 -> 87 | G12: =K12+L12 -> 394.361 | H12: =+F12-G12 -> -307.361 | I12: =1-G12/F12 -> -3.5328851 | J12: 27.01.14 | K12: 394.361 | L12: 0
B13: F. Acompañante | C13: 21 | E13: 21 | F13: =+E13 -> 21 | G13: =K13+L13 -> 0 | K13: 0 | L13: 0
A14: Langostino amarillo | B14: Objetivo | C14: 7 | D14: Ene -Dic. | E14: =C14 -> 7 | F14: =+E14 -> 7 | G14: =K14+L14 -> 0 | H14: =+F14-G14 -> 7 | I14: =1-G14/F14 -> 1
B15: F. Acompañante | C15: 13 | E15: =C15 -> 13 | F15: =+E15 -> 13 | G15: =K15+L15 -> 0
A16: Camarón nailon | B16: Objetivo | C16: 20 | D16: Ene -Dic. | E16: =C16 -> 20 | F16: =+E16 -> 20 | G16: =K16+L16 -> 0 | H16: =+F16-G16 -> 20 | I16: =1-G16/F16 -> 1
B17: F. Acompañante | C17: 10 | E17: =C17 -> 10 | F17: =+E17 -> 10 | G17: =K17+L17 -> 0
A18: Langostino colorado | B18: Objetivo | C18: 5 | D18: Ene -Dic. | E18: =C18 -> 5 | F18: =+E18 -> 5 | G18: =K18+L18 -> 0 | H18: =+F18-G18 -> 5 | I18: =1-G18/F18 -> 1
B19: F. Acompañante | C19: 7 | E19: =C19 -> 7 | F19: =+E19 -> 7 | G19: =K19+L19 -> 0
A20: Congrio Dorado | B20: V Región | C20: =E20+E21+E22 -> 6 | D20: Enero-Junio | E20: 2.5 | F20: =+E20 -> 2.5 | G20: =K20+L20 -> 0.232 | H20: =+F20-G20 -> 2.268 | I20: =1-G20/F20 -> 0.9072 | K20: 0 | L20: 0.232
D21: Julio-Diciembre | E21: 2.5 | F21: =+E21+H20 -> 4.768 | G21: =K21+L21 -> 0.843 | H21: =+F21-G21 -> 3.925 | I21: =1-G21/F21 -> 0.82319631 | K21: 0 | L21: 0.843
D22: F. Acompañante | E22: 1 | F22: =E22 -> 1 | G22: =K22+L22 -> 0 | K22: 0 | L22: 0
B23: VI Región | C23: =E23+E24+E25 -> 6 | D23: Enero-Junio | E23: 2.5 | F23: =+E23 -> 2.5 | G23: =K23+L23 -> 0 | H23: =+F23-G23 -> 2.5 | I23: =1-G23/F23 -> 1 | K23: 0 | L23: 0
D24: Julio-Diciembre | E24: 2.5 | F24: =+E24+H23 -> 5 | G24: =K24+L24 -> 0 | H24: =+F24-G24 -> 5 | I24: =1-G24/F24 -> 1 | K24: 0 | L24: 0
D25: F. Acompañante | E25: 1 | F25: =E25 -> 1 | G25: =K25+L25 -> 0 | K25: 0 | L25: 0
B26: VII Región | C26: =E26+E27+E28 -> 6 | D26: Enero-Junio | E26: 2.5 | F26: =+E26 -> 2.5 | G26: =K26+L26 -> 2.688 | H26: =+F26-G26 -> -0.188 | I26: =1-G26/F26 -> -0.0752 | J26: 21.03.14 | K26: 0 | L26: 2.688
D27: Julio-Diciembre | E27: 2.5 | F27: =+E27+H26 -> 2.312 | G27: =K27+L27 -> 0.193 | H27: =+F27-G27 -> 2.119 | I27: =1-G27/F27 -> 0.91652249 | K27: 0 | L27: 0.193
D28: F. Acompañante | E28: 1 | F28: =E28 -> 1 | G28: =K28+L28 -> 0 | K28: 0 | L28: 0
B29: VIII Región | C29: =E29+E30+E31 -> 36 | D29: Enero-Junio | E29: 16 | F29: =+E29 -> 16 | G29: =K29+L29 -> 32.486 | H29: =+F29-G29 -> -16.486 | I29: =1-G29/F29 -> -1.030375 | J29: 27.01.14 | K29: 0 | L29: 32.486
D30: Julio-Diciembre | E30: 16 | F30: =+E30+H29 -> -0.486 | G30: =K30+L30 -> 0 | H30: =+F30-G30 -> -0.486 | I30: =1-G30/F30 -> 1 | J30: 06.02.14 | K30: 0 | L30: 0
D31: F. Acompañante | E31: 4 | F31: =E31 -> 4 | G31: =K31+L31 -> 0 | K31: 0 | L31: 0
B32: IX Región | C32: =E32+E33+E34 -> 6 | D32: Enero-Junio | E32: 2.5 | F32: =+E32 -> 2.5 | G32: =K32+L32 -> 0.031 | H32: =+F32-G32 -> 2.469 | I32: =1-G32/F32 -> 0.9876 | K32: 0.031
D33: Julio-Diciembre | E33: 2.5 | F33: =+E33+H32 -> 4.969 | G33: =K33+L33 -> 0 | H33: =+F33-G33 -> 4.969 | I33: =1-G33/F33 -> 1 | K33: 0
D34: F. Acompañante | E34: 1 | F34: =E34 -> 1 | G34: =K34+L34 -> 0 | K34: 0
B35: XIV Región | C35: =E35+E36+E37 -> 36 | D35: Enero-Junio | E35: 16 | F35: =+E35 -> 16 | G35: =K35+L35 -> 22.053 | H35: =+F35-G35 -> -6.053 | I35: =1-G35/F35 -> -0.3783125 | J35: 25.02.14 | K35: 0.877 | L35: 21.176
D36: Julio-Diciembre | E36: 16 | F36: =+E36+H35 -> 9.947 | G36: =K36+L36 -> 11.035 | H36: =+F36-G36 -> -1.088 | I36: =1-G36/F36 -> -0.10937971 | K36: 0 | L36: 11.035
D37: F. Acompañante | E37: 4 | F37: =E37 -> 4 | G37: =K37+L37 -> 0 | K37: 0 | L37: 0
B38: X Región (al norte del 41º28,6´S) | C38: =E38+E40+E39 -> 6 | D38: Enero-Junio | E38: 2.5 | F38: =+E38 -> 2.5 | G38: =K38+L38 -> 3.394 | H38: =+F38-G38 -> -0.894 | I38: =1-G38/F38 -> -0.3576 | J38: 24.02.14 | K38: 0 | L38: 3.394
D39: Julio-Diciembre | E39: 2.5 | F39: =E39+H38 -> 1.606 | G39: =K39+L39 -> 0
D40: F. Acompañante | E40: 1 | F40: =E40 -> 1 | G40: =K40+L40 -> 0 | H40: =+F40-G40 -> 1 | I40: =1-G40/F40 -> 1
A43: Recursos sin cuota
A44: Unidad de Pesquería | B44: Cuota | C44: Período | D44: Sector | F44: Desem. (ton) | G44: Total Desem. (ton)
A45: Caballa XV-XII | B45: S/cuota | C45: enero - diciembre | D45: Artesanal | F45: 8500.598 | G45: =+SUM(F45:F46) -> 24166.45
D46: Industrial | F46: 15665.852
A47: Pez espada XV-XII | B47: S/cuota | C47: enero - diciembre | D47: Artesanal | F47: 5548.869 | G47: =+SUM(F47:F48) -> 5805.354
D48: Industrial | F48: 256.485
A49: Reineta | B49: S/cuota | C49: enero - diciembre | D49: Artesanal | F49: 32978.389 | G49: =F49+F50 -> 35894.516
D50: Industrial | F50: 2916.127
A52: Recursos con cuota Global
A53: Unidad de Pesquería | B53: Fracción | C53: Cuota (t) | D53: Período | E53: Sector | G53: Desem. (ton) | H53: Total Desem. (ton) | J53: Saldo | K53: Fecha de Cierre
A54: Jibia o calamar rojo XV-XII | B54: Investigación | C54: 4000 | D54: Ene- 07.08.14 | E54: Artesanal e industrial | G54: 0 | H54: =G56+G55+G54+G57+G58 -> 161548.13 | J54: =C54-G54 -> 4000
B55: F. Acompañante (al 7 de agosto) | C55: 1960 | G55: =4.882+0.055 -> 4.937 | J55: =C55-G55 -> 1955.063 | K55: 07.08.14
B56: Objetivo (al 7 de agosto) | C56: 194040 | G56: =36493.155+83945.694 -> 120438.85 | J56: =C56-G56 -> 73601.151 | K56: 07.08.14
B57: F. Acompañante (desde el 8.08.14) | C57: 1955.063 | D57: 08.08.14-Dic | E57: Artesanal e industrial | G57: 0 | H57: =G57+G58+G59 -> 55812.179 | J57: =C57-G57 -> 1955.063
B58: Objetivo Artesanal (desde el 8.08.14) | C58: 58880.921 | E58: Artesanal | G58: 41104.347 | J58: =C58-G58 -> 17776.574
B59: Objetivo Industrial (desde el 8.08.14) | C59: 14720.23 | E59: Industrial | G59: 14707.832 | J59: =C59-G59 -> 12.398 | K59: 16.12.14
A60: Raya Volantín | B60: IV-VII | C60: 22 | D60: Ene- Dic. | E60: Artesanal e industrial | G60: =0.241+0.13 -> 0.371 | H60: =G60+G61 -> 5.567 | J60: =C60-G60 -> 21.629
B61: VIII-41º28,6´LS | C61: 40 | E61: Artesanal e industrial | G61: =2.765+2.431 -> 5.196 | J61: =C61-G61 -> 34.804
A62: Raya espinosa | B62: IV-VII | C62: 11 | D62: Ene- Dic. | E62: Artesanal e industrial | G62: =0.039+0.18 -> 0.219 | H62: =G62+G63 -> 1.377 | J62: =C62-G62 -> 10.781
B63: VIII-41º28,6´LS | C63: 20 | E63: Artesanal e industrial | G63: =1.113+0.045 -> 1.158 | J63: =C63-G63 -> 18.842
A64: Bacalao de profundidad | B64: XV hasta paralelo 47º LS | C64: 968.2 | D64: Ene- Dic. | E64: Artesanal | G64: 1056.952 | H64: =G64 -> 1056.952 | J64: =C64-H64 -> -88.752 | K64: 28.07.14
B68: Desembarque de Besugo como Fauna Acompañante
A69: Armador | B69: De Esp Ob. Crustaceos demersales | C69: De Esp. Obj. Peces arrastre | D69: De Esp. Obj. Peces palangre | E69: Total
A70: Baycic Baycic Maria | E70: =B70+C70+D70 -> 0
A71: Congelados del Pacifico | B71: 1.662 | E71: =B71+C71+D71 -> 1.662
A72: Blumar S.A. | E72: =B72+C72+D72 -> 0
A73: Bracpesca S.A. | E73: =B73+C73+D73 -> 0
A74: Concepción S.A. | E74: =B74+C74+D74 -> 0
A75: Grimar | E75: =B75+C75+D75 -> 0
A76: Isladamas S.A. | B76: 0.008 | E76: =B76+C76+D76 -> 0.008
A77: Morozin Yurecic Mario | E77: =B77+C77+D77 -> 0
A78: Quintero Ltda. | E78: =B78+C78+D78 -> 0
A79: Quintero S.A. Pesq. | B79: 0.188 | E79: =B79+C79+D79 -> 0.188
A80: Pesca Chile | B80: 0.005 | E80: =B80+C80+D80 -> 0.005
A81: Total | B81: =SUM(B70:B79) -> 1.858 | C81: =SUM(C70:C79) -> 0 | D81: =SUM(D70:D79) -> 0 | E81: =SUM(E70:E80) -> 1.863
A85: Lota Protein, Res Nº 3288. Traspaso cuota ORP Jurel
A86: Embarcaciones | B86: Desembarque | C86: Cuota ton | D86: Saldo
A87: Santa Maria II | B87: 1207.506 | C87: 4400 | D87: =C87-(B87+B88+B89+B90) -> 735.967
A88: Coral I | B88: 748.79
A89: Don Boris | B89: 1370.149
A90: Don Tito | B90: 337.588

Sheet Pescas de Investigación
B2: PESCAS DE INVESTIGACIÓN AÑO 2014. Consumo al 31 de Diciembre
B4: Pesca de Investigacion: Resolucion Nº 1829. Del 17.07.14 al 30.11.14
B5: Zona | C5: Imputa a reserva de Inv. | D5: Cuota (ton) | E5: Desembarque (ton) | F5: Saldo
A6: Langostino amarillo | B6: III-IV | C6: Dec. Nº 1408/2013 | D6: 35 | E6: 0 | F6: =D6-E6 -> 35
B7: V-VIII | C7: Dec. Nº 1243/2013 | D7: 20 | E7: 20.332 | F7: =D7-E7 -> -0.332
A8: Langostino colorado | B8: XV-IV | C8: Dec. Nº 1408/2013 | D8: 15 | E8: 0 | F8: =D8-E8 -> 15
B9: V-VIII | C9: Dec. Nº 1242/2013 | D9: 50 | E9: 47.658 | F9: =D9-E9 -> 2.342
A10: Merluza Común | B10: IV-VIII | C10: Dec. Nº 1410/2014 | D10: 10 | E10: 0 | F10: =D10-E10 -> 10
A11: Camaron nailón | B11: II-VIII | C11: Dec. Nº 1408/2013 | D11: 20 | E11: 12.592 | F11: =D11-E11 -> 7.408
B14: Pesca de Investigación: Resolución Nº 2693. Del 10.10.14 al 31.12.14
B15: Zona | C15: Imputa a reserva de Inv. | D15: Cuota (ton) | E15: Desembarque (ton) | F15: Saldo | I15: Naves titulares
A16: Camarón nailon | B16: II-VIII | C16: Res. Nº 1408/2013 | D16: 79 | E16: 42.666 | F16: =D16-E16 -> 36.334 | I16: Don José Miguel (A)
A17: Langostino amarillo (Como F.A.) | B17: III-IV | C17: Res. Nº 1408/2013 | D17: 5 | E17: 5.584 | F17: =D17-E17 -> -0.584 | I17: Cocha (I)
B18: V-VIII | C18: Res. Nº 1243/2013 | D18: 3 | E18: 2.632 | F18: =D18-E18 -> 0.368 | I18: Naves suplentes
A19: Langostino colorado | B19: V-VIII | C19: Res. Nº 1242/2013 | D19: 25 | E19: 0 | F19: =D19-E19 -> 25 | I19: Amancay I (I)
A20: Merluza común | B20: IV-VIII | C20: Res. Nº 1410/2013 | D20: 10 | E20: 3.227 | F20: =D20-E20 -> 6.773 | I20: Lonquimay II (I)
C23: Pesca de Investigación: Resolución Nº 2878. Del 30.10.14 al 31.12.14
C24: Cuota | E24: Desembarque | G24: Saldos
A25: Nombre Embarcación | B25: Region o zona | C25: Cuota (Ton) Raya Volantin | D25: Cuota (Ton) Raya espinosa | E25: Desembarque Raya Volantin | F25: Desembarque Raya Espinoza | G25: Saldo R. volantin | H25: Saldo R. Espinoza
A26: Maria Loreto (952273) | B26: V | C26: 12 | D26: 1.2 | E26: 4.556 | F26: 0 | G26: =C26-(E26+E27+E28+E29+E30+E31) -> 2.647 | H26: =D26-(F26+F27+F28+F29+F30+F31) -> 0.971
A27: Damary (39575) | B27: VIII | E27: 0 | F27: 0
A28: Nirvana (11025) | B28: XIV | E28: 0.734 | F28: 0.229
A29: Aguila (952079) | B29: X | E29: 2.601 | F29: 0
A30: Fernanda III (952143) | B30: XI | E30: 0 | F30: 0
A31: Don Ariel (955769) | B31: XII | E31: 1.462 | F31: 0
A34: Pesca de Investigación: Resolución Nº 3297. Del 05.12.14 al 31.12.14
A35: Nombre Embarcación | B35: Region o zona | C35: Cuota por Nave | D35: Desembarque | E35: Saldo Nave | F35: Cuota Puerto | G35: Saldo Puerto
A36: La Esperanza | B36: Iquique (101-104) | C36: 1.02 | D36: 0.844 | E36: =C36-D36 -> 0.176 | F36: =C36+C37+C38 -> 3.06 | G36: =E36+E37+E38 -> 0.46
A37: Aldo y Felipe | C37: 1.02 | D37: 0.545 | E37: =C37-D37 -> 0.475
A38: Marisol III | C38: 1.02 | D38: 1.211 | E38: =C38-D38 -> -0.191
A39: Belen Antonia | B39: Caldera (105-108) | C39: 1.8 | D39: 0 | E39: =C39-D39 -> 1.8 | F39: =C39+C40 -> 3.6 | G39: =E39+E40 -> 1.935
A40: Rocio III | C40: 1.8 | D40: 1.665 | E40: =C40-D40 -> 0.135
A41: Huanay | B41: Constitución (111-113) | C41: 1.063 | D41: 0.953 | E41: =C41-D41 -> 0.11 | F41: =C41+C42+C43+C44 -> 4.252 | G41: =E41+E42+E43+E44 -> -0.04
A42: Coña | C42: 1.063 | D42: 1.168 | E42: =C42-D42 -> -0.105
A43: Travesia | C43: 1.063 | D43: 1.154 | E43: =C43-D43 -> -0.091
A44: Yolanda Filomena | C44: 1.063 | D44: 1.017 | E44: =C44-D44 -> 0.046
A45: Oscar Alonso | B45: Lebu (114-115) | C45: 2.125 | D45: 2.1 | E45: =C45-D45 -> 0.025 | F45: =C45+C46 -> 4.25 | G45: =E45+E46 -> 0.876
A46: Esperanza VII | C46: 2.125 | D46: 1.274 | E46: =C46-D46 -> 0.851
A47: Don Felix II | B47: Valdivia (115-118) | C47: 2.3 | D47: 2.469 | E47: =C47-D47 -> -0.169 | F47: =C47+C48 -> 4.6 | G47: =E47+E48 -> -0.182
A48: Magdalena III | C48: 2.3 | D48: 2.313 | E48: =C48-D48 -> -0.013

Sheet Cuotas Licitadas
B2: Cuotas Industriales Licitadas, año 2014
B3: Al 31 de Diciembre de 2014
B5: Langostino amarillo V-VIII | C5: 1160
B6: Armador | C6: % Licitado | D6: Cuota licitada (t) | E6: Sanción (t) | F6: Transferencias | H6: Cuota efectiva (t) | I6: Operación
F7: Ingresos (t) | G7: Egresos (t) | I7: Desembarque (t) | J7: Saldo (t) | K7: % consumido
B8: CAMANCHACA PESCA SUR | C8: 39.76 | D8: =+$C$5*C8/100 -> 461.216 | G8: 310 | H8: =+D8+F8-G8-E8 -> 151.216 | I8: 145.512 | J8: =+H8-I8 -> 5.704 | K8: =+I8/H8 -> 0.96227912
B9: BLUMAR S.A. | C9: 17.91 | D9: =+$C$5*C9/100 -> 207.756 | G9: 207.36 | H9: =+D9+F9-G9-E9 -> 0.396 | I9: 0 | J9: =+H9-I9 -> 0.396 | K9: =+I9/H9 -> 0
B10: SUNRISE | C10: 1.16 | D10: =+$C$5*C10/100 -> 13.456 | G10: 13.46 | H10: =+D10+F10-G10-E10 -> -0.004 | I10: 0 | J10: =+H10-I10 -> -0.004 | K10: =+I10/H10 -> 0
B11: BRACPESCA | C11: 16.98 | D11: =+$C$5*C11/100 -> 196.968 | F11: 205.76 | G11: 1 | H11: =+D11+F11-G11-E11 -> 401.728 | I11: 399.838 | J11: =+H11-I11 -> 1.89 | K11: =+I11/H11 -> 0.99529532
B12: ISLADAMAS | C12: 10 | D12: =+$C$5*C12/100 -> 116 | F12: 163.46 | G12: 0.02 | H12: =+D12+F12-G12-E12 -> 279.44 | I12: 242.626 | J12: =+H12-I12 -> 36.814 | K12: =+I12/H12 -> 0.86825794
B13: VELIZ Y VELIZ | C13: 0.3 | D13: =+$C$5*C13/100 -> 3.48 | G13: 3.48 | H13: =+D13+F13-G13-E13 -> 0 | I13: 0 | J13: =+H13-I13 -> 0 | K13: =+I13/H13 -> #DIV/0!
B14: DISTRIMAR | C14: 2.87 | D14: =+$C$5*C14/100 -> 33.292 | G14: 33.29 | H14: =+D14+F14-G14-E14 -> 0.002 | I14: 0 | J14: =+H14-I14 -> 0.002 | K14: =+I14/H14 -> 0
B15: ANTARTIC SEAFOOD | C15: 7.84 | D15: =+$C$5*C15/100 -> 90.944 | F15: 25.26 | G15: 0.60092 | H15: =+D15+F15-G15-E15 -> 115.60308 | I15: 114.388 | J15: =+H15-I15 -> 1.21508 | K15: =+I15/H15 -> 0.98948921
B16: GRIMAR S.A. | C16: 1 | D16: =+$C$5*C16/100 -> 11.6 | F16: 1 | H16: =+D16+F16-G16-E16 -> 12.6 | I16: 0 | J16: =+H16-I16 -> 12.6 | K16: =+I16/H16 -> 0
B17: RUBIO Y MAUAD LTDA. | C17: 1.64 | D17: =+$C$5*C17/100 -> 19.024 | F17: 30.51 | G17: 19 | H17: =+D17+F17-G17-E17 -> 30.534 | I17: 23.812 | J17: =+H17-I17 -> 6.722 | K17: =+I17/H17 -> 0.77985197
B18: MARIO MOROZIN YURECIC | C18: 0 | D18: =+$C$5*C18/100 -> 0 | F18: 0.11 | G18: 0.11 | H18: =+D18+F18-G18-E18 -> 0 | I18: 0 | J18: =+H18-I18 -> 0 | K18: =+I18/H18 -> #DIV/0!
B19: SOC. PESQUERA QUINTERO LTDA. | C19: 0 | D19: =+$C$5*C19/100 -> 0 | F19: 0.03 | G19: 0.03 | H19: =+D19+F19-G19-E19 -> 0 | I19: 0 | J19: =+H19-I19 -> 0 | K19: =+I19/H19 -> #DIV/0!
B20: PESQUERA QUINTERO S.A. | C20: 0.54 | D20: =+$C$5*C20/100 -> 6.264 | F20: 0.5 | H20: =+D20+F20-G20-E20 -> 6.764 | I20: 5.898 | J20: =+H20-I20 -> 0.866 | K20: =+I20/H20 -> 0.87196925
B21: CONGELADOS PACIFICO S.A. | C21: 0 | D21: =+$C$5*C21/100 -> 0 | F21: 0.75 | H21: =+D21+F21-G21-E21 -> 0.75 | I21: 0 | J21: =+H21-I21 -> 0.75 | K21: =+I21/H21 -> 0
B22: PESQUERA BIO BIO S.A. | C22: 0 | D22: =+$C$5*C22/100 -> 0 | F22: 0.75 | H22: =+D22+F22-G22-E22 -> 0.75 | I22: 0 | J22: =+H22-I22 -> 0.75 | K22: =+I22/H22 -> 0
B23: PESQUERA ANTONIO CORDIVA NAKOUZI E.I.R.L. | C23: 0 | D23: =+$C$5*C23/100 -> 0 | F23: 0.10092 | H23: =+D23+F23-G23-E23 -> 0.10092 | I23: 0 | J23: =+H23-I23 -> 0.10092 | K23: =+I23/H23 -> 0
B24: PESQUERA ENFEMAR LTDA. | C24: 0 | D24: =+$C$5*C24/100 -> 0 | F24: 0.1 | H24: =+D24+F24-G24-E24 -> 0.1 | I24: 0 | J24: =+H24-I24 -> 0.1 | K24: =+I24/H24 -> 0
B25: ANTONIO DA VENEZIA RETAMALES | C25: 0 | D25: =+$C$5*C25/100 -> 0 | F25: 0.02 | H25: =+D25+F25-G25-E25 -> 0.02 | I25: 0.027 | J25: =+H25-I25 -> -0.007 | K25: =+I25/H25 -> 1.35
B26: JORGE COFRE REYES | C26: 0 | D26: =+$C$5*C26/100 -> 0 | F26: 5 | H26: =+D26+F26-G26-E26 -> 5 | I26: 2.389 | J26: =+H26-I26 -> 2.611 | K26: =+I26/H26 -> 0.4778
B27: PESQUERA CKM LTDA. | C27: 0 | D27: =+$C$5*C27/100 -> 0 | F27: 150 | H27: =+D27+F27-G27-E27 -> 150 | I27: 148.771 | J27: =+H27-I27 -> 1.229 | K27: =+I27/H27 -> 0.99180667
B28: SOC. PESQUERA GENMAR LTDA. | C28: 0 | D28: =+$C$5*C28/100 -> 0 | F28: 5 | H28: =+D28+F28-G28-E28 -> 5 | I28: 2.457 | J28: =+H28-I28 -> 2.543 | K28: =+I28/H28 -> 0.4914
B30: Resumen | C30: % Licitado | D30: Cuota licitada (t) | E30: Sanción (t) | F30: Transferencias | H30: Cuota efectiva (t) | I30: Operación
B31: Langostino amarillo V-VIII | F31: Ingresos (t) | G31: Egresos (t) | I31: Desembarque (t) | J31: Saldo (t) | K31: % consumido
C32: =SUM(C8:C28) -> 100 | D32: =SUM(D8:D28) -> 1160 | E32: =SUM(E8:E18) -> 0 | F32: =SUM(F8:F28) -> 588.35092 | G32: =SUM(G8:G28) -> 588.35092 | H32: =SUM(H8:H28) -> 1160 | I32: =SUM(I8:I28) -> 1085.718 | J32: =SUM(J8:J28) -> 74.282 | K32: =+I32/H32 -> 0.93596379
B35: Langostino colorado V-VIII | C35: 7800
B36: Armador | C36: % Licitado | D36: Cuota licitada (t) | E36: Sanción (t) | F36: Transferencias | H36: Cuota efectiva (t) | I36: Operación
F37: Ingresos (t) | G37: Egresos (t) | I37: Desembarque (t) | J37: Saldo (t) | K37: % consumido
B38: CAMANCHACA PESCA SUR | C38: 69.82 | D38: =+$C$35*C38/100 -> 5445.96 | F38: 1164.04 | G38: 2500 | H38: =+D38+F38-G38-E38 -> 4110 | I38: 4108.601 | J38: =H38-I38 -> 1.399 | K38: =+I38/H38 -> 0.99965961
B39: BLUMAR S.A. | C39: 15.18 | D39: =+$C$35*C39/100 -> 1184.04 | G39: 1165.64 | H39: =+D39+F39-G39-E39 -> 18.4 | I39: 0 | J39: =H39-I39 -> 18.4 | K39: =+I39/H39 -> 0
B40: SUNRISE | C40: 0.5 | D40: =+$C$35*C40/100 -> 39 | G40: 39 | H40: =+D40+F40-G40-E40 -> 0 | I40: 0 | J40: =H40-I40 -> 0 | K40: =+I40/H40 -> #DIV/0!
B41: BRACPESCA | C41: 4.82 | D41: =+$C$35*C41/100 -> 375.96 | F41: 0.408 | G41: 1.5 | H41: =+D41+F41-G41-E41 -> 374.868 | I41: 374.785 | J41: =H41-I41 -> 0.083 | K41: =+I41/H41 -> 0.99977859
B42: ISLADAMAS | C42: 2.81 | D42: =+$C$35*C42/100 -> 219.18 | F42: 928 | G42: 0.024 | H42: =+D42+F42-G42-E42 -> 1147.156 | I42: 1110.878 | J42: =H42-I42 -> 36.278 | K42: =+I42/H42 -> 0.9683757
B43: EMPACADORA DEL PACIFICO | C43: 1.5 | D43: =+$C$35*C43/100 -> 117 | H43: =+D43+F43-G43-E43 -> 117 | I43: 0 | J43: =H43-I43 -> 117 | K43: =+I43/H43 -> 0
B44: DISTRIMAR | C44: 0.53 | D44: =+$C$35*C44/100 -> 41.34 | G44: 40.95 | H44: =+D44+F44-G44-E44 -> 0.39 | I44: 0 | J44: =H44-I44 -> 0.39 | K44: =+I44/H44 -> 0
B45: ANTARTIC SEAFOOD | C45: 3.31 | D45: =+$C$35*C45/100 -> 258.18 | F45: 32.85 | G45: 0.5094 | H45: =+D45+F45-G45-E45 -> 290.5206 | I45: 289.827 | J45: =H45-I45 -> 0.6936 | K45: =+I45/H45 -> 0.99761256
B46: ALIMAR | C46: 0.5 | D46: =+$C$35*C46/100 -> 39 | G46: 39 | H46: =+D46+F46-G46-E46 -> 0 | I46: 0 | J46: =H46-I46 -> 0 | K46: =+I46/H46 -> #DIV/0!
B47: RUBIO Y MAUAD LTDA. | C47: 0.53 | D47: =+$C$35*C47/100 -> 41.34 | F47: 35.1 | G47: 27 | H47: =+D47+F47-G47-E47 -> 49.44 | I47: 49.066 | J47: =H47-I47 -> 0.374 | K47: =+I47/H47 -> 0.99243528
B48: ARTIC S.A. ELAB | C48: 0.5 | D48: =+$C$35*C48/100 -> 39 | H48: =+D48+F48-G48-E48 -> 39 | I48: 0 | J48: =H48-I48 -> 39 | K48: =+I48/H48 -> 0
B49: MARIO MOROZIN YURECIC | C49: 0 | D49: =+$C$35*C49/100 -> 0 | F49: 0.11 | G49: 0.11 | H49: =+D49+F49-G49-E49 -> 0 | I49: 0 | J49: =H49-I49 -> 0 | K49: =+I49/H49 -> #DIV/0!
B50: SOC. PESQUERA QUINTERO LTDA. | C50: 0 | D50: =+$C$35*C50/100 -> 0 | F50: 0.03 | G50: 0.03 | H50: =+D50+F50-G50-E50 -> 0 | I50: 0 | J50: =H50-I50 -> 0 | K50: =+I50/H50 -> #DIV/0!
B51: PESQUERA QUINTERO S.A. | C51: 0 | D51: =+$C$35*C51/100 -> 0 | F51: 0.5 | H51: =+D51+F51-G51-E51 -> 0.5 | I51: 0 | J51: =H51-I51 -> 0.5 | K51: =+I51/H51 -> 0
B52: PESQUERA GRIMAR S.A. | C52: 0 | D52: =+$C$35*C52/100 -> 0 | F52: 1 | H52: =+D52+F52-G52-E52 -> 1 | I52: 0 | J52: =H52-I52 -> 1 | K52: =+I52/H52 -> 0
B53: CONGELADOS PACIFICO S.A. | C53: 0 | D53: =+$C$35*C53/100 -> 0 | F53: 0.75 | H53: =+D53+F53-G53-E53 -> 0.75 | I53: 0 | J53: =H53-I53 -> 0.75 | K53: =+I53/H53 -> 0
B54: PESQUERA BIO BIO S.A. | C54: 0 | D54: =+$C$35*C54/100 -> 0 | F54: 0.75 | H54: =+D54+F54-G54-E54 -> 0.75 | I54: 0 | J54: =H54-I54 -> 0.75 | K54: =+I54/H54 -> 0
B55: PESQUERA ANTONIO CORDOVA NAKOUZI E.I.R.L. | C55: 0 | D55: =+$C$35*C55/100 -> 0 | F55: 0.1014 | H55: =+D55+F55-G55-E55 -> 0.1014 | I55: 0 | J55: =H55-I55 -> 0.1014 | K55: =+I55/H55 -> 0
B56: PESQUERA ENFEMAR LTDA. | C56: 0 | D56: =+$C$35*C56/100 -> 0 | F56: 0.124 | H56: =+D56+F56-G56-E56 -> 0.124 | I56: 0 | J56: =H56-I56 -> 0.124 | K56: =+I56/H56 -> 0
B57: =B25 -> ANTONIO DA VENEZIA RETAMALES | C57: 0 | D57: =+$C$35*C57/100 -> 0 | F57: 0 | H57: =+D57+F57-G57-E57 -> 0 | I57: 0 | J57: =H57-I57 -> 0 | K57: =+I57/H57 -> #DIV/0!
B58: JORGE COFRE REYES | C58: 0 | D58: =+$C$35*C58/100 -> 0 | F58: 800 | H58: =+D58+F58-G58-E58 -> 800 | I58: 798.149 | J58: =H58-I58 -> 1.851 | K58: =+I58/H58 -> 0.99768625
B59: PESQUERA CKM LTDA. | C59: 0 | D59: =+$C$35*C59/100 -> 0 | F59: 650 | H59: =+D59+F59-G59-E59 -> 650 | I59: 648.692 | J59: =H59-I59 -> 1.308 | K59: =+I59/H59 -> 0.99798769
B60: SOC. PESQUERA GENMAR LTDA. | C60: 0 | D60: =+$C$35*C60/100 -> 0 | F60: 200 | H60: =+D60+F60-G60-E60 -> 200 | I60: 167.03 | J60: =H60-I60 -> 32.97 | K60: =+I60/H60 -> 0.83515
B62: Resumen | C62: % Licitado | D62: Cuota licitada (t) | E62: Sanción (t) | F62: Transferencias | H62: Cuota efectiva (t) | I62: Operación
B63: Langostino colorado V-VIII | F63: Ingresos (t) | G63: Egresos (t) | I63: Desembarque (t) | J63: Saldo (t) | K63: % consumido
C64: =SUM(C38:C60) -> 100 | D64: =SUM(D38:D60) -> 7800 | E64: =SUM(E38:E49) -> 0 | F64: =SUM(F38:F60) -> 3813.7634 | G64: =SUM(G38:G60) -> 3813.7634 | H64: =SUM(H38:H60) -> 7800 | I64: =SUM(I38:I60) -> 7547.028 | J64: =SUM(J38:J60) -> 252.972 | K64: =+I64/H64 -> 0.96756769
B66: Bacalao de profundidad | C66: 1076
B67: Armador | C67: % Licitado | D67: Cuota licitada (t) | E67: Sanción (t) | F67: Transferencias | H67: Cuota efectiva (t) | I67: Operación
F68: Ingresos (t) | G68: Egresos (t) | I68: Desembarque (t) | J68: Saldo (t) | K68: % consumido
A69: INDUSTRIALES | B69: Blue Ocean Seafood | C69: 12.81 | D69: =+C69*$C$66/100 -> 137.8356 | G69: 137.836 | H69: =+D69-E69+F69-G69 -> -0.0004 | I69: 0 | J69: =H69-I69 -> -0.0004 | K69: =+I69/H69 -> 0
B70: Pesca Chile | C70: 21.815 | D70: =+C70*$C$66/100 -> 234.7294 | G70: 4 | H70: =+D70-E70+F70-G70 -> 230.7294 | I70: 229.47 | J70: =H70-I70 -> 1.2594 | K70: =+I70/H70 -> 0.99454166
B71: Pesca Cisne | C71: 6.5 | D71: =+C71*$C$66/100 -> 69.94 | F71: 137.836 | H71: =+D71-E71+F71-G71 -> 207.776 | I71: 207.425 | J71: =H71-I71 -> 0.351 | K71: =+I71/H71 -> 0.99831068
B72: Globalpesca | C72: 48.875 | D72: =+C72*$C$66/100 -> 525.895 | H72: =+D72-E72+F72-G72 -> 525.895 | I72: 530.735 | J72: =H72-I72 -> -4.84 | K72: =+I72/H72 -> 1.0092034
A73: ARTESANALES | B73: DANIEL MOLINA CISTERNAS | C73: 1 | D73: =+C73*$C$66/100 -> 10.76 | H73: =+D73-E73+F73-G73 -> 10.76 | I73: 10.614 | J73: =H73-I73 -> 0.146 | K73: =+I73/H73 -> 0.98643123
B74: JOSE LISER SOTO VELASQUEZ | C74: 0 | D74: =+C74*$C$66/100 -> 0 | G74: 10.76 | H74: =+D74-E74+F74-G74 -> -10.76 | I74: 0 | J74: =H74-I74 -> -10.76 | K74: =+I74/H74 -> 0
B75: JOSE FREDY SOTO VELASQUEZ | C75: 0 | D75: =+C75*$C$66/100 -> 0 | G75: 10.76 | H75: =+D75-E75+F75-G75 -> -10.76 | I75: 0 | J75: =H75-I75 -> -10.76 | K75: =+I75/H75 -> 0
B76: PESQUERA FRAPOLI S.A. | C76: 1 | D76: =+C76*$C$66/100 -> 10.76 | H76: =+D76-E76+F76-G76 -> 10.76 | I76: 10.769 | J76: =H76-I76 -> -0.009 | K76: =+I76/H76 -> 1.0008364
B77: JOSE ACEVEDO CORNEJO | C77: 0.5 | D77: =+C77*$C$66/100 -> 5.38 | H77: =+D77-E77+F77-G77 -> 5.38 | I77: 4.853 | J77: =H77-I77 -> 0.527 | K77: =+I77/H77 -> 0.90204461
B78: ROBERTO GONZALEZ NAVARRO | C78: 2.5 | D78: =+C78*$C$66/100 -> 26.9 | G78: 26.9 | H78: =+D78-E78+F78-G78 -> 0 | I78: 0 | J78: =H78-I78 -> 0 | K78: =+I78/H78 -> #DIV/0!
B79: PAOLA MORA BURGOS | C79: 1 | D79: =+C79*$C$66/100 -> 10.76 | H79: =+D79-E79+F79-G79 -> 10.76 | I79: 10.654 | J79: =H79-I79 -> 0.106 | K79: =+I79/H79 -> 0.9901487
B80: TOMAS NEIRA PARRA | C80: 0.5 | D80: =+C80*$C$66/100 -> 5.38 | H80: =+D80-E80+F80-G80 -> 5.38 | I80: 4.29 | J80: =H80-I80 -> 1.09 | K80: =+I80/H80 -> 0.79739777
B81: BOLIVAR GUZMAN ACUÑA | C81: 1.5 | D81: =+C81*$C$66/100 -> 16.14 | G81: 6.955 | H81: =+D81-E81+F81-G81 -> 9.185 | I81: 0 | J81: =H81-I81 -> 9.185 | K81: =+I81/H81 -> 0
B82: RAUL GONZALEZ HURTADO | C82: 1 | D82: =+C82*$C$66/100 -> 10.76 | H82: =+D82-E82+F82-G82 -> 10.76 | I82: 10.553 | J82: =H82-I82 -> 0.207 | K82: =+I82/H82 -> 0.98076208
B83: TERRANOVA SPA | C83: 0 | D83: =+C83*$C$66/100 -> 0 | F83: 52.42 | H83: =+D83-E83+F83-G83 -> 52.42 | I83: 41.332 | J83: =H83-I83 -> 11.088 | K83: =+I83/H83 -> 0.78847768
B84: JUAN JOSE GUZMAN ROJAS | C84: 1 | D84: =+C84*$C$66/100 -> 10.76 | G84: 1.575 | H84: =+D84-E84+F84-G84 -> 9.185 | I84: 0 | J84: =H84-I84 -> 9.185 | K84: =+I84/H84 -> 0
B85: JOSE MORA MOYA | C85: 0 | D85: =+C85*$C$66/100 -> 0 | F85: 8.53 | H85: =+D85-E85+F85-G85 -> 8.53 | I85: 8.328 | J85: =H85-I85 -> 0.202 | K85: =+I85/H85 -> 0.97631887
B87: Resumen | C87: % Licitado | D87: Cuota licitada (t) | E87: Sanción (t) | F87: Transferencias | H87: Cuota efectiva (t) | I87: Operación
B88: Bacalao de profundidad | F88: Ingresos (t) | G88: Egresos (t) | I88: Desembarque (t) | J88: Saldo (t) | K88: % consumido
C89: =SUM(C69:C85) -> 100 | D89: =SUM(D69:D85) -> 1076 | E89: =SUM(E69:E85) -> 0 | F89: =SUM(F69:F85) -> 198.786 | G89: =SUM(G69:G85) -> 198.786 | H89: =SUM(H69:H85) -> 1076 | I89: =SUM(I69:I85) -> 1069.023 | J89: =SUM(J69:J85) -> 6.977 | K89: =+I89/H89 -> 0.9935158
